Workbook
Name A_1: [1]IMS!$J$67
Name A_2: [1]IMS!$O$67
Name A_3: [1]IMS!$T$67
Name A_4: [1]IMS!$Y$67
Name AC: [2]DatiIndici!A$9
Name Acc: [2]DatiIndici!A$28
Name Am: [2]DatiIndici!A$8
Name AP: [1]SI!$E$13
Name Beni: [3]!B[Bene]
Name C_1: [1]IMS!$J$29
Name C_2: [1]IMS!$O$29
Name C_3: [1]IMS!$T$29
Name C_4: [1]IMS!$Y$29
Name Cat: [3]!Gruppi[Cat]
Name cf: [4]Prospetto!$F$5
Name cg: 8-WEEKDAY([5]Calcoli!XFD1,2)
Name Ci: [2]DatiIndici!A$10
Name CodTrib: Codici[Codice]
Name Cr: [2]DatiIndici!A$5
Name da: RISULTATI!$E$12
Name DAD: [4]Calcoli!$D$14
Name DAT: [4]Calcoli!$D$15
Name descp: [1]SI!$F$10
Name dp: [1]SI!$E$11
Name dr: [4]Calcoli!$G$29
Name Ei: [2]DatiIndici!A$30
Name En: [2]DatiIndici!A$29
Name F_1: [1]IMS!$J$11
Name F_2: [1]IMS!$O$11
Name F_3: [1]IMS!$T$11
Name F_4: [1]IMS!$Y$11
Name Fa: [2]DatiIndici!A$17
Name g: [1]SI!$F$11
Name i: [4]Calcoli!$D$12
Name ia: [4]Prospetto!$C$5
Name II: [2]DatiIndici!A$31
Name Im: [2]DatiIndici!A$3
Name Imm: [2]DatiIndici!A$32
Name L: 42369
Name m: [1]T!$H$1
Name MOL: [2]DatiIndici!A$25
Name NUMCART: Tabella1[NUMERO CARTELLA]
Name NUMCART: Tabella1[NUMERO CARTELLA]
Name Of: [2]DatiIndici!A$26
Name p: [3]DATI!#REF!
Name P_1: [1]IMS!$J$47
Name P_2: [1]IMS!$O$47
Name P_3: [1]IMS!$T$47
Name P_4: [1]IMS!$Y$47
Name par: [1]SI!$E$9
Name Pb: [2]DatiIndici!A$14
Name pe: [1]T!$G$3:$G$11
Name Pers: [2]DatiIndici!A$27
Name Pfn: [2]DatiIndici!A$16
Name PI: [1]PI!$A$10:$AE$91
Name Pl: [2]DatiIndici!A$13
Name Pn: [2]DatiIndici!A$12
Name PROT: MENU!$F$25
Name rate: #REF!
Name RATEA: #REF!

Sheet MENU
C10: Studio | F10: Cliente
C12: Ind. Studio | F12: Indirizzo
C14: Cap-Città | F14: Cap-Città
C16: P. IVA - C.F. | F16: P. IVA - C.F.
D23: Capitale da rateizzare | F23: =+ROTP -> 7899.8
D24: Massima rateazione concessa | F24: =+MAX(1,MIN(54,TRUNC(F23/100))) -> 54 | J24: Importo residuo dovuto | O24: =+RISULTATI!D10 -> 11918.8
D25: Numero di rate scelte | F25: 17 | J25: Risparmio con rottamazione | O25: =+SUMIF(RISULTATI!C:C,J25,RISULTATI!E:E) -> 4019
J26: Interessi per rateazione | O26: =+G87 -> 316.4376
E30: Piano di rateazione
E31: Data versamento | F31: Rata Capitale | G31: Importo rata
C32: 1 | E32: =+IF(PROT>0,"31/07/2026","") -> 31/07/2026 | F32: =+IF(PROT>0,IF(PROT>=C32,ROTP/PROT,""),"") -> 464.69412 | G32: =+IF(PROT>0,IF(PROT>=C32,F23/PROT,""),"") -> 464.69412
C33: =+IFERROR(IF(C32+1<=PROT,C32+1,""),"") -> 2 | E33: =+IFERROR(EOMONTH(start,(C33-1)*2),"") -> 46295 | F33: =+IF(PROT>0,IF(PROT>=C33,ROTP/PROT,""),"") -> 464.69412 | G33: =+IFERROR((E33-E32)/365*SUM(F33:$F$85)*3%+F33,"") -> 501.9715
C34: =+IFERROR(IF(C33+1<=PROT,C33+1,""),"") -> 3 | E34: =+IFERROR(EOMONTH(start,(C34-1)*2),"") -> 46356 | F34: =+IF(PROT>0,IF(PROT>=C34,ROTP/PROT,""),"") -> 464.69412 | G34: =+IFERROR((E34-E33)/365*SUM(F34:$F$85)*3%+F34,"") -> 499.64166
C35: =+IFERROR(IF(C34+1<=PROT,C34+1,""),"") -> 4 | E35: =+IFERROR(EOMONTH(start,(C35-1)*2),"") -> 46418 | F35: =+IF(PROT>0,IF(PROT>=C35,ROTP/PROT,""),"") -> 464.69412 | G35: =+IFERROR((E35-E34)/365*SUM(F35:$F$85)*3%+F35,"") -> 497.84654
C36: =+IFERROR(IF(C35+1<=PROT,C35+1,""),"") -> 5 | E36: =+IFERROR(EOMONTH(start,(C36-1)*2),"") -> 46477 | F36: =+IF(PROT>0,IF(PROT>=C36,ROTP/PROT,""),"") -> 464.69412 | G36: =+IFERROR((E36-E35)/365*SUM(F36:$F$85)*3%+F36,"") -> 493.98894
C37: =+IFERROR(IF(C36+1<=PROT,C36+1,""),"") -> 6 | E37: =+IFERROR(EOMONTH(start,(C37-1)*2),"") -> 46538 | F37: =+IF(PROT>0,IF(PROT>=C37,ROTP/PROT,""),"") -> 464.69412 | G37: =+IFERROR((E37-E36)/365*SUM(F37:$F$85)*3%+F37,"") -> 492.65215
C38: =+IFERROR(IF(C37+1<=PROT,C37+1,""),"") -> 7 | E38: =+IFERROR(EOMONTH(start,(C38-1)*2),"") -> 46599 | F38: =+IF(PROT>0,IF(PROT>=C38,ROTP/PROT,""),"") -> 464.69412 | G38: =+IFERROR((E38-E37)/365*SUM(F38:$F$85)*3%+F38,"") -> 490.32232
C39: =+IFERROR(IF(C38+1<=PROT,C38+1,""),"") -> 8 | E39: =+IFERROR(EOMONTH(start,(C39-1)*2),"") -> 46660 | F39: =+IF(PROT>0,IF(PROT>=C39,ROTP/PROT,""),"") -> 464.69412 | G39: =+IFERROR((E39-E38)/365*SUM(F39:$F$85)*3%+F39,"") -> 487.99248
C40: =+IFERROR(IF(C39+1<=PROT,C39+1,""),"") -> 9 | E40: =+IFERROR(EOMONTH(start,(C40-1)*2),"") -> 46721 | F40: =+IF(PROT>0,IF(PROT>=C40,ROTP/PROT,""),"") -> 464.69412 | G40: =+IFERROR((E40-E39)/365*SUM(F40:$F$85)*3%+F40,"") -> 485.66264
C41: =+IFERROR(IF(C40+1<=PROT,C40+1,""),"") -> 10 | E41: =+IFERROR(EOMONTH(start,(C41-1)*2),"") -> 46783 | F41: =+IF(PROT>0,IF(PROT>=C41,ROTP/PROT,""),"") -> 464.69412 | G41: =+IFERROR((E41-E40)/365*SUM(F41:$F$85)*3%+F41,"") -> 483.63836
C42: =+IFERROR(IF(C41+1<=PROT,C41+1,""),"") -> 11 | E42: =+IFERROR(EOMONTH(start,(C42-1)*2),"") -> 46843 | F42: =+IF(PROT>0,IF(PROT>=C42,ROTP/PROT,""),"") -> 464.69412 | G42: =+IFERROR((E42-E41)/365*SUM(F42:$F$85)*3%+F42,"") -> 480.73561
C43: =+IFERROR(IF(C42+1<=PROT,C42+1,""),"") -> 12 | E43: =+IFERROR(EOMONTH(start,(C43-1)*2),"") -> 46904 | F43: =+IF(PROT>0,IF(PROT>=C43,ROTP/PROT,""),"") -> 464.69412 | G43: =+IFERROR((E43-E42)/365*SUM(F43:$F$85)*3%+F43,"") -> 478.67314
C44: =+IFERROR(IF(C43+1<=PROT,C43+1,""),"") -> 13 | E44: =+IFERROR(EOMONTH(start,(C44-1)*2),"") -> 46965 | F44: =+IF(PROT>0,IF(PROT>=C44,ROTP/PROT,""),"") -> 464.69412 | G44: =+IFERROR((E44-E43)/365*SUM(F44:$F$85)*3%+F44,"") -> 476.3433
... C85: =+IFERROR(IF(C84+1<=PROT,C84+1,""),"") | E85: =+IFERROR(EOMONTH(start,(C85-1)*2),"") | F85: =+IF(PROT>0,IF(PROT>=C85,ROTP/PROT,""),"") | G85: =+IFERROR((E85-E84)/365*SUM(F85:$F$85)*3%+F85,"")
E86: TOTALE VERSATO CON PAGAMENTO RATEALE | G86: =SUM(G32:G85) -> 8216.2376
E87: - DI CUI INTERESSI | G87: =+G86-ROTP -> 316.4376
E105: Importo finanziato se diverso dal totale
E107: RATE | F107: 120
E109: TASSO | F109: 0.05
F111: Rata mensile | G111: Importo annuale
E112: RATA IPOTIZZATA | F112: =-PMT(F109/12,F107,IF(F105>0,F105,#REF!)) -> #REF! | G112: =+F112*12 -> #REF!
F114: Totale restituito | G114: Di cui interessi
F115: =+F112*F107 -> #REF! | G115: =+F112*F107-(IF(F105>0,F105,#REF!)) -> #REF!

Sheet DATI
L11: Inserisci codice tributo | M11: 5490
L12: =+VLOOKUP(M11,Codici[],3,0) -> Sanzione amministrativa l.24/11/1981 n,689 circoscrizione aeroportuale
B14: TOTALE CARTELLE DA ROTTAMARE | C14: =SUM(Tabella1[TOTALE CARTELLA]) -> 11918.8
B16: NUMERO CARTELLA | C16: LA CARTELLA RIPORTA CARICHI INCLUSI NELLA TABELLA SOTTOSTANTE | D16: DATA AFFIDAMENTO AGENZIA DELLE ENTRATE - RISCOSSIONE | E16: IMPOSTE | F16: SANZIONI | G16: INTERESSI DI MORA | H16: INTERESSI DI DILAZIONE | I16: INTERESSI RITARDATA ISCRIZIONE A RUOLO | J16: ONERI DI RISCOSSIONE (AGGIO) | K16: SPESE DI NOTIFICA | L16: SPESE PER PROCEDURE ESECUTIVE | M16: TOTALE CARTELLA | N16: DATA NOTIFICA | O16: NOTE | P16: TIPO RATEAZIONE
B17: 097 2023 000123456789 | C17: No | D17: 45089 | E17: 7890 | F17: 2367 | G17: 421 | H17: 278 | I17: 139 | J17: 814 | K17: 9.8 | M17: =SUM(Tabella1[[#This Row],[IMPOSTE]:[SPESE PER PROCEDURE ESECUTIVE]]) -> 11918.8 | N17: 45110 | O17: =+IF(Tabella1[[#This Row],[LA CARTELLA RIPORTA CARICHI INCLUSI NELLA TABELLA SOTTOSTANTE]]="","",+IF(Tabella1[[#This Row],[LA CARTELLA RIPORTA CARICHI INCLUSI NELLA TABELLA SOTTOSTANTE]]="Sì","RUOLO ESCLUSO DALLA DEFINIZIONE AGEVOLATA","RUOLO ROTTAMABILE")) -> RUOLO ROTTAMABILE | P17: =+IF(Tabella1[[#This Row],[DATA AFFIDAMENTO AGENZIA DELLE ENTRATE - RISCOSSIONE]]<42736,1,2) -> 2
M18: =SUM(Tabella1[[#This Row],[IMPOSTE]:[SPESE PER PROCEDURE ESECUTIVE]]) -> 0 | O18: =+IF(Tabella1[[#This Row],[LA CARTELLA RIPORTA CARICHI INCLUSI NELLA TABELLA SOTTOSTANTE]]="","",+IF(Tabella1[[#This Row],[LA CARTELLA RIPORTA CARICHI INCLUSI NELLA TABELLA SOTTOSTANTE]]="Sì","RUOLO ESCLUSO DALLA DEFINIZIONE AGEVOLATA","RUOLO ROTTAMABILE")) | P18: =+IF(Tabella1[[#This Row],[DATA AFFIDAMENTO AGENZIA DELLE ENTRATE - RISCOSSIONE]]<42736,1,2) -> 1
M19: =SUM(Tabella1[[#This Row],[IMPOSTE]:[SPESE PER PROCEDURE ESECUTIVE]]) -> 0 | O19: =+IF(Tabella1[[#This Row],[LA CARTELLA RIPORTA CARICHI INCLUSI NELLA TABELLA SOTTOSTANTE]]="","",+IF(Tabella1[[#This Row],[LA CARTELLA RIPORTA CARICHI INCLUSI NELLA TABELLA SOTTOSTANTE]]="Sì","RUOLO ESCLUSO DALLA DEFINIZIONE AGEVOLATA","RUOLO ROTTAMABILE")) | P19: =+IF(Tabella1[[#This Row],[DATA AFFIDAMENTO AGENZIA DELLE ENTRATE - RISCOSSIONE]]<42736,1,2) -> 1
M20: =SUM(Tabella1[[#This Row],[IMPOSTE]:[SPESE PER PROCEDURE ESECUTIVE]]) -> 0 | O20: =+IF(Tabella1[[#This Row],[LA CARTELLA RIPORTA CARICHI INCLUSI NELLA TABELLA SOTTOSTANTE]]="","",+IF(Tabella1[[#This Row],[LA CARTELLA RIPORTA CARICHI INCLUSI NELLA TABELLA SOTTOSTANTE]]="Sì","RUOLO ESCLUSO DALLA DEFINIZIONE AGEVOLATA","RUOLO ROTTAMABILE")) | P20: =+IF(Tabella1[[#This Row],[DATA AFFIDAMENTO AGENZIA DELLE ENTRATE - RISCOSSIONE]]<42736,1,2) -> 1
M21: =SUM(Tabella1[[#This Row],[IMPOSTE]:[SPESE PER PROCEDURE ESECUTIVE]]) -> 0 | O21: =+IF(Tabella1[[#This Row],[LA CARTELLA RIPORTA CARICHI INCLUSI NELLA TABELLA SOTTOSTANTE]]="","",+IF(Tabella1[[#This Row],[LA CARTELLA RIPORTA CARICHI INCLUSI NELLA TABELLA SOTTOSTANTE]]="Sì","RUOLO ESCLUSO DALLA DEFINIZIONE AGEVOLATA","RUOLO ROTTAMABILE")) | P21: =+IF(Tabella1[[#This Row],[DATA AFFIDAMENTO AGENZIA DELLE ENTRATE - RISCOSSIONE]]<42736,1,2) -> 1
M22: =SUM(Tabella1[[#This Row],[IMPOSTE]:[SPESE PER PROCEDURE ESECUTIVE]]) -> 0 | O22: =+IF(Tabella1[[#This Row],[LA CARTELLA RIPORTA CARICHI INCLUSI NELLA TABELLA SOTTOSTANTE]]="","",+IF(Tabella1[[#This Row],[LA CARTELLA RIPORTA CARICHI INCLUSI NELLA TABELLA SOTTOSTANTE]]="Sì","RUOLO ESCLUSO DALLA DEFINIZIONE AGEVOLATA","RUOLO ROTTAMABILE")) | P22: =+IF(Tabella1[[#This Row],[DATA AFFIDAMENTO AGENZIA DELLE ENTRATE - RISCOSSIONE]]<42736,1,2) -> 1
M23: =SUM(Tabella1[[#This Row],[IMPOSTE]:[SPESE PER PROCEDURE ESECUTIVE]]) -> 0 | O23: =+IF(Tabella1[[#This Row],[LA CARTELLA RIPORTA CARICHI INCLUSI NELLA TABELLA SOTTOSTANTE]]="","",+IF(Tabella1[[#This Row],[LA CARTELLA RIPORTA CARICHI INCLUSI NELLA TABELLA SOTTOSTANTE]]="Sì","RUOLO ESCLUSO DALLA DEFINIZIONE AGEVOLATA","RUOLO ROTTAMABILE")) | P23: =+IF(Tabella1[[#This Row],[DATA AFFIDAMENTO AGENZIA DELLE ENTRATE - RISCOSSIONE]]<42736,1,2) -> 1
M24: =SUM(Tabella1[[#This Row],[IMPOSTE]:[SPESE PER PROCEDURE ESECUTIVE]]) -> 0 | O24: =+IF(Tabella1[[#This Row],[LA CARTELLA RIPORTA CARICHI INCLUSI NELLA TABELLA SOTTOSTANTE]]="","",+IF(Tabella1[[#This Row],[LA CARTELLA RIPORTA CARICHI INCLUSI NELLA TABELLA SOTTOSTANTE]]="Sì","RUOLO ESCLUSO DALLA DEFINIZIONE AGEVOLATA","RUOLO ROTTAMABILE")) | P24: =+IF(Tabella1[[#This Row],[DATA AFFIDAMENTO AGENZIA DELLE ENTRATE - RISCOSSIONE]]<42736,1,2) -> 1
M25: =SUM(Tabella1[[#This Row],[IMPOSTE]:[SPESE PER PROCEDURE ESECUTIVE]]) -> 0 | O25: =+IF(Tabella1[[#This Row],[LA CARTELLA RIPORTA CARICHI INCLUSI NELLA TABELLA SOTTOSTANTE]]="","",+IF(Tabella1[[#This Row],[LA CARTELLA RIPORTA CARICHI INCLUSI NELLA TABELLA SOTTOSTANTE]]="Sì","RUOLO ESCLUSO DALLA DEFINIZIONE AGEVOLATA","RUOLO ROTTAMABILE")) | P25: =+IF(Tabella1[[#This Row],[DATA AFFIDAMENTO AGENZIA DELLE ENTRATE - RISCOSSIONE]]<42736,1,2) -> 1
M26: =SUM(Tabella1[[#This Row],[IMPOSTE]:[SPESE PER PROCEDURE ESECUTIVE]]) -> 0 | O26: =+IF(Tabella1[[#This Row],[LA CARTELLA RIPORTA CARICHI INCLUSI NELLA TABELLA SOTTOSTANTE]]="","",+IF(Tabella1[[#This Row],[LA CARTELLA RIPORTA CARICHI INCLUSI NELLA TABELLA SOTTOSTANTE]]="Sì","RUOLO ESCLUSO DALLA DEFINIZIONE AGEVOLATA","RUOLO ROTTAMABILE")) | P26: =+IF(Tabella1[[#This Row],[DATA AFFIDAMENTO AGENZIA DELLE ENTRATE - RISCOSSIONE]]<42736,1,2) -> 1
M27: =SUM(Tabella1[[#This Row],[IMPOSTE]:[SPESE PER PROCEDURE ESECUTIVE]]) -> 0 | O27: =+IF(Tabella1[[#This Row],[LA CARTELLA RIPORTA CARICHI INCLUSI NELLA TABELLA SOTTOSTANTE]]="","",+IF(Tabella1[[#This Row],[LA CARTELLA RIPORTA CARICHI INCLUSI NELLA TABELLA SOTTOSTANTE]]="Sì","RUOLO ESCLUSO DALLA DEFINIZIONE AGEVOLATA","RUOLO ROTTAMABILE")) | P27: =+IF(Tabella1[[#This Row],[DATA AFFIDAMENTO AGENZIA DELLE ENTRATE - RISCOSSIONE]]<42736,1,2) -> 1
M28: =SUM(Tabella1[[#This Row],[IMPOSTE]:[SPESE PER PROCEDURE ESECUTIVE]]) -> 0 | O28: =+IF(Tabella1[[#This Row],[LA CARTELLA RIPORTA CARICHI INCLUSI NELLA TABELLA SOTTOSTANTE]]="","",+IF(Tabella1[[#This Row],[LA CARTELLA RIPORTA CARICHI INCLUSI NELLA TABELLA SOTTOSTANTE]]="Sì","RUOLO ESCLUSO DALLA DEFINIZIONE AGEVOLATA","RUOLO ROTTAMABILE")) | P28: =+IF(Tabella1[[#This Row],[DATA AFFIDAMENTO AGENZIA DELLE ENTRATE - RISCOSSIONE]]<42736,1,2) -> 1
B29: TOTALE | E29: =SUBTOTAL(109,Tabella1[IMPOSTE]) -> 7890 | F29: =SUBTOTAL(109,Tabella1[SANZIONI]) -> 2367 | G29: =SUBTOTAL(109,Tabella1[INTERESSI DI MORA]) -> 421 | H29: =SUBTOTAL(109,Tabella1[INTERESSI DI DILAZIONE]) -> 278 | I29: =SUBTOTAL(109,Tabella1[INTERESSI RITARDATA ISCRIZIONE A RUOLO]) -> 139 | J29: =SUBTOTAL(109,Tabella1[ONERI DI RISCOSSIONE (AGGIO)]) -> 814 | K29: =SUBTOTAL(109,Tabella1[SPESE DI NOTIFICA]) -> 9.8 | L29: =SUBTOTAL(109,Tabella1[SPESE PER PROCEDURE ESECUTIVE]) -> 0 | M29: =SUBTOTAL(109,Tabella1[TOTALE CARTELLA]) -> 11918.8
C30: CARICHI ESCLUSI DALLA DEFINIZIONE AGEVOLATA
C31: Risorse proprie tradizionali previste dall’articolo 2, paragrafo 1, lettera a), delle decisioni 2007/436/CE/Euratom del Consiglio, del 7 giugno 2007, e 2014/335/UE/Euratom del Consiglio, del 26 maggio 2014
C32: IVA riscossa all'importazione
C33: Somme dovute a titolo di recupero di aiuti di Stato ai sensi dell’articolo 16 del regolamento (UE) n. 2015/1589 del Consiglio, del 13 luglio 2015
C34: Carichi emessi per il recupero di crediti tributari sorti in uno Stato membro dell’Unione Europea, in uno Stato estero aderente alla Convenzione OCSE/CoE o in uno Stato estero con cui l’Italia ha stipulato una convenzione bilaterale in materia di assistenza alla riscossione
C35: Crediti derivanti da pronunce di condanna della Corte dei conti
C36: Multe, ammende e sanzioni pecuniarie dovute a seguito di provvedimenti e sentenze penali di condanna
C37: Altre sanzioni diverse da quelle irrogate per violazioni tributarie
C38: Carichi già inclusi in precedenti definizioni agevolate con piano regolarmente in corso.

Sheet RATEAZIONI
B12: RATEAZIONE CARTELLE
B16: INS CARTELLA | C16: Cartella2 | D16: N° RATA | E16: DATA VERSAMENTO | F16: IMPORTO VERSATO | G16: Quota imposta | H16: Quota Sanzioni | I16: Quota Int. Mora | J16: Quota Int. di dilazione | K16: Quota Interessi per rit. Iscr. a ruolo | L16: Oneri di riscossione (aggio esattoriale) | M16: Spese per procedure esecutive | N16: X | O16: Spese di Notifica
B17: 1 | C17: =+IF(Tabella24[[#This Row],[INS CARTELLA]]="",C16,+VLOOKUP(Tabella24[[#This Row],[INS CARTELLA]],Tabella1[[NUMERO CARTELLA]:[IMPOSTE]],1,0)) -> #N/A | D17: 1 | E17: 44255 | F17: 1500 | G17: =+IFERROR(+Tabella24[[#This Row],[IMPORTO VERSATO]]/SUMIF(DATI!B:B,Tabella24[[#This Row],[Cartella2]],DATI!M:M)*SUMIF(DATI!B:B,Tabella24[[#This Row],[Cartella2]],DATI!E:E),"") | H17: =+IFERROR(+Tabella24[[#This Row],[IMPORTO VERSATO]]/SUMIF(DATI!$B:$B,Tabella24[[#This Row],[Cartella2]],DATI!$M:$M)*SUMIF(DATI!$B:$B,Tabella24[[#This Row],[Cartella2]],DATI!$F:$F),"") | I17: =+IFERROR(+Tabella24[[#This Row],[IMPORTO VERSATO]]/SUMIF(DATI!$B:$B,Tabella24[[#This Row],[Cartella2]],DATI!$M:$M)*SUMIF(DATI!$B:$B,Tabella24[[#This Row],[Cartella2]],DATI!$G:$G),"") | J17: =+IFERROR(+Tabella24[[#This Row],[IMPORTO VERSATO]]/SUMIF(DATI!$B:$B,Tabella24[[#This Row],[Cartella2]],DATI!$M:$M)*SUMIF(DATI!$B:$B,Tabella24[[#This Row],[Cartella2]],DATI!$H:$H),"") | K17: =+IFERROR(+Tabella24[[#This Row],[IMPORTO VERSATO]]/SUMIF(DATI!$B:$B,Tabella24[[#This Row],[Cartella2]],DATI!$M:$M)*SUMIF(DATI!$B:$B,Tabella24[[#This Row],[Cartella2]],DATI!$I:$I),"") | L17: =+IFERROR(+Tabella24[[#This Row],[IMPORTO VERSATO]]/SUMIF(DATI!$B:$B,Tabella24[[#This Row],[Cartella2]],DATI!$M:$M)*SUMIF(DATI!$B:$B,Tabella24[[#This Row],[Cartella2]],DATI!$J:$J),"") | M17: =+IFERROR(+Tabella24[[#This Row],[IMPORTO VERSATO]]/SUMIF(DATI!$B:$B,Tabella24[[#This Row],[Cartella2]],DATI!$M:$M)*SUMIF(DATI!$B:$B,Tabella24[[#This Row],[Cartella2]],DATI!$L:$L),"") | O17: =+IFERROR(+Tabella24[[#This Row],[IMPORTO VERSATO]]/SUMIF(DATI!$B:$B,Tabella24[[#This Row],[Cartella2]],DATI!$M:$M)*SUMIF(DATI!$B:$B,Tabella24[[#This Row],[Cartella2]],DATI!$K:$K),"")
C18: =+IF(Tabella24[[#This Row],[INS CARTELLA]]="",C17,+VLOOKUP(Tabella24[[#This Row],[INS CARTELLA]],Tabella1[[NUMERO CARTELLA]:[IMPOSTE]],1,0)) -> #N/A | D18: 2 | E18: 44286 | F18: 1500 | G18: =+IFERROR(+Tabella24[[#This Row],[IMPORTO VERSATO]]/SUMIF(DATI!B:B,Tabella24[[#This Row],[Cartella2]],DATI!M:M)*SUMIF(DATI!B:B,Tabella24[[#This Row],[Cartella2]],DATI!E:E),"") | H18: =+IFERROR(+Tabella24[[#This Row],[IMPORTO VERSATO]]/SUMIF(DATI!$B:$B,Tabella24[[#This Row],[Cartella2]],DATI!$M:$M)*SUMIF(DATI!$B:$B,Tabella24[[#This Row],[Cartella2]],DATI!$F:$F),"") | I18: =+IFERROR(+Tabella24[[#This Row],[IMPORTO VERSATO]]/SUMIF(DATI!$B:$B,Tabella24[[#This Row],[Cartella2]],DATI!$M:$M)*SUMIF(DATI!$B:$B,Tabella24[[#This Row],[Cartella2]],DATI!$G:$G),"") | J18: =+IFERROR(+Tabella24[[#This Row],[IMPORTO VERSATO]]/SUMIF(DATI!$B:$B,Tabella24[[#This Row],[Cartella2]],DATI!$M:$M)*SUMIF(DATI!$B:$B,Tabella24[[#This Row],[Cartella2]],DATI!$H:$H),"") | K18: =+IFERROR(+Tabella24[[#This Row],[IMPORTO VERSATO]]/SUMIF(DATI!$B:$B,Tabella24[[#This Row],[Cartella2]],DATI!$M:$M)*SUMIF(DATI!$B:$B,Tabella24[[#This Row],[Cartella2]],DATI!$I:$I),"") | L18: =+IFERROR(+Tabella24[[#This Row],[IMPORTO VERSATO]]/SUMIF(DATI!$B:$B,Tabella24[[#This Row],[Cartella2]],DATI!$M:$M)*SUMIF(DATI!$B:$B,Tabella24[[#This Row],[Cartella2]],DATI!$J:$J),"") | M18: =+IFERROR(+Tabella24[[#This Row],[IMPORTO VERSATO]]/SUMIF(DATI!$B:$B,Tabella24[[#This Row],[Cartella2]],DATI!$M:$M)*SUMIF(DATI!$B:$B,Tabella24[[#This Row],[Cartella2]],DATI!$L:$L),"") | O18: =+IFERROR(+Tabella24[[#This Row],[IMPORTO VERSATO]]/SUMIF(DATI!$B:$B,Tabella24[[#This Row],[Cartella2]],DATI!$M:$M)*SUMIF(DATI!$B:$B,Tabella24[[#This Row],[Cartella2]],DATI!$K:$K),"")
C19: =+IF(Tabella24[[#This Row],[INS CARTELLA]]="",C18,+VLOOKUP(Tabella24[[#This Row],[INS CARTELLA]],Tabella1[[NUMERO CARTELLA]:[IMPOSTE]],1,0)) -> #N/A | D19: 3 | E19: 44316 | F19: 1500 | G19: =+IFERROR(+Tabella24[[#This Row],[IMPORTO VERSATO]]/SUMIF(DATI!B:B,Tabella24[[#This Row],[Cartella2]],DATI!M:M)*SUMIF(DATI!B:B,Tabella24[[#This Row],[Cartella2]],DATI!E:E),"") | H19: =+IFERROR(+Tabella24[[#This Row],[IMPORTO VERSATO]]/SUMIF(DATI!$B:$B,Tabella24[[#This Row],[Cartella2]],DATI!$M:$M)*SUMIF(DATI!$B:$B,Tabella24[[#This Row],[Cartella2]],DATI!$F:$F),"") | I19: =+IFERROR(+Tabella24[[#This Row],[IMPORTO VERSATO]]/SUMIF(DATI!$B:$B,Tabella24[[#This Row],[Cartella2]],DATI!$M:$M)*SUMIF(DATI!$B:$B,Tabella24[[#This Row],[Cartella2]],DATI!$G:$G),"") | J19: =+IFERROR(+Tabella24[[#This Row],[IMPORTO VERSATO]]/SUMIF(DATI!$B:$B,Tabella24[[#This Row],[Cartella2]],DATI!$M:$M)*SUMIF(DATI!$B:$B,Tabella24[[#This Row],[Cartella2]],DATI!$H:$H),"") | K19: =+IFERROR(+Tabella24[[#This Row],[IMPORTO VERSATO]]/SUMIF(DATI!$B:$B,Tabella24[[#This Row],[Cartella2]],DATI!$M:$M)*SUMIF(DATI!$B:$B,Tabella24[[#This Row],[Cartella2]],DATI!$I:$I),"") | L19: =+IFERROR(+Tabella24[[#This Row],[IMPORTO VERSATO]]/SUMIF(DATI!$B:$B,Tabella24[[#This Row],[Cartella2]],DATI!$M:$M)*SUMIF(DATI!$B:$B,Tabella24[[#This Row],[Cartella2]],DATI!$J:$J),"") | M19: =+IFERROR(+Tabella24[[#This Row],[IMPORTO VERSATO]]/SUMIF(DATI!$B:$B,Tabella24[[#This Row],[Cartella2]],DATI!$M:$M)*SUMIF(DATI!$B:$B,Tabella24[[#This Row],[Cartella2]],DATI!$L:$L),"") | O19: =+IFERROR(+Tabella24[[#This Row],[IMPORTO VERSATO]]/SUMIF(DATI!$B:$B,Tabella24[[#This Row],[Cartella2]],DATI!$M:$M)*SUMIF(DATI!$B:$B,Tabella24[[#This Row],[Cartella2]],DATI!$K:$K),"")
B20: 2 | C20: =+IF(Tabella24[[#This Row],[INS CARTELLA]]="",C19,+VLOOKUP(Tabella24[[#This Row],[INS CARTELLA]],Tabella1[[NUMERO CARTELLA]:[IMPOSTE]],1,0)) -> #N/A | D20: 1 | E20: 44469 | F20: 500 | G20: =+IFERROR(+Tabella24[[#This Row],[IMPORTO VERSATO]]/SUMIF(DATI!B:B,Tabella24[[#This Row],[Cartella2]],DATI!M:M)*SUMIF(DATI!B:B,Tabella24[[#This Row],[Cartella2]],DATI!E:E),"") | H20: =+IFERROR(+Tabella24[[#This Row],[IMPORTO VERSATO]]/SUMIF(DATI!$B:$B,Tabella24[[#This Row],[Cartella2]],DATI!$M:$M)*SUMIF(DATI!$B:$B,Tabella24[[#This Row],[Cartella2]],DATI!$F:$F),"") | I20: =+IFERROR(+Tabella24[[#This Row],[IMPORTO VERSATO]]/SUMIF(DATI!$B:$B,Tabella24[[#This Row],[Cartella2]],DATI!$M:$M)*SUMIF(DATI!$B:$B,Tabella24[[#This Row],[Cartella2]],DATI!$G:$G),"") | J20: =+IFERROR(+Tabella24[[#This Row],[IMPORTO VERSATO]]/SUMIF(DATI!$B:$B,Tabella24[[#This Row],[Cartella2]],DATI!$M:$M)*SUMIF(DATI!$B:$B,Tabella24[[#This Row],[Cartella2]],DATI!$H:$H),"") | K20: =+IFERROR(+Tabella24[[#This Row],[IMPORTO VERSATO]]/SUMIF(DATI!$B:$B,Tabella24[[#This Row],[Cartella2]],DATI!$M:$M)*SUMIF(DATI!$B:$B,Tabella24[[#This Row],[Cartella2]],DATI!$I:$I),"") | L20: =+IFERROR(+Tabella24[[#This Row],[IMPORTO VERSATO]]/SUMIF(DATI!$B:$B,Tabella24[[#This Row],[Cartella2]],DATI!$M:$M)*SUMIF(DATI!$B:$B,Tabella24[[#This Row],[Cartella2]],DATI!$J:$J),"") | M20: =+IFERROR(+Tabella24[[#This Row],[IMPORTO VERSATO]]/SUMIF(DATI!$B:$B,Tabella24[[#This Row],[Cartella2]],DATI!$M:$M)*SUMIF(DATI!$B:$B,Tabella24[[#This Row],[Cartella2]],DATI!$L:$L),"") | O20: =+IFERROR(+Tabella24[[#This Row],[IMPORTO VERSATO]]/SUMIF(DATI!$B:$B,Tabella24[[#This Row],[Cartella2]],DATI!$M:$M)*SUMIF(DATI!$B:$B,Tabella24[[#This Row],[Cartella2]],DATI!$K:$K),"")
C21: =+IF(Tabella24[[#This Row],[INS CARTELLA]]="",C20,+VLOOKUP(Tabella24[[#This Row],[INS CARTELLA]],Tabella1[[NUMERO CARTELLA]:[IMPOSTE]],1,0)) -> #N/A | D21: 2 | E21: 44500 | F21: 500 | G21: =+IFERROR(+Tabella24[[#This Row],[IMPORTO VERSATO]]/SUMIF(DATI!B:B,Tabella24[[#This Row],[Cartella2]],DATI!M:M)*SUMIF(DATI!B:B,Tabella24[[#This Row],[Cartella2]],DATI!E:E),"") | H21: =+IFERROR(+Tabella24[[#This Row],[IMPORTO VERSATO]]/SUMIF(DATI!$B:$B,Tabella24[[#This Row],[Cartella2]],DATI!$M:$M)*SUMIF(DATI!$B:$B,Tabella24[[#This Row],[Cartella2]],DATI!$F:$F),"") | I21: =+IFERROR(+Tabella24[[#This Row],[IMPORTO VERSATO]]/SUMIF(DATI!$B:$B,Tabella24[[#This Row],[Cartella2]],DATI!$M:$M)*SUMIF(DATI!$B:$B,Tabella24[[#This Row],[Cartella2]],DATI!$G:$G),"") | J21: =+IFERROR(+Tabella24[[#This Row],[IMPORTO VERSATO]]/SUMIF(DATI!$B:$B,Tabella24[[#This Row],[Cartella2]],DATI!$M:$M)*SUMIF(DATI!$B:$B,Tabella24[[#This Row],[Cartella2]],DATI!$H:$H),"") | K21: =+IFERROR(+Tabella24[[#This Row],[IMPORTO VERSATO]]/SUMIF(DATI!$B:$B,Tabella24[[#This Row],[Cartella2]],DATI!$M:$M)*SUMIF(DATI!$B:$B,Tabella24[[#This Row],[Cartella2]],DATI!$I:$I),"") | L21: =+IFERROR(+Tabella24[[#This Row],[IMPORTO VERSATO]]/SUMIF(DATI!$B:$B,Tabella24[[#This Row],[Cartella2]],DATI!$M:$M)*SUMIF(DATI!$B:$B,Tabella24[[#This Row],[Cartella2]],DATI!$J:$J),"") | M21: =+IFERROR(+Tabella24[[#This Row],[IMPORTO VERSATO]]/SUMIF(DATI!$B:$B,Tabella24[[#This Row],[Cartella2]],DATI!$M:$M)*SUMIF(DATI!$B:$B,Tabella24[[#This Row],[Cartella2]],DATI!$L:$L),"") | O21: =+IFERROR(+Tabella24[[#This Row],[IMPORTO VERSATO]]/SUMIF(DATI!$B:$B,Tabella24[[#This Row],[Cartella2]],DATI!$M:$M)*SUMIF(DATI!$B:$B,Tabella24[[#This Row],[Cartella2]],DATI!$K:$K),"")
C22: =+IF(Tabella24[[#This Row],[INS CARTELLA]]="",C21,+VLOOKUP(Tabella24[[#This Row],[INS CARTELLA]],Tabella1[[NUMERO CARTELLA]:[IMPOSTE]],1,0)) -> #N/A | D22: 3 | E22: 44530 | F22: 500 | G22: =+IFERROR(+Tabella24[[#This Row],[IMPORTO VERSATO]]/SUMIF(DATI!B:B,Tabella24[[#This Row],[Cartella2]],DATI!M:M)*SUMIF(DATI!B:B,Tabella24[[#This Row],[Cartella2]],DATI!E:E),"") | H22: =+IFERROR(+Tabella24[[#This Row],[IMPORTO VERSATO]]/SUMIF(DATI!$B:$B,Tabella24[[#This Row],[Cartella2]],DATI!$M:$M)*SUMIF(DATI!$B:$B,Tabella24[[#This Row],[Cartella2]],DATI!$F:$F),"") | I22: =+IFERROR(+Tabella24[[#This Row],[IMPORTO VERSATO]]/SUMIF(DATI!$B:$B,Tabella24[[#This Row],[Cartella2]],DATI!$M:$M)*SUMIF(DATI!$B:$B,Tabella24[[#This Row],[Cartella2]],DATI!$G:$G),"") | J22: =+IFERROR(+Tabella24[[#This Row],[IMPORTO VERSATO]]/SUMIF(DATI!$B:$B,Tabella24[[#This Row],[Cartella2]],DATI!$M:$M)*SUMIF(DATI!$B:$B,Tabella24[[#This Row],[Cartella2]],DATI!$H:$H),"") | K22: =+IFERROR(+Tabella24[[#This Row],[IMPORTO VERSATO]]/SUMIF(DATI!$B:$B,Tabella24[[#This Row],[Cartella2]],DATI!$M:$M)*SUMIF(DATI!$B:$B,Tabella24[[#This Row],[Cartella2]],DATI!$I:$I),"") | L22: =+IFERROR(+Tabella24[[#This Row],[IMPORTO VERSATO]]/SUMIF(DATI!$B:$B,Tabella24[[#This Row],[Cartella2]],DATI!$M:$M)*SUMIF(DATI!$B:$B,Tabella24[[#This Row],[Cartella2]],DATI!$J:$J),"") | M22: =+IFERROR(+Tabella24[[#This Row],[IMPORTO VERSATO]]/SUMIF(DATI!$B:$B,Tabella24[[#This Row],[Cartella2]],DATI!$M:$M)*SUMIF(DATI!$B:$B,Tabella24[[#This Row],[Cartella2]],DATI!$L:$L),"") | O22: =+IFERROR(+Tabella24[[#This Row],[IMPORTO VERSATO]]/SUMIF(DATI!$B:$B,Tabella24[[#This Row],[Cartella2]],DATI!$M:$M)*SUMIF(DATI!$B:$B,Tabella24[[#This Row],[Cartella2]],DATI!$K:$K),"")
C23: =+IF(Tabella24[[#This Row],[INS CARTELLA]]="",C22,+VLOOKUP(Tabella24[[#This Row],[INS CARTELLA]],Tabella1[[NUMERO CARTELLA]:[IMPOSTE]],1,0)) -> #N/A | G23: =+IFERROR(+Tabella24[[#This Row],[IMPORTO VERSATO]]/SUMIF(DATI!B:B,Tabella24[[#This Row],[Cartella2]],DATI!M:M)*SUMIF(DATI!B:B,Tabella24[[#This Row],[Cartella2]],DATI!E:E),"") | H23: =+IFERROR(+Tabella24[[#This Row],[IMPORTO VERSATO]]/SUMIF(DATI!$B:$B,Tabella24[[#This Row],[Cartella2]],DATI!$M:$M)*SUMIF(DATI!$B:$B,Tabella24[[#This Row],[Cartella2]],DATI!$F:$F),"") | I23: =+IFERROR(+Tabella24[[#This Row],[IMPORTO VERSATO]]/SUMIF(DATI!$B:$B,Tabella24[[#This Row],[Cartella2]],DATI!$M:$M)*SUMIF(DATI!$B:$B,Tabella24[[#This Row],[Cartella2]],DATI!$G:$G),"") | J23: =+IFERROR(+Tabella24[[#This Row],[IMPORTO VERSATO]]/SUMIF(DATI!$B:$B,Tabella24[[#This Row],[Cartella2]],DATI!$M:$M)*SUMIF(DATI!$B:$B,Tabella24[[#This Row],[Cartella2]],DATI!$H:$H),"") | K23: =+IFERROR(+Tabella24[[#This Row],[IMPORTO VERSATO]]/SUMIF(DATI!$B:$B,Tabella24[[#This Row],[Cartella2]],DATI!$M:$M)*SUMIF(DATI!$B:$B,Tabella24[[#This Row],[Cartella2]],DATI!$I:$I),"") | L23: =+IFERROR(+Tabella24[[#This Row],[IMPORTO VERSATO]]/SUMIF(DATI!$B:$B,Tabella24[[#This Row],[Cartella2]],DATI!$M:$M)*SUMIF(DATI!$B:$B,Tabella24[[#This Row],[Cartella2]],DATI!$J:$J),"") | M23: =+IFERROR(+Tabella24[[#This Row],[IMPORTO VERSATO]]/SUMIF(DATI!$B:$B,Tabella24[[#This Row],[Cartella2]],DATI!$M:$M)*SUMIF(DATI!$B:$B,Tabella24[[#This Row],[Cartella2]],DATI!$L:$L),"") | O23: =+IFERROR(+Tabella24[[#This Row],[IMPORTO VERSATO]]/SUMIF(DATI!$B:$B,Tabella24[[#This Row],[Cartella2]],DATI!$M:$M)*SUMIF(DATI!$B:$B,Tabella24[[#This Row],[Cartella2]],DATI!$K:$K),"")
C24: =+IF(Tabella24[[#This Row],[INS CARTELLA]]="",C23,+VLOOKUP(Tabella24[[#This Row],[INS CARTELLA]],Tabella1[[NUMERO CARTELLA]:[IMPOSTE]],1,0)) -> #N/A | G24: =+IFERROR(+Tabella24[[#This Row],[IMPORTO VERSATO]]/SUMIF(DATI!B:B,Tabella24[[#This Row],[Cartella2]],DATI!M:M)*SUMIF(DATI!B:B,Tabella24[[#This Row],[Cartella2]],DATI!E:E),"") | H24: =+IFERROR(+Tabella24[[#This Row],[IMPORTO VERSATO]]/SUMIF(DATI!$B:$B,Tabella24[[#This Row],[Cartella2]],DATI!$M:$M)*SUMIF(DATI!$B:$B,Tabella24[[#This Row],[Cartella2]],DATI!$F:$F),"") | I24: =+IFERROR(+Tabella24[[#This Row],[IMPORTO VERSATO]]/SUMIF(DATI!$B:$B,Tabella24[[#This Row],[Cartella2]],DATI!$M:$M)*SUMIF(DATI!$B:$B,Tabella24[[#This Row],[Cartella2]],DATI!$G:$G),"") | J24: =+IFERROR(+Tabella24[[#This Row],[IMPORTO VERSATO]]/SUMIF(DATI!$B:$B,Tabella24[[#This Row],[Cartella2]],DATI!$M:$M)*SUMIF(DATI!$B:$B,Tabella24[[#This Row],[Cartella2]],DATI!$H:$H),"") | K24: =+IFERROR(+Tabella24[[#This Row],[IMPORTO VERSATO]]/SUMIF(DATI!$B:$B,Tabella24[[#This Row],[Cartella2]],DATI!$M:$M)*SUMIF(DATI!$B:$B,Tabella24[[#This Row],[Cartella2]],DATI!$I:$I),"") | L24: =+IFERROR(+Tabella24[[#This Row],[IMPORTO VERSATO]]/SUMIF(DATI!$B:$B,Tabella24[[#This Row],[Cartella2]],DATI!$M:$M)*SUMIF(DATI!$B:$B,Tabella24[[#This Row],[Cartella2]],DATI!$J:$J),"") | M24: =+IFERROR(+Tabella24[[#This Row],[IMPORTO VERSATO]]/SUMIF(DATI!$B:$B,Tabella24[[#This Row],[Cartella2]],DATI!$M:$M)*SUMIF(DATI!$B:$B,Tabella24[[#This Row],[Cartella2]],DATI!$L:$L),"") | O24: =+IFERROR(+Tabella24[[#This Row],[IMPORTO VERSATO]]/SUMIF(DATI!$B:$B,Tabella24[[#This Row],[Cartella2]],DATI!$M:$M)*SUMIF(DATI!$B:$B,Tabella24[[#This Row],[Cartella2]],DATI!$K:$K),"")
C25: =+IF(Tabella24[[#This Row],[INS CARTELLA]]="",C24,+VLOOKUP(Tabella24[[#This Row],[INS CARTELLA]],Tabella1[[NUMERO CARTELLA]:[IMPOSTE]],1,0)) -> #N/A | G25: =+IFERROR(+Tabella24[[#This Row],[IMPORTO VERSATO]]/SUMIF(DATI!B:B,Tabella24[[#This Row],[Cartella2]],DATI!M:M)*SUMIF(DATI!B:B,Tabella24[[#This Row],[Cartella2]],DATI!E:E),"") | H25: =+IFERROR(+Tabella24[[#This Row],[IMPORTO VERSATO]]/SUMIF(DATI!$B:$B,Tabella24[[#This Row],[Cartella2]],DATI!$M:$M)*SUMIF(DATI!$B:$B,Tabella24[[#This Row],[Cartella2]],DATI!$F:$F),"") | I25: =+IFERROR(+Tabella24[[#This Row],[IMPORTO VERSATO]]/SUMIF(DATI!$B:$B,Tabella24[[#This Row],[Cartella2]],DATI!$M:$M)*SUMIF(DATI!$B:$B,Tabella24[[#This Row],[Cartella2]],DATI!$G:$G),"") | J25: =+IFERROR(+Tabella24[[#This Row],[IMPORTO VERSATO]]/SUMIF(DATI!$B:$B,Tabella24[[#This Row],[Cartella2]],DATI!$M:$M)*SUMIF(DATI!$B:$B,Tabella24[[#This Row],[Cartella2]],DATI!$H:$H),"") | K25: =+IFERROR(+Tabella24[[#This Row],[IMPORTO VERSATO]]/SUMIF(DATI!$B:$B,Tabella24[[#This Row],[Cartella2]],DATI!$M:$M)*SUMIF(DATI!$B:$B,Tabella24[[#This Row],[Cartella2]],DATI!$I:$I),"") | L25: =+IFERROR(+Tabella24[[#This Row],[IMPORTO VERSATO]]/SUMIF(DATI!$B:$B,Tabella24[[#This Row],[Cartella2]],DATI!$M:$M)*SUMIF(DATI!$B:$B,Tabella24[[#This Row],[Cartella2]],DATI!$J:$J),"") | M25: =+IFERROR(+Tabella24[[#This Row],[IMPORTO VERSATO]]/SUMIF(DATI!$B:$B,Tabella24[[#This Row],[Cartella2]],DATI!$M:$M)*SUMIF(DATI!$B:$B,Tabella24[[#This Row],[Cartella2]],DATI!$L:$L),"") | O25: =+IFERROR(+Tabella24[[#This Row],[IMPORTO VERSATO]]/SUMIF(DATI!$B:$B,Tabella24[[#This Row],[Cartella2]],DATI!$M:$M)*SUMIF(DATI!$B:$B,Tabella24[[#This Row],[Cartella2]],DATI!$K:$K),"")
C26: =+IF(Tabella24[[#This Row],[INS CARTELLA]]="",C25,+VLOOKUP(Tabella24[[#This Row],[INS CARTELLA]],Tabella1[[NUMERO CARTELLA]:[IMPOSTE]],1,0)) -> #N/A | G26: =+IFERROR(+Tabella24[[#This Row],[IMPORTO VERSATO]]/SUMIF(DATI!B:B,Tabella24[[#This Row],[Cartella2]],DATI!M:M)*SUMIF(DATI!B:B,Tabella24[[#This Row],[Cartella2]],DATI!E:E),"") | H26: =+IFERROR(+Tabella24[[#This Row],[IMPORTO VERSATO]]/SUMIF(DATI!$B:$B,Tabella24[[#This Row],[Cartella2]],DATI!$M:$M)*SUMIF(DATI!$B:$B,Tabella24[[#This Row],[Cartella2]],DATI!$F:$F),"") | I26: =+IFERROR(+Tabella24[[#This Row],[IMPORTO VERSATO]]/SUMIF(DATI!$B:$B,Tabella24[[#This Row],[Cartella2]],DATI!$M:$M)*SUMIF(DATI!$B:$B,Tabella24[[#This Row],[Cartella2]],DATI!$G:$G),"") | J26: =+IFERROR(+Tabella24[[#This Row],[IMPORTO VERSATO]]/SUMIF(DATI!$B:$B,Tabella24[[#This Row],[Cartella2]],DATI!$M:$M)*SUMIF(DATI!$B:$B,Tabella24[[#This Row],[Cartella2]],DATI!$H:$H),"") | K26: =+IFERROR(+Tabella24[[#This Row],[IMPORTO VERSATO]]/SUMIF(DATI!$B:$B,Tabella24[[#This Row],[Cartella2]],DATI!$M:$M)*SUMIF(DATI!$B:$B,Tabella24[[#This Row],[Cartella2]],DATI!$I:$I),"") | L26: =+IFERROR(+Tabella24[[#This Row],[IMPORTO VERSATO]]/SUMIF(DATI!$B:$B,Tabella24[[#This Row],[Cartella2]],DATI!$M:$M)*SUMIF(DATI!$B:$B,Tabella24[[#This Row],[Cartella2]],DATI!$J:$J),"") | M26: =+IFERROR(+Tabella24[[#This Row],[IMPORTO VERSATO]]/SUMIF(DATI!$B:$B,Tabella24[[#This Row],[Cartella2]],DATI!$M:$M)*SUMIF(DATI!$B:$B,Tabella24[[#This Row],[Cartella2]],DATI!$L:$L),"") | O26: =+IFERROR(+Tabella24[[#This Row],[IMPORTO VERSATO]]/SUMIF(DATI!$B:$B,Tabella24[[#This Row],[Cartella2]],DATI!$M:$M)*SUMIF(DATI!$B:$B,Tabella24[[#This Row],[Cartella2]],DATI!$K:$K),"")
C27: =+IF(Tabella24[[#This Row],[INS CARTELLA]]="",C26,+VLOOKUP(Tabella24[[#This Row],[INS CARTELLA]],Tabella1[[NUMERO CARTELLA]:[IMPOSTE]],1,0)) -> #N/A | G27: =+IFERROR(+Tabella24[[#This Row],[IMPORTO VERSATO]]/SUMIF(DATI!B:B,Tabella24[[#This Row],[Cartella2]],DATI!M:M)*SUMIF(DATI!B:B,Tabella24[[#This Row],[Cartella2]],DATI!E:E),"") | H27: =+IFERROR(+Tabella24[[#This Row],[IMPORTO VERSATO]]/SUMIF(DATI!$B:$B,Tabella24[[#This Row],[Cartella2]],DATI!$M:$M)*SUMIF(DATI!$B:$B,Tabella24[[#This Row],[Cartella2]],DATI!$F:$F),"") | I27: =+IFERROR(+Tabella24[[#This Row],[IMPORTO VERSATO]]/SUMIF(DATI!$B:$B,Tabella24[[#This Row],[Cartella2]],DATI!$M:$M)*SUMIF(DATI!$B:$B,Tabella24[[#This Row],[Cartella2]],DATI!$G:$G),"") | J27: =+IFERROR(+Tabella24[[#This Row],[IMPORTO VERSATO]]/SUMIF(DATI!$B:$B,Tabella24[[#This Row],[Cartella2]],DATI!$M:$M)*SUMIF(DATI!$B:$B,Tabella24[[#This Row],[Cartella2]],DATI!$H:$H),"") | K27: =+IFERROR(+Tabella24[[#This Row],[IMPORTO VERSATO]]/SUMIF(DATI!$B:$B,Tabella24[[#This Row],[Cartella2]],DATI!$M:$M)*SUMIF(DATI!$B:$B,Tabella24[[#This Row],[Cartella2]],DATI!$I:$I),"") | L27: =+IFERROR(+Tabella24[[#This Row],[IMPORTO VERSATO]]/SUMIF(DATI!$B:$B,Tabella24[[#This Row],[Cartella2]],DATI!$M:$M)*SUMIF(DATI!$B:$B,Tabella24[[#This Row],[Cartella2]],DATI!$J:$J),"") | M27: =+IFERROR(+Tabella24[[#This Row],[IMPORTO VERSATO]]/SUMIF(DATI!$B:$B,Tabella24[[#This Row],[Cartella2]],DATI!$M:$M)*SUMIF(DATI!$B:$B,Tabella24[[#This Row],[Cartella2]],DATI!$L:$L),"") | O27: =+IFERROR(+Tabella24[[#This Row],[IMPORTO VERSATO]]/SUMIF(DATI!$B:$B,Tabella24[[#This Row],[Cartella2]],DATI!$M:$M)*SUMIF(DATI!$B:$B,Tabella24[[#This Row],[Cartella2]],DATI!$K:$K),"")
C28: =+IF(Tabella24[[#This Row],[INS CARTELLA]]="",C27,+VLOOKUP(Tabella24[[#This Row],[INS CARTELLA]],Tabella1[[NUMERO CARTELLA]:[IMPOSTE]],1,0)) -> #N/A | G28: =+IFERROR(+Tabella24[[#This Row],[IMPORTO VERSATO]]/SUMIF(DATI!B:B,Tabella24[[#This Row],[Cartella2]],DATI!M:M)*SUMIF(DATI!B:B,Tabella24[[#This Row],[Cartella2]],DATI!E:E),"") | H28: =+IFERROR(+Tabella24[[#This Row],[IMPORTO VERSATO]]/SUMIF(DATI!$B:$B,Tabella24[[#This Row],[Cartella2]],DATI!$M:$M)*SUMIF(DATI!$B:$B,Tabella24[[#This Row],[Cartella2]],DATI!$F:$F),"") | I28: =+IFERROR(+Tabella24[[#This Row],[IMPORTO VERSATO]]/SUMIF(DATI!$B:$B,Tabella24[[#This Row],[Cartella2]],DATI!$M:$M)*SUMIF(DATI!$B:$B,Tabella24[[#This Row],[Cartella2]],DATI!$G:$G),"") | J28: =+IFERROR(+Tabella24[[#This Row],[IMPORTO VERSATO]]/SUMIF(DATI!$B:$B,Tabella24[[#This Row],[Cartella2]],DATI!$M:$M)*SUMIF(DATI!$B:$B,Tabella24[[#This Row],[Cartella2]],DATI!$H:$H),"") | K28: =+IFERROR(+Tabella24[[#This Row],[IMPORTO VERSATO]]/SUMIF(DATI!$B:$B,Tabella24[[#This Row],[Cartella2]],DATI!$M:$M)*SUMIF(DATI!$B:$B,Tabella24[[#This Row],[Cartella2]],DATI!$I:$I),"") | L28: =+IFERROR(+Tabella24[[#This Row],[IMPORTO VERSATO]]/SUMIF(DATI!$B:$B,Tabella24[[#This Row],[Cartella2]],DATI!$M:$M)*SUMIF(DATI!$B:$B,Tabella24[[#This Row],[Cartella2]],DATI!$J:$J),"") | M28: =+IFERROR(+Tabella24[[#This Row],[IMPORTO VERSATO]]/SUMIF(DATI!$B:$B,Tabella24[[#This Row],[Cartella2]],DATI!$M:$M)*SUMIF(DATI!$B:$B,Tabella24[[#This Row],[Cartella2]],DATI!$L:$L),"") | O28: =+IFERROR(+Tabella24[[#This Row],[IMPORTO VERSATO]]/SUMIF(DATI!$B:$B,Tabella24[[#This Row],[Cartella2]],DATI!$M:$M)*SUMIF(DATI!$B:$B,Tabella24[[#This Row],[Cartella2]],DATI!$K:$K),"")
C29: =+IF(Tabella24[[#This Row],[INS CARTELLA]]="",C28,+VLOOKUP(Tabella24[[#This Row],[INS CARTELLA]],Tabella1[[NUMERO CARTELLA]:[IMPOSTE]],1,0)) -> #N/A | G29: =+IFERROR(+Tabella24[[#This Row],[IMPORTO VERSATO]]/SUMIF(DATI!B:B,Tabella24[[#This Row],[Cartella2]],DATI!M:M)*SUMIF(DATI!B:B,Tabella24[[#This Row],[Cartella2]],DATI!E:E),"") | H29: =+IFERROR(+Tabella24[[#This Row],[IMPORTO VERSATO]]/SUMIF(DATI!$B:$B,Tabella24[[#This Row],[Cartella2]],DATI!$M:$M)*SUMIF(DATI!$B:$B,Tabella24[[#This Row],[Cartella2]],DATI!$F:$F),"") | I29: =+IFERROR(+Tabella24[[#This Row],[IMPORTO VERSATO]]/SUMIF(DATI!$B:$B,Tabella24[[#This Row],[Cartella2]],DATI!$M:$M)*SUMIF(DATI!$B:$B,Tabella24[[#This Row],[Cartella2]],DATI!$G:$G),"") | J29: =+IFERROR(+Tabella24[[#This Row],[IMPORTO VERSATO]]/SUMIF(DATI!$B:$B,Tabella24[[#This Row],[Cartella2]],DATI!$M:$M)*SUMIF(DATI!$B:$B,Tabella24[[#This Row],[Cartella2]],DATI!$H:$H),"") | K29: =+IFERROR(+Tabella24[[#This Row],[IMPORTO VERSATO]]/SUMIF(DATI!$B:$B,Tabella24[[#This Row],[Cartella2]],DATI!$M:$M)*SUMIF(DATI!$B:$B,Tabella24[[#This Row],[Cartella2]],DATI!$I:$I),"") | L29: =+IFERROR(+Tabella24[[#This Row],[IMPORTO VERSATO]]/SUMIF(DATI!$B:$B,Tabella24[[#This Row],[Cartella2]],DATI!$M:$M)*SUMIF(DATI!$B:$B,Tabella24[[#This Row],[Cartella2]],DATI!$J:$J),"") | M29: =+IFERROR(+Tabella24[[#This Row],[IMPORTO VERSATO]]/SUMIF(DATI!$B:$B,Tabella24[[#This Row],[Cartella2]],DATI!$M:$M)*SUMIF(DATI!$B:$B,Tabella24[[#This Row],[Cartella2]],DATI!$L:$L),"") | N29: =+IF(COUNTIF($C$17:C29,Tabella24[[#This Row],[Cartella2]])=1,"X","") | O29: =+IFERROR(+Tabella24[[#This Row],[IMPORTO VERSATO]]/SUMIF(DATI!$B:$B,Tabella24[[#This Row],[Cartella2]],DATI!$M:$M)*SUMIF(DATI!$B:$B,Tabella24[[#This Row],[Cartella2]],DATI!$K:$K),"")
C30: =+IF(Tabella24[[#This Row],[INS CARTELLA]]="",C29,+VLOOKUP(Tabella24[[#This Row],[INS CARTELLA]],Tabella1[[NUMERO CARTELLA]:[IMPOSTE]],1,0)) -> #N/A | G30: =+IFERROR(+Tabella24[[#This Row],[IMPORTO VERSATO]]/SUMIF(DATI!B:B,Tabella24[[#This Row],[Cartella2]],DATI!M:M)*SUMIF(DATI!B:B,Tabella24[[#This Row],[Cartella2]],DATI!E:E),"") | H30: =+IFERROR(+Tabella24[[#This Row],[IMPORTO VERSATO]]/SUMIF(DATI!$B:$B,Tabella24[[#This Row],[Cartella2]],DATI!$M:$M)*SUMIF(DATI!$B:$B,Tabella24[[#This Row],[Cartella2]],DATI!$F:$F),"") | I30: =+IFERROR(+Tabella24[[#This Row],[IMPORTO VERSATO]]/SUMIF(DATI!$B:$B,Tabella24[[#This Row],[Cartella2]],DATI!$M:$M)*SUMIF(DATI!$B:$B,Tabella24[[#This Row],[Cartella2]],DATI!$G:$G),"") | J30: =+IFERROR(+Tabella24[[#This Row],[IMPORTO VERSATO]]/SUMIF(DATI!$B:$B,Tabella24[[#This Row],[Cartella2]],DATI!$M:$M)*SUMIF(DATI!$B:$B,Tabella24[[#This Row],[Cartella2]],DATI!$H:$H),"") | K30: =+IFERROR(+Tabella24[[#This Row],[IMPORTO VERSATO]]/SUMIF(DATI!$B:$B,Tabella24[[#This Row],[Cartella2]],DATI!$M:$M)*SUMIF(DATI!$B:$B,Tabella24[[#This Row],[Cartella2]],DATI!$I:$I),"") | L30: =+IFERROR(+Tabella24[[#This Row],[IMPORTO VERSATO]]/SUMIF(DATI!$B:$B,Tabella24[[#This Row],[Cartella2]],DATI!$M:$M)*SUMIF(DATI!$B:$B,Tabella24[[#This Row],[Cartella2]],DATI!$J:$J),"") | M30: =+IFERROR(+Tabella24[[#This Row],[IMPORTO VERSATO]]/SUMIF(DATI!$B:$B,Tabella24[[#This Row],[Cartella2]],DATI!$M:$M)*SUMIF(DATI!$B:$B,Tabella24[[#This Row],[Cartella2]],DATI!$L:$L),"") | N30: =+IF(COUNTIF($C$17:C30,Tabella24[[#This Row],[Cartella2]])=1,"X","") | O30: =+IFERROR(+Tabella24[[#This Row],[IMPORTO VERSATO]]/SUMIF(DATI!$B:$B,Tabella24[[#This Row],[Cartella2]],DATI!$M:$M)*SUMIF(DATI!$B:$B,Tabella24[[#This Row],[Cartella2]],DATI!$K:$K),"")
C31: =+IF(Tabella24[[#This Row],[INS CARTELLA]]="",C30,+VLOOKUP(Tabella24[[#This Row],[INS CARTELLA]],Tabella1[[NUMERO CARTELLA]:[IMPOSTE]],1,0)) -> #N/A | G31: =+IFERROR(+Tabella24[[#This Row],[IMPORTO VERSATO]]/SUMIF(DATI!B:B,Tabella24[[#This Row],[Cartella2]],DATI!M:M)*SUMIF(DATI!B:B,Tabella24[[#This Row],[Cartella2]],DATI!E:E),"") | H31: =+IFERROR(+Tabella24[[#This Row],[IMPORTO VERSATO]]/SUMIF(DATI!$B:$B,Tabella24[[#This Row],[Cartella2]],DATI!$M:$M)*SUMIF(DATI!$B:$B,Tabella24[[#This Row],[Cartella2]],DATI!$F:$F),"") | I31: =+IFERROR(+Tabella24[[#This Row],[IMPORTO VERSATO]]/SUMIF(DATI!$B:$B,Tabella24[[#This Row],[Cartella2]],DATI!$M:$M)*SUMIF(DATI!$B:$B,Tabella24[[#This Row],[Cartella2]],DATI!$G:$G),"") | J31: =+IFERROR(+Tabella24[[#This Row],[IMPORTO VERSATO]]/SUMIF(DATI!$B:$B,Tabella24[[#This Row],[Cartella2]],DATI!$M:$M)*SUMIF(DATI!$B:$B,Tabella24[[#This Row],[Cartella2]],DATI!$H:$H),"") | K31: =+IFERROR(+Tabella24[[#This Row],[IMPORTO VERSATO]]/SUMIF(DATI!$B:$B,Tabella24[[#This Row],[Cartella2]],DATI!$M:$M)*SUMIF(DATI!$B:$B,Tabella24[[#This Row],[Cartella2]],DATI!$I:$I),"") | L31: =+IFERROR(+Tabella24[[#This Row],[IMPORTO VERSATO]]/SUMIF(DATI!$B:$B,Tabella24[[#This Row],[Cartella2]],DATI!$M:$M)*SUMIF(DATI!$B:$B,Tabella24[[#This Row],[Cartella2]],DATI!$J:$J),"") | M31: =+IFERROR(+Tabella24[[#This Row],[IMPORTO VERSATO]]/SUMIF(DATI!$B:$B,Tabella24[[#This Row],[Cartella2]],DATI!$M:$M)*SUMIF(DATI!$B:$B,Tabella24[[#This Row],[Cartella2]],DATI!$L:$L),"") | N31: =+IF(COUNTIF($C$17:C31,Tabella24[[#This Row],[Cartella2]])=1,"X","") | O31: =+IFERROR(+Tabella24[[#This Row],[IMPORTO VERSATO]]/SUMIF(DATI!$B:$B,Tabella24[[#This Row],[Cartella2]],DATI!$M:$M)*SUMIF(DATI!$B:$B,Tabella24[[#This Row],[Cartella2]],DATI!$K:$K),"")
C32: =+IF(Tabella24[[#This Row],[INS CARTELLA]]="",C31,+VLOOKUP(Tabella24[[#This Row],[INS CARTELLA]],Tabella1[[NUMERO CARTELLA]:[IMPOSTE]],1,0)) -> #N/A | G32: =+IFERROR(+Tabella24[[#This Row],[IMPORTO VERSATO]]/SUMIF(DATI!B:B,Tabella24[[#This Row],[Cartella2]],DATI!M:M)*SUMIF(DATI!B:B,Tabella24[[#This Row],[Cartella2]],DATI!E:E),"") | H32: =+IFERROR(+Tabella24[[#This Row],[IMPORTO VERSATO]]/SUMIF(DATI!$B:$B,Tabella24[[#This Row],[Cartella2]],DATI!$M:$M)*SUMIF(DATI!$B:$B,Tabella24[[#This Row],[Cartella2]],DATI!$F:$F),"") | I32: =+IFERROR(+Tabella24[[#This Row],[IMPORTO VERSATO]]/SUMIF(DATI!$B:$B,Tabella24[[#This Row],[Cartella2]],DATI!$M:$M)*SUMIF(DATI!$B:$B,Tabella24[[#This Row],[Cartella2]],DATI!$G:$G),"") | J32: =+IFERROR(+Tabella24[[#This Row],[IMPORTO VERSATO]]/SUMIF(DATI!$B:$B,Tabella24[[#This Row],[Cartella2]],DATI!$M:$M)*SUMIF(DATI!$B:$B,Tabella24[[#This Row],[Cartella2]],DATI!$H:$H),"") | K32: =+IFERROR(+Tabella24[[#This Row],[IMPORTO VERSATO]]/SUMIF(DATI!$B:$B,Tabella24[[#This Row],[Cartella2]],DATI!$M:$M)*SUMIF(DATI!$B:$B,Tabella24[[#This Row],[Cartella2]],DATI!$I:$I),"") | L32: =+IFERROR(+Tabella24[[#This Row],[IMPORTO VERSATO]]/SUMIF(DATI!$B:$B,Tabella24[[#This Row],[Cartella2]],DATI!$M:$M)*SUMIF(DATI!$B:$B,Tabella24[[#This Row],[Cartella2]],DATI!$J:$J),"") | M32: =+IFERROR(+Tabella24[[#This Row],[IMPORTO VERSATO]]/SUMIF(DATI!$B:$B,Tabella24[[#This Row],[Cartella2]],DATI!$M:$M)*SUMIF(DATI!$B:$B,Tabella24[[#This Row],[Cartella2]],DATI!$L:$L),"") | N32: =+IF(COUNTIF($C$17:C32,Tabella24[[#This Row],[Cartella2]])=1,"X","") | O32: =+IFERROR(+Tabella24[[#This Row],[IMPORTO VERSATO]]/SUMIF(DATI!$B:$B,Tabella24[[#This Row],[Cartella2]],DATI!$M:$M)*SUMIF(DATI!$B:$B,Tabella24[[#This Row],[Cartella2]],DATI!$K:$K),"")
C33: =+IF(Tabella24[[#This Row],[INS CARTELLA]]="",C32,+VLOOKUP(Tabella24[[#This Row],[INS CARTELLA]],Tabella1[[NUMERO CARTELLA]:[IMPOSTE]],1,0)) -> #N/A | G33: =+IFERROR(+Tabella24[[#This Row],[IMPORTO VERSATO]]/SUMIF(DATI!B:B,Tabella24[[#This Row],[Cartella2]],DATI!M:M)*SUMIF(DATI!B:B,Tabella24[[#This Row],[Cartella2]],DATI!E:E),"") | H33: =+IFERROR(+Tabella24[[#This Row],[IMPORTO VERSATO]]/SUMIF(DATI!$B:$B,Tabella24[[#This Row],[Cartella2]],DATI!$M:$M)*SUMIF(DATI!$B:$B,Tabella24[[#This Row],[Cartella2]],DATI!$F:$F),"") | I33: =+IFERROR(+Tabella24[[#This Row],[IMPORTO VERSATO]]/SUMIF(DATI!$B:$B,Tabella24[[#This Row],[Cartella2]],DATI!$M:$M)*SUMIF(DATI!$B:$B,Tabella24[[#This Row],[Cartella2]],DATI!$G:$G),"") | J33: =+IFERROR(+Tabella24[[#This Row],[IMPORTO VERSATO]]/SUMIF(DATI!$B:$B,Tabella24[[#This Row],[Cartella2]],DATI!$M:$M)*SUMIF(DATI!$B:$B,Tabella24[[#This Row],[Cartella2]],DATI!$H:$H),"") | K33: =+IFERROR(+Tabella24[[#This Row],[IMPORTO VERSATO]]/SUMIF(DATI!$B:$B,Tabella24[[#This Row],[Cartella2]],DATI!$M:$M)*SUMIF(DATI!$B:$B,Tabella24[[#This Row],[Cartella2]],DATI!$I:$I),"") | L33: =+IFERROR(+Tabella24[[#This Row],[IMPORTO VERSATO]]/SUMIF(DATI!$B:$B,Tabella24[[#This Row],[Cartella2]],DATI!$M:$M)*SUMIF(DATI!$B:$B,Tabella24[[#This Row],[Cartella2]],DATI!$J:$J),"") | M33: =+IFERROR(+Tabella24[[#This Row],[IMPORTO VERSATO]]/SUMIF(DATI!$B:$B,Tabella24[[#This Row],[Cartella2]],DATI!$M:$M)*SUMIF(DATI!$B:$B,Tabella24[[#This Row],[Cartella2]],DATI!$L:$L),"") | N33: =+IF(COUNTIF($C$17:C33,Tabella24[[#This Row],[Cartella2]])=1,"X","") | O33: =+IFERROR(+Tabella24[[#This Row],[IMPORTO VERSATO]]/SUMIF(DATI!$B:$B,Tabella24[[#This Row],[Cartella2]],DATI!$M:$M)*SUMIF(DATI!$B:$B,Tabella24[[#This Row],[Cartella2]],DATI!$K:$K),"")
C34: =+IF(Tabella24[[#This Row],[INS CARTELLA]]="",C33,+VLOOKUP(Tabella24[[#This Row],[INS CARTELLA]],Tabella1[[NUMERO CARTELLA]:[IMPOSTE]],1,0)) -> #N/A | G34: =+IFERROR(+Tabella24[[#This Row],[IMPORTO VERSATO]]/SUMIF(DATI!B:B,Tabella24[[#This Row],[Cartella2]],DATI!M:M)*SUMIF(DATI!B:B,Tabella24[[#This Row],[Cartella2]],DATI!E:E),"") | H34: =+IFERROR(+Tabella24[[#This Row],[IMPORTO VERSATO]]/SUMIF(DATI!$B:$B,Tabella24[[#This Row],[Cartella2]],DATI!$M:$M)*SUMIF(DATI!$B:$B,Tabella24[[#This Row],[Cartella2]],DATI!$F:$F),"") | I34: =+IFERROR(+Tabella24[[#This Row],[IMPORTO VERSATO]]/SUMIF(DATI!$B:$B,Tabella24[[#This Row],[Cartella2]],DATI!$M:$M)*SUMIF(DATI!$B:$B,Tabella24[[#This Row],[Cartella2]],DATI!$G:$G),"") | J34: =+IFERROR(+Tabella24[[#This Row],[IMPORTO VERSATO]]/SUMIF(DATI!$B:$B,Tabella24[[#This Row],[Cartella2]],DATI!$M:$M)*SUMIF(DATI!$B:$B,Tabella24[[#This Row],[Cartella2]],DATI!$H:$H),"") | K34: =+IFERROR(+Tabella24[[#This Row],[IMPORTO VERSATO]]/SUMIF(DATI!$B:$B,Tabella24[[#This Row],[Cartella2]],DATI!$M:$M)*SUMIF(DATI!$B:$B,Tabella24[[#This Row],[Cartella2]],DATI!$I:$I),"") | L34: =+IFERROR(+Tabella24[[#This Row],[IMPORTO VERSATO]]/SUMIF(DATI!$B:$B,Tabella24[[#This Row],[Cartella2]],DATI!$M:$M)*SUMIF(DATI!$B:$B,Tabella24[[#This Row],[Cartella2]],DATI!$J:$J),"") | M34: =+IFERROR(+Tabella24[[#This Row],[IMPORTO VERSATO]]/SUMIF(DATI!$B:$B,Tabella24[[#This Row],[Cartella2]],DATI!$M:$M)*SUMIF(DATI!$B:$B,Tabella24[[#This Row],[Cartella2]],DATI!$L:$L),"") | N34: =+IF(COUNTIF($C$17:C34,Tabella24[[#This Row],[Cartella2]])=1,"X","") | O34: =+IFERROR(+Tabella24[[#This Row],[IMPORTO VERSATO]]/SUMIF(DATI!$B:$B,Tabella24[[#This Row],[Cartella2]],DATI!$M:$M)*SUMIF(DATI!$B:$B,Tabella24[[#This Row],[Cartella2]],DATI!$K:$K),"")
C35: =+IF(Tabella24[[#This Row],[INS CARTELLA]]="",C34,+VLOOKUP(Tabella24[[#This Row],[INS CARTELLA]],Tabella1[[NUMERO CARTELLA]:[IMPOSTE]],1,0)) -> #N/A | G35: =+IFERROR(+Tabella24[[#This Row],[IMPORTO VERSATO]]/SUMIF(DATI!B:B,Tabella24[[#This Row],[Cartella2]],DATI!M:M)*SUMIF(DATI!B:B,Tabella24[[#This Row],[Cartella2]],DATI!E:E),"") | H35: =+IFERROR(+Tabella24[[#This Row],[IMPORTO VERSATO]]/SUMIF(DATI!$B:$B,Tabella24[[#This Row],[Cartella2]],DATI!$M:$M)*SUMIF(DATI!$B:$B,Tabella24[[#This Row],[Cartella2]],DATI!$F:$F),"") | I35: =+IFERROR(+Tabella24[[#This Row],[IMPORTO VERSATO]]/SUMIF(DATI!$B:$B,Tabella24[[#This Row],[Cartella2]],DATI!$M:$M)*SUMIF(DATI!$B:$B,Tabella24[[#This Row],[Cartella2]],DATI!$G:$G),"") | J35: =+IFERROR(+Tabella24[[#This Row],[IMPORTO VERSATO]]/SUMIF(DATI!$B:$B,Tabella24[[#This Row],[Cartella2]],DATI!$M:$M)*SUMIF(DATI!$B:$B,Tabella24[[#This Row],[Cartella2]],DATI!$H:$H),"") | K35: =+IFERROR(+Tabella24[[#This Row],[IMPORTO VERSATO]]/SUMIF(DATI!$B:$B,Tabella24[[#This Row],[Cartella2]],DATI!$M:$M)*SUMIF(DATI!$B:$B,Tabella24[[#This Row],[Cartella2]],DATI!$I:$I),"") | L35: =+IFERROR(+Tabella24[[#This Row],[IMPORTO VERSATO]]/SUMIF(DATI!$B:$B,Tabella24[[#This Row],[Cartella2]],DATI!$M:$M)*SUMIF(DATI!$B:$B,Tabella24[[#This Row],[Cartella2]],DATI!$J:$J),"") | M35: =+IFERROR(+Tabella24[[#This Row],[IMPORTO VERSATO]]/SUMIF(DATI!$B:$B,Tabella24[[#This Row],[Cartella2]],DATI!$M:$M)*SUMIF(DATI!$B:$B,Tabella24[[#This Row],[Cartella2]],DATI!$L:$L),"") | N35: =+IF(COUNTIF($C$17:C35,Tabella24[[#This Row],[Cartella2]])=1,"X","") | O35: =+IFERROR(+Tabella24[[#This Row],[IMPORTO VERSATO]]/SUMIF(DATI!$B:$B,Tabella24[[#This Row],[Cartella2]],DATI!$M:$M)*SUMIF(DATI!$B:$B,Tabella24[[#This Row],[Cartella2]],DATI!$K:$K),"")
C36: =+IF(Tabella24[[#This Row],[INS CARTELLA]]="",C35,+VLOOKUP(Tabella24[[#This Row],[INS CARTELLA]],Tabella1[[NUMERO CARTELLA]:[IMPOSTE]],1,0)) -> #N/A | G36: =+IFERROR(+Tabella24[[#This Row],[IMPORTO VERSATO]]/SUMIF(DATI!B:B,Tabella24[[#This Row],[Cartella2]],DATI!M:M)*SUMIF(DATI!B:B,Tabella24[[#This Row],[Cartella2]],DATI!E:E),"") | H36: =+IFERROR(+Tabella24[[#This Row],[IMPORTO VERSATO]]/SUMIF(DATI!$B:$B,Tabella24[[#This Row],[Cartella2]],DATI!$M:$M)*SUMIF(DATI!$B:$B,Tabella24[[#This Row],[Cartella2]],DATI!$F:$F),"") | I36: =+IFERROR(+Tabella24[[#This Row],[IMPORTO VERSATO]]/SUMIF(DATI!$B:$B,Tabella24[[#This Row],[Cartella2]],DATI!$M:$M)*SUMIF(DATI!$B:$B,Tabella24[[#This Row],[Cartella2]],DATI!$G:$G),"") | J36: =+IFERROR(+Tabella24[[#This Row],[IMPORTO VERSATO]]/SUMIF(DATI!$B:$B,Tabella24[[#This Row],[Cartella2]],DATI!$M:$M)*SUMIF(DATI!$B:$B,Tabella24[[#This Row],[Cartella2]],DATI!$H:$H),"") | K36: =+IFERROR(+Tabella24[[#This Row],[IMPORTO VERSATO]]/SUMIF(DATI!$B:$B,Tabella24[[#This Row],[Cartella2]],DATI!$M:$M)*SUMIF(DATI!$B:$B,Tabella24[[#This Row],[Cartella2]],DATI!$I:$I),"") | L36: =+IFERROR(+Tabella24[[#This Row],[IMPORTO VERSATO]]/SUMIF(DATI!$B:$B,Tabella24[[#This Row],[Cartella2]],DATI!$M:$M)*SUMIF(DATI!$B:$B,Tabella24[[#This Row],[Cartella2]],DATI!$J:$J),"") | M36: =+IFERROR(+Tabella24[[#This Row],[IMPORTO VERSATO]]/SUMIF(DATI!$B:$B,Tabella24[[#This Row],[Cartella2]],DATI!$M:$M)*SUMIF(DATI!$B:$B,Tabella24[[#This Row],[Cartella2]],DATI!$L:$L),"") | N36: =+IF(COUNTIF($C$17:C36,Tabella24[[#This Row],[Cartella2]])=1,"X","") | O36: =+IFERROR(+Tabella24[[#This Row],[IMPORTO VERSATO]]/SUMIF(DATI!$B:$B,Tabella24[[#This Row],[Cartella2]],DATI!$M:$M)*SUMIF(DATI!$B:$B,Tabella24[[#This Row],[Cartella2]],DATI!$K:$K),"")
C37: =+IF(Tabella24[[#This Row],[INS CARTELLA]]="",C36,+VLOOKUP(Tabella24[[#This Row],[INS CARTELLA]],Tabella1[[NUMERO CARTELLA]:[IMPOSTE]],1,0)) -> #N/A | G37: =+IFERROR(+Tabella24[[#This Row],[IMPORTO VERSATO]]/SUMIF(DATI!B:B,Tabella24[[#This Row],[Cartella2]],DATI!M:M)*SUMIF(DATI!B:B,Tabella24[[#This Row],[Cartella2]],DATI!E:E),"") | H37: =+IFERROR(+Tabella24[[#This Row],[IMPORTO VERSATO]]/SUMIF(DATI!$B:$B,Tabella24[[#This Row],[Cartella2]],DATI!$M:$M)*SUMIF(DATI!$B:$B,Tabella24[[#This Row],[Cartella2]],DATI!$F:$F),"") | I37: =+IFERROR(+Tabella24[[#This Row],[IMPORTO VERSATO]]/SUMIF(DATI!$B:$B,Tabella24[[#This Row],[Cartella2]],DATI!$M:$M)*SUMIF(DATI!$B:$B,Tabella24[[#This Row],[Cartella2]],DATI!$G:$G),"") | J37: =+IFERROR(+Tabella24[[#This Row],[IMPORTO VERSATO]]/SUMIF(DATI!$B:$B,Tabella24[[#This Row],[Cartella2]],DATI!$M:$M)*SUMIF(DATI!$B:$B,Tabella24[[#This Row],[Cartella2]],DATI!$H:$H),"") | K37: =+IFERROR(+Tabella24[[#This Row],[IMPORTO VERSATO]]/SUMIF(DATI!$B:$B,Tabella24[[#This Row],[Cartella2]],DATI!$M:$M)*SUMIF(DATI!$B:$B,Tabella24[[#This Row],[Cartella2]],DATI!$I:$I),"") | L37: =+IFERROR(+Tabella24[[#This Row],[IMPORTO VERSATO]]/SUMIF(DATI!$B:$B,Tabella24[[#This Row],[Cartella2]],DATI!$M:$M)*SUMIF(DATI!$B:$B,Tabella24[[#This Row],[Cartella2]],DATI!$J:$J),"") | M37: =+IFERROR(+Tabella24[[#This Row],[IMPORTO VERSATO]]/SUMIF(DATI!$B:$B,Tabella24[[#This Row],[Cartella2]],DATI!$M:$M)*SUMIF(DATI!$B:$B,Tabella24[[#This Row],[Cartella2]],DATI!$L:$L),"") | N37: =+IF(COUNTIF($C$17:C37,Tabella24[[#This Row],[Cartella2]])=1,"X","") | O37: =+IFERROR(+Tabella24[[#This Row],[IMPORTO VERSATO]]/SUMIF(DATI!$B:$B,Tabella24[[#This Row],[Cartella2]],DATI!$M:$M)*SUMIF(DATI!$B:$B,Tabella24[[#This Row],[Cartella2]],DATI!$K:$K),"")
C38: =+IF(Tabella24[[#This Row],[INS CARTELLA]]="",C37,+VLOOKUP(Tabella24[[#This Row],[INS CARTELLA]],Tabella1[[NUMERO CARTELLA]:[IMPOSTE]],1,0)) -> #N/A | G38: =+IFERROR(+Tabella24[[#This Row],[IMPORTO VERSATO]]/SUMIF(DATI!B:B,Tabella24[[#This Row],[Cartella2]],DATI!M:M)*SUMIF(DATI!B:B,Tabella24[[#This Row],[Cartella2]],DATI!E:E),"") | H38: =+IFERROR(+Tabella24[[#This Row],[IMPORTO VERSATO]]/SUMIF(DATI!$B:$B,Tabella24[[#This Row],[Cartella2]],DATI!$M:$M)*SUMIF(DATI!$B:$B,Tabella24[[#This Row],[Cartella2]],DATI!$F:$F),"") | I38: =+IFERROR(+Tabella24[[#This Row],[IMPORTO VERSATO]]/SUMIF(DATI!$B:$B,Tabella24[[#This Row],[Cartella2]],DATI!$M:$M)*SUMIF(DATI!$B:$B,Tabella24[[#This Row],[Cartella2]],DATI!$G:$G),"") | J38: =+IFERROR(+Tabella24[[#This Row],[IMPORTO VERSATO]]/SUMIF(DATI!$B:$B,Tabella24[[#This Row],[Cartella2]],DATI!$M:$M)*SUMIF(DATI!$B:$B,Tabella24[[#This Row],[Cartella2]],DATI!$H:$H),"") | K38: =+IFERROR(+Tabella24[[#This Row],[IMPORTO VERSATO]]/SUMIF(DATI!$B:$B,Tabella24[[#This Row],[Cartella2]],DATI!$M:$M)*SUMIF(DATI!$B:$B,Tabella24[[#This Row],[Cartella2]],DATI!$I:$I),"") | L38: =+IFERROR(+Tabella24[[#This Row],[IMPORTO VERSATO]]/SUMIF(DATI!$B:$B,Tabella24[[#This Row],[Cartella2]],DATI!$M:$M)*SUMIF(DATI!$B:$B,Tabella24[[#This Row],[Cartella2]],DATI!$J:$J),"") | M38: =+IFERROR(+Tabella24[[#This Row],[IMPORTO VERSATO]]/SUMIF(DATI!$B:$B,Tabella24[[#This Row],[Cartella2]],DATI!$M:$M)*SUMIF(DATI!$B:$B,Tabella24[[#This Row],[Cartella2]],DATI!$L:$L),"") | N38: =+IF(COUNTIF($C$17:C38,Tabella24[[#This Row],[Cartella2]])=1,"X","") | O38: =+IFERROR(+Tabella24[[#This Row],[IMPORTO VERSATO]]/SUMIF(DATI!$B:$B,Tabella24[[#This Row],[Cartella2]],DATI!$M:$M)*SUMIF(DATI!$B:$B,Tabella24[[#This Row],[Cartella2]],DATI!$K:$K),"")
C39: =+IF(Tabella24[[#This Row],[INS CARTELLA]]="",C38,+VLOOKUP(Tabella24[[#This Row],[INS CARTELLA]],Tabella1[[NUMERO CARTELLA]:[IMPOSTE]],1,0)) -> #N/A | G39: =+IFERROR(+Tabella24[[#This Row],[IMPORTO VERSATO]]/SUMIF(DATI!B:B,Tabella24[[#This Row],[Cartella2]],DATI!M:M)*SUMIF(DATI!B:B,Tabella24[[#This Row],[Cartella2]],DATI!E:E),"") | H39: =+IFERROR(+Tabella24[[#This Row],[IMPORTO VERSATO]]/SUMIF(DATI!$B:$B,Tabella24[[#This Row],[Cartella2]],DATI!$M:$M)*SUMIF(DATI!$B:$B,Tabella24[[#This Row],[Cartella2]],DATI!$F:$F),"") | I39: =+IFERROR(+Tabella24[[#This Row],[IMPORTO VERSATO]]/SUMIF(DATI!$B:$B,Tabella24[[#This Row],[Cartella2]],DATI!$M:$M)*SUMIF(DATI!$B:$B,Tabella24[[#This Row],[Cartella2]],DATI!$G:$G),"") | J39: =+IFERROR(+Tabella24[[#This Row],[IMPORTO VERSATO]]/SUMIF(DATI!$B:$B,Tabella24[[#This Row],[Cartella2]],DATI!$M:$M)*SUMIF(DATI!$B:$B,Tabella24[[#This Row],[Cartella2]],DATI!$H:$H),"") | K39: =+IFERROR(+Tabella24[[#This Row],[IMPORTO VERSATO]]/SUMIF(DATI!$B:$B,Tabella24[[#This Row],[Cartella2]],DATI!$M:$M)*SUMIF(DATI!$B:$B,Tabella24[[#This Row],[Cartella2]],DATI!$I:$I),"") | L39: =+IFERROR(+Tabella24[[#This Row],[IMPORTO VERSATO]]/SUMIF(DATI!$B:$B,Tabella24[[#This Row],[Cartella2]],DATI!$M:$M)*SUMIF(DATI!$B:$B,Tabella24[[#This Row],[Cartella2]],DATI!$J:$J),"") | M39: =+IFERROR(+Tabella24[[#This Row],[IMPORTO VERSATO]]/SUMIF(DATI!$B:$B,Tabella24[[#This Row],[Cartella2]],DATI!$M:$M)*SUMIF(DATI!$B:$B,Tabella24[[#This Row],[Cartella2]],DATI!$L:$L),"") | N39: =+IF(COUNTIF($C$17:C39,Tabella24[[#This Row],[Cartella2]])=1,"X","") | O39: =+IFERROR(+Tabella24[[#This Row],[IMPORTO VERSATO]]/SUMIF(DATI!$B:$B,Tabella24[[#This Row],[Cartella2]],DATI!$M:$M)*SUMIF(DATI!$B:$B,Tabella24[[#This Row],[Cartella2]],DATI!$K:$K),"")
C40: =+IF(Tabella24[[#This Row],[INS CARTELLA]]="",C39,+VLOOKUP(Tabella24[[#This Row],[INS CARTELLA]],Tabella1[[NUMERO CARTELLA]:[IMPOSTE]],1,0)) -> #N/A | G40: =+IFERROR(+Tabella24[[#This Row],[IMPORTO VERSATO]]/SUMIF(DATI!B:B,Tabella24[[#This Row],[Cartella2]],DATI!M:M)*SUMIF(DATI!B:B,Tabella24[[#This Row],[Cartella2]],DATI!E:E),"") | H40: =+IFERROR(+Tabella24[[#This Row],[IMPORTO VERSATO]]/SUMIF(DATI!$B:$B,Tabella24[[#This Row],[Cartella2]],DATI!$M:$M)*SUMIF(DATI!$B:$B,Tabella24[[#This Row],[Cartella2]],DATI!$F:$F),"") | I40: =+IFERROR(+Tabella24[[#This Row],[IMPORTO VERSATO]]/SUMIF(DATI!$B:$B,Tabella24[[#This Row],[Cartella2]],DATI!$M:$M)*SUMIF(DATI!$B:$B,Tabella24[[#This Row],[Cartella2]],DATI!$G:$G),"") | J40: =+IFERROR(+Tabella24[[#This Row],[IMPORTO VERSATO]]/SUMIF(DATI!$B:$B,Tabella24[[#This Row],[Cartella2]],DATI!$M:$M)*SUMIF(DATI!$B:$B,Tabella24[[#This Row],[Cartella2]],DATI!$H:$H),"") | K40: =+IFERROR(+Tabella24[[#This Row],[IMPORTO VERSATO]]/SUMIF(DATI!$B:$B,Tabella24[[#This Row],[Cartella2]],DATI!$M:$M)*SUMIF(DATI!$B:$B,Tabella24[[#This Row],[Cartella2]],DATI!$I:$I),"") | L40: =+IFERROR(+Tabella24[[#This Row],[IMPORTO VERSATO]]/SUMIF(DATI!$B:$B,Tabella24[[#This Row],[Cartella2]],DATI!$M:$M)*SUMIF(DATI!$B:$B,Tabella24[[#This Row],[Cartella2]],DATI!$J:$J),"") | M40: =+IFERROR(+Tabella24[[#This Row],[IMPORTO VERSATO]]/SUMIF(DATI!$B:$B,Tabella24[[#This Row],[Cartella2]],DATI!$M:$M)*SUMIF(DATI!$B:$B,Tabella24[[#This Row],[Cartella2]],DATI!$L:$L),"") | N40: =+IF(COUNTIF($C$17:C40,Tabella24[[#This Row],[Cartella2]])=1,"X","") | O40: =+IFERROR(+Tabella24[[#This Row],[IMPORTO VERSATO]]/SUMIF(DATI!$B:$B,Tabella24[[#This Row],[Cartella2]],DATI!$M:$M)*SUMIF(DATI!$B:$B,Tabella24[[#This Row],[Cartella2]],DATI!$K:$K),"")
... C1436: =+IF(Tabella24[[#This Row],[INS CARTELLA]]="",C1435,+VLOOKUP(Tabella24[[#This Row],[INS CARTELLA]],Tabella1[[NUMERO CARTELLA]:[IMPOSTE]],1,0)) -> #N/A | G1436: =+IFERROR(+Tabella24[[#This Row],[IMPORTO VERSATO]]/SUMIF(DATI!B:B,Tabella24[[#This Row],[Cartella2]],DATI!M:M)*SUMIF(DATI!B:B,Tabella24[[#This Row],[Cartella2]],DATI!E:E),"") | H1436: =+IFERROR(+Tabella24[[#This Row],[IMPORTO VERSATO]]/SUMIF(DATI!$B:$B,Tabella24[[#This Row],[Cartella2]],DATI!$M:$M)*SUMIF(DATI!$B:$B,Tabella24[[#This Row],[Cartella2]],DATI!$F:$F),"") | I1436: =+IFERROR(+Tabella24[[#This Row],[IMPORTO VERSATO]]/SUMIF(DATI!$B:$B,Tabella24[[#This Row],[Cartella2]],DATI!$M:$M)*SUMIF(DATI!$B:$B,Tabella24[[#This Row],[Cartella2]],DATI!$G:$G),"") | J1436: =+IFERROR(+Tabella24[[#This Row],[IMPORTO VERSATO]]/SUMIF(DATI!$B:$B,Tabella24[[#This Row],[Cartella2]],DATI!$M:$M)*SUMIF(DATI!$B:$B,Tabella24[[#This Row],[Cartella2]],DATI!$H:$H),"") | K1436: =+IFERROR(+Tabella24[[#This Row],[IMPORTO VERSATO]]/SUMIF(DATI!$B:$B,Tabella24[[#This Row],[Cartella2]],DATI!$M:$M)*SUMIF(DATI!$B:$B,Tabella24[[#This Row],[Cartella2]],DATI!$I:$I),"") | L1436: =+IFERROR(+Tabella24[[#This Row],[IMPORTO VERSATO]]/SUMIF(DATI!$B:$B,Tabella24[[#This Row],[Cartella2]],DATI!$M:$M)*SUMIF(DATI!$B:$B,Tabella24[[#This Row],[Cartella2]],DATI!$J:$J),"") | M1436: =+IFERROR(+Tabella24[[#This Row],[IMPORTO VERSATO]]/SUMIF(DATI!$B:$B,Tabella24[[#This Row],[Cartella2]],DATI!$M:$M)*SUMIF(DATI!$B:$B,Tabella24[[#This Row],[Cartella2]],DATI!$L:$L),"") | N1436: =+IF(COUNTIF($C$17:C1436,Tabella24[[#This Row],[Cartella2]])=1,"X","") | O1436: =+IFERROR(+Tabella24[[#This Row],[IMPORTO VERSATO]]/SUMIF(DATI!$B:$B,Tabella24[[#This Row],[Cartella2]],DATI!$M:$M)*SUMIF(DATI!$B:$B,Tabella24[[#This Row],[Cartella2]],DATI!$K:$K),"")
C1437: =+IF(Tabella24[[#This Row],[INS CARTELLA]]="",C1436,+VLOOKUP(Tabella24[[#This Row],[INS CARTELLA]],Tabella1[[NUMERO CARTELLA]:[IMPOSTE]],1,0)) -> #N/A | G1437: =+IFERROR(+Tabella24[[#This Row],[IMPORTO VERSATO]]/SUMIF(DATI!B:B,Tabella24[[#This Row],[Cartella2]],DATI!M:M)*SUMIF(DATI!B:B,Tabella24[[#This Row],[Cartella2]],DATI!E:E),"") | H1437: =+IFERROR(+Tabella24[[#This Row],[IMPORTO VERSATO]]/SUMIF(DATI!$B:$B,Tabella24[[#This Row],[Cartella2]],DATI!$M:$M)*SUMIF(DATI!$B:$B,Tabella24[[#This Row],[Cartella2]],DATI!$F:$F),"") | I1437: =+IFERROR(+Tabella24[[#This Row],[IMPORTO VERSATO]]/SUMIF(DATI!$B:$B,Tabella24[[#This Row],[Cartella2]],DATI!$M:$M)*SUMIF(DATI!$B:$B,Tabella24[[#This Row],[Cartella2]],DATI!$G:$G),"") | J1437: =+IFERROR(+Tabella24[[#This Row],[IMPORTO VERSATO]]/SUMIF(DATI!$B:$B,Tabella24[[#This Row],[Cartella2]],DATI!$M:$M)*SUMIF(DATI!$B:$B,Tabella24[[#This Row],[Cartella2]],DATI!$H:$H),"") | K1437: =+IFERROR(+Tabella24[[#This Row],[IMPORTO VERSATO]]/SUMIF(DATI!$B:$B,Tabella24[[#This Row],[Cartella2]],DATI!$M:$M)*SUMIF(DATI!$B:$B,Tabella24[[#This Row],[Cartella2]],DATI!$I:$I),"") | L1437: =+IFERROR(+Tabella24[[#This Row],[IMPORTO VERSATO]]/SUMIF(DATI!$B:$B,Tabella24[[#This Row],[Cartella2]],DATI!$M:$M)*SUMIF(DATI!$B:$B,Tabella24[[#This Row],[Cartella2]],DATI!$J:$J),"") | M1437: =+IFERROR(+Tabella24[[#This Row],[IMPORTO VERSATO]]/SUMIF(DATI!$B:$B,Tabella24[[#This Row],[Cartella2]],DATI!$M:$M)*SUMIF(DATI!$B:$B,Tabella24[[#This Row],[Cartella2]],DATI!$L:$L),"") | N1437: =+IF(COUNTIF($C$17:C1502,Tabella24[[#This Row],[Cartella2]])=1,"X","") | O1437: =+IFERROR(+Tabella24[[#This Row],[IMPORTO VERSATO]]/SUMIF(DATI!$B:$B,Tabella24[[#This Row],[Cartella2]],DATI!$M:$M)*SUMIF(DATI!$B:$B,Tabella24[[#This Row],[Cartella2]],DATI!$K:$K),"")
C1438: =+IF(Tabella24[[#This Row],[INS CARTELLA]]="",C1437,+VLOOKUP(Tabella24[[#This Row],[INS CARTELLA]],Tabella1[[NUMERO CARTELLA]:[IMPOSTE]],1,0)) -> #N/A | G1438: =+IFERROR(+Tabella24[[#This Row],[IMPORTO VERSATO]]/SUMIF(DATI!B:B,Tabella24[[#This Row],[Cartella2]],DATI!M:M)*SUMIF(DATI!B:B,Tabella24[[#This Row],[Cartella2]],DATI!E:E),"") | H1438: =+IFERROR(+Tabella24[[#This Row],[IMPORTO VERSATO]]/SUMIF(DATI!$B:$B,Tabella24[[#This Row],[Cartella2]],DATI!$M:$M)*SUMIF(DATI!$B:$B,Tabella24[[#This Row],[Cartella2]],DATI!$F:$F),"") | I1438: =+IFERROR(+Tabella24[[#This Row],[IMPORTO VERSATO]]/SUMIF(DATI!$B:$B,Tabella24[[#This Row],[Cartella2]],DATI!$M:$M)*SUMIF(DATI!$B:$B,Tabella24[[#This Row],[Cartella2]],DATI!$G:$G),"") | J1438: =+IFERROR(+Tabella24[[#This Row],[IMPORTO VERSATO]]/SUMIF(DATI!$B:$B,Tabella24[[#This Row],[Cartella2]],DATI!$M:$M)*SUMIF(DATI!$B:$B,Tabella24[[#This Row],[Cartella2]],DATI!$H:$H),"") | K1438: =+IFERROR(+Tabella24[[#This Row],[IMPORTO VERSATO]]/SUMIF(DATI!$B:$B,Tabella24[[#This Row],[Cartella2]],DATI!$M:$M)*SUMIF(DATI!$B:$B,Tabella24[[#This Row],[Cartella2]],DATI!$I:$I),"") | L1438: =+IFERROR(+Tabella24[[#This Row],[IMPORTO VERSATO]]/SUMIF(DATI!$B:$B,Tabella24[[#This Row],[Cartella2]],DATI!$M:$M)*SUMIF(DATI!$B:$B,Tabella24[[#This Row],[Cartella2]],DATI!$J:$J),"") | M1438: =+IFERROR(+Tabella24[[#This Row],[IMPORTO VERSATO]]/SUMIF(DATI!$B:$B,Tabella24[[#This Row],[Cartella2]],DATI!$M:$M)*SUMIF(DATI!$B:$B,Tabella24[[#This Row],[Cartella2]],DATI!$L:$L),"") | N1438: =+IF(COUNTIF($C$17:C1438,Tabella24[[#This Row],[Cartella2]])=1,"X","") | O1438: =+IFERROR(+Tabella24[[#This Row],[IMPORTO VERSATO]]/SUMIF(DATI!$B:$B,Tabella24[[#This Row],[Cartella2]],DATI!$M:$M)*SUMIF(DATI!$B:$B,Tabella24[[#This Row],[Cartella2]],DATI!$K:$K),"")
C1439: =+IF(Tabella24[[#This Row],[INS CARTELLA]]="",C1438,+VLOOKUP(Tabella24[[#This Row],[INS CARTELLA]],Tabella1[[NUMERO CARTELLA]:[IMPOSTE]],1,0)) -> #N/A | G1439: =+IFERROR(+Tabella24[[#This Row],[IMPORTO VERSATO]]/SUMIF(DATI!B:B,Tabella24[[#This Row],[Cartella2]],DATI!M:M)*SUMIF(DATI!B:B,Tabella24[[#This Row],[Cartella2]],DATI!E:E),"") | H1439: =+IFERROR(+Tabella24[[#This Row],[IMPORTO VERSATO]]/SUMIF(DATI!$B:$B,Tabella24[[#This Row],[Cartella2]],DATI!$M:$M)*SUMIF(DATI!$B:$B,Tabella24[[#This Row],[Cartella2]],DATI!$F:$F),"") | I1439: =+IFERROR(+Tabella24[[#This Row],[IMPORTO VERSATO]]/SUMIF(DATI!$B:$B,Tabella24[[#This Row],[Cartella2]],DATI!$M:$M)*SUMIF(DATI!$B:$B,Tabella24[[#This Row],[Cartella2]],DATI!$G:$G),"") | J1439: =+IFERROR(+Tabella24[[#This Row],[IMPORTO VERSATO]]/SUMIF(DATI!$B:$B,Tabella24[[#This Row],[Cartella2]],DATI!$M:$M)*SUMIF(DATI!$B:$B,Tabella24[[#This Row],[Cartella2]],DATI!$H:$H),"") | K1439: =+IFERROR(+Tabella24[[#This Row],[IMPORTO VERSATO]]/SUMIF(DATI!$B:$B,Tabella24[[#This Row],[Cartella2]],DATI!$M:$M)*SUMIF(DATI!$B:$B,Tabella24[[#This Row],[Cartella2]],DATI!$I:$I),"") | L1439: =+IFERROR(+Tabella24[[#This Row],[IMPORTO VERSATO]]/SUMIF(DATI!$B:$B,Tabella24[[#This Row],[Cartella2]],DATI!$M:$M)*SUMIF(DATI!$B:$B,Tabella24[[#This Row],[Cartella2]],DATI!$J:$J),"") | M1439: =+IFERROR(+Tabella24[[#This Row],[IMPORTO VERSATO]]/SUMIF(DATI!$B:$B,Tabella24[[#This Row],[Cartella2]],DATI!$M:$M)*SUMIF(DATI!$B:$B,Tabella24[[#This Row],[Cartella2]],DATI!$L:$L),"") | N1439: =+IF(COUNTIF($C$17:C1439,Tabella24[[#This Row],[Cartella2]])=1,"X","") | O1439: =+IFERROR(+Tabella24[[#This Row],[IMPORTO VERSATO]]/SUMIF(DATI!$B:$B,Tabella24[[#This Row],[Cartella2]],DATI!$M:$M)*SUMIF(DATI!$B:$B,Tabella24[[#This Row],[Cartella2]],DATI!$K:$K),"")
C1440: =+IF(Tabella24[[#This Row],[INS CARTELLA]]="",C1439,+VLOOKUP(Tabella24[[#This Row],[INS CARTELLA]],Tabella1[[NUMERO CARTELLA]:[IMPOSTE]],1,0)) -> #N/A | G1440: =+IFERROR(+Tabella24[[#This Row],[IMPORTO VERSATO]]/SUMIF(DATI!B:B,Tabella24[[#This Row],[Cartella2]],DATI!M:M)*SUMIF(DATI!B:B,Tabella24[[#This Row],[Cartella2]],DATI!E:E),"") | H1440: =+IFERROR(+Tabella24[[#This Row],[IMPORTO VERSATO]]/SUMIF(DATI!$B:$B,Tabella24[[#This Row],[Cartella2]],DATI!$M:$M)*SUMIF(DATI!$B:$B,Tabella24[[#This Row],[Cartella2]],DATI!$F:$F),"") | I1440: =+IFERROR(+Tabella24[[#This Row],[IMPORTO VERSATO]]/SUMIF(DATI!$B:$B,Tabella24[[#This Row],[Cartella2]],DATI!$M:$M)*SUMIF(DATI!$B:$B,Tabella24[[#This Row],[Cartella2]],DATI!$G:$G),"") | J1440: =+IFERROR(+Tabella24[[#This Row],[IMPORTO VERSATO]]/SUMIF(DATI!$B:$B,Tabella24[[#This Row],[Cartella2]],DATI!$M:$M)*SUMIF(DATI!$B:$B,Tabella24[[#This Row],[Cartella2]],DATI!$H:$H),"") | K1440: =+IFERROR(+Tabella24[[#This Row],[IMPORTO VERSATO]]/SUMIF(DATI!$B:$B,Tabella24[[#This Row],[Cartella2]],DATI!$M:$M)*SUMIF(DATI!$B:$B,Tabella24[[#This Row],[Cartella2]],DATI!$I:$I),"") | L1440: =+IFERROR(+Tabella24[[#This Row],[IMPORTO VERSATO]]/SUMIF(DATI!$B:$B,Tabella24[[#This Row],[Cartella2]],DATI!$M:$M)*SUMIF(DATI!$B:$B,Tabella24[[#This Row],[Cartella2]],DATI!$J:$J),"") | M1440: =+IFERROR(+Tabella24[[#This Row],[IMPORTO VERSATO]]/SUMIF(DATI!$B:$B,Tabella24[[#This Row],[Cartella2]],DATI!$M:$M)*SUMIF(DATI!$B:$B,Tabella24[[#This Row],[Cartella2]],DATI!$L:$L),"") | N1440: =+IF(COUNTIF($C$17:C1440,Tabella24[[#This Row],[Cartella2]])=1,"X","") | O1440: =+IFERROR(+Tabella24[[#This Row],[IMPORTO VERSATO]]/SUMIF(DATI!$B:$B,Tabella24[[#This Row],[Cartella2]],DATI!$M:$M)*SUMIF(DATI!$B:$B,Tabella24[[#This Row],[Cartella2]],DATI!$K:$K),"")
C1441: =+IF(Tabella24[[#This Row],[INS CARTELLA]]="",C1440,+VLOOKUP(Tabella24[[#This Row],[INS CARTELLA]],Tabella1[[NUMERO CARTELLA]:[IMPOSTE]],1,0)) -> #N/A | G1441: =+IFERROR(+Tabella24[[#This Row],[IMPORTO VERSATO]]/SUMIF(DATI!B:B,Tabella24[[#This Row],[Cartella2]],DATI!M:M)*SUMIF(DATI!B:B,Tabella24[[#This Row],[Cartella2]],DATI!E:E),"") | H1441: =+IFERROR(+Tabella24[[#This Row],[IMPORTO VERSATO]]/SUMIF(DATI!$B:$B,Tabella24[[#This Row],[Cartella2]],DATI!$M:$M)*SUMIF(DATI!$B:$B,Tabella24[[#This Row],[Cartella2]],DATI!$F:$F),"") | I1441: =+IFERROR(+Tabella24[[#This Row],[IMPORTO VERSATO]]/SUMIF(DATI!$B:$B,Tabella24[[#This Row],[Cartella2]],DATI!$M:$M)*SUMIF(DATI!$B:$B,Tabella24[[#This Row],[Cartella2]],DATI!$G:$G),"") | J1441: =+IFERROR(+Tabella24[[#This Row],[IMPORTO VERSATO]]/SUMIF(DATI!$B:$B,Tabella24[[#This Row],[Cartella2]],DATI!$M:$M)*SUMIF(DATI!$B:$B,Tabella24[[#This Row],[Cartella2]],DATI!$H:$H),"") | K1441: =+IFERROR(+Tabella24[[#This Row],[IMPORTO VERSATO]]/SUMIF(DATI!$B:$B,Tabella24[[#This Row],[Cartella2]],DATI!$M:$M)*SUMIF(DATI!$B:$B,Tabella24[[#This Row],[Cartella2]],DATI!$I:$I),"") | L1441: =+IFERROR(+Tabella24[[#This Row],[IMPORTO VERSATO]]/SUMIF(DATI!$B:$B,Tabella24[[#This Row],[Cartella2]],DATI!$M:$M)*SUMIF(DATI!$B:$B,Tabella24[[#This Row],[Cartella2]],DATI!$J:$J),"") | M1441: =+IFERROR(+Tabella24[[#This Row],[IMPORTO VERSATO]]/SUMIF(DATI!$B:$B,Tabella24[[#This Row],[Cartella2]],DATI!$M:$M)*SUMIF(DATI!$B:$B,Tabella24[[#This Row],[Cartella2]],DATI!$L:$L),"") | N1441: =+IF(COUNTIF($C$17:C1441,Tabella24[[#This Row],[Cartella2]])=1,"X","") | O1441: =+IFERROR(+Tabella24[[#This Row],[IMPORTO VERSATO]]/SUMIF(DATI!$B:$B,Tabella24[[#This Row],[Cartella2]],DATI!$M:$M)*SUMIF(DATI!$B:$B,Tabella24[[#This Row],[Cartella2]],DATI!$K:$K),"")
C1442: =+IF(Tabella24[[#This Row],[INS CARTELLA]]="",C1441,+VLOOKUP(Tabella24[[#This Row],[INS CARTELLA]],Tabella1[[NUMERO CARTELLA]:[IMPOSTE]],1,0)) -> #N/A | G1442: =+IFERROR(+Tabella24[[#This Row],[IMPORTO VERSATO]]/SUMIF(DATI!B:B,Tabella24[[#This Row],[Cartella2]],DATI!M:M)*SUMIF(DATI!B:B,Tabella24[[#This Row],[Cartella2]],DATI!E:E),"") | H1442: =+IFERROR(+Tabella24[[#This Row],[IMPORTO VERSATO]]/SUMIF(DATI!$B:$B,Tabella24[[#This Row],[Cartella2]],DATI!$M:$M)*SUMIF(DATI!$B:$B,Tabella24[[#This Row],[Cartella2]],DATI!$F:$F),"") | I1442: =+IFERROR(+Tabella24[[#This Row],[IMPORTO VERSATO]]/SUMIF(DATI!$B:$B,Tabella24[[#This Row],[Cartella2]],DATI!$M:$M)*SUMIF(DATI!$B:$B,Tabella24[[#This Row],[Cartella2]],DATI!$G:$G),"") | J1442: =+IFERROR(+Tabella24[[#This Row],[IMPORTO VERSATO]]/SUMIF(DATI!$B:$B,Tabella24[[#This Row],[Cartella2]],DATI!$M:$M)*SUMIF(DATI!$B:$B,Tabella24[[#This Row],[Cartella2]],DATI!$H:$H),"") | K1442: =+IFERROR(+Tabella24[[#This Row],[IMPORTO VERSATO]]/SUMIF(DATI!$B:$B,Tabella24[[#This Row],[Cartella2]],DATI!$M:$M)*SUMIF(DATI!$B:$B,Tabella24[[#This Row],[Cartella2]],DATI!$I:$I),"") | L1442: =+IFERROR(+Tabella24[[#This Row],[IMPORTO VERSATO]]/SUMIF(DATI!$B:$B,Tabella24[[#This Row],[Cartella2]],DATI!$M:$M)*SUMIF(DATI!$B:$B,Tabella24[[#This Row],[Cartella2]],DATI!$J:$J),"") | M1442: =+IFERROR(+Tabella24[[#This Row],[IMPORTO VERSATO]]/SUMIF(DATI!$B:$B,Tabella24[[#This Row],[Cartella2]],DATI!$M:$M)*SUMIF(DATI!$B:$B,Tabella24[[#This Row],[Cartella2]],DATI!$L:$L),"") | N1442: =+IF(COUNTIF($C$17:C1442,Tabella24[[#This Row],[Cartella2]])=1,"X","") | O1442: =+IFERROR(+Tabella24[[#This Row],[IMPORTO VERSATO]]/SUMIF(DATI!$B:$B,Tabella24[[#This Row],[Cartella2]],DATI!$M:$M)*SUMIF(DATI!$B:$B,Tabella24[[#This Row],[Cartella2]],DATI!$K:$K),"")
C1443: =+IF(Tabella24[[#This Row],[INS CARTELLA]]="",C1442,+VLOOKUP(Tabella24[[#This Row],[INS CARTELLA]],Tabella1[[NUMERO CARTELLA]:[IMPOSTE]],1,0)) -> #N/A | G1443: =+IFERROR(+Tabella24[[#This Row],[IMPORTO VERSATO]]/SUMIF(DATI!B:B,Tabella24[[#This Row],[Cartella2]],DATI!M:M)*SUMIF(DATI!B:B,Tabella24[[#This Row],[Cartella2]],DATI!E:E),"") | H1443: =+IFERROR(+Tabella24[[#This Row],[IMPORTO VERSATO]]/SUMIF(DATI!$B:$B,Tabella24[[#This Row],[Cartella2]],DATI!$M:$M)*SUMIF(DATI!$B:$B,Tabella24[[#This Row],[Cartella2]],DATI!$F:$F),"") | I1443: =+IFERROR(+Tabella24[[#This Row],[IMPORTO VERSATO]]/SUMIF(DATI!$B:$B,Tabella24[[#This Row],[Cartella2]],DATI!$M:$M)*SUMIF(DATI!$B:$B,Tabella24[[#This Row],[Cartella2]],DATI!$G:$G),"") | J1443: =+IFERROR(+Tabella24[[#This Row],[IMPORTO VERSATO]]/SUMIF(DATI!$B:$B,Tabella24[[#This Row],[Cartella2]],DATI!$M:$M)*SUMIF(DATI!$B:$B,Tabella24[[#This Row],[Cartella2]],DATI!$H:$H),"") | K1443: =+IFERROR(+Tabella24[[#This Row],[IMPORTO VERSATO]]/SUMIF(DATI!$B:$B,Tabella24[[#This Row],[Cartella2]],DATI!$M:$M)*SUMIF(DATI!$B:$B,Tabella24[[#This Row],[Cartella2]],DATI!$I:$I),"") | L1443: =+IFERROR(+Tabella24[[#This Row],[IMPORTO VERSATO]]/SUMIF(DATI!$B:$B,Tabella24[[#This Row],[Cartella2]],DATI!$M:$M)*SUMIF(DATI!$B:$B,Tabella24[[#This Row],[Cartella2]],DATI!$J:$J),"") | M1443: =+IFERROR(+Tabella24[[#This Row],[IMPORTO VERSATO]]/SUMIF(DATI!$B:$B,Tabella24[[#This Row],[Cartella2]],DATI!$M:$M)*SUMIF(DATI!$B:$B,Tabella24[[#This Row],[Cartella2]],DATI!$L:$L),"") | N1443: =+IF(COUNTIF($C$17:C1443,Tabella24[[#This Row],[Cartella2]])=1,"X","") | O1443: =+IFERROR(+Tabella24[[#This Row],[IMPORTO VERSATO]]/SUMIF(DATI!$B:$B,Tabella24[[#This Row],[Cartella2]],DATI!$M:$M)*SUMIF(DATI!$B:$B,Tabella24[[#This Row],[Cartella2]],DATI!$K:$K),"")
C1444: =+IF(Tabella24[[#This Row],[INS CARTELLA]]="",C1443,+VLOOKUP(Tabella24[[#This Row],[INS CARTELLA]],Tabella1[[NUMERO CARTELLA]:[IMPOSTE]],1,0)) -> #N/A | G1444: =+IFERROR(+Tabella24[[#This Row],[IMPORTO VERSATO]]/SUMIF(DATI!B:B,Tabella24[[#This Row],[Cartella2]],DATI!M:M)*SUMIF(DATI!B:B,Tabella24[[#This Row],[Cartella2]],DATI!E:E),"") | H1444: =+IFERROR(+Tabella24[[#This Row],[IMPORTO VERSATO]]/SUMIF(DATI!$B:$B,Tabella24[[#This Row],[Cartella2]],DATI!$M:$M)*SUMIF(DATI!$B:$B,Tabella24[[#This Row],[Cartella2]],DATI!$F:$F),"") | I1444: =+IFERROR(+Tabella24[[#This Row],[IMPORTO VERSATO]]/SUMIF(DATI!$B:$B,Tabella24[[#This Row],[Cartella2]],DATI!$M:$M)*SUMIF(DATI!$B:$B,Tabella24[[#This Row],[Cartella2]],DATI!$G:$G),"") | J1444: =+IFERROR(+Tabella24[[#This Row],[IMPORTO VERSATO]]/SUMIF(DATI!$B:$B,Tabella24[[#This Row],[Cartella2]],DATI!$M:$M)*SUMIF(DATI!$B:$B,Tabella24[[#This Row],[Cartella2]],DATI!$H:$H),"") | K1444: =+IFERROR(+Tabella24[[#This Row],[IMPORTO VERSATO]]/SUMIF(DATI!$B:$B,Tabella24[[#This Row],[Cartella2]],DATI!$M:$M)*SUMIF(DATI!$B:$B,Tabella24[[#This Row],[Cartella2]],DATI!$I:$I),"") | L1444: =+IFERROR(+Tabella24[[#This Row],[IMPORTO VERSATO]]/SUMIF(DATI!$B:$B,Tabella24[[#This Row],[Cartella2]],DATI!$M:$M)*SUMIF(DATI!$B:$B,Tabella24[[#This Row],[Cartella2]],DATI!$J:$J),"") | M1444: =+IFERROR(+Tabella24[[#This Row],[IMPORTO VERSATO]]/SUMIF(DATI!$B:$B,Tabella24[[#This Row],[Cartella2]],DATI!$M:$M)*SUMIF(DATI!$B:$B,Tabella24[[#This Row],[Cartella2]],DATI!$L:$L),"") | N1444: =+IF(COUNTIF($C$17:C1444,Tabella24[[#This Row],[Cartella2]])=1,"X","") | O1444: =+IFERROR(+Tabella24[[#This Row],[IMPORTO VERSATO]]/SUMIF(DATI!$B:$B,Tabella24[[#This Row],[Cartella2]],DATI!$M:$M)*SUMIF(DATI!$B:$B,Tabella24[[#This Row],[Cartella2]],DATI!$K:$K),"")
C1445: =+IF(Tabella24[[#This Row],[INS CARTELLA]]="",C1444,+VLOOKUP(Tabella24[[#This Row],[INS CARTELLA]],Tabella1[[NUMERO CARTELLA]:[IMPOSTE]],1,0)) -> #N/A | G1445: =+IFERROR(+Tabella24[[#This Row],[IMPORTO VERSATO]]/SUMIF(DATI!B:B,Tabella24[[#This Row],[Cartella2]],DATI!M:M)*SUMIF(DATI!B:B,Tabella24[[#This Row],[Cartella2]],DATI!E:E),"") | H1445: =+IFERROR(+Tabella24[[#This Row],[IMPORTO VERSATO]]/SUMIF(DATI!$B:$B,Tabella24[[#This Row],[Cartella2]],DATI!$M:$M)*SUMIF(DATI!$B:$B,Tabella24[[#This Row],[Cartella2]],DATI!$F:$F),"") | I1445: =+IFERROR(+Tabella24[[#This Row],[IMPORTO VERSATO]]/SUMIF(DATI!$B:$B,Tabella24[[#This Row],[Cartella2]],DATI!$M:$M)*SUMIF(DATI!$B:$B,Tabella24[[#This Row],[Cartella2]],DATI!$G:$G),"") | J1445: =+IFERROR(+Tabella24[[#This Row],[IMPORTO VERSATO]]/SUMIF(DATI!$B:$B,Tabella24[[#This Row],[Cartella2]],DATI!$M:$M)*SUMIF(DATI!$B:$B,Tabella24[[#This Row],[Cartella2]],DATI!$H:$H),"") | K1445: =+IFERROR(+Tabella24[[#This Row],[IMPORTO VERSATO]]/SUMIF(DATI!$B:$B,Tabella24[[#This Row],[Cartella2]],DATI!$M:$M)*SUMIF(DATI!$B:$B,Tabella24[[#This Row],[Cartella2]],DATI!$I:$I),"") | L1445: =+IFERROR(+Tabella24[[#This Row],[IMPORTO VERSATO]]/SUMIF(DATI!$B:$B,Tabella24[[#This Row],[Cartella2]],DATI!$M:$M)*SUMIF(DATI!$B:$B,Tabella24[[#This Row],[Cartella2]],DATI!$J:$J),"") | M1445: =+IFERROR(+Tabella24[[#This Row],[IMPORTO VERSATO]]/SUMIF(DATI!$B:$B,Tabella24[[#This Row],[Cartella2]],DATI!$M:$M)*SUMIF(DATI!$B:$B,Tabella24[[#This Row],[Cartella2]],DATI!$L:$L),"") | N1445: =+IF(COUNTIF($C$17:C1445,Tabella24[[#This Row],[Cartella2]])=1,"X","") | O1445: =+IFERROR(+Tabella24[[#This Row],[IMPORTO VERSATO]]/SUMIF(DATI!$B:$B,Tabella24[[#This Row],[Cartella2]],DATI!$M:$M)*SUMIF(DATI!$B:$B,Tabella24[[#This Row],[Cartella2]],DATI!$K:$K),"")
C1446: =+IF(Tabella24[[#This Row],[INS CARTELLA]]="",C1445,+VLOOKUP(Tabella24[[#This Row],[INS CARTELLA]],Tabella1[[NUMERO CARTELLA]:[IMPOSTE]],1,0)) -> #N/A | G1446: =+IFERROR(+Tabella24[[#This Row],[IMPORTO VERSATO]]/SUMIF(DATI!B:B,Tabella24[[#This Row],[Cartella2]],DATI!M:M)*SUMIF(DATI!B:B,Tabella24[[#This Row],[Cartella2]],DATI!E:E),"") | H1446: =+IFERROR(+Tabella24[[#This Row],[IMPORTO VERSATO]]/SUMIF(DATI!$B:$B,Tabella24[[#This Row],[Cartella2]],DATI!$M:$M)*SUMIF(DATI!$B:$B,Tabella24[[#This Row],[Cartella2]],DATI!$F:$F),"") | I1446: =+IFERROR(+Tabella24[[#This Row],[IMPORTO VERSATO]]/SUMIF(DATI!$B:$B,Tabella24[[#This Row],[Cartella2]],DATI!$M:$M)*SUMIF(DATI!$B:$B,Tabella24[[#This Row],[Cartella2]],DATI!$G:$G),"") | J1446: =+IFERROR(+Tabella24[[#This Row],[IMPORTO VERSATO]]/SUMIF(DATI!$B:$B,Tabella24[[#This Row],[Cartella2]],DATI!$M:$M)*SUMIF(DATI!$B:$B,Tabella24[[#This Row],[Cartella2]],DATI!$H:$H),"") | K1446: =+IFERROR(+Tabella24[[#This Row],[IMPORTO VERSATO]]/SUMIF(DATI!$B:$B,Tabella24[[#This Row],[Cartella2]],DATI!$M:$M)*SUMIF(DATI!$B:$B,Tabella24[[#This Row],[Cartella2]],DATI!$I:$I),"") | L1446: =+IFERROR(+Tabella24[[#This Row],[IMPORTO VERSATO]]/SUMIF(DATI!$B:$B,Tabella24[[#This Row],[Cartella2]],DATI!$M:$M)*SUMIF(DATI!$B:$B,Tabella24[[#This Row],[Cartella2]],DATI!$J:$J),"") | M1446: =+IFERROR(+Tabella24[[#This Row],[IMPORTO VERSATO]]/SUMIF(DATI!$B:$B,Tabella24[[#This Row],[Cartella2]],DATI!$M:$M)*SUMIF(DATI!$B:$B,Tabella24[[#This Row],[Cartella2]],DATI!$L:$L),"") | N1446: =+IF(COUNTIF($C$17:C1446,Tabella24[[#This Row],[Cartella2]])=1,"X","") | O1446: =+IFERROR(+Tabella24[[#This Row],[IMPORTO VERSATO]]/SUMIF(DATI!$B:$B,Tabella24[[#This Row],[Cartella2]],DATI!$M:$M)*SUMIF(DATI!$B:$B,Tabella24[[#This Row],[Cartella2]],DATI!$K:$K),"")
C1447: =+IF(Tabella24[[#This Row],[INS CARTELLA]]="",C1446,+VLOOKUP(Tabella24[[#This Row],[INS CARTELLA]],Tabella1[[NUMERO CARTELLA]:[IMPOSTE]],1,0)) -> #N/A | G1447: =+IFERROR(+Tabella24[[#This Row],[IMPORTO VERSATO]]/SUMIF(DATI!B:B,Tabella24[[#This Row],[Cartella2]],DATI!M:M)*SUMIF(DATI!B:B,Tabella24[[#This Row],[Cartella2]],DATI!E:E),"") | H1447: =+IFERROR(+Tabella24[[#This Row],[IMPORTO VERSATO]]/SUMIF(DATI!$B:$B,Tabella24[[#This Row],[Cartella2]],DATI!$M:$M)*SUMIF(DATI!$B:$B,Tabella24[[#This Row],[Cartella2]],DATI!$F:$F),"") | I1447: =+IFERROR(+Tabella24[[#This Row],[IMPORTO VERSATO]]/SUMIF(DATI!$B:$B,Tabella24[[#This Row],[Cartella2]],DATI!$M:$M)*SUMIF(DATI!$B:$B,Tabella24[[#This Row],[Cartella2]],DATI!$G:$G),"") | J1447: =+IFERROR(+Tabella24[[#This Row],[IMPORTO VERSATO]]/SUMIF(DATI!$B:$B,Tabella24[[#This Row],[Cartella2]],DATI!$M:$M)*SUMIF(DATI!$B:$B,Tabella24[[#This Row],[Cartella2]],DATI!$H:$H),"") | K1447: =+IFERROR(+Tabella24[[#This Row],[IMPORTO VERSATO]]/SUMIF(DATI!$B:$B,Tabella24[[#This Row],[Cartella2]],DATI!$M:$M)*SUMIF(DATI!$B:$B,Tabella24[[#This Row],[Cartella2]],DATI!$I:$I),"") | L1447: =+IFERROR(+Tabella24[[#This Row],[IMPORTO VERSATO]]/SUMIF(DATI!$B:$B,Tabella24[[#This Row],[Cartella2]],DATI!$M:$M)*SUMIF(DATI!$B:$B,Tabella24[[#This Row],[Cartella2]],DATI!$J:$J),"") | M1447: =+IFERROR(+Tabella24[[#This Row],[IMPORTO VERSATO]]/SUMIF(DATI!$B:$B,Tabella24[[#This Row],[Cartella2]],DATI!$M:$M)*SUMIF(DATI!$B:$B,Tabella24[[#This Row],[Cartella2]],DATI!$L:$L),"") | N1447: =+IF(COUNTIF($C$17:C1447,Tabella24[[#This Row],[Cartella2]])=1,"X","") | O1447: =+IFERROR(+Tabella24[[#This Row],[IMPORTO VERSATO]]/SUMIF(DATI!$B:$B,Tabella24[[#This Row],[Cartella2]],DATI!$M:$M)*SUMIF(DATI!$B:$B,Tabella24[[#This Row],[Cartella2]],DATI!$K:$K),"")
C1448: =+IF(Tabella24[[#This Row],[INS CARTELLA]]="",C1447,+VLOOKUP(Tabella24[[#This Row],[INS CARTELLA]],Tabella1[[NUMERO CARTELLA]:[IMPOSTE]],1,0)) -> #N/A | G1448: =+IFERROR(+Tabella24[[#This Row],[IMPORTO VERSATO]]/SUMIF(DATI!B:B,Tabella24[[#This Row],[Cartella2]],DATI!M:M)*SUMIF(DATI!B:B,Tabella24[[#This Row],[Cartella2]],DATI!E:E),"") | H1448: =+IFERROR(+Tabella24[[#This Row],[IMPORTO VERSATO]]/SUMIF(DATI!$B:$B,Tabella24[[#This Row],[Cartella2]],DATI!$M:$M)*SUMIF(DATI!$B:$B,Tabella24[[#This Row],[Cartella2]],DATI!$F:$F),"") | I1448: =+IFERROR(+Tabella24[[#This Row],[IMPORTO VERSATO]]/SUMIF(DATI!$B:$B,Tabella24[[#This Row],[Cartella2]],DATI!$M:$M)*SUMIF(DATI!$B:$B,Tabella24[[#This Row],[Cartella2]],DATI!$G:$G),"") | J1448: =+IFERROR(+Tabella24[[#This Row],[IMPORTO VERSATO]]/SUMIF(DATI!$B:$B,Tabella24[[#This Row],[Cartella2]],DATI!$M:$M)*SUMIF(DATI!$B:$B,Tabella24[[#This Row],[Cartella2]],DATI!$H:$H),"") | K1448: =+IFERROR(+Tabella24[[#This Row],[IMPORTO VERSATO]]/SUMIF(DATI!$B:$B,Tabella24[[#This Row],[Cartella2]],DATI!$M:$M)*SUMIF(DATI!$B:$B,Tabella24[[#This Row],[Cartella2]],DATI!$I:$I),"") | L1448: =+IFERROR(+Tabella24[[#This Row],[IMPORTO VERSATO]]/SUMIF(DATI!$B:$B,Tabella24[[#This Row],[Cartella2]],DATI!$M:$M)*SUMIF(DATI!$B:$B,Tabella24[[#This Row],[Cartella2]],DATI!$J:$J),"") | M1448: =+IFERROR(+Tabella24[[#This Row],[IMPORTO VERSATO]]/SUMIF(DATI!$B:$B,Tabella24[[#This Row],[Cartella2]],DATI!$M:$M)*SUMIF(DATI!$B:$B,Tabella24[[#This Row],[Cartella2]],DATI!$L:$L),"") | N1448: =+IF(COUNTIF($C$17:C1448,Tabella24[[#This Row],[Cartella2]])=1,"X","") | O1448: =+IFERROR(+Tabella24[[#This Row],[IMPORTO VERSATO]]/SUMIF(DATI!$B:$B,Tabella24[[#This Row],[Cartella2]],DATI!$M:$M)*SUMIF(DATI!$B:$B,Tabella24[[#This Row],[Cartella2]],DATI!$K:$K),"")
C1449: =+IF(Tabella24[[#This Row],[INS CARTELLA]]="",C1448,+VLOOKUP(Tabella24[[#This Row],[INS CARTELLA]],Tabella1[[NUMERO CARTELLA]:[IMPOSTE]],1,0)) -> #N/A | G1449: =+IFERROR(+Tabella24[[#This Row],[IMPORTO VERSATO]]/SUMIF(DATI!B:B,Tabella24[[#This Row],[Cartella2]],DATI!M:M)*SUMIF(DATI!B:B,Tabella24[[#This Row],[Cartella2]],DATI!E:E),"") | H1449: =+IFERROR(+Tabella24[[#This Row],[IMPORTO VERSATO]]/SUMIF(DATI!$B:$B,Tabella24[[#This Row],[Cartella2]],DATI!$M:$M)*SUMIF(DATI!$B:$B,Tabella24[[#This Row],[Cartella2]],DATI!$F:$F),"") | I1449: =+IFERROR(+Tabella24[[#This Row],[IMPORTO VERSATO]]/SUMIF(DATI!$B:$B,Tabella24[[#This Row],[Cartella2]],DATI!$M:$M)*SUMIF(DATI!$B:$B,Tabella24[[#This Row],[Cartella2]],DATI!$G:$G),"") | J1449: =+IFERROR(+Tabella24[[#This Row],[IMPORTO VERSATO]]/SUMIF(DATI!$B:$B,Tabella24[[#This Row],[Cartella2]],DATI!$M:$M)*SUMIF(DATI!$B:$B,Tabella24[[#This Row],[Cartella2]],DATI!$H:$H),"") | K1449: =+IFERROR(+Tabella24[[#This Row],[IMPORTO VERSATO]]/SUMIF(DATI!$B:$B,Tabella24[[#This Row],[Cartella2]],DATI!$M:$M)*SUMIF(DATI!$B:$B,Tabella24[[#This Row],[Cartella2]],DATI!$I:$I),"") | L1449: =+IFERROR(+Tabella24[[#This Row],[IMPORTO VERSATO]]/SUMIF(DATI!$B:$B,Tabella24[[#This Row],[Cartella2]],DATI!$M:$M)*SUMIF(DATI!$B:$B,Tabella24[[#This Row],[Cartella2]],DATI!$J:$J),"") | M1449: =+IFERROR(+Tabella24[[#This Row],[IMPORTO VERSATO]]/SUMIF(DATI!$B:$B,Tabella24[[#This Row],[Cartella2]],DATI!$M:$M)*SUMIF(DATI!$B:$B,Tabella24[[#This Row],[Cartella2]],DATI!$L:$L),"") | N1449: =+IF(COUNTIF($C$17:C1449,Tabella24[[#This Row],[Cartella2]])=1,"X","") | O1449: =+IFERROR(+Tabella24[[#This Row],[IMPORTO VERSATO]]/SUMIF(DATI!$B:$B,Tabella24[[#This Row],[Cartella2]],DATI!$M:$M)*SUMIF(DATI!$B:$B,Tabella24[[#This Row],[Cartella2]],DATI!$K:$K),"")
... C1502: =+IF(Tabella24[[#This Row],[INS CARTELLA]]="",C1501,+VLOOKUP(Tabella24[[#This Row],[INS CARTELLA]],Tabella1[[NUMERO CARTELLA]:[IMPOSTE]],1,0)) -> #N/A | G1502: =+IFERROR(+Tabella24[[#This Row],[IMPORTO VERSATO]]/SUMIF(DATI!B:B,Tabella24[[#This Row],[Cartella2]],DATI!M:M)*SUMIF(DATI!B:B,Tabella24[[#This Row],[Cartella2]],DATI!E:E),"") | H1502: =+IFERROR(+Tabella24[[#This Row],[IMPORTO VERSATO]]/SUMIF(DATI!$B:$B,Tabella24[[#This Row],[Cartella2]],DATI!$M:$M)*SUMIF(DATI!$B:$B,Tabella24[[#This Row],[Cartella2]],DATI!$F:$F),"") | I1502: =+IFERROR(+Tabella24[[#This Row],[IMPORTO VERSATO]]/SUMIF(DATI!$B:$B,Tabella24[[#This Row],[Cartella2]],DATI!$M:$M)*SUMIF(DATI!$B:$B,Tabella24[[#This Row],[Cartella2]],DATI!$G:$G),"") | J1502: =+IFERROR(+Tabella24[[#This Row],[IMPORTO VERSATO]]/SUMIF(DATI!$B:$B,Tabella24[[#This Row],[Cartella2]],DATI!$M:$M)*SUMIF(DATI!$B:$B,Tabella24[[#This Row],[Cartella2]],DATI!$H:$H),"") | K1502: =+IFERROR(+Tabella24[[#This Row],[IMPORTO VERSATO]]/SUMIF(DATI!$B:$B,Tabella24[[#This Row],[Cartella2]],DATI!$M:$M)*SUMIF(DATI!$B:$B,Tabella24[[#This Row],[Cartella2]],DATI!$I:$I),"") | L1502: =+IFERROR(+Tabella24[[#This Row],[IMPORTO VERSATO]]/SUMIF(DATI!$B:$B,Tabella24[[#This Row],[Cartella2]],DATI!$M:$M)*SUMIF(DATI!$B:$B,Tabella24[[#This Row],[Cartella2]],DATI!$J:$J),"") | M1502: =+IFERROR(+Tabella24[[#This Row],[IMPORTO VERSATO]]/SUMIF(DATI!$B:$B,Tabella24[[#This Row],[Cartella2]],DATI!$M:$M)*SUMIF(DATI!$B:$B,Tabella24[[#This Row],[Cartella2]],DATI!$L:$L),"") | N1502: =+IF(COUNTIF($C$17:C1502,Tabella24[[#This Row],[Cartella2]])=1,"X","") | O1502: =+IFERROR(+Tabella24[[#This Row],[IMPORTO VERSATO]]/SUMIF(DATI!$B:$B,Tabella24[[#This Row],[Cartella2]],DATI!$M:$M)*SUMIF(DATI!$B:$B,Tabella24[[#This Row],[Cartella2]],DATI!$K:$K),"")

Sheet RATEAZIONI (dati liberi)
B12: RATEAZIONE CARTELLE
B16: Ins Cartella | C16: Cartella2 | D16: N° RATA | E16: Data versamento | F16: Capitale Versato | G16: Quota imposta | H16: Quota Sanzioni | I16: Quota Int. Mora | J16: Quota Int. di dilazione | K16: Quota Interessi per rit. Iscr. a ruolo | L16: Oneri di riscossione (aggio esattoriale) | M16: Spese per procedure esecutive | N16: X | O16: Spese di Notifica
C17: =+IF(Tabella245[[#This Row],[Ins Cartella]]="",C16,+VLOOKUP(Tabella245[[#This Row],[Ins Cartella]],Tabella1[[NUMERO CARTELLA]:[IMPOSTE]],1,0)) -> Cartella2
C18: =+IF(Tabella245[[#This Row],[Ins Cartella]]="",C17,+VLOOKUP(Tabella245[[#This Row],[Ins Cartella]],Tabella1[[NUMERO CARTELLA]:[IMPOSTE]],1,0)) -> Cartella2
C19: =+IF(Tabella245[[#This Row],[Ins Cartella]]="",C18,+VLOOKUP(Tabella245[[#This Row],[Ins Cartella]],Tabella1[[NUMERO CARTELLA]:[IMPOSTE]],1,0)) -> Cartella2
C20: =+IF(Tabella245[[#This Row],[Ins Cartella]]="",C19,+VLOOKUP(Tabella245[[#This Row],[Ins Cartella]],Tabella1[[NUMERO CARTELLA]:[IMPOSTE]],1,0)) -> Cartella2
C21: =+IF(Tabella245[[#This Row],[Ins Cartella]]="",C20,+VLOOKUP(Tabella245[[#This Row],[Ins Cartella]],Tabella1[[NUMERO CARTELLA]:[IMPOSTE]],1,0)) -> Cartella2
C22: =+IF(Tabella245[[#This Row],[Ins Cartella]]="",C21,+VLOOKUP(Tabella245[[#This Row],[Ins Cartella]],Tabella1[[NUMERO CARTELLA]:[IMPOSTE]],1,0)) -> Cartella2
C23: =+IF(Tabella245[[#This Row],[Ins Cartella]]="",C22,+VLOOKUP(Tabella245[[#This Row],[Ins Cartella]],Tabella1[[NUMERO CARTELLA]:[IMPOSTE]],1,0)) -> Cartella2
C24: =+IF(Tabella245[[#This Row],[Ins Cartella]]="",C23,+VLOOKUP(Tabella245[[#This Row],[Ins Cartella]],Tabella1[[NUMERO CARTELLA]:[IMPOSTE]],1,0)) -> Cartella2
C25: =+IF(Tabella245[[#This Row],[Ins Cartella]]="",C24,+VLOOKUP(Tabella245[[#This Row],[Ins Cartella]],Tabella1[[NUMERO CARTELLA]:[IMPOSTE]],1,0)) -> Cartella2
C26: =+IF(Tabella245[[#This Row],[Ins Cartella]]="",C25,+VLOOKUP(Tabella245[[#This Row],[Ins Cartella]],Tabella1[[NUMERO CARTELLA]:[IMPOSTE]],1,0)) -> Cartella2
C27: =+IF(Tabella245[[#This Row],[Ins Cartella]]="",C26,+VLOOKUP(Tabella245[[#This Row],[Ins Cartella]],Tabella1[[NUMERO CARTELLA]:[IMPOSTE]],1,0)) -> Cartella2
C28: =+IF(Tabella245[[#This Row],[Ins Cartella]]="",C27,+VLOOKUP(Tabella245[[#This Row],[Ins Cartella]],Tabella1[[NUMERO CARTELLA]:[IMPOSTE]],1,0)) -> Cartella2
... C1502: =+IF(Tabella245[[#This Row],[Ins Cartella]]="",C1501,+VLOOKUP(Tabella245[[#This Row],[Ins Cartella]],Tabella1[[NUMERO CARTELLA]:[IMPOSTE]],1,0)) -> Cartella2

Sheet RISULTATI
B10: RESIDUO DA VERSARE | D10: =+K22+K37+K52+K67+K82+K97+K112+K127+K142+K157+K172+K187 -> 11918.8
B12: TOTALE DA PAGARE CON ROTTAMAZIONE QUINQUIES | D12: =+K24+K39+K54+K69+K84+K99+K114+K129+K144+K159+K174+K189 -> 7899.8
B14: RISPARMIO | D14: =+D10-ROTP -> 4019 | E14: =+D14/D10 -> 0.33719838
A16: 0 | B16: N. Cartella | C16: Data Notifica | D16: Data Pagamento | E16: Aggio | M16: =SUM(M24:M189) -> 0 | N16: =SUM(N24:N189) -> 7899.8 | O16: =+M16+N16-D12 -> 0
A17: =+MATCH("X",OFFSET(RATEAZIONI!$N$16:$N$1438,RISULTATI!A16,0*da),0) -> 1 | B17: =+IF(DATI!$B$17="","",DATI!$B$17) -> 097 2023 000123456789 | C17: =+IFERROR(+VLOOKUP(B17,DATI!B:N,13,0),"") -> 45110 | D17: 46234 | E17: =+IFERROR( IF(DATI!D17>TABELLE!C4,"", (+INDEX(TABELLE!$J$11:$M$13,MATCH(F17,TABELLE!$J$11:$J$13,1),MATCH(C17,TABELLE!$J$11:$M$11,1)))),0) | F17: =+D17-C17 -> 1124 | M17: ANTE 2017 | N17: 2017
C18: =+IFERROR(+VLOOKUP(B17,DATI!B:P,15,0),"") -> 2
C19: Imposte al ruolo | D19: Sanzioni cartella | E19: Interessi di mora | F19: Interessi di dilazione | G19: Interessi per ritardata iscrizione a ruolo | H19: Aggio esattoriale (oneri di riscossione) | I19: Spese di Notifica | J19: Spese per proced. esecutive | K19: TOTALE
B20: TOTALE CARTELLA | C20: =+SUMIF(DATI!$B:$B,RISULTATI!$B$17,DATI!E:E) -> 7890 | D20: =+SUMIF(DATI!$B:$B,RISULTATI!$B$17,DATI!F:F) -> 2367 | E20: =+SUMIF(DATI!$B:$B,RISULTATI!$B$17,DATI!G:G) -> 421 | F20: =+SUMIF(DATI!$B:$B,RISULTATI!$B$17,DATI!H:H) -> 278 | G20: =+SUMIF(DATI!$B:$B,RISULTATI!$B$17,DATI!I:I) -> 139 | H20: =+SUMIF(DATI!$B:$B,RISULTATI!$B$17,DATI!J:J) -> 814 | I20: =+SUMIF(DATI!$B:$B,RISULTATI!$B$17,DATI!K:K) -> 9.8 | J20: =+SUMIF(DATI!$B:$B,RISULTATI!$B$17,DATI!L:L) -> 0
B21: IMPORTO GIA' VERSATO | C21: =+IF(-SUMIF(RATEAZIONI!$C:$C,RISULTATI!$B$17,RATEAZIONI!G:G)<>0,-SUMIF(RATEAZIONI!$C:$C,RISULTATI!$B$17,RATEAZIONI!G:G),-SUMIF('RATEAZIONI (dati liberi)'!$C:$C,RISULTATI!$B$17,'RATEAZIONI (dati liberi)'!G:G)) -> 0 | D21: =+IF(-SUMIF(RATEAZIONI!$C:$C,RISULTATI!$B$17,RATEAZIONI!H:H)<>0,-SUMIF(RATEAZIONI!$C:$C,RISULTATI!$B$17,RATEAZIONI!H:H),-SUMIF('RATEAZIONI (dati liberi)'!$C:$C,RISULTATI!$B$17,'RATEAZIONI (dati liberi)'!H:H)) -> 0 | E21: =+IF(-SUMIF(RATEAZIONI!$C:$C,RISULTATI!$B$17,RATEAZIONI!I:I)<>0,-SUMIF(RATEAZIONI!$C:$C,RISULTATI!$B$17,RATEAZIONI!I:I),-SUMIF('RATEAZIONI (dati liberi)'!$C:$C,RISULTATI!$B$17,'RATEAZIONI (dati liberi)'!I:I)) -> 0 | F21: =+IF(-SUMIF(RATEAZIONI!$C:$C,RISULTATI!$B$17,RATEAZIONI!J:J)<>0,-SUMIF(RATEAZIONI!$C:$C,RISULTATI!$B$17,RATEAZIONI!J:J),-SUMIF('RATEAZIONI (dati liberi)'!$C:$C,RISULTATI!$B$17,'RATEAZIONI (dati liberi)'!J:J)) -> 0 | G21: =+IF(-SUMIF(RATEAZIONI!$C:$C,RISULTATI!$B$17,RATEAZIONI!K:K)<>0,-SUMIF(RATEAZIONI!$C:$C,RISULTATI!$B$17,RATEAZIONI!K:K),-SUMIF('RATEAZIONI (dati liberi)'!$C:$C,RISULTATI!$B$17,'RATEAZIONI (dati liberi)'!K:K)) -> 0 | H21: =+IF(-SUMIF(RATEAZIONI!$C:$C,RISULTATI!$B$17,RATEAZIONI!L:L)<>0,-SUMIF(RATEAZIONI!$C:$C,RISULTATI!$B$17,RATEAZIONI!L:L),-SUMIF('RATEAZIONI (dati liberi)'!$C:$C,RISULTATI!$B$17,'RATEAZIONI (dati liberi)'!L:L)) -> 0 | I21: =+IF(-SUMIF(RATEAZIONI!$C:$C,RISULTATI!$B$17,RATEAZIONI!O:O)<>0,-SUMIF(RATEAZIONI!$C:$C,RISULTATI!$B$17,RATEAZIONI!O:O),-SUMIF('RATEAZIONI (dati liberi)'!$C:$C,RISULTATI!$B$17,'RATEAZIONI (dati liberi)'!O:O)) -> 0 | J21: =+IF( -SUMIF(RATEAZIONI!$C:$C,RISULTATI!$B$17,RATEAZIONI!M:M)<>0,-SUMIF(RATEAZIONI!$C:$C,RISULTATI!$B$17,RATEAZIONI!M:M),-SUMIF('RATEAZIONI (dati liberi)'!$C:$C,RISULTATI!$B$17,'RATEAZIONI (dati liberi)'!M:M)) -> 0
B22: RESIDUO DA VERSARE | C22: =SUM(C20:C21) -> 7890 | D22: =+D20+D21 -> 2367 | E22: =+E20+E21 -> 421 | F22: =+F20+F21 -> 278 | G22: =+G20+G21 -> 139 | H22: =MAX(0,+H20+H21) -> 814 | I22: =+I20+I21 -> 9.8 | J22: =+J20+J21 -> 0 | K22: =SUM(C22:J22) -> 11918.8
B23: IMPORTO ROTTAMABILE | D23: =-D22 -> -2367 | E23: =-E22 -> -421 | F23: =-F22 -> -278 | G23: =-G22 -> -139 | H23: =-H22 -> -814
B24: RESIDUO CON ROTTAMAZIONE | C24: =+SUM(C22:C23) -> 7890 | D24: =+SUM(D22:D23) -> 0 | E24: =+SUM(E22:E23) -> 0 | F24: =+SUM(F22:F23) -> 0 | G24: =+SUM(G22:G23) -> 0 | H24: =+SUM(H22:H23) -> 0 | I24: =+SUM(I22:I23) -> 9.8 | J24: =+SUM(J22:J23) -> 0 | K24: =SUM(C24:J24) -> 7899.8 | M24: =+IF(C18=2,0,K24) -> 0 | N24: =+K24 -> 7899.8
C26: RISPARMIO CON ROTTAMAZIONE | E26: =+K22-K24 -> 4019
C27: RISPARMIO IN % | E27: =+IFERROR(+E26/K22,0) -> 0.33719838
B31: N. Cartella | C31: Data Notifica | D31: Data Pagamento | E31: Aggio
A32: =+MATCH("X",OFFSET(RATEAZIONI!$N$17:$N$1438,RISULTATI!A17,0*da),0)+A17 -> #N/A | B32: =+IF(DATI!$B$18="","",DATI!$B$18) | C32: =+IFERROR(+VLOOKUP(B32,DATI!B:N,13,0),"") | D32: 46234 | E32: =+IFERROR( IF(DATI!D18>TABELLE!C4,"", (+INDEX(TABELLE!$J$11:$M$13,MATCH(F32,TABELLE!$J$11:$J$13,1),MATCH(C32,TABELLE!$J$11:$M$11,1)))),0) -> 0 | F32: =+D32-C32 -> #VALUE!
C33: =+IFERROR(+VLOOKUP(B32,DATI!B:P,15,0),"")
C34: Imposte al ruolo | D34: Sanzioni cartella | E34: Interessi di mora | F34: Interessi di dilazione | G34: Interessi per ritardata iscrizione a ruolo | H34: Aggio esattoriale (oneri di riscossione) | I34: Spese di Notifica | J34: Spese per proced. esecutive | K34: TOTALE
B35: TOTALE CARTELLA | C35: =+SUMIF(DATI!$B:$B,RISULTATI!$B$32,DATI!E:E) -> 0 | D35: =+SUMIF(DATI!$B:$B,RISULTATI!$B$32,DATI!F:F) -> 0 | E35: =+SUMIF(DATI!$B:$B,RISULTATI!$B$32,DATI!G:G) -> 0 | F35: =+SUMIF(DATI!$B:$B,RISULTATI!$B$32,DATI!H:H) -> 0 | G35: =+SUMIF(DATI!$B:$B,RISULTATI!$B$32,DATI!I:I) -> 0 | H35: =+SUMIF(DATI!$B:$B,RISULTATI!$B$32,DATI!J:J) -> 0 | I35: =+SUMIF(DATI!$B:$B,RISULTATI!$B$32,DATI!K:K) -> 0 | J35: =+SUMIF(DATI!$B:$B,RISULTATI!$B$32,DATI!L:L) -> 0
B36: IMPORTO GIA' VERSATO | C36: =+IF(-SUMIF(RATEAZIONI!$C:$C,RISULTATI!$B32,RATEAZIONI!G:G)<>0,-SUMIF(RATEAZIONI!$C:$C,RISULTATI!$B32,RATEAZIONI!G:G),-SUMIF('RATEAZIONI (dati liberi)'!$C:$C,RISULTATI!$B32,'RATEAZIONI (dati liberi)'!G:G)) -> 0 | D36: =+IF(-SUMIF(RATEAZIONI!$C:$C,RISULTATI!$B32,RATEAZIONI!H:H)<>0,-SUMIF(RATEAZIONI!$C:$C,RISULTATI!$B32,RATEAZIONI!H:H),-SUMIF('RATEAZIONI (dati liberi)'!$C:$C,RISULTATI!$B32,'RATEAZIONI (dati liberi)'!H:H)) -> 0 | E36: =+IF(-SUMIF(RATEAZIONI!$C:$C,RISULTATI!$B32,RATEAZIONI!I:I)<>0,-SUMIF(RATEAZIONI!$C:$C,RISULTATI!$B32,RATEAZIONI!I:I),-SUMIF('RATEAZIONI (dati liberi)'!$C:$C,RISULTATI!$B32,'RATEAZIONI (dati liberi)'!I:I)) -> 0 | F36: =+IF(-SUMIF(RATEAZIONI!$C:$C,RISULTATI!$B32,RATEAZIONI!J:J)<>0,-SUMIF(RATEAZIONI!$C:$C,RISULTATI!$B32,RATEAZIONI!J:J),-SUMIF('RATEAZIONI (dati liberi)'!$C:$C,RISULTATI!$B32,'RATEAZIONI (dati liberi)'!J:J)) -> 0 | G36: =+IF(-SUMIF(RATEAZIONI!$C:$C,RISULTATI!$B32,RATEAZIONI!K:K)<>0,-SUMIF(RATEAZIONI!$C:$C,RISULTATI!$B32,RATEAZIONI!K:K),-SUMIF('RATEAZIONI (dati liberi)'!$C:$C,RISULTATI!$B32,'RATEAZIONI (dati liberi)'!K:K)) -> 0 | H36: =+IF(-SUMIF(RATEAZIONI!$C:$C,RISULTATI!$B32,RATEAZIONI!L:L)<>0,-SUMIF(RATEAZIONI!$C:$C,RISULTATI!$B32,RATEAZIONI!L:L),-SUMIF('RATEAZIONI (dati liberi)'!$C:$C,RISULTATI!$B32,'RATEAZIONI (dati liberi)'!L:L)) -> 0 | I36: =+IF(-SUMIF(RATEAZIONI!$C:$C,RISULTATI!$B32,RATEAZIONI!O:O)<>0,-SUMIF(RATEAZIONI!$C:$C,RISULTATI!$B32,RATEAZIONI!O:O),-SUMIF('RATEAZIONI (dati liberi)'!$C:$C,RISULTATI!$B32,'RATEAZIONI (dati liberi)'!O:O)) -> 0 | J36: =+IF(-SUMIF(RATEAZIONI!$C:$C,RISULTATI!$B32,RATEAZIONI!M:M)<>0,-SUMIF(RATEAZIONI!$C:$C,RISULTATI!$B32,RATEAZIONI!M:M),-SUMIF('RATEAZIONI (dati liberi)'!$C:$C,RISULTATI!$B32,'RATEAZIONI (dati liberi)'!M:M)) -> 0
B37: RESIDUO DA VERSARE | C37: =SUM(C35:C36) -> 0 | D37: =+D35+D36 -> 0 | E37: =+E35+E36 -> 0 | F37: =+F35+F36 -> 0 | G37: =+G35+G36 -> 0 | H37: =MAX(0,+H35+H36) -> 0 | I37: =+I35+I36 -> 0 | J37: =+J35+J36 -> 0 | K37: =SUM(C37:J37) -> 0
B38: IMPORTO ROTTAMABILE | D38: =-D37 -> 0 | E38: =-E37 -> 0 | F38: =-F37 -> 0 | G38: =-G37 -> 0 | H38: =-H37 -> 0
B39: RESIDUO CON ROTTAMAZIONE | C39: =+SUM(C37:C38) -> 0 | D39: =+SUM(D37:D38) -> 0 | E39: =+SUM(E37:E38) -> 0 | F39: =+SUM(F37:F38) -> 0 | G39: =+SUM(G37:G38) -> 0 | H39: =+SUM(H37:H38) -> 0 | I39: =+SUM(I37:I38) -> 0 | J39: =+SUM(J37:J38) -> 0 | K39: =SUM(C39:J39) -> 0 | M39: =+IF(C33=2,0,K39) -> 0 | N39: =+K39 -> 0
C41: RISPARMIO CON ROTTAMAZIONE | E41: =+K37-K39 -> 0
C42: RISPARMIO IN % | E42: =+IFERROR(+E41/K37,0) -> 0
B46: N. Cartella | C46: Data Notifica | D46: Data Pagamento | E46: Aggio
B47: =+IF(DATI!$B$19="","",DATI!$B$19) | C47: =+IFERROR(+VLOOKUP(B47,DATI!B:N,13,0),"") | D47: 44926 | E47: =+IFERROR( IF(DATI!D19>TABELLE!C4,"", (+INDEX(TABELLE!$J$11:$M$13,MATCH(F47,TABELLE!$J$11:$J$13,1),MATCH(C47,TABELLE!$J$11:$M$11,1)))),0) -> 0 | F47: =+D47-C47 -> #VALUE!
C48: =+IFERROR(+VLOOKUP(B47,DATI!B:P,15,0),"")
C49: Imposte al ruolo | D49: Sanzioni | E49: Interessi di mora | F49: Interessi di dilazione | G49: Interessi per ritardata iscrizione a ruolo | H49: Aggio esattoriale (oneri di riscossione) | I49: Spese di Notifica | J49: Spese per proced. esecutive | K49: TOTALE
B50: TOTALE CARTELLA | C50: =+SUMIF(DATI!$B:$B,RISULTATI!$B$47,DATI!E:E) -> 0 | D50: =+SUMIF(DATI!$B:$B,RISULTATI!$B$47,DATI!F:F) -> 0 | E50: =+SUMIF(DATI!$B:$B,RISULTATI!$B$47,DATI!G:G) -> 0 | F50: =+SUMIF(DATI!$B:$B,RISULTATI!$B$47,DATI!H:H) -> 0 | G50: =+SUMIF(DATI!$B:$B,RISULTATI!$B$47,DATI!I:I) -> 0 | H50: =+SUMIF(DATI!$B:$B,RISULTATI!$B$47,DATI!J:J) -> 0 | I50: =+SUMIF(DATI!$B:$B,RISULTATI!$B$47,DATI!K:K) -> 0 | J50: =+SUMIF(DATI!$B:$B,RISULTATI!$B$47,DATI!L:L) -> 0
B51: IMPORTO GIA' VERSATO | C51: =+IF(-SUMIF(RATEAZIONI!$C:$C,RISULTATI!$B47,RATEAZIONI!G:G)<>0,-SUMIF(RATEAZIONI!$C:$C,RISULTATI!$B47,RATEAZIONI!G:G),-SUMIF('RATEAZIONI (dati liberi)'!$C:$C,RISULTATI!$B47,'RATEAZIONI (dati liberi)'!G:G)) -> 0 | D51: =+IF(-SUMIF(RATEAZIONI!$C:$C,RISULTATI!$B47,RATEAZIONI!H:H)<>0,-SUMIF(RATEAZIONI!$C:$C,RISULTATI!$B47,RATEAZIONI!H:H),-SUMIF('RATEAZIONI (dati liberi)'!$C:$C,RISULTATI!$B47,'RATEAZIONI (dati liberi)'!H:H)) -> 0 | E51: =+IF(-SUMIF(RATEAZIONI!$C:$C,RISULTATI!$B47,RATEAZIONI!I:I)<>0,-SUMIF(RATEAZIONI!$C:$C,RISULTATI!$B47,RATEAZIONI!I:I),-SUMIF('RATEAZIONI (dati liberi)'!$C:$C,RISULTATI!$B47,'RATEAZIONI (dati liberi)'!I:I)) -> 0 | F51: =+IF(-SUMIF(RATEAZIONI!$C:$C,RISULTATI!$B47,RATEAZIONI!J:J)<>0,-SUMIF(RATEAZIONI!$C:$C,RISULTATI!$B47,RATEAZIONI!J:J),-SUMIF('RATEAZIONI (dati liberi)'!$C:$C,RISULTATI!$B47,'RATEAZIONI (dati liberi)'!J:J)) -> 0 | G51: =+IF(-SUMIF(RATEAZIONI!$C:$C,RISULTATI!$B47,RATEAZIONI!K:K)<>0,-SUMIF(RATEAZIONI!$C:$C,RISULTATI!$B47,RATEAZIONI!K:K),-SUMIF('RATEAZIONI (dati liberi)'!$C:$C,RISULTATI!$B47,'RATEAZIONI (dati liberi)'!K:K)) -> 0 | H51: =+IF(-SUMIF(RATEAZIONI!$C:$C,RISULTATI!$B47,RATEAZIONI!L:L)<>0,-SUMIF(RATEAZIONI!$C:$C,RISULTATI!$B47,RATEAZIONI!L:L),-SUMIF('RATEAZIONI (dati liberi)'!$C:$C,RISULTATI!$B47,'RATEAZIONI (dati liberi)'!L:L)) -> 0 | I51: =+IF(-SUMIF(RATEAZIONI!$C:$C,RISULTATI!$B47,RATEAZIONI!O:O)<>0,-SUMIF(RATEAZIONI!$C:$C,RISULTATI!$B47,RATEAZIONI!O:O),-SUMIF('RATEAZIONI (dati liberi)'!$C:$C,RISULTATI!$B47,'RATEAZIONI (dati liberi)'!O:O)) -> 0 | J51: =+IF(-SUMIF(RATEAZIONI!$C:$C,RISULTATI!$B47,RATEAZIONI!M:M)<>0,-SUMIF(RATEAZIONI!$C:$C,RISULTATI!$B47,RATEAZIONI!M:M),-SUMIF('RATEAZIONI (dati liberi)'!$C:$C,RISULTATI!$B47,'RATEAZIONI (dati liberi)'!M:M)) -> 0
B52: RESIDUO DA VERSARE | C52: =SUM(C50:C51) -> 0 | D52: =SUM(D50:D51) -> 0 | E52: =SUM(E50:E51) -> 0 | F52: =SUM(F50:F51) -> 0 | G52: =SUM(G50:G51) -> 0 | H52: =MAX(0,+H50+H51) -> 0 | I52: =SUM(I50:I51) -> 0 | J52: =SUM(J50:J51) -> 0 | K52: =SUM(C52:J52) -> 0
B53: IMPORTO ROTTAMABILE | D53: =-D52 -> 0 | E53: =-E52 -> 0 | F53: =-F52 -> 0 | G53: =-G52 -> 0 | H53: =-H52 -> 0
B54: RESIDUO CON ROTTAMAZIONE | C54: =+SUM(C52:C53) -> 0 | D54: =+SUM(D52:D53) -> 0 | E54: =+SUM(E52:E53) -> 0 | F54: =+SUM(F52:F53) -> 0 | G54: =+SUM(G52:G53) -> 0 | H54: =+SUM(H52:H53) -> 0 | I54: =+SUM(I52:I53) -> 0 | J54: =+SUM(J52:J53) -> 0 | K54: =+IFERROR(SUM(C54:J54),0) -> 0 | M54: =+IF(C48=2,0,K54) -> 0 | N54: =+K54 -> 0
C56: RISPARMIO CON ROTTAMAZIONE | E56: =+K52-K54 -> 0
C57: RISPARMIO IN % | E57: =+IFERROR(+E56/K52,0) -> 0
B61: N. Cartella | C61: Data Notifica | D61: Data Pagamento | E61: Aggio
B62: =+IF(DATI!$B$20="","",DATI!$B$20) | C62: =+IFERROR(+VLOOKUP(B62,DATI!B:N,13,0),"") | D62: 44926 | E62: =+IFERROR( IF(DATI!D20>TABELLE!C4,"", (+INDEX(TABELLE!$J$11:$M$13,MATCH(F62,TABELLE!$J$11:$J$13,1),MATCH(C62,TABELLE!$J$11:$M$11,1)))),0) -> 0 | F62: =+D62-C62 -> #VALUE!
C63: =+IFERROR(+VLOOKUP(B62,DATI!B:P,15,0),"")
C64: Imposte al ruolo | D64: Sanzioni | E64: Interessi di mora | F64: Interessi di dilazione | G64: Interessi per ritardata iscrizione a ruolo | H64: Aggio esattoriale (oneri di riscossione) | I64: Spese di Notifica | J64: Spese per proced. esecutive | K64: TOTALE
B65: TOTALE CARTELLA | C65: =+SUMIF(DATI!$B:$B,RISULTATI!$B62,DATI!E:E) -> 0 | D65: =+SUMIF(DATI!$B:$B,RISULTATI!$B62,DATI!F:F) -> 0 | E65: =+SUMIF(DATI!$B:$B,RISULTATI!$B62,DATI!G:G) -> 0 | F65: =+SUMIF(DATI!$B:$B,RISULTATI!$B62,DATI!H:H) -> 0 | G65: =+SUMIF(DATI!$B:$B,RISULTATI!$B62,DATI!I:I) -> 0 | H65: =+SUMIF(DATI!$B:$B,RISULTATI!$B62,DATI!J:J) -> 0 | I65: =+SUMIF(DATI!$B:$B,RISULTATI!$B62,DATI!K:K) -> 0 | J65: =+SUMIF(DATI!$B:$B,RISULTATI!$B62,DATI!L:L) -> 0
B66: IMPORTO GIA' VERSATO | C66: =+IF(-SUMIF(RATEAZIONI!$C:$C,RISULTATI!$B62,RATEAZIONI!G:G)<>0,-SUMIF(RATEAZIONI!$C:$C,RISULTATI!$B62,RATEAZIONI!G:G),-SUMIF('RATEAZIONI (dati liberi)'!$C:$C,RISULTATI!$B62,'RATEAZIONI (dati liberi)'!G:G)) -> 0 | D66: =+IF(-SUMIF(RATEAZIONI!$C:$C,RISULTATI!$B62,RATEAZIONI!H:H)<>0,-SUMIF(RATEAZIONI!$C:$C,RISULTATI!$B62,RATEAZIONI!H:H),-SUMIF('RATEAZIONI (dati liberi)'!$C:$C,RISULTATI!$B62,'RATEAZIONI (dati liberi)'!H:H)) -> 0 | E66: =+IF(-SUMIF(RATEAZIONI!$C:$C,RISULTATI!$B62,RATEAZIONI!I:I)<>0,-SUMIF(RATEAZIONI!$C:$C,RISULTATI!$B62,RATEAZIONI!I:I),-SUMIF('RATEAZIONI (dati liberi)'!$C:$C,RISULTATI!$B62,'RATEAZIONI (dati liberi)'!I:I)) -> 0 | F66: =+IF(-SUMIF(RATEAZIONI!$C:$C,RISULTATI!$B62,RATEAZIONI!J:J)<>0,-SUMIF(RATEAZIONI!$C:$C,RISULTATI!$B62,RATEAZIONI!J:J),-SUMIF('RATEAZIONI (dati liberi)'!$C:$C,RISULTATI!$B62,'RATEAZIONI (dati liberi)'!J:J)) -> 0 | G66: =+IF(-SUMIF(RATEAZIONI!$C:$C,RISULTATI!$B62,RATEAZIONI!K:K)<>0,-SUMIF(RATEAZIONI!$C:$C,RISULTATI!$B62,RATEAZIONI!K:K),-SUMIF('RATEAZIONI (dati liberi)'!$C:$C,RISULTATI!$B62,'RATEAZIONI (dati liberi)'!K:K)) -> 0 | H66: =+IF(-SUMIF(RATEAZIONI!$C:$C,RISULTATI!$B62,RATEAZIONI!L:L)<>0,-SUMIF(RATEAZIONI!$C:$C,RISULTATI!$B62,RATEAZIONI!L:L),-SUMIF('RATEAZIONI (dati liberi)'!$C:$C,RISULTATI!$B62,'RATEAZIONI (dati liberi)'!L:L)) -> 0 | I66: =+IF(-SUMIF(RATEAZIONI!$C:$C,RISULTATI!$B62,RATEAZIONI!O:O)<>0,-SUMIF(RATEAZIONI!$C:$C,RISULTATI!$B62,RATEAZIONI!O:O),-SUMIF('RATEAZIONI (dati liberi)'!$C:$C,RISULTATI!$B62,'RATEAZIONI (dati liberi)'!O:O)) -> 0 | J66: =+IF(-SUMIF(RATEAZIONI!$C:$C,RISULTATI!$B62,RATEAZIONI!M:M)<>0,-SUMIF(RATEAZIONI!$C:$C,RISULTATI!$B62,RATEAZIONI!M:M),-SUMIF('RATEAZIONI (dati liberi)'!$C:$C,RISULTATI!$B62,'RATEAZIONI (dati liberi)'!M:M)) -> 0
B67: RESIDUO DA VERSARE | C67: =SUM(C65:C66) -> 0 | D67: =SUM(D65:D66) -> 0 | E67: =SUM(E65:E66) -> 0 | F67: =SUM(F65:F66) -> 0 | G67: =SUM(G65:G66) -> 0 | H67: =MAX(0,+H65+H66) -> 0 | I67: =SUM(I65:I66) -> 0 | J67: =SUM(J65:J66) -> 0 | K67: =SUM(C67:J67) -> 0
B68: IMPORTO ROTTAMABILE | D68: =-D67 -> 0 | E68: =-E67 -> 0 | F68: =-F67 -> 0 | G68: =-G67 -> 0 | H68: =-H67 -> 0
B69: RESIDUO CON ROTTAMAZIONE | C69: =+SUM(C67:C68) -> 0 | D69: =+SUM(D67:D68) -> 0 | E69: =+SUM(E67:E68) -> 0 | F69: =+SUM(F67:F68) -> 0 | G69: =+SUM(G67:G68) -> 0 | H69: =+SUM(H67:H68) -> 0 | I69: =+SUM(I67:I68) -> 0 | J69: =+SUM(J67:J68) -> 0 | K69: =+IFERROR(SUM(C69:J69),0) -> 0 | M69: =+IF(C63=2,0,K69) -> 0 | N69: =+K69 -> 0
C71: RISPARMIO CON ROTTAMAZIONE | E71: =+K67-K69 -> 0
C72: RISPARMIO IN % | E72: =+IFERROR(+E71/K67,0) -> 0
B76: N. Cartella | C76: Data Notifica | D76: Data Pagamento | E76: Aggio
B77: =+IF(DATI!$B$21="","",DATI!$B$21) | C77: =+IFERROR(+VLOOKUP(B77,DATI!B:N,13,0),"") | D77: 44926 | E77: =+IFERROR( IF(DATI!D21>TABELLE!C4,"", (+INDEX(TABELLE!$J$11:$M$13,MATCH(F77,TABELLE!$J$11:$J$13,1),MATCH(C77,TABELLE!$J$11:$M$11,1)))),0) -> 0 | F77: =+D77-C77 -> #VALUE!
C78: =+IFERROR(+VLOOKUP(B77,DATI!B:P,15,0),"")
C79: Imposte al ruolo | D79: Sanzioni | E79: Interessi di mora | F79: Interessi di dilazione | G79: Interessi per ritardata iscrizione a ruolo | H79: Aggio esattoriale (oneri di riscossione) | I79: Spese di Notifica | J79: Spese per proced. esecutive | K79: TOTALE
B80: TOTALE CARTELLA | C80: =+SUMIF(DATI!$B:$B,RISULTATI!$B77,DATI!E:E) -> 0 | D80: =+SUMIF(DATI!$B:$B,RISULTATI!$B77,DATI!F:F) -> 0 | E80: =+SUMIF(DATI!$B:$B,RISULTATI!$B77,DATI!G:G) -> 0 | F80: =+SUMIF(DATI!$B:$B,RISULTATI!$B77,DATI!H:H) -> 0 | G80: =+SUMIF(DATI!$B:$B,RISULTATI!$B77,DATI!I:I) -> 0 | H80: =+SUMIF(DATI!$B:$B,RISULTATI!$B77,DATI!J:J) -> 0 | I80: =+SUMIF(DATI!$B:$B,RISULTATI!$B77,DATI!K:K) -> 0 | J80: =+SUMIF(DATI!$B:$B,RISULTATI!$B77,DATI!L:L) -> 0
B81: IMPORTO GIA' VERSATO | C81: =+IF(-SUMIF(RATEAZIONI!$C:$C,RISULTATI!$B77,RATEAZIONI!G:G)<>0,-SUMIF(RATEAZIONI!$C:$C,RISULTATI!$B77,RATEAZIONI!G:G),-SUMIF('RATEAZIONI (dati liberi)'!$C:$C,RISULTATI!$B77,'RATEAZIONI (dati liberi)'!G:G)) -> 0 | D81: =+IF(-SUMIF(RATEAZIONI!$C:$C,RISULTATI!$B77,RATEAZIONI!H:H)<>0,-SUMIF(RATEAZIONI!$C:$C,RISULTATI!$B77,RATEAZIONI!H:H),-SUMIF('RATEAZIONI (dati liberi)'!$C:$C,RISULTATI!$B77,'RATEAZIONI (dati liberi)'!H:H)) -> 0 | E81: =+IF(-SUMIF(RATEAZIONI!$C:$C,RISULTATI!$B77,RATEAZIONI!I:I)<>0,-SUMIF(RATEAZIONI!$C:$C,RISULTATI!$B77,RATEAZIONI!I:I),-SUMIF('RATEAZIONI (dati liberi)'!$C:$C,RISULTATI!$B77,'RATEAZIONI (dati liberi)'!I:I)) -> 0 | F81: =+IF(-SUMIF(RATEAZIONI!$C:$C,RISULTATI!$B77,RATEAZIONI!J:J)<>0,-SUMIF(RATEAZIONI!$C:$C,RISULTATI!$B77,RATEAZIONI!J:J),-SUMIF('RATEAZIONI (dati liberi)'!$C:$C,RISULTATI!$B77,'RATEAZIONI (dati liberi)'!J:J)) -> 0 | G81: =+IF(-SUMIF(RATEAZIONI!$C:$C,RISULTATI!$B77,RATEAZIONI!K:K)<>0,-SUMIF(RATEAZIONI!$C:$C,RISULTATI!$B77,RATEAZIONI!K:K),-SUMIF('RATEAZIONI (dati liberi)'!$C:$C,RISULTATI!$B77,'RATEAZIONI (dati liberi)'!K:K)) -> 0 | H81: =+IF(-SUMIF(RATEAZIONI!$C:$C,RISULTATI!$B77,RATEAZIONI!L:L)<>0,-SUMIF(RATEAZIONI!$C:$C,RISULTATI!$B77,RATEAZIONI!L:L),-SUMIF('RATEAZIONI (dati liberi)'!$C:$C,RISULTATI!$B77,'RATEAZIONI (dati liberi)'!L:L)) -> 0 | I81: =+IF(-SUMIF(RATEAZIONI!$C:$C,RISULTATI!$B77,RATEAZIONI!O:O)<>0,-SUMIF(RATEAZIONI!$C:$C,RISULTATI!$B77,RATEAZIONI!O:O),-SUMIF('RATEAZIONI (dati liberi)'!$C:$C,RISULTATI!$B77,'RATEAZIONI (dati liberi)'!O:O)) -> 0 | J81: =+IF(-SUMIF(RATEAZIONI!$C:$C,RISULTATI!$B77,RATEAZIONI!M:M)<>0,-SUMIF(RATEAZIONI!$C:$C,RISULTATI!$B77,RATEAZIONI!M:M),-SUMIF('RATEAZIONI (dati liberi)'!$C:$C,RISULTATI!$B77,'RATEAZIONI (dati liberi)'!M:M)) -> 0
B82: RESIDUO DA VERSARE | C82: =SUM(C80:C81) -> 0 | D82: =SUM(D80:D81) -> 0 | E82: =SUM(E80:E81) -> 0 | F82: =SUM(F80:F81) -> 0 | G82: =SUM(G80:G81) -> 0 | H82: =MAX(0,+H80+H81) -> 0 | I82: =SUM(I80:I81) -> 0 | J82: =SUM(J80:J81) -> 0 | K82: =SUM(C82:J82) -> 0
B83: IMPORTO ROTTAMABILE | D83: =-D82 -> 0 | E83: =-E82 -> 0 | F83: =-F82 -> 0 | G83: =-G82 -> 0 | H83: =-H82 -> 0
B84: RESIDUO CON ROTTAMAZIONE | C84: =+SUM(C82:C83) -> 0 | D84: =+SUM(D82:D83) -> 0 | E84: =+SUM(E82:E83) -> 0 | F84: =+SUM(F82:F83) -> 0 | G84: =+SUM(G82:G83) -> 0 | H84: =+SUM(H82:H83) -> 0 | I84: =+SUM(I82:I83) -> 0 | J84: =+SUM(J82:J83) -> 0 | K84: =+IFERROR(SUM(C84:J84),0) -> 0 | M84: =+IF(C78=2,0,K84) -> 0 | N84: =+K84 -> 0
C86: RISPARMIO CON ROTTAMAZIONE | E86: =+K82-K84 -> 0
C87: RISPARMIO IN % | E87: =+IFERROR(+E86/K82,0) -> 0
B91: N. Cartella | C91: Data Notifica | D91: Data Pagamento | E91: Aggio
B92: =+IF(DATI!$B$22="","",DATI!$B$22) | C92: =+IFERROR(+VLOOKUP(B92,DATI!B:N,13,0),"") | D92: 44926 | E92: =+IFERROR( IF(DATI!D22>TABELLE!C4,"", (+INDEX(TABELLE!$J$11:$M$13,MATCH(F92,TABELLE!$J$11:$J$13,1),MATCH(C92,TABELLE!$J$11:$M$11,1)))),0) -> 0 | F92: =+D92-C92 -> #VALUE!
C93: =+IFERROR(+VLOOKUP(B92,DATI!B:P,15,0),"")
C94: Imposte al ruolo | D94: Sanzioni | E94: Interessi di mora | F94: Interessi di dilazione | G94: Interessi per ritardata iscrizione a ruolo | H94: Aggio esattoriale (oneri di riscossione) | I94: Spese di Notifica | J94: Spese per proced. esecutive | K94: TOTALE
B95: TOTALE CARTELLA | C95: =+SUMIF(DATI!$B:$B,RISULTATI!$B92,DATI!E:E) -> 0 | D95: =+SUMIF(DATI!$B:$B,RISULTATI!$B92,DATI!F:F) -> 0 | E95: =+SUMIF(DATI!$B:$B,RISULTATI!$B92,DATI!G:G) -> 0 | F95: =+SUMIF(DATI!$B:$B,RISULTATI!$B92,DATI!H:H) -> 0 | G95: =+SUMIF(DATI!$B:$B,RISULTATI!$B92,DATI!I:I) -> 0 | H95: =+SUMIF(DATI!$B:$B,RISULTATI!$B92,DATI!J:J) -> 0 | I95: =+SUMIF(DATI!$B:$B,RISULTATI!$B92,DATI!K:K) -> 0 | J95: =+SUMIF(DATI!$B:$B,RISULTATI!$B92,DATI!L:L) -> 0
B96: IMPORTO GIA' VERSATO | C96: =+IF(-SUMIF(RATEAZIONI!$C:$C,RISULTATI!$B92,RATEAZIONI!G:G)<>0,-SUMIF(RATEAZIONI!$C:$C,RISULTATI!$B92,RATEAZIONI!G:G),-SUMIF('RATEAZIONI (dati liberi)'!$C:$C,RISULTATI!$B92,'RATEAZIONI (dati liberi)'!G:G)) -> 0 | D96: =+IF(-SUMIF(RATEAZIONI!$C:$C,RISULTATI!$B92,RATEAZIONI!H:H)<>0,-SUMIF(RATEAZIONI!$C:$C,RISULTATI!$B92,RATEAZIONI!H:H),-SUMIF('RATEAZIONI (dati liberi)'!$C:$C,RISULTATI!$B92,'RATEAZIONI (dati liberi)'!H:H)) -> 0 | E96: =+IF(-SUMIF(RATEAZIONI!$C:$C,RISULTATI!$B92,RATEAZIONI!I:I)<>0,-SUMIF(RATEAZIONI!$C:$C,RISULTATI!$B92,RATEAZIONI!I:I),-SUMIF('RATEAZIONI (dati liberi)'!$C:$C,RISULTATI!$B92,'RATEAZIONI (dati liberi)'!I:I)) -> 0 | F96: =+IF(-SUMIF(RATEAZIONI!$C:$C,RISULTATI!$B92,RATEAZIONI!J:J)<>0,-SUMIF(RATEAZIONI!$C:$C,RISULTATI!$B92,RATEAZIONI!J:J),-SUMIF('RATEAZIONI (dati liberi)'!$C:$C,RISULTATI!$B92,'RATEAZIONI (dati liberi)'!J:J)) -> 0 | G96: =+IF(-SUMIF(RATEAZIONI!$C:$C,RISULTATI!$B92,RATEAZIONI!K:K)<>0,-SUMIF(RATEAZIONI!$C:$C,RISULTATI!$B92,RATEAZIONI!K:K),-SUMIF('RATEAZIONI (dati liberi)'!$C:$C,RISULTATI!$B92,'RATEAZIONI (dati liberi)'!K:K)) -> 0 | H96: =+IF(-SUMIF(RATEAZIONI!$C:$C,RISULTATI!$B92,RATEAZIONI!L:L)<>0,-SUMIF(RATEAZIONI!$C:$C,RISULTATI!$B92,RATEAZIONI!L:L),-SUMIF('RATEAZIONI (dati liberi)'!$C:$C,RISULTATI!$B92,'RATEAZIONI (dati liberi)'!L:L)) -> 0 | I96: =+IF(-SUMIF(RATEAZIONI!$C:$C,RISULTATI!$B92,RATEAZIONI!O:O)<>0,-SUMIF(RATEAZIONI!$C:$C,RISULTATI!$B92,RATEAZIONI!O:O),-SUMIF('RATEAZIONI (dati liberi)'!$C:$C,RISULTATI!$B92,'RATEAZIONI (dati liberi)'!O:O)) -> 0 | J96: =+IF(-SUMIF(RATEAZIONI!$C:$C,RISULTATI!$B92,RATEAZIONI!M:M)<>0,-SUMIF(RATEAZIONI!$C:$C,RISULTATI!$B92,RATEAZIONI!M:M),-SUMIF('RATEAZIONI (dati liberi)'!$C:$C,RISULTATI!$B92,'RATEAZIONI (dati liberi)'!M:M)) -> 0
B97: RESIDUO DA VERSARE | C97: =SUM(C95:C96) -> 0 | D97: =SUM(D95:D96) -> 0 | E97: =SUM(E95:E96) -> 0 | F97: =SUM(F95:F96) -> 0 | G97: =SUM(G95:G96) -> 0 | H97: =MAX(0,+H95+H96) -> 0 | I97: =SUM(I95:I96) -> 0 | J97: =SUM(J95:J96) -> 0 | K97: =SUM(C97:J97) -> 0
B98: IMPORTO ROTTAMABILE | D98: =-D97 -> 0 | E98: =-E97 -> 0 | F98: =-F97 -> 0 | G98: =-G97 -> 0 | H98: =-H97 -> 0
B99: RESIDUO CON ROTTAMAZIONE | C99: =+SUM(C97:C98) -> 0 | D99: =+SUM(D97:D98) -> 0 | E99: =+SUM(E97:E98) -> 0 | F99: =+SUM(F97:F98) -> 0 | G99: =+SUM(G97:G98) -> 0 | H99: =+SUM(H97:H98) -> 0 | I99: =+SUM(I97:I98) -> 0 | J99: =+SUM(J97:J98) -> 0 | K99: =+IFERROR(SUM(C99:J99),0) -> 0 | M99: =+IF(C93=2,0,K99) -> 0 | N99: =+K99 -> 0
C101: RISPARMIO CON ROTTAMAZIONE | E101: =+K97-K99 -> 0
C102: RISPARMIO IN % | E102: =+IFERROR(+E101/K97,0) -> 0
B106: N. Cartella | C106: Data Notifica | D106: Data Pagamento | E106: Aggio
B107: =+IF(DATI!$B$23="","",DATI!$B$23) | C107: =+IFERROR(+VLOOKUP(B107,DATI!B:N,13,0),"") | D107: 44926 | E107: =+IFERROR( IF(DATI!D23>TABELLE!C4,"", (+INDEX(TABELLE!$J$11:$M$13,MATCH(F107,TABELLE!$J$11:$J$13,1),MATCH(C107,TABELLE!$J$11:$M$11,1)))),0) -> 0 | F107: =+D107-C107 -> #VALUE!
C108: =+IFERROR(+VLOOKUP(B107,DATI!B:P,15,0),"")
C109: Imposte al ruolo | D109: Sanzioni | E109: Interessi di mora | F109: Interessi di dilazione | G109: Interessi per ritardata iscrizione a ruolo | H109: Aggio esattoriale (oneri di riscossione) | I109: Spese di Notifica | J109: Spese per proced. esecutive | K109: TOTALE
B110: TOTALE CARTELLA | C110: =+SUMIF(DATI!$B:$B,RISULTATI!$B107,DATI!E:E) -> 0 | D110: =+SUMIF(DATI!$B:$B,RISULTATI!$B107,DATI!F:F) -> 0 | E110: =+SUMIF(DATI!$B:$B,RISULTATI!$B107,DATI!G:G) -> 0 | F110: =+SUMIF(DATI!$B:$B,RISULTATI!$B107,DATI!H:H) -> 0 | G110: =+SUMIF(DATI!$B:$B,RISULTATI!$B107,DATI!I:I) -> 0 | H110: =+SUMIF(DATI!$B:$B,RISULTATI!$B107,DATI!J:J) -> 0 | I110: =+SUMIF(DATI!$B:$B,RISULTATI!$B107,DATI!K:K) -> 0 | J110: =+SUMIF(DATI!$B:$B,RISULTATI!$B107,DATI!L:L) -> 0
B111: IMPORTO GIA' VERSATO | C111: =+IF(-SUMIF(RATEAZIONI!$C:$C,RISULTATI!$B107,RATEAZIONI!G:G)<>0,-SUMIF(RATEAZIONI!$C:$C,RISULTATI!$B107,RATEAZIONI!G:G),-SUMIF('RATEAZIONI (dati liberi)'!$C:$C,RISULTATI!$B107,'RATEAZIONI (dati liberi)'!G:G)) -> 0 | D111: =+IF(-SUMIF(RATEAZIONI!$C:$C,RISULTATI!$B107,RATEAZIONI!H:H)<>0,-SUMIF(RATEAZIONI!$C:$C,RISULTATI!$B107,RATEAZIONI!H:H),-SUMIF('RATEAZIONI (dati liberi)'!$C:$C,RISULTATI!$B107,'RATEAZIONI (dati liberi)'!H:H)) -> 0 | E111: =+IF(-SUMIF(RATEAZIONI!$C:$C,RISULTATI!$B107,RATEAZIONI!I:I)<>0,-SUMIF(RATEAZIONI!$C:$C,RISULTATI!$B107,RATEAZIONI!I:I),-SUMIF('RATEAZIONI (dati liberi)'!$C:$C,RISULTATI!$B107,'RATEAZIONI (dati liberi)'!I:I)) -> 0 | F111: =+IF(-SUMIF(RATEAZIONI!$C:$C,RISULTATI!$B107,RATEAZIONI!J:J)<>0,-SUMIF(RATEAZIONI!$C:$C,RISULTATI!$B107,RATEAZIONI!J:J),-SUMIF('RATEAZIONI (dati liberi)'!$C:$C,RISULTATI!$B107,'RATEAZIONI (dati liberi)'!J:J)) -> 0 | G111: =+IF(-SUMIF(RATEAZIONI!$C:$C,RISULTATI!$B107,RATEAZIONI!K:K)<>0,-SUMIF(RATEAZIONI!$C:$C,RISULTATI!$B107,RATEAZIONI!K:K),-SUMIF('RATEAZIONI (dati liberi)'!$C:$C,RISULTATI!$B107,'RATEAZIONI (dati liberi)'!K:K)) -> 0 | H111: =+IF(-SUMIF(RATEAZIONI!$C:$C,RISULTATI!$B107,RATEAZIONI!L:L)<>0,-SUMIF(RATEAZIONI!$C:$C,RISULTATI!$B107,RATEAZIONI!L:L),-SUMIF('RATEAZIONI (dati liberi)'!$C:$C,RISULTATI!$B107,'RATEAZIONI (dati liberi)'!L:L)) -> 0 | I111: =+IF(-SUMIF(RATEAZIONI!$C:$C,RISULTATI!$B107,RATEAZIONI!O:O)<>0,-SUMIF(RATEAZIONI!$C:$C,RISULTATI!$B107,RATEAZIONI!O:O),-SUMIF('RATEAZIONI (dati liberi)'!$C:$C,RISULTATI!$B107,'RATEAZIONI (dati liberi)'!O:O)) -> 0 | J111: =+IF(-SUMIF(RATEAZIONI!$C:$C,RISULTATI!$B107,RATEAZIONI!M:M)<>0,-SUMIF(RATEAZIONI!$C:$C,RISULTATI!$B107,RATEAZIONI!M:M),-SUMIF('RATEAZIONI (dati liberi)'!$C:$C,RISULTATI!$B107,'RATEAZIONI (dati liberi)'!M:M)) -> 0
B112: RESIDUO DA VERSARE | C112: =SUM(C110:C111) -> 0 | D112: =SUM(D110:D111) -> 0 | E112: =SUM(E110:E111) -> 0 | F112: =SUM(F110:F111) -> 0 | G112: =SUM(G110:G111) -> 0 | H112: =MAX(0,+H110+H111) -> 0 | I112: =SUM(I110:I111) -> 0 | J112: =SUM(J110:J111) -> 0 | K112: =SUM(C112:J112) -> 0
B113: IMPORTO ROTTAMABILE | D113: =-D112 -> 0 | E113: =-E112 -> 0 | F113: =-F112 -> 0 | G113: =-G112 -> 0 | H113: =-H112 -> 0
B114: RESIDUO CON ROTTAMAZIONE | C114: =+SUM(C112:C113) -> 0 | D114: =+SUM(D112:D113) -> 0 | E114: =+SUM(E112:E113) -> 0 | F114: =+SUM(F112:F113) -> 0 | G114: =+SUM(G112:G113) -> 0 | H114: =+SUM(H112:H113) -> 0 | I114: =+SUM(I112:I113) -> 0 | J114: =+SUM(J112:J113) -> 0 | K114: =+IFERROR(SUM(C114:J114),0) -> 0 | M114: =+IF(C108=2,0,K114) -> 0 | N114: =+K114 -> 0
C116: RISPARMIO CON ROTTAMAZIONE | E116: =+K112-K114 -> 0
C117: RISPARMIO IN % | E117: =+IFERROR(+E116/K112,0) -> 0
B121: N. Cartella | C121: Data Notifica | D121: Data Pagamento | E121: Aggio
B122: =+IF(DATI!$B$24="","",DATI!$B$24) | C122: =+IFERROR(+VLOOKUP(B122,DATI!B:N,13,0),"") | D122: 44926 | E122: =+IFERROR( IF(DATI!D24>TABELLE!C4,"", (+INDEX(TABELLE!$J$11:$M$13,MATCH(F122,TABELLE!$J$11:$J$13,1),MATCH(C122,TABELLE!$J$11:$M$11,1)))),0) -> 0 | F122: =+D122-C122 -> #VALUE!
C123: =+IFERROR(+VLOOKUP(B122,DATI!B:P,15,0),"")
C124: Imposte al ruolo | D124: Sanzioni | E124: Interessi di mora | F124: Interessi di dilazione | G124: Interessi per ritardata iscrizione a ruolo | H124: Aggio esattoriale (oneri di riscossione) | I124: Spese di Notifica | J124: Spese per proced. esecutive | K124: TOTALE
B125: TOTALE CARTELLA | C125: =+SUMIF(DATI!$B:$B,RISULTATI!$B122,DATI!E:E) -> 0 | D125: =+SUMIF(DATI!$B:$B,RISULTATI!$B122,DATI!F:F) -> 0 | E125: =+SUMIF(DATI!$B:$B,RISULTATI!$B122,DATI!G:G) -> 0 | F125: =+SUMIF(DATI!$B:$B,RISULTATI!$B122,DATI!H:H) -> 0 | G125: =+SUMIF(DATI!$B:$B,RISULTATI!$B122,DATI!I:I) -> 0 | H125: =+SUMIF(DATI!$B:$B,RISULTATI!$B122,DATI!J:J) -> 0 | I125: =+SUMIF(DATI!$B:$B,RISULTATI!$B122,DATI!K:K) -> 0 | J125: =+SUMIF(DATI!$B:$B,RISULTATI!$B122,DATI!L:L) -> 0
B126: IMPORTO GIA' VERSATO | C126: =+IF(-SUMIF(RATEAZIONI!$C:$C,RISULTATI!$B122,RATEAZIONI!G:G)<>0,-SUMIF(RATEAZIONI!$C:$C,RISULTATI!$B122,RATEAZIONI!G:G),-SUMIF('RATEAZIONI (dati liberi)'!$C:$C,RISULTATI!$B122,'RATEAZIONI (dati liberi)'!G:G)) -> 0 | D126: =+IF(-SUMIF(RATEAZIONI!$C:$C,RISULTATI!$B122,RATEAZIONI!H:H)<>0,-SUMIF(RATEAZIONI!$C:$C,RISULTATI!$B122,RATEAZIONI!H:H),-SUMIF('RATEAZIONI (dati liberi)'!$C:$C,RISULTATI!$B122,'RATEAZIONI (dati liberi)'!H:H)) -> 0 | E126: =+IF(-SUMIF(RATEAZIONI!$C:$C,RISULTATI!$B122,RATEAZIONI!I:I)<>0,-SUMIF(RATEAZIONI!$C:$C,RISULTATI!$B122,RATEAZIONI!I:I),-SUMIF('RATEAZIONI (dati liberi)'!$C:$C,RISULTATI!$B122,'RATEAZIONI (dati liberi)'!I:I)) -> 0 | F126: =+IF(-SUMIF(RATEAZIONI!$C:$C,RISULTATI!$B122,RATEAZIONI!J:J)<>0,-SUMIF(RATEAZIONI!$C:$C,RISULTATI!$B122,RATEAZIONI!J:J),-SUMIF('RATEAZIONI (dati liberi)'!$C:$C,RISULTATI!$B122,'RATEAZIONI (dati liberi)'!J:J)) -> 0 | G126: =+IF(-SUMIF(RATEAZIONI!$C:$C,RISULTATI!$B122,RATEAZIONI!K:K)<>0,-SUMIF(RATEAZIONI!$C:$C,RISULTATI!$B122,RATEAZIONI!K:K),-SUMIF('RATEAZIONI (dati liberi)'!$C:$C,RISULTATI!$B122,'RATEAZIONI (dati liberi)'!K:K)) -> 0 | H126: =+IF(-SUMIF(RATEAZIONI!$C:$C,RISULTATI!$B122,RATEAZIONI!L:L)<>0,-SUMIF(RATEAZIONI!$C:$C,RISULTATI!$B122,RATEAZIONI!L:L),-SUMIF('RATEAZIONI (dati liberi)'!$C:$C,RISULTATI!$B122,'RATEAZIONI (dati liberi)'!L:L)) -> 0 | I126: =+IF(-SUMIF(RATEAZIONI!$C:$C,RISULTATI!$B122,RATEAZIONI!O:O)<>0,-SUMIF(RATEAZIONI!$C:$C,RISULTATI!$B122,RATEAZIONI!O:O),-SUMIF('RATEAZIONI (dati liberi)'!$C:$C,RISULTATI!$B122,'RATEAZIONI (dati liberi)'!O:O)) -> 0 | J126: =+IF(-SUMIF(RATEAZIONI!$C:$C,RISULTATI!$B122,RATEAZIONI!M:M)<>0,-SUMIF(RATEAZIONI!$C:$C,RISULTATI!$B122,RATEAZIONI!M:M),-SUMIF('RATEAZIONI (dati liberi)'!$C:$C,RISULTATI!$B122,'RATEAZIONI (dati liberi)'!M:M)) -> 0
B127: RESIDUO DA VERSARE | C127: =SUM(C125:C126) -> 0 | D127: =SUM(D125:D126) -> 0 | E127: =SUM(E125:E126) -> 0 | F127: =SUM(F125:F126) -> 0 | G127: =SUM(G125:G126) -> 0 | H127: =MAX(0,+H125+H126) -> 0 | I127: =SUM(I125:I126) -> 0 | J127: =SUM(J125:J126) -> 0 | K127: =SUM(C127:J127) -> 0
B128: IMPORTO ROTTAMABILE | D128: =-D127 -> 0 | E128: =-E127 -> 0 | F128: =-F127 -> 0 | G128: =-G127 -> 0 | H128: =-H127 -> 0
B129: RESIDUO CON ROTTAMAZIONE | C129: =+SUM(C127:C128) -> 0 | D129: =+SUM(D127:D128) -> 0 | E129: =+SUM(E127:E128) -> 0 | F129: =+SUM(F127:F128) -> 0 | G129: =+SUM(G127:G128) -> 0 | H129: =+SUM(H127:H128) -> 0 | I129: =+SUM(I127:I128) -> 0 | J129: =+SUM(J127:J128) -> 0 | K129: =+IFERROR(SUM(C129:J129),0) -> 0 | M129: =+IF(C123=2,0,K129) -> 0 | N129: =+K129 -> 0
C131: RISPARMIO CON ROTTAMAZIONE | E131: =+K127-K129 -> 0
C132: RISPARMIO IN % | E132: =+IFERROR(+E131/K127,0) -> 0
B136: N. Cartella | C136: Data Notifica | D136: Data Pagamento | E136: Aggio
B137: =+IF(DATI!$B$25="","",DATI!$B$25) | C137: =+IFERROR(+VLOOKUP(B137,DATI!B:N,13,0),"") | D137: 44926 | E137: =+IFERROR( IF(DATI!D25>TABELLE!C4,"", (+INDEX(TABELLE!$J$11:$M$13,MATCH(F137,TABELLE!$J$11:$J$13,1),MATCH(C137,TABELLE!$J$11:$M$11,1)))),0) -> 0 | F137: =+D137-C137 -> #VALUE!
C138: =+IFERROR(+VLOOKUP(B137,DATI!B:P,15,0),"")
C139: Imposte al ruolo | D139: Sanzioni | E139: Interessi di mora | F139: Interessi di dilazione | G139: Interessi per ritardata iscrizione a ruolo | H139: Aggio esattoriale (oneri di riscossione) | I139: Spese di Notifica | J139: Spese per proced. esecutive | K139: TOTALE
B140: TOTALE CARTELLA | C140: =+SUMIF(DATI!$B:$B,RISULTATI!$B137,DATI!E:E) -> 0 | D140: =+SUMIF(DATI!$B:$B,RISULTATI!$B137,DATI!F:F) -> 0 | E140: =+SUMIF(DATI!$B:$B,RISULTATI!$B137,DATI!G:G) -> 0 | F140: =+SUMIF(DATI!$B:$B,RISULTATI!$B137,DATI!H:H) -> 0 | G140: =+SUMIF(DATI!$B:$B,RISULTATI!$B137,DATI!I:I) -> 0 | H140: =+SUMIF(DATI!$B:$B,RISULTATI!$B137,DATI!J:J) -> 0 | I140: =+SUMIF(DATI!$B:$B,RISULTATI!$B137,DATI!K:K) -> 0 | J140: =+SUMIF(DATI!$B:$B,RISULTATI!$B137,DATI!L:L) -> 0
B141: IMPORTO GIA' VERSATO | C141: =+IF(-SUMIF(RATEAZIONI!$C:$C,RISULTATI!$B137,RATEAZIONI!G:G)<>0,-SUMIF(RATEAZIONI!$C:$C,RISULTATI!$B137,RATEAZIONI!G:G),-SUMIF('RATEAZIONI (dati liberi)'!$C:$C,RISULTATI!$B137,'RATEAZIONI (dati liberi)'!G:G)) -> 0 | D141: =+IF(-SUMIF(RATEAZIONI!$C:$C,RISULTATI!$B137,RATEAZIONI!H:H)<>0,-SUMIF(RATEAZIONI!$C:$C,RISULTATI!$B137,RATEAZIONI!H:H),-SUMIF('RATEAZIONI (dati liberi)'!$C:$C,RISULTATI!$B137,'RATEAZIONI (dati liberi)'!H:H)) -> 0 | E141: =+IF(-SUMIF(RATEAZIONI!$C:$C,RISULTATI!$B137,RATEAZIONI!I:I)<>0,-SUMIF(RATEAZIONI!$C:$C,RISULTATI!$B137,RATEAZIONI!I:I),-SUMIF('RATEAZIONI (dati liberi)'!$C:$C,RISULTATI!$B137,'RATEAZIONI (dati liberi)'!I:I)) -> 0 | F141: =+IF(-SUMIF(RATEAZIONI!$C:$C,RISULTATI!$B137,RATEAZIONI!J:J)<>0,-SUMIF(RATEAZIONI!$C:$C,RISULTATI!$B137,RATEAZIONI!J:J),-SUMIF('RATEAZIONI (dati liberi)'!$C:$C,RISULTATI!$B137,'RATEAZIONI (dati liberi)'!J:J)) -> 0 | G141: =+IF(-SUMIF(RATEAZIONI!$C:$C,RISULTATI!$B137,RATEAZIONI!K:K)<>0,-SUMIF(RATEAZIONI!$C:$C,RISULTATI!$B137,RATEAZIONI!K:K),-SUMIF('RATEAZIONI (dati liberi)'!$C:$C,RISULTATI!$B137,'RATEAZIONI (dati liberi)'!K:K)) -> 0 | H141: =+IF(-SUMIF(RATEAZIONI!$C:$C,RISULTATI!$B137,RATEAZIONI!L:L)<>0,-SUMIF(RATEAZIONI!$C:$C,RISULTATI!$B137,RATEAZIONI!L:L),-SUMIF('RATEAZIONI (dati liberi)'!$C:$C,RISULTATI!$B137,'RATEAZIONI (dati liberi)'!L:L)) -> 0 | I141: =+IF(-SUMIF(RATEAZIONI!$C:$C,RISULTATI!$B137,RATEAZIONI!O:O)<>0,-SUMIF(RATEAZIONI!$C:$C,RISULTATI!$B137,RATEAZIONI!O:O),-SUMIF('RATEAZIONI (dati liberi)'!$C:$C,RISULTATI!$B137,'RATEAZIONI (dati liberi)'!O:O)) -> 0 | J141: =+IF(-SUMIF(RATEAZIONI!$C:$C,RISULTATI!$B137,RATEAZIONI!M:M)<>0,-SUMIF(RATEAZIONI!$C:$C,RISULTATI!$B137,RATEAZIONI!M:M),-SUMIF('RATEAZIONI (dati liberi)'!$C:$C,RISULTATI!$B137,'RATEAZIONI (dati liberi)'!M:M)) -> 0
B142: RESIDUO DA VERSARE | C142: =SUM(C140:C141) -> 0 | D142: =SUM(D140:D141) -> 0 | E142: =SUM(E140:E141) -> 0 | F142: =SUM(F140:F141) -> 0 | G142: =SUM(G140:G141) -> 0 | H142: =MAX(0,+H140+H141) -> 0 | I142: =SUM(I140:I141) -> 0 | J142: =SUM(J140:J141) -> 0 | K142: =SUM(C142:J142) -> 0
B143: IMPORTO ROTTAMABILE | D143: =-D142 -> 0 | E143: =-E142 -> 0 | F143: =-F142 -> 0 | G143: =-G142 -> 0 | H143: =-H142 -> 0
B144: RESIDUO CON ROTTAMAZIONE | C144: =+SUM(C142:C143) -> 0 | D144: =+SUM(D142:D143) -> 0 | E144: =+SUM(E142:E143) -> 0 | F144: =+SUM(F142:F143) -> 0 | G144: =+SUM(G142:G143) -> 0 | H144: =+SUM(H142:H143) -> 0 | I144: =+SUM(I142:I143) -> 0 | J144: =+SUM(J142:J143) -> 0 | K144: =IFERROR(SUM(C144:J144),0) -> 0 | M144: =+IF(C138=2,0,K144) -> 0 | N144: =+K144 -> 0
...

Sheet TABELLE
P1: Codice | Q1: Imposta | R1: Descrizione | S1: Sanz. | T1: Int. | U1: Sezione
A2: VER. 1.0 | C2: Date Rif | P2: 1001 | Q2: IRPEF DIPENDENTI | R2: IRPEF DIPENDENTI | S2: 8906 | U2: 1
P3: 1004 | Q3: IRPEF DIPENDENTI | R3: IRPEF DIPENDENTI | S3: 8906 | U3: 1
A4: 36528 | C4: 44561 | P4: 1012 | Q4: IRPEF DIPENDENTI | R4: IRPEF DIPENDENTI | S4: 8906 | U4: 1
P5: 1038 | Q5: RITENUTA | R5: RITENUTE SU PROVVIGIONI PER RAPPORTI DI COMMISSIONE, DI AGENZIA DI MEDIAZIONE DI RAPPRESENTANZA | S5: 8906 | U5: 1
P6: 1040 | Q6: RITENUTA | R6: RITENUTA SU REDDITI DA LAVORO AUTONOMO | S6: 8906 | U6: 1
P7: 1100 | Q7: Imposte sostitutive | R7: Imposta sostitutiva su plusvalenza per cessione a titolo oneroso di partecipazioni non qualificate (RT sez. I e II) | S7: 8913 | T7: 1992 | U7: 1
C8: 36526 | P8: 1121 | Q8: Sez. III - Conferimenti in SIIQ e SINQ | R8: Imposta sostitutiva dell'imposta sul reddito e dell'IRAP sui conferimenti in siiq, siinq e fondi immobiliari, ai sensi della legge 27-12-2006, art. 1, comma 137 e 140. risoluzione n. 37/e del 7/2/2008 | S8: 8913 | T8: 1992 | U8: 1
C9: 42369 | P9: 1123 | Q9: Sez. IV - Deduzioni extracontabili | R9: Imposta sostitutiva per il recupero a tassazione dell'eccedenza dedotta ai sensi dell'art. 109, comma 4, lett b) del tuir - art. 1, comma 48, legge n. 244/2007 | S9: 8913 | T9: 1992 | U9: 1
P10: 1128 | Q10: Imposte rideterminate | R10: Imposta rideterminata ai fini IRPEF a seguito della plusvalenza non reinvestita derivante dalla cessione di partecipazione qualificata - art. 68, c. 6-bis, del tui (quadro RT sez. III - Start Up) | S10: 8913 | T10: 1992 | U10: 1
K11: 0 | L11: 41275 | M11: 42370 | P11: 1239 | Q11: Imposte sostitutive | R11: Imposta sostitutiva su intermediazione premi e frutti di obbligazioni e titoli similari (quadro RM, sez V - RM13) | S11: 8913 | T11: 1992 | U11: 1
J12: 0 | K12: 0.0465 | L12: 0.0465 | M12: 0.03 | P12: 1242 | Q12: Imposte sostitutive | R12: Imposta sostitutiva alle imposte sui redditi di capitale di fonte estera (quadro RM, sez V - RM12) | S12: 8913 | T12: 1992 | U12: 1
J13: 60 | K13: 0.09 | L13: 0.08 | M13: 0.06 | P13: 1245 | Q13: Imposte sostitutive | R13: Proventi derivanti da depositi a garanzia di finanziamenti (quadro RM, sez VII) | S13: 8913 | T13: 1992 | U13: 1
E14: Importo residuo dovuto | F14: =+MENU!O24 -> 11918.8 | P14: 1668 | Q14: IRES/IRPEF/ILOR/IVA/IMPOSTE SOSTITUTIVE | R14: INTERESSI PAGAMENTO DILAZIONATO IMPORTI RATEIZZABILI SEZIONE 2 DEL MODELLO DI VERSAMENTO UNITARIO | S14: 8913 | T14: 1992 | U14: 1
E15: Capitale da versare | F15: =+MENU!F23 -> 7899.8 | P15: 1684 | Q15: Imposte sostitutive | R15: Addizionale su compensi erogati a titolo di bonus e stock options di cui all'articolo 33 del d.l. n. 78/2010, versamento in autotassazione (quadro RM, sez XIV) | S15: 8908 | T15: 1684 | U15: 1
A16: sì-no | E16: Risparmio | F16: =+MENU!O25 -> 4019 | P16: 1712 | Q16: IRPEF DIPENDENTI | R16: IRPEF DIPENDENTI | S16: 8906 | U16: 1
A17: Sì | P17: 1714 | Q17: Imposte sostitutive | R17: Imposta sostitutiva sui redditi derivanti dalle rivalutazioni del trattamento di fine rapporto versata dal soggetto percettore in dichiarazione (quadro RM, sez XII) | S17: 8913 | T17: 1992 | U17: 1
A18: No | J18: 90 | P18: 1793 | Q18: Imposta sostitutiva regime fiscale di vantaggio | R18: Imposta sostitutiva per regime fiscale di vantaggio per l'imprenditoria giovanile e lavoratori in mobilit_x001A_ - acconto prima rata - art. 27, dl 06/06/2011, n. 98, conv., con modif., dalla l. n. 111/2011 | S18: 8913 | T18: 1992 | U18: 1
J19: 41276 | L19: =+MATCH(J18,J11:J13,1) -> 3 | N19: =+INDEX($J$11:$L$13,MATCH(J18,J11:J13,1),MATCH(J19,J11:L11,1)) -> 0.08 | P19: 1794 | Q19: Imposta sostitutiva regime fiscale di vantaggio | R19: Imposta sostitutiva per regime fiscale di vantaggio per l'imprenditoria giovanile e lavoratori in mobilit_x001A_ - acconto seconda rata o in unica soluzione - art. 27, dl 06/06/2011, n. 98, conv., con modif., dalla l. n. 111/2011 | S19: 8913 | T19: 1992 | U19: 1
L20: =+MATCH(J19,J11:L11,1) -> 3 | P20: 1795 | Q20: Imposte sostitutive regime fiscale di vantaggio | R20: Imposta sostitutiva sul regime fiscale di vantaggio per l'imprenditoria giovanile e lavoratori in mobilit_x001A_ saldo - art. 27, dl 06/06/2011, n. 98, conv., con modif., dalla l. n. 111/2011 | S20: 8913 | T20: 1992 | U20: 1
P21: 1816 | Q21: Imposte sostitutive lavoro straordinario | R21: Imposta sostitutiva dell'IRPEF e delle addizionali regionali e comunali sui compensi accessori del reddito da lavoro dipendente, applicata in sede di dichiarazione unico pf 2009 - art. 2, d.l. 93/2008 - ris. n. 115/e del 28 Aprile 2009 | S21: 8913 | T21: 1992 | U21: 1
P22: 1822 | Q22: Quadro RM, sez. XIII - Operazioni Straord. - Altre attività - D.L. 185/2008 | R22: Imposta a seguito di operazione straordinaria di cui all'art. 15, c. 11, d.l. 185/2008 - maggiori valori altre attivita'-risoluzione n. 127/e del 25/05/2009 | S22: 8913 | T22: 1992 | U22: 1
E23: =E15 -> Capitale da versare | F23: =F15 -> 7899.8 | P23: 1840 | Q23: Cedolare secca | R23: Imp.sost.dell'IRPEF e delle relat.add.li,nonche' delle imposte di registro e di bollo, sul canon di locaz.relat. ai contrat.aventi ad ogg.immobili ad uso abitat.e le relative pertinenze locate congiunt.all'abitaz.-art.3, dlgs. n.23/2011-acconto prima rata | S23: 8913 | T23: 1992 | U23: 1
P24: 1841 | Q24: Cedolare secca | R24: Imp.sost.dell'IRPEF e delle rel.add.li,nonche'delle imposte di registroe di bollo,sul can. di loc.relat. ai contr.aventi ad ogg.immob ad uso abit. e le rel. pertin. locate congiun.all'abit.-art.3,dlgs.n.23/2011-acconto secondarata o accont.in unica soluz. | S24: 8913 | T24: 1992 | U24: 1
P25: 1842 | Q25: Cedolare secca | R25: Impost.sostitutivadell'IRPEF e delle relat addiz.,nonche' delle imposte di registro e di bollo, sul canon di locazione relat. ai contr.aventi ad ogg.immobili ad uso abitat. e le relativ.pertin.locate congiuntam.all'abitazione-art. 3, dlgs.n.23/2011- saldo | S25: 8913 | T25: 1992 | U25: 1
P26: 1847 | Q26: Quadro RM, sez. XV - Noleggio occasionale imbarcazioni da diporto | R26: Imposta sostitutiva delle imposte sui redditi e delle relative addizionali sui proventi derivanti dall'attivit_x001A_ di noleggio occasionale - art. 49-bis del d.lgs. n. 171/2005 | S26: 8913 | T26: 1992 | U26: 1
P27: 2001 | Q27: VERSAMENTO IRES | R27: VERSAMENTO IRES ACCONTO I RATA | S27: 8918 | T27: 1990 | U27: 1
E28: =E14 -> Importo residuo dovuto | F28: =F14 -> 11918.8 | P28: 2002 | Q28: VERSAMENTO IRES | R28: VERSAMENTO IRES ACCONTO II RATA O ACCONTO IN UNICA SOLUZIONE | S28: 8918 | T28: 1990 | U28: 1
E29: =E16 -> Risparmio | F29: =-F16 -> -4019 | P29: 2003 | Q29: VERSAMENTO IRES | R29: VERSAMENTO IRES SALDO | S29: 8918 | T29: 1990 | U29: 1
E30: Capitale da versare | F30: =+F28+F29 -> 7899.8 | P30: 2728 | Q30: Sez. I - Plusvalenze da conferimenti e cessioni a CAF | R30: Imposta sostitutiva delle imposte sui redditi sulle plusvalenze derivanti da conferimenti o cessioni di beni o aziende a favore dei caf | S30: 8913 | T30: 1992 | U30: 1
P31: 3800 | Q31: VERSAMENTO IRAP | R31: VERSAMENTO IRAP SALDO | S31: 8907 | T31: 1993 | U31: 3
P32: 3801 | Q32: ADDIZIONALE REGIONALE IRPEF | R32: ADDIZIONALE REGIONALE ALL'IMPOSTA SUL REDDITO DELLE PERSONE FISICHE | S32: 8902 | T32: 1994 | U32: 3
P33: 3804 | Q33: ADDIZIONALE COMUNALE IRPEF | R33: INTERESSI PAGAMENTO DILAZIONATO TRIBUTI ENTI LOCALI | S33: 8926 | T33: 1998 | U33: 3
P34: 3805 | Q34: ADDIZIONALE REGIONALE IRPEF/IRAP | R34: INTERESSI PAGAMENTO DILAZIONATO TRIBUTI REGIONALI | S34: 8902 | T34: 1994 | U34: 3
P35: 3812 | Q35: VERSAMENTO IRAP | R35: VERSAMENTO IRAP I RATA di ACCONTO | S35: 8907 | T35: 1993 | U35: 3
A36: SCADENZIARIO | P36: 3813 | Q36: VERSAMENTO IRAP | R36: VERSAMENTO IRAP II RATA di ACCONTO | S36: 8907 | T36: 1993 | U36: 3
A37: 43069 | B37: VERSAMENTO RATE DI LUGLIO E SETTEMBRE RELATIVE ALLA PRIMA DEFINIZIONE AGEVOLATA | P37: 3817 | Q37: ADDIZIONALE COMUNALE IRPEF | R37: ADDIZIONALE ALL'IRPEF AUTOTASSAZIONE - SALDO | S37: 8926 | T37: 1998 | U37: 3
A38: 43100 | B38: PRESENTAZIONE DOMANDA ADE PER CONTRIBUENTI NON IN REGOLA CON I PIANI DI DILAZIONE AL 31/12/2016 | P38: 3843 | Q38: Addizionale comunale | R38: Addizionale comunale all'IRPEF-autotassazione-acconto (ris. n. 368 /e del 12/12/2007) | S38: 8926 | T38: 1998 | U38: 4
A39: 43190 | B39: COMUNICAZIONE VIA POSTA ORDINARUIA DA PARTE DELL'AdE R AL DEBITORE DELL'IMPORTO DEI CARICHI DEFINIBILI | P39: 3872 | Q39: Imposte rideterminate Add. Com. IRPEF | R39: Addizionale comunale all'IRPEF rideterminata a seguito della plusvalenza non reinvestita derivante dalla cessione di partecipazione qualificata - art. 68, c. 6-bis, del tuir (quadro RT sez. III-A - Start Up) | S39: 8903 | T39: 1998 | U39: 4
A40: 43235 | B40: SCADENZA PRESENTAZIONE DOMANDA DEFINIZIONE AGEVOLATA | P40: 3880 | Q40: Imposte rideterminate Add. Reg. IRPEF | R40: Addizionale regionale all'IRPEF rideterminata a seguito della plusvalenza non reinvestita derivante dalla cessione di partecipazione qualificata - art.68, c. 6-bis, del tui (quadro RT sez. III-A - Start Up) | S40: 8902 | T40: 1994 | U40: 3
A41: 43251 | B41: PAGAMENTO RATE NON CORRISPOSTE ENTRO IL 31/12/2016 relative ai piani di rateazione in essere al 24/10/2016 | P41: 4001 | Q41: IRPEF | R41: SALDO IRPEF | S41: 8901 | T41: 1989 | U41: 1
A42: 43312 | B42: VERSAMENTO UNICA SOLUZIONE O PRIMA RATA DELLA DEFINIZIONE AGEVOLATA BIS | P42: 4003 | Q42: Tassa etica | R42: Addizionale all'IRPEF - art. 31, c.3, d.l. 185/2008 - acconto prima rata | S42: 8908 | U42: 1
P43: 4004 | Q43: Tassa etica | R43: Addizionale all'IRPEF - art. 31, c.3, d.l. 185/2008 - acconto seconda rata o acconto in unica soluzione | S43: 8908 | U43: 1
P44: 4005 | Q44: Sez. XII - Tassa etica | R44: Addizionale all'IRPEF - art. 31, c.3, d.l. 185/2008 - saldo | S44: 8908 | T44: 4005 | U44: 1
P45: 4025 | Q45: Imposte sostitutive nuove iniziative produttive | R45: Imposta sostitutiva dell'IRPEF per le nuove iniziative imprenditoriali e di lavoro autonomo | S45: 8913 | T45: 1992 | U45: 1
P46: 4033 | Q46: IRPEF | R46: IRPEF ACCONTO - PRIMA RATA | S46: 8901 | T46: 1989 | U46: 1
P47: 4034 | Q47: IRPEF | R47: IRPEF ACCONTO - SECONDA RATA O ACCONTO IN UNICA SOLUZIONE | S47: 8901 | T47: 1989 | U47: 1
P48: 4040 | Q48: Imposte sostitutive | R48: Imposta sui redditi soggetti a tassazione separata, a ritenuta a titolo di imposta o a imposta sostitutiva derivanti da pignoramento presso terzi dovuta dal creditore pignoratizio )quadro RM, sez XI) | S48: 8913 | T48: 1992 | U48: 1
P49: 4041 | Q49: IVIE | R49: Imposta sul valore degli immobili situati all'estero, a qualsiasi uso destinati dalle persone fisiche residenti nel territorio dello stato - art. 19, c. 13, d.l. n. 201/2011, conv., con modif., dalla l. n. 214/2011, e succ. modif.- saldo | S49: 8913 | T49: 1992 | U49: 1
P50: 4043 | Q50: IVAFE | R50: Imposta sul valore delle attivit_x001A_ finanziarie detenute all'estero dalle persone fisiche residenti nel territorio dello stato - art. 19, c. 18, d.l. 201/2011 conv., con modif., dalla l. 214/2011, e succ. modif.-saldo | S50: 8913 | T50: 1992 | U50: 1
P51: 4044 | Q51: IVIE | R51: Imposta sul valore degli immobili situati all'estero, a qualsiasi uso destinati da persone fisiche residenti nel territorio dello stato - art.19, c.13, dl. n. 201/11, conv., con mod., da l.n. 214/2011, e succ. modif., - acconto prima rata | S51: 8908 | U51: 1
P52: 4045 | Q52: IVIE | R52: Imposta sul valore degli immobili situati all'estero, a qualsiasi uso destinati da persone fisiche residenti nel territ. dello stato - art.19, c.13, dl. n.201/2011, conv., con modif., dalla l.214/2011, e succ.mod., - acconto seconda rata o acc. unica sol. | S52: 8908 | U52: 1
P53: 4047 | Q53: IVAFE | R53: Imposta sul valore delle attivit_x001A_ finanziarie detenute all'estero dalle pers. fisiche residenti nel territorio dello stato - art. 19, c. 18, dl. n. 201/2011 conv., con modif., dalla l. n. 214/2011, e succ. mod. acconto prima rata | S53: 8908 | U53: 1
P54: 4048 | Q54: IVAFE | R54: Imposta sul valore delle attivit_x001A_ finanziarie detenute all'estero dalle persone fisiche residenti nel territorio dello stato - art. 19, c.18, dl. n. 201/2011 conv., con modif., dalla l. n. 214/2011, e succ. modif. - acc.seconda rata o acc. in unica soluz. | S54: 8908 | U54: 1
P55: 4049 | Q55: Exit Tax - IRPEF - 1a rata | R55: Imposta rateizzata sulla plusvalenza da exit-tax di cui all'articolo 166 del tuir-IRPEF | S55: 8908 | U55: 1
P56: 4200 | Q56: Tassazione separata | R56: Acconto imposte sui redditi soggetti a tassazione separata (quadro RM) | S56: 8908 | U56: 1
P57: 4723 | Q57: Tassazione separata CFC | R57: Imposta sul reddito prodotto da imprese estere controllate.art. 127 bis del tuir - soggetti IRPEF - primo acconto | S57: 8908 | T57: 1793 | U57: 1
P58: 4724 | Q58: Tassazione separata CFC | R58: Imposta sul reddito prodotto da imprese estere controllate.art. 127 bis del tuir - soggetti IRPEF - secondo acconto | S58: 8908 | U58: 1
P59: 6001 | Q59: VERSAMENTO IVA | R59: VERSAMENTO IVA MENSILE GENNAIO | S59: 8904 | T59: 1991 | U59: 1
P60: 6002 | Q60: VERSAMENTO IVA | R60: VERSAMENTO IVA MENSILE FEBBRAIO | S60: 8904 | T60: 1991 | U60: 1
P61: 6003 | Q61: VERSAMENTO IVA | R61: VERSAMENTO IVA MENSILE MARZO | S61: 8904 | T61: 1991 | U61: 1
P62: 6004 | Q62: VERSAMENTO IVA | R62: VERSAMENTO IVA MENSILE APRILE | S62: 8904 | T62: 1991 | U62: 1
P63: 6005 | Q63: VERSAMENTO IVA | R63: VERSAMENTO IVA MENSILE MAGGIO | S63: 8904 | T63: 1991 | U63: 1
P64: 6006 | Q64: VERSAMENTO IVA | R64: VERSAMENTO IVA MENSILE GIUGNO | S64: 8904 | T64: 1991 | U64: 1
P65: 6007 | Q65: VERSAMENTO IVA | R65: VERSAMENTO IVA MENSILE LUGLIO | S65: 8904 | T65: 1991 | U65: 1
P66: 6008 | Q66: VERSAMENTO IVA | R66: VERSAMENTO IVA MENSILE AGOSTO | S66: 8904 | T66: 1991 | U66: 1
P67: 6009 | Q67: VERSAMENTO IVA | R67: VERSAMENTO IVA MENSILE SETTEMBRE | S67: 8904 | T67: 1991 | U67: 1
P68: 6010 | Q68: VERSAMENTO IVA | R68: VERSAMENTO IVA MENSILE OTTOBRE | S68: 8904 | T68: 1991 | U68: 1
P69: 6011 | Q69: VERSAMENTO IVA | R69: VERSAMENTO IVA MENSILE NOVEMBRE | S69: 8904 | T69: 1991 | U69: 1
P70: 6012 | Q70: VERSAMENTO IVA | R70: VERSAMENTO IVA MENSILE DICEMBRE | S70: 8904 | T70: 1991 | U70: 1
... P79: 6494 | Q79: VERSAMENTO IVA | R79: IVA ADEGUAMENTO STUDI DI SETTORE | S79: 8904 | T79: 1991 | U79: 1
P80: 6497 | Q80: Regime di vantaggio/Ex minimi - Rettifica della detrazione IVA | R80: IVA derivante da rettifica della detrazione per i contribuenti minimi di cui all'articolo 1 commi da 96 a 117 della legge 24/12/2007 n. 244 - ris. 80/e del 06/03/2008 | S80: 8904 | T80: 1991 | U80: 1
P81: 8055 | Q81: Quadro RT - RT105 e RT106 - Rivalutazione partecipazioni | R81: Imposta sostitutiva delle imposte sui redditi per la rideterminazione dei valori di acquisto di partecipazioni non negoziate nei mercati regolamentati | S81: 8913 | T81: 1992 | U81: 1
P82: 8056 | Q82: Quadro RM, sez. X - rivalutazione terreni | R82: Imposta sostitutiva delle imposte sui redditi per la rideterminazione dei valori di acquisto dei terreni edificabili e con destinazione agricola | S82: 8913 | T82: 1992 | U82: 1
P83: 9001 | Q83: Artt. 36 bis - 54 bis (Imposte) | R83: Artt. 36 bis - 54 bis (Imposte) | S83: 8929 | T83: 1980 | U83: 1
P84: 9002 | Q84: Artt. 36 bis - 54 bis (Interessi) | R84: Artt. 36 bis - 54 bis (Interessi) | S84: 8929 | T84: 1980 | U84: 1
P85: 107T | Q85: IMPOSTA DI REGISTRO | R85: IMPOSTA DI REGISTRO PER CONTRATTI DI LOCAZIONE FABBRICATI INTERO PERIODO | S85: 671T | T85: 731T | U85: 5
P86: 109T | Q86: IMPOSTA DI REGISTRO | R86: IMPOSTA DI REGISTRO PER CESSIONI CONTRATTI DI LOCAZIONE (SE SI SCEGLIE IL PAGAMENTO ANNUALE) | S86: 671T | T86: 731T | U86: 5
P87: 110T | Q87: IMPOSTA DI REGISTRO | R87: IMPOSTA DI REGISTRO PER CESSIONI CONTRATTI DI LOCAZIONE (SE SI SCEGLIE DI PAGARE L'INTERO PERIODO) | S87: 671T | T87: 731T | U87: 5
P88: 112T | Q88: IMPOSTA DI REGISTRO | R88: IMPOSTA DI REGISTRO PER CONTRATTI DI LOCAZIONE FABBRICATI ANNUALITA' SUCESSIVE | S88: 671T | T88: 731T | U88: 5
P89: 113T | Q89: IMPOSTA DI REGISTRO | R89: IMPOSTA DI REGISTRO PER RISOLUZIONI (CONTRATTI DI LOCAZIONE E AFFITTI) | S89: 671T | T89: 731T | U89: 5
P90: 114T | Q90: IMPOSTA DI REGISTRO | R90: IMPOSTA DI REGISTRO PER PROROGHE (CONTRATTI DI LOCAZIONE E AFFITTO) | S90: 671T | T90: 731T | U90: 5
P91: 115T | Q91: IMPOSTA DI REGISTRO | R91: IMPOSTA DI REGISTRO PER CONTRATTI DI LOCAZIONE FABBRICATI PRIMA ANNUALITA' | S91: 671T | T91: 731T | U91: 5
P92: 455T | Q92: IMPOSTA DI BOLLO | R92: IMPOSTA DI BOLLO - ACCONTO | S92: 675T | T92: 731T | U92: 5
P93: 649T | Q93: IMPOSTA IPOTECARIA | R93: IMPOSTE E TASSE IPOTECARIE E CATASTALI | S93: 674T | T93: 731T | U93: 5
P94: A00D | Q94: Equitalia | R94: Dogane - dazi ed altri diritti C.E.E.
P95: A00D | Q95: Equitalia | R95: Zoll-Zollamt und and.Gebuehren EU
P96: A101 | Q96: Equitalia | R96: Imposta sulle assicurazioni
P97: A101 | Q97: Equitalia | R97: Abgabe auf Versicherungen
P98: A103 | Q98: Equitalia | R98: Imposta sulle assicurazioni - interessi
P99: A103 | Q99: Equitalia | R99: Abgabe auf Versicherungen - Zinsen
P100: A104 | Q100: Equitalia | R100: Imposta e contributi sulle assicurazioni - sanzione
P101: A104 | Q101: Equitalia | R101: Abgaben und Beiträge Versicherungen - Strafe
P102: A105 | Q102: Equitalia | R102: Contributo fondo antiracket sulle assicurazioni
P103: A105 | Q103: Equitalia | R103: Beitrag Fonds gegen org. Kriminalität auf Versicherungen
P104: A106 | Q104: Equitalia | R104: Contributo fondo antiracket sulle assicurazioni - interessi
P105: A106 | Q105: Equitalia | R105: Beitrag Fonds gegen org. Kriminalität auf Versicherungen - Zinsen
... P20375: 9B7T | Q20375: Equitalia | R20375: Fuersorge-Vorsorgefond der Stadtpolizisten
P20376: 1600 | R20376: Soprattasse e pene pecuniarie (pendenze e controversie tributarie).
P20377: 3816 | R20377: Addizionale comunale all'IRPEF trattenuta dal sostituto d'imposta - saldo.
...
