Workbook

Sheet INPUT DATI
A1: IPERAMMORTAMENTO
A4: SEZIONE A - DATI IDENTIFICATIVI IMPRESA
A5: Denominazione impresa: | B5: Alfa S.r.l. | F5: Forma giuridica:
A6: Partita IVA: | B6: 3456780123 | F6: Codice fiscale:
A7: Settore attività: | B7: Costruzioni e ristrutturazioni | F7: Codice ATECO:
A9: SEZIONE B- REQUISITI SOGGETTIVI (tutti obbligatori)
A10: Rispetto normative sicurezza luoghi di lavoro (D.Lgs. 81/2008): | B10: SI | D10: Esito: | E10: =IF(B10="SI","✓ Requisito soddisfatto","✗ REQUISITO NON SODDISFATTO") -> ✓ Requisito soddisfatto
A11: Corretto versamento contributi previdenziali e assistenziali: | B11: SI | D11: Esito: | E11: =IF(B11="SI","✓ Requisito soddisfatto","✗ REQUISITO NON SODDISFATTO") -> ✓ Requisito soddisfatto
A12: Impresa NON in liquidazione/fallimento/concordato s. continuità: | B12: SI | D12: Esito: | E12: =IF(B12="SI","✓ Requisito soddisfatto","✗ REQUISITO NON SODDISFATTO") -> ✓ Requisito soddisfatto
A13: Impresa NON destinataria sanzioni interdittive D.Lgs. 231/2001: | B13: SI | D13: Esito: | E13: =IF(B13="SI","✓ Requisito soddisfatto","✗ REQUISITO NON SODDISFATTO") -> ✓ Requisito soddisfatto
A15: VERIFICA COMPLESSIVA REQUISITI: | C15: =IF(AND(B10="SI",B11="SI",B12="SI",B13="SI"),"✓ TUTTI I REQUISITI SODDISFATTI - IMPRESA AMMISSIBILE","✗ REQUISITI NON SODDISFATTI - VERIFICARE ANOMALIE") -> ✓ TUTTI I REQUISITI SODDISFATTI - IMPRESA AMMISSIBILE
A17: SEZIONE C - TABELLA INVESTIMENTI
A18: N. | B18: Descrizione bene | C18: Categoria bene | D18: Costo acquisizione (€) | E18: Aliquota Fiscale | F18: Contributi/Sovvenzioni (€) | G18: Base imponibile netta (€) | H18: Origine UE/SEE | I18: Data Investimento | J18: Validazione | K18: Anno d'Imposta Investimento | L18: Validazione
A19: 1 | B19: Macchinario interconnesso industria 4.0 | C19: Beni materiali 4.0 - All. IV | D19: 480000 | E19: 0.1 | F19: 0 | G19: =IF(D19="","",D19-IF(F19="",0,F19)) -> 480000 | H19: SI | I19: 46063 | J19: =IF(I19="","-",IF(AND(I19>=DATE(2026,1,1),I19<=DATE(2028,9,30)),"✓ Data nel periodo agevolato","✗ Data fuori periodo (01.01.2026 - 30.09.2028)")) -> ✓ Data nel periodo agevolato | K19: 2026 | L19: =IF(K19="","-",IF(AND(K19>=2026,K19<=2028),"✓ Anno valido","✗ Anno non valido")) -> ✓ Anno valido
A20: 2 | B20: Sistema di visione artificiale controllo qualità | C20: Beni materiali 4.0 - All. IV | D20: 95000 | E20: 0.12 | F20: 0 | G20: =IF(D20="","",D20-IF(F20="",0,F20)) -> 95000 | H20: SI | I20: 46109 | J20: =IF(I20="","-",IF(AND(I20>=DATE(2026,1,1),I20<=DATE(2028,9,30)),"✓ Data nel periodo agevolato","✗ Data fuori periodo (01.01.2026 - 30.09.2028)")) -> ✓ Data nel periodo agevolato | K20: 2026
A21: 3 | G21: =IF(D21="","",D21-IF(F21="",0,F21)) | J21: =IF(I21="","-",IF(AND(I21>=DATE(2026,1,1),I21<=DATE(2028,9,30)),"✓ Data nel periodo agevolato","✗ Data fuori periodo (01.01.2026 - 30.09.2028)")) -> - | L21: =IF(K21="","-",IF(AND(K21>=2026,K21<=2028),"✓ Anno valido","✗ Anno non valido")) -> -
A22: 4 | G22: =IF(D22="","",D22-IF(F22="",0,F22)) | J22: =IF(I22="","-",IF(AND(I22>=DATE(2026,1,1),I22<=DATE(2028,9,30)),"✓ Data nel periodo agevolato","✗ Data fuori periodo (01.01.2026 - 30.09.2028)")) -> - | L22: =IF(K22="","-",IF(AND(K22>=2026,K22<=2028),"✓ Anno valido","✗ Anno non valido")) -> -
A23: 5 | G23: =IF(D23="","",D23-IF(F23="",0,F23)) | J23: =IF(I23="","-",IF(AND(I23>=DATE(2026,1,1),I23<=DATE(2028,9,30)),"✓ Data nel periodo agevolato","✗ Data fuori periodo (01.01.2026 - 30.09.2028)")) -> - | L23: =IF(K23="","-",IF(AND(K23>=2026,K23<=2028),"✓ Anno valido","✗ Anno non valido")) -> -
A24: 6 | G24: =IF(D24="","",D24-IF(F24="",0,F24)) | J24: =IF(I24="","-",IF(AND(I24>=DATE(2026,1,1),I24<=DATE(2028,9,30)),"✓ Data nel periodo agevolato","✗ Data fuori periodo (01.01.2026 - 30.09.2028)")) -> - | L24: =IF(K24="","-",IF(AND(K24>=2026,K24<=2028),"✓ Anno valido","✗ Anno non valido")) -> -
A25: 7 | G25: =IF(D25="","",D25-IF(F25="",0,F25)) | J25: =IF(I25="","-",IF(AND(I25>=DATE(2026,1,1),I25<=DATE(2028,9,30)),"✓ Data nel periodo agevolato","✗ Data fuori periodo (01.01.2026 - 30.09.2028)")) -> - | L25: =IF(K25="","-",IF(AND(K25>=2026,K25<=2028),"✓ Anno valido","✗ Anno non valido")) -> -
A26: 8 | G26: =IF(D26="","",D26-IF(F26="",0,F26)) | J26: =IF(I26="","-",IF(AND(I26>=DATE(2026,1,1),I26<=DATE(2028,9,30)),"✓ Data nel periodo agevolato","✗ Data fuori periodo (01.01.2026 - 30.09.2028)")) -> - | L26: =IF(K26="","-",IF(AND(K26>=2026,K26<=2028),"✓ Anno valido","✗ Anno non valido")) -> -
A27: 9 | G27: =IF(D27="","",D27-IF(F27="",0,F27)) | J27: =IF(I27="","-",IF(AND(I27>=DATE(2026,1,1),I27<=DATE(2028,9,30)),"✓ Data nel periodo agevolato","✗ Data fuori periodo (01.01.2026 - 30.09.2028)")) -> - | L27: =IF(K27="","-",IF(AND(K27>=2026,K27<=2028),"✓ Anno valido","✗ Anno non valido")) -> -
A28: 10 | G28: =IF(D28="","",D28-IF(F28="",0,F28)) | J28: =IF(I28="","-",IF(AND(I28>=DATE(2026,1,1),I28<=DATE(2028,9,30)),"✓ Data nel periodo agevolato","✗ Data fuori periodo (01.01.2026 - 30.09.2028)")) -> - | L28: =IF(K28="","-",IF(AND(K28>=2026,K28<=2028),"✓ Anno valido","✗ Anno non valido")) -> -
B29: TOTALE | D29: =SUM(D19:D28) -> 575000 | F29: =SUM(F19:F28) -> 0 | G29: =SUM(G19:G28) -> 575000
A31: SEZIONE D - PARAMETRI FISCALI
A32: Aliquota IRES: | B32: 0.24 | D32: (standard 24%)
A33: Tasso di attualizzazione: | B33: 0.05 | D33: (per calcolo VAN beneficio)
A34: Anno inizio ammortamento: | B34: 2026 | D34: (anno entrata in funzione bene)
A36: NOTA: Le celle con sfondo giallo sono celle di input modificabili.
A37: I valori in BLU sono dati inseriti dall'utente. I valori in NERO sono formule calcolate.
A38: Riferimento normativo: L. 199/2025, art. 1, commi 427-436

Sheet DOCUMENTAZIONE
A1: DOCUMENTAZIONE E CHECKLIST ADEMPIMENTI
A2: Checklist completa degli adempimenti per l'accesso al beneficio - L. 199/2025
A4: CHECKLIST ADEMPIMENTI OBBLIGATORI
A5: N. | B5: Adempimento | C5: Stato | D5: Inv.1 | E5: Inv.2 | F5: Inv.3 | G5: Inv.4 | H5: Inv.5 | I5: Inv.6 | J5: Inv.7 | K5: Inv.8 | L5: Inv.9 | M5: Inv.10 | N5: Note / Riferimento
A6: 1 | B6: Verifica origine UE/SEE beni (certificato CCIAA / dichiarazione produttore DPR 445/2000) | D6: FATTO | E6: FATTO | N6: Dichiarazione produttore
A7: 2 | B7: Perizia tecnica giurata per beni interconnessi (se costo > €300.000) | D7: FATTO | E7: N/A | N7: Perizia Ing.
A8: 3 | B8: Conservazione ordine fornitore con data certa | D8: FATTO | E8: FATTO | N8: Ordini firmati digitalmente
A9: 4 | B9: Conservazione fattura/e di acquisto | D9: FATTO | E9: FATTO | N9: Fatture elettroniche
A10: 5 | B10: Conservazione documenti di pagamento (bonifico, assegno, ecc.) | D10: FATTO | E10: FATTO | N10: Bonifico bancario
A11: 6 | B11: Verbale di consegna e messa in funzione del bene | D11: FATTO | E11: FATTO | N11: Verbali interni
A12: 7 | B12: Documentazione interconnessione bene al sistema aziendale | D12: FATTO | E12: FATTO | N12: Report tecnico IT
A13: 8 | B13: Per software: documentazione funzionale e prova interconnessione | D13: N/A | E13: N/A | N13: Software MES e analytics
A14: 9 | B14: Comunicazione/certificazione GSE (da definire con decreto attuativo) | D14: N/A | E14: N/A | N14: Non applicabile
A15: 10 | B15: DURC (Documento Unico di Regolarità Contributiva) in corso di validità | C15: FATTO | N15: DURC regolare
A16: 11 | B16: DVR (Documento Valutazione Rischi) aggiornato e conforme D.Lgs. 81/2008 | C16: FATTO | N16: Aggiornato 2026
A17: 12 | B17: Modello autocertificazione requisiti (da predisporre entro fine periodo d'imposta) | C17: FATTO | N17: Dichiarazione legale rappresentante
A21: DOCUMENTI DA CONSERVARE PER 10 ANNI
A22: 1. Ordini di acquisto con data certa e conferma d'ordine
A23: 2. Fatture di acquisto (originali o copie conformi)
A24: 3. Documenti di pagamento (estratti conto, bonifici)
A25: 4. Perizia tecnica giurata / dichiarazione resa dal legale rappresentante
A26: 5. Certificazione di interconnessione al sistema aziendale
A27: 6. DVR e DURC validi al momento dell'investimento
A28: 7. Dichiarazioni dei redditi relative ai periodi di fruizione
A29: 8. Documentazione attestante origine UE/SEE dei beni
A30: 9. Eventuale certificazione GSE per impianti rinnovabili
A31: 10. Contratti di fornitura e condizioni generali

Sheet CALCOLO MAGGIORAZIONI
A1: CALCOLO MAGGIORAZIONI - IPERAMMORTAMENTO L. 199/2025
A2: Calcolo automatico degli scaglioni e delle maggiorazioni per ciascun investimento
A4: N. | B4: Descrizione | C4: Categoria | D4: Costo acquis. (€) | E4: Contributi (€) | F4: Base netta (€) | G4: Scagl. 1 Base (€) | H4: Scagl. 1 Magg. (€) | I4: Scagl. 2 Base (€) | J4: Scagl. 2 Magg. (€) | K4: Scagl. 3 Base (€) | L4: Scagl. 3 Magg. (€) | M4: Scagl. 4 Base (€) | N4: Scagl. 4 Magg. (€) | O4: Tot. Maggioraz. (€) | P4: Costo fiscale tot. (€) | Q4: % Magg. effettiva | R4: Tot.Risparmio Attualizzato
A5: ='INPUT DATI'!A19 -> 1 | B5: ='INPUT DATI'!B19 -> Macchinario interconnesso industria 4.0 | C5: ='INPUT DATI'!C19 -> Beni materiali 4.0 - All. IV | D5: ='INPUT DATI'!D19 -> 480000 | E5: ='INPUT DATI'!F19 -> 0 | F5: ='INPUT DATI'!G19 -> 480000 | G5: =IF(F5="","",MIN(F5,2500000)) -> 480000 | H5: =IF(G5="","",G5*IF(OR(C5="Beni materiali 4.0 - All. IV",C5="Beni immateriali 4.0 - All. V",C5="Impianti energie rinnovabili"),1.8,0)) -> 864000 | I5: =IF(F5="","",MAX(0,MIN(F5,10000000)-2500000)) -> 0 | J5: =IF(I5="","",I5*IF(OR(C5="Beni materiali 4.0 - All. IV",C5="Beni immateriali 4.0 - All. V",C5="Impianti energie rinnovabili"),1,0)) -> 0 | K5: =IF(F5="","",MAX(0,MIN(F5,20000000)-10000000)) -> 0 | L5: =IF(K5="","",K5*IF(OR(C5="Beni materiali 4.0 - All. IV",C5="Beni immateriali 4.0 - All. V",C5="Impianti energie rinnovabili"),0.5,0)) -> 0 | M5: =IF(F5="","",MAX(0,F5-20000000)) -> 0 | N5: =IF(M5="","",M5*0) -> 0 | O5: =IF(F5="","",H5+J5+L5+N5) -> 864000 | P5: =IF(F5="","",F5+O5) -> 1344000 | Q5: =IF(F5="","",IF(F5=0,0,O5/F5)) -> 1.8 | R5: {=+_xlfn.XLOOKUP(A5:A14,'PIANO AMMORTAMENTO'!B38:B47,'PIANO AMMORTAMENTO'!C38:C47,,0,1)} -> 164120.84
A6: ='INPUT DATI'!A20 -> 2 | B6: ='INPUT DATI'!B20 -> Sistema di visione artificiale controllo qualità | C6: ='INPUT DATI'!C20 -> Beni materiali 4.0 - All. IV | D6: ='INPUT DATI'!D20 -> 95000 | E6: ='INPUT DATI'!F20 -> 0 | F6: ='INPUT DATI'!G20 -> 95000 | G6: =IF(F6="","",MIN(F6,2500000)) -> 95000 | H6: =IF(G6="","",G6*IF(OR(C6="Beni materiali 4.0 - All. IV",C6="Beni immateriali 4.0 - All. V",C6="Impianti energie rinnovabili"),1.8,0)) -> 171000 | I6: =IF(F6="","",MAX(0,MIN(F6,10000000)-2500000)) -> 0 | J6: =IF(I6="","",I6*IF(OR(C6="Beni materiali 4.0 - All. IV",C6="Beni immateriali 4.0 - All. V",C6="Impianti energie rinnovabili"),1,0)) -> 0 | K6: =IF(F6="","",MAX(0,MIN(F6,20000000)-10000000)) -> 0 | L6: =IF(K6="","",K6*IF(OR(C6="Beni materiali 4.0 - All. IV",C6="Beni immateriali 4.0 - All. V",C6="Impianti energie rinnovabili"),0.5,0)) -> 0 | M6: =IF(F6="","",MAX(0,F6-20000000)) -> 0 | N6: =IF(M6="","",M6*0) -> 0 | O6: =IF(F6="","",H6+J6+L6+N6) -> 171000 | P6: =IF(F6="","",F6+O6) -> 266000 | Q6: =IF(F6="","",IF(F6=0,0,O6/F6)) -> 1.8 | R6: 33736.88
A7: ='INPUT DATI'!A21 -> 3 | B7: ='INPUT DATI'!B21 -> 0 | C7: ='INPUT DATI'!C21 -> 0 | D7: ='INPUT DATI'!D21 -> 0 | E7: ='INPUT DATI'!F21 -> 0 | F7: ='INPUT DATI'!G21 | G7: =IF(F7="","",MIN(F7,2500000)) | H7: =IF(G7="","",G7*IF(OR(C7="Beni materiali 4.0 - All. IV",C7="Beni immateriali 4.0 - All. V",C7="Impianti energie rinnovabili"),1.8,0)) | I7: =IF(F7="","",MAX(0,MIN(F7,10000000)-2500000)) | J7: =IF(I7="","",I7*IF(OR(C7="Beni materiali 4.0 - All. IV",C7="Beni immateriali 4.0 - All. V",C7="Impianti energie rinnovabili"),1,0)) | K7: =IF(F7="","",MAX(0,MIN(F7,20000000)-10000000)) | L7: =IF(K7="","",K7*IF(OR(C7="Beni materiali 4.0 - All. IV",C7="Beni immateriali 4.0 - All. V",C7="Impianti energie rinnovabili"),0.5,0)) | M7: =IF(F7="","",MAX(0,F7-20000000)) | N7: =IF(M7="","",M7*0) | O7: =IF(F7="","",H7+J7+L7+N7) | P7: =IF(F7="","",F7+O7) | Q7: =IF(F7="","",IF(F7=0,0,O7/F7)) | R7: 0
A8: ='INPUT DATI'!A22 -> 4 | B8: ='INPUT DATI'!B22 -> 0 | C8: ='INPUT DATI'!C22 -> 0 | D8: ='INPUT DATI'!D22 -> 0 | E8: ='INPUT DATI'!F22 -> 0 | F8: ='INPUT DATI'!G22 | G8: =IF(F8="","",MIN(F8,2500000)) | H8: =IF(G8="","",G8*IF(OR(C8="Beni materiali 4.0 - All. IV",C8="Beni immateriali 4.0 - All. V",C8="Impianti energie rinnovabili"),1.8,0)) | I8: =IF(F8="","",MAX(0,MIN(F8,10000000)-2500000)) | J8: =IF(I8="","",I8*IF(OR(C8="Beni materiali 4.0 - All. IV",C8="Beni immateriali 4.0 - All. V",C8="Impianti energie rinnovabili"),1,0)) | K8: =IF(F8="","",MAX(0,MIN(F8,20000000)-10000000)) | L8: =IF(K8="","",K8*IF(OR(C8="Beni materiali 4.0 - All. IV",C8="Beni immateriali 4.0 - All. V",C8="Impianti energie rinnovabili"),0.5,0)) | M8: =IF(F8="","",MAX(0,F8-20000000)) | N8: =IF(M8="","",M8*0) | O8: =IF(F8="","",H8+J8+L8+N8) | P8: =IF(F8="","",F8+O8) | Q8: =IF(F8="","",IF(F8=0,0,O8/F8)) | R8: 0
A9: ='INPUT DATI'!A23 -> 5 | B9: ='INPUT DATI'!B23 -> 0 | C9: ='INPUT DATI'!C23 -> 0 | D9: ='INPUT DATI'!D23 -> 0 | E9: ='INPUT DATI'!F23 -> 0 | F9: ='INPUT DATI'!G23 | G9: =IF(F9="","",MIN(F9,2500000)) | H9: =IF(G9="","",G9*IF(OR(C9="Beni materiali 4.0 - All. IV",C9="Beni immateriali 4.0 - All. V",C9="Impianti energie rinnovabili"),1.8,0)) | I9: =IF(F9="","",MAX(0,MIN(F9,10000000)-2500000)) | J9: =IF(I9="","",I9*IF(OR(C9="Beni materiali 4.0 - All. IV",C9="Beni immateriali 4.0 - All. V",C9="Impianti energie rinnovabili"),1,0)) | K9: =IF(F9="","",MAX(0,MIN(F9,20000000)-10000000)) | L9: =IF(K9="","",K9*IF(OR(C9="Beni materiali 4.0 - All. IV",C9="Beni immateriali 4.0 - All. V",C9="Impianti energie rinnovabili"),0.5,0)) | M9: =IF(F9="","",MAX(0,F9-20000000)) | N9: =IF(M9="","",M9*0) | O9: =IF(F9="","",H9+J9+L9+N9) | P9: =IF(F9="","",F9+O9) | Q9: =IF(F9="","",IF(F9=0,0,O9/F9)) | R9: 0
A10: ='INPUT DATI'!A24 -> 6 | B10: ='INPUT DATI'!B24 -> 0 | C10: ='INPUT DATI'!C24 -> 0 | D10: ='INPUT DATI'!D24 -> 0 | E10: ='INPUT DATI'!F24 -> 0 | F10: ='INPUT DATI'!G24 | G10: =IF(F10="","",MIN(F10,2500000)) | H10: =IF(G10="","",G10*IF(OR(C10="Beni materiali 4.0 - All. IV",C10="Beni immateriali 4.0 - All. V",C10="Impianti energie rinnovabili"),1.8,0)) | I10: =IF(F10="","",MAX(0,MIN(F10,10000000)-2500000)) | J10: =IF(I10="","",I10*IF(OR(C10="Beni materiali 4.0 - All. IV",C10="Beni immateriali 4.0 - All. V",C10="Impianti energie rinnovabili"),1,0)) | K10: =IF(F10="","",MAX(0,MIN(F10,20000000)-10000000)) | L10: =IF(K10="","",K10*IF(OR(C10="Beni materiali 4.0 - All. IV",C10="Beni immateriali 4.0 - All. V",C10="Impianti energie rinnovabili"),0.5,0)) | M10: =IF(F10="","",MAX(0,F10-20000000)) | N10: =IF(M10="","",M10*0) | O10: =IF(F10="","",H10+J10+L10+N10) | P10: =IF(F10="","",F10+O10) | Q10: =IF(F10="","",IF(F10=0,0,O10/F10)) | R10: 0
A11: ='INPUT DATI'!A25 -> 7 | B11: ='INPUT DATI'!B25 -> 0 | C11: ='INPUT DATI'!C25 -> 0 | D11: ='INPUT DATI'!D25 -> 0 | E11: ='INPUT DATI'!F25 -> 0 | F11: ='INPUT DATI'!G25 | G11: =IF(F11="","",MIN(F11,2500000)) | H11: =IF(G11="","",G11*IF(OR(C11="Beni materiali 4.0 - All. IV",C11="Beni immateriali 4.0 - All. V",C11="Impianti energie rinnovabili"),1.8,0)) | I11: =IF(F11="","",MAX(0,MIN(F11,10000000)-2500000)) | J11: =IF(I11="","",I11*IF(OR(C11="Beni materiali 4.0 - All. IV",C11="Beni immateriali 4.0 - All. V",C11="Impianti energie rinnovabili"),1,0)) | K11: =IF(F11="","",MAX(0,MIN(F11,20000000)-10000000)) | L11: =IF(K11="","",K11*IF(OR(C11="Beni materiali 4.0 - All. IV",C11="Beni immateriali 4.0 - All. V",C11="Impianti energie rinnovabili"),0.5,0)) | M11: =IF(F11="","",MAX(0,F11-20000000)) | N11: =IF(M11="","",M11*0) | O11: =IF(F11="","",H11+J11+L11+N11) | P11: =IF(F11="","",F11+O11) | Q11: =IF(F11="","",IF(F11=0,0,O11/F11)) | R11: 0
A12: ='INPUT DATI'!A26 -> 8 | B12: ='INPUT DATI'!B26 -> 0 | C12: ='INPUT DATI'!C26 -> 0 | D12: ='INPUT DATI'!D26 -> 0 | E12: ='INPUT DATI'!F26 -> 0 | F12: ='INPUT DATI'!G26 | G12: =IF(F12="","",MIN(F12,2500000)) | H12: =IF(G12="","",G12*IF(OR(C12="Beni materiali 4.0 - All. IV",C12="Beni immateriali 4.0 - All. V",C12="Impianti energie rinnovabili"),1.8,0)) | I12: =IF(F12="","",MAX(0,MIN(F12,10000000)-2500000)) | J12: =IF(I12="","",I12*IF(OR(C12="Beni materiali 4.0 - All. IV",C12="Beni immateriali 4.0 - All. V",C12="Impianti energie rinnovabili"),1,0)) | K12: =IF(F12="","",MAX(0,MIN(F12,20000000)-10000000)) | L12: =IF(K12="","",K12*IF(OR(C12="Beni materiali 4.0 - All. IV",C12="Beni immateriali 4.0 - All. V",C12="Impianti energie rinnovabili"),0.5,0)) | M12: =IF(F12="","",MAX(0,F12-20000000)) | N12: =IF(M12="","",M12*0) | O12: =IF(F12="","",H12+J12+L12+N12) | P12: =IF(F12="","",F12+O12) | Q12: =IF(F12="","",IF(F12=0,0,O12/F12)) | R12: 0
A13: ='INPUT DATI'!A27 -> 9 | B13: ='INPUT DATI'!B27 -> 0 | C13: ='INPUT DATI'!C27 -> 0 | D13: ='INPUT DATI'!D27 -> 0 | E13: ='INPUT DATI'!F27 -> 0 | F13: ='INPUT DATI'!G27 | G13: =IF(F13="","",MIN(F13,2500000)) | H13: =IF(G13="","",G13*IF(OR(C13="Beni materiali 4.0 - All. IV",C13="Beni immateriali 4.0 - All. V",C13="Impianti energie rinnovabili"),1.8,0)) | I13: =IF(F13="","",MAX(0,MIN(F13,10000000)-2500000)) | J13: =IF(I13="","",I13*IF(OR(C13="Beni materiali 4.0 - All. IV",C13="Beni immateriali 4.0 - All. V",C13="Impianti energie rinnovabili"),1,0)) | K13: =IF(F13="","",MAX(0,MIN(F13,20000000)-10000000)) | L13: =IF(K13="","",K13*IF(OR(C13="Beni materiali 4.0 - All. IV",C13="Beni immateriali 4.0 - All. V",C13="Impianti energie rinnovabili"),0.5,0)) | M13: =IF(F13="","",MAX(0,F13-20000000)) | N13: =IF(M13="","",M13*0) | O13: =IF(F13="","",H13+J13+L13+N13) | P13: =IF(F13="","",F13+O13) | Q13: =IF(F13="","",IF(F13=0,0,O13/F13)) | R13: 0
A14: ='INPUT DATI'!A28 -> 10 | B14: ='INPUT DATI'!B28 -> 0 | C14: ='INPUT DATI'!C28 -> 0 | D14: ='INPUT DATI'!D28 -> 0 | E14: ='INPUT DATI'!F28 -> 0 | F14: ='INPUT DATI'!G28 | G14: =IF(F14="","",MIN(F14,2500000)) | H14: =IF(G14="","",G14*IF(OR(C14="Beni materiali 4.0 - All. IV",C14="Beni immateriali 4.0 - All. V",C14="Impianti energie rinnovabili"),1.8,0)) | I14: =IF(F14="","",MAX(0,MIN(F14,10000000)-2500000)) | J14: =IF(I14="","",I14*IF(OR(C14="Beni materiali 4.0 - All. IV",C14="Beni immateriali 4.0 - All. V",C14="Impianti energie rinnovabili"),1,0)) | K14: =IF(F14="","",MAX(0,MIN(F14,20000000)-10000000)) | L14: =IF(K14="","",K14*IF(OR(C14="Beni materiali 4.0 - All. IV",C14="Beni immateriali 4.0 - All. V",C14="Impianti energie rinnovabili"),0.5,0)) | M14: =IF(F14="","",MAX(0,F14-20000000)) | N14: =IF(M14="","",M14*0) | O14: =IF(F14="","",H14+J14+L14+N14) | P14: =IF(F14="","",F14+O14) | Q14: =IF(F14="","",IF(F14=0,0,O14/F14)) | R14: 0
B15: TOTALE | D15: =SUM(D5:D14) -> 575000 | E15: =SUM(E5:E14) -> 0 | F15: =SUM(F5:F14) -> 575000 | G15: =SUM(G5:G14) -> 575000 | H15: =SUM(H5:H14) -> 1035000 | I15: =SUM(I5:I14) -> 0 | J15: =SUM(J5:J14) -> 0 | K15: =SUM(K5:K14) -> 0 | ... P15: =SUM(P5:P14) -> 1610000 | Q15: =IF(F15=0,0,O15/F15) -> 1.8 | R15: =+SUM(_xlfn.ANCHORARRAY(R5)) -> 197857.72

Sheet PIANO AMMORTAMENTO
A1: PIANO DI AMMORTAMENTO FISCALE MAGGIORATO
A2: Calcolo ammortamento civilistico e fiscale con deduzione aggiuntiva e risparmio d'imposta
A4: PARAMETRI AMMORTAMENTO INVESTIMENTO
A5: Seleziona investimento (N.): | B5: 2 | D5: Descrizione: | E5: {=IF(B5="","",INDEX('INPUT DATI'!B19:B28,B5))} -> Sistema di visione artificiale controllo qualità | H5: Categoria: | I5: {=IF(B5="","",INDEX('INPUT DATI'!C19:C28,B5))} -> Beni materiali 4.0 - All. IV
A6: Costo storico: | B6: {=IF(B5="",0,IFERROR(INDEX('INPUT DATI'!D19:D28,B5),0))} -> 95000 | D6: Base netta (al netto contributi): | E6: {=IFERROR(IF(B5="",0,INDEX('INPUT DATI'!G19:G28,B5)+0),0)} -> 95000 | H6: Costo fiscale maggiorato: | I6: {=IFERROR(IF(B5="",0,INDEX('CALCOLO MAGGIORAZIONI'!P5:P14,B5)+0),0)} -> 266000
A7: Aliquota ammortamento civilistico: | B7: =E7 -> 0.12 | D7: Coefficiente fiscale: | E7: =_xlfn.XLOOKUP(B5,'INPUT DATI'!A19:A28,'INPUT DATI'!E19:E28,,0,1) -> 0.12 | H7: Vita utile (anni): | I7: =IF(E7=0,0,ROUNDUP(1/E7,0)) -> 9
A8: Aliquota IRES: | B8: ='INPUT DATI'!B32 -> 0.24 | H8: Totale maggiorazione: | I8: {=IFERROR(IF(B5="",0,INDEX('CALCOLO MAGGIORAZIONI'!O5:O14,B5)+0),0)} -> 171000
A10: PIANO DI AMMORTAMENTO DETTAGLIATO
A11: Anno | B11: Costo storico | C11: Quota amm. civilist. | D11: Fondo amm. civilist. | E11: Valore netto cont. | F11: Costo fiscale magg. | G11: Quota amm. fiscale | H11: Deduzione aggiuntiva | I11: Risparmio IRES (€) | J11: Risparmio totale Attuallizzato(€)
A12: ='INPUT DATI'!B34 -> 2026 | B12: =$E$6 -> 95000 | C12: =IF($E$6=0,0,$E$6*$B$7/2) -> 5700 | D12: =C12 -> 5700 | E12: =MAX(0,B12-D12) -> 89300 | F12: =$I$6 -> 266000 | G12: =IF($I$6=0,0,$I$6*$E$7/2) -> 15960 | H12: =MAX(0,G12-C12) -> 10260 | I12: =H12*$B$8 -> 2462.4 | J12: =I12 -> 2462.4
A13: =A12+1 -> 2027 | B13: =$E$6 -> 95000 | C13: =IF($E$6=0,0,MIN($E$6*$B$7,MAX(0,$E$6-D12))) -> 11400 | D13: =D12+C13 -> 17100 | E13: =MAX(0,B13-D13) -> 77900 | F13: =$I$6 -> 266000 | G13: =IF($I$6=0,0,MIN($I$6*$E$7,MAX(0,$I$6-SUM($G$12:G12)))) -> 31920 | H13: =MAX(0,G13-C13) -> 20520 | I13: =H13*$B$8 -> 4924.8 | J13: =I13*(1+'INPUT DATI'!$B$33)^-('PIANO AMMORTAMENTO'!A13-'PIANO AMMORTAMENTO'!$A$12) -> 4690.2857
A14: =A13+1 -> 2028 | B14: =$E$6 -> 95000 | C14: =IF($E$6=0,0,MIN($E$6*$B$7,MAX(0,$E$6-D13))) -> 11400 | D14: =D13+C14 -> 28500 | E14: =MAX(0,B14-D14) -> 66500 | F14: =$I$6 -> 266000 | G14: =IF($I$6=0,0,MIN($I$6*$E$7,MAX(0,$I$6-SUM($G$12:G13)))) -> 31920 | H14: =MAX(0,G14-C14) -> 20520 | I14: =H14*$B$8 -> 4924.8 | J14: =I14*(1+'INPUT DATI'!$B$33)^-('PIANO AMMORTAMENTO'!A14-'PIANO AMMORTAMENTO'!$A$12) -> 4466.9388
A15: =A14+1 -> 2029 | B15: =$E$6 -> 95000 | C15: =IF($E$6=0,0,MIN($E$6*$B$7,MAX(0,$E$6-D14))) -> 11400 | D15: =D14+C15 -> 39900 | E15: =MAX(0,B15-D15) -> 55100 | F15: =$I$6 -> 266000 | G15: =IF($I$6=0,0,MIN($I$6*$E$7,MAX(0,$I$6-SUM($G$12:G14)))) -> 31920 | H15: =MAX(0,G15-C15) -> 20520 | I15: =H15*$B$8 -> 4924.8 | J15: =I15*(1+'INPUT DATI'!$B$33)^-('PIANO AMMORTAMENTO'!A15-'PIANO AMMORTAMENTO'!$A$12) -> 4254.2274
A16: =A15+1 -> 2030 | B16: =$E$6 -> 95000 | C16: =IF($E$6=0,0,MIN($E$6*$B$7,MAX(0,$E$6-D15))) -> 11400 | D16: =D15+C16 -> 51300 | E16: =MAX(0,B16-D16) -> 43700 | F16: =$I$6 -> 266000 | G16: =IF($I$6=0,0,MIN($I$6*$E$7,MAX(0,$I$6-SUM($G$12:G15)))) -> 31920 | H16: =MAX(0,G16-C16) -> 20520 | I16: =H16*$B$8 -> 4924.8 | J16: =I16*(1+'INPUT DATI'!$B$33)^-('PIANO AMMORTAMENTO'!A16-'PIANO AMMORTAMENTO'!$A$12) -> 4051.6451
A17: =A16+1 -> 2031 | B17: =$E$6 -> 95000 | C17: =IF($E$6=0,0,MIN($E$6*$B$7,MAX(0,$E$6-D16))) -> 11400 | D17: =D16+C17 -> 62700 | E17: =MAX(0,B17-D17) -> 32300 | F17: =$I$6 -> 266000 | G17: =IF($I$6=0,0,MIN($I$6*$E$7,MAX(0,$I$6-SUM($G$12:G16)))) -> 31920 | H17: =MAX(0,G17-C17) -> 20520 | I17: =H17*$B$8 -> 4924.8 | J17: =I17*(1+'INPUT DATI'!$B$33)^-('PIANO AMMORTAMENTO'!A17-'PIANO AMMORTAMENTO'!$A$12) -> 3858.7097
A18: =A17+1 -> 2032 | B18: =$E$6 -> 95000 | C18: =IF($E$6=0,0,MIN($E$6*$B$7,MAX(0,$E$6-D17))) -> 11400 | D18: =D17+C18 -> 74100 | E18: =MAX(0,B18-D18) -> 20900 | F18: =$I$6 -> 266000 | G18: =IF($I$6=0,0,MIN($I$6*$E$7,MAX(0,$I$6-SUM($G$12:G17)))) -> 31920 | H18: =MAX(0,G18-C18) -> 20520 | I18: =H18*$B$8 -> 4924.8 | J18: =I18*(1+'INPUT DATI'!$B$33)^-('PIANO AMMORTAMENTO'!A18-'PIANO AMMORTAMENTO'!$A$12) -> 3674.9616
A19: =A18+1 -> 2033 | B19: =$E$6 -> 95000 | C19: =IF($E$6=0,0,MIN($E$6*$B$7,MAX(0,$E$6-D18))) -> 11400 | D19: =D18+C19 -> 85500 | E19: =MAX(0,B19-D19) -> 9500 | F19: =$I$6 -> 266000 | G19: =IF($I$6=0,0,MIN($I$6*$E$7,MAX(0,$I$6-SUM($G$12:G18)))) -> 31920 | H19: =MAX(0,G19-C19) -> 20520 | I19: =H19*$B$8 -> 4924.8 | J19: =I19*(1+'INPUT DATI'!$B$33)^-('PIANO AMMORTAMENTO'!A19-'PIANO AMMORTAMENTO'!$A$12) -> 3499.9634
A20: =A19+1 -> 2034 | B20: =$E$6 -> 95000 | C20: =IF($E$6=0,0,MIN($E$6*$B$7,MAX(0,$E$6-D19))) -> 9500 | D20: =D19+C20 -> 95000 | E20: =MAX(0,B20-D20) -> 0 | F20: =$I$6 -> 266000 | G20: =IF($I$6=0,0,MIN($I$6*$E$7,MAX(0,$I$6-SUM($G$12:G19)))) -> 26600 | H20: =MAX(0,G20-C20) -> 17100 | I20: =H20*$B$8 -> 4104 | J20: =I20*(1+'INPUT DATI'!$B$33)^-('PIANO AMMORTAMENTO'!A20-'PIANO AMMORTAMENTO'!$A$12) -> 2777.7487
A21: =A20+1 -> 2035 | B21: =$E$6 -> 95000 | C21: =IF($E$6=0,0,MIN($E$6*$B$7,MAX(0,$E$6-D20))) -> 0 | D21: =D20+C21 -> 95000 | E21: =MAX(0,B21-D21) -> 0 | F21: =$I$6 -> 266000 | G21: =IF($I$6=0,0,MIN($I$6*$E$7,MAX(0,$I$6-SUM($G$12:G20)))) -> 0 | H21: =MAX(0,G21-C21) -> 0 | I21: =H21*$B$8 -> 0 | J21: =I21*(1+'INPUT DATI'!$B$33)^-('PIANO AMMORTAMENTO'!A21-'PIANO AMMORTAMENTO'!$A$12) -> 0
A22: =A21+1 -> 2036 | B22: =$E$6 -> 95000 | C22: =IF($E$6=0,0,MIN($E$6*$B$7,MAX(0,$E$6-D21))) -> 0 | D22: =D21+C22 -> 95000 | E22: =MAX(0,B22-D22) -> 0 | F22: =$I$6 -> 266000 | G22: =IF($I$6=0,0,MIN($I$6*$E$7,MAX(0,$I$6-SUM($G$12:G21)))) -> 0 | H22: =MAX(0,G22-C22) -> 0 | I22: =H22*$B$8 -> 0 | J22: =I22*(1+'INPUT DATI'!$B$33)^-('PIANO AMMORTAMENTO'!A22-'PIANO AMMORTAMENTO'!$A$12) -> 0
A23: =A22+1 -> 2037 | B23: =$E$6 -> 95000 | C23: =IF($E$6=0,0,MIN($E$6*$B$7,MAX(0,$E$6-D22))) -> 0 | D23: =D22+C23 -> 95000 | E23: =MAX(0,B23-D23) -> 0 | F23: =$I$6 -> 266000 | G23: =IF($I$6=0,0,MIN($I$6*$E$7,MAX(0,$I$6-SUM($G$12:G22)))) -> 0 | H23: =MAX(0,G23-C23) -> 0 | I23: =H23*$B$8 -> 0 | J23: =I23*(1+'INPUT DATI'!$B$33)^-('PIANO AMMORTAMENTO'!A23-'PIANO AMMORTAMENTO'!$A$12) -> 0
A24: =A23+1 -> 2038 | B24: =$E$6 -> 95000 | C24: =IF($E$6=0,0,MIN($E$6*$B$7,MAX(0,$E$6-D23))) -> 0 | D24: =D23+C24 -> 95000 | E24: =MAX(0,B24-D24) -> 0 | F24: =$I$6 -> 266000 | G24: =IF($I$6=0,0,MIN($I$6*$E$7,MAX(0,$I$6-SUM($G$12:G23)))) -> 0 | H24: =MAX(0,G24-C24) -> 0 | I24: =H24*$B$8 -> 0 | J24: =I24*(1+'INPUT DATI'!$B$33)^-('PIANO AMMORTAMENTO'!A24-'PIANO AMMORTAMENTO'!$A$12) -> 0
... A31: =A30+1 -> 2045 | B31: =$E$6 -> 95000 | C31: =IF($E$6=0,0,MIN($E$6*$B$7,MAX(0,$E$6-D30))) -> 0 | D31: =D30+C31 -> 95000 | E31: =MAX(0,B31-D31) -> 0 | F31: =$I$6 -> 266000 | G31: =IF($I$6=0,0,MIN($I$6*$E$7,MAX(0,$I$6-SUM($G$12:G30)))) -> 0 | H31: =MAX(0,G31-C31) -> 0 | I31: =H31*$B$8 -> 0 | J31: =I31*(1+'INPUT DATI'!$B$33)^-('PIANO AMMORTAMENTO'!A31-'PIANO AMMORTAMENTO'!$A$12) -> 0
A32: TOTALE | C32: =SUM(C12:C31) -> 95000 | G32: =SUM(G12:G31) -> 266000 | H32: =SUM(H12:H31) -> 171000 | I32: =SUM(I12:I31) -> 41040 | J32: =SUM(J12:J31) -> 33736.88
C37: =J32 -> 33736.88
B38: 1 | C38: 164120.84
B39: 2 | C39: 33736.88
B40: 3 | C40: 0
B41: 4 | C41: 0
B42: 5 | C42: 0
B43: 6 | C43: 0
B44: 7 | C44: 0
B45: 8 | C45: 0
B46: 9 | C46: 0
B47: 10 | C47: 0

Sheet RIEPILOGO BENEFICIO
A1: RIEPILOGO BENEFICIO FISCALE - IPERAMMORTAMENTO
A2: Dashboard riassuntiva dei benefici fiscali derivanti dall'iperammortamento
A4: RIEPILOGO INVESTIMENTI PER CATEGORIA
A5: Categoria | B5: N. investimenti | C5: Costo acquisizione | D5: Contributi | E5: Base netta | F5: Totale maggioraz.
A6: Beni materiali 4.0 - All. IV | B6: =COUNTIF('INPUT DATI'!C19:C28,"Beni materiali 4.0 - All. IV") -> 2 | C6: =SUMIF('INPUT DATI'!C19:C28,"Beni materiali 4.0 - All. IV",'INPUT DATI'!D19:D28) -> 575000 | D6: =SUMIF('INPUT DATI'!C19:C28,"Beni materiali 4.0 - All. IV",'INPUT DATI'!F19:F28) -> 0 | E6: =SUMIF('INPUT DATI'!C19:C28,"Beni materiali 4.0 - All. IV",'INPUT DATI'!G19:G28) -> 575000 | F6: =SUMIF('CALCOLO MAGGIORAZIONI'!C5:C14,"Beni materiali 4.0 - All. IV",'CALCOLO MAGGIORAZIONI'!O5:O14) -> 1035000
A7: Beni immateriali 4.0 - All. V | B7: =COUNTIF('INPUT DATI'!C19:C28,"Beni immateriali 4.0 - All. V") -> 0 | C7: =SUMIF('INPUT DATI'!C19:C28,"Beni immateriali 4.0 - All. V",'INPUT DATI'!D19:D28) -> 0 | D7: =SUMIF('INPUT DATI'!C19:C28,"Beni immateriali 4.0 - All. V",'INPUT DATI'!F19:F28) -> 0 | E7: =SUMIF('INPUT DATI'!C19:C28,"Beni immateriali 4.0 - All. V",'INPUT DATI'!G19:G28) -> 0 | F7: =SUMIF('CALCOLO MAGGIORAZIONI'!C5:C14,"Beni immateriali 4.0 - All. V",'CALCOLO MAGGIORAZIONI'!O5:O14) -> 0
A8: Impianti energie rinnovabili | B8: =COUNTIF('INPUT DATI'!C19:C28,"Impianti energie rinnovabili") -> 0 | C8: =SUMIF('INPUT DATI'!C19:C28,"Impianti energie rinnovabili",'INPUT DATI'!D19:D28) -> 0 | D8: =SUMIF('INPUT DATI'!C19:C28,"Impianti energie rinnovabili",'INPUT DATI'!F19:F28) -> 0 | E8: =SUMIF('INPUT DATI'!C19:C28,"Impianti energie rinnovabili",'INPUT DATI'!G19:G28) -> 0 | F8: =SUMIF('CALCOLO MAGGIORAZIONI'!C5:C14,"Impianti energie rinnovabili",'CALCOLO MAGGIORAZIONI'!O5:O14) -> 0
A9: TOTALE | B9: =SUM(B6:B8) -> 2 | C9: =SUM(C6:C8) -> 575000 | D9: =SUM(D6:D8) -> 0 | E9: =SUM(E6:E8) -> 575000 | F9: =SUM(F6:F8) -> 1035000
A11: SINTESI BENEFICIO FISCALE
A12: Totale costi acquisizione: | C12: =C9 -> 575000
A13: Totale contributi/sovvenzioni: | C13: =D9 -> 0
A14: Totale base netta: | C14: =E9 -> 575000
A15: Totale maggiorazioni ottenute: | C15: =F9 -> 1035000
A16: Totale costi fiscalmente deducibili: | C16: =E9+F9 -> 1610000
A17: % Maggiorazione media effettiva: | C17: =IF(E9=0,0,F9/E9) -> 1.8
A18: Risparmio IRES stimato (totale vita utile): | C18: =F9*'INPUT DATI'!B32 -> 248400
A19: RISPARMIO FISCALE COMPLESSIVO: | C19: =C18 -> 248400
A20: RISPARMIO COMPLESSIVO ATTUALIZZATO | C20: ='CALCOLO MAGGIORAZIONI'!$R$15 -> 197857.72
