Workbook
Name a: Score!$E$52
Name aa: LEFT(Score!$F$5,2)*1
Name ATE: ATECO[Cod]
Name BVCEE: OFFSET(BVCC,0,1)
Name cemcc: Score!$AB$43:$AF$68
Name crisi: "ragionevole presunzione di uno stato di crisi"
Name RA: +MATCH(CF,RAZ,0)
Name rateco: Score!$K$8
Name SETT: Tabella139[Desc. Crisi]
Name TBA: IF(ta="Abbreviato Cee",1,IF(ta="CEE",2,3))
Name TitSc: "Analisi indicatori per "

Sheet TabelleCompilate
A1: Indice | B1: Voce | C1: AnnoPrec | D1: AnnoCorr | E1: C | F1: C | G1: Indice | H1: Voce | I1: AnnoPrec | J1: AnnoCorr | K1: C
A2: 10 | B2: Stato patrimoniale | G2: 6 | H2: Conto economico abbreviato
A3: 11 | B3: Attivo | G3: 9 | H3: Conto economico
A4: 12 | B4: A) Crediti verso soci per versamenti ancora dovuti | C4: =+#REF! -> #REF! | D4: =+#REF! -> #REF! | E4: 1 | F4: =+IF(E4>0,"SP"&RIGHT(0&E4,2),"") -> SP01 | G4: 10 | H4: A) Valore della produzione
A5: 13 | B5: B) Immobilizzazioni | C5: =+#REF! -> #REF! | D5: =+#REF! -> #REF! | F5: =+IF(E5>0,"SP"&RIGHT(0&E5,2),"") | G5: 11 | H5: 1) ricavi delle vendite e delle prestazioni | I5: =+#REF! -> #REF! | J5: =+#REF! -> #REF! | K5: 1 | L5: =+IF(K5>0,"CE"&RIGHT(0&K5,2),"") -> CE01
A6: 14 | B6: I - Immobilizzazioni immateriali | C6: =+#REF! -> #REF! | D6: =+#REF! -> #REF! | E6: 2 | F6: =+IF(E6>0,"SP"&RIGHT(0&E6,2),"") -> SP02 | G6: 12 | H6: 2), 3) variazioni delle rimanenze di prodotti in corso di lavorazione, semilavorati e finiti e dei lavori in corso su ordinazione | I6: =+#REF! -> #REF! | J6: =+#REF! -> #REF! | L6: =+IF(K6>0,"CE"&RIGHT(0&K6,2),"")
A7: 15 | B7: II - Immobilizzazioni materiali | C7: =+#REF! -> #REF! | D7: =+#REF! -> #REF! | E7: 3 | F7: =+IF(E7>0,"SP"&RIGHT(0&E7,2),"") -> SP03 | G7: 13 | H7: 2), 3) variazioni delle rimanenze di prodotti in corso di lavorazione, semilavorati e finiti e dei lavori in corso su ordinazione | I7: =+#REF! -> #REF! | J7: =+#REF! -> #REF! | L7: =+IF(K7>0,"CE"&RIGHT(0&K7,2),"")
A8: 16 | B8: III - Immobilizzazioni finanziarie | C8: =+#REF! -> #REF! | D8: =+#REF! -> #REF! | E8: 4 | F8: =+IF(E8>0,"SP"&RIGHT(0&E8,2),"") -> SP04 | G8: 14 | H8: 2) variazioni delle rimanenze di prodotti in corso di lavorazione, semilavorati e finiti | I8: =+#REF! -> #REF! | J8: =+#REF! -> #REF! | K8: 2 | L8: =+IF(K8>0,"CE"&RIGHT(0&K8,2),"") -> CE02
A9: 17 | B9: Totale immobilizzazioni (B) | C9: =+#REF! -> #REF! | D9: =+#REF! -> #REF! | E9: 5 | F9: =+IF(E9>0,"SP"&RIGHT(0&E9,2),"") -> SP05 | G9: 15 | H9: 3) variazioni dei lavori in corso su ordinazione | I9: =+#REF! -> #REF! | J9: =+#REF! -> #REF! | K9: 3 | L9: =+IF(K9>0,"CE"&RIGHT(0&K9,2),"") -> CE03
A10: 18 | B10: C) Attivo circolante | C10: =+#REF! -> #REF! | D10: =+#REF! -> #REF! | F10: =+IF(E10>0,"SP"&RIGHT(0&E10,2),"") | G10: 16 | H10: 4) incrementi di immobilizzazioni per lavori interni | I10: =+#REF! -> #REF! | J10: =+#REF! -> #REF! | K10: 4 | L10: =+IF(K10>0,"CE"&RIGHT(0&K10,2),"") -> CE04
A11: 19 | B11: I - Rimanenze | C11: =+#REF! -> #REF! | D11: =+#REF! -> #REF! | E11: 6 | F11: =+IF(E11>0,"SP"&RIGHT(0&E11,2),"") -> SP06 | G11: 17 | H11: 5) altri ricavi e proventi | I11: =+#REF! -> #REF! | J11: =+#REF! -> #REF! | K11: 5 | L11: =+IF(K11>0,"CE"&RIGHT(0&K11,2),"") -> CE05
A12: 20 | B12: Immobilizzazioni materiali destinate alla vendita | C12: =+#REF! -> #REF! | D12: =+#REF! -> #REF! | F12: =+IF(E12>0,"SP"&RIGHT(0&E12,2),"") | G12: 18 | H12: contributi in conto esercizio | I12: =+#REF! -> #REF! | J12: =+#REF! -> #REF! | L12: =+IF(K12>0,"CE"&RIGHT(0&K12,2),"")
A13: 21 | B13: II - Crediti | C13: =+#REF! -> #REF! | D13: =+#REF! -> #REF! | F13: =+IF(E13>0,"SP"&RIGHT(0&E13,2),"") | G13: 19 | H13: altri | I13: =+#REF! -> #REF! | J13: =+#REF! -> #REF! | L13: =+IF(K13>0,"CE"&RIGHT(0&K13,2),"")
A14: 22 | B14: esigibili entro l'esercizio successivo | C14: =+#REF! -> #REF! | D14: =+#REF! -> #REF! | E14: 7 | F14: =+IF(E14>0,"SP"&RIGHT(0&E14,2),"") -> SP07 | G14: 20 | H14: Totale altri ricavi e proventi | I14: =+#REF! -> #REF! | J14: =+#REF! -> #REF! | L14: =+IF(K14>0,"CE"&RIGHT(0&K14,2),"")
A15: 23 | B15: esigibili oltre l'esercizio successivo | C15: =+#REF! -> #REF! | D15: =+#REF! -> #REF! | E15: 8 | F15: =+IF(E15>0,"SP"&RIGHT(0&E15,2),"") -> SP08 | G15: 21 | H15: Totale valore della produzione | I15: =+#REF! -> #REF! | J15: =+#REF! -> #REF! | K15: 6 | L15: =+IF(K15>0,"CE"&RIGHT(0&K15,2),"") -> CE06
A16: 24 | B16: imposte anticipate | C16: =+#REF! -> #REF! | D16: =+#REF! -> #REF! | F16: =+IF(E16>0,"SP"&RIGHT(0&E16,2),"") | G16: 22 | H16: B) Costi della produzione | I16: =+#REF! -> #REF! | J16: =+#REF! -> #REF! | L16: =+IF(K16>0,"CE"&RIGHT(0&K16,2),"")
A17: 25 | B17: Totale crediti | C17: =+#REF! -> #REF! | D17: =+#REF! -> #REF! | E17: 9 | F17: =+IF(E17>0,"SP"&RIGHT(0&E17,2),"") -> SP09 | G17: 23 | H17: 6) per materie prime, sussidiarie, di consumo e di merci | I17: =+#REF! -> #REF! | J17: =+#REF! -> #REF! | K17: 7 | L17: =+IF(K17>0,"CE"&RIGHT(0&K17,2),"") -> CE07
A18: 26 | B18: III - Attività finanziarie che non costituiscono immobilizzazioni | C18: =+#REF! -> #REF! | D18: =+#REF! -> #REF! | E18: 10 | F18: =+IF(E18>0,"SP"&RIGHT(0&E18,2),"") -> SP10 | G18: 24 | H18: 7) per servizi | I18: =+#REF! -> #REF! | J18: =+#REF! -> #REF! | K18: 8 | L18: =+IF(K18>0,"CE"&RIGHT(0&K18,2),"") -> CE08
A19: 27 | B19: IV - Disponibilità liquide | C19: =+#REF! -> #REF! | D19: =+#REF! -> #REF! | E19: 11 | F19: =+IF(E19>0,"SP"&RIGHT(0&E19,2),"") -> SP11 | G19: 25 | H19: 8) per godimento di beni di terzi | I19: =+#REF! -> #REF! | J19: =+#REF! -> #REF! | K19: 9 | L19: =+IF(K19>0,"CE"&RIGHT(0&K19,2),"") -> CE09
A20: 28 | B20: Totale attivo circolante (C) | C20: =+#REF! -> #REF! | D20: =+#REF! -> #REF! | E20: 12 | F20: =+IF(E20>0,"SP"&RIGHT(0&E20,2),"") -> SP12 | G20: 26 | H20: 9) per il personale | I20: =+#REF! -> #REF! | J20: =+#REF! -> #REF! | L20: =+IF(K20>0,"CE"&RIGHT(0&K20,2),"")
A21: 29 | B21: D) Ratei e risconti | C21: =+#REF! -> #REF! | D21: =+#REF! -> #REF! | E21: 13 | F21: =+IF(E21>0,"SP"&RIGHT(0&E21,2),"") -> SP13 | G21: 27 | H21: a) salari e stipendi | I21: =+#REF! -> #REF! | J21: =+#REF! -> #REF! | L21: =+IF(K21>0,"CE"&RIGHT(0&K21,2),"")
A22: 30 | B22: Totale attivo | C22: =+#REF! -> #REF! | D22: =+#REF! -> #REF! | E22: 14 | F22: =+IF(E22>0,"SP"&RIGHT(0&E22,2),"") -> SP14 | G22: 28 | H22: b) oneri sociali | I22: =+#REF! -> #REF! | J22: =+#REF! -> #REF! | L22: =+IF(K22>0,"CE"&RIGHT(0&K22,2),"")
A23: 31 | B23: Passivo | C23: =+#REF! -> #REF! | D23: =+#REF! -> #REF! | F23: =+IF(E23>0,"SP"&RIGHT(0&E23,2),"") | G23: 29 | H23: c), d), e) trattamento di fine rapporto, trattamento di quiescenza, altri costi del personale | I23: =+#REF! -> #REF! | J23: =+#REF! -> #REF! | L23: =+IF(K23>0,"CE"&RIGHT(0&K23,2),"")
A24: 32 | B24: A) Patrimonio netto | C24: =+#REF! -> #REF! | D24: =+#REF! -> #REF! | F24: =+IF(E24>0,"SP"&RIGHT(0&E24,2),"") | G24: 30 | H24: c), d), e) trattamento di fine rapporto, trattamento di quiescenza, altri costi del personale | I24: =+#REF! -> #REF! | J24: =+#REF! -> #REF! | L24: =+IF(K24>0,"CE"&RIGHT(0&K24,2),"")
A25: 33 | B25: I - Capitale | C25: =+#REF! -> #REF! | D25: =+#REF! -> #REF! | F25: =+IF(E25>0,"SP"&RIGHT(0&E25,2),"") | G25: 31 | H25: c) trattamento di fine rapporto | I25: =+#REF! -> #REF! | J25: =+#REF! -> #REF! | L25: =+IF(K25>0,"CE"&RIGHT(0&K25,2),"")
A26: 34 | B26: II - Riserva da soprapprezzo delle azioni | C26: =+#REF! -> #REF! | D26: =+#REF! -> #REF! | F26: =+IF(E26>0,"SP"&RIGHT(0&E26,2),"") | G26: 32 | H26: d) trattamento di quiescenza e simili | I26: =+#REF! -> #REF! | J26: =+#REF! -> #REF! | L26: =+IF(K26>0,"CE"&RIGHT(0&K26,2),"")
A27: 35 | B27: III - Riserve di rivalutazione | C27: =+#REF! -> #REF! | D27: =+#REF! -> #REF! | F27: =+IF(E27>0,"SP"&RIGHT(0&E27,2),"") | G27: 33 | H27: e) altri costi | I27: =+#REF! -> #REF! | J27: =+#REF! -> #REF! | L27: =+IF(K27>0,"CE"&RIGHT(0&K27,2),"")
A28: 36 | B28: IV - Riserva legale | C28: =+#REF! -> #REF! | D28: =+#REF! -> #REF! | F28: =+IF(E28>0,"SP"&RIGHT(0&E28,2),"") | G28: 34 | H28: Totale costi per il personale | I28: =+#REF! -> #REF! | J28: =+#REF! -> #REF! | K28: 10 | L28: =+IF(K28>0,"CE"&RIGHT(0&K28,2),"") -> CE10
A29: 37 | B29: V - Riserve statutarie | C29: =+#REF! -> #REF! | D29: =+#REF! -> #REF! | F29: =+IF(E29>0,"SP"&RIGHT(0&E29,2),"") | G29: 35 | H29: 10) ammortamenti e svalutazioni | I29: =+#REF! -> #REF! | J29: =+#REF! -> #REF! | L29: =+IF(K29>0,"CE"&RIGHT(0&K29,2),"")
A30: 38 | B30: VI - Altre riserve | C30: =+#REF! -> #REF! | D30: =+#REF! -> #REF! | F30: =+IF(E30>0,"SP"&RIGHT(0&E30,2),"") | G30: 36 | H30: a), b), c) ammortamento delle immobilizzazioni immateriali e materiali, altre svalutazioni delle immobilizzazioni | I30: =+#REF! -> #REF! | J30: =+#REF! -> #REF! | L30: =+IF(K30>0,"CE"&RIGHT(0&K30,2),"")
A31: 39 | B31: VII - Riserva per operazioni di copertura dei flussi finanziari attesi | C31: =+#REF! -> #REF! | D31: =+#REF! -> #REF! | F31: =+IF(E31>0,"SP"&RIGHT(0&E31,2),"") | G31: 37 | H31: a), b), c) ammortamento delle immobilizzazioni immateriali e materiali, altre svalutazioni delle immobilizzazioni | I31: =+#REF! -> #REF! | J31: =+#REF! -> #REF! | L31: =+IF(K31>0,"CE"&RIGHT(0&K31,2),"")
A32: 40 | B32: VIII - Utili (perdite) portati a nuovo | C32: =+#REF! -> #REF! | D32: =+#REF! -> #REF! | F32: =+IF(E32>0,"SP"&RIGHT(0&E32,2),"") | G32: 38 | H32: a) ammortamento delle immobilizzazioni immateriali | I32: =+#REF! -> #REF! | J32: =+#REF! -> #REF! | K32: 11 | L32: =+IF(K32>0,"CE"&RIGHT(0&K32,2),"") -> CE11
A33: 41 | B33: IX - Utile (perdita) dell'esercizio | C33: =+#REF! -> #REF! | D33: =+#REF! -> #REF! | F33: =+IF(E33>0,"SP"&RIGHT(0&E33,2),"") | G33: 39 | H33: b) ammortamento delle immobilizzazioni materiali | I33: =+#REF! -> #REF! | J33: =+#REF! -> #REF! | K33: 12 | L33: =+IF(K33>0,"CE"&RIGHT(0&K33,2),"") -> CE12
A34: 42 | B34: Perdita ripianata nell'esercizio | C34: =+#REF! -> #REF! | D34: =+#REF! -> #REF! | F34: =+IF(E34>0,"SP"&RIGHT(0&E34,2),"") | G34: 40 | H34: c) altre svalutazioni delle immobilizzazioni | I34: =+#REF! -> #REF! | J34: =+#REF! -> #REF! | L34: =+IF(K34>0,"CE"&RIGHT(0&K34,2),"")
A35: 43 | B35: X - Riserva negativa per azioni proprie in portafoglio | C35: =+#REF! -> #REF! | D35: =+#REF! -> #REF! | F35: =+IF(E35>0,"SP"&RIGHT(0&E35,2),"") | G35: 41 | H35: d) svalutazioni dei crediti compresi nell'attivo circolante e delle disponibilità liquide | I35: =+#REF! -> #REF! | J35: =+#REF! -> #REF! | L35: =+IF(K35>0,"CE"&RIGHT(0&K35,2),"")
A36: 44 | B36: Totale patrimonio netto | C36: =+#REF! -> #REF! | D36: =+#REF! -> #REF! | E36: 15 | F36: =+IF(E36>0,"SP"&RIGHT(0&E36,2),"") -> SP15 | G36: 42 | H36: Totale ammortamenti e svalutazioni | I36: =+#REF! -> #REF! | J36: =+#REF! -> #REF! | K36: 13 | L36: =+IF(K36>0,"CE"&RIGHT(0&K36,2),"") -> CE13
A37: 45 | B37: B) Fondi per rischi e oneri | C37: =+#REF! -> #REF! | D37: =+#REF! -> #REF! | E37: 17 | F37: =+IF(E37>0,"SP"&RIGHT(0&E37,2),"") -> SP17 | G37: 43 | H37: 11) variazioni delle rimanenze di materie prime, sussidiarie, di consumo e merci | I37: =+#REF! -> #REF! | J37: =+#REF! -> #REF! | K37: 14 | L37: =+IF(K37>0,"CE"&RIGHT(0&K37,2),"") -> CE14
A38: 46 | B38: C) Trattamento di fine rapporto di lavoro subordinato | C38: =+#REF! -> #REF! | D38: =+#REF! -> #REF! | E38: 18 | F38: =+IF(E38>0,"SP"&RIGHT(0&E38,2),"") -> SP18 | G38: 44 | H38: 12) accantonamenti per rischi | I38: =+#REF! -> #REF! | J38: =+#REF! -> #REF! | K38: 15 | L38: =+IF(K38>0,"CE"&RIGHT(0&K38,2),"") -> CE15
A39: 47 | B39: D) Debiti | C39: =+#REF! -> #REF! | D39: =+#REF! -> #REF! | F39: =+IF(E39>0,"SP"&RIGHT(0&E39,2),"") | G39: 45 | H39: 13) altri accantonamenti | I39: =+#REF! -> #REF! | J39: =+#REF! -> #REF! | K39: 16 | L39: =+IF(K39>0,"CE"&RIGHT(0&K39,2),"") -> CE16
A40: 48 | B40: esigibili entro l'esercizio successivo | C40: =+#REF! -> #REF! | D40: =+#REF! -> #REF! | E40: 19 | F40: =+IF(E40>0,"SP"&RIGHT(0&E40,2),"") -> SP19 | G40: 46 | H40: 14) oneri diversi di gestione | I40: =+#REF! -> #REF! | J40: =+#REF! -> #REF! | K40: 17 | L40: =+IF(K40>0,"CE"&RIGHT(0&K40,2),"") -> CE17
A41: 49 | B41: esigibili oltre l'esercizio successivo | C41: =+#REF! -> #REF! | D41: =+#REF! -> #REF! | E41: 20 | F41: =+IF(E41>0,"SP"&RIGHT(0&E41,2),"") -> SP20 | G41: 47 | H41: Totale costi della produzione | I41: =+#REF! -> #REF! | J41: =+#REF! -> #REF! | K41: 18 | L41: =+IF(K41>0,"CE"&RIGHT(0&K41,2),"") -> CE18
A42: 50 | B42: Totale debiti | C42: =+#REF! -> #REF! | D42: =+#REF! -> #REF! | E42: 21 | F42: =+IF(E42>0,"SP"&RIGHT(0&E42,2),"") -> SP21 | G42: 48 | H42: Differenza tra valore e costi della produzione (A - B) | I42: =+#REF! -> #REF! | J42: =+#REF! -> #REF! | L42: =+IF(K42>0,"CE"&RIGHT(0&K42,2),"")
A43: 51 | B43: E) Ratei e risconti | C43: =+#REF! -> #REF! | D43: =+#REF! -> #REF! | E43: 22 | F43: =+IF(E43>0,"SP"&RIGHT(0&E43,2),"") -> SP22 | G43: 49 | H43: C) Proventi e oneri finanziari | I43: =+#REF! -> #REF! | J43: =+#REF! -> #REF! | L43: =+IF(K43>0,"CE"&RIGHT(0&K43,2),"")
A44: 52 | B44: Totale passivo | C44: =+#REF! -> #REF! | D44: =+#REF! -> #REF! | E44: 23 | F44: =+IF(E44>0,"SP"&RIGHT(0&E44,2),"") -> SP23 | G44: 50 | H44: 15) proventi da partecipazioni | I44: =+#REF! -> #REF! | J44: =+#REF! -> #REF! | L44: =+IF(K44>0,"CE"&RIGHT(0&K44,2),"")
C45: =+#REF! -> #REF! | D45: =+#REF! -> #REF! | F45: =+IF(E45>0,"SP"&RIGHT(0&E45,2),"") | G45: 51 | H45: da imprese controllate | I45: =+#REF! -> #REF! | J45: =+#REF! -> #REF! | L45: =+IF(K45>0,"CE"&RIGHT(0&K45,2),"")
F46: =+IF(E46>0,"SP"&RIGHT(0&E46,2),"") | G46: 52 | H46: da imprese collegate | I46: =+#REF! -> #REF! | J46: =+#REF! -> #REF! | L46: =+IF(K46>0,"CE"&RIGHT(0&K46,2),"")
F47: =+IF(E47>0,"SP"&RIGHT(0&E47,2),"") | G47: 53 | H47: da imprese controllanti | I47: =+#REF! -> #REF! | J47: =+#REF! -> #REF! | L47: =+IF(K47>0,"CE"&RIGHT(0&K47,2),"")
F48: =+IF(E48>0,"SP"&RIGHT(0&E48,2),"") | G48: 54 | H48: da imprese sottoposte al controllo delle controllanti | I48: =+#REF! -> #REF! | J48: =+#REF! -> #REF! | L48: =+IF(K48>0,"CE"&RIGHT(0&K48,2),"")
F49: =+IF(E49>0,"SP"&RIGHT(0&E49,2),"") | G49: 55 | H49: altri | I49: =+#REF! -> #REF! | J49: =+#REF! -> #REF! | L49: =+IF(K49>0,"CE"&RIGHT(0&K49,2),"")
F50: =+IF(E50>0,"SP"&RIGHT(0&E50,2),"") | G50: 56 | H50: Totale proventi da partecipazioni | I50: =+#REF! -> #REF! | J50: =+#REF! -> #REF! | L50: =+IF(K50>0,"CE"&RIGHT(0&K50,2),"")
F51: =+IF(E51>0,"SP"&RIGHT(0&E51,2),"") | G51: 57 | H51: 16) altri proventi finanziari | I51: =+#REF! -> #REF! | J51: =+#REF! -> #REF! | L51: =+IF(K51>0,"CE"&RIGHT(0&K51,2),"")
F52: =+IF(E52>0,"SP"&RIGHT(0&E52,2),"") | G52: 58 | H52: a) da crediti iscritti nelle immobilizzazioni | I52: =+#REF! -> #REF! | J52: =+#REF! -> #REF! | L52: =+IF(K52>0,"CE"&RIGHT(0&K52,2),"")
F53: =+IF(E53>0,"SP"&RIGHT(0&E53,2),"") | G53: 59 | H53: da imprese controllate | I53: =+#REF! -> #REF! | J53: =+#REF! -> #REF! | L53: =+IF(K53>0,"CE"&RIGHT(0&K53,2),"")
F54: =+IF(E54>0,"SP"&RIGHT(0&E54,2),"") | G54: 60 | H54: da imprese collegate | I54: =+#REF! -> #REF! | J54: =+#REF! -> #REF! | L54: =+IF(K54>0,"CE"&RIGHT(0&K54,2),"")
F55: =+IF(E55>0,"SP"&RIGHT(0&E55,2),"") | G55: 61 | H55: da imprese controllanti | I55: =+#REF! -> #REF! | J55: =+#REF! -> #REF! | L55: =+IF(K55>0,"CE"&RIGHT(0&K55,2),"")
F56: =+IF(E56>0,"SP"&RIGHT(0&E56,2),"") | G56: 62 | H56: da imprese sottoposte al controllo delle controllanti | I56: =+#REF! -> #REF! | J56: =+#REF! -> #REF! | L56: =+IF(K56>0,"CE"&RIGHT(0&K56,2),"")
F57: =+IF(E57>0,"SP"&RIGHT(0&E57,2),"") | G57: 63 | H57: altri | I57: =+#REF! -> #REF! | J57: =+#REF! -> #REF! | L57: =+IF(K57>0,"CE"&RIGHT(0&K57,2),"")
... F76: =+IF(E76>0,"SP"&RIGHT(0&E76,2),"") | G76: 82 | H76: altri | I76: =+#REF! -> #REF! | J76: =+#REF! -> #REF! | L76: =+IF(K76>0,"CE"&RIGHT(0&K76,2),"")
F77: =+IF(E77>0,"SP"&RIGHT(0&E77,2),"") | G77: 83 | H77: Totale interessi e altri oneri finanziari | I77: =+#REF! -> #REF! | J77: =+#REF! -> #REF! | K77: 19 | L77: =+IF(K77>0,"CE"&RIGHT(0&K77,2),"") -> CE19
F78: =+IF(E78>0,"SP"&RIGHT(0&E78,2),"") | G78: 84 | H78: 17-bis) utili e perdite su cambi | I78: =+#REF! -> #REF! | J78: =+#REF! -> #REF! | L78: =+IF(K78>0,"CE"&RIGHT(0&K78,2),"")
F79: =+IF(E79>0,"SP"&RIGHT(0&E79,2),"") | G79: 85 | H79: Totale proventi e oneri finanziari (15 + 16 - 17 + - 17-bis) | I79: =+#REF! -> #REF! | J79: =+#REF! -> #REF! | K79: 20 | L79: =+IF(K79>0,"CE"&RIGHT(0&K79,2),"") -> CE20
F80: =+IF(E80>0,"SP"&RIGHT(0&E80,2),"") | G80: 86 | H80: D) Rettifiche di valore di attività e passività finanziarie | I80: =+#REF! -> #REF! | J80: =+#REF! -> #REF! | L80: =+IF(K80>0,"CE"&RIGHT(0&K80,2),"")
F81: =+IF(E81>0,"SP"&RIGHT(0&E81,2),"") | G81: 87 | H81: 18) rivalutazioni | I81: =+#REF! -> #REF! | J81: =+#REF! -> #REF! | L81: =+IF(K81>0,"CE"&RIGHT(0&K81,2),"")
F82: =+IF(E82>0,"SP"&RIGHT(0&E82,2),"") | G82: 88 | H82: a) di partecipazioni | I82: =+#REF! -> #REF! | J82: =+#REF! -> #REF! | L82: =+IF(K82>0,"CE"&RIGHT(0&K82,2),"")
F83: =+IF(E83>0,"SP"&RIGHT(0&E83,2),"") | G83: 89 | H83: b) di immobilizzazioni finanziarie che non costituiscono partecipazioni | I83: =+#REF! -> #REF! | J83: =+#REF! -> #REF! | L83: =+IF(K83>0,"CE"&RIGHT(0&K83,2),"")
F84: =+IF(E84>0,"SP"&RIGHT(0&E84,2),"") | G84: 90 | H84: c) di titoli iscritti all'attivo circolante che non costituiscono partecipazioni | I84: =+#REF! -> #REF! | J84: =+#REF! -> #REF! | L84: =+IF(K84>0,"CE"&RIGHT(0&K84,2),"")
F85: =+IF(E85>0,"SP"&RIGHT(0&E85,2),"") | G85: 91 | H85: d) di strumenti finanziari derivati | I85: =+#REF! -> #REF! | J85: =+#REF! -> #REF! | L85: =+IF(K85>0,"CE"&RIGHT(0&K85,2),"")
F86: =+IF(E86>0,"SP"&RIGHT(0&E86,2),"") | G86: 92 | H86: di attività finanziarie per la gestione accentrata della tesoreria | I86: =+#REF! -> #REF! | J86: =+#REF! -> #REF! | L86: =+IF(K86>0,"CE"&RIGHT(0&K86,2),"")
F87: =+IF(E87>0,"SP"&RIGHT(0&E87,2),"") | G87: 93 | H87: Totale rivalutazioni | I87: =+#REF! -> #REF! | J87: =+#REF! -> #REF! | L87: =+IF(K87>0,"CE"&RIGHT(0&K87,2),"")
F88: =+IF(E88>0,"SP"&RIGHT(0&E88,2),"") | G88: 94 | H88: 19) svalutazioni | I88: =+#REF! -> #REF! | J88: =+#REF! -> #REF! | L88: =+IF(K88>0,"CE"&RIGHT(0&K88,2),"")
F89: =+IF(E89>0,"SP"&RIGHT(0&E89,2),"") | G89: 95 | H89: a) di partecipazioni | I89: =+#REF! -> #REF! | J89: =+#REF! -> #REF! | L89: =+IF(K89>0,"CE"&RIGHT(0&K89,2),"")
F90: =+IF(E90>0,"SP"&RIGHT(0&E90,2),"") | G90: 96 | H90: b) di immobilizzazioni finanziarie che non costituiscono partecipazioni | I90: =+#REF! -> #REF! | J90: =+#REF! -> #REF! | L90: =+IF(K90>0,"CE"&RIGHT(0&K90,2),"")
F91: =+IF(E91>0,"SP"&RIGHT(0&E91,2),"") | G91: 97 | H91: c) di titoli iscritti nell'attivo circolante che non costituiscono partecipazioni | I91: =+#REF! -> #REF! | J91: =+#REF! -> #REF! | L91: =+IF(K91>0,"CE"&RIGHT(0&K91,2),"")
... F94: =+IF(E94>0,"SP"&RIGHT(0&E94,2),"") | G94: 100 | H94: Totale svalutazioni | I94: =+#REF! -> #REF! | J94: =+#REF! -> #REF! | L94: =+IF(K94>0,"CE"&RIGHT(0&K94,2),"")
F95: =+IF(E95>0,"SP"&RIGHT(0&E95,2),"") | G95: 101 | H95: Totale delle rettifiche di valore di attività e passività finanziarie (18 - 19) | I95: =+#REF! -> #REF! | J95: =+#REF! -> #REF! | K95: 21 | L95: =+IF(K95>0,"CE"&RIGHT(0&K95,2),"") -> CE21
F96: =+IF(E96>0,"SP"&RIGHT(0&E96,2),"") | G96: 102 | H96: Risultato prima delle imposte (A - B + - C + - D) | I96: =+#REF! -> #REF! | J96: =+#REF! -> #REF! | K96: 23 | L96: =+IF(K96>0,"CE"&RIGHT(0&K96,2),"") -> CE23
F97: =+IF(E97>0,"SP"&RIGHT(0&E97,2),"") | G97: 103 | H97: 20) Imposte sul reddito dell'esercizio, correnti, differite e anticipate | I97: =+#REF! -> #REF! | J97: =+#REF! -> #REF! | L97: =+IF(K97>0,"CE"&RIGHT(0&K97,2),"")
F98: =+IF(E98>0,"SP"&RIGHT(0&E98,2),"") | G98: 104 | H98: imposte correnti | I98: =+#REF! -> #REF! | J98: =+#REF! -> #REF! | L98: =+IF(K98>0,"CE"&RIGHT(0&K98,2),"")
F99: =+IF(E99>0,"SP"&RIGHT(0&E99,2),"") | G99: 105 | H99: imposte relative a esercizi precedenti | I99: =+#REF! -> #REF! | J99: =+#REF! -> #REF! | L99: =+IF(K99>0,"CE"&RIGHT(0&K99,2),"")
F100: =+IF(E100>0,"SP"&RIGHT(0&E100,2),"") | G100: 106 | H100: imposte differite e anticipate | I100: =+#REF! -> #REF! | J100: =+#REF! -> #REF! | L100: =+IF(K100>0,"CE"&RIGHT(0&K100,2),"")
F101: =+IF(E101>0,"SP"&RIGHT(0&E101,2),"") | G101: 107 | H101: proventi (oneri) da adesione al regime di consolidato fiscale / trasparenza fiscale | I101: =+#REF! -> #REF! | J101: =+#REF! -> #REF! | L101: =+IF(K101>0,"CE"&RIGHT(0&K101,2),"")
F102: =+IF(E102>0,"SP"&RIGHT(0&E102,2),"") | G102: 108 | H102: Totale delle imposte sul reddito dell'esercizio, correnti, differite e anticipate | I102: =+#REF! -> #REF! | J102: =+#REF! -> #REF! | K102: 24 | L102: =+IF(K102>0,"CE"&RIGHT(0&K102,2),"") -> CE24
F103: =+IF(E103>0,"SP"&RIGHT(0&E103,2),"") | G103: 109 | H103: 21) Utile (perdita) dell'esercizio | I103: =+#REF! -> #REF! | J103: =+#REF! -> #REF! | K103: 25 | L103: =+IF(K103>0,"CE"&RIGHT(0&K103,2),"") -> CE25

Sheet Score
C2: DATI AZIENDA
C3: NOME AZIENDA | D3: Alfa S.r.l.
C5: Tipologia società | D5: S.r.l. | E5: ATECO | F5: 43.21.02 | H5: =+VLOOKUP(F5,ATECO[],2,0) -> Installazione di impianti elettronici (inclusa manutenzione e riparazione)
C6: Limite Capitale | D6: =+IF(D5="S.r.l.",10000,IF(D5="S.p.a.",100000,0)) -> 10000 | E6: Consulta Ateco | F6: SETTORE (IN BASE ATECO) | H6: =+VLOOKUP(F5,ATECO[],3,0) -> F42) Ingegneria civile; F43) Costruzioni specializzate
D7: Periodo n-1 | E7: Periodo n | F7: SETTORE (INSER. MANUALE)
C8: ESERCIZI ANALISI | D8: 45291 | E8: 45657 | F8: SETTORE | H8: =+IF(H7>"",H7,H6) -> F42) Ingegneria civile; F43) Costruzioni specializzate | K8: =+MATCH(H8,Tabella139[Desc. Crisi],0) -> 5
C9: Inizio esercizio se diverso da 1/1 | D9: 44927 | E9: 45292
C10: Inizio esercizio | D10: =+IF(D9>0,D9,DATE(YEAR(D8),1,1)) -> 44927 | E10: =+IF(E9>0,E9,DATE(YEAR(E8),1,1)) -> 45292
C11: Giorni | D11: =+D8-D10+1 -> 365 | E11: =+E8-E10+1 -> 366
C12: Durata esercizio | D12: =+EOMONTH(D10,11)-D10+1 -> 365 | E12: =+EOMONTH(E10,11)-E10+1 -> 366
D13: =+D11/D12 -> 1 | E13: =+E11/E12 -> 1
C14: VALORI DA BILANCIO
C15: CALCOLO INDICATORI
A16: 1 | C16: PATRIMONIO NETTO | F16: 100000
A17: 1 | C17: =+UPPER("Patrimonio netto >"&TEXT(D6,"0.000")) -> PATRIMONIO NETTO >10.000 | F17: =+(F16>$D$6)*1 -> 1
A18: 2 | C18: Calcolo DSCR a sei mesi | F18: =+E8 -> 45657
C19: 1° Approccio
C20: Calcolo Numeratore
C21: Giacenze iniziali cassa | F21: 50000
C22: Entrate previste nei 6 mesi | F22: 300000
C23: Altre entrate | F23: 50000
C24: (Uscite previste esclusi i rimborsi debiti) | F24: 250000
C25: Totale Numeratore (Entrate) | F25: =SUM(F21:F24) -> 650000
C26: Calcolo Denominatore
C27: Rate finanziamenti previste (quota capitale) | F27: 30000
C28: Rateazioni imposte | F28: 20000
C29: Totale Denominatore (Uscite finanziarie) | F29: =SUM(F26:F28) -> 50000
A30: 2 | C30: DSCR risultante 1° Approccio | F30: =+IFERROR(F25/F29,0) -> 13
C31: 2° Approccio
C32: Calcolo Numeratore
C33: Flusso finanziario della gestione reddituale (A) | F33: 100000
C34: Flusso per la gestione degli investimenti e disinv | F34: -40000
C35: - Componenti da escludere e) e f)
C36: a) Flussi operativi al servizio del debito | F36: =SUM(F33:F35) -> 60000
C37: b) Disponibilità liquide iniziali | F37: 50000
C38: c) Linee di credito utilizzabili a 6 mesi | F38: 100000
C39: Totale Numeratore | F39: =SUM(F36:F38) -> 210000
C40: d) Pagamenti previsti, capitali ed interessi deb. Finanziari | F40: 35000
C41: e) debito fiscale o contributivo (+ sanzioni e int.) a sei mesi | F41: 40000
C42: f) debito verso fornitori non fisiologico | F42: 25000
C43: linee di credito in scadenza prossimi 6 mesi (no rinnovo) | F43: 50000 | W43: CODICE | X43: DESCRIZIONE | Y43: =+#REF! -> #REF! | Z43: =+#REF! -> #REF!
C44: Totale Denominatore | F44: =SUM(F40:F43) -> 150000 | W44: SP01 | X44: Crediti verso soci per versamenti ancora dovuti | Y44: =+#REF! -> #REF! | Z44: =+#REF! -> #REF!
C45: DSCR risultante 2° Approccio | F45: =+IFERROR(F39/F44,0) -> 1.4 | W45: SP02 | X45: Totale immobilizzazioni immateriali | Y45: =+#REF! -> #REF! | Z45: =+#REF! -> #REF!
C46: Scelta approccio | F46: 2° Approccio | W46: SP03 | X46: Totale immobilizzazioni materiali | Y46: =+#REF! -> #REF! | Z46: =+#REF! -> #REF!
A47: 2 | C47: =+UPPER("Calcolo DSCR a sei mesi") -> CALCOLO DSCR A SEI MESI | F47: =+IF(LEFT(F46)*1=1,F30,F45) -> 1.4 | W47: SP04 | X47: Totale immobilizzazioni finanziarie | Y47: =+#REF! -> #REF! | Z47: =+#REF! -> #REF!
F48: 1 | W48: SP05 | X48: Totale Immobilizzazioni | Y48: =+#REF! -> #REF! | Z48: =+#REF! -> #REF!
W49: SP06 | X49: Totale rimanenze | Y49: =+#REF! -> #REF! | Z49: =+#REF! -> #REF!
W50: SP07 | X50: Crediti esigibili entro l'esercizio successivo | Y50: =+#REF! -> #REF! | Z50: =+#REF! -> #REF!
C51: =+IF(F48=1, IF(OR(F17=0,F47<1),UPPER(crisi),UPPER("Assenza di una "&crisi)),UPPER("necessità di ricorrere agli indicatori di settore")) -> ASSENZA DI UNA RAGIONEVOLE PRESUNZIONE DI UNO STATO DI CRISI | W51: SP08 | X51: Crediti esigibili oltre l'esercizio successivo | Y51: =+#REF! -> #REF! | Z51: =+#REF! -> #REF!
E52: FALSE | W52: SP09 | X52: Totale Crediti | Y52: =+#REF! -> #REF! | Z52: =+#REF! -> #REF!
W53: SP10 | X53: Attività finanziarie che non costituiscono immobilizzazioni | Y53: =+#REF! -> #REF! | Z53: =+#REF! -> #REF!
C54: INDICI SETTORIALI | W54: SP11 | X54: Disponibilità liquide | Y54: =+#REF! -> #REF! | Z54: =+#REF! -> #REF!
A55: 3 | C55: 1) SOSTENIBILITÀ ONERI FINANZIARI | W55: SP12 | X55: Totale attivo circolante | Y55: =+#REF! -> #REF! | Z55: =+#REF! -> #REF!
C56: Calcolo Numeratore: Oneri finanziari | E56: =+D8 -> 45291 | F56: =+E8 -> 45657 | W56: SP13 | X56: Totale ratei e risconti | Y56: =+#REF! -> #REF! | Z56: =+#REF! -> #REF!
C57: Interessi e altri oneri finanziari (c17 art 2425) | E57: 15000 | F57: 18000 | W57: SP14 | X57: Totale Attivo | Y57: =+#REF! -> #REF! | Z57: =+#REF! -> #REF!
C58: Totale Numeratore | E58: =SUM(E57) -> 15000 | F58: =SUM(F57) -> 18000 | W58: SP15 | X58: Patrimonio netto | Y58: =+#REF! -> #REF! | Z58: =+#REF! -> #REF!
C59: Calcolo Denominatore: Ricavi | W59: SP16 | X59: Di cui Utile (Perdita) di esercizio | Y59: =+#REF! -> #REF! | Z59: =+#REF! -> #REF!
C60: Ricavi netti (A1 art. 2425) | E60: 500000 | F60: 600000 | W60: SP17 | X60: Totale fondi per rischi e oneri | Y60: =+#REF! -> #REF! | Z60: =+#REF! -> #REF!
C61: Lavori in corso (A5 art. 2423) | E61: 50000 | F61: 40000 | W61: SP18 | X61: Trattamento di fine rapporto di lavoro sub. | Y61: =+#REF! -> #REF! | Z61: =+#REF! -> #REF!
C62: Totale Denominatore | E62: =SUM(E60:E61) -> 550000 | F62: =SUM(F60:F61) -> 640000 | W62: SP19 | X62: Debiti esigibili entro l'esercizio successivo | Y62: =+#REF! -> #REF! | Z62: =+#REF! -> #REF!
A63: 3 | C63: =+C55 -> 1) SOSTENIBILITÀ ONERI FINANZIARI | E63: =+IFERROR(E58/E60,0) -> 0.03 | F63: =+IFERROR(F58/F60,0) -> 0.03 | H63: =+$F$56 -> 45657 | I63: =+F64-F63 -> -0.002 | J63: =+F63*(F63<F64) -> 0 | W63: SP20 | X63: Debiti esigibili oltre l'esercizio successivo | Y63: =+#REF! -> #REF! | Z63: =+#REF! -> #REF!
C64: =+"Soglia per settore "&$H$7 -> Soglia per settore | E64: {=+INDEX(Tabella139[],rateco,Score!$A$63)} -> 0.028 | F64: {=+INDEX(Tabella139[],rateco,Score!$A$63)} -> 0.028 | G64: =+IF(a,(H64<H63)*1,(F64<F63)*1) -> 1 | K64: =+(E63>E64)*E63 -> 0.03 | W64: SP21 | X64: Totale debiti | Y64: =+#REF! -> #REF! | Z64: =+#REF! -> #REF!
W65: SP22 | X65: Totale ratei e risconti | Y65: =+#REF! -> #REF! | Z65: =+#REF! -> #REF!
A66: 4 | C66: 2) ADEGUATEZZA PATRIMONIALE | W66: SP23 | X66: Totale Passivo | Y66: =+#REF! -> #REF! | Z66: =+#REF! -> #REF!
C67: Calcolo Numeratore: Patrimonio Netto
C68: Patrimonio netto (A SP Passivo) | E68: 200000 | F68: 220000
C69: - Crediti verso soci (A SP Attivo) | E69: 30000 | F69: 25000
C70: - Dividendi deliberati sull'utile di esercizio | E70: 10000 | F70: 15000
C71: Totale Numeratore | E71: =+E68-E69-E70 -> 160000 | F71: =+F68-F69-F70 -> 180000
C72: Calcolo Denominatore: Debiti
C73: Debiti (D Passivo) | E73: 300000 | F73: 350000
C74: Ratei e risconti passivi (E Passivo) | E74: 20000 | F74: 25000
C75: Totale Denominatore | E75: =SUM(E73:E74) -> 320000 | F75: =SUM(F73:F74) -> 375000
A76: =+A66 -> 4 | C76: =+C66 -> 2) ADEGUATEZZA PATRIMONIALE | E76: =+IFERROR(E71/E75,"") -> 0.5 | F76: =+IFERROR(F71/F75,"") -> 0.48 | H76: =+$F$56 -> 45657 | I76: =+F77-F76 -> -0.427 | J76: =+F76*(F76<F77) -> 0
C77: =+"Soglia per settore "&$H$7 -> Soglia per settore | E77: {=+INDEX(Tabella139[],rateco,Score!$A76)} -> 0.053 | F77: {=+INDEX(Tabella139[],rateco,Score!$A76)} -> 0.053 | G77: =+IF(a,(H77>H76)*1,(F77>F76)*1) -> 0
A78: 5 | C78: 3) EQUILIBRIO FINANZIARIO
C79: Calcolo Numeratore: Attività a breve
C80: Attivo circolante (C Attivo entro esercizio) | E80: 400000 | F80: 450000
C81: Ratei e risconti attivi (D Attivo) | E81: 15000 | F81: 18000
C82: Totale Numeratore | E82: =SUM(E80:E81) -> 415000 | F82: =SUM(F80:F81) -> 468000
C83: Calcolo Denominatore: Passività a breve
C84: Debiti (D Passivo entro esercizio) | E84: 150000 | F84: 160000
C85: Ratei e risconti passivi (E Passivo) | E85: 10000 | F85: 12000
C86: Totale Denominatore | E86: =SUM(E84:E85) -> 160000 | F86: =SUM(F84:F85) -> 172000
A87: =+A78 -> 5 | C87: =+C78 -> 3) EQUILIBRIO FINANZIARIO | E87: =+IFERROR(E82/E86,"") -> 2.59375 | F87: =+IFERROR(F82/F86,"") -> 2.7209302 | H87: =+$F$56 -> 45657 | I87: =+F88-F87 -> -1.7099302 | J87: =+F87*(F87<F88) -> 0
A88: =+A78 -> 5 | C88: =+"Soglia per settore "&$H$7 -> Soglia per settore | E88: {=+INDEX(Tabella139[],rateco,Score!$A87)} -> 1.011 | F88: {=+INDEX(Tabella139[],rateco,Score!$A87)} -> 1.011 | G88: =+IF(a,(H88>H87)*1,(F88>F87)*1) -> 0
A89: 6 | C89: 4) REDDITIVITÀ
C90: Calcolo Numeratore: Cash flow
C91: Utile (perdita) d'esercizio | E91: 40000 | F91: 50000
C92: Costi non monetari (Amm., Acc., Sval.) | E92: 25000 | F92: 28000
C93: - Ricavi non monetari (Rival., Imposte Anticipate.) | E93: 5000 | F93: 6000
C94: Totale non rapportato ad anno | E94: =SUM(E91:E93) -> 70000 | F94: =SUM(F91:F93) -> 84000
C95: Totale Numeratore | E95: =+E94/D13 -> 70000 | F95: =+F94/E13 -> 84000
C96: Calcolo Denominatore: Attivo
C97: Totale Attivo Stato Patrimoniale | E97: 750000 | F97: 800000
C98: Totale Denominatore | E98: =+E97 -> 750000 | F98: =+F97 -> 800000
A99: =+A89 -> 6 | C99: =+C89 -> 4) REDDITIVITÀ | E99: =+IFERROR(E95/E98,"") -> 0.093333333 | F99: =+IFERROR(F95/F98,"") -> 0.105 | H99: =+$F$56 -> 45657 | I99: =+F100-F99 -> -0.091 | J99: =+F99*(F99<F100) -> 0
A100: =+A89 -> 6 | C100: =+"Soglia per settore "&$H$7 -> Soglia per settore | E100: {=+INDEX(Tabella139[],rateco,Score!$A99)} -> 0.014 | F100: {=+INDEX(Tabella139[],rateco,Score!$A99)} -> 0.014 | G100: =+IF(a,(H100>H99)*1,(F100>F99)*1) -> 0
A101: 7 | C101: 5) ALTRI INDICI DI INDEBITAMENTO
C102: Calcolo Numeratore: Debiti Tributari e Previdenziali
...

Sheet ATECO
A1: CODICE | B1: DESCRIZIONE | C1: COD. CRISI | D1: descr | E1: Soglia1 | F1: Soglia2 | G1: Soglia3 | H1: Soglia4 | I1: Soglia5 | L1: Cod | M1: Descr | N1: Settore | R1: Cod. Crisi | S1: Desc. Crisi | T1: OF/Ric | U1: PN/Tot.Deb | V1: AC/PB | W1: CashFlow/Att | X1: Deb.Trib./Att
A2: A | B2: AGRICOLTURA, SILVICOLTURA E PESCA | C2: 1 | D2: =+VLOOKUP(AtecoCrisi[[#This Row],[COD. CRISI]],Tabella139[],2,0) -> A) Agricoltura silvicoltura e pesca | E2: =+VLOOKUP(C2,$R$2:$X$11,3,FALSE) -> 0.028 | F2: =+VLOOKUP(C2,$R$2:$X$11,4,FALSE) -> 0.094 | G2: =+VLOOKUP(C2,$R$2:$X$11,5,FALSE) -> 0.921 | H2: =+VLOOKUP(C2,$R$2:$X$11,6,FALSE) -> 0.003 | I2: =+VLOOKUP(C2,$R$2:$X$11,7,FALSE) -> 0.056 | L2: 01.11.10 | M2: =+VLOOKUP(L2,A:B,2,0) -> Coltivazione di cereali (escluso il riso) | N2: =+VLOOKUP(L2,A:D,4,0) -> A) Agricoltura silvicoltura e pesca | R2: 1 | S2: A) Agricoltura silvicoltura e pesca | T2: 0.028 | U2: 0.094 | V2: 0.921 | W2: 0.003 | X2: 0.056
A3: 01 | B3: COLTIVAZIONI AGRICOLE E PRODUZIONE DI PRODOTTI ANIMALI, CACCIA E SERVIZI CONNESSI | C3: 1 | D3: =+VLOOKUP(AtecoCrisi[[#This Row],[COD. CRISI]],Tabella139[],2,0) -> A) Agricoltura silvicoltura e pesca | E3: =+VLOOKUP(C3,$R$2:$X$11,3,FALSE) -> 0.028 | F3: =+VLOOKUP(C3,$R$2:$X$11,4,FALSE) -> 0.094 | G3: =+VLOOKUP(C3,$R$2:$X$11,5,FALSE) -> 0.921 | H3: =+VLOOKUP(C3,$R$2:$X$11,6,FALSE) -> 0.003 | I3: =+VLOOKUP(C3,$R$2:$X$11,7,FALSE) -> 0.056 | L3: 01.11.20 | M3: =+VLOOKUP(L3,A:B,2,0) -> Coltivazione di semi oleosi | N3: =+VLOOKUP(L3,A:D,4,0) -> A) Agricoltura silvicoltura e pesca | R3: 2 | S3: B) Estrazione; C) Manifattura; D) Produzione energia/gas | T3: 0.03 | U3: 0.076 | V3: 0.937 | W3: 0.005 | X3: 0.049
A4: 01.11.10 | B4: Coltivazione di cereali (escluso il riso) | C4: 1 | D4: =+VLOOKUP(AtecoCrisi[[#This Row],[COD. CRISI]],Tabella139[],2,0) -> A) Agricoltura silvicoltura e pesca | E4: =+VLOOKUP(C4,$R$2:$X$11,3,FALSE) -> 0.028 | F4: =+VLOOKUP(C4,$R$2:$X$11,4,FALSE) -> 0.094 | G4: =+VLOOKUP(C4,$R$2:$X$11,5,FALSE) -> 0.921 | H4: =+VLOOKUP(C4,$R$2:$X$11,6,FALSE) -> 0.003 | I4: =+VLOOKUP(C4,$R$2:$X$11,7,FALSE) -> 0.056 | L4: 01.11.30 | M4: =+VLOOKUP(L4,A:B,2,0) -> Coltivazione di legumi da granella | N4: =+VLOOKUP(L4,A:D,4,0) -> A) Agricoltura silvicoltura e pesca | R4: 3 | S4: E) Fornitura acqua reti fognarie rifiuti; D) Trasmissione energia/gas | T4: 0.026 | U4: 0.067 | V4: 0.842 | W4: 0.019 | X4: 0.065
A5: 01.11.20 | B5: Coltivazione di semi oleosi | C5: 1 | D5: =+VLOOKUP(AtecoCrisi[[#This Row],[COD. CRISI]],Tabella139[],2,0) -> A) Agricoltura silvicoltura e pesca | E5: =+VLOOKUP(C5,$R$2:$X$11,3,FALSE) -> 0.028 | F5: =+VLOOKUP(C5,$R$2:$X$11,4,FALSE) -> 0.094 | G5: =+VLOOKUP(C5,$R$2:$X$11,5,FALSE) -> 0.921 | H5: =+VLOOKUP(C5,$R$2:$X$11,6,FALSE) -> 0.003 | I5: =+VLOOKUP(C5,$R$2:$X$11,7,FALSE) -> 0.056 | L5: 01.11.40 | M5: =+VLOOKUP(L5,A:B,2,0) -> Coltivazioni miste di cereali, legumi da granella e semi oleosi | N5: =+VLOOKUP(L5,A:D,4,0) -> A) Agricoltura silvicoltura e pesca | R5: 4 | S5: F41) Costruzione di edifici | T5: 0.038 | U5: 0.049 | V5: 1.08 | W5: 0.004 | X5: 0.038
A6: 01.11.30 | B6: Coltivazione di legumi da granella | C6: 1 | D6: =+VLOOKUP(AtecoCrisi[[#This Row],[COD. CRISI]],Tabella139[],2,0) -> A) Agricoltura silvicoltura e pesca | E6: =+VLOOKUP(C6,$R$2:$X$11,3,FALSE) -> 0.028 | F6: =+VLOOKUP(C6,$R$2:$X$11,4,FALSE) -> 0.094 | G6: =+VLOOKUP(C6,$R$2:$X$11,5,FALSE) -> 0.921 | H6: =+VLOOKUP(C6,$R$2:$X$11,6,FALSE) -> 0.003 | I6: =+VLOOKUP(C6,$R$2:$X$11,7,FALSE) -> 0.056 | L6: 01.12.00 | M6: =+VLOOKUP(L6,A:B,2,0) -> Coltivazione di riso | N6: =+VLOOKUP(L6,A:D,4,0) -> A) Agricoltura silvicoltura e pesca | R6: 5 | S6: F42) Ingegneria civile; F43) Costruzioni specializzate | T6: 0.028 | U6: 0.053 | V6: 1.011 | W6: 0.014 | X6: 0.053
A7: 01.11.40 | B7: Coltivazioni miste di cereali, legumi da granella e semi oleosi | C7: 1 | D7: =+VLOOKUP(AtecoCrisi[[#This Row],[COD. CRISI]],Tabella139[],2,0) -> A) Agricoltura silvicoltura e pesca | E7: =+VLOOKUP(C7,$R$2:$X$11,3,FALSE) -> 0.028 | F7: =+VLOOKUP(C7,$R$2:$X$11,4,FALSE) -> 0.094 | G7: =+VLOOKUP(C7,$R$2:$X$11,5,FALSE) -> 0.921 | H7: =+VLOOKUP(C7,$R$2:$X$11,6,FALSE) -> 0.003 | I7: =+VLOOKUP(C7,$R$2:$X$11,7,FALSE) -> 0.056 | L7: 01.13.10 | M7: =+VLOOKUP(L7,A:B,2,0) -> Coltivazione di ortaggi (inclusi i meloni) in foglia, a fusto, a frutto, in radici, bulbi e tuberi in piena aria (escluse barbabietola da zucchero e patate) | N7: =+VLOOKUP(L7,A:D,4,0) -> A) Agricoltura silvicoltura e pesca | R7: 6 | S7: G45) Commercio autoveicoli; G46) Comm. Ingrosso; D) Distr. Energia/gas | T7: 0.021 | U7: 0.063 | V7: 1.014 | W7: 0.006 | X7: 0.029
A8: 01.12.00 | B8: Coltivazione di riso | C8: 1 | D8: =+VLOOKUP(AtecoCrisi[[#This Row],[COD. CRISI]],Tabella139[],2,0) -> A) Agricoltura silvicoltura e pesca | E8: =+VLOOKUP(C8,$R$2:$X$11,3,FALSE) -> 0.028 | F8: =+VLOOKUP(C8,$R$2:$X$11,4,FALSE) -> 0.094 | G8: =+VLOOKUP(C8,$R$2:$X$11,5,FALSE) -> 0.921 | H8: =+VLOOKUP(C8,$R$2:$X$11,6,FALSE) -> 0.003 | I8: =+VLOOKUP(C8,$R$2:$X$11,7,FALSE) -> 0.056 | L8: 01.13.20 | M8: =+VLOOKUP(L8,A:B,2,0) -> Coltivazione di ortaggi (inclusi i meloni) in foglia, a fusto, a frutto, in radici, bulbi e tuberi in colture protette (escluse barbabietola da zucchero e patate) | N8: =+VLOOKUP(L8,A:D,4,0) -> A) Agricoltura silvicoltura e pesca | R8: 7 | S8: G47) Commercio dettaglio; I56) Bar e ristoranti | T8: 0.015 | U8: 0.042 | V8: 0.898 | W8: 0.01 | X8: 0.078
A9: 01.13.10 | B9: Coltivazione di ortaggi (inclusi i meloni) in foglia, a fusto, a frutto, in radici, bulbi e tuberi in piena aria (escluse barbabietola da zucchero e patate) | C9: 1 | D9: =+VLOOKUP(AtecoCrisi[[#This Row],[COD. CRISI]],Tabella139[],2,0) -> A) Agricoltura silvicoltura e pesca | E9: =+VLOOKUP(C9,$R$2:$X$11,3,FALSE) -> 0.028 | F9: =+VLOOKUP(C9,$R$2:$X$11,4,FALSE) -> 0.094 | G9: =+VLOOKUP(C9,$R$2:$X$11,5,FALSE) -> 0.921 | H9: =+VLOOKUP(C9,$R$2:$X$11,6,FALSE) -> 0.003 | I9: =+VLOOKUP(C9,$R$2:$X$11,7,FALSE) -> 0.056 | L9: 01.13.30 | M9: =+VLOOKUP(L9,A:B,2,0) -> Coltivazione di barbabietola da zucchero | N9: =+VLOOKUP(L9,A:D,4,0) -> A) Agricoltura silvicoltura e pesca | R9: 8 | S9: H) Trasporto e magazzinaggio; I55) Hotel | T9: 0.015 | U9: 0.041 | V9: 0.86 | W9: 0.014 | X9: 0.102
A10: 01.13.20 | B10: Coltivazione di ortaggi (inclusi i meloni) in foglia, a fusto, a frutto, in radici, bulbi e tuberi in colture protette (escluse barbabietola da zucchero e patate) | C10: 1 | D10: =+VLOOKUP(AtecoCrisi[[#This Row],[COD. CRISI]],Tabella139[],2,0) -> A) Agricoltura silvicoltura e pesca | E10: =+VLOOKUP(C10,$R$2:$X$11,3,FALSE) -> 0.028 | F10: =+VLOOKUP(C10,$R$2:$X$11,4,FALSE) -> 0.094 | G10: =+VLOOKUP(C10,$R$2:$X$11,5,FALSE) -> 0.921 | H10: =+VLOOKUP(C10,$R$2:$X$11,6,FALSE) -> 0.003 | I10: =+VLOOKUP(C10,$R$2:$X$11,7,FALSE) -> 0.056 | L10: 01.13.40 | M10: =+VLOOKUP(L10,A:B,2,0) -> Coltivazione di patate | N10: =+VLOOKUP(L10,A:D,4,0) -> A) Agricoltura silvicoltura e pesca | R10: 9 | S10: JMN) Servizi alle imprese | T10: 0.018 | U10: 0.052 | V10: 0.954 | W10: 0.017 | X10: 0.119
A11: 01.13.30 | B11: Coltivazione di barbabietola da zucchero | C11: 1 | D11: =+VLOOKUP(AtecoCrisi[[#This Row],[COD. CRISI]],Tabella139[],2,0) -> A) Agricoltura silvicoltura e pesca | E11: =+VLOOKUP(C11,$R$2:$X$11,3,FALSE) -> 0.028 | F11: =+VLOOKUP(C11,$R$2:$X$11,4,FALSE) -> 0.094 | G11: =+VLOOKUP(C11,$R$2:$X$11,5,FALSE) -> 0.921 | H11: =+VLOOKUP(C11,$R$2:$X$11,6,FALSE) -> 0.003 | I11: =+VLOOKUP(C11,$R$2:$X$11,7,FALSE) -> 0.056 | L11: 01.14.00 | M11: =+VLOOKUP(L11,A:B,2,0) -> Coltivazione di canna da zucchero | N11: =+VLOOKUP(L11,A:D,4,0) -> A) Agricoltura silvicoltura e pesca | R11: 10 | S11: PQRS) Servizi alle persone | T11: 0.027 | U11: 0.023 | V11: 0.698 | W11: 0.005 | X11: 0.146
A12: 01.13.40 | B12: Coltivazione di patate | C12: 1 | D12: =+VLOOKUP(AtecoCrisi[[#This Row],[COD. CRISI]],Tabella139[],2,0) -> A) Agricoltura silvicoltura e pesca | E12: =+VLOOKUP(C12,$R$2:$X$11,3,FALSE) -> 0.028 | F12: =+VLOOKUP(C12,$R$2:$X$11,4,FALSE) -> 0.094 | G12: =+VLOOKUP(C12,$R$2:$X$11,5,FALSE) -> 0.921 | H12: =+VLOOKUP(C12,$R$2:$X$11,6,FALSE) -> 0.003 | I12: =+VLOOKUP(C12,$R$2:$X$11,7,FALSE) -> 0.056 | L12: 01.15.00 | M12: =+VLOOKUP(L12,A:B,2,0) -> Coltivazione di tabacco | N12: =+VLOOKUP(L12,A:D,4,0) -> A) Agricoltura silvicoltura e pesca
A13: 01.14.00 | B13: Coltivazione di canna da zucchero | C13: 1 | D13: =+VLOOKUP(AtecoCrisi[[#This Row],[COD. CRISI]],Tabella139[],2,0) -> A) Agricoltura silvicoltura e pesca | E13: =+VLOOKUP(C13,$R$2:$X$11,3,FALSE) -> 0.028 | F13: =+VLOOKUP(C13,$R$2:$X$11,4,FALSE) -> 0.094 | G13: =+VLOOKUP(C13,$R$2:$X$11,5,FALSE) -> 0.921 | H13: =+VLOOKUP(C13,$R$2:$X$11,6,FALSE) -> 0.003 | I13: =+VLOOKUP(C13,$R$2:$X$11,7,FALSE) -> 0.056 | L13: 01.16.00 | M13: =+VLOOKUP(L13,A:B,2,0) -> Coltivazione di piante per la preparazione di fibre tessili | N13: =+VLOOKUP(L13,A:D,4,0) -> A) Agricoltura silvicoltura e pesca
A14: 01.15.00 | B14: Coltivazione di tabacco | C14: 1 | D14: =+VLOOKUP(AtecoCrisi[[#This Row],[COD. CRISI]],Tabella139[],2,0) -> A) Agricoltura silvicoltura e pesca | E14: =+VLOOKUP(C14,$R$2:$X$11,3,FALSE) -> 0.028 | F14: =+VLOOKUP(C14,$R$2:$X$11,4,FALSE) -> 0.094 | G14: =+VLOOKUP(C14,$R$2:$X$11,5,FALSE) -> 0.921 | H14: =+VLOOKUP(C14,$R$2:$X$11,6,FALSE) -> 0.003 | I14: =+VLOOKUP(C14,$R$2:$X$11,7,FALSE) -> 0.056 | L14: 01.19.10 | M14: =+VLOOKUP(L14,A:B,2,0) -> Coltivazione di fiori in piena aria | N14: =+VLOOKUP(L14,A:D,4,0) -> A) Agricoltura silvicoltura e pesca
A15: 01.16.00 | B15: Coltivazione di piante per la preparazione di fibre tessili | C15: 1 | D15: =+VLOOKUP(AtecoCrisi[[#This Row],[COD. CRISI]],Tabella139[],2,0) -> A) Agricoltura silvicoltura e pesca | E15: =+VLOOKUP(C15,$R$2:$X$11,3,FALSE) -> 0.028 | F15: =+VLOOKUP(C15,$R$2:$X$11,4,FALSE) -> 0.094 | G15: =+VLOOKUP(C15,$R$2:$X$11,5,FALSE) -> 0.921 | H15: =+VLOOKUP(C15,$R$2:$X$11,6,FALSE) -> 0.003 | I15: =+VLOOKUP(C15,$R$2:$X$11,7,FALSE) -> 0.056 | L15: 01.19.20 | M15: =+VLOOKUP(L15,A:B,2,0) -> Coltivazione di fiori in colture protette | N15: =+VLOOKUP(L15,A:D,4,0) -> A) Agricoltura silvicoltura e pesca
A16: 01.19.10 | B16: Coltivazione di fiori in piena aria | C16: 1 | D16: =+VLOOKUP(AtecoCrisi[[#This Row],[COD. CRISI]],Tabella139[],2,0) -> A) Agricoltura silvicoltura e pesca | E16: =+VLOOKUP(C16,$R$2:$X$11,3,FALSE) -> 0.028 | F16: =+VLOOKUP(C16,$R$2:$X$11,4,FALSE) -> 0.094 | G16: =+VLOOKUP(C16,$R$2:$X$11,5,FALSE) -> 0.921 | H16: =+VLOOKUP(C16,$R$2:$X$11,6,FALSE) -> 0.003 | I16: =+VLOOKUP(C16,$R$2:$X$11,7,FALSE) -> 0.056 | L16: 01.19.90 | M16: =+VLOOKUP(L16,A:B,2,0) -> Coltivazione di piante da foraggio e di altre colture non permanenti | N16: =+VLOOKUP(L16,A:D,4,0) -> A) Agricoltura silvicoltura e pesca
A17: 01.19.20 | B17: Coltivazione di fiori in colture protette | C17: 1 | D17: =+VLOOKUP(AtecoCrisi[[#This Row],[COD. CRISI]],Tabella139[],2,0) -> A) Agricoltura silvicoltura e pesca | E17: =+VLOOKUP(C17,$R$2:$X$11,3,FALSE) -> 0.028 | F17: =+VLOOKUP(C17,$R$2:$X$11,4,FALSE) -> 0.094 | G17: =+VLOOKUP(C17,$R$2:$X$11,5,FALSE) -> 0.921 | H17: =+VLOOKUP(C17,$R$2:$X$11,6,FALSE) -> 0.003 | I17: =+VLOOKUP(C17,$R$2:$X$11,7,FALSE) -> 0.056 | L17: 01.21.00 | M17: =+VLOOKUP(L17,A:B,2,0) -> Coltivazione di uva | N17: =+VLOOKUP(L17,A:D,4,0) -> A) Agricoltura silvicoltura e pesca
A18: 01.19.90 | B18: Coltivazione di piante da foraggio e di altre colture non permanenti | C18: 1 | D18: =+VLOOKUP(AtecoCrisi[[#This Row],[COD. CRISI]],Tabella139[],2,0) -> A) Agricoltura silvicoltura e pesca | E18: =+VLOOKUP(C18,$R$2:$X$11,3,FALSE) -> 0.028 | F18: =+VLOOKUP(C18,$R$2:$X$11,4,FALSE) -> 0.094 | G18: =+VLOOKUP(C18,$R$2:$X$11,5,FALSE) -> 0.921 | H18: =+VLOOKUP(C18,$R$2:$X$11,6,FALSE) -> 0.003 | I18: =+VLOOKUP(C18,$R$2:$X$11,7,FALSE) -> 0.056 | L18: 01.22.00 | M18: =+VLOOKUP(L18,A:B,2,0) -> Coltivazione di frutta di origine tropicale e subtropicale | N18: =+VLOOKUP(L18,A:D,4,0) -> A) Agricoltura silvicoltura e pesca
A19: 01.21.00 | B19: Coltivazione di uva | C19: 1 | D19: =+VLOOKUP(AtecoCrisi[[#This Row],[COD. CRISI]],Tabella139[],2,0) -> A) Agricoltura silvicoltura e pesca | E19: =+VLOOKUP(C19,$R$2:$X$11,3,FALSE) -> 0.028 | F19: =+VLOOKUP(C19,$R$2:$X$11,4,FALSE) -> 0.094 | G19: =+VLOOKUP(C19,$R$2:$X$11,5,FALSE) -> 0.921 | H19: =+VLOOKUP(C19,$R$2:$X$11,6,FALSE) -> 0.003 | I19: =+VLOOKUP(C19,$R$2:$X$11,7,FALSE) -> 0.056 | L19: 01.23.00 | M19: =+VLOOKUP(L19,A:B,2,0) -> Coltivazione di agrumi | N19: =+VLOOKUP(L19,A:D,4,0) -> A) Agricoltura silvicoltura e pesca
A20: 01.22.00 | B20: Coltivazione di frutta di origine tropicale e subtropicale | C20: 1 | D20: =+VLOOKUP(AtecoCrisi[[#This Row],[COD. CRISI]],Tabella139[],2,0) -> A) Agricoltura silvicoltura e pesca | E20: =+VLOOKUP(C20,$R$2:$X$11,3,FALSE) -> 0.028 | F20: =+VLOOKUP(C20,$R$2:$X$11,4,FALSE) -> 0.094 | G20: =+VLOOKUP(C20,$R$2:$X$11,5,FALSE) -> 0.921 | H20: =+VLOOKUP(C20,$R$2:$X$11,6,FALSE) -> 0.003 | I20: =+VLOOKUP(C20,$R$2:$X$11,7,FALSE) -> 0.056 | L20: 01.24.00 | M20: =+VLOOKUP(L20,A:B,2,0) -> Coltivazione di pomacee e frutta a nocciolo | N20: =+VLOOKUP(L20,A:D,4,0) -> A) Agricoltura silvicoltura e pesca
A21: 01.23.00 | B21: Coltivazione di agrumi | C21: 1 | D21: =+VLOOKUP(AtecoCrisi[[#This Row],[COD. CRISI]],Tabella139[],2,0) -> A) Agricoltura silvicoltura e pesca | E21: =+VLOOKUP(C21,$R$2:$X$11,3,FALSE) -> 0.028 | F21: =+VLOOKUP(C21,$R$2:$X$11,4,FALSE) -> 0.094 | G21: =+VLOOKUP(C21,$R$2:$X$11,5,FALSE) -> 0.921 | H21: =+VLOOKUP(C21,$R$2:$X$11,6,FALSE) -> 0.003 | I21: =+VLOOKUP(C21,$R$2:$X$11,7,FALSE) -> 0.056 | L21: 01.25.00 | M21: =+VLOOKUP(L21,A:B,2,0) -> Coltivazione di altri alberi da frutta, frutti di bosco e frutta in guscio | N21: =+VLOOKUP(L21,A:D,4,0) -> A) Agricoltura silvicoltura e pesca
A22: 01.24.00 | B22: Coltivazione di pomacee e frutta a nocciolo | C22: 1 | D22: =+VLOOKUP(AtecoCrisi[[#This Row],[COD. CRISI]],Tabella139[],2,0) -> A) Agricoltura silvicoltura e pesca | E22: =+VLOOKUP(C22,$R$2:$X$11,3,FALSE) -> 0.028 | F22: =+VLOOKUP(C22,$R$2:$X$11,4,FALSE) -> 0.094 | G22: =+VLOOKUP(C22,$R$2:$X$11,5,FALSE) -> 0.921 | H22: =+VLOOKUP(C22,$R$2:$X$11,6,FALSE) -> 0.003 | I22: =+VLOOKUP(C22,$R$2:$X$11,7,FALSE) -> 0.056 | L22: 01.26.00 | M22: =+VLOOKUP(L22,A:B,2,0) -> Coltivazione di frutti oleosi | N22: =+VLOOKUP(L22,A:D,4,0) -> A) Agricoltura silvicoltura e pesca
A23: 01.25.00 | B23: Coltivazione di altri alberi da frutta, frutti di bosco e frutta in guscio | C23: 1 | D23: =+VLOOKUP(AtecoCrisi[[#This Row],[COD. CRISI]],Tabella139[],2,0) -> A) Agricoltura silvicoltura e pesca | E23: =+VLOOKUP(C23,$R$2:$X$11,3,FALSE) -> 0.028 | F23: =+VLOOKUP(C23,$R$2:$X$11,4,FALSE) -> 0.094 | G23: =+VLOOKUP(C23,$R$2:$X$11,5,FALSE) -> 0.921 | H23: =+VLOOKUP(C23,$R$2:$X$11,6,FALSE) -> 0.003 | I23: =+VLOOKUP(C23,$R$2:$X$11,7,FALSE) -> 0.056 | L23: 01.27.00 | M23: =+VLOOKUP(L23,A:B,2,0) -> Coltivazione di piante per la produzione di bevande | N23: =+VLOOKUP(L23,A:D,4,0) -> A) Agricoltura silvicoltura e pesca
... A499: 33.13.01 | B499: Riparazione e manutenzione di apparecchiature ottiche, fotografiche e cinematografiche (escluse videocamere) | C499: 2 | D499: =+VLOOKUP(AtecoCrisi[[#This Row],[COD. CRISI]],Tabella139[],2,0) -> B) Estrazione; C) Manifattura; D) Produzione energia/gas | E499: =+VLOOKUP(C499,$R$2:$X$11,3,FALSE) -> 0.03 | F499: =+VLOOKUP(C499,$R$2:$X$11,4,FALSE) -> 0.076 | G499: =+VLOOKUP(C499,$R$2:$X$11,5,FALSE) -> 0.937 | H499: =+VLOOKUP(C499,$R$2:$X$11,6,FALSE) -> 0.005 | I499: =+VLOOKUP(C499,$R$2:$X$11,7,FALSE) -> 0.049 | L499: 38.11.00 | M499: =+VLOOKUP(L499,A:B,2,0) -> Raccolta di rifiuti solidi non pericolosi | N499: =+VLOOKUP(L499,A:D,4,0) -> E) Fornitura acqua reti fognarie rifiuti; D) Trasmissione energia/gas
A500: 33.13.02 | C500: 2 | D500: =+VLOOKUP(AtecoCrisi[[#This Row],[COD. CRISI]],Tabella139[],2,0) -> B) Estrazione; C) Manifattura; D) Produzione energia/gas | E500: =+VLOOKUP(C500,$R$2:$X$11,3,FALSE) -> 0.03 | F500: =+VLOOKUP(C500,$R$2:$X$11,4,FALSE) -> 0.076 | G500: =+VLOOKUP(C500,$R$2:$X$11,5,FALSE) -> 0.937 | H500: =+VLOOKUP(C500,$R$2:$X$11,6,FALSE) -> 0.005 | I500: =+VLOOKUP(C500,$R$2:$X$11,7,FALSE) -> 0.049 | L500: 38.12.00 | M500: =+VLOOKUP(L500,A:B,2,0) -> Raccolta di rifiuti pericolosi solidi e non solidi | N500: =+VLOOKUP(L500,A:D,4,0) -> E) Fornitura acqua reti fognarie rifiuti; D) Trasmissione energia/gas
A501: 33.13.03 | B501: Riparazione e manutenzione di apparecchi elettromedicali, di materiale medico-chirurgico e veterinario, di apparecchi e strumenti per odontoiatria | C501: 2 | D501: =+VLOOKUP(AtecoCrisi[[#This Row],[COD. CRISI]],Tabella139[],2,0) -> B) Estrazione; C) Manifattura; D) Produzione energia/gas | E501: =+VLOOKUP(C501,$R$2:$X$11,3,FALSE) -> 0.03 | F501: =+VLOOKUP(C501,$R$2:$X$11,4,FALSE) -> 0.076 | G501: =+VLOOKUP(C501,$R$2:$X$11,5,FALSE) -> 0.937 | H501: =+VLOOKUP(C501,$R$2:$X$11,6,FALSE) -> 0.005 | I501: =+VLOOKUP(C501,$R$2:$X$11,7,FALSE) -> 0.049 | L501: 38.21.01 | M501: =+VLOOKUP(L501,A:B,2,0) -> Produzione di compost | N501: =+VLOOKUP(L501,A:D,4,0) -> E) Fornitura acqua reti fognarie rifiuti; D) Trasmissione energia/gas
A502: 33.13.04 | B502: Riparazione e manutenzione di apparati di distillazione per laboratori, di centrifughe per laboratori e di macchinari per pulizia ad ultrasuoni per laboratori | C502: 2 | D502: =+VLOOKUP(AtecoCrisi[[#This Row],[COD. CRISI]],Tabella139[],2,0) -> B) Estrazione; C) Manifattura; D) Produzione energia/gas | E502: =+VLOOKUP(C502,$R$2:$X$11,3,FALSE) -> 0.03 | F502: =+VLOOKUP(C502,$R$2:$X$11,4,FALSE) -> 0.076 | G502: =+VLOOKUP(C502,$R$2:$X$11,5,FALSE) -> 0.937 | H502: =+VLOOKUP(C502,$R$2:$X$11,6,FALSE) -> 0.005 | I502: =+VLOOKUP(C502,$R$2:$X$11,7,FALSE) -> 0.049 | L502: 38.21.09 | M502: =+VLOOKUP(L502,A:B,2,0) -> Trattamento e smaltimento di altri rifiuti non pericolosi | N502: =+VLOOKUP(L502,A:D,4,0) -> E) Fornitura acqua reti fognarie rifiuti; D) Trasmissione energia/gas
A503: 33.13.09 | B503: Riparazione e manutenzione di altre apparecchiature elettroniche (escluse quelle per le telecomunicazioni ed i computer) | C503: 2 | D503: =+VLOOKUP(AtecoCrisi[[#This Row],[COD. CRISI]],Tabella139[],2,0) -> B) Estrazione; C) Manifattura; D) Produzione energia/gas | E503: =+VLOOKUP(C503,$R$2:$X$11,3,FALSE) -> 0.03 | F503: =+VLOOKUP(C503,$R$2:$X$11,4,FALSE) -> 0.076 | G503: =+VLOOKUP(C503,$R$2:$X$11,5,FALSE) -> 0.937 | H503: =+VLOOKUP(C503,$R$2:$X$11,6,FALSE) -> 0.005 | I503: =+VLOOKUP(C503,$R$2:$X$11,7,FALSE) -> 0.049 | L503: 38.22.00 | M503: =+VLOOKUP(L503,A:B,2,0) -> Trattamento e smaltimento di rifiuti pericolosi | N503: =+VLOOKUP(L503,A:D,4,0) -> E) Fornitura acqua reti fognarie rifiuti; D) Trasmissione energia/gas
A504: 33.14.00 | B504: Riparazione e manutenzione di apparecchiature elettriche (esclusi gli elettrodomestici) | C504: 2 | D504: =+VLOOKUP(AtecoCrisi[[#This Row],[COD. CRISI]],Tabella139[],2,0) -> B) Estrazione; C) Manifattura; D) Produzione energia/gas | E504: =+VLOOKUP(C504,$R$2:$X$11,3,FALSE) -> 0.03 | F504: =+VLOOKUP(C504,$R$2:$X$11,4,FALSE) -> 0.076 | G504: =+VLOOKUP(C504,$R$2:$X$11,5,FALSE) -> 0.937 | H504: =+VLOOKUP(C504,$R$2:$X$11,6,FALSE) -> 0.005 | I504: =+VLOOKUP(C504,$R$2:$X$11,7,FALSE) -> 0.049 | L504: 38.31.10 | M504: =+VLOOKUP(L504,A:B,2,0) -> Demolizione di carcasse | N504: =+VLOOKUP(L504,A:D,4,0) -> E) Fornitura acqua reti fognarie rifiuti; D) Trasmissione energia/gas
A505: 33.14.01 | C505: 2 | D505: =+VLOOKUP(AtecoCrisi[[#This Row],[COD. CRISI]],Tabella139[],2,0) -> B) Estrazione; C) Manifattura; D) Produzione energia/gas | E505: =+VLOOKUP(C505,$R$2:$X$11,3,FALSE) -> 0.03 | F505: =+VLOOKUP(C505,$R$2:$X$11,4,FALSE) -> 0.076 | G505: =+VLOOKUP(C505,$R$2:$X$11,5,FALSE) -> 0.937 | H505: =+VLOOKUP(C505,$R$2:$X$11,6,FALSE) -> 0.005 | I505: =+VLOOKUP(C505,$R$2:$X$11,7,FALSE) -> 0.049 | L505: 38.31.20 | M505: =+VLOOKUP(L505,A:B,2,0) -> Cantieri di demolizione navali | N505: =+VLOOKUP(L505,A:D,4,0) -> E) Fornitura acqua reti fognarie rifiuti; D) Trasmissione energia/gas
A506: 33.14.09 | C506: 2 | D506: =+VLOOKUP(AtecoCrisi[[#This Row],[COD. CRISI]],Tabella139[],2,0) -> B) Estrazione; C) Manifattura; D) Produzione energia/gas | E506: =+VLOOKUP(C506,$R$2:$X$11,3,FALSE) -> 0.03 | F506: =+VLOOKUP(C506,$R$2:$X$11,4,FALSE) -> 0.076 | G506: =+VLOOKUP(C506,$R$2:$X$11,5,FALSE) -> 0.937 | H506: =+VLOOKUP(C506,$R$2:$X$11,6,FALSE) -> 0.005 | I506: =+VLOOKUP(C506,$R$2:$X$11,7,FALSE) -> 0.049 | L506: 38.32.10 | M506: =+VLOOKUP(L506,A:B,2,0) -> Recupero e preparazione per il riciclaggio di cascami e rottami metallici | N506: =+VLOOKUP(L506,A:D,4,0) -> E) Fornitura acqua reti fognarie rifiuti; D) Trasmissione energia/gas
A507: 33.15.00 | B507: Riparazione e manutenzione di navi commerciali e imbarcazioni da diporto (esclusi i loro motori) | C507: 2 | D507: =+VLOOKUP(AtecoCrisi[[#This Row],[COD. CRISI]],Tabella139[],2,0) -> B) Estrazione; C) Manifattura; D) Produzione energia/gas | E507: =+VLOOKUP(C507,$R$2:$X$11,3,FALSE) -> 0.03 | F507: =+VLOOKUP(C507,$R$2:$X$11,4,FALSE) -> 0.076 | G507: =+VLOOKUP(C507,$R$2:$X$11,5,FALSE) -> 0.937 | H507: =+VLOOKUP(C507,$R$2:$X$11,6,FALSE) -> 0.005 | I507: =+VLOOKUP(C507,$R$2:$X$11,7,FALSE) -> 0.049 | L507: 38.32.20 | M507: =+VLOOKUP(L507,A:B,2,0) -> Recupero e preparazione per il riciclaggio di materiale plastico per produzione di materie prime plastiche, resine sintetiche | N507: =+VLOOKUP(L507,A:D,4,0) -> E) Fornitura acqua reti fognarie rifiuti; D) Trasmissione energia/gas
A508: 33.16.00 | B508: Riparazione e manutenzione di aeromobili e di veicoli spaziali | C508: 2 | D508: =+VLOOKUP(AtecoCrisi[[#This Row],[COD. CRISI]],Tabella139[],2,0) -> B) Estrazione; C) Manifattura; D) Produzione energia/gas | E508: =+VLOOKUP(C508,$R$2:$X$11,3,FALSE) -> 0.03 | F508: =+VLOOKUP(C508,$R$2:$X$11,4,FALSE) -> 0.076 | G508: =+VLOOKUP(C508,$R$2:$X$11,5,FALSE) -> 0.937 | H508: =+VLOOKUP(C508,$R$2:$X$11,6,FALSE) -> 0.005 | I508: =+VLOOKUP(C508,$R$2:$X$11,7,FALSE) -> 0.049 | L508: 38.32.30 | M508: =+VLOOKUP(L508,A:B,2,0) -> Recupero e preparazione per il riciclaggio dei rifiuti solidi urbani, industriali e biomasse | N508: =+VLOOKUP(L508,A:D,4,0) -> E) Fornitura acqua reti fognarie rifiuti; D) Trasmissione energia/gas
A509: 33.17.00 | B509: Riparazione e manutenzione di materiale rotabile ferroviario, tranviario, filoviario e per metropolitane (esclusi i loro motori) | C509: 2 | D509: =+VLOOKUP(AtecoCrisi[[#This Row],[COD. CRISI]],Tabella139[],2,0) -> B) Estrazione; C) Manifattura; D) Produzione energia/gas | E509: =+VLOOKUP(C509,$R$2:$X$11,3,FALSE) -> 0.03 | F509: =+VLOOKUP(C509,$R$2:$X$11,4,FALSE) -> 0.076 | G509: =+VLOOKUP(C509,$R$2:$X$11,5,FALSE) -> 0.937 | H509: =+VLOOKUP(C509,$R$2:$X$11,6,FALSE) -> 0.005 | I509: =+VLOOKUP(C509,$R$2:$X$11,7,FALSE) -> 0.049 | L509: 39.00.01 | M509: =+VLOOKUP(L509,A:B,2,0) -> Attività di rimozione di strutture ed elementi in amianto specializzata per l'edilizia | N509: =+VLOOKUP(L509,A:D,4,0) -> E) Fornitura acqua reti fognarie rifiuti; D) Trasmissione energia/gas
A510: 33.19.01 | B510: Riparazioni di pallets e contenitori in legno per trasporto | C510: 2 | D510: =+VLOOKUP(AtecoCrisi[[#This Row],[COD. CRISI]],Tabella139[],2,0) -> B) Estrazione; C) Manifattura; D) Produzione energia/gas | E510: =+VLOOKUP(C510,$R$2:$X$11,3,FALSE) -> 0.03 | F510: =+VLOOKUP(C510,$R$2:$X$11,4,FALSE) -> 0.076 | G510: =+VLOOKUP(C510,$R$2:$X$11,5,FALSE) -> 0.937 | H510: =+VLOOKUP(C510,$R$2:$X$11,6,FALSE) -> 0.005 | I510: =+VLOOKUP(C510,$R$2:$X$11,7,FALSE) -> 0.049 | L510: 39.00.09 | M510: =+VLOOKUP(L510,A:B,2,0) -> Altre attività di risanamento e altri servizi di gestione dei rifiuti | N510: =+VLOOKUP(L510,A:D,4,0) -> E) Fornitura acqua reti fognarie rifiuti; D) Trasmissione energia/gas
A511: 33.19.02 | B511: Riparazione di prodotti in gomma | C511: 2 | D511: =+VLOOKUP(AtecoCrisi[[#This Row],[COD. CRISI]],Tabella139[],2,0) -> B) Estrazione; C) Manifattura; D) Produzione energia/gas | E511: =+VLOOKUP(C511,$R$2:$X$11,3,FALSE) -> 0.03 | F511: =+VLOOKUP(C511,$R$2:$X$11,4,FALSE) -> 0.076 | G511: =+VLOOKUP(C511,$R$2:$X$11,5,FALSE) -> 0.937 | H511: =+VLOOKUP(C511,$R$2:$X$11,6,FALSE) -> 0.005 | I511: =+VLOOKUP(C511,$R$2:$X$11,7,FALSE) -> 0.049 | L511: 41.10.00 | M511: =+VLOOKUP(L511,A:B,2,0) -> Sviluppo di progetti immobiliari senza costruzione | N511: =+VLOOKUP(L511,A:D,4,0) -> F41) Costruzione di edifici
A512: 33.19.03 | B512: Riparazione di articoli in vetro | C512: 2 | D512: =+VLOOKUP(AtecoCrisi[[#This Row],[COD. CRISI]],Tabella139[],2,0) -> B) Estrazione; C) Manifattura; D) Produzione energia/gas | E512: =+VLOOKUP(C512,$R$2:$X$11,3,FALSE) -> 0.03 | F512: =+VLOOKUP(C512,$R$2:$X$11,4,FALSE) -> 0.076 | G512: =+VLOOKUP(C512,$R$2:$X$11,5,FALSE) -> 0.937 | H512: =+VLOOKUP(C512,$R$2:$X$11,6,FALSE) -> 0.005 | I512: =+VLOOKUP(C512,$R$2:$X$11,7,FALSE) -> 0.049 | L512: 41.20.00 | M512: =+VLOOKUP(L512,A:B,2,0) -> Costruzione di edifici residenziali e non residenziali | N512: =+VLOOKUP(L512,A:D,4,0) -> F41) Costruzione di edifici
A513: 33.19.04 | B513: Riparazioni di altri prodotti in legno nca | C513: 2 | D513: =+VLOOKUP(AtecoCrisi[[#This Row],[COD. CRISI]],Tabella139[],2,0) -> B) Estrazione; C) Manifattura; D) Produzione energia/gas | E513: =+VLOOKUP(C513,$R$2:$X$11,3,FALSE) -> 0.03 | F513: =+VLOOKUP(C513,$R$2:$X$11,4,FALSE) -> 0.076 | G513: =+VLOOKUP(C513,$R$2:$X$11,5,FALSE) -> 0.937 | H513: =+VLOOKUP(C513,$R$2:$X$11,6,FALSE) -> 0.005 | I513: =+VLOOKUP(C513,$R$2:$X$11,7,FALSE) -> 0.049 | L513: 42.11.00 | M513: =+VLOOKUP(L513,A:B,2,0) -> Costruzione di strade, autostrade e piste aeroportuali | N513: =+VLOOKUP(L513,A:D,4,0) -> F42) Ingegneria civile; F43) Costruzioni specializzate
A514: 33.19.09 | B514: Riparazione di altre apparecchiature nca | C514: 2 | D514: =+VLOOKUP(AtecoCrisi[[#This Row],[COD. CRISI]],Tabella139[],2,0) -> B) Estrazione; C) Manifattura; D) Produzione energia/gas | E514: =+VLOOKUP(C514,$R$2:$X$11,3,FALSE) -> 0.03 | F514: =+VLOOKUP(C514,$R$2:$X$11,4,FALSE) -> 0.076 | G514: =+VLOOKUP(C514,$R$2:$X$11,5,FALSE) -> 0.937 | H514: =+VLOOKUP(C514,$R$2:$X$11,6,FALSE) -> 0.005 | I514: =+VLOOKUP(C514,$R$2:$X$11,7,FALSE) -> 0.049 | L514: 42.12.00 | M514: =+VLOOKUP(L514,A:B,2,0) -> Costruzione di linee ferroviarie e metropolitane | N514: =+VLOOKUP(L514,A:D,4,0) -> F42) Ingegneria civile; F43) Costruzioni specializzate
A515: 33.20.01 | B515: Installazione di motori, generatori e trasformatori elettrici; di apparecchiature per la distribuzione e il controllo dell'elettricità (esclusa l'installazione all'interno degli edifici) | C515: 2 | D515: =+VLOOKUP(AtecoCrisi[[#This Row],[COD. CRISI]],Tabella139[],2,0) -> B) Estrazione; C) Manifattura; D) Produzione energia/gas | E515: =+VLOOKUP(C515,$R$2:$X$11,3,FALSE) -> 0.03 | F515: =+VLOOKUP(C515,$R$2:$X$11,4,FALSE) -> 0.076 | G515: =+VLOOKUP(C515,$R$2:$X$11,5,FALSE) -> 0.937 | H515: =+VLOOKUP(C515,$R$2:$X$11,6,FALSE) -> 0.005 | I515: =+VLOOKUP(C515,$R$2:$X$11,7,FALSE) -> 0.049 | L515: 42.13.00 | M515: =+VLOOKUP(L515,A:B,2,0) -> Costruzione di ponti e gallerie | N515: =+VLOOKUP(L515,A:D,4,0) -> F42) Ingegneria civile; F43) Costruzioni specializzate
A516: 33.20.02 | B516: Installazione di apparecchi elettrici ed elettronici per telecomunicazioni, di apparecchi trasmittenti radiotelevisivi, di impianti di apparecchiature elettriche ed elettroniche (esclusa l'installazione all'interno degli edifici) | C516: 2 | D516: =+VLOOKUP(AtecoCrisi[[#This Row],[COD. CRISI]],Tabella139[],2,0) -> B) Estrazione; C) Manifattura; D) Produzione energia/gas | E516: =+VLOOKUP(C516,$R$2:$X$11,3,FALSE) -> 0.03 | F516: =+VLOOKUP(C516,$R$2:$X$11,4,FALSE) -> 0.076 | G516: =+VLOOKUP(C516,$R$2:$X$11,5,FALSE) -> 0.937 | H516: =+VLOOKUP(C516,$R$2:$X$11,6,FALSE) -> 0.005 | I516: =+VLOOKUP(C516,$R$2:$X$11,7,FALSE) -> 0.049 | L516: 42.21.00 | M516: =+VLOOKUP(L516,A:B,2,0) -> Costruzione di opere di pubblica utilità per il trasporto di fluidi | N516: =+VLOOKUP(L516,A:D,4,0) -> F42) Ingegneria civile; F43) Costruzioni specializzate
A517: 33.20.03 | B517: Installazione di strumenti ed apparecchi di misurazione, controllo, prova, navigazione e simili (incluse le apparecchiature di controllo dei processi industriali) | C517: 2 | D517: =+VLOOKUP(AtecoCrisi[[#This Row],[COD. CRISI]],Tabella139[],2,0) -> B) Estrazione; C) Manifattura; D) Produzione energia/gas | E517: =+VLOOKUP(C517,$R$2:$X$11,3,FALSE) -> 0.03 | F517: =+VLOOKUP(C517,$R$2:$X$11,4,FALSE) -> 0.076 | G517: =+VLOOKUP(C517,$R$2:$X$11,5,FALSE) -> 0.937 | H517: =+VLOOKUP(C517,$R$2:$X$11,6,FALSE) -> 0.005 | I517: =+VLOOKUP(C517,$R$2:$X$11,7,FALSE) -> 0.049 | L517: 42.22.00 | M517: =+VLOOKUP(L517,A:B,2,0) -> Costruzione di opere di pubblica utilità per l'energia elettrica e le telecomunicazioni | N517: =+VLOOKUP(L517,A:D,4,0) -> F42) Ingegneria civile; F43) Costruzioni specializzate
A518: 33.20.04 | B518: Installazione di cisterne, serbatoi e contenitori in metallo | C518: 2 | D518: =+VLOOKUP(AtecoCrisi[[#This Row],[COD. CRISI]],Tabella139[],2,0) -> B) Estrazione; C) Manifattura; D) Produzione energia/gas | E518: =+VLOOKUP(C518,$R$2:$X$11,3,FALSE) -> 0.03 | F518: =+VLOOKUP(C518,$R$2:$X$11,4,FALSE) -> 0.076 | G518: =+VLOOKUP(C518,$R$2:$X$11,5,FALSE) -> 0.937 | H518: =+VLOOKUP(C518,$R$2:$X$11,6,FALSE) -> 0.005 | I518: =+VLOOKUP(C518,$R$2:$X$11,7,FALSE) -> 0.049 | L518: 42.91.00 | M518: =+VLOOKUP(L518,A:B,2,0) -> Costruzione di opere idrauliche | N518: =+VLOOKUP(L518,A:D,4,0) -> F42) Ingegneria civile; F43) Costruzioni specializzate
... A523: 33.20.09 | B523: Installazione di altre macchine ed apparecchiature industriali | C523: 2 | D523: =+VLOOKUP(AtecoCrisi[[#This Row],[COD. CRISI]],Tabella139[],2,0) -> B) Estrazione; C) Manifattura; D) Produzione energia/gas | E523: =+VLOOKUP(C523,$R$2:$X$11,3,FALSE) -> 0.03 | F523: =+VLOOKUP(C523,$R$2:$X$11,4,FALSE) -> 0.076 | G523: =+VLOOKUP(C523,$R$2:$X$11,5,FALSE) -> 0.937 | H523: =+VLOOKUP(C523,$R$2:$X$11,6,FALSE) -> 0.005 | I523: =+VLOOKUP(C523,$R$2:$X$11,7,FALSE) -> 0.049 | L523: 43.13.00 | M523: =+VLOOKUP(L523,A:B,2,0) -> Trivellazioni e perforazioni | N523: =+VLOOKUP(L523,A:D,4,0) -> F42) Ingegneria civile; F43) Costruzioni specializzate
A524: D | B524: FORNITURA DI ENERGIA ELETTRICA, GAS, VAPORE E ARIA CONDIZIONATA | D524: =+VLOOKUP(AtecoCrisi[[#This Row],[COD. CRISI]],Tabella139[],2,0) -> #N/A | E524: =+VLOOKUP(C524,$R$2:$X$11,3,FALSE) -> #N/A | F524: =+VLOOKUP(C524,$R$2:$X$11,4,FALSE) -> #N/A | G524: =+VLOOKUP(C524,$R$2:$X$11,5,FALSE) -> #N/A | H524: =+VLOOKUP(C524,$R$2:$X$11,6,FALSE) -> #N/A | I524: =+VLOOKUP(C524,$R$2:$X$11,7,FALSE) -> #N/A | L524: 43.21.01 | M524: =+VLOOKUP(L524,A:B,2,0) -> Installazione di impianti elettrici in edifici o in altre opere di costruzione (inclusa manutenzione e riparazione) | N524: =+VLOOKUP(L524,A:D,4,0) -> F42) Ingegneria civile; F43) Costruzioni specializzate
A525: 35 | B525: FORNITURA DI ENERGIA ELETTRICA, GAS, VAPORE E ARIA CONDIZIONATA | D525: =+VLOOKUP(AtecoCrisi[[#This Row],[COD. CRISI]],Tabella139[],2,0) -> #N/A | E525: =+VLOOKUP(C525,$R$2:$X$11,3,FALSE) -> #N/A | F525: =+VLOOKUP(C525,$R$2:$X$11,4,FALSE) -> #N/A | G525: =+VLOOKUP(C525,$R$2:$X$11,5,FALSE) -> #N/A | H525: =+VLOOKUP(C525,$R$2:$X$11,6,FALSE) -> #N/A | I525: =+VLOOKUP(C525,$R$2:$X$11,7,FALSE) -> #N/A | L525: 43.21.02 | M525: =+VLOOKUP(L525,A:B,2,0) -> Installazione di impianti elettronici (inclusa manutenzione e riparazione) | N525: =+VLOOKUP(L525,A:D,4,0) -> F42) Ingegneria civile; F43) Costruzioni specializzate
A526: 35.11.00 | B526: Produzione di energia elettrica | C526: 2 | D526: =+VLOOKUP(AtecoCrisi[[#This Row],[COD. CRISI]],Tabella139[],2,0) -> B) Estrazione; C) Manifattura; D) Produzione energia/gas | E526: =+VLOOKUP(C526,$R$2:$X$11,3,FALSE) -> 0.03 | F526: =+VLOOKUP(C526,$R$2:$X$11,4,FALSE) -> 0.076 | G526: =+VLOOKUP(C526,$R$2:$X$11,5,FALSE) -> 0.937 | H526: =+VLOOKUP(C526,$R$2:$X$11,6,FALSE) -> 0.005 | I526: =+VLOOKUP(C526,$R$2:$X$11,7,FALSE) -> 0.049 | L526: 43.21.03 | M526: =+VLOOKUP(L526,A:B,2,0) -> Installazione impianti di illuminazione stradale e dispositivi elettrici di segnalazione, illuminazione delle piste degli aeroporti (inclusa manutenzione e riparazione) | N526: =+VLOOKUP(L526,A:D,4,0) -> F42) Ingegneria civile; F43) Costruzioni specializzate
A527: 35.12.00 | B527: Trasmissione di energia elettrica | C527: 3 | D527: =+VLOOKUP(AtecoCrisi[[#This Row],[COD. CRISI]],Tabella139[],2,0) -> E) Fornitura acqua reti fognarie rifiuti; D) Trasmissione energia/gas | E527: =+VLOOKUP(C527,$R$2:$X$11,3,FALSE) -> 0.026 | F527: =+VLOOKUP(C527,$R$2:$X$11,4,FALSE) -> 0.067 | G527: =+VLOOKUP(C527,$R$2:$X$11,5,FALSE) -> 0.842 | H527: =+VLOOKUP(C527,$R$2:$X$11,6,FALSE) -> 0.019 | I527: =+VLOOKUP(C527,$R$2:$X$11,7,FALSE) -> 0.065 | L527: 43.22.01 | M527: =+VLOOKUP(L527,A:B,2,0) -> Installazione di impianti idraulici, di riscaldamento e di condizionamento dell'aria (inclusa manutenzione e riparazione) in edifici o in altre opere di costruzione | N527: =+VLOOKUP(L527,A:D,4,0) -> F42) Ingegneria civile; F43) Costruzioni specializzate
A528: 35.13.00 | B528: Distribuzione di energia elettrica | C528: 6 | D528: =+VLOOKUP(AtecoCrisi[[#This Row],[COD. CRISI]],Tabella139[],2,0) -> G45) Commercio autoveicoli; G46) Comm. Ingrosso; D) Distr. Energia/gas | E528: =+VLOOKUP(C528,$R$2:$X$11,3,FALSE) -> 0.021 | F528: =+VLOOKUP(C528,$R$2:$X$11,4,FALSE) -> 0.063 | G528: =+VLOOKUP(C528,$R$2:$X$11,5,FALSE) -> 1.014 | H528: =+VLOOKUP(C528,$R$2:$X$11,6,FALSE) -> 0.006 | I528: =+VLOOKUP(C528,$R$2:$X$11,7,FALSE) -> 0.029 | L528: 43.22.02 | M528: =+VLOOKUP(L528,A:B,2,0) -> Installazione di impianti per la distribuzione del gas (inclusa manutenzione e riparazione) | N528: =+VLOOKUP(L528,A:D,4,0) -> F42) Ingegneria civile; F43) Costruzioni specializzate
A529: 35.14.00 | B529: Commercio di energia elettrica | C529: 6 | D529: =+VLOOKUP(AtecoCrisi[[#This Row],[COD. CRISI]],Tabella139[],2,0) -> G45) Commercio autoveicoli; G46) Comm. Ingrosso; D) Distr. Energia/gas | E529: =+VLOOKUP(C529,$R$2:$X$11,3,FALSE) -> 0.021 | F529: =+VLOOKUP(C529,$R$2:$X$11,4,FALSE) -> 0.063 | G529: =+VLOOKUP(C529,$R$2:$X$11,5,FALSE) -> 1.014 | H529: =+VLOOKUP(C529,$R$2:$X$11,6,FALSE) -> 0.006 | I529: =+VLOOKUP(C529,$R$2:$X$11,7,FALSE) -> 0.029 | L529: 43.22.03 | M529: =+VLOOKUP(L529,A:B,2,0) -> Installazione di impianti di spegnimento antincendio (inclusi quelli integrati e la manutenzione e riparazione) | N529: =+VLOOKUP(L529,A:D,4,0) -> F42) Ingegneria civile; F43) Costruzioni specializzate
A530: 35.21.00 | B530: Produzione di gas | C530: 2 | D530: =+VLOOKUP(AtecoCrisi[[#This Row],[COD. CRISI]],Tabella139[],2,0) -> B) Estrazione; C) Manifattura; D) Produzione energia/gas | E530: =+VLOOKUP(C530,$R$2:$X$11,3,FALSE) -> 0.03 | F530: =+VLOOKUP(C530,$R$2:$X$11,4,FALSE) -> 0.076 | G530: =+VLOOKUP(C530,$R$2:$X$11,5,FALSE) -> 0.937 | H530: =+VLOOKUP(C530,$R$2:$X$11,6,FALSE) -> 0.005 | I530: =+VLOOKUP(C530,$R$2:$X$11,7,FALSE) -> 0.049 | L530: 43.22.04 | M530: =+VLOOKUP(L530,A:B,2,0) -> Installazione di impianti di depurazione per piscine (inclusa manutenzione e riparazione) | N530: =+VLOOKUP(L530,A:D,4,0) -> F42) Ingegneria civile; F43) Costruzioni specializzate
A531: 35.22.00 | B531: Distribuzione di combustibili gassosi mediante condotte | C531: 6 | D531: =+VLOOKUP(AtecoCrisi[[#This Row],[COD. CRISI]],Tabella139[],2,0) -> G45) Commercio autoveicoli; G46) Comm. Ingrosso; D) Distr. Energia/gas | E531: =+VLOOKUP(C531,$R$2:$X$11,3,FALSE) -> 0.021 | F531: =+VLOOKUP(C531,$R$2:$X$11,4,FALSE) -> 0.063 | G531: =+VLOOKUP(C531,$R$2:$X$11,5,FALSE) -> 1.014 | H531: =+VLOOKUP(C531,$R$2:$X$11,6,FALSE) -> 0.006 | I531: =+VLOOKUP(C531,$R$2:$X$11,7,FALSE) -> 0.029 | L531: 43.22.05 | M531: =+VLOOKUP(L531,A:B,2,0) -> Installazione di impianti di irrigazione per giardini (inclusa manutenzione e riparazione) | N531: =+VLOOKUP(L531,A:D,4,0) -> F42) Ingegneria civile; F43) Costruzioni specializzate
A532: 35.23.00 | B532: Commercio di gas distribuito mediante condotte | C532: 6 | D532: =+VLOOKUP(AtecoCrisi[[#This Row],[COD. CRISI]],Tabella139[],2,0) -> G45) Commercio autoveicoli; G46) Comm. Ingrosso; D) Distr. Energia/gas | E532: =+VLOOKUP(C532,$R$2:$X$11,3,FALSE) -> 0.021 | F532: =+VLOOKUP(C532,$R$2:$X$11,4,FALSE) -> 0.063 | G532: =+VLOOKUP(C532,$R$2:$X$11,5,FALSE) -> 1.014 | H532: =+VLOOKUP(C532,$R$2:$X$11,6,FALSE) -> 0.006 | I532: =+VLOOKUP(C532,$R$2:$X$11,7,FALSE) -> 0.029 | L532: 43.29.01 | M532: =+VLOOKUP(L532,A:B,2,0) -> Installazione, riparazione e manutenzione di ascensori e scale mobili | N532: =+VLOOKUP(L532,A:D,4,0) -> F42) Ingegneria civile; F43) Costruzioni specializzate
A533: 35.30.00 | B533: Fornitura di vapore e aria condizionata | C533: 6 | D533: =+VLOOKUP(AtecoCrisi[[#This Row],[COD. CRISI]],Tabella139[],2,0) -> G45) Commercio autoveicoli; G46) Comm. Ingrosso; D) Distr. Energia/gas | E533: =+VLOOKUP(C533,$R$2:$X$11,3,FALSE) -> 0.021 | F533: =+VLOOKUP(C533,$R$2:$X$11,4,FALSE) -> 0.063 | G533: =+VLOOKUP(C533,$R$2:$X$11,5,FALSE) -> 1.014 | H533: =+VLOOKUP(C533,$R$2:$X$11,6,FALSE) -> 0.006 | I533: =+VLOOKUP(C533,$R$2:$X$11,7,FALSE) -> 0.029 | L533: 43.29.02 | M533: =+VLOOKUP(L533,A:B,2,0) -> Lavori di isolamento termico, acustico o antivibrazioni | N533: =+VLOOKUP(L533,A:D,4,0) -> F42) Ingegneria civile; F43) Costruzioni specializzate
A534: E | B534: FORNITURA DI ACQUA; RETI FOGNARIE, ATTIVITÀ DI GESTIONE DEI RIFIUTI E RISANAMENTO | C534: 3 | D534: =+VLOOKUP(AtecoCrisi[[#This Row],[COD. CRISI]],Tabella139[],2,0) -> E) Fornitura acqua reti fognarie rifiuti; D) Trasmissione energia/gas | E534: =+VLOOKUP(C534,$R$2:$X$11,3,FALSE) -> 0.026 | F534: =+VLOOKUP(C534,$R$2:$X$11,4,FALSE) -> 0.067 | G534: =+VLOOKUP(C534,$R$2:$X$11,5,FALSE) -> 0.842 | H534: =+VLOOKUP(C534,$R$2:$X$11,6,FALSE) -> 0.019 | I534: =+VLOOKUP(C534,$R$2:$X$11,7,FALSE) -> 0.065 | L534: 43.29.09 | M534: =+VLOOKUP(L534,A:B,2,0) -> Altri lavori di costruzione e installazione nca | N534: =+VLOOKUP(L534,A:D,4,0) -> F42) Ingegneria civile; F43) Costruzioni specializzate
A535: 36 | B535: RACCOLTA, TRATTAMENTO E FORNITURA DI ACQUA | C535: 3 | D535: =+VLOOKUP(AtecoCrisi[[#This Row],[COD. CRISI]],Tabella139[],2,0) -> E) Fornitura acqua reti fognarie rifiuti; D) Trasmissione energia/gas | E535: =+VLOOKUP(C535,$R$2:$X$11,3,FALSE) -> 0.026 | F535: =+VLOOKUP(C535,$R$2:$X$11,4,FALSE) -> 0.067 | G535: =+VLOOKUP(C535,$R$2:$X$11,5,FALSE) -> 0.842 | H535: =+VLOOKUP(C535,$R$2:$X$11,6,FALSE) -> 0.019 | I535: =+VLOOKUP(C535,$R$2:$X$11,7,FALSE) -> 0.065 | L535: 43.31.00 | M535: =+VLOOKUP(L535,A:B,2,0) -> Intonacatura e stuccatura | N535: =+VLOOKUP(L535,A:D,4,0) -> F42) Ingegneria civile; F43) Costruzioni specializzate
A536: 36.00.00 | B536: Raccolta, trattamento e fornitura di acqua | C536: 3 | D536: =+VLOOKUP(AtecoCrisi[[#This Row],[COD. CRISI]],Tabella139[],2,0) -> E) Fornitura acqua reti fognarie rifiuti; D) Trasmissione energia/gas | E536: =+VLOOKUP(C536,$R$2:$X$11,3,FALSE) -> 0.026 | F536: =+VLOOKUP(C536,$R$2:$X$11,4,FALSE) -> 0.067 | G536: =+VLOOKUP(C536,$R$2:$X$11,5,FALSE) -> 0.842 | H536: =+VLOOKUP(C536,$R$2:$X$11,6,FALSE) -> 0.019 | I536: =+VLOOKUP(C536,$R$2:$X$11,7,FALSE) -> 0.065 | L536: 43.32.01 | M536: =+VLOOKUP(L536,A:B,2,0) -> Posa in opera di casseforti, forzieri, porte blindate | N536: =+VLOOKUP(L536,A:D,4,0) -> F42) Ingegneria civile; F43) Costruzioni specializzate
A537: 37 | B537: GESTIONE DELLE RETI FOGNARIE | C537: 3 | D537: =+VLOOKUP(AtecoCrisi[[#This Row],[COD. CRISI]],Tabella139[],2,0) -> E) Fornitura acqua reti fognarie rifiuti; D) Trasmissione energia/gas | E537: =+VLOOKUP(C537,$R$2:$X$11,3,FALSE) -> 0.026 | F537: =+VLOOKUP(C537,$R$2:$X$11,4,FALSE) -> 0.067 | G537: =+VLOOKUP(C537,$R$2:$X$11,5,FALSE) -> 0.842 | H537: =+VLOOKUP(C537,$R$2:$X$11,6,FALSE) -> 0.019 | I537: =+VLOOKUP(C537,$R$2:$X$11,7,FALSE) -> 0.065 | L537: 43.32.02 | M537: =+VLOOKUP(L537,A:B,2,0) -> Posa in opera di infissi, arredi, controsoffitti, pareti mobili e simili | N537: =+VLOOKUP(L537,A:D,4,0) -> F42) Ingegneria civile; F43) Costruzioni specializzate
... A552: 39.00.09 | B552: Altre attività di risanamento e altri servizi di gestione dei rifiuti | C552: 3 | D552: =+VLOOKUP(AtecoCrisi[[#This Row],[COD. CRISI]],Tabella139[],2,0) -> E) Fornitura acqua reti fognarie rifiuti; D) Trasmissione energia/gas | E552: =+VLOOKUP(C552,$R$2:$X$11,3,FALSE) -> 0.026 | F552: =+VLOOKUP(C552,$R$2:$X$11,4,FALSE) -> 0.067 | G552: =+VLOOKUP(C552,$R$2:$X$11,5,FALSE) -> 0.842 | H552: =+VLOOKUP(C552,$R$2:$X$11,6,FALSE) -> 0.019 | I552: =+VLOOKUP(C552,$R$2:$X$11,7,FALSE) -> 0.065 | L552: 45.20.30 | M552: =+VLOOKUP(L552,A:B,2,0) -> Riparazione di impianti elettrici e di alimentazione per autoveicoli | N552: =+VLOOKUP(L552,A:D,4,0) -> G45) Commercio autoveicoli; G46) Comm. Ingrosso; D) Distr. Energia/gas
A553: F | B553: COSTRUZIONI | D553: =+VLOOKUP(AtecoCrisi[[#This Row],[COD. CRISI]],Tabella139[],2,0) -> #N/A | E553: =+VLOOKUP(C553,$R$2:$X$11,3,FALSE) -> #N/A | F553: =+VLOOKUP(C553,$R$2:$X$11,4,FALSE) -> #N/A | G553: =+VLOOKUP(C553,$R$2:$X$11,5,FALSE) -> #N/A | H553: =+VLOOKUP(C553,$R$2:$X$11,6,FALSE) -> #N/A | I553: =+VLOOKUP(C553,$R$2:$X$11,7,FALSE) -> #N/A | L553: 45.20.40 | M553: =+VLOOKUP(L553,A:B,2,0) -> Riparazione e sostituzione di pneumatici per autoveicoli | N553: =+VLOOKUP(L553,A:D,4,0) -> G45) Commercio autoveicoli; G46) Comm. Ingrosso; D) Distr. Energia/gas
A554: 41 | B554: COSTRUZIONE DI EDIFICI | C554: 4 | D554: =+VLOOKUP(AtecoCrisi[[#This Row],[COD. CRISI]],Tabella139[],2,0) -> F41) Costruzione di edifici | E554: =+VLOOKUP(C554,$R$2:$X$11,3,FALSE) -> 0.038 | F554: =+VLOOKUP(C554,$R$2:$X$11,4,FALSE) -> 0.049 | G554: =+VLOOKUP(C554,$R$2:$X$11,5,FALSE) -> 1.08 | H554: =+VLOOKUP(C554,$R$2:$X$11,6,FALSE) -> 0.004 | I554: =+VLOOKUP(C554,$R$2:$X$11,7,FALSE) -> 0.038 | L554: 45.20.91 | M554: =+VLOOKUP(L554,A:B,2,0) -> Lavaggio auto | N554: =+VLOOKUP(L554,A:D,4,0) -> G45) Commercio autoveicoli; G46) Comm. Ingrosso; D) Distr. Energia/gas
A555: 41.10.00 | B555: Sviluppo di progetti immobiliari senza costruzione | C555: 4 | D555: =+VLOOKUP(AtecoCrisi[[#This Row],[COD. CRISI]],Tabella139[],2,0) -> F41) Costruzione di edifici | E555: =+VLOOKUP(C555,$R$2:$X$11,3,FALSE) -> 0.038 | F555: =+VLOOKUP(C555,$R$2:$X$11,4,FALSE) -> 0.049 | G555: =+VLOOKUP(C555,$R$2:$X$11,5,FALSE) -> 1.08 | H555: =+VLOOKUP(C555,$R$2:$X$11,6,FALSE) -> 0.004 | I555: =+VLOOKUP(C555,$R$2:$X$11,7,FALSE) -> 0.038 | L555: 45.20.99 | M555: =+VLOOKUP(L555,A:B,2,0) -> Altre attività di manutenzione e di riparazione di autoveicoli | N555: =+VLOOKUP(L555,A:D,4,0) -> G45) Commercio autoveicoli; G46) Comm. Ingrosso; D) Distr. Energia/gas
A556: 41.20.00 | B556: Costruzione di edifici residenziali e non residenziali | C556: 4 | D556: =+VLOOKUP(AtecoCrisi[[#This Row],[COD. CRISI]],Tabella139[],2,0) -> F41) Costruzione di edifici | E556: =+VLOOKUP(C556,$R$2:$X$11,3,FALSE) -> 0.038 | F556: =+VLOOKUP(C556,$R$2:$X$11,4,FALSE) -> 0.049 | G556: =+VLOOKUP(C556,$R$2:$X$11,5,FALSE) -> 1.08 | H556: =+VLOOKUP(C556,$R$2:$X$11,6,FALSE) -> 0.004 | I556: =+VLOOKUP(C556,$R$2:$X$11,7,FALSE) -> 0.038 | L556: 45.31.01 | M556: =+VLOOKUP(L556,A:B,2,0) -> Commercio all'ingrosso di parti e accessori di autoveicoli | N556: =+VLOOKUP(L556,A:D,4,0) -> G45) Commercio autoveicoli; G46) Comm. Ingrosso; D) Distr. Energia/gas
A557: 42 | B557: INGEGNERIA CIVILE | C557: 5 | D557: =+VLOOKUP(AtecoCrisi[[#This Row],[COD. CRISI]],Tabella139[],2,0) -> F42) Ingegneria civile; F43) Costruzioni specializzate | E557: =+VLOOKUP(C557,$R$2:$X$11,3,FALSE) -> 0.028 | F557: =+VLOOKUP(C557,$R$2:$X$11,4,FALSE) -> 0.053 | G557: =+VLOOKUP(C557,$R$2:$X$11,5,FALSE) -> 1.011 | H557: =+VLOOKUP(C557,$R$2:$X$11,6,FALSE) -> 0.014 | I557: =+VLOOKUP(C557,$R$2:$X$11,7,FALSE) -> 0.053 | L557: 45.31.02 | M557: =+VLOOKUP(L557,A:B,2,0) -> Intermediari del commercio di parti ed accessori di autoveicoli | N557: =+VLOOKUP(L557,A:D,4,0) -> G45) Commercio autoveicoli; G46) Comm. Ingrosso; D) Distr. Energia/gas
A558: 42.11.00 | B558: Costruzione di strade, autostrade e piste aeroportuali | C558: 5 | D558: =+VLOOKUP(AtecoCrisi[[#This Row],[COD. CRISI]],Tabella139[],2,0) -> F42) Ingegneria civile; F43) Costruzioni specializzate | E558: =+VLOOKUP(C558,$R$2:$X$11,3,FALSE) -> 0.028 | F558: =+VLOOKUP(C558,$R$2:$X$11,4,FALSE) -> 0.053 | G558: =+VLOOKUP(C558,$R$2:$X$11,5,FALSE) -> 1.011 | H558: =+VLOOKUP(C558,$R$2:$X$11,6,FALSE) -> 0.014 | I558: =+VLOOKUP(C558,$R$2:$X$11,7,FALSE) -> 0.053 | L558: 45.32.00 | M558: =+VLOOKUP(L558,A:B,2,0) -> Commercio al dettaglio di parti e accessori di autoveicoli | N558: =+VLOOKUP(L558,A:D,4,0) -> G45) Commercio autoveicoli; G46) Comm. Ingrosso; D) Distr. Energia/gas
A559: 42.12.00 | B559: Costruzione di linee ferroviarie e metropolitane | C559: 5 | D559: =+VLOOKUP(AtecoCrisi[[#This Row],[COD. CRISI]],Tabella139[],2,0) -> F42) Ingegneria civile; F43) Costruzioni specializzate | E559: =+VLOOKUP(C559,$R$2:$X$11,3,FALSE) -> 0.028 | F559: =+VLOOKUP(C559,$R$2:$X$11,4,FALSE) -> 0.053 | G559: =+VLOOKUP(C559,$R$2:$X$11,5,FALSE) -> 1.011 | H559: =+VLOOKUP(C559,$R$2:$X$11,6,FALSE) -> 0.014 | I559: =+VLOOKUP(C559,$R$2:$X$11,7,FALSE) -> 0.053 | L559: 45.40.11 | M559: =+VLOOKUP(L559,A:B,2,0) -> Commercio all'ingrosso e al dettaglio di motocicli e ciclomotori | N559: =+VLOOKUP(L559,A:D,4,0) -> G45) Commercio autoveicoli; G46) Comm. Ingrosso; D) Distr. Energia/gas
A560: 42.13.00 | B560: Costruzione di ponti e gallerie | C560: 5 | D560: =+VLOOKUP(AtecoCrisi[[#This Row],[COD. CRISI]],Tabella139[],2,0) -> F42) Ingegneria civile; F43) Costruzioni specializzate | E560: =+VLOOKUP(C560,$R$2:$X$11,3,FALSE) -> 0.028 | F560: =+VLOOKUP(C560,$R$2:$X$11,4,FALSE) -> 0.053 | G560: =+VLOOKUP(C560,$R$2:$X$11,5,FALSE) -> 1.011 | H560: =+VLOOKUP(C560,$R$2:$X$11,6,FALSE) -> 0.014 | I560: =+VLOOKUP(C560,$R$2:$X$11,7,FALSE) -> 0.053 | L560: 45.40.12 | M560: =+VLOOKUP(L560,A:B,2,0) -> Intermediari del commercio di motocicli e ciclomotori | N560: =+VLOOKUP(L560,A:D,4,0) -> G45) Commercio autoveicoli; G46) Comm. Ingrosso; D) Distr. Energia/gas
A561: 42.21.00 | B561: Costruzione di opere di pubblica utilità per il trasporto di fluidi | C561: 5 | D561: =+VLOOKUP(AtecoCrisi[[#This Row],[COD. CRISI]],Tabella139[],2,0) -> F42) Ingegneria civile; F43) Costruzioni specializzate | E561: =+VLOOKUP(C561,$R$2:$X$11,3,FALSE) -> 0.028 | F561: =+VLOOKUP(C561,$R$2:$X$11,4,FALSE) -> 0.053 | G561: =+VLOOKUP(C561,$R$2:$X$11,5,FALSE) -> 1.011 | H561: =+VLOOKUP(C561,$R$2:$X$11,6,FALSE) -> 0.014 | I561: =+VLOOKUP(C561,$R$2:$X$11,7,FALSE) -> 0.053 | L561: 45.40.21 | M561: =+VLOOKUP(L561,A:B,2,0) -> Commercio all'ingrosso e al dettaglio di parti e accessori per motocicli e ciclomotori | N561: =+VLOOKUP(L561,A:D,4,0) -> G45) Commercio autoveicoli; G46) Comm. Ingrosso; D) Distr. Energia/gas
A562: 42.22.00 | B562: Costruzione di opere di pubblica utilità per l'energia elettrica e le telecomunicazioni | C562: 5 | D562: =+VLOOKUP(AtecoCrisi[[#This Row],[COD. CRISI]],Tabella139[],2,0) -> F42) Ingegneria civile; F43) Costruzioni specializzate | E562: =+VLOOKUP(C562,$R$2:$X$11,3,FALSE) -> 0.028 | F562: =+VLOOKUP(C562,$R$2:$X$11,4,FALSE) -> 0.053 | G562: =+VLOOKUP(C562,$R$2:$X$11,5,FALSE) -> 1.011 | H562: =+VLOOKUP(C562,$R$2:$X$11,6,FALSE) -> 0.014 | I562: =+VLOOKUP(C562,$R$2:$X$11,7,FALSE) -> 0.053 | L562: 45.40.22 | M562: =+VLOOKUP(L562,A:B,2,0) -> Intermediari del commercio di parti ed accessori di motocicli e ciclomotori | N562: =+VLOOKUP(L562,A:D,4,0) -> G45) Commercio autoveicoli; G46) Comm. Ingrosso; D) Distr. Energia/gas
A563: 42.91.00 | B563: Costruzione di opere idrauliche | C563: 5 | D563: =+VLOOKUP(AtecoCrisi[[#This Row],[COD. CRISI]],Tabella139[],2,0) -> F42) Ingegneria civile; F43) Costruzioni specializzate | E563: =+VLOOKUP(C563,$R$2:$X$11,3,FALSE) -> 0.028 | F563: =+VLOOKUP(C563,$R$2:$X$11,4,FALSE) -> 0.053 | G563: =+VLOOKUP(C563,$R$2:$X$11,5,FALSE) -> 1.011 | H563: =+VLOOKUP(C563,$R$2:$X$11,6,FALSE) -> 0.014 | I563: =+VLOOKUP(C563,$R$2:$X$11,7,FALSE) -> 0.053 | L563: 45.40.30 | M563: =+VLOOKUP(L563,A:B,2,0) -> Manutenzione e riparazione di motocicli e ciclomotori (inclusi i pneumatici) | N563: =+VLOOKUP(L563,A:D,4,0) -> G45) Commercio autoveicoli; G46) Comm. Ingrosso; D) Distr. Energia/gas
A564: 42.99.01 | B564: Lottizzazione dei terreni connessa con l'urbanizzazione | C564: 5 | D564: =+VLOOKUP(AtecoCrisi[[#This Row],[COD. CRISI]],Tabella139[],2,0) -> F42) Ingegneria civile; F43) Costruzioni specializzate | E564: =+VLOOKUP(C564,$R$2:$X$11,3,FALSE) -> 0.028 | F564: =+VLOOKUP(C564,$R$2:$X$11,4,FALSE) -> 0.053 | G564: =+VLOOKUP(C564,$R$2:$X$11,5,FALSE) -> 1.011 | H564: =+VLOOKUP(C564,$R$2:$X$11,6,FALSE) -> 0.014 | I564: =+VLOOKUP(C564,$R$2:$X$11,7,FALSE) -> 0.053 | L564: 46.11.01 | M564: =+VLOOKUP(L564,A:B,2,0) -> Agenti e rappresentanti di materie prime agricole | N564: =+VLOOKUP(L564,A:D,4,0) -> G45) Commercio autoveicoli; G46) Comm. Ingrosso; D) Distr. Energia/gas
A565: 42.99.09 | B565: Altre attività di costruzione di altre opere di ingegneria civile nca | C565: 5 | D565: =+VLOOKUP(AtecoCrisi[[#This Row],[COD. CRISI]],Tabella139[],2,0) -> F42) Ingegneria civile; F43) Costruzioni specializzate | E565: =+VLOOKUP(C565,$R$2:$X$11,3,FALSE) -> 0.028 | F565: =+VLOOKUP(C565,$R$2:$X$11,4,FALSE) -> 0.053 | G565: =+VLOOKUP(C565,$R$2:$X$11,5,FALSE) -> 1.011 | H565: =+VLOOKUP(C565,$R$2:$X$11,6,FALSE) -> 0.014 | I565: =+VLOOKUP(C565,$R$2:$X$11,7,FALSE) -> 0.053 | L565: 46.11.02 | M565: =+VLOOKUP(L565,A:B,2,0) -> Agenti e rappresentanti di fiori e piante | N565: =+VLOOKUP(L565,A:D,4,0) -> G45) Commercio autoveicoli; G46) Comm. Ingrosso; D) Distr. Energia/gas
... A1118: 82.99.99 | B1118: Altri servizi di sostegno alle imprese nca | C1118: 9 | D1118: =+VLOOKUP(AtecoCrisi[[#This Row],[COD. CRISI]],Tabella139[],2,0) -> JMN) Servizi alle imprese | E1118: =+VLOOKUP(C1118,$R$2:$X$11,3,FALSE) -> 0.018 | F1118: =+VLOOKUP(C1118,$R$2:$X$11,4,FALSE) -> 0.052 | G1118: =+VLOOKUP(C1118,$R$2:$X$11,5,FALSE) -> 0.954 | H1118: =+VLOOKUP(C1118,$R$2:$X$11,6,FALSE) -> 0.017 | I1118: =+VLOOKUP(C1118,$R$2:$X$11,7,FALSE) -> 0.119 | L1118: 91.02.00 | M1118: =+VLOOKUP(L1118,A:B,2,0) -> Attività di musei | N1118: =+VLOOKUP(L1118,A:D,4,0) -> PQRS) Servizi alle persone
A1119: O | B1119: AMMINISTRAZIONE PUBBLICA E DIFESA; ASSICURAZIONE SOCIALE OBBLIGATORIA | D1119: =+VLOOKUP(AtecoCrisi[[#This Row],[COD. CRISI]],Tabella139[],2,0) -> #N/A | E1119: =+VLOOKUP(C1119,$R$2:$X$11,3,FALSE) -> #N/A | F1119: =+VLOOKUP(C1119,$R$2:$X$11,4,FALSE) -> #N/A | G1119: =+VLOOKUP(C1119,$R$2:$X$11,5,FALSE) -> #N/A | H1119: =+VLOOKUP(C1119,$R$2:$X$11,6,FALSE) -> #N/A | I1119: =+VLOOKUP(C1119,$R$2:$X$11,7,FALSE) -> #N/A | L1119: 91.03.00 | M1119: =+VLOOKUP(L1119,A:B,2,0) -> Gestione di luoghi e monumenti storici e attrazioni simili | N1119: =+VLOOKUP(L1119,A:D,4,0) -> PQRS) Servizi alle persone
A1120: 84 | B1120: AMMINISTRAZIONE PUBBLICA E DIFESA; ASSICURAZIONE SOCIALE OBBLIGATORIA | D1120: =+VLOOKUP(AtecoCrisi[[#This Row],[COD. CRISI]],Tabella139[],2,0) -> #N/A | E1120: =+VLOOKUP(C1120,$R$2:$X$11,3,FALSE) -> #N/A | F1120: =+VLOOKUP(C1120,$R$2:$X$11,4,FALSE) -> #N/A | G1120: =+VLOOKUP(C1120,$R$2:$X$11,5,FALSE) -> #N/A | H1120: =+VLOOKUP(C1120,$R$2:$X$11,6,FALSE) -> #N/A | I1120: =+VLOOKUP(C1120,$R$2:$X$11,7,FALSE) -> #N/A | L1120: 91.04.00 | M1120: =+VLOOKUP(L1120,A:B,2,0) -> Attività degli orti botanici, dei giardini zoologici e delle riserve naturali | N1120: =+VLOOKUP(L1120,A:D,4,0) -> PQRS) Servizi alle persone
A1121: 84.11.10 | B1121: Attività degli organi legislativi ed esecutivi, centrali e locali; amministrazione finanziaria; amministrazioni regionali, provinciali e comunali | D1121: =+VLOOKUP(AtecoCrisi[[#This Row],[COD. CRISI]],Tabella139[],2,0) -> #N/A | E1121: =+VLOOKUP(C1121,$R$2:$X$11,3,FALSE) -> #N/A | F1121: =+VLOOKUP(C1121,$R$2:$X$11,4,FALSE) -> #N/A | G1121: =+VLOOKUP(C1121,$R$2:$X$11,5,FALSE) -> #N/A | H1121: =+VLOOKUP(C1121,$R$2:$X$11,6,FALSE) -> #N/A | I1121: =+VLOOKUP(C1121,$R$2:$X$11,7,FALSE) -> #N/A | L1121: 92.00.01 | M1121: =+VLOOKUP(L1121,A:B,2,0) -> Ricevitorie del Lotto, SuperEnalotto, Totocalcio eccetera | N1121: =+VLOOKUP(L1121,A:D,4,0) -> PQRS) Servizi alle persone
A1122: 84.11.20 | B1122: Attività di pianificazione generale e servizi statistici generali | D1122: =+VLOOKUP(AtecoCrisi[[#This Row],[COD. CRISI]],Tabella139[],2,0) -> #N/A | E1122: =+VLOOKUP(C1122,$R$2:$X$11,3,FALSE) -> #N/A | F1122: =+VLOOKUP(C1122,$R$2:$X$11,4,FALSE) -> #N/A | G1122: =+VLOOKUP(C1122,$R$2:$X$11,5,FALSE) -> #N/A | H1122: =+VLOOKUP(C1122,$R$2:$X$11,6,FALSE) -> #N/A | I1122: =+VLOOKUP(C1122,$R$2:$X$11,7,FALSE) -> #N/A | L1122: 92.00.02 | M1122: =+VLOOKUP(L1122,A:B,2,0) -> Gestione di apparecchi che consentono vincite in denaro funzionanti a moneta o a gettone | N1122: =+VLOOKUP(L1122,A:D,4,0) -> PQRS) Servizi alle persone
A1123: 84.12.10 | B1123: Regolamentazione dell'attività degli organismi preposti alla sanità | D1123: =+VLOOKUP(AtecoCrisi[[#This Row],[COD. CRISI]],Tabella139[],2,0) -> #N/A | E1123: =+VLOOKUP(C1123,$R$2:$X$11,3,FALSE) -> #N/A | F1123: =+VLOOKUP(C1123,$R$2:$X$11,4,FALSE) -> #N/A | G1123: =+VLOOKUP(C1123,$R$2:$X$11,5,FALSE) -> #N/A | H1123: =+VLOOKUP(C1123,$R$2:$X$11,6,FALSE) -> #N/A | I1123: =+VLOOKUP(C1123,$R$2:$X$11,7,FALSE) -> #N/A | L1123: 92.00.09 | M1123: =+VLOOKUP(L1123,A:B,2,0) -> Altre attività connesse con le lotterie e le scommesse | N1123: =+VLOOKUP(L1123,A:D,4,0) -> PQRS) Servizi alle persone
A1124: 84.12.20 | B1124: Regolamentazione dell'attività degli organismi preposti all'istruzione | D1124: =+VLOOKUP(AtecoCrisi[[#This Row],[COD. CRISI]],Tabella139[],2,0) -> #N/A | E1124: =+VLOOKUP(C1124,$R$2:$X$11,3,FALSE) -> #N/A | F1124: =+VLOOKUP(C1124,$R$2:$X$11,4,FALSE) -> #N/A | G1124: =+VLOOKUP(C1124,$R$2:$X$11,5,FALSE) -> #N/A | H1124: =+VLOOKUP(C1124,$R$2:$X$11,6,FALSE) -> #N/A | I1124: =+VLOOKUP(C1124,$R$2:$X$11,7,FALSE) -> #N/A | L1124: 93.11.10 | M1124: =+VLOOKUP(L1124,A:B,2,0) -> Gestione di stadi | N1124: =+VLOOKUP(L1124,A:D,4,0) -> PQRS) Servizi alle persone
A1125: 84.12.30 | B1125: Regolamentazione dell'attività degli organismi preposti alla gestione di progetti per l'edilizia abitativa e l'assetto del territorio e per la tutela dell'ambiente | D1125: =+VLOOKUP(AtecoCrisi[[#This Row],[COD. CRISI]],Tabella139[],2,0) -> #N/A | E1125: =+VLOOKUP(C1125,$R$2:$X$11,3,FALSE) -> #N/A | F1125: =+VLOOKUP(C1125,$R$2:$X$11,4,FALSE) -> #N/A | G1125: =+VLOOKUP(C1125,$R$2:$X$11,5,FALSE) -> #N/A | H1125: =+VLOOKUP(C1125,$R$2:$X$11,6,FALSE) -> #N/A | I1125: =+VLOOKUP(C1125,$R$2:$X$11,7,FALSE) -> #N/A | L1125: 93.11.20 | M1125: =+VLOOKUP(L1125,A:B,2,0) -> Gestione di piscine | N1125: =+VLOOKUP(L1125,A:D,4,0) -> PQRS) Servizi alle persone
A1126: 84.12.40 | B1126: Regolamentazione dell'attività degli organismi preposti ai servizi ricreativi, culturali e sociali vari | D1126: =+VLOOKUP(AtecoCrisi[[#This Row],[COD. CRISI]],Tabella139[],2,0) -> #N/A | E1126: =+VLOOKUP(C1126,$R$2:$X$11,3,FALSE) -> #N/A | F1126: =+VLOOKUP(C1126,$R$2:$X$11,4,FALSE) -> #N/A | G1126: =+VLOOKUP(C1126,$R$2:$X$11,5,FALSE) -> #N/A | H1126: =+VLOOKUP(C1126,$R$2:$X$11,6,FALSE) -> #N/A | I1126: =+VLOOKUP(C1126,$R$2:$X$11,7,FALSE) -> #N/A | L1126: 93.11.30 | M1126: =+VLOOKUP(L1126,A:B,2,0) -> Gestione di impianti sportivi polivalenti | N1126: =+VLOOKUP(L1126,A:D,4,0) -> PQRS) Servizi alle persone
A1127: 84.13.10 | B1127: Regolamentazione degli affari concernenti i combustibili e l'energia | D1127: =+VLOOKUP(AtecoCrisi[[#This Row],[COD. CRISI]],Tabella139[],2,0) -> #N/A | E1127: =+VLOOKUP(C1127,$R$2:$X$11,3,FALSE) -> #N/A | F1127: =+VLOOKUP(C1127,$R$2:$X$11,4,FALSE) -> #N/A | G1127: =+VLOOKUP(C1127,$R$2:$X$11,5,FALSE) -> #N/A | H1127: =+VLOOKUP(C1127,$R$2:$X$11,6,FALSE) -> #N/A | I1127: =+VLOOKUP(C1127,$R$2:$X$11,7,FALSE) -> #N/A | L1127: 93.11.90 | M1127: =+VLOOKUP(L1127,A:B,2,0) -> Gestione di altri impianti sportivi nca | N1127: =+VLOOKUP(L1127,A:D,4,0) -> PQRS) Servizi alle persone
A1128: 84.13.20 | B1128: Regolamentazione degli affari e servizi concernenti l'agricoltura, silvicoltura, caccia e pesca | D1128: =+VLOOKUP(AtecoCrisi[[#This Row],[COD. CRISI]],Tabella139[],2,0) -> #N/A | E1128: =+VLOOKUP(C1128,$R$2:$X$11,3,FALSE) -> #N/A | F1128: =+VLOOKUP(C1128,$R$2:$X$11,4,FALSE) -> #N/A | G1128: =+VLOOKUP(C1128,$R$2:$X$11,5,FALSE) -> #N/A | H1128: =+VLOOKUP(C1128,$R$2:$X$11,6,FALSE) -> #N/A | I1128: =+VLOOKUP(C1128,$R$2:$X$11,7,FALSE) -> #N/A | L1128: 93.12.00 | M1128: =+VLOOKUP(L1128,A:B,2,0) -> Attività di club sportivi | N1128: =+VLOOKUP(L1128,A:D,4,0) -> PQRS) Servizi alle persone
A1129: 84.13.30 | B1129: Regolamentazione degli affari e dei servizi concernenti le industrie estrattive e le risorse minerarie (eccetto i combustibili) le industrie manifatturiere, le costruzioni e le opere pubbliche ad eccezione delle strade e opere per la navigazione | D1129: =+VLOOKUP(AtecoCrisi[[#This Row],[COD. CRISI]],Tabella139[],2,0) -> #N/A | E1129: =+VLOOKUP(C1129,$R$2:$X$11,3,FALSE) -> #N/A | F1129: =+VLOOKUP(C1129,$R$2:$X$11,4,FALSE) -> #N/A | G1129: =+VLOOKUP(C1129,$R$2:$X$11,5,FALSE) -> #N/A | H1129: =+VLOOKUP(C1129,$R$2:$X$11,6,FALSE) -> #N/A | I1129: =+VLOOKUP(C1129,$R$2:$X$11,7,FALSE) -> #N/A | L1129: 93.13.00 | M1129: =+VLOOKUP(L1129,A:B,2,0) -> Gestione di palestre | N1129: =+VLOOKUP(L1129,A:D,4,0) -> PQRS) Servizi alle persone
A1130: 84.13.40 | B1130: Regolamentazione degli affari e servizi concernenti la costruzione di strade | D1130: =+VLOOKUP(AtecoCrisi[[#This Row],[COD. CRISI]],Tabella139[],2,0) -> #N/A | E1130: =+VLOOKUP(C1130,$R$2:$X$11,3,FALSE) -> #N/A | F1130: =+VLOOKUP(C1130,$R$2:$X$11,4,FALSE) -> #N/A | G1130: =+VLOOKUP(C1130,$R$2:$X$11,5,FALSE) -> #N/A | H1130: =+VLOOKUP(C1130,$R$2:$X$11,6,FALSE) -> #N/A | I1130: =+VLOOKUP(C1130,$R$2:$X$11,7,FALSE) -> #N/A | L1130: 93.19.10 | M1130: =+VLOOKUP(L1130,A:B,2,0) -> Enti e organizzazioni sportive, promozione di eventi sportivi | N1130: =+VLOOKUP(L1130,A:D,4,0) -> PQRS) Servizi alle persone
... A1142: 84.30.00 | B1142: Assicurazione sociale obbligatoria | D1142: =+VLOOKUP(AtecoCrisi[[#This Row],[COD. CRISI]],Tabella139[],2,0) -> #N/A | E1142: =+VLOOKUP(C1142,$R$2:$X$11,3,FALSE) -> #N/A | F1142: =+VLOOKUP(C1142,$R$2:$X$11,4,FALSE) -> #N/A | G1142: =+VLOOKUP(C1142,$R$2:$X$11,5,FALSE) -> #N/A | H1142: =+VLOOKUP(C1142,$R$2:$X$11,6,FALSE) -> #N/A | I1142: =+VLOOKUP(C1142,$R$2:$X$11,7,FALSE) -> #N/A | L1142: 94.20.00 | M1142: =+VLOOKUP(L1142,A:B,2,0) -> Attività dei sindacati di lavoratori dipendenti | N1142: =+VLOOKUP(L1142,A:D,4,0) -> PQRS) Servizi alle persone
A1143: P | B1143: ISTRUZIONE | C1143: 10 | D1143: =+VLOOKUP(AtecoCrisi[[#This Row],[COD. CRISI]],Tabella139[],2,0) -> PQRS) Servizi alle persone | E1143: =+VLOOKUP(C1143,$R$2:$X$11,3,FALSE) -> 0.027 | F1143: =+VLOOKUP(C1143,$R$2:$X$11,4,FALSE) -> 0.023 | G1143: =+VLOOKUP(C1143,$R$2:$X$11,5,FALSE) -> 0.698 | H1143: =+VLOOKUP(C1143,$R$2:$X$11,6,FALSE) -> 0.005 | I1143: =+VLOOKUP(C1143,$R$2:$X$11,7,FALSE) -> 0.146 | L1143: 94.91.00 | M1143: =+VLOOKUP(L1143,A:B,2,0) -> Attività delle organizzazioni religiose nell'esercizio del culto | N1143: =+VLOOKUP(L1143,A:D,4,0) -> PQRS) Servizi alle persone
A1144: 85 | B1144: ISTRUZIONE | C1144: 10 | D1144: =+VLOOKUP(AtecoCrisi[[#This Row],[COD. CRISI]],Tabella139[],2,0) -> PQRS) Servizi alle persone | E1144: =+VLOOKUP(C1144,$R$2:$X$11,3,FALSE) -> 0.027 | F1144: =+VLOOKUP(C1144,$R$2:$X$11,4,FALSE) -> 0.023 | G1144: =+VLOOKUP(C1144,$R$2:$X$11,5,FALSE) -> 0.698 | H1144: =+VLOOKUP(C1144,$R$2:$X$11,6,FALSE) -> 0.005 | I1144: =+VLOOKUP(C1144,$R$2:$X$11,7,FALSE) -> 0.146 | L1144: 94.92.00 | M1144: =+VLOOKUP(L1144,A:B,2,0) -> Attività dei partiti e delle associazioni politiche | N1144: =+VLOOKUP(L1144,A:D,4,0) -> PQRS) Servizi alle persone
A1145: 85.10.00 | B1145: Istruzione di grado preparatorio: scuole dell'infanzia, scuole speciali collegate a quelle primarie | C1145: 10 | D1145: =+VLOOKUP(AtecoCrisi[[#This Row],[COD. CRISI]],Tabella139[],2,0) -> PQRS) Servizi alle persone | E1145: =+VLOOKUP(C1145,$R$2:$X$11,3,FALSE) -> 0.027 | F1145: =+VLOOKUP(C1145,$R$2:$X$11,4,FALSE) -> 0.023 | G1145: =+VLOOKUP(C1145,$R$2:$X$11,5,FALSE) -> 0.698 | H1145: =+VLOOKUP(C1145,$R$2:$X$11,6,FALSE) -> 0.005 | I1145: =+VLOOKUP(C1145,$R$2:$X$11,7,FALSE) -> 0.146 | L1145: 94.99.10 | M1145: =+VLOOKUP(L1145,A:B,2,0) -> Attività di organizzazioni per la tutela degli interessi e dei diritti dei cittadini | N1145: =+VLOOKUP(L1145,A:D,4,0) -> PQRS) Servizi alle persone
A1146: 85.20.00 | B1146: Istruzione primaria: scuole elementari | C1146: 10 | D1146: =+VLOOKUP(AtecoCrisi[[#This Row],[COD. CRISI]],Tabella139[],2,0) -> PQRS) Servizi alle persone | E1146: =+VLOOKUP(C1146,$R$2:$X$11,3,FALSE) -> 0.027 | F1146: =+VLOOKUP(C1146,$R$2:$X$11,4,FALSE) -> 0.023 | G1146: =+VLOOKUP(C1146,$R$2:$X$11,5,FALSE) -> 0.698 | H1146: =+VLOOKUP(C1146,$R$2:$X$11,6,FALSE) -> 0.005 | I1146: =+VLOOKUP(C1146,$R$2:$X$11,7,FALSE) -> 0.146 | L1146: 94.99.20 | M1146: =+VLOOKUP(L1146,A:B,2,0) -> Attività di organizzazioni che perseguono fini culturali, ricreativi e la coltivazione di hobby | N1146: =+VLOOKUP(L1146,A:D,4,0) -> PQRS) Servizi alle persone
A1147: 85.31.10 | B1147: Istruzione secondaria di primo grado: scuole medie | C1147: 10 | D1147: =+VLOOKUP(AtecoCrisi[[#This Row],[COD. CRISI]],Tabella139[],2,0) -> PQRS) Servizi alle persone | E1147: =+VLOOKUP(C1147,$R$2:$X$11,3,FALSE) -> 0.027 | F1147: =+VLOOKUP(C1147,$R$2:$X$11,4,FALSE) -> 0.023 | G1147: =+VLOOKUP(C1147,$R$2:$X$11,5,FALSE) -> 0.698 | H1147: =+VLOOKUP(C1147,$R$2:$X$11,6,FALSE) -> 0.005 | I1147: =+VLOOKUP(C1147,$R$2:$X$11,7,FALSE) -> 0.146 | L1147: 94.99.30 | M1147: =+VLOOKUP(L1147,A:B,2,0) -> Attività di organizzazioni patriottiche e associazioni combattentistiche | N1147: =+VLOOKUP(L1147,A:D,4,0) -> PQRS) Servizi alle persone
A1148: 85.31.20 | B1148: Istruzione secondaria di secondo grado di formazione generale: licei | C1148: 10 | D1148: =+VLOOKUP(AtecoCrisi[[#This Row],[COD. CRISI]],Tabella139[],2,0) -> PQRS) Servizi alle persone | E1148: =+VLOOKUP(C1148,$R$2:$X$11,3,FALSE) -> 0.027 | F1148: =+VLOOKUP(C1148,$R$2:$X$11,4,FALSE) -> 0.023 | G1148: =+VLOOKUP(C1148,$R$2:$X$11,5,FALSE) -> 0.698 | H1148: =+VLOOKUP(C1148,$R$2:$X$11,6,FALSE) -> 0.005 | I1148: =+VLOOKUP(C1148,$R$2:$X$11,7,FALSE) -> 0.146 | L1148: 94.99.40 | M1148: =+VLOOKUP(L1148,A:B,2,0) -> Attività di organizzazioni per la cooperazione e la solidarietà internazionale | N1148: =+VLOOKUP(L1148,A:D,4,0) -> PQRS) Servizi alle persone
A1149: 85.32.01 | B1149: Scuole di vela e navigazione che rilasciano brevetti o patenti commerciali | C1149: 10 | D1149: =+VLOOKUP(AtecoCrisi[[#This Row],[COD. CRISI]],Tabella139[],2,0) -> PQRS) Servizi alle persone | E1149: =+VLOOKUP(C1149,$R$2:$X$11,3,FALSE) -> 0.027 | F1149: =+VLOOKUP(C1149,$R$2:$X$11,4,FALSE) -> 0.023 | G1149: =+VLOOKUP(C1149,$R$2:$X$11,5,FALSE) -> 0.698 | H1149: =+VLOOKUP(C1149,$R$2:$X$11,6,FALSE) -> 0.005 | I1149: =+VLOOKUP(C1149,$R$2:$X$11,7,FALSE) -> 0.146 | L1149: 94.99.50 | M1149: =+VLOOKUP(L1149,A:B,2,0) -> Attività di organizzazioni per la filantropia | N1149: =+VLOOKUP(L1149,A:D,4,0) -> PQRS) Servizi alle persone
A1150: 85.32.02 | B1150: Scuole di volo che rilasciano brevetti o patenti commerciali | C1150: 10 | D1150: =+VLOOKUP(AtecoCrisi[[#This Row],[COD. CRISI]],Tabella139[],2,0) -> PQRS) Servizi alle persone | E1150: =+VLOOKUP(C1150,$R$2:$X$11,3,FALSE) -> 0.027 | F1150: =+VLOOKUP(C1150,$R$2:$X$11,4,FALSE) -> 0.023 | G1150: =+VLOOKUP(C1150,$R$2:$X$11,5,FALSE) -> 0.698 | H1150: =+VLOOKUP(C1150,$R$2:$X$11,6,FALSE) -> 0.005 | I1150: =+VLOOKUP(C1150,$R$2:$X$11,7,FALSE) -> 0.146 | L1150: 94.99.60 | M1150: =+VLOOKUP(L1150,A:B,2,0) -> Attività di organizzazioni per la promozione e la difesa degli animali e dell'ambiente | N1150: =+VLOOKUP(L1150,A:D,4,0) -> PQRS) Servizi alle persone
A1151: 85.32.03 | B1151: Scuole di guida professionale per autisti, ad esempio di autocarri, di autobus e di pullman | C1151: 10 | D1151: =+VLOOKUP(AtecoCrisi[[#This Row],[COD. CRISI]],Tabella139[],2,0) -> PQRS) Servizi alle persone | E1151: =+VLOOKUP(C1151,$R$2:$X$11,3,FALSE) -> 0.027 | F1151: =+VLOOKUP(C1151,$R$2:$X$11,4,FALSE) -> 0.023 | G1151: =+VLOOKUP(C1151,$R$2:$X$11,5,FALSE) -> 0.698 | H1151: =+VLOOKUP(C1151,$R$2:$X$11,6,FALSE) -> 0.005 | I1151: =+VLOOKUP(C1151,$R$2:$X$11,7,FALSE) -> 0.146 | L1151: 94.99.90 | M1151: =+VLOOKUP(L1151,A:B,2,0) -> Attività di altre organizzazioni associative nca | N1151: =+VLOOKUP(L1151,A:D,4,0) -> PQRS) Servizi alle persone
A1152: 85.32.09 | B1152: Altra istruzione secondaria di secondo grado di formazione tecnica, professionale e artistica | C1152: 10 | D1152: =+VLOOKUP(AtecoCrisi[[#This Row],[COD. CRISI]],Tabella139[],2,0) -> PQRS) Servizi alle persone | E1152: =+VLOOKUP(C1152,$R$2:$X$11,3,FALSE) -> 0.027 | F1152: =+VLOOKUP(C1152,$R$2:$X$11,4,FALSE) -> 0.023 | G1152: =+VLOOKUP(C1152,$R$2:$X$11,5,FALSE) -> 0.698 | H1152: =+VLOOKUP(C1152,$R$2:$X$11,6,FALSE) -> 0.005 | I1152: =+VLOOKUP(C1152,$R$2:$X$11,7,FALSE) -> 0.146 | L1152: 95.11.00 | M1152: =+VLOOKUP(L1152,A:B,2,0) -> Riparazione e manutenzione di computer e periferiche | N1152: =+VLOOKUP(L1152,A:D,4,0) -> PQRS) Servizi alle persone
A1153: 85.41.00 | B1153: Istruzione e formazione tecnica superiore (IFTS) | C1153: 10 | D1153: =+VLOOKUP(AtecoCrisi[[#This Row],[COD. CRISI]],Tabella139[],2,0) -> PQRS) Servizi alle persone | E1153: =+VLOOKUP(C1153,$R$2:$X$11,3,FALSE) -> 0.027 | F1153: =+VLOOKUP(C1153,$R$2:$X$11,4,FALSE) -> 0.023 | G1153: =+VLOOKUP(C1153,$R$2:$X$11,5,FALSE) -> 0.698 | H1153: =+VLOOKUP(C1153,$R$2:$X$11,6,FALSE) -> 0.005 | I1153: =+VLOOKUP(C1153,$R$2:$X$11,7,FALSE) -> 0.146 | L1153: 95.12.01 | M1153: =+VLOOKUP(L1153,A:B,2,0) -> Riparazione e manutenzione di telefoni fissi, cordless e cellulari | N1153: =+VLOOKUP(L1153,A:D,4,0) -> PQRS) Servizi alle persone
A1154: 85.42.00 | B1154: Istruzione universitaria e post-universitaria; accademie e conservatori | C1154: 10 | D1154: =+VLOOKUP(AtecoCrisi[[#This Row],[COD. CRISI]],Tabella139[],2,0) -> PQRS) Servizi alle persone | E1154: =+VLOOKUP(C1154,$R$2:$X$11,3,FALSE) -> 0.027 | F1154: =+VLOOKUP(C1154,$R$2:$X$11,4,FALSE) -> 0.023 | G1154: =+VLOOKUP(C1154,$R$2:$X$11,5,FALSE) -> 0.698 | H1154: =+VLOOKUP(C1154,$R$2:$X$11,6,FALSE) -> 0.005 | I1154: =+VLOOKUP(C1154,$R$2:$X$11,7,FALSE) -> 0.146 | L1154: 95.12.09 | M1154: =+VLOOKUP(L1154,A:B,2,0) -> Riparazione e manutenzione di altre apparecchiature per le comunicazioni | N1154: =+VLOOKUP(L1154,A:D,4,0) -> PQRS) Servizi alle persone
... A1184: 86.90.29 | B1184: Altre attività paramediche indipendenti nca | C1184: 10 | D1184: =+VLOOKUP(AtecoCrisi[[#This Row],[COD. CRISI]],Tabella139[],2,0) -> PQRS) Servizi alle persone | E1184: =+VLOOKUP(C1184,$R$2:$X$11,3,FALSE) -> 0.027 | F1184: =+VLOOKUP(C1184,$R$2:$X$11,4,FALSE) -> 0.023 | G1184: =+VLOOKUP(C1184,$R$2:$X$11,5,FALSE) -> 0.698 | H1184: =+VLOOKUP(C1184,$R$2:$X$11,6,FALSE) -> 0.005 | I1184: =+VLOOKUP(C1184,$R$2:$X$11,7,FALSE) -> 0.146 | L1184: 99.00.00 | M1184: =+VLOOKUP(L1184,A:B,2,0) -> Organizzazioni ed organismi extraterritoriali | N1184: =+VLOOKUP(L1184,A:D,4,0) -> #N/A
A1185: 86.90.30 | B1185: Attività svolta da psicologi | C1185: 10 | D1185: =+VLOOKUP(AtecoCrisi[[#This Row],[COD. CRISI]],Tabella139[],2,0) -> PQRS) Servizi alle persone | E1185: =+VLOOKUP(C1185,$R$2:$X$11,3,FALSE) -> 0.027 | F1185: =+VLOOKUP(C1185,$R$2:$X$11,4,FALSE) -> 0.023 | G1185: =+VLOOKUP(C1185,$R$2:$X$11,5,FALSE) -> 0.698 | H1185: =+VLOOKUP(C1185,$R$2:$X$11,6,FALSE) -> 0.005 | I1185: =+VLOOKUP(C1185,$R$2:$X$11,7,FALSE) -> 0.146
...
