Workbook
Name Ac: DatiI!A$14
Name Acq: DatiI!A$34
Name Am: DatiI!A$13
Name Anni: '1'!$B$4:$H$4
Name br: BR!$A$6:$A$131
Name CB: BR!$A$5:$A$78
Name CBG: BR!$A$110:$A$131
Name cbr: BR!$A$6:$L$78
Name Cf: DatiI!A$30
Name Ci: DatiI!A$15
Name CIn: DatiI!A$16
Name Cini: DatiI!A$17
Name Cli: DatiI!A$11
Name Co: DatiI!A$24
Name CODCEE: Tabella4[COD CEE]
Name col: #REF!
Name Cr: DatiI!A$10
Name Cv: DatiI!A$29
Name D: DatiI!A$21
Name E: DatiI!A$31
Name Ebit: DatiI!A$31
Name F: OFFSET(ss!$A$4,0,0,COUNTA(ss!$A$4:$A$2999),2)
Name Fa: DatiI!A$23
Name Fdo: DatiI!A$8
Name For: DatiI!A$35
Name g: Indici!A$3
Name i: Menu!$E$12
Name Il: DatiI!A$6
Name Im: DatiI!A$7
Name Iva: DatiI!A$33
Name L: DatiI!A$12
Name M: DatiI!A$25
Name MOL: DatiI!A$36
Name Mp: DatiI!A$28
Name Of: DatiI!A$37
Name Pb: DatiI!A$20
Name per: DatiI!$D$4:$J$4
Name Pfn: DatiI!A$22
Name Pl: DatiI!A$19
Name Pn: DatiI!A$18
Name Ri: DatiI!A$9
Name Rn: DatiI!A$26
Name Ro: DatiI!A$27
Name s: Menu!$E$8
Name STR: OFFSET(ss!$E$4,1,0,COUNTA(ss!$A$4:$A$2999),1)
Name t: Menu!$N$12
Name TB: IF(t="Abbreviato Cee",1,IF(t="CEE",2,3))
Name V: DatiI!A$32

Sheet Menu
B8: Nome azienda | E8: ALFA SPA
B10: Anno ultimo bilancio | E10: 2024 | H10: Mese chiusura bilancio | K10: 12
B12: Bilancio infrannuale | E12: Sì | G12: 45900 | K12: Tipo Bilancio | N12: Bilancio di Verifica
B15: =+IF(t="Abbreviato Cee","BILANCIO CEE ABBREVIATO","") | G15: =+IF(t="cee","BILANCIO CEE","") | K15: =+IF(t<>"Bilancio di Verifica","CONTO ECONOMICO","") | O15: =+IF(t="Bilancio di Verifica","Bilancio di Verifica","") -> Bilancio di Verifica | AC15: =+IF(t="libero","","")
B18: BILANCIO RICLASSIFICATO | G18: ANALISI PER INDICI | O18: RENDICONTO FINANZIARIO OIC. 10
O22: Manuale d'uso

Sheet 2
A1: =+Menu!B2 -> 0
A3: =+"Stato Patrimoniale" -> Stato Patrimoniale
B4: =+EOMONTH(D4,-12) -> 44926 | D4: =+EOMONTH(F4,-12) -> 45291 | F4: =+EOMONTH(DATE(Menu!E10,Menu!K10,1),0) -> 45657 | H4: =+Menu!G12 -> 45900 | I4: x | J4: codBil
A6: Attivo | B6: =+IF(OR(AND(B166-B276<1,B166-B276>-1),TB<>2),"","Squadratura di "&TEXT(B166-B276,"#.###,00")) | D6: =+IF(OR(AND(D166-D276<1,D166-D276>-1),TB<>2),"","Squadratura di "&TEXT(D166-D276,"#.###,00")) | F6: =+IF(OR(AND(F166-F276<1,F166-F276>-1),TB<>2),"","Squadratura di "&TEXT(F166-F276,"#.###,00")) | H6: =+IF(OR(AND(H166-H276<1,H166-H276>-1),TB<>2),"","Squadratura di "&TEXT(H166-H276,"#.###,00"))
A8: A) Crediti verso soci per versamenti ancora dovuti | J8: 100
A10: B) Immobilizzazioni
A12: I - Immobilizzazioni immateriali:
A14: 1) costi di impianto e di ampliamento
A16: 2) costi di sviluppo
A18: 3) diritti di brevetto industriale e diritti di utilizzazione delle opere dell'ingegno
A20: 4) concessioni, licenze, marchi e diritti simili
A22: 5) avviamento
A24: 6) immobilizzazioni in corso e acconti
A26: 7) altre
A28: Totale | B28: =SUM(B14:B26) -> 0 | D28: =SUM(D14:D26) -> 0 | F28: =SUM(F14:F26) -> 0 | H28: =SUM(H14:H26) -> 0
A30: II - Immobilizzazioni materiali:
A32: 1) terreni e fabbricati
A34: 2) impianti e macchinario
A36: 3) attrezzature industriali e commerciali
A38: 4) altri beni
A40: 5) immobilizzazioni in corso e acconti
A42: Totale | B42: =SUM(B32:B40) -> 0 | D42: =SUM(D32:D40) -> 0 | F42: =SUM(F32:F40) -> 0 | H42: =SUM(H32:H40) -> 0
A44: III - Immobilizzazioni finanziarie:
A46: 1) partecipazioni in:
A48: a) imprese controllate
A50: b) imprese collegate
A52: c) imprese controllanti
A54: d) imprese sottoposte al controllo delle controllanti
A56: d bis) altre imprese
A58: 2) crediti:
A60: a) verso imprese controllate
A62: b) verso imprese collegate
A64: c) verso controllanti
A66: d) verso imprese sottoposte al controllo delle controllanti
... A72: 4) Strumenti finanziari derivati attivi
A74: Totale | B74: =SUM(B46:B72) -> 0 | D74: =SUM(D46:D72) -> 0 | F74: =SUM(F46:F72) -> 0 | H74: =SUM(H46:H72) -> 0 | J74: 30
A76: Totale immobilizzazioni (B) | B76: =+B74+B42+B28 -> 0 | D76: =+D74+D42+D28 -> 0 | F76: =+F74+F42+F28 -> 0 | H76: =+H74+H42+H28 -> 0 | J76: 35
A78: C) Attivo circolante:
A80: I - Rimanenze:
A82: 1) materie prime, sussidiarie e di consumo
A84: 2) prodotti in corso di lavorazione e semilavorati
A86: 3) lavori in corso su ordinazione
A88: 4) prodotti finiti e merci
A90: 5) acconti
A92: Totale | B92: =SUM(B81:B90) -> 0 | D92: =SUM(D81:D90) -> 0 | F92: =SUM(F81:F90) -> 0 | H92: =SUM(H81:H90) -> 0 | J92: 40
A94: II - Crediti, con separata indicazione, per ciascuna voce, degli importi esigibili oltre l'esercizio successivo:
A96: 1) verso clienti | J96: 50
A98: =+LEFT(A96,LEN(A96))&" oltre l'esercizio" -> 1) verso clienti oltre l'esercizio | J98: 30
A100: 2) verso imprese controllate | J100: 54
A102: =+LEFT(A100,LEN(A100))&" oltre l'esercizio" -> 2) verso imprese controllate oltre l'esercizio | J102: 30
A104: 3) verso imprese collegate | J104: 54
A106: =+LEFT(A104,LEN(A104))&" oltre l'esercizio" -> 3) verso imprese collegate oltre l'esercizio | J106: 30
A108: 4) verso controllanti | J108: 54
A110: =+LEFT(A108,LEN(A108))&" oltre l'esercizio" -> 4) verso controllanti oltre l'esercizio | J110: 30
A112: 5) crediti verso imprese sottoposte al controllo di controllanti | J112: 54
A114: =+LEFT(A112,LEN(A112))&" oltre l'esercizio" -> 5) crediti verso imprese sottoposte al controllo di controllanti oltre l'esercizio | J114: 30
A116: 5 bis) crediti tributari | J116: 54
A118: =+LEFT(A116,LEN(A116))&" oltre l'esercizio" -> 5 bis) crediti tributari oltre l'esercizio | J118: 30
A120: 5 ter) imposte anticipate | J120: 54
A122: =+LEFT(A120,LEN(A120))&" oltre l'esercizio" -> 5 ter) imposte anticipate oltre l'esercizio | J122: 30
A124: 5 quater) verso altri | J124: 54
A126: =+LEFT(A124,LEN(A124))&" oltre l'esercizio" -> 5 quater) verso altri oltre l'esercizio | J126: 30
A128: Totale | B128: =SUM(B96:B126) -> 0 | D128: =SUM(D96:D126) -> 0 | F128: =SUM(F96:F126) -> 0 | H128: =SUM(H96:H126) -> 0
A130: III - Attività finanziarie che non costituiscono immobilizzazioni:
A132: 1) partecipazioni in imprese controllate | J132: 70
A134: 2) partecipazioni in imprese collegate | J134: 70
A136: 3) partecipazioni in imprese controllanti | J136: 70
A138: 3 bis) partecipazioni in imprese sottoposte al controllo di controllanti | J138: 70
A140: 4) altre partecipazioni | J140: 70
A142: 5) strumenti finanziari derivati attivi | J142: 70
A144: 6) altri titoli | J144: 70
A146: Totale | B146: =SUM(B132:B144) -> 0 | D146: =SUM(D132:D144) -> 0 | F146: =SUM(F132:F144) -> 0 | H146: =SUM(H132:H144) -> 0
A148: IV - Disponibilità liquide:
A150: 1) depositi bancari e postali
A152: 2) assegni
A154: 3) danaro e valori in cassa
A156: Totale | B156: =SUM(B150:B154) -> 0 | D156: =SUM(D150:D154) -> 0 | F156: =SUM(F150:F154) -> 0 | H156: =SUM(H150:H154) -> 0 | J156: 80
A158: Totale attivo circolante (C) | B158: =+B156+B146+B128+B92 -> 0 | D158: =+D156+D146+D128+D92 -> 0 | F158: =+F156+F146+F128+F92 -> 0 | H158: =+H156+H146+H128+H92 -> 0
A160: D) Ratei e risconti entro l'esercizio | J160: 54
A162: D) Ratei e risconti oltre l'esercizio | J162: 30
A164: Totale Ratei e risconti (D) | B164: =+B160+B162 -> 0 | D164: =+D160+D162 -> 0 | F164: =+F160+F162 -> 0 | H164: =+H160+H162 -> 0
A166: Totale Attivo | B166: =+B8+B76+B158+B160+B162 -> 0 | D166: =+D8+D76+D158+D160+D162 -> 0 | F166: =+F8+F76+F158+F160+F162 -> 0 | H166: =+H8+H76+H158+H160+H162 -> 0
A168: Passivo:
A170: A) Patrimonio netto:
A172: I - Capitale | J172: 90
A174: II - Riserva da soprapprezzo delle azioni | J174: 120
A176: III - Riserve di rivalutazione | J176: 130
A178: IV - Riserva legale | J178: 110
A180: V - Riserve statutarie | J180: 120
A182: VI - Altre riserve, distintamente indicate | J182: 120
A184: VII - Riserva per operazioni di copertura dei flussi finanziari attesi | J184: 120
A186: VIII - Utili (perdite) portati a nuovo | J186: 120
A188: IX - Utile (perdita) dell'esercizio | B188: =CE!B130 -> 0 | D188: =CE!D130 -> 0 | F188: =CE!F130 -> 0 | H188: =+CE!H130 -> 0
A190: Totale | B190: =SUM(B172:B188) -> 0 | D190: =SUM(D172:D188) -> 0 | F190: =SUM(F172:F188) -> 0 | H190: =SUM(H172:H188) -> 0
A192: B) Fondi per rischi e oneri:
A194: 1) per trattamento di quiescenza e obblighi simili
A196: 2) per imposte, anche differite
A198: 3) strumenti finanziari derivati passivi
A200: 4) altri fondi per rischi ed oneri
A202: Totale | B202: =SUM(B194:B201) -> 0 | D202: =SUM(D194:D201) -> 0 | F202: =SUM(F194:F201) -> 0 | H202: =SUM(H194:H201) -> 0 | J202: 160
...

Sheet 1
A1: =+Menu!B2 -> 0
A3: Stato Patrimoniale ex art. 2435 bis
B4: =+EOMONTH(D4,-12) -> 44926 | D4: =+EOMONTH(F4,-12) -> 45291 | F4: =+EOMONTH(DATE(Menu!E10,Menu!K10,1),0) -> 45657 | H4: =+Menu!G12 -> 45900 | I4: x | J4: cod | K4: x | L4: x | M4: x | N4: x | O4: x | P4: x | Q4: x | R4: x | S4: x | T4: x | U4: x | V4: x | W4: x | X4: x | Y4: x | Z4: x | AA4: x
A6: Attivo | B6: =+IF(OR(AND(B38-B76<1,B38-B76>-1),TB<>1),"","Squadratura di "&TEXT(B38-B76,"#.###,00")) | D6: =+IF(OR(AND(D38-D76<1,D38-D76>-1),TB<>1),"","Squadratura di "&TEXT(D38-D76,"#.###,00")) | F6: =+IF(OR(AND(F38-F76<1,F38-F76>-1),TB<>1),"","Squadratura di "&TEXT(F38-F76,"#.###,00")) | H6: =+IF(OR(AND(H38-H76<1,H38-H76>-1),TB<>1),"","Squadratura di "&TEXT(H38-H76,"#.###,00"))
A8: A) Crediti verso soci per versamenti ancora dovuti | J8: 100
A10: B) Immobilizzazioni, con separata indicazione di quelle concesse in locazione finanziaria:
A12: I - Immobilizzazioni immateriali:
A14: II - Immobilizzazioni materiali:
A16: III - Immobilizzazioni finanziarie | F16: =+D16 -> 0 | H16: =+F16 -> 0 | J16: 30
A18: Totale immobilizzazioni (B); | B18: =SUM(B12:B17) -> 0 | D18: =SUM(D12:D17) -> 0 | F18: =SUM(F12:F17) -> 0 | H18: =SUM(H12:H17) -> 0
A20: C) Attivo circolante:
A22: I - Rimanenze: | J22: 40
A24: II - Crediti (compresi eventualmente Ratei , Risconti e crediti vs soci)
A26: II - Crediti oltre l'es. (compresi eventualmente Ratei , Risconti e crediti vs soci) | J26: 30
A28: III - Attività finanziarie che non costituiscono immobilizzazioni: | J28: 70
A30: IV - Disponibilità liquide: | J30: 80
A32: Totale attivo circolante (C). | B32: =SUM(B22:B30) -> 0 | D32: =SUM(D22:D30) -> 0 | F32: =SUM(F22:F30) -> 0 | H32: =SUM(H22:H30) -> 0
A34: D) Ratei e risconti entro l'esercizio | J34: 52
A36: D) Ratei e risconti oltre l'esercizio | J36: 30
A38: Totale Attivo | B38: =+B32+B18+B8+B34+B36 -> 0 | D38: =+D32+D18+D8+D34+D36 -> 0 | F38: =+F32+F18+F8+F34+F36 -> 0 | G38: =+G32+G18+G8 -> 0 | H38: =+H32+H18+H8+H34+H36 -> 0
A40: Passivo:
A42: A) Patrimonio netto:
A44: I - Capitale. | J44: 90
A46: II - Riserva da soprapprezzo delle azioni. | J46: 120
A48: III - Riserve di rivalutazione. | J48: 130
A50: IV - Riserva legale. | J50: 110
A52: V - Riserve statutarie | J52: 120
A54: VI - Riserva per azioni proprie in portafoglio. | J54: 120
A56: VII - Altre riserve, distintamente indicate. | J56: 120
A58: VIII - Utili (perdite) portati a nuovo. | J58: 140
A60: IX - Utile (perdita) dell'esercizio. | B60: =+CE!B130 -> 0 | D60: =+CE!D130 -> 0 | F60: =+CE!F130 -> 0 | H60: =+CE!H130 -> 0
A62: Totale. | B62: =SUM(B44:B60) -> 0 | D62: =SUM(D44:D60) -> 0 | F62: =SUM(F44:F60) -> 0 | H62: =SUM(H44:H60) -> 0
A64: B) Fondi per rischi e oneri: | J64: 160 | K64: x
A66: C) Trattamento di fine rapporto di lavoro subordinato. | J66: 170
A68: D) Debiti (compresi eventualmente Ratei , Risconti)
A70: D) Debiti oltre l'es. (compresi eventualmente Ratei , Risconti)
A72: E) Ratei e risconti entro l'esercizio | J72: 232
A74: E) Ratei e risconti oltre l'esercizio | J74: 192
A76: Totale Passivo | B76: =+B72+B70+B68+B66+B64+B62+B74 -> 0 | D76: =+D72+D70+D68+D66+D64+D62+D74 -> 0 | F76: =+F72+F70+F68+F66+F64+F62+F74 -> 0 | H76: =+H72+H70+H68+H66+H64+H62+H74 -> 0
A78: Informazioni aggiuntive
A80: Immobilizzazioni immateriali | B80: =+B12 -> 0 | D80: =+D12 -> 0 | F80: =+F12 -> 0 | H80: =+H12 -> 0
A82: Fondi ammortamento immateriali | J82: 12
A84: Immobilizzazioni immateriali lorde | B84: =+B80+B82 -> 0 | D84: =+D80+D82 -> 0 | F84: =+F80+F82 -> 0 | H84: =+H80+H82 -> 0 | J84: 10
A86: Immobilizzazioni materiali | B86: =+B14 -> 0 | D86: =+D14 -> 0 | F86: =+F14 -> 0 | H86: =+H14 -> 0
A88: Fondi ammortamento materiali | J88: 22
A90: Immobilizzazioni materiali lorde | B90: =+B86+B88 -> 0 | D90: =+D86+D88 -> 0 | F90: =+F86+F88 -> 0 | H90: =+H86+H88 -> 0 | J90: 20
A92: Crediti | B92: =+B24 -> 0 | D92: =+D24 -> 0 | F92: =+F24 -> 0 | H92: =+H24 -> 0
A94: 1) Crediti verso clienti; | J94: 50
A96: Altri Crediti | B96: =+B92-B94 -> 0 | D96: =+D92-D94 -> 0 | F96: =+F92-F94 -> 0 | H96: =+H92-H94 -> 0 | J96: 54
A98: Debiti entro l'esercizio | B98: =+B68 -> 0 | D98: =+D68 -> 0 | F98: =+F68 -> 0 | H98: =+H68 -> 0
A100: 1) obbligazioni; | J100: 234
A102: 2) obbligazioni convertibili; | J102: 234
A104: 3) debiti verso soci per finanziamenti; | J104: 234
A106: 4) debiti verso banche; | J106: 220
A108: 5) debiti verso altri finanziatori; | J108: 234
A110: 6) acconti; | J110: 200
A112: 7) debiti verso fornitori; | J112: 210
A114: 8) debiti rappresentati da titoli di credito; | J114: 210
A116: 9) debiti verso imprese controllate; | J116: 234
A118: 10) debiti verso imprese collegate; | J118: 234
A120: 11) debiti verso controllanti; | J120: 234
A122: 12) debiti tributari; | J122: 230
A124: 13) debiti verso istituti di previdenza e di sicurezza sociale; | J124: 230
A126: 14) altri debiti. | B126: =+B98-SUM(B100:B124) -> 0 | D126: =+D98-SUM(D100:D124) -> 0 | F126: =+F98-SUM(F100:F124) -> 0 | H126: =+H98-SUM(H100:H124) -> 0 | J126: 234
A128: Debiti oltre l'esercizio | B128: =+B70 -> 0 | D128: =+D70 -> 0 | F128: =+F70 -> 0 | H128: =+H70 -> 0
A130: =+LEFT(A100,LEN(A100)-1)&" oltre l'es." -> 1) obbligazioni oltre l'es. | J130: 192
A132: =+LEFT(A102,LEN(A102)-1)&" oltre l'es." -> 2) obbligazioni convertibili oltre l'es. | J132: 192
A134: =+LEFT(A104,LEN(A104)-1)&" oltre l'es." -> 3) debiti verso soci per finanziamenti oltre l'es. | J134: 150
A136: =+LEFT(A106,LEN(A106)-1)&" oltre l'es." -> 4) debiti verso banche oltre l'es. | J136: 180
A138: =+LEFT(A108,LEN(A108)-1)&" oltre l'es." -> 5) debiti verso altri finanziatori oltre l'es. | J138: 192
A140: =+LEFT(A110,LEN(A110)-1)&" oltre l'es." -> 6) acconti oltre l'es. | J140: 192
A142: =+LEFT(A112,LEN(A112)-1)&" oltre l'es." -> 7) debiti verso fornitori oltre l'es. | J142: 192
A144: =+LEFT(A114,LEN(A114)-1)&" oltre l'es." -> 8) debiti rappresentati da titoli di credito oltre l'es. | J144: 192
A146: =+LEFT(A116,LEN(A116)-1)&" oltre l'es." -> 9) debiti verso imprese controllate oltre l'es. | J146: 150
A148: =+LEFT(A118,LEN(A118)-1)&" oltre l'es." -> 10) debiti verso imprese collegate oltre l'es. | J148: 150
A150: =+LEFT(A120,LEN(A120)-1)&" oltre l'es." -> 11) debiti verso controllanti oltre l'es. | J150: 150
A152: =+LEFT(A122,LEN(A122)-1)&" oltre l'es." -> 12) debiti tributari oltre l'es. | J152: 190
A154: =+LEFT(A124,LEN(A124)-1)&" oltre l'es." -> 13) debiti verso istituti di previdenza e di sicurezza sociale oltre l'es. | J154: 190
A156: =+LEFT(A126,LEN(A126)-1)&" oltre l'es." -> 14) altri debiti oltre l'es. | B156: =+B128-SUM(B130:B154) -> 0 | D156: =+D128-SUM(D130:D154) -> 0 | F156: =+F128-SUM(F130:F154) -> 0 | H156: =+H128-SUM(H130:H154) -> 0 | J156: 192
A158: Leasing entro | J158: 220
A160: Leasing oltre | J160: 180
A162: Totale beni in leasing | B162: =+B158+B160 -> 0 | D162: =+D158+D160 -> 0 | F162: =+F158+F160 -> 0 | H162: =+H158+H160 -> 0 | J162: 20

Sheet CE
A1: =+Menu!B2 -> 0
A3: Conto Economico | B3: =IF(TB=2,+'2'!B3,'1'!B3) -> 0 | D3: =IF(TB=2,+'2'!D3,'1'!D3) -> 0 | F3: =IF(TB=2,+'2'!F3,'1'!F3) -> 0 | H3: =IF(TB=2,+'2'!H3,'1'!H3) -> 0
B4: =+EOMONTH(D4,-12) -> 44926 | C4: . | D4: =+EOMONTH(F4,-12) -> 45291 | E4: . | F4: =+EOMONTH(DATE(Menu!E10,Menu!K10,1),0) -> 45657 | G4: . | H4: =+Menu!G12 -> 45900 | I4: x | J4: codBil | K4: x | L4: CodBil2 | M4: x
I5: X | K5: X | M5: X
A6: A) Valore della produzione:
A8: 1) ricavi delle vendite e delle prestazioni; | J8: 300 | L8: 500
A10: 2) variazioni delle rimanenze di prodotti in corso di lavorazione, semilavorati e finiti; | J10: 310 | L10: 510
A12: 3) variazioni dei lavori in corso su ordinazione; | J12: 310 | L12: 510
A14: 4) incrementi di immobilizzazioni per lavori interni; | J14: 310 | L14: 525
A16: 5) altri ricavi e proventi | B16: =+B18+B20+B22+B24 -> 0 | D16: =+D18+D20+D22+D24 -> 0 | F16: =+F18+F20+F22+F24 -> 0 | H16: =+H18+H20+H22+H24 -> 0
A18: 5a) ricavi vari | J18: 320 | L18: 620
A20: 5b) contributi in conto esercizio | J20: 315 | L20: 620
A22: 5c) contributi in conto capitale | J22: 315 | L22: 620
A24: 5-1) proventi straordinari | J24: 440 | L24: 620
A26: Totale. | B26: =SUM(B8:B16) -> 0 | D26: =SUM(D8:D16) -> 0 | F26: =SUM(F8:F16) -> 0 | H26: =SUM(H8:H16) -> 0
A28: B) Costi della produzione:
A30: 6) per materie prime, sussidiarie, di consumo e di merci; | J30: 330 | L30: 530
A32: 7) per servizi; | J32: 360
A34: 8) per godimento di beni di terzi; | J34: 370
A36: 9) per il personale: | B36: =SUM(B38:B46) -> 0 | D36: =SUM(D38:D46) -> 0 | F36: =SUM(F38:F46) -> 0 | H36: =SUM(H38:H46) -> 0
A38: a) salari e stipendi; | J38: 390
A40: b) oneri sociali; | D40: =+B40*1.2 -> 0 | F40: =+D40*1.2 -> 0 | H40: =+F40*1.2 -> 0 | J40: 390
A42: c) trattamento di fine rapporto; | D42: =+B42*1.2 -> 0 | F42: =+D42*1.2 -> 0 | H42: =+F42*1.2 -> 0 | J42: 400
A44: d) trattamento di quiescenza e simili; | J44: 400
A46: e) altri costi; | J46: 390
A48: 10) ammortamenti e svalutazioni: | B48: =SUM(B50:B56) -> 0 | D48: =SUM(D50:D56) -> 0 | F48: =SUM(F50:F56) -> 0 | H48: =SUM(H50:H56) -> 0 | J48: 410
A50: a) ammortamento delle immobilizzazioni immateriali;
A52: b) ammortamento delle immobilizzazioni materiali; | D52: =+D50*2 -> 0 | F52: =+F50*2 -> 0 | H52: =+H50*2 -> 0
A54: c) altre svalutazioni delle immobilizzazioni;
A56: d) svalutazioni dei crediti compresi nell'attivo circolante e delle disponibilità liquide; | L56: 595
A58: 11) variazioni delle rimanenze di materie prime, sussidiarie, di consumo e merci; | J58: 340 | L58: 520
A60: 12) accantonamenti per rischi; | J60: 415 | L60: 603
A62: 13) altri accantonamenti; | J62: 415 | L62: 603
A64: 14) oneri diversi di gestione. | B64: =+B66+B68 -> 0 | D64: =+D66+D68 -> 0 | F64: =+F66+F68 -> 0 | H64: =+H66+H68 -> 0
A66: a) oneri diversi di gestione. | J66: 380 | L66: 600
A68: b) oneri straordinari | J68: 450 | L68: 620
A70: Totale B | B70: =+SUM(B50:B64,B36,B30:B34) -> 0 | D70: =+SUM(D50:D64,D36,D30:D34) -> 0 | F70: =+SUM(F50:F64,F36,F30:F34) -> 0 | H70: =+SUM(H50:H64,H36,H30:H34) -> 0
A72: Differenza tra valore e costi della produzione (A - B). | B72: =+B26+B70 -> 0 | D72: =+D26+D70 -> 0 | F72: =+F26+F70 -> 0 | H72: =+H26+H70 -> 0
A74: C) Proventi e oneri finanziari:
A76: 15) proventi da partecipazioni | B76: =SUM(B78:B84) -> 0 | D76: =SUM(D78:D84) -> 0 | F76: =SUM(F78:F84) -> 0 | H76: =SUM(H78:H84) -> 0
A78: a) da imprese controllate | J78: 432
A80: b) da imprese collegate | J80: 432
A82: c) da imprese controllanti | J82: 432
A84: d) da imprese sottoposte al controllo di controllanti | J84: 432
A86: 16) altri proventi finanziari: | B86: =+B88+B90+B92+B94 -> 0 | D86: =+D88+D90+D92+D94 -> 0 | F86: =+F88+F90+F92+F94 -> 0 | H86: =+H88+H90+H92+H94 -> 0
A88: a) da crediti iscritti nelle immobilizzazioni | J88: 420
A90: b) da titoli iscritti nelle immobilizzazioni che non costituiscono partecipazioni; | J90: 420
A92: c) da titoli iscritti nell'attivo circolante che non costituiscono partecipazioni; | J92: 420
A94: d) proventi diversi dai precedenti | J94: 420
A96: 17) interessi e altri oneri finanziari | J96: 430
A98: 17 bis) utili e perdite su cambi. | B98: 0 | D98: =+D96 -> 0 | F98: =+F96 -> 0 | H98: =+H96 -> 0 | J98: 430
A100: Totale (15 + 16 - 17+ - 17 bis) | B100: =+B98+B96+B86+B76 -> 0 | D100: =+D98+D96+D86+D76 -> 0 | F100: =+F98+F96+F86+F76 -> 0 | H100: =+H98+H96+H86+H76 -> 0 | L100: 610
A102: D) Rettifiche di valore di attività finanziarie: | B102: =+B104+B114 -> 0 | D102: =+D104+D114 -> 0 | F102: =+F104+F114 -> 0 | H102: =+H104+H114 -> 0
A104: 18) rivalutazioni: | B104: =+B106+B108+B110+B112 -> 0 | D104: =+D106+D108+D110+D112 -> 0 | F104: =+F106+F108+F110+F112 -> 0 | H104: =+H106+H108+H110+H112 -> 0
A106: a) di partecipazioni; | J106: 440 | L106: 620
A108: b) di immobilizzazioni finanziarie che non costituiscono partecipazioni; | J108: 440 | L108: 620
A110: c) di titoli iscritti all'attivo circolante che non costituiscono partecipazioni; | J110: 440 | L110: 620
A112: d) di strumenti finanziari derivati | J112: 440 | L112: 620
A114: 19) svalutazioni: | B114: =+B116+B118+B120+B122 -> 0 | D114: =+D116+D118+D120 -> 0 | F114: =+F116+F118+F120 -> 0 | H114: =+H116+H118+H120 -> 0
A116: a) di partecipazioni; | J116: 450 | L116: 620
A118: b) di immobilizzazioni finanziarie che non costituiscono partecipazioni; | J118: 450 | L118: 620
A120: c) di titoli iscritti nell'attivo circolante che non costituiscono partecipazioni. | J120: 450 | L120: 620
A122: d) di strumenti finanziari derivati | J122: 450 | L122: 620
A124: Totale delle rettifiche (18 - 19). | B124: =+B104+B114 -> 0 | D124: =+D104+D114 -> 0 | F124: =+F104+F114 -> 0 | H124: =+H104+H114 -> 0
A126: Risultato prima delle imposte (A - B + - C + - D); | B126: =+B72+B100+B124 -> 0 | D126: =+D72+D100+D124 -> 0 | F126: =+F72+F100+F124 -> 0 | H126: =+H72+H100+H124 -> 0
A128: 22) imposte sul reddito dell'esercizio, correnti, differite e anticipate; | J128: 460 | L128: 630
A130: 23) utile (perdite) dell'esercizio. (1) | B130: =+B126+B128 -> 0 | D130: =+D126+D128 -> 0 | F130: =+F126+F128 -> 0 | H130: =+H126+H128 -> 0
A131: Informazioni aggiuntive
A134: Costi per servizi | B134: =+B32 -> 0 | D134: =+D32 -> 0 | F134: =+F32 -> 0 | H134: =+H32 -> 0
A136: Servizi variabili industriali | L136: 540
A138: Servizi variabili commerciali | B138: =+B136/1.1 -> 0 | D138: =+D136/1.1 -> 0 | F138: =+F136/1.1 -> 0 | H138: =+H136/1.1 -> 0 | L138: 590
A140: Costi fissi industriali | L140: 550
A142: Costi fissi commerciali | L142: 595
A144: Costi fissi generali e amministrativi | B144: =+B134-B136-B138-B140-B142 -> 0 | D144: =+D134-D136-D138-D140-D142 -> 0 | F144: =+F134-F136-F138-F140-F142 -> 0 | H144: =+H134-H136-H138-H140-H142 -> 0 | L144: 600
A146: Costi per godimento beni di terzi | B146: =+B34 -> 0 | D146: =+D34 -> 0 | F146: =+F34 -> 0 | H146: =+H34 -> 0
A148: Leasing industriali | D148: =+B148 -> 0 | F148: =+D148 -> 0 | H148: =+F148 -> 0 | L148: 560
A150: Leasing commerciali | L150: 595
A152: Affitti/noleggi industriali | L152: 560
A154: Affitti/noleggi commerciali | L154: 595
A156: Altri leasing | L156: 600
A158: Royalties | L158: 590
A160: Altri costi godimento beni di terzi | B160: =+B146-B148-B150-B152-B154-B156-B158 -> 0 | D160: =+D146-D148-D150-D152-D154-D156-D158 -> 0 | F160: =+F146-F148-F150-F152-F154-F156-F158 -> 0 | H160: =+H146-SUM(H148:H158) -> 0 | L160: 600
A162: Costi del Personale | B162: =+B38+B40+B42+B44+B46 -> 0 | D162: =+D38+D40+D42+D44+D46 -> 0 | F162: =+F38+F40+F42+F44+F46 -> 0 | H162: =+H36 -> 0
A164: Personale industriale diretto (MOD) | H164: =+F164 -> 0 | L164: 570
A166: Personale Industriale indiretto | L166: 550
A168: Personale commerciale | L168: 595
A170: Personale amministrativo | L170: 600
A172: Altri costi del personale | B172: =+B162-B164-B166-B168-B170 -> 0 | D172: =+D162-D164-D166-D168-D170 -> 0 | F172: =+F162-F164-F166-F168-F170 -> 0 | H172: =+H162-SUM(H164:H170) -> 0 | L172: 600
A174: Ammortamenti e svalutazioni | B174: =+B50+B52 -> 0 | D174: =+D50+D52 -> 0 | F174: =+F50+F52 -> 0 | H174: =+H48 -> 0
A176: Ammortamenti industriali | L176: 550
A178: Ammortamenti commerciali | L178: 595
A180: Ammortamenti amministrativi e generali | B180: =+B174-B176-B178 -> 0 | D180: =+D174-D176-D178 -> 0 | F180: =+F174-F176-F178 -> 0 | H180: =+H174-H176-H178 -> 0 | L180: 600
A182: Informazioni per il rendiconto finanziario
A185: Vendita Cespiti (valore di realizzo)
A187: Vendita Cespiti (valore di libro)
A189: Plusvalenza (minusvalenza) | D189: =+D185-D187 -> 0 | F189: =+F185-F187 -> 0
A191: Vendita imm. fin. (valore di realizzo)
A193: Vendita imm. fin (valore di libro)
A195: Plusvalenza (minusvalenza) | D195: =+D191-D193 -> 0 | F195: =+F191-F193 -> 0
A197: Vendita attività fin. (valore di realizzo)
...

Sheet 3
A3: Bilancio di Verifica
A4: Copiare Bilancio di verifica e riclassificare in base ai codici contenuti nel foglio BR e riportati a lato
B6: Quadratura | C6: =+ROUND(SUM(C8:C792),0) -> 0 | K6: Elenco Codici
A7: Codice | B7: Descrizione | C7: Saldo | D7: Periodo | E7: Codice Suggerito | F7: Inserimento codice | G7: Codice Assegnato | H7: Descrizione
A8: 03/05/501 | B8: SPESE COSTITUZIONE E MODIF. | C8: 2086.45 | D8: 45657 | E8: =+IF(A8="","",VLOOKUP(A8,$A$7:H8,6,0)) -> 10 | F8: 10 | G8: =+IF(F8>0,F8,E8) -> 10 | H8: =+IFERROR(IF(A8="","",VLOOKUP(G8,cbr,2,0)),"Codice non inserito") -> IMMOBILIZZ. IMMATERIALI
A9: 04/05/005 | B9: F/AMM COSTI IMPIANTO | C9: -251.21 | D9: 45657 | E9: =+IF(A9="","",VLOOKUP(A9,$A$7:H9,6,0)) -> 12 | F9: 12 | G9: =+IF(F9>0,F9,E9) -> 12 | H9: =+IFERROR(IF(A9="","",VLOOKUP(G9,cbr,2,0)),"Codice non inserito") -> FDO IMM. IMMAT.
A10: 06/05/015 | B10: FABBRICATI IND.LI. E COMM.LI | C10: 700 | D10: 45657 | E10: =+IF(A10="","",VLOOKUP(A10,$A$7:H10,6,0)) -> 20 | F10: 20 | G10: =+IF(F10>0,F10,E10) -> 20 | H10: =+IFERROR(IF(A10="","",VLOOKUP(G10,cbr,2,0)),"Codice non inserito") -> IMMOBILIZZ. MATERIALI
A11: 06/15/005 | B11: ATTREZZAT. IND.LI E COMM.LI | C11: 7550.77 | D11: 45657 | E11: =+IF(A11="","",VLOOKUP(A11,$A$7:H11,6,0)) -> 20 | F11: 20 | G11: =+IF(F11>0,F11,E11) -> 20 | H11: =+IFERROR(IF(A11="","",VLOOKUP(G11,cbr,2,0)),"Codice non inserito") -> IMMOBILIZZ. MATERIALI
A12: 06/20/005 | B12: MOBILI E MACCHINE ORD. D'UFFICIO | C12: 5848.16 | D12: 45657 | E12: =+IF(A12="","",VLOOKUP(A12,$A$7:H12,6,0)) -> 20 | F12: 20 | G12: =+IF(F12>0,F12,E12) -> 20 | H12: =+IFERROR(IF(A12="","",VLOOKUP(G12,cbr,2,0)),"Codice non inserito") -> IMMOBILIZZ. MATERIALI
A13: 06/20/501 | B13: CELLULARI | C13: 3806.65 | D13: 45657 | E13: =+IF(A13="","",VLOOKUP(A13,$A$7:H13,6,0)) -> 20 | F13: 20 | G13: =+IF(F13>0,F13,E13) -> 20 | H13: =+IFERROR(IF(A13="","",VLOOKUP(G13,cbr,2,0)),"Codice non inserito") -> IMMOBILIZZ. MATERIALI
A14: 06/25/015 | B14: AUTOCARRI/AUTOVETTURE | C14: 76695.22 | D14: 45657 | E14: =+IF(A14="","",VLOOKUP(A14,$A$7:H14,6,0)) -> 20 | F14: 20 | G14: =+IF(F14>0,F14,E14) -> 20 | H14: =+IFERROR(IF(A14="","",VLOOKUP(G14,cbr,2,0)),"Codice non inserito") -> IMMOBILIZZ. MATERIALI
A15: 07/05/015 | B15: F/AMM FABBR. IND.LI E COMM.LI. | C15: -63.21 | D15: 45657 | E15: =+IF(A15="","",VLOOKUP(A15,$A$7:H15,6,0)) -> 22 | F15: 22 | G15: =+IF(F15>0,F15,E15) -> 22 | H15: =+IFERROR(IF(A15="","",VLOOKUP(G15,cbr,2,0)),"Codice non inserito") -> FDO IMM. MAT.
A16: 07/15/005 | B16: F/AMM ATTREZ. IND.LI E COMM.LI | C16: -538.19 | D16: 45657 | E16: =+IF(A16="","",VLOOKUP(A16,$A$7:H16,6,0)) -> 22 | F16: 22 | G16: =+IF(F16>0,F16,E16) -> 22 | H16: =+IFERROR(IF(A16="","",VLOOKUP(G16,cbr,2,0)),"Codice non inserito") -> FDO IMM. MAT.
A17: 07/20/005 | B17: F/AMM MOBILI E MACCH. ORD. D'UFF | C17: -405.05 | D17: 45657 | E17: =+IF(A17="","",VLOOKUP(A17,$A$7:H17,6,0)) -> 22 | F17: 22 | G17: =+IF(F17>0,F17,E17) -> 22 | H17: =+IFERROR(IF(A17="","",VLOOKUP(G17,cbr,2,0)),"Codice non inserito") -> FDO IMM. MAT.
A18: 07/20/010 | B18: F/AMM MACCH. ELETTROM. D'UFF. | C18: -386.64 | D18: 45657 | E18: =+IF(A18="","",VLOOKUP(A18,$A$7:H18,6,0)) -> 22 | F18: 22 | G18: =+IF(F18>0,F18,E18) -> 22 | H18: =+IFERROR(IF(A18="","",VLOOKUP(G18,cbr,2,0)),"Codice non inserito") -> FDO IMM. MAT.
A19: 07/25/015 | B19: F/AMM. AUTOCARRI/AUTOVETTURE | C19: -6289.37 | D19: 45657 | E19: =+IF(A19="","",VLOOKUP(A19,$A$7:H19,6,0)) -> 22 | F19: 22 | G19: =+IF(F19>0,F19,E19) -> 22 | H19: =+IFERROR(IF(A19="","",VLOOKUP(G19,cbr,2,0)),"Codice non inserito") -> FDO IMM. MAT.
... A21: 11/05/020 | B21: MATERIALI VARI | C21: 1920.13 | D21: 45657 | E21: =+IF(A21="","",VLOOKUP(A21,$A$7:H21,6,0)) -> 40 | F21: 40 | G21: =+IF(F21>0,F21,E21) -> 40 | H21: =+IFERROR(IF(A21="","",VLOOKUP(G21,cbr,2,0)),"Codice non inserito") -> RIMANENZE
A22: 14/00000 | B22: CREDITI V/CLIENTI | C22: 44739.79 | D22: 45657 | E22: =+IF(A22="","",VLOOKUP(A22,$A$7:H22,6,0)) -> 50 | F22: 50 | G22: 54 | H22: =+IFERROR(IF(A22="","",VLOOKUP(G22,cbr,2,0)),"Codice non inserito") -> ALTRI CREDITI
A23: 15/05/503 | B23: CARTA CARBURANTE | C23: 231.89 | D23: 45657 | E23: =+IF(A23="","",VLOOKUP(A23,$A$7:H23,6,0)) -> 80 | F23: 80 | G23: =+IF(F23>0,F23,E23) -> 80 | H23: =+IFERROR(IF(A23="","",VLOOKUP(G23,cbr,2,0)),"Codice non inserito") -> CASSA E BANCHE
A24: 24/05/001 | B24: BANCA | C24: 117180.65 | D24: 45657 | E24: =+IF(A24="","",VLOOKUP(A24,$A$7:H24,6,0)) -> 80 | F24: 80 | G24: =+IF(F24>0,F24,E24) -> 80 | H24: =+IFERROR(IF(A24="","",VLOOKUP(G24,cbr,2,0)),"Codice non inserito") -> CASSA E BANCHE
A25: 26/10/005 | B25: RISCONTI ATTIVI | C25: 367.54 | D25: 45657 | E25: =+IF(A25="","",VLOOKUP(A25,$A$7:H25,6,0)) -> 54 | F25: 54 | G25: =+IF(F25>0,F25,E25) -> 54 | H25: =+IFERROR(IF(A25="","",VLOOKUP(G25,cbr,2,0)),"Codice non inserito") -> ALTRI CREDITI
A26: 28/05/005 | B26: CAPITALE SOCIALE | C26: -10000 | D26: 45657 | E26: =+IF(A26="","",VLOOKUP(A26,$A$7:H26,6,0)) -> 90 | F26: 90 | G26: =+IF(F26>0,F26,E26) -> 90 | H26: =+IFERROR(IF(A26="","",VLOOKUP(G26,cbr,2,0)),"Codice non inserito") -> CAPITALE
A27: 31/05/005 | B27: DEBITI P/T.F.R. | C27: -1530.97 | D27: 45657 | E27: =+IF(A27="","",VLOOKUP(A27,$A$7:H27,6,0)) -> 170 | F27: 170 | G27: =+IF(F27>0,F27,E27) -> 170 | H27: =+IFERROR(IF(A27="","",VLOOKUP(G27,cbr,2,0)),"Codice non inserito") -> TFR
A28: 34/05/045 | B28: BANCA C/FINANZIAMENTI | C28: -16215.78 | D28: 45657 | E28: =+IF(A28="","",VLOOKUP(A28,$A$7:H28,6,0)) -> 180 | F28: 180 | G28: =+IF(F28>0,F28,E28) -> 180 | H28: =+IFERROR(IF(A28="","",VLOOKUP(G28,cbr,2,0)),"Codice non inserito") -> DEBITI VS BANCHE A MEDIO LUNGO T.
A29: 34/05/501 | B29: FINANZIAMENTO | C29: -3173.25 | D29: 45657 | E29: =+IF(A29="","",VLOOKUP(A29,$A$7:H29,6,0)) -> 180 | F29: 180 | G29: =+IF(F29>0,F29,E29) -> 180 | H29: =+IFERROR(IF(A29="","",VLOOKUP(G29,cbr,2,0)),"Codice non inserito") -> DEBITI VS BANCHE A MEDIO LUNGO T.
A30: 34/05/502 | B30: FINANZIAMENTO | C30: -14508.71 | D30: 45657 | E30: =+IF(A30="","",VLOOKUP(A30,$A$7:H30,6,0)) -> 180 | F30: 180 | G30: =+IF(F30>0,F30,E30) -> 180 | H30: =+IFERROR(IF(A30="","",VLOOKUP(G30,cbr,2,0)),"Codice non inserito") -> DEBITI VS BANCHE A MEDIO LUNGO T.
A31: 36/05/501 | B31: SOCI C/FINANZIAMENTI (INFRUTT.) | C31: -195.75 | D31: 45657 | E31: =+IF(A31="","",VLOOKUP(A31,$A$7:H31,6,0)) -> 150 | F31: 150 | G31: =+IF(F31>0,F31,E31) -> 150 | H31: =+IFERROR(IF(A31="","",VLOOKUP(G31,cbr,2,0)),"Codice non inserito") -> FINANZIAMENTO SOCI E INFRAGR.
A32: 38/05/501 | B32: CLIENTI C/ANTICIPI | C32: 69.5 | D32: 45657 | E32: =+IF(A32="","",VLOOKUP(A32,$A$7:H32,6,0)) -> 192 | F32: 192 | G32: =+IF(F32>0,F32,E32) -> 192 | H32: =+IFERROR(IF(A32="","",VLOOKUP(G32,cbr,2,0)),"Codice non inserito") -> ALTRI DEBITI A M/L
A33: 40/00000 | B33: DEBITI V/FORNITORI | C33: -57641.77 | D33: 45657 | E33: =+IF(A33="","",VLOOKUP(A33,$A$7:H33,6,0)) -> 210 | F33: 210 | G33: =+IF(F33>0,F33,E33) -> 210 | H33: =+IFERROR(IF(A33="","",VLOOKUP(G33,cbr,2,0)),"Codice non inserito") -> FORNITORI
A34: 41/05/005 | B34: FATTURE DA RICEVERE | C34: -2604.64 | D34: 45657 | E34: =+IF(A34="","",VLOOKUP(A34,$A$7:H34,6,0)) -> 210 | F34: 210 | G34: =+IF(F34>0,F34,E34) -> 210 | H34: =+IFERROR(IF(A34="","",VLOOKUP(G34,cbr,2,0)),"Codice non inserito") -> FORNITORI
... A224: 88/20/502 | B224: INTERESSI IVA TRIM. | C224: 56.96 | D224: 45900 | E224: =+IF(A224="","",VLOOKUP(A224,$A$7:H224,6,0)) -> 430 | F224: 430 | G224: =+IF(F224>0,F224,E224) -> 430 | H224: =+IFERROR(IF(A224="","",VLOOKUP(G224,cbr,2,0)),"Codice non inserito") -> ONERI FINANZIARI
E225: =+IF(A225="","",VLOOKUP(A225,$A$7:H225,6,0)) | G225: =+IF(F225>0,F225,E225) | H225: =+IFERROR(IF(A225="","",VLOOKUP(G225,cbr,2,0)),"Codice non inserito")
E226: =+IF(A226="","",VLOOKUP(A226,$A$7:H226,6,0)) | G226: =+IF(F226>0,F226,E226) | H226: =+IFERROR(IF(A226="","",VLOOKUP(G226,cbr,2,0)),"Codice non inserito")
E227: =+IF(A227="","",VLOOKUP(A227,$A$7:H227,6,0)) | G227: =+IF(F227>0,F227,E227) | H227: =+IFERROR(IF(A227="","",VLOOKUP(G227,cbr,2,0)),"Codice non inserito")
E228: =+IF(A228="","",VLOOKUP(A228,$A$7:H228,6,0)) | G228: =+IF(F228>0,F228,E228) | H228: =+IFERROR(IF(A228="","",VLOOKUP(G228,cbr,2,0)),"Codice non inserito")
E229: =+IF(A229="","",VLOOKUP(A229,$A$7:H229,6,0)) | G229: =+IF(F229>0,F229,E229) | H229: =+IFERROR(IF(A229="","",VLOOKUP(G229,cbr,2,0)),"Codice non inserito")
E230: =+IF(A230="","",VLOOKUP(A230,$A$7:H230,6,0)) | G230: =+IF(F230>0,F230,E230) | H230: =+IFERROR(IF(A230="","",VLOOKUP(G230,cbr,2,0)),"Codice non inserito")
E231: =+IF(A231="","",VLOOKUP(A231,$A$7:H231,6,0)) | G231: =+IF(F231>0,F231,E231) | H231: =+IFERROR(IF(A231="","",VLOOKUP(G231,cbr,2,0)),"Codice non inserito")
E232: =+IF(A232="","",VLOOKUP(A232,$A$7:H232,6,0)) | G232: =+IF(F232>0,F232,E232) | H232: =+IFERROR(IF(A232="","",VLOOKUP(G232,cbr,2,0)),"Codice non inserito")
E233: =+IF(A233="","",VLOOKUP(A233,$A$7:H233,6,0)) | G233: =+IF(F233>0,F233,E233) | H233: =+IFERROR(IF(A233="","",VLOOKUP(G233,cbr,2,0)),"Codice non inserito")
E234: =+IF(A234="","",VLOOKUP(A234,$A$7:H234,6,0)) | G234: =+IF(F234>0,F234,E234) | H234: =+IFERROR(IF(A234="","",VLOOKUP(G234,cbr,2,0)),"Codice non inserito")
E235: =+IF(A235="","",VLOOKUP(A235,$A$7:H235,6,0)) | G235: =+IF(F235>0,F235,E235) | H235: =+IFERROR(IF(A235="","",VLOOKUP(G235,cbr,2,0)),"Codice non inserito")
E236: =+IF(A236="","",VLOOKUP(A236,$A$7:H236,6,0)) | G236: =+IF(F236>0,F236,E236) | H236: =+IFERROR(IF(A236="","",VLOOKUP(G236,cbr,2,0)),"Codice non inserito")
... E792: =+IF(A792="","",VLOOKUP(A792,$A$7:H792,6,0)) | G792: =+IF(F792>0,F792,E792) | H792: =+IFERROR(IF(A792="","",VLOOKUP(G792,cbr,2,0)),"Codice non inserito")

Sheet BR
B1: =+Menu!B2 -> 0
B4: =+s -> ALFA SPA | D4: =+EOMONTH(F4,-12) -> 44926 | E4: % | F4: =+EOMONTH(H4,-12) -> 45291 | G4: % | H4: =+EOMONTH(DATE(Menu!E10,Menu!K10,1),0) -> 45657 | I4: % | J4: =+Menu!G12 -> 45900 | K4: =+IF(J4=0,"","%") -> %
A5: d | B5: ATTIVO | C5: Voce Bilancio CEE | L5: a
A6: 10 | B6: IMMOBILIZZ. IMMATERIALI | C6: B.I | D6: =+SUMIF('1'!$J:$J,BR!$A6,'1'!B:B)*(TB=1)+SUMIF('2'!$J:$J,BR!$A6,'2'!B:B)*(TB=2)+SUMIFS('3'!$C:$C,'3'!$D:$D,BR!D$4,'3'!$G:$G,BR!$A6)*(TB=3) -> 0 | E6: =+IF(D$21=0,"",D6/D$21) | F6: =+SUMIF('1'!$J:$J,BR!$A6,'1'!D:D)*(TB=1)+SUMIF('2'!$J:$J,BR!$A6,'2'!D:D)*(TB=2)+SUMIFS('3'!$C:$C,'3'!$D:$D,BR!F$4,'3'!$G:$G,BR!$A6)*(TB=3) -> 0 | G6: =+IF(F$21=0,"",F6/F$21) | H6: =+SUMIF('1'!$J:$J,BR!$A6,'1'!F:F)*(TB=1)+SUMIF('2'!$J:$J,BR!$A6,'2'!F:F)*(TB=2)+SUMIFS('3'!$C:$C,'3'!$D:$D,BR!H$4,'3'!$G:$G,BR!$A6)*(TB=3) -> 2086.45 | I6: =+IF(H$21=0,"",H6/H$21) -> 0.0076743457 | J6: =+SUMIF('1'!$J:$J,BR!$A6,'1'!H:H)*(TB=1)+SUMIF('2'!$J:$J,BR!$A6,'2'!H:H)*(TB=2)+SUMIFS('3'!$C:$C,'3'!$D:$D,BR!J$4,'3'!$G:$G,BR!$A6)*(TB=3) -> 2086.45 | K6: =+IF(J$21 =0,"",J6/J$21) -> 0.0063223052 | L6: =+A6 -> 10
A7: 12 | B7: FDO IMM. IMMAT. | D7: =-SUMIF('1'!$J:$J,BR!$A7,'1'!B:B)*(TB=1)-SUMIF('2'!$J:$J,BR!$A7,'2'!B:B)*(TB=2)+SUMIFS('3'!$C:$C,'3'!$D:$D,BR!D$4,'3'!$G:$G,BR!$A7)*(TB=3) -> 0 | E7: =+IF(D$21=0,"",D7/D$21) | F7: =-SUMIF('1'!$J:$J,BR!$A7,'1'!D:D)*(TB=1)-SUMIF('2'!$J:$J,BR!$A7,'2'!D:D)*(TB=2)+SUMIFS('3'!$C:$C,'3'!$D:$D,BR!F$4,'3'!$G:$G,BR!$A7)*(TB=3) -> 0 | G7: =+IF(F$21=0,"",F7/F$21) | H7: =-SUMIF('1'!$J:$J,BR!$A7,'1'!F:F)*(TB=1)-SUMIF('2'!$J:$J,BR!$A7,'2'!F:F)*(TB=2)+SUMIFS('3'!$C:$C,'3'!$D:$D,BR!H$4,'3'!$G:$G,BR!$A7)*(TB=3) -> -251.21 | I7: =+IF(H$21=0,"",H7/H$21) -> -0.00092399645 | J7: =-SUMIF('1'!$J:$J,BR!$A7,'1'!H:H)*(TB=1)-SUMIF('2'!$J:$J,BR!$A7,'2'!H:H)*(TB=2)+SUMIFS('3'!$C:$C,'3'!$D:$D,BR!J$4,'3'!$G:$G,BR!$A7)*(TB=3) -> -528.92 | K7: =+IF(J$21 =0,"",J7/J$21) -> -0.0016027193 | L7: =+A7 -> 12
A8: 20 | B8: IMMOBILIZZ. MATERIALI | C8: B.II | D8: =+SUMIF('1'!$J:$J,BR!$A8,'1'!B:B)*(TB=1)+SUMIF('2'!$J:$J,BR!$A8,'2'!B:B)*(TB=2)+SUMIFS('3'!$C:$C,'3'!$D:$D,BR!D$4,'3'!$G:$G,BR!$A8)*(TB=3) -> 0 | E8: =+IF(D$21=0,"",D8/D$21) | F8: =+SUMIF('1'!$J:$J,BR!$A8,'1'!D:D)*(TB=1)+SUMIF('2'!$J:$J,BR!$A8,'2'!D:D)*(TB=2)+SUMIFS('3'!$C:$C,'3'!$D:$D,BR!F$4,'3'!$G:$G,BR!$A8)*(TB=3) -> 0 | G8: =+IF(F$21=0,"",F8/F$21) | H8: =+SUMIF('1'!$J:$J,BR!$A8,'1'!F:F)*(TB=1)+SUMIF('2'!$J:$J,BR!$A8,'2'!F:F)*(TB=2)+SUMIFS('3'!$C:$C,'3'!$D:$D,BR!H$4,'3'!$G:$G,BR!$A8)*(TB=3) -> 94600.8 | I8: =+IF(H$21=0,"",H8/H$21) -> 0.34795909 | J8: =+SUMIF('1'!$J:$J,BR!$A8,'1'!H:H)*(TB=1)+SUMIF('2'!$J:$J,BR!$A8,'2'!H:H)*(TB=2)+SUMIFS('3'!$C:$C,'3'!$D:$D,BR!J$4,'3'!$G:$G,BR!$A8)*(TB=3) -> 95070.31 | K8: =+IF(J$21 =0,"",J8/J$21) -> 0.28807952 | L8: =+A8 -> 20
A9: 22 | B9: FDO IMM. MAT. | D9: =-SUMIF('1'!$J:$J,BR!$A9,'1'!B:B)*(TB=1)-SUMIF('2'!$J:$J,BR!$A9,'2'!B:B)*(TB=2)+SUMIFS('3'!$C:$C,'3'!$D:$D,BR!D$4,'3'!$G:$G,BR!$A9)*(TB=3) -> 0 | E9: =+IF(D$21=0,"",D9/D$21) | F9: =-SUMIF('1'!$J:$J,BR!$A9,'1'!D:D)*(TB=1)-SUMIF('2'!$J:$J,BR!$A9,'2'!D:D)*(TB=2)+SUMIFS('3'!$C:$C,'3'!$D:$D,BR!F$4,'3'!$G:$G,BR!$A9)*(TB=3) -> 0 | G9: =+IF(F$21=0,"",F9/F$21) | H9: =-SUMIF('1'!$J:$J,BR!$A9,'1'!F:F)*(TB=1)-SUMIF('2'!$J:$J,BR!$A9,'2'!F:F)*(TB=2)+SUMIFS('3'!$C:$C,'3'!$D:$D,BR!H$4,'3'!$G:$G,BR!$A9)*(TB=3) -> -7682.46 | I9: =+IF(H$21=0,"",H9/H$21) -> -0.028257497 | J9: =-SUMIF('1'!$J:$J,BR!$A9,'1'!H:H)*(TB=1)-SUMIF('2'!$J:$J,BR!$A9,'2'!H:H)*(TB=2)+SUMIFS('3'!$C:$C,'3'!$D:$D,BR!J$4,'3'!$G:$G,BR!$A9)*(TB=3) -> -16172.96 | K9: =+IF(J$21 =0,"",J9/J$21) -> -0.049006873 | L9: =+A9 -> 22
A10: 30 | B10: IMMOBILIZZ. FINANZIARIE | C10: B.III + C.II oltre es. | D10: =+SUMIF('1'!$J:$J,BR!$A10,'1'!B:B)*(TB=1)+SUMIF('2'!$J:$J,BR!$A10,'2'!B:B)*(TB=2)+SUMIFS('3'!$C:$C,'3'!$D:$D,BR!D$4,'3'!$G:$G,BR!$A10)*(TB=3) -> 0 | E10: =+IF(D$21=0,"",D10/D$21) | F10: =+SUMIF('1'!$J:$J,BR!$A10,'1'!D:D)*(TB=1)+SUMIF('2'!$J:$J,BR!$A10,'2'!D:D)*(TB=2)+SUMIFS('3'!$C:$C,'3'!$D:$D,BR!F$4,'3'!$G:$G,BR!$A10)*(TB=3) -> 0 | G10: =+IF(F$21=0,"",F10/F$21) | H10: =+SUMIF('1'!$J:$J,BR!$A10,'1'!F:F)*(TB=1)+SUMIF('2'!$J:$J,BR!$A10,'2'!F:F)*(TB=2)+SUMIFS('3'!$C:$C,'3'!$D:$D,BR!H$4,'3'!$G:$G,BR!$A10)*(TB=3) -> 0 | I10: =+IF(H$21=0,"",H10/H$21) -> 0 | J10: =+SUMIF('1'!$J:$J,BR!$A10,'1'!H:H)*(TB=1)+SUMIF('2'!$J:$J,BR!$A10,'2'!H:H)*(TB=2)+SUMIFS('3'!$C:$C,'3'!$D:$D,BR!J$4,'3'!$G:$G,BR!$A10)*(TB=3) -> 0 | K10: =+IF(J$21 =0,"",J10/J$21) -> 0 | L10: 30
A11: 35 | B11: IMMOBILIZZAZIONI | D11: =SUM(D6:D10) -> 0 | E11: =+IF(D$21=0,"",D11/D$21) | F11: =SUM(F6:F10) -> 0 | G11: =+IF(F$21=0,"",F11/F$21) | H11: =SUM(H6:H10) -> 88753.58 | I11: =+IF(H$21=0,"",H11/H$21) -> 0.32645194 | J11: =SUM(J6:J10) -> 80454.88 | K11: =+IF(J$21 =0,"",J11/J$21) -> 0.24379224
A12: 40 | B12: RIMANENZE | C12: C.I | D12: =+SUMIF('1'!$J:$J,BR!$A12,'1'!B:B)*(TB=1)+SUMIF('2'!$J:$J,BR!$A12,'2'!B:B)*(TB=2)+SUMIFS('3'!$C:$C,'3'!$D:$D,BR!D$4,'3'!$G:$G,BR!$A12)*(TB=3) -> 0 | E12: =+IF(D$21=0,"",D12/D$21) | F12: =+SUMIF('1'!$J:$J,BR!$A12,'1'!D:D)*(TB=1)+SUMIF('2'!$J:$J,BR!$A12,'2'!D:D)*(TB=2)+SUMIFS('3'!$C:$C,'3'!$D:$D,BR!F$4,'3'!$G:$G,BR!$A12)*(TB=3) -> 0 | G12: =+IF(F$21=0,"",F12/F$21) | H12: =+SUMIF('1'!$J:$J,BR!$A12,'1'!F:F)*(TB=1)+SUMIF('2'!$J:$J,BR!$A12,'2'!F:F)*(TB=2)+SUMIFS('3'!$C:$C,'3'!$D:$D,BR!H$4,'3'!$G:$G,BR!$A12)*(TB=3) -> 1920.13 | I12: =+IF(H$21=0,"",H12/H$21) -> 0.0070625902 | J12: =+SUMIF('1'!$J:$J,BR!$A12,'1'!H:H)*(TB=1)+SUMIF('2'!$J:$J,BR!$A12,'2'!H:H)*(TB=2)+SUMIFS('3'!$C:$C,'3'!$D:$D,BR!J$4,'3'!$G:$G,BR!$A12)*(TB=3) -> 1920.13 | K12: =+IF(J$21 =0,"",J12/J$21) -> 0.0058183268 | L12: =+A12 -> 40
A13: 50 | B13: CREDITI COMMERCIALI | C13: C.II.1 oppure dettaglio C.II N.I) | D13: =+SUMIF('1'!$J:$J,BR!$A13,'1'!B:B)*(TB=1)+SUMIF('2'!$J:$J,BR!$A13,'2'!B:B)*(TB=2)+SUMIFS('3'!$C:$C,'3'!$D:$D,BR!D$4,'3'!$G:$G,BR!$A13)*(TB=3) -> 0 | E13: =+IF(D$21=0,"",D13/D$21) | F13: =+SUMIF('1'!$J:$J,BR!$A13,'1'!D:D)*(TB=1)+SUMIF('2'!$J:$J,BR!$A13,'2'!D:D)*(TB=2)+SUMIFS('3'!$C:$C,'3'!$D:$D,BR!F$4,'3'!$G:$G,BR!$A13)*(TB=3) -> 0 | G13: =+IF(F$21=0,"",F13/F$21) | H13: =+SUMIF('1'!$J:$J,BR!$A13,'1'!F:F)*(TB=1)+SUMIF('2'!$J:$J,BR!$A13,'2'!F:F)*(TB=2)+SUMIFS('3'!$C:$C,'3'!$D:$D,BR!H$4,'3'!$G:$G,BR!$A13)*(TB=3) -> 0 | I13: =+IF(H$21=0,"",H13/H$21) -> 0 | J13: =+SUMIF('1'!$J:$J,BR!$A13,'1'!H:H)*(TB=1)+SUMIF('2'!$J:$J,BR!$A13,'2'!H:H)*(TB=2)+SUMIFS('3'!$C:$C,'3'!$D:$D,BR!J$4,'3'!$G:$G,BR!$A13)*(TB=3) -> 137151.13 | K13: =+IF(J$21 =0,"",J13/J$21) -> 0.4155917 | L13: 200
A14: 52 | B14: RATEI E RISCONTI ATTIVI | D14: =+SUMIF('1'!$J:$J,BR!$A14,'1'!B:B)*(TB=1)+SUMIF('2'!$J:$J,BR!$A14,'2'!B:B)*(TB=2)+SUMIFS('3'!$C:$C,'3'!$D:$D,BR!D$4,'3'!$G:$G,BR!$A14)*(TB=3) -> 0 | E14: =+IF(D$21=0,"",D14/D$21) | F14: =+SUMIF('1'!$J:$J,BR!$A14,'1'!D:D)*(TB=1)+SUMIF('2'!$J:$J,BR!$A14,'2'!D:D)*(TB=2)+SUMIFS('3'!$C:$C,'3'!$D:$D,BR!F$4,'3'!$G:$G,BR!$A14)*(TB=3) -> 0 | G14: =+IF(F$21=0,"",F14/F$21) | H14: =+SUMIF('1'!$J:$J,BR!$A14,'1'!F:F)*(TB=1)+SUMIF('2'!$J:$J,BR!$A14,'2'!F:F)*(TB=2)+SUMIFS('3'!$C:$C,'3'!$D:$D,BR!H$4,'3'!$G:$G,BR!$A14)*(TB=3) -> 0 | I14: =+IF(H$21=0,"",H14/H$21) -> 0 | J14: =+SUMIF('1'!$J:$J,BR!$A14,'1'!H:H)*(TB=1)+SUMIF('2'!$J:$J,BR!$A14,'2'!H:H)*(TB=2)+SUMIFS('3'!$C:$C,'3'!$D:$D,BR!J$4,'3'!$G:$G,BR!$A14)*(TB=3) -> 0 | K14: =+IF(J$21 =0,"",J14/J$21) -> 0 | L14: 52
A15: 54 | B15: ALTRI CREDITI | D15: =+SUMIF('1'!$J:$J,BR!$A15,'1'!B:B)*(TB=1)+SUMIF('2'!$J:$J,BR!$A15,'2'!B:B)*(TB=2)+SUMIFS('3'!$C:$C,'3'!$D:$D,BR!D$4,'3'!$G:$G,BR!$A15)*(TB=3) -> 0 | E15: =+IF(D$21=0,"",D15/D$21) | F15: =+SUMIF('1'!$J:$J,BR!$A15,'1'!D:D)*(TB=1)+SUMIF('2'!$J:$J,BR!$A15,'2'!D:D)*(TB=2)+SUMIFS('3'!$C:$C,'3'!$D:$D,BR!F$4,'3'!$G:$G,BR!$A15)*(TB=3) -> 0 | G15: =+IF(F$21=0,"",F15/F$21) | H15: =+SUMIF('1'!$J:$J,BR!$A15,'1'!F:F)*(TB=1)+SUMIF('2'!$J:$J,BR!$A15,'2'!F:F)*(TB=2)+SUMIFS('3'!$C:$C,'3'!$D:$D,BR!H$4,'3'!$G:$G,BR!$A15)*(TB=3) -> 63787.09 | I15: =+IF(H$21=0,"",H15/H$21) -> 0.23462061 | J15: =+SUMIF('1'!$J:$J,BR!$A15,'1'!H:H)*(TB=1)+SUMIF('2'!$J:$J,BR!$A15,'2'!H:H)*(TB=2)+SUMIFS('3'!$C:$C,'3'!$D:$D,BR!J$4,'3'!$G:$G,BR!$A15)*(TB=3) -> 43985.39 | K15: =+IF(J$21 =0,"",J15/J$21) -> 0.13328336 | L15: 54
A16: 60 | B16: ALTRI CREDITI E RATEI E RISC. | C16: C.II-C.II.1+D | D16: =SUM(D14:D15) -> 0 | E16: =+IF(D$21=0,"",D16/D$21) | F16: =SUM(F14:F15) -> 0 | G16: =+IF(F$21=0,"",F16/F$21) | H16: =SUM(H14:H15) -> 63787.09 | I16: =+IF(H$21=0,"",H16/H$21) -> 0.23462061 | J16: =SUM(J14:J15) -> 43985.39 | K16: =+IF(J$21 =0,"",J16/J$21) -> 0.13328336 | L16: 240
A17: 65 | B17: CREDITI | C17: C.II entro es. | D17: =SUM(D13:D15) -> 0 | E17: =+IF(D$21=0,"",D17/D$21) | F17: =SUM(F13:F15) -> 0 | G17: =+IF(F$21=0,"",F17/F$21) | H17: =SUM(H13:H15) -> 63787.09 | I17: =+IF(H$21=0,"",H17/H$21) -> 0.23462061 | J17: =SUM(J13:J15) -> 181136.52 | K17: =+IF(J$21 =0,"",J17/J$21) -> 0.54887506
A18: 70 | B18: ALTRE ATTIVITÀ FIN. NON IMMOBILIZZ | C18: C.III | D18: =+SUMIF('1'!$J:$J,BR!$A18,'1'!B:B)*(TB=1)+SUMIF('2'!$J:$J,BR!$A18,'2'!B:B)*(TB=2)+SUMIFS('3'!$C:$C,'3'!$D:$D,BR!D$4,'3'!$G:$G,BR!$A18)*(TB=3) -> 0 | E18: =+IF(D$21=0,"",D18/D$21) | F18: =+SUMIF('1'!$J:$J,BR!$A18,'1'!D:D)*(TB=1)+SUMIF('2'!$J:$J,BR!$A18,'2'!D:D)*(TB=2)+SUMIFS('3'!$C:$C,'3'!$D:$D,BR!F$4,'3'!$G:$G,BR!$A18)*(TB=3) -> 0 | G18: =+IF(F$21=0,"",F18/F$21) | H18: =+SUMIF('1'!$J:$J,BR!$A18,'1'!F:F)*(TB=1)+SUMIF('2'!$J:$J,BR!$A18,'2'!F:F)*(TB=2)+SUMIFS('3'!$C:$C,'3'!$D:$D,BR!H$4,'3'!$G:$G,BR!$A18)*(TB=3) -> 0 | I18: =+IF(H$21=0,"",H18/H$21) -> 0 | J18: =+SUMIF('1'!$J:$J,BR!$A18,'1'!H:H)*(TB=1)+SUMIF('2'!$J:$J,BR!$A18,'2'!H:H)*(TB=2)+SUMIFS('3'!$C:$C,'3'!$D:$D,BR!J$4,'3'!$G:$G,BR!$A18)*(TB=3) -> 0 | K18: =+IF(J$21 =0,"",J18/J$21) -> 0 | L18: 70
A19: 80 | B19: CASSA E BANCHE | C19: C.IV | D19: =+SUMIF('1'!$J:$J,BR!$A19,'1'!B:B)*(TB=1)+SUMIF('2'!$J:$J,BR!$A19,'2'!B:B)*(TB=2)+SUMIFS('3'!$C:$C,'3'!$D:$D,BR!D$4,'3'!$G:$G,BR!$A19)*(TB=3) -> 0 | E19: =+IF(D$21=0,"",D19/D$21) | F19: =+SUMIF('1'!$J:$J,BR!$A19,'1'!D:D)*(TB=1)+SUMIF('2'!$J:$J,BR!$A19,'2'!D:D)*(TB=2)+SUMIFS('3'!$C:$C,'3'!$D:$D,BR!F$4,'3'!$G:$G,BR!$A19)*(TB=3) -> 0 | G19: =+IF(F$21=0,"",F19/F$21) | H19: =+SUMIF('1'!$J:$J,BR!$A19,'1'!F:F)*(TB=1)+SUMIF('2'!$J:$J,BR!$A19,'2'!F:F)*(TB=2)+SUMIFS('3'!$C:$C,'3'!$D:$D,BR!H$4,'3'!$G:$G,BR!$A19)*(TB=3) -> 117412.54 | I19: =+IF(H$21=0,"",H19/H$21) -> 0.43186485 | J19: =+SUMIF('1'!$J:$J,BR!$A19,'1'!H:H)*(TB=1)+SUMIF('2'!$J:$J,BR!$A19,'2'!H:H)*(TB=2)+SUMIFS('3'!$C:$C,'3'!$D:$D,BR!J$4,'3'!$G:$G,BR!$A19)*(TB=3) -> 66502.59 | K19: =+IF(J$21 =0,"",J19/J$21) -> 0.20151438 | L19: 220
A20: 85 | B20: ATTIVO CIRCOLANTE | C20: (C entro es.+D) | D20: =+D17+D12+D18+D19 -> 0 | E20: =+IF(D$21=0,"",D20/D$21) | F20: =+F17+F12+F18+F19 -> 0 | G20: =+IF(F$21=0,"",F20/F$21) | H20: =+H17+H12+H18+H19 -> 183119.76 | I20: =+IF(H$21=0,"",H20/H$21) -> 0.67354806 | J20: =+J17+J12+J18+J19 -> 249559.24 | K20: =+IF(J$21 =0,"",J20/J$21) -> 0.75620776
A21: 89 | B21: TOTALE ATTIVO | D21: =+D11+D20 -> 0 | E21: =+IF(D$21=0,"",D21/D$21) | F21: =+F11+F20 -> 0 | G21: =+IF(F$21=0,"",F21/F$21) | H21: =+H11+H20 -> 271873.34 | I21: =+IF(H$21=0,"",H21/H$21) -> 1 | J21: =+J11+J20 -> 330014.12 | K21: =+IF(J$21 =0,"",J21/J$21) -> 1
B23: VOCI PASSIVO | C23: Voce Bilancio CEE
A24: 90 | B24: CAPITALE | C24: A.I | D24: =-(-SUMIF('1'!$J:$J,BR!$A24,'1'!B:B)*(TB=1)-SUMIF('2'!$J:$J,BR!$A24,'2'!B:B)*(TB=2)+SUMIFS('3'!$C:$C,'3'!$D:$D,BR!D$4,'3'!$G:$G,BR!$A24)*(TB=3)) -> 0 | E24: =+IF(D$21=0,"",D24/D$21) | F24: =-(-SUMIF('1'!$J:$J,BR!$A24,'1'!D:D)*(TB=1)-SUMIF('2'!$J:$J,BR!$A24,'2'!D:D)*(TB=2)+SUMIFS('3'!$C:$C,'3'!$D:$D,BR!F$4,'3'!$G:$G,BR!$A24)*(TB=3)) -> 0 | G24: =+IF(F$21=0,"",F24/F$21) | H24: =-(-SUMIF('1'!$J:$J,BR!$A24,'1'!F:F)*(TB=1)-SUMIF('2'!$J:$J,BR!$A24,'2'!F:F)*(TB=2)+SUMIFS('3'!$C:$C,'3'!$D:$D,BR!H$4,'3'!$G:$G,BR!$A24)*(TB=3)) -> 10000 | I24: =+IF(H$21=0,"",H24/H$21) -> 0.036781834 | J24: =-(-SUMIF('1'!$J:$J,BR!$A24,'1'!H:H)*(TB=1)-SUMIF('2'!$J:$J,BR!$A24,'2'!H:H)*(TB=2)+SUMIFS('3'!$C:$C,'3'!$D:$D,BR!J$4,'3'!$G:$G,BR!$A24)*(TB=3)) -> 10000 | K24: =+IF(J$21 =0,"",J24/J$21) -> 0.030301734 | L24: =+A24 -> 90
A25: 100 | B25: (CAPITALE NON VERSATO) | C25: A (Attivo) | D25: =(-SUMIF('1'!$J:$J,BR!$A25,'1'!B:B)*(TB=1)-SUMIF('2'!$J:$J,BR!$A25,'2'!B:B)*(TB=2)+SUMIFS('3'!$C:$C,'3'!$D:$D,BR!D$4,'3'!$G:$G,BR!$A25)*(TB=3)) -> 0 | E25: =+IF(D$21=0,"",D25/D$21) | F25: =(-SUMIF('1'!$J:$J,BR!$A25,'1'!D:D)*(TB=1)-SUMIF('2'!$J:$J,BR!$A25,'2'!D:D)*(TB=2)+SUMIFS('3'!$C:$C,'3'!$D:$D,BR!F$4,'3'!$G:$G,BR!$A25)*(TB=3)) -> 0 | G25: =+IF(F$21=0,"",F25/F$21) | H25: =(-SUMIF('1'!$J:$J,BR!$A25,'1'!F:F)*(TB=1)-SUMIF('2'!$J:$J,BR!$A25,'2'!F:F)*(TB=2)+SUMIFS('3'!$C:$C,'3'!$D:$D,BR!H$4,'3'!$G:$G,BR!$A25)*(TB=3)) -> 0 | I25: =+IF(H$21=0,"",H25/H$21) -> 0 | J25: =(-SUMIF('1'!$J:$J,BR!$A25,'1'!H:H)*(TB=1)-SUMIF('2'!$J:$J,BR!$A25,'2'!H:H)*(TB=2)+SUMIFS('3'!$C:$C,'3'!$D:$D,BR!J$4,'3'!$G:$G,BR!$A25)*(TB=3)) -> 0 | K25: =+IF(J$21 =0,"",J25/J$21) -> 0 | L25: =+A25 -> 100
A26: 110 | B26: RISERVA LEGALE | C26: A.IV | D26: =-(-SUMIF('1'!$J:$J,BR!$A26,'1'!B:B)*(TB=1)-SUMIF('2'!$J:$J,BR!$A26,'2'!B:B)*(TB=2)+SUMIFS('3'!$C:$C,'3'!$D:$D,BR!D$4,'3'!$G:$G,BR!$A26)*(TB=3)) -> 0 | E26: =+IF(D$21=0,"",D26/D$21) | F26: =-(-SUMIF('1'!$J:$J,BR!$A26,'1'!D:D)*(TB=1)-SUMIF('2'!$J:$J,BR!$A26,'2'!D:D)*(TB=2)+SUMIFS('3'!$C:$C,'3'!$D:$D,BR!F$4,'3'!$G:$G,BR!$A26)*(TB=3)) -> 0 | G26: =+IF(F$21=0,"",F26/F$21) | H26: =-(-SUMIF('1'!$J:$J,BR!$A26,'1'!F:F)*(TB=1)-SUMIF('2'!$J:$J,BR!$A26,'2'!F:F)*(TB=2)+SUMIFS('3'!$C:$C,'3'!$D:$D,BR!H$4,'3'!$G:$G,BR!$A26)*(TB=3)) -> 0 | I26: =+IF(H$21=0,"",H26/H$21) -> 0 | J26: =-(-SUMIF('1'!$J:$J,BR!$A26,'1'!H:H)*(TB=1)-SUMIF('2'!$J:$J,BR!$A26,'2'!H:H)*(TB=2)+SUMIFS('3'!$C:$C,'3'!$D:$D,BR!J$4,'3'!$G:$G,BR!$A26)*(TB=3)) -> 2000 | K26: =+IF(J$21 =0,"",J26/J$21) -> 0.0060603468 | L26: =+A26 -> 110
A27: 120 | B27: ALTRE RISERVE | C27: A.V + A.VI + A.VII | D27: =-(-SUMIF('1'!$J:$J,BR!$A27,'1'!B:B)*(TB=1)-SUMIF('2'!$J:$J,BR!$A27,'2'!B:B)*(TB=2)+SUMIFS('3'!$C:$C,'3'!$D:$D,BR!D$4,'3'!$G:$G,BR!$A27)*(TB=3)) -> 0 | E27: =+IF(D$21=0,"",D27/D$21) | F27: =-(-SUMIF('1'!$J:$J,BR!$A27,'1'!D:D)*(TB=1)-SUMIF('2'!$J:$J,BR!$A27,'2'!D:D)*(TB=2)+SUMIFS('3'!$C:$C,'3'!$D:$D,BR!F$4,'3'!$G:$G,BR!$A27)*(TB=3)) -> 0 | G27: =+IF(F$21=0,"",F27/F$21) | H27: =-(-SUMIF('1'!$J:$J,BR!$A27,'1'!F:F)*(TB=1)-SUMIF('2'!$J:$J,BR!$A27,'2'!F:F)*(TB=2)+SUMIFS('3'!$C:$C,'3'!$D:$D,BR!H$4,'3'!$G:$G,BR!$A27)*(TB=3)) -> 0 | I27: =+IF(H$21=0,"",H27/H$21) -> 0 | J27: =-(-SUMIF('1'!$J:$J,BR!$A27,'1'!H:H)*(TB=1)-SUMIF('2'!$J:$J,BR!$A27,'2'!H:H)*(TB=2)+SUMIFS('3'!$C:$C,'3'!$D:$D,BR!J$4,'3'!$G:$G,BR!$A27)*(TB=3)) -> 0 | K27: =+IF(J$21 =0,"",J27/J$21) -> 0 | L27: =+A27 -> 120
A28: 130 | B28: RISERVE RIVAL. | C28: A.IV | D28: =-(-SUMIF('1'!$J:$J,BR!$A28,'1'!B:B)*(TB=1)-SUMIF('2'!$J:$J,BR!$A28,'2'!B:B)*(TB=2)+SUMIFS('3'!$C:$C,'3'!$D:$D,BR!D$4,'3'!$G:$G,BR!$A28)*(TB=3)) -> 0 | E28: =+IF(D$21=0,"",D28/D$21) | F28: =-(-SUMIF('1'!$J:$J,BR!$A28,'1'!D:D)*(TB=1)-SUMIF('2'!$J:$J,BR!$A28,'2'!D:D)*(TB=2)+SUMIFS('3'!$C:$C,'3'!$D:$D,BR!F$4,'3'!$G:$G,BR!$A28)*(TB=3)) -> 0 | G28: =+IF(F$21=0,"",F28/F$21) | H28: =-(-SUMIF('1'!$J:$J,BR!$A28,'1'!F:F)*(TB=1)-SUMIF('2'!$J:$J,BR!$A28,'2'!F:F)*(TB=2)+SUMIFS('3'!$C:$C,'3'!$D:$D,BR!H$4,'3'!$G:$G,BR!$A28)*(TB=3)) -> 0 | I28: =+IF(H$21=0,"",H28/H$21) -> 0 | J28: =-(-SUMIF('1'!$J:$J,BR!$A28,'1'!H:H)*(TB=1)-SUMIF('2'!$J:$J,BR!$A28,'2'!H:H)*(TB=2)+SUMIFS('3'!$C:$C,'3'!$D:$D,BR!J$4,'3'!$G:$G,BR!$A28)*(TB=3)) -> 0 | K28: =+IF(J$21 =0,"",J28/J$21) -> 0 | L28: =+A28 -> 130
A29: 140 | B29: UTILI ES. PRECEDENTI | C29: A.VIII | D29: =-(-SUMIF('1'!$J:$J,BR!$A29,'1'!B:B)*(TB=1)-SUMIF('2'!$J:$J,BR!$A29,'2'!B:B)*(TB=2)+SUMIFS('3'!$C:$C,'3'!$D:$D,BR!D$4,'3'!$G:$G,BR!$A29)*(TB=3)) -> 0 | E29: =+IF(D$21=0,"",D29/D$21) | F29: =-(-SUMIF('1'!$J:$J,BR!$A29,'1'!D:D)*(TB=1)-SUMIF('2'!$J:$J,BR!$A29,'2'!D:D)*(TB=2)+SUMIFS('3'!$C:$C,'3'!$D:$D,BR!F$4,'3'!$G:$G,BR!$A29)*(TB=3)) -> 0 | G29: =+IF(F$21=0,"",F29/F$21) | H29: =-(-SUMIF('1'!$J:$J,BR!$A29,'1'!F:F)*(TB=1)-SUMIF('2'!$J:$J,BR!$A29,'2'!F:F)*(TB=2)+SUMIFS('3'!$C:$C,'3'!$D:$D,BR!H$4,'3'!$G:$G,BR!$A29)*(TB=3)) -> 0 | I29: =+IF(H$21=0,"",H29/H$21) -> 0 | J29: =-(-SUMIF('1'!$J:$J,BR!$A29,'1'!H:H)*(TB=1)-SUMIF('2'!$J:$J,BR!$A29,'2'!H:H)*(TB=2)+SUMIFS('3'!$C:$C,'3'!$D:$D,BR!J$4,'3'!$G:$G,BR!$A29)*(TB=3)) -> 122642.08 | K29: =+IF(J$21 =0,"",J29/J$21) -> 0.37162677 | L29: 140
B30: UTILE (PERDITA) | C30: A.IX | D30: =D78 -> 0 | E30: =+IF(D$21=0,"",D30/D$21) | F30: =F78 -> 0 | G30: =+IF(F$21=0,"",F30/F$21) | H30: =H78 -> 124642.08 | I30: =+IF(H$21=0,"",H30/H$21) -> 0.45845643 | J30: =J78 -> 22181.68 | K30: =+IF(J$21 =0,"",J30/J$21) -> 0.067214336
A31: 145 | B31: PATRIMONIO NETTO | C31: A | D31: =SUM(D24:D30) -> 0 | E31: =+IF(D$21=0,"",D31/D$21) | F31: =SUM(F24:F30) -> 0 | G31: =+IF(F$21=0,"",F31/F$21) | H31: =SUM(H24:H30) -> 134642.08 | I31: =+IF(H$21=0,"",H31/H$21) -> 0.49523826 | J31: =SUM(J24:J30) -> 156823.76 | K31: =+IF(J$21 =0,"",J31/J$21) -> 0.47520318
A32: 150 | B32: FINANZIAMENTO SOCI E INFRAGR. | C32: D.3 o dett N.I. | D32: =-(-SUMIF('1'!$J:$J,BR!$A32,'1'!B:B)*(TB=1)-SUMIF('2'!$J:$J,BR!$A32,'2'!B:B)*(TB=2)+SUMIFS('3'!$C:$C,'3'!$D:$D,BR!D$4,'3'!$G:$G,BR!$A32)*(TB=3)) -> 0 | E32: =+IF(D$21=0,"",D32/D$21) | F32: =-(-SUMIF('1'!$J:$J,BR!$A32,'1'!D:D)*(TB=1)-SUMIF('2'!$J:$J,BR!$A32,'2'!D:D)*(TB=2)+SUMIFS('3'!$C:$C,'3'!$D:$D,BR!F$4,'3'!$G:$G,BR!$A32)*(TB=3)) -> 0 | G32: =+IF(F$21=0,"",F32/F$21) | H32: =-(-SUMIF('1'!$J:$J,BR!$A32,'1'!F:F)*(TB=1)-SUMIF('2'!$J:$J,BR!$A32,'2'!F:F)*(TB=2)+SUMIFS('3'!$C:$C,'3'!$D:$D,BR!H$4,'3'!$G:$G,BR!$A32)*(TB=3)) -> 195.75 | I32: =+IF(H$21=0,"",H32/H$21) -> 0.0007200044 | J32: =-(-SUMIF('1'!$J:$J,BR!$A32,'1'!H:H)*(TB=1)-SUMIF('2'!$J:$J,BR!$A32,'2'!H:H)*(TB=2)+SUMIFS('3'!$C:$C,'3'!$D:$D,BR!J$4,'3'!$G:$G,BR!$A32)*(TB=3)) -> -18113.92 | K32: =+IF(J$21 =0,"",J32/J$21) -> -0.054888318 | L32: =+A32 -> 150
A33: 160 | B33: FONDI RISCHI | C33: B | D33: =-(-SUMIF('1'!$J:$J,BR!$A33,'1'!B:B)*(TB=1)-SUMIF('2'!$J:$J,BR!$A33,'2'!B:B)*(TB=2)+SUMIFS('3'!$C:$C,'3'!$D:$D,BR!D$4,'3'!$G:$G,BR!$A33)*(TB=3)) -> 0 | E33: =+IF(D$21=0,"",D33/D$21) | F33: =-(-SUMIF('1'!$J:$J,BR!$A33,'1'!D:D)*(TB=1)-SUMIF('2'!$J:$J,BR!$A33,'2'!D:D)*(TB=2)+SUMIFS('3'!$C:$C,'3'!$D:$D,BR!F$4,'3'!$G:$G,BR!$A33)*(TB=3)) -> 0 | G33: =+IF(F$21=0,"",F33/F$21) | H33: =-(-SUMIF('1'!$J:$J,BR!$A33,'1'!F:F)*(TB=1)-SUMIF('2'!$J:$J,BR!$A33,'2'!F:F)*(TB=2)+SUMIFS('3'!$C:$C,'3'!$D:$D,BR!H$4,'3'!$G:$G,BR!$A33)*(TB=3)) -> 0 | I33: =+IF(H$21=0,"",H33/H$21) -> 0 | J33: =-(-SUMIF('1'!$J:$J,BR!$A33,'1'!H:H)*(TB=1)-SUMIF('2'!$J:$J,BR!$A33,'2'!H:H)*(TB=2)+SUMIFS('3'!$C:$C,'3'!$D:$D,BR!J$4,'3'!$G:$G,BR!$A33)*(TB=3)) -> 0 | K33: =+IF(J$21 =0,"",J33/J$21) -> 0 | L33: =+A33 -> 160
A34: 170 | B34: TFR | C34: C | D34: =-(-SUMIF('1'!$J:$J,BR!$A34,'1'!B:B)*(TB=1)-SUMIF('2'!$J:$J,BR!$A34,'2'!B:B)*(TB=2)+SUMIFS('3'!$C:$C,'3'!$D:$D,BR!D$4,'3'!$G:$G,BR!$A34)*(TB=3)) -> 0 | E34: =+IF(D$21=0,"",D34/D$21) | F34: =-(-SUMIF('1'!$J:$J,BR!$A34,'1'!D:D)*(TB=1)-SUMIF('2'!$J:$J,BR!$A34,'2'!D:D)*(TB=2)+SUMIFS('3'!$C:$C,'3'!$D:$D,BR!F$4,'3'!$G:$G,BR!$A34)*(TB=3)) -> 0 | G34: =+IF(F$21=0,"",F34/F$21) | H34: =-(-SUMIF('1'!$J:$J,BR!$A34,'1'!F:F)*(TB=1)-SUMIF('2'!$J:$J,BR!$A34,'2'!F:F)*(TB=2)+SUMIFS('3'!$C:$C,'3'!$D:$D,BR!H$4,'3'!$G:$G,BR!$A34)*(TB=3)) -> 1530.97 | I34: =+IF(H$21=0,"",H34/H$21) -> 0.0056311884 | J34: =-(-SUMIF('1'!$J:$J,BR!$A34,'1'!H:H)*(TB=1)-SUMIF('2'!$J:$J,BR!$A34,'2'!H:H)*(TB=2)+SUMIFS('3'!$C:$C,'3'!$D:$D,BR!J$4,'3'!$G:$G,BR!$A34)*(TB=3)) -> 1530.97 | K34: =+IF(J$21 =0,"",J34/J$21) -> 0.0046391045 | L34: =+A34 -> 170
A35: 180 | B35: DEBITI VS BANCHE A MEDIO LUNGO T. | C35: D.4 oltre | D35: =-(-SUMIF('1'!$J:$J,BR!$A35,'1'!B:B)*(TB=1)-SUMIF('2'!$J:$J,BR!$A35,'2'!B:B)*(TB=2)+SUMIFS('3'!$C:$C,'3'!$D:$D,BR!D$4,'3'!$G:$G,BR!$A35)*(TB=3)) -> 0 | E35: =+IF(D$21=0,"",D35/D$21) | F35: =-(-SUMIF('1'!$J:$J,BR!$A35,'1'!D:D)*(TB=1)-SUMIF('2'!$J:$J,BR!$A35,'2'!D:D)*(TB=2)+SUMIFS('3'!$C:$C,'3'!$D:$D,BR!F$4,'3'!$G:$G,BR!$A35)*(TB=3)) -> 0 | G35: =+IF(F$21=0,"",F35/F$21) | H35: =-(-SUMIF('1'!$J:$J,BR!$A35,'1'!F:F)*(TB=1)-SUMIF('2'!$J:$J,BR!$A35,'2'!F:F)*(TB=2)+SUMIFS('3'!$C:$C,'3'!$D:$D,BR!H$4,'3'!$G:$G,BR!$A35)*(TB=3)) -> 33897.74 | I35: =+IF(H$21=0,"",H35/H$21) -> 0.1246821 | J35: =-(-SUMIF('1'!$J:$J,BR!$A35,'1'!H:H)*(TB=1)-SUMIF('2'!$J:$J,BR!$A35,'2'!H:H)*(TB=2)+SUMIFS('3'!$C:$C,'3'!$D:$D,BR!J$4,'3'!$G:$G,BR!$A35)*(TB=3)) -> 27040.51 | K35: =+IF(J$21 =0,"",J35/J$21) -> 0.081937433 | L35: =+A35 -> 180
A36: 190 | B36: DEBITI TRIB. E CONTRIB. RATEIZZATI OLTRE ES. | C36: D.4 oltre | D36: =-(-SUMIF('1'!$J:$J,BR!$A36,'1'!B:B)*(TB=1)-SUMIF('2'!$J:$J,BR!$A36,'2'!B:B)*(TB=2)+SUMIFS('3'!$C:$C,'3'!$D:$D,BR!D$4,'3'!$G:$G,BR!$A36)*(TB=3)) -> 0 | E36: =+IF(D$21=0,"",D36/D$21) | F36: =-(-SUMIF('1'!$J:$J,BR!$A36,'1'!D:D)*(TB=1)-SUMIF('2'!$J:$J,BR!$A36,'2'!D:D)*(TB=2)+SUMIFS('3'!$C:$C,'3'!$D:$D,BR!F$4,'3'!$G:$G,BR!$A36)*(TB=3)) -> 0 | G36: =+IF(F$21=0,"",F36/F$21) | H36: =-(-SUMIF('1'!$J:$J,BR!$A36,'1'!F:F)*(TB=1)-SUMIF('2'!$J:$J,BR!$A36,'2'!F:F)*(TB=2)+SUMIFS('3'!$C:$C,'3'!$D:$D,BR!H$4,'3'!$G:$G,BR!$A36)*(TB=3)) -> 0 | I36: =+IF(H$21=0,"",H36/H$21) -> 0 | J36: =-(-SUMIF('1'!$J:$J,BR!$A36,'1'!H:H)*(TB=1)-SUMIF('2'!$J:$J,BR!$A36,'2'!H:H)*(TB=2)+SUMIFS('3'!$C:$C,'3'!$D:$D,BR!J$4,'3'!$G:$G,BR!$A36)*(TB=3)) -> 0 | K36: =+IF(J$21 =0,"",J36/J$21) -> 0 | L36: =+A36 -> 190
A37: 192 | B37: ALTRI DEBITI A M/L | C37: D.4 oltre | D37: =-(-SUMIF('1'!$J:$J,BR!$A37,'1'!B:B)*(TB=1)-SUMIF('2'!$J:$J,BR!$A37,'2'!B:B)*(TB=2)+SUMIFS('3'!$C:$C,'3'!$D:$D,BR!D$4,'3'!$G:$G,BR!$A37)*(TB=3)) -> 0 | E37: =+IF(D$21=0,"",D37/D$21) | F37: =-(-SUMIF('1'!$J:$J,BR!$A37,'1'!D:D)*(TB=1)-SUMIF('2'!$J:$J,BR!$A37,'2'!D:D)*(TB=2)+SUMIFS('3'!$C:$C,'3'!$D:$D,BR!F$4,'3'!$G:$G,BR!$A37)*(TB=3)) -> 0 | G37: =+IF(F$21=0,"",F37/F$21) | H37: =-(-SUMIF('1'!$J:$J,BR!$A37,'1'!F:F)*(TB=1)-SUMIF('2'!$J:$J,BR!$A37,'2'!F:F)*(TB=2)+SUMIFS('3'!$C:$C,'3'!$D:$D,BR!H$4,'3'!$G:$G,BR!$A37)*(TB=3)) -> -69.5 | I37: =+IF(H$21=0,"",H37/H$21) -> -0.00025563374 | J37: =-(-SUMIF('1'!$J:$J,BR!$A37,'1'!H:H)*(TB=1)-SUMIF('2'!$J:$J,BR!$A37,'2'!H:H)*(TB=2)+SUMIFS('3'!$C:$C,'3'!$D:$D,BR!J$4,'3'!$G:$G,BR!$A37)*(TB=3)) -> 0 | K37: =+IF(J$21 =0,"",J37/J$21) -> 0 | L37: =+A37 -> 192
A38: 195 | B38: PASSIVITA' CONSOLIDATE | D38: =SUM(D32:D37) -> 0 | E38: =+IF(D$21=0,"",D38/D$21) | F38: =SUM(F32:F37) -> 0 | G38: =+IF(F$21=0,"",F38/F$21) | H38: =SUM(H32:H37) -> 35554.96 | I38: =+IF(H$21=0,"",H38/H$21) -> 0.13077766 | J38: =SUM(J32:J37) -> 10457.56 | K38: =+IF(J$21 =0,"",J38/J$21) -> 0.03168822
A39: 200 | B39: ACCONTI | C39: D.6 | D39: =-(-SUMIF('1'!$J:$J,BR!$A39,'1'!B:B)*(TB=1)-SUMIF('2'!$J:$J,BR!$A39,'2'!B:B)*(TB=2)+SUMIFS('3'!$C:$C,'3'!$D:$D,BR!D$4,'3'!$G:$G,BR!$A39)*(TB=3)) -> 0 | E39: =+IF(D$21=0,"",D39/D$21) | F39: =-(-SUMIF('1'!$J:$J,BR!$A39,'1'!D:D)*(TB=1)-SUMIF('2'!$J:$J,BR!$A39,'2'!D:D)*(TB=2)+SUMIFS('3'!$C:$C,'3'!$D:$D,BR!F$4,'3'!$G:$G,BR!$A39)*(TB=3)) -> 0 | G39: =+IF(F$21=0,"",F39/F$21) | H39: =-(-SUMIF('1'!$J:$J,BR!$A39,'1'!F:F)*(TB=1)-SUMIF('2'!$J:$J,BR!$A39,'2'!F:F)*(TB=2)+SUMIFS('3'!$C:$C,'3'!$D:$D,BR!H$4,'3'!$G:$G,BR!$A39)*(TB=3)) -> 0 | I39: =+IF(H$21=0,"",H39/H$21) -> 0 | J39: =-(-SUMIF('1'!$J:$J,BR!$A39,'1'!H:H)*(TB=1)-SUMIF('2'!$J:$J,BR!$A39,'2'!H:H)*(TB=2)+SUMIFS('3'!$C:$C,'3'!$D:$D,BR!J$4,'3'!$G:$G,BR!$A39)*(TB=3)) -> 0 | K39: =+IF(J$21 =0,"",J39/J$21) -> 0 | L39: =+A39 -> 200
A40: 210 | B40: FORNITORI | C40: D.7 | D40: =-(-SUMIF('1'!$J:$J,BR!$A40,'1'!B:B)*(TB=1)-SUMIF('2'!$J:$J,BR!$A40,'2'!B:B)*(TB=2)+SUMIFS('3'!$C:$C,'3'!$D:$D,BR!D$4,'3'!$G:$G,BR!$A40)*(TB=3)) -> 0 | E40: =+IF(D$21=0,"",D40/D$21) | F40: =-(-SUMIF('1'!$J:$J,BR!$A40,'1'!D:D)*(TB=1)-SUMIF('2'!$J:$J,BR!$A40,'2'!D:D)*(TB=2)+SUMIFS('3'!$C:$C,'3'!$D:$D,BR!F$4,'3'!$G:$G,BR!$A40)*(TB=3)) -> 0 | G40: =+IF(F$21=0,"",F40/F$21) | H40: =-(-SUMIF('1'!$J:$J,BR!$A40,'1'!F:F)*(TB=1)-SUMIF('2'!$J:$J,BR!$A40,'2'!F:F)*(TB=2)+SUMIFS('3'!$C:$C,'3'!$D:$D,BR!H$4,'3'!$G:$G,BR!$A40)*(TB=3)) -> 60246.41 | I40: =+IF(H$21=0,"",H40/H$21) -> 0.22159734 | J40: =-(-SUMIF('1'!$J:$J,BR!$A40,'1'!H:H)*(TB=1)-SUMIF('2'!$J:$J,BR!$A40,'2'!H:H)*(TB=2)+SUMIFS('3'!$C:$C,'3'!$D:$D,BR!J$4,'3'!$G:$G,BR!$A40)*(TB=3)) -> 133395.41 | K40: =+IF(J$21 =0,"",J40/J$21) -> 0.40421122 | L40: =+A40 -> 210
A41: 220 | B41: DEBITI VS. BANCHE | C41: D.4 entro | D41: =-(-SUMIF('1'!$J:$J,BR!$A41,'1'!B:B)*(TB=1)-SUMIF('2'!$J:$J,BR!$A41,'2'!B:B)*(TB=2)+SUMIFS('3'!$C:$C,'3'!$D:$D,BR!D$4,'3'!$G:$G,BR!$A41)*(TB=3)) -> 0 | E41: =+IF(D$21=0,"",D41/D$21) | F41: =-(-SUMIF('1'!$J:$J,BR!$A41,'1'!D:D)*(TB=1)-SUMIF('2'!$J:$J,BR!$A41,'2'!D:D)*(TB=2)+SUMIFS('3'!$C:$C,'3'!$D:$D,BR!F$4,'3'!$G:$G,BR!$A41)*(TB=3)) -> 0 | G41: =+IF(F$21=0,"",F41/F$21) | H41: =-(-SUMIF('1'!$J:$J,BR!$A41,'1'!F:F)*(TB=1)-SUMIF('2'!$J:$J,BR!$A41,'2'!F:F)*(TB=2)+SUMIFS('3'!$C:$C,'3'!$D:$D,BR!H$4,'3'!$G:$G,BR!$A41)*(TB=3)) -> 0 | I41: =+IF(H$21=0,"",H41/H$21) -> 0 | J41: =-(-SUMIF('1'!$J:$J,BR!$A41,'1'!H:H)*(TB=1)-SUMIF('2'!$J:$J,BR!$A41,'2'!H:H)*(TB=2)+SUMIFS('3'!$C:$C,'3'!$D:$D,BR!J$4,'3'!$G:$G,BR!$A41)*(TB=3)) -> 0 | K41: =+IF(J$21 =0,"",J41/J$21) -> 0 | L41: 80
A42: 230 | B42: DEBITI TRIBUTARI E CONTRIBUTIVI | C42: D.12+D.13 | D42: =-(-SUMIF('1'!$J:$J,BR!$A42,'1'!B:B)*(TB=1)-SUMIF('2'!$J:$J,BR!$A42,'2'!B:B)*(TB=2)+SUMIFS('3'!$C:$C,'3'!$D:$D,BR!D$4,'3'!$G:$G,BR!$A42)*(TB=3)) -> 0 | E42: =+IF(D$21=0,"",D42/D$21) | F42: =-(-SUMIF('1'!$J:$J,BR!$A42,'1'!D:D)*(TB=1)-SUMIF('2'!$J:$J,BR!$A42,'2'!D:D)*(TB=2)+SUMIFS('3'!$C:$C,'3'!$D:$D,BR!F$4,'3'!$G:$G,BR!$A42)*(TB=3)) -> 0 | G42: =+IF(F$21=0,"",F42/F$21) | H42: =-(-SUMIF('1'!$J:$J,BR!$A42,'1'!F:F)*(TB=1)-SUMIF('2'!$J:$J,BR!$A42,'2'!F:F)*(TB=2)+SUMIFS('3'!$C:$C,'3'!$D:$D,BR!H$4,'3'!$G:$G,BR!$A42)*(TB=3)) -> 29545.89 | I42: =+IF(H$21=0,"",H42/H$21) -> 0.1086752 | J42: =-(-SUMIF('1'!$J:$J,BR!$A42,'1'!H:H)*(TB=1)-SUMIF('2'!$J:$J,BR!$A42,'2'!H:H)*(TB=2)+SUMIFS('3'!$C:$C,'3'!$D:$D,BR!J$4,'3'!$G:$G,BR!$A42)*(TB=3)) -> 13246.16 | K42: =+IF(J$21 =0,"",J42/J$21) -> 0.040138161 | L42: 230
A43: 232 | B43: RATEI E RISCONTI PASSIVI | D43: =-(-SUMIF('1'!$J:$J,BR!$A43,'1'!B:B)*(TB=1)-SUMIF('2'!$J:$J,BR!$A43,'2'!B:B)*(TB=2)+SUMIFS('3'!$C:$C,'3'!$D:$D,BR!D$4,'3'!$G:$G,BR!$A43)*(TB=3)) -> 0 | E43: =+IF(D$21=0,"",D43/D$21) | F43: =-(-SUMIF('1'!$J:$J,BR!$A43,'1'!D:D)*(TB=1)-SUMIF('2'!$J:$J,BR!$A43,'2'!D:D)*(TB=2)+SUMIFS('3'!$C:$C,'3'!$D:$D,BR!F$4,'3'!$G:$G,BR!$A43)*(TB=3)) -> 0 | G43: =+IF(F$21=0,"",F43/F$21) | H43: =-(-SUMIF('1'!$J:$J,BR!$A43,'1'!F:F)*(TB=1)-SUMIF('2'!$J:$J,BR!$A43,'2'!F:F)*(TB=2)+SUMIFS('3'!$C:$C,'3'!$D:$D,BR!H$4,'3'!$G:$G,BR!$A43)*(TB=3)) -> 0 | I43: =+IF(H$21=0,"",H43/H$21) -> 0 | J43: =-(-SUMIF('1'!$J:$J,BR!$A43,'1'!H:H)*(TB=1)-SUMIF('2'!$J:$J,BR!$A43,'2'!H:H)*(TB=2)+SUMIFS('3'!$C:$C,'3'!$D:$D,BR!J$4,'3'!$G:$G,BR!$A43)*(TB=3)) -> 0 | K43: =+IF(J$21 =0,"",J43/J$21) -> 0 | L43: 232
A44: 234 | B44: ALTRI DEBITI | D44: =-(-SUMIF('1'!$J:$J,BR!$A44,'1'!B:B)*(TB=1)-SUMIF('2'!$J:$J,BR!$A44,'2'!B:B)*(TB=2)+SUMIFS('3'!$C:$C,'3'!$D:$D,BR!D$4,'3'!$G:$G,BR!$A44)*(TB=3)) -> 0 | E44: =+IF(D$21=0,"",D44/D$21) | F44: =-(-SUMIF('1'!$J:$J,BR!$A44,'1'!D:D)*(TB=1)-SUMIF('2'!$J:$J,BR!$A44,'2'!D:D)*(TB=2)+SUMIFS('3'!$C:$C,'3'!$D:$D,BR!F$4,'3'!$G:$G,BR!$A44)*(TB=3)) -> 0 | G44: =+IF(F$21=0,"",F44/F$21) | H44: =-(-SUMIF('1'!$J:$J,BR!$A44,'1'!F:F)*(TB=1)-SUMIF('2'!$J:$J,BR!$A44,'2'!F:F)*(TB=2)+SUMIFS('3'!$C:$C,'3'!$D:$D,BR!H$4,'3'!$G:$G,BR!$A44)*(TB=3)) -> 11884 | I44: =+IF(H$21=0,"",H44/H$21) -> 0.043711531 | J44: =-(-SUMIF('1'!$J:$J,BR!$A44,'1'!H:H)*(TB=1)-SUMIF('2'!$J:$J,BR!$A44,'2'!H:H)*(TB=2)+SUMIFS('3'!$C:$C,'3'!$D:$D,BR!J$4,'3'!$G:$G,BR!$A44)*(TB=3)) -> 16091.23 | K44: =+IF(J$21 =0,"",J44/J$21) -> 0.048759217 | L44: 234
B45: ALTRE PASSIVITA' E RATEI E RISC | C45: D + E -D.6-D.7-D.4-D.12-D.13 | D45: =+SUM(D43:D44) -> 0 | E45: =+IF(D$21=0,"",D45/D$21) | F45: =+SUM(F43:F44) -> 0 | G45: =+IF(F$21=0,"",F45/F$21) | H45: =+SUM(H43:H44) -> 11884 | I45: =+IF(H$21=0,"",H45/H$21) -> 0.043711531 | J45: =+SUM(J43:J44) -> 16091.23 | K45: =+IF(J$21 =0,"",J45/J$21) -> 0.048759217 | L45: 240
A46: 245 | B46: PASSIVITA' CORRENTI | C46: D entro es. | D46: =SUM(D39:D44) -> 0 | E46: =+IF(D$21=0,"",D46/D$21) | F46: =SUM(F39:F44) -> 0 | G46: =+IF(F$21=0,"",F46/F$21) | H46: =SUM(H39:H44) -> 101676.3 | I46: =+IF(H$21=0,"",H46/H$21) -> 0.37398408 | J46: =SUM(J39:J44) -> 162732.8 | K46: =+IF(J$21 =0,"",J46/J$21) -> 0.4931086
A47: 245 | B47: MEZZI DI TERZI | D47: =+D38+D46 -> 0 | E47: =+IF(D$21=0,"",D47/D$21) | F47: =+F38+F46 -> 0 | G47: =+IF(F$21=0,"",F47/F$21) | H47: =+H38+H46 -> 137231.26 | I47: =+IF(H$21=0,"",H47/H$21) -> 0.50476174 | J47: =+J38+J46 -> 173190.36 | K47: =+IF(J$21 =0,"",J47/J$21) -> 0.52479682
A48: 249 | B48: TOTALE PASSIVO | D48: =+D47+D31 -> 0 | E48: =+IF(D$21=0,"",D48/D$21) | F48: =+F47+F31 -> 0 | G48: =+IF(F$21=0,"",F48/F$21) | H48: =+H47+H31 -> 271873.34 | I48: =+IF(H$21=0,"",H48/H$21) -> 1 | J48: =+J47+J31 -> 330014.12 | K48: =+IF(J$21 =0,"",J48/J$21) -> 1
D49: =+D48-D21 -> 0 | F49: =+F48-F21 -> 0 | H49: =+H48-H21 -> 0 | J49: =+J48-J21 -> 0
B50: =+s -> ALFA SPA | D50: =+D4 -> 44926 | E50: =+E4 -> % | F50: =+F4 -> 45291 | G50: =+G4 -> % | H50: =+H4 -> 45657 | I50: =+I4 -> % | J50: =+J4 -> 45900 | K50: =+K4 -> %
B51: CONTO ECONOMICO | C51: Voce Bilancio CEE
A52: 300 | B52: RICAVI | C52: A.1 | D52: =+SUMIF(CE!$J:$J,BR!$A52,CE!B:B)*(TB<3)-SUMIFS('3'!$C:$C,'3'!$D:$D,BR!D$50,'3'!$G:$G,BR!$A52)*(TB=3) -> 0 | E52: =IF(D$52=0,0,D52/D$52) -> 0 | F52: =+SUMIF(CE!$J:$J,BR!$A52,CE!D:D)*(TB<3)-SUMIFS('3'!$C:$C,'3'!$D:$D,BR!F$50,'3'!$G:$G,BR!$A52)*(TB=3) -> 0 | G52: =IF(F$52=0,0,F52/F$52) -> 0 | H52: =+SUMIF(CE!$J:$J,BR!$A52,CE!F:F)*(TB<3)-SUMIFS('3'!$C:$C,'3'!$D:$D,BR!H$50,'3'!$G:$G,BR!$A52)*(TB=3) -> 938760.35 | I52: =IF(H$52=0,0,H52/H$52) -> 1 | J52: =+SUMIF(CE!$J:$J,BR!$A52,CE!H:H)*(TB<3)-SUMIFS('3'!$C:$C,'3'!$D:$D,BR!J$50,'3'!$G:$G,BR!$A52)*(TB=3) -> 510950.21 | K52: =+IF(J$52=0,"",J52/J$52) -> 1 | L52: =+A52 -> 300
A53: 310 | B53: VARIAZIONE RIMAN. PF-SL E LAV. IN CORSO | C53: A.2 | D53: =+SUMIF(CE!$J:$J,BR!$A53,CE!B:B)*(TB<3)-SUMIFS('3'!$C:$C,'3'!$D:$D,BR!D$50,'3'!$G:$G,BR!$A53)*(TB=3) -> 0 | E53: =IF(D$52=0,0,D53/D$52) -> 0 | F53: =+SUMIF(CE!$J:$J,BR!$A53,CE!D:D)*(TB<3)-SUMIFS('3'!$C:$C,'3'!$D:$D,BR!F$50,'3'!$G:$G,BR!$A53)*(TB=3) -> 0 | G53: =IF(F$52=0,0,F53/F$52) -> 0 | H53: =+SUMIF(CE!$J:$J,BR!$A53,CE!F:F)*(TB<3)-SUMIFS('3'!$C:$C,'3'!$D:$D,BR!H$50,'3'!$G:$G,BR!$A53)*(TB=3) -> 1920.13 | I53: =IF(H$52=0,0,H53/H$52) -> 0.0020453889 | J53: =+SUMIF(CE!$J:$J,BR!$A53,CE!H:H)*(TB<3)-SUMIFS('3'!$C:$C,'3'!$D:$D,BR!J$50,'3'!$G:$G,BR!$A53)*(TB=3) -> 0 | K53: =+IF(J$52=0,"",J53/J$52) -> 0 | L53: =+A53 -> 310
A54: 315 | B54: CONTRIBUTI IN CONTO ESERCIZIO E CAP. | D54: =+SUMIF(CE!$J:$J,BR!$A54,CE!B:B)*(TB<3)-SUMIFS('3'!$C:$C,'3'!$D:$D,BR!D$50,'3'!$G:$G,BR!$A54)*(TB=3) -> 0 | E54: =IF(D$52=0,0,D54/D$52) -> 0 | F54: =+SUMIF(CE!$J:$J,BR!$A54,CE!D:D)*(TB<3)-SUMIFS('3'!$C:$C,'3'!$D:$D,BR!F$50,'3'!$G:$G,BR!$A54)*(TB=3) -> 0 | G54: =IF(F$52=0,0,F54/F$52) -> 0 | H54: =+SUMIF(CE!$J:$J,BR!$A54,CE!F:F)*(TB<3)-SUMIFS('3'!$C:$C,'3'!$D:$D,BR!H$50,'3'!$G:$G,BR!$A54)*(TB=3) -> 0 | I54: =IF(H$52=0,0,H54/H$52) -> 0 | J54: =+SUMIF(CE!$J:$J,BR!$A54,CE!H:H)*(TB<3)-SUMIFS('3'!$C:$C,'3'!$D:$D,BR!J$50,'3'!$G:$G,BR!$A54)*(TB=3) -> 0 | K54: =+IF(J$52=0,"",J54/J$52) -> 0 | L54: 315
A55: 320 | B55: ALTRI RICAVI | C55: A.5 - A.5.2 | D55: =+SUMIF(CE!$J:$J,BR!$A55,CE!B:B)*(TB<3)-SUMIFS('3'!$C:$C,'3'!$D:$D,BR!D$50,'3'!$G:$G,BR!$A55)*(TB=3) -> 0 | E55: =IF(D$52=0,0,D55/D$52) -> 0 | F55: =+SUMIF(CE!$J:$J,BR!$A55,CE!D:D)*(TB<3)-SUMIFS('3'!$C:$C,'3'!$D:$D,BR!F$50,'3'!$G:$G,BR!$A55)*(TB=3) -> 0 | G55: =IF(F$52=0,0,F55/F$52) -> 0 | H55: =+SUMIF(CE!$J:$J,BR!$A55,CE!F:F)*(TB<3)-SUMIFS('3'!$C:$C,'3'!$D:$D,BR!H$50,'3'!$G:$G,BR!$A55)*(TB=3) -> 1305.97 | I55: =IF(H$52=0,0,H55/H$52) -> 0.0013911644 | J55: =+SUMIF(CE!$J:$J,BR!$A55,CE!H:H)*(TB<3)-SUMIFS('3'!$C:$C,'3'!$D:$D,BR!J$50,'3'!$G:$G,BR!$A55)*(TB=3) -> 12.59 | K55: =+IF(J$52=0,"",J55/J$52) -> 2.4640366e-05 | L55: =+A55 -> 320
A56: 325 | B56: VALORE DELLA PDZ | D56: =SUM(D52:D55) -> 0 | E56: =IF(D$52=0,0,D56/D$52) -> 0 | F56: =SUM(F52:F55) -> 0 | G56: =IF(F$52=0,0,F56/F$52) -> 0 | H56: =SUM(H52:H55) -> 941986.45 | I56: =IF(H$52=0,0,H56/H$52) -> 1.0034366 | J56: =SUM(J52:J55) -> 510962.8 | K56: =+IF(J$52=0,"",J56/J$52) -> 1.0000246 | L56: =+A56 -> 325
A57: 330 | B57: COSTI PER MATERIE PRIME SUSS. E DI CONS. E DI MERCI | C57: B.6 | D57: =+SUMIF(CE!$J:$J,BR!$A57,CE!B:B)*(TB<3)-SUMIFS('3'!$C:$C,'3'!$D:$D,BR!D$50,'3'!$G:$G,BR!$A57)*(TB=3) -> 0 | E57: =IF(D$52=0,0,D57/D$52) -> 0 | F57: =+SUMIF(CE!$J:$J,BR!$A57,CE!D:D)*(TB<3)-SUMIFS('3'!$C:$C,'3'!$D:$D,BR!F$50,'3'!$G:$G,BR!$A57)*(TB=3) -> 0 | G57: =IF(F$52=0,0,F57/F$52) -> 0 | H57: =+SUMIF(CE!$J:$J,BR!$A57,CE!F:F)*(TB<3)-SUMIFS('3'!$C:$C,'3'!$D:$D,BR!H$50,'3'!$G:$G,BR!$A57)*(TB=3) -> -87474.1 | I57: =IF(H$52=0,0,H57/H$52) -> -0.093180437 | J57: =+SUMIF(CE!$J:$J,BR!$A57,CE!H:H)*(TB<3)-SUMIFS('3'!$C:$C,'3'!$D:$D,BR!J$50,'3'!$G:$G,BR!$A57)*(TB=3) -> -75145.49 | K57: =+IF(J$52=0,"",J57/J$52) -> -0.14707008 | L57: =+A57 -> 330
A58: 340 | B58: VARIAZIONE RIMANENZE MP E MERCI | C58: B.11 | D58: =+SUMIF(CE!$J:$J,BR!$A58,CE!B:B)*(TB<3)-SUMIFS('3'!$C:$C,'3'!$D:$D,BR!D$50,'3'!$G:$G,BR!$A58)*(TB=3) -> 0 | E58: =IF(D$52=0,0,D58/D$52) -> 0 | F58: =+SUMIF(CE!$J:$J,BR!$A58,CE!D:D)*(TB<3)-SUMIFS('3'!$C:$C,'3'!$D:$D,BR!F$50,'3'!$G:$G,BR!$A58)*(TB=3) -> 0 | G58: =IF(F$52=0,0,F58/F$52) -> 0 | H58: =+SUMIF(CE!$J:$J,BR!$A58,CE!F:F)*(TB<3)-SUMIFS('3'!$C:$C,'3'!$D:$D,BR!H$50,'3'!$G:$G,BR!$A58)*(TB=3) -> 0 | I58: =IF(H$52=0,0,H58/H$52) -> 0 | J58: =+SUMIF(CE!$J:$J,BR!$A58,CE!H:H)*(TB<3)-SUMIFS('3'!$C:$C,'3'!$D:$D,BR!J$50,'3'!$G:$G,BR!$A58)*(TB=3) -> 0 | K58: =+IF(J$52=0,"",J58/J$52) -> 0 | L58: =+A58 -> 340
A59: 355 | B59: MARGINE SUL PRODOTTO | D59: =SUM(D56:D58) -> 0 | E59: =IF(D$52=0,0,D59/D$52) -> 0 | F59: =SUM(F56:F58) -> 0 | G59: =IF(F$52=0,0,F59/F$52) -> 0 | H59: =SUM(H56:H58) -> 854512.35 | I59: =IF(H$52=0,0,H59/H$52) -> 0.91025612 | J59: =SUM(J56:J58) -> 435817.31 | K59: =+IF(J$52=0,"",J59/J$52) -> 0.85295456 | L59: =+A59 -> 355
A60: 360 | B60: COSTI PER SERVIZI | C60: B.7 | D60: =+SUMIF(CE!$J:$J,BR!$A60,CE!B:B)*(TB<3)-SUMIFS('3'!$C:$C,'3'!$D:$D,BR!D$50,'3'!$G:$G,BR!$A60)*(TB=3) -> 0 | E60: =IF(D$52=0,0,D60/D$52) -> 0 | F60: =+SUMIF(CE!$J:$J,BR!$A60,CE!D:D)*(TB<3)-SUMIFS('3'!$C:$C,'3'!$D:$D,BR!F$50,'3'!$G:$G,BR!$A60)*(TB=3) -> 0 | G60: =IF(F$52=0,0,F60/F$52) -> 0 | H60: =+SUMIF(CE!$J:$J,BR!$A60,CE!F:F)*(TB<3)-SUMIFS('3'!$C:$C,'3'!$D:$D,BR!H$50,'3'!$G:$G,BR!$A60)*(TB=3) -> -516258.55 | I60: =IF(H$52=0,0,H60/H$52) -> -0.54993647 | J60: =+SUMIF(CE!$J:$J,BR!$A60,CE!H:H)*(TB<3)-SUMIFS('3'!$C:$C,'3'!$D:$D,BR!J$50,'3'!$G:$G,BR!$A60)*(TB=3) -> -340417.72 | K60: =+IF(J$52=0,"",J60/J$52) -> -0.66624441 | L60: =+A60 -> 360
A61: 370 | B61: GODIMENTO BENI 3° | C61: B.8 | D61: =+SUMIF(CE!$J:$J,BR!$A61,CE!B:B)*(TB<3)-SUMIFS('3'!$C:$C,'3'!$D:$D,BR!D$50,'3'!$G:$G,BR!$A61)*(TB=3) -> 0 | E61: =IF(D$52=0,0,D61/D$52) -> 0 | F61: =+SUMIF(CE!$J:$J,BR!$A61,CE!D:D)*(TB<3)-SUMIFS('3'!$C:$C,'3'!$D:$D,BR!F$50,'3'!$G:$G,BR!$A61)*(TB=3) -> 0 | G61: =IF(F$52=0,0,F61/F$52) -> 0 | H61: =+SUMIF(CE!$J:$J,BR!$A61,CE!F:F)*(TB<3)-SUMIFS('3'!$C:$C,'3'!$D:$D,BR!H$50,'3'!$G:$G,BR!$A61)*(TB=3) -> -32773.27 | I61: =IF(H$52=0,0,H61/H$52) -> -0.034911221 | J61: =+SUMIF(CE!$J:$J,BR!$A61,CE!H:H)*(TB<3)-SUMIFS('3'!$C:$C,'3'!$D:$D,BR!J$50,'3'!$G:$G,BR!$A61)*(TB=3) -> -12773.52 | K61: =+IF(J$52=0,"",J61/J$52) -> -0.02499954 | L61: =+A61 -> 370
A62: 380 | B62: ONERI DIV. DI GESTIONE | C62: B,14 | D62: =+SUMIF(CE!$J:$J,BR!$A62,CE!B:B)*(TB<3)-SUMIFS('3'!$C:$C,'3'!$D:$D,BR!D$50,'3'!$G:$G,BR!$A62)*(TB=3) -> 0 | E62: =IF(D$52=0,0,D62/D$52) -> 0 | F62: =+SUMIF(CE!$J:$J,BR!$A62,CE!D:D)*(TB<3)-SUMIFS('3'!$C:$C,'3'!$D:$D,BR!F$50,'3'!$G:$G,BR!$A62)*(TB=3) -> 0 | G62: =IF(F$52=0,0,F62/F$52) -> 0 | H62: =+SUMIF(CE!$J:$J,BR!$A62,CE!F:F)*(TB<3)-SUMIFS('3'!$C:$C,'3'!$D:$D,BR!H$50,'3'!$G:$G,BR!$A62)*(TB=3) -> -6851.69 | I62: =IF(H$52=0,0,H62/H$52) -> -0.0072986572 | J62: =+SUMIF(CE!$J:$J,BR!$A62,CE!H:H)*(TB<3)-SUMIFS('3'!$C:$C,'3'!$D:$D,BR!J$50,'3'!$G:$G,BR!$A62)*(TB=3) -> 13629.11 | K62: =+IF(J$52=0,"",J62/J$52) -> 0.026674047 | L62: =+A62 -> 380
A63: 385 | B63: VALORE AGGIUNTO | D63: =SUM(D59:D62) -> 0 | E63: =IF(D$52=0,0,D63/D$52) -> 0 | F63: =SUM(F59:F62) -> 0 | G63: =IF(F$52=0,0,F63/F$52) -> 0 | H63: =SUM(H59:H62) -> 298628.84 | I63: =IF(H$52=0,0,H63/H$52) -> 0.31810977 | J63: =SUM(J59:J62) -> 96255.18 | K63: =+IF(J$52=0,"",J63/J$52) -> 0.18838466 | L63: =+A63 -> 385
A64: 390 | B64: COSTO DEL LAVORO | C64: B.9 a b | D64: =+SUMIF(CE!$J:$J,BR!$A64,CE!B:B)*(TB<3)-SUMIFS('3'!$C:$C,'3'!$D:$D,BR!D$50,'3'!$G:$G,BR!$A64)*(TB=3) -> 0 | E64: =IF(D$52=0,0,D64/D$52) -> 0 | F64: =+SUMIF(CE!$J:$J,BR!$A64,CE!D:D)*(TB<3)-SUMIFS('3'!$C:$C,'3'!$D:$D,BR!F$50,'3'!$G:$G,BR!$A64)*(TB=3) -> 0 | G64: =IF(F$52=0,0,F64/F$52) -> 0 | H64: =+SUMIF(CE!$J:$J,BR!$A64,CE!F:F)*(TB<3)-SUMIFS('3'!$C:$C,'3'!$D:$D,BR!H$50,'3'!$G:$G,BR!$A64)*(TB=3) -> -103424.82 | I64: =IF(H$52=0,0,H64/H$52) -> -0.1101717 | J64: =+SUMIF(CE!$J:$J,BR!$A64,CE!H:H)*(TB<3)-SUMIFS('3'!$C:$C,'3'!$D:$D,BR!J$50,'3'!$G:$G,BR!$A64)*(TB=3) -> -63331.6 | K64: =+IF(J$52=0,"",J64/J$52) -> -0.12394867 | L64: =+A64 -> 390
A65: 400 | B65: ACC. TFR | C65: B.9 c | D65: =+SUMIF(CE!$J:$J,BR!$A65,CE!B:B)*(TB<3)-SUMIFS('3'!$C:$C,'3'!$D:$D,BR!D$50,'3'!$G:$G,BR!$A65)*(TB=3) -> 0 | E65: =IF(D$52=0,0,D65/D$52) -> 0 | F65: =+SUMIF(CE!$J:$J,BR!$A65,CE!D:D)*(TB<3)-SUMIFS('3'!$C:$C,'3'!$D:$D,BR!F$50,'3'!$G:$G,BR!$A65)*(TB=3) -> 0 | G65: =IF(F$52=0,0,F65/F$52) -> 0 | H65: =+SUMIF(CE!$J:$J,BR!$A65,CE!F:F)*(TB<3)-SUMIFS('3'!$C:$C,'3'!$D:$D,BR!H$50,'3'!$G:$G,BR!$A65)*(TB=3) -> -2320.92 | I65: =IF(H$52=0,0,H65/H$52) -> -0.0024723243 | J65: =+SUMIF(CE!$J:$J,BR!$A65,CE!H:H)*(TB<3)-SUMIFS('3'!$C:$C,'3'!$D:$D,BR!J$50,'3'!$G:$G,BR!$A65)*(TB=3) -> 0 | K65: =+IF(J$52=0,"",J65/J$52) -> 0 | L65: =+A65 -> 400
A66: 405 | B66: MARGINE OPERATIVO LORDO (EBITDA) | D66: =SUM(D63:D65) -> 0 | E66: =IF(D$52=0,0,D66/D$52) -> 0 | F66: =SUM(F63:F65) -> 0 | G66: =IF(F$52=0,0,F66/F$52) -> 0 | H66: =SUM(H63:H65) -> 192883.1 | I66: =IF(H$52=0,0,H66/H$52) -> 0.20546575 | J66: =SUM(J63:J65) -> 32923.58 | K66: =+IF(J$52=0,"",J66/J$52) -> 0.064435985 | L66: =+A66 -> 405
A67: 410 | B67: AMMORTAMENTI | C67: B.10+B.11 | D67: =+SUMIF(CE!$J:$J,BR!$A67,CE!B:B)*(TB<3)-SUMIFS('3'!$C:$C,'3'!$D:$D,BR!D$50,'3'!$G:$G,BR!$A67)*(TB=3) -> 0 | E67: =IF(D$52=0,0,D67/D$52) -> 0 | F67: =+SUMIF(CE!$J:$J,BR!$A67,CE!D:D)*(TB<3)-SUMIFS('3'!$C:$C,'3'!$D:$D,BR!F$50,'3'!$G:$G,BR!$A67)*(TB=3) -> 0 | G67: =IF(F$52=0,0,F67/F$52) -> 0 | H67: =+SUMIF(CE!$J:$J,BR!$A67,CE!F:F)*(TB<3)-SUMIFS('3'!$C:$C,'3'!$D:$D,BR!H$50,'3'!$G:$G,BR!$A67)*(TB=3) -> -7933.67 | I67: =IF(H$52=0,0,H67/H$52) -> -0.0084512197 | J67: =+SUMIF(CE!$J:$J,BR!$A67,CE!H:H)*(TB<3)-SUMIFS('3'!$C:$C,'3'!$D:$D,BR!J$50,'3'!$G:$G,BR!$A67)*(TB=3) -> -8768.21 | K67: =+IF(J$52=0,"",J67/J$52) -> -0.017160596 | L67: =+A67 -> 410
A68: 415 | B68: ACCANTONAMENTI | C68: B.12+B.13 | D68: =+SUMIF(CE!$J:$J,BR!$A68,CE!B:B)*(TB<3)-SUMIFS('3'!$C:$C,'3'!$D:$D,BR!D$50,'3'!$G:$G,BR!$A68)*(TB=3) -> 0 | E68: =IF(D$52=0,0,D68/D$52) -> 0 | F68: =+SUMIF(CE!$J:$J,BR!$A68,CE!D:D)*(TB<3)-SUMIFS('3'!$C:$C,'3'!$D:$D,BR!F$50,'3'!$G:$G,BR!$A68)*(TB=3) -> 0 | G68: =IF(F$52=0,0,F68/F$52) -> 0 | H68: =+SUMIF(CE!$J:$J,BR!$A68,CE!F:F)*(TB<3)-SUMIFS('3'!$C:$C,'3'!$D:$D,BR!H$50,'3'!$G:$G,BR!$A68)*(TB=3) -> 0 | I68: =IF(H$52=0,0,H68/H$52) -> 0 | L68: =+A68 -> 415
A69: 415 | B69: MARGINE OPERATIVO (EBIT) | D69: =SUM(D66:D68) -> 0 | E69: =IF(D$52=0,0,D69/D$52) -> 0 | F69: =SUM(F66:F68) -> 0 | G69: =IF(F$52=0,0,F69/F$52) -> 0 | H69: =SUM(H66:H68) -> 184949.43 | I69: =IF(H$52=0,0,H69/H$52) -> 0.19701453 | J69: =SUM(J66:J68) -> 24155.37 | K69: =+IF(J$52=0,"",J69/J$52) -> 0.047275389 | L69: =+A69 -> 415
A70: 420 | B70: PROVENTI FINANZIARI | C70: C.15+C.16 | D70: =+SUMIF(CE!$J:$J,BR!$A70,CE!B:B)*(TB<3)-SUMIFS('3'!$C:$C,'3'!$D:$D,BR!D$50,'3'!$G:$G,BR!$A70)*(TB=3) -> 0 | E70: =IF(D$52=0,0,D70/D$52) -> 0 | F70: =+SUMIF(CE!$J:$J,BR!$A70,CE!D:D)*(TB<3)-SUMIFS('3'!$C:$C,'3'!$D:$D,BR!F$50,'3'!$G:$G,BR!$A70)*(TB=3) -> 0 | G70: =IF(F$52=0,0,F70/F$52) -> 0 | H70: =+SUMIF(CE!$J:$J,BR!$A70,CE!F:F)*(TB<3)-SUMIFS('3'!$C:$C,'3'!$D:$D,BR!H$50,'3'!$G:$G,BR!$A70)*(TB=3) -> 0 | I70: =IF(H$52=0,0,H70/H$52) -> 0 | J70: =+SUMIF(CE!$J:$J,BR!$A70,CE!H:H)*(TB<3)-SUMIFS('3'!$C:$C,'3'!$D:$D,BR!J$50,'3'!$G:$G,BR!$A70)*(TB=3) -> 0 | K70: =+IF(J$52=0,"",J70/J$52) -> 0 | L70: =+A70 -> 420
A71: 430 | B71: ONERI FINANZIARI | C71: C.17 | D71: =+SUMIF(CE!$J:$J,BR!$A71,CE!B:B)*(TB<3)-SUMIFS('3'!$C:$C,'3'!$D:$D,BR!D$50,'3'!$G:$G,BR!$A71)*(TB=3) -> 0 | E71: =IF(D$52=0,0,D71/D$52) -> 0 | F71: =+SUMIF(CE!$J:$J,BR!$A71,CE!D:D)*(TB<3)-SUMIFS('3'!$C:$C,'3'!$D:$D,BR!F$50,'3'!$G:$G,BR!$A71)*(TB=3) -> 0 | G71: =IF(F$52=0,0,F71/F$52) -> 0 | H71: =+SUMIF(CE!$J:$J,BR!$A71,CE!F:F)*(TB<3)-SUMIFS('3'!$C:$C,'3'!$D:$D,BR!H$50,'3'!$G:$G,BR!$A71)*(TB=3) -> -4299.35 | I71: =IF(H$52=0,0,H71/H$52) -> -0.0045798164 | J71: =+SUMIF(CE!$J:$J,BR!$A71,CE!H:H)*(TB<3)-SUMIFS('3'!$C:$C,'3'!$D:$D,BR!J$50,'3'!$G:$G,BR!$A71)*(TB=3) -> -1898.67 | K71: =+IF(J$52=0,"",J71/J$52) -> -0.0037159589 | L71: =+A71 -> 430
A72: 432 | B72: DIVIDENDI RICEVUTI | D72: =+SUMIF(CE!$J:$J,BR!$A72,CE!B:B)*(TB<3)-SUMIFS('3'!$C:$C,'3'!$D:$D,BR!D$50,'3'!$G:$G,BR!$A72)*(TB=3) -> 0 | E72: =IF(D$52=0,0,D72/D$52) -> 0 | F72: =+SUMIF(CE!$J:$J,BR!$A72,CE!D:D)*(TB<3)-SUMIFS('3'!$C:$C,'3'!$D:$D,BR!F$50,'3'!$G:$G,BR!$A72)*(TB=3) -> 0 | G72: =IF(F$52=0,0,F72/F$52) -> 0 | H72: =+SUMIF(CE!$J:$J,BR!$A72,CE!F:F)*(TB<3)-SUMIFS('3'!$C:$C,'3'!$D:$D,BR!H$50,'3'!$G:$G,BR!$A72)*(TB=3) -> 0 | I72: =IF(H$52=0,0,H72/H$52) -> 0 | J72: =+SUMIF(CE!$J:$J,BR!$A72,CE!H:H)*(TB<3)-SUMIFS('3'!$C:$C,'3'!$D:$D,BR!J$50,'3'!$G:$G,BR!$A72)*(TB=3) -> 0 | K72: =+IF(J$52=0,"",J72/J$52) -> 0 | L72: =+A72 -> 432
A73: 435 | B73: RISULTATO DELLA GEST CARATT. | D73: =SUM(D69:D72) -> 0 | E73: =IF(D$52=0,0,D73/D$52) -> 0 | F73: =SUM(F69:F72) -> 0 | G73: =IF(F$52=0,0,F73/F$52) -> 0 | H73: =SUM(H69:H72) -> 180650.08 | I73: =IF(H$52=0,0,H73/H$52) -> 0.19243471 | J73: =SUM(J69:J72) -> 22256.7 | K73: =+IF(J$52=0,"",J73/J$52) -> 0.04355943 | L73: =+A73 -> 435
A74: 440 | B74: PROVENTI NON OPERATIVI | D74: =+SUMIF(CE!$J:$J,BR!$A74,CE!B:B)*(TB<3)-SUMIFS('3'!$C:$C,'3'!$D:$D,BR!D$50,'3'!$G:$G,BR!$A74)*(TB=3) -> 0 | E74: =IF(D$52=0,0,D74/D$52) -> 0 | F74: =+SUMIF(CE!$J:$J,BR!$A74,CE!D:D)*(TB<3)-SUMIFS('3'!$C:$C,'3'!$D:$D,BR!F$50,'3'!$G:$G,BR!$A74)*(TB=3) -> 0 | G74: =IF(F$52=0,0,F74/F$52) -> 0 | H74: =+SUMIF(CE!$J:$J,BR!$A74,CE!F:F)*(TB<3)-SUMIFS('3'!$C:$C,'3'!$D:$D,BR!H$50,'3'!$G:$G,BR!$A74)*(TB=3) -> 0 | I74: =IF(H$52=0,0,H74/H$52) -> 0 | J74: =+SUMIF(CE!$J:$J,BR!$A74,CE!H:H)*(TB<3)-SUMIFS('3'!$C:$C,'3'!$D:$D,BR!J$50,'3'!$G:$G,BR!$A74)*(TB=3) -> 326.88 | K74: =+IF(J$52=0,"",J74/J$52) -> 0.00063974922 | L74: =+A74 -> 440
A75: 450 | B75: COSTI NON OPERATIVI | D75: =+SUMIF(CE!$J:$J,BR!$A75,CE!B:B)*(TB<3)-SUMIFS('3'!$C:$C,'3'!$D:$D,BR!D$50,'3'!$G:$G,BR!$A75)*(TB=3) -> 0 | E75: =IF(D$52=0,0,D75/D$52) -> 0 | F75: =+SUMIF(CE!$J:$J,BR!$A75,CE!D:D)*(TB<3)-SUMIFS('3'!$C:$C,'3'!$D:$D,BR!F$50,'3'!$G:$G,BR!$A75)*(TB=3) -> 0 | G75: =IF(F$52=0,0,F75/F$52) -> 0 | H75: =+SUMIF(CE!$J:$J,BR!$A75,CE!F:F)*(TB<3)-SUMIFS('3'!$C:$C,'3'!$D:$D,BR!H$50,'3'!$G:$G,BR!$A75)*(TB=3) -> 0 | I75: =IF(H$52=0,0,H75/H$52) -> 0 | J75: =+SUMIF(CE!$J:$J,BR!$A75,CE!H:H)*(TB<3)-SUMIFS('3'!$C:$C,'3'!$D:$D,BR!J$50,'3'!$G:$G,BR!$A75)*(TB=3) -> -401.9 | K75: =+IF(J$52=0,"",J75/J$52) -> -0.00078657371 | L75: =+A75 -> 450
A76: 455 | B76: RISULTATO ANTE IMPOSTE | D76: =SUM(D73:D75) -> 0 | E76: =IF(D$52=0,0,D76/D$52) -> 0 | F76: =SUM(F73:F75) -> 0 | G76: =IF(F$52=0,0,F76/F$52) -> 0 | H76: =SUM(H73:H75) -> 180650.08 | I76: =IF(H$52=0,0,H76/H$52) -> 0.19243471 | J76: =SUM(J73:J75) -> 22181.68 | K76: =+IF(J$52=0,"",J76/J$52) -> 0.043412606 | L76: =+A76 -> 455
A77: 460 | B77: IMPOSTE | D77: =+SUMIF(CE!$J:$J,BR!$A77,CE!B:B)*(TB<3)-SUMIFS('3'!$C:$C,'3'!$D:$D,BR!D$50,'3'!$G:$G,BR!$A77)*(TB=3) -> 0 | E77: =IF(D$52=0,0,D77/D$52) -> 0 | F77: =+SUMIF(CE!$J:$J,BR!$A77,CE!D:D)*(TB<3)-SUMIFS('3'!$C:$C,'3'!$D:$D,BR!F$50,'3'!$G:$G,BR!$A77)*(TB=3) -> 0 | G77: =IF(F$52=0,0,F77/F$52) -> 0 | H77: =+SUMIF(CE!$J:$J,BR!$A77,CE!F:F)*(TB<3)-SUMIFS('3'!$C:$C,'3'!$D:$D,BR!H$50,'3'!$G:$G,BR!$A77)*(TB=3) -> -56008 | I77: =IF(H$52=0,0,H77/H$52) -> -0.059661659 | J77: =+SUMIF(CE!$J:$J,BR!$A77,CE!H:H)*(TB<3)-SUMIFS('3'!$C:$C,'3'!$D:$D,BR!J$50,'3'!$G:$G,BR!$A77)*(TB=3) -> 0 | K77: =+IF(J$52=0,"",J77/J$52) -> 0 | L77: =+A77 -> 460
A78: 469 | B78: RISULTATO NETTO | D78: =+D76+D77 -> 0 | E78: =IF(D$52=0,0,D78/D$52) -> 0 | F78: =+F76+F77 -> 0 | G78: =IF(F$52=0,0,F78/F$52) -> 0 | H78: =+H76+H77 -> 124642.08 | I78: =IF(H$52=0,0,H78/H$52) -> 0.13277306 | J78: =+J76+J77 -> 22181.68 | K78: =+IF(J$52=0,"",J78/J$52) -> 0.043412606 | L78: =+A78 -> 469
D79: =+(D78-CE!B130)*(TB<>3) -> 0 | F79: =+(F78-CE!D130)*(TB<>3) -> 0 | H79: =+(H78-CE!F130)*(TB<>3) -> 0 | J79: =+(J78-CE!H130)*(TB<>3) -> 0 | L79: =+A79 -> 0
B80: =B50 -> ALFA SPA | C80: =C50 -> 0 | D80: =D50 -> 44926 | E80: =E50 -> % | F80: =F50 -> 45291 | G80: =G50 -> % | H80: =H50 -> 45657 | I80: =I50 -> % | ... K80: =K50 -> % | L80: =+A80 -> 0
B81: STATO PATRIMONIALE GESTIONALE | C81: Voce Bilancio CEE | L81: =+A81 -> 0
B82: IMPIEGHI | C82: IMPIEGHI | L82: =+A82 -> 0
B83: IMMOBILIZZ. IMMATERIALI NETTE | D83: =+D6+D7 -> 0 | E83: =+IF(D$94=0,"",D83/D$94) | F83: =+F6+F7 -> 0 | G83: =+IF(F$94=0,"",F83/F$94) | H83: =+H6+H7 -> 1835.24 | I83: =+IF(H$94=0,"",H83/H$94) -> 0.035895514 | J83: =+J6+J7 -> 1557.53 | K83: =+IF(J$94=0,"",J83/J$94) -> 0.013271197 | L83: =+A83 -> 0
B84: IMMOBILIZZ. MATERIALI NETTE | D84: =+D8+D9 -> 0 | E84: =+IF(D$94=0,"",D84/D$94) | F84: =+F8+F9 -> 0 | G84: =+IF(F$94=0,"",F84/F$94) | H84: =+H8+H9 -> 86918.34 | I84: =+IF(H$94=0,"",H84/H$94) -> 1.7000384 | J84: =+J8+J9 -> 78897.35 | K84: =+IF(J$94=0,"",J84/J$94) -> 0.67225819 | L84: =+A84 -> 0
B85: IMMOBILIZZ. FINANZIARIE | D85: =+D10 -> 0 | E85: =+IF(D$94=0,"",D85/D$94) | F85: =+F10 -> 0 | G85: =+IF(F$94=0,"",F85/F$94) | H85: =+H10 -> 0 | I85: =+IF(H$94=0,"",H85/H$94) -> 0 | J85: =+J10 -> 0 | K85: =+IF(J$94=0,"",J85/J$94) -> 0 | L85: =+A85 -> 0
B86: IMMOBILIZZAZIONI | D86: =SUM(D83:D85) -> 0 | E86: =+IF(D$94=0,"",D86/D$94) | F86: =SUM(F83:F85) -> 0 | G86: =+IF(F$94=0,"",F86/F$94) | H86: =SUM(H83:H85) -> 88753.58 | I86: =+IF(H$94=0,"",H86/H$94) -> 1.7359339 | J86: =SUM(J83:J85) -> 80454.88 | K86: =+IF(J$94=0,"",J86/J$94) -> 0.68552938 | L86: =+A86 -> 0
B87: RIMANENZE | D87: =+D12 -> 0 | E87: =+IF(D$94=0,"",D87/D$94) | F87: =+F12 -> 0 | G87: =+IF(F$94=0,"",F87/F$94) | H87: =+H12 -> 1920.13 | I87: =+IF(H$94=0,"",H87/H$94) -> 0.03755588 | J87: =+J12 -> 1920.13 | K87: =+IF(J$94=0,"",J87/J$94) -> 0.016360792 | L87: =+A87 -> 0
B88: CREDITI COMMERCIALI | D88: =+D13 -> 0 | E88: =+IF(D$94=0,"",D88/D$94) | F88: =+F13 -> 0 | G88: =+IF(F$94=0,"",F88/F$94) | H88: =+H13 -> 0 | I88: =+IF(H$94=0,"",H88/H$94) -> 0 | J88: =+J13 -> 137151.13 | K88: =+IF(J$94=0,"",J88/J$94) -> 1.1686193 | L88: =+A88 -> 0
B89: ALTRI CREDITI E RATEI E RISC. | D89: =+D16 -> 0 | E89: =+IF(D$94=0,"",D89/D$94) | F89: =+F16 -> 0 | G89: =+IF(F$94=0,"",F89/F$94) | H89: =+H16 -> 63787.09 | I89: =+IF(H$94=0,"",H89/H$94) -> 1.2476136 | J89: =+J16 -> 43985.39 | K89: =+IF(J$94=0,"",J89/J$94) -> 0.37478494 | L89: =+A89 -> 0
B90: (DEBITI COMMERCIALI) | D90: =-D39-D40 -> 0 | E90: =+IF(D$94=0,"",D90/D$94) | F90: =-F39-F40 -> 0 | G90: =+IF(F$94=0,"",F90/F$94) | H90: =-H39-H40 -> -60246.41 | I90: =+IF(H$94=0,"",H90/H$94) -> -1.1783613 | J90: =-J39-J40 -> -133395.41 | K90: =+IF(J$94=0,"",J90/J$94) -> -1.1366181 | L90: =+A90 -> 0
B91: (ALTRI DEBITI RATEI E RISCONTI) | D91: =-D42-D45-D36-D37-D32 -> 0 | E91: =+IF(D$94=0,"",D91/D$94) | F91: =-F42-F45-F36-F37-F32 -> 0 | G91: =+IF(F$94=0,"",F91/F$94) | H91: =-H42-H45-H36-H37-H32 -> -41556.14 | I91: =+IF(H$94=0,"",H91/H$94) -> -0.81279779 | J91: =-J42-J45-J36-J37-J32 -> -11223.47 | K91: =+IF(J$94=0,"",J91/J$94) -> -0.09563147 | L91: =+A91 -> 0
B92: CAPITALE DI GIRO | D92: =SUM(D87:D91) -> 0 | E92: =+IF(D$94=0,"",D92/D$94) | F92: =SUM(F87:F91) -> 0 | G92: =+IF(F$94=0,"",F92/F$94) | H92: =SUM(H87:H91) -> -36095.33 | I92: =+IF(H$94=0,"",H92/H$94) -> -0.70598964 | J92: =SUM(J87:J91) -> 38437.77 | K92: =+IF(J$94=0,"",J92/J$94) -> 0.32751551 | L92: =+A92 -> 0
B93: FONDI | D93: =-D33-D34 -> 0 | E93: =+IF(D$94=0,"",D93/D$94) | F93: =-F33-F34 -> 0 | G93: =+IF(F$94=0,"",F93/F$94) | H93: =-H33-H34 -> -1530.97 | I93: =+IF(H$94=0,"",H93/H$94) -> -0.029944288 | J93: =-J33-J34 -> -1530.97 | K93: =+IF(J$94=0,"",J93/J$94) -> -0.013044888 | L93: =+A93 -> 0
B94: CAPITALE INVESTITO NETTO | D94: =+D86+D92+D93 -> 0 | E94: =+IF(D$94=0,"",D94/D$94) | F94: =+F86+F92+F93 -> 0 | G94: =+IF(F$94=0,"",F94/F$94) | H94: =+H86+H92+H93 -> 51127.28 | I94: =+IF(H$94=0,"",H94/H$94) -> 1 | J94: =+J86+J92+J93 -> 117361.68 | K94: =+IF(J$94=0,"",J94/J$94) -> 1 | L94: =+A94 -> 0
B95: FONTI | E95: =+IF(D$94=0,"",D95/D$94) | G95: =+IF(F$94=0,"",F95/F$94) | I95: =+IF(H$94=0,"",H95/H$94) -> 0 | K95: =+IF(J$94=0,"",J95/J$94) -> 0 | L95: =+A95 -> 0
B96: CAPITALE VERSATO | D96: =+D24+D25 -> 0 | E96: =+IF(D$94=0,"",D96/D$94) | F96: =+F24+F25 -> 0 | G96: =+IF(F$94=0,"",F96/F$94) | H96: =+H24+H25 -> 10000 | I96: =+IF(H$94=0,"",H96/H$94) -> 0.1955903 | J96: =+J24+J25 -> 10000 | K96: =+IF(J$94=0,"",J96/J$94) -> 0.085206688 | L96: =+A96 -> 0
B97: RISERVE | D97: =+D26+D27+D28 -> 0 | E97: =+IF(D$94=0,"",D97/D$94) | F97: =+F26+F27+F28 -> 0 | G97: =+IF(F$94=0,"",F97/F$94) | H97: =+H26+H27+H28 -> 0 | I97: =+IF(H$94=0,"",H97/H$94) -> 0 | J97: =+J26+J27+J28 -> 2000 | K97: =+IF(J$94=0,"",J97/J$94) -> 0.017041338 | L97: =+A97 -> 0
B98: UTILI (PERDITE) | D98: =+D29+D30 -> 0 | E98: =+IF(D$94=0,"",D98/D$94) | F98: =+F29+F30 -> 0 | G98: =+IF(F$94=0,"",F98/F$94) | H98: =+H29+H30 -> 124642.08 | I98: =+IF(H$94=0,"",H98/H$94) -> 2.4378782 | J98: =+J29+J30 -> 144823.76 | K98: =+IF(J$94=0,"",J98/J$94) -> 1.2339953 | L98: =+A98 -> 0
B99: PATRIMONIO NETTO | D99: =SUM(D96:D98) -> 0 | E99: =+IF(D$94=0,"",D99/D$94) | F99: =SUM(F96:F98) -> 0 | G99: =+IF(F$94=0,"",F99/F$94) | H99: =SUM(H96:H98) -> 134642.08 | I99: =+IF(H$94=0,"",H99/H$94) -> 2.6334685 | J99: =SUM(J96:J98) -> 156823.76 | K99: =+IF(J$94=0,"",J99/J$94) -> 1.3362433 | L99: =+A99 -> 0
B100: BANCHE PASSIVE A BT | D100: =+D41 -> 0 | E100: =+IF(D$94=0,"",D100/D$94) | F100: =+F41 -> 0 | G100: =+IF(F$94=0,"",F100/F$94) | H100: =+H41 -> 0 | I100: =+IF(H$94=0,"",H100/H$94) -> 0 | J100: =+J41 -> 0 | K100: =+IF(J$94=0,"",J100/J$94) -> 0 | L100: =+A100 -> 0
B101: (CASSA E BANCHE ATTIVE) | D101: =-D19 -> 0 | E101: =+IF(D$94=0,"",D101/D$94) | F101: =-F19 -> 0 | G101: =+IF(F$94=0,"",F101/F$94) | H101: =-H19 -> -117412.54 | I101: =+IF(H$94=0,"",H101/H$94) -> -2.2964754 | J101: =-J19 -> -66502.59 | K101: =+IF(J$94=0,"",J101/J$94) -> -0.56664654 | L101: =+A101 -> 0
B102: POSIZ. FINANZ. NETTA BT | D102: =SUM(D100:D101) -> 0 | E102: =+IF(D$94=0,"",D102/D$94) | F102: =SUM(F100:F101) -> 0 | G102: =+IF(F$94=0,"",F102/F$94) | H102: =SUM(H100:H101) -> -117412.54 | I102: =+IF(H$94=0,"",H102/H$94) -> -2.2964754 | J102: =SUM(J100:J101) -> -66502.59 | K102: =+IF(J$94=0,"",J102/J$94) -> -0.56664654 | L102: =+A102 -> 0
B103: BANCHE PASSIVE A ML | D103: =+D35 -> 0 | E103: =+IF(D$94=0,"",D103/D$94) | F103: =+F35 -> 0 | G103: =+IF(F$94=0,"",F103/F$94) | H103: =+H35 -> 33897.74 | I103: =+IF(H$94=0,"",H103/H$94) -> 0.66300691 | J103: =+J35 -> 27040.51 | K103: =+IF(J$94=0,"",J103/J$94) -> 0.23040323 | L103: =+A103 -> 0
...

Sheet Indici
B1: =+Menu!B2 -> 0
B3: =+s -> ALFA SPA | D3: =+D4-EDATE(D4,-12) -> 365 | F3: =+F4-D4 -> 365 | H3: =+H4-F4 -> 366 | J3: =+IF(i="Sì",J4-H4,"") -> 243
B4: INDICI DI BILANCIO | D4: =+EOMONTH(F4,-12) -> 44926 | F4: =+EOMONTH(H4,-12) -> 45291 | G4: qp | H4: =+EOMONTH(DATE(Menu!E10,Menu!K10,1),0) -> 45657 | I4: qp | J4: =+IF(i="Sì",Menu!G12,"") -> 45900 | K4: qp
B6: GRADO DI AUTONOMIA FINANZIARIA | D6: =+IF(Ci=0,"",Pn/Ci) | F6: =+IF(Ci=0,"",Pn/Ci) | G6: =+IF(F6>D6,"p","q") -> q | H6: =+IF(Ci=0,"",Pn/Ci) -> 0.49523826 | I6: =+IF(H6>F6,"p","q") -> q | J6: =+IF(Ci=0,"",Pn/Ci) -> 0.47520318 | K6: =+IF(i="Sì",IF(J6>H6,"p","q"),"") -> q
B7: Valore consigliato : > 20%-25%
B8: Indica quanta parte di 1 euro di finanziamenti proviene da mezzi propri; più è alto e più l’impresa si affida all’autofinanziamento per reperire i fondi da investire negli impieghi elencati tra le attività. Viceversa, più è basso e più l’impresa fa ricorso a fonti esterne per finanziare gli investimenti.
B12: =+IFERROR("Al "&TEXT(D$4,"gg/mm/aaaa")&" il capitale investito risultava coperto da capitale proprio per il "& TEXT(D6,"0,00%")&". Pertanto l'azienda risultava finanziata dai terzi per il "&TEXT(1-D6,"0,00%")&".","")
B13: =IFERROR(+"Al "&TEXT(F4,"gg/mm/aaaa")&" il capitale investito risultava coperto da capitale proprio per il "& TEXT(F6,"0,00%")&". Pertanto l'azienda risultava finanziata dai terzi per il "&TEXT(1-F6,"0,00%")&".","")
B14: =+IFERROR("Al "&TEXT(H4,"gg/mm/aaaa")&" il capitale investito risultava coperto da capitale proprio per il "& TEXT(H6,"0,00%")&". Pertanto l'azienda risultava finanziata dai terzi per il "&TEXT(1-H6,"0,00%")&".","") -> Al 31/12/2024 il capitale investito risultava coperto da capitale proprio per il 49,52%. Pertanto l'azienda risultava finanziata dai terzi per il 50,48%.
B15: =+IFERROR(IF(i="No","","Al "&TEXT(J4,"gg/mm/aaaa")&" il capitale investito risultava coperto da capitale proprio per il "& TEXT(J6,"0,00%")&". Pertanto per ogni euro investito nel capitale "&TEXT((1-J6)*100,"#.###")&" centesimi sono stati messi dai terzi"),"") -> Al 31/08/2025 il capitale investito risultava coperto da capitale proprio per il 47,52%. Pertanto per ogni euro investito nel capitale 52 centesimi sono stati messi dai terzi
B16: GRADO DI ELASTICITA' DEGLI IMPIEGHI | D16: =+IF(Ci=0,"",Ac/Ci) | F16: =+IF(Ci=0,"",Ac/Ci) | G16: =+IF(F16>D16,"p","q") -> q | H16: =+IF(Ci=0,"",Ac/Ci) -> 0.67354806 | I16: =+IF(H16>F16,"p","q") -> q | J16: =+IF(Ci=0,"",Ac/Ci) -> 0.75620776 | K16: =+IF(i="Sì",IF(J16>H16,"p","q"),"") -> p
B17: Valore consigliato : < 20%-40%
B18: Evidenzia il peso degli impieghi a breve rispetto al totale degli investimenti e quanto è elastica la struttura attiva del patrimonio. | I18: GRAFICO
B22: =+"Al "&TEXT(D$4,"gg/mm/aaaa")&" la maggiorparte degli impieghi aziendali è rappresentato da "&IF(D16>0.5," attività circolanti. ("&TEXT(D16,"0,00%")&")"," attività immobilizzate. ("&TEXT(1-D16,"0,00%")&")") -> Al 31/12/2022 la maggiorparte degli impieghi aziendali è rappresentato da attività circolanti. ()
B23: =+"Al "&TEXT(F$4,"gg/mm/aaaa")&" la maggiorparte degli impieghi aziendali è rappresentato da "&IF(F16>0.5," attività circolanti. ("&TEXT(F16,"0,00%")&")"," attività immobilizzate. ("&TEXT(1-F16,"0,00%")&")") -> Al 31/12/2023 la maggiorparte degli impieghi aziendali è rappresentato da attività circolanti. ()
B24: =+"Al "&TEXT(H$4,"gg/mm/aaaa")&" la maggiorparte degli impieghi aziendali è rappresentato da "&IF(H16>0.5," attività circolanti. ("&TEXT(H16,"0,00%")&")"," attività immobilizzate. ("&TEXT(1-H16,"0,00%")&")") -> Al 31/12/2024 la maggiorparte degli impieghi aziendali è rappresentato da attività circolanti. (67,35%)
B25: =+IF(i="No","","Al "&TEXT(J$4,"gg/mm/aaaa")&" la maggiorparte degli impieghi aziendali è rappresentato da "&IF(J16>0.5," attività circolanti. ("&TEXT(J16,"0,00%")&")"," attività immobilizzate. ("&TEXT(1-J16,"0,00%")&")")) -> Al 31/08/2025 la maggiorparte degli impieghi aziendali è rappresentato da attività circolanti. (75,62%)
A26: inv | B26: GRADO DI INDEBITAMENTO CORRENTE | D26: =+IF(Ci=0,"",Pb/Ci) | F26: =+IF(Ci=0,"",Pb/Ci) | G26: =+IF(F26>D26,"p","q") -> q | H26: =+IF(Ci=0,"",Pb/Ci) -> 0.37398408 | I26: =+IF(H26>F26,"p","q") -> q | J26: =+IF(Ci=0,"",Pb/Ci) -> 0.4931086 | K26: =+IF(i="Sì",IF(J26>H26,"p","q"),"") -> p
B27: Valore soglia : < 30% - 40%
B28: Fornisce il peso dell’indebitamento a breve rispetto al totale delle fonti finanziarie. Un elevato indebitamento corrente può essere pericoloso, soprattutto quando finanzia investimenti a lungo termine, oppure quando l’azienda avrà a breve bisogno di investimento per adeguamento impianti e macchinari. | I28: GRAFICO
B32: =IFERROR(+"Al "&TEXT(D$4,"gg/mm/aaaa")&IF(D26>0.4," l'azienda è eccessivamente sbilanciata sui debiti a breve "," l'azienda utilizzava il debito a breve in maniera non prevalente rispetto alle altre fonti di finanziamento ")&". Per ogni 100 euro di fonti finanziarie "&TEXT(D26*100,"#.###")&" sono formati da debiti a breve","")
B33: =IFERROR(+"Al "&TEXT(F$4,"gg/mm/aaaa")&IF(F26>0.4," l'azienda è eccessivamente sbilanciata sui debiti a breve "," l'azienda utilizzava il debito a breve in maniera non prevalente rispetto alle altre fonti di finanziamento ")&". Per ogni 100 euro di fonti finanziarie "&TEXT(F26*100,"#.###")&" sono formati da debiti a breve","")
B34: =+IFERROR("Al "&TEXT(H$4,"gg/mm/aaaa")&IF(H26>0.4," l'azienda è eccessivamente sbilanciata sui debiti a breve "," l'azienda utilizzava il debito a breve in maniera non prevalente rispetto alle altre fonti di finanziamento ")&". Per ogni 100 euro di fonti finanziarie "&TEXT(H26*100,"#.###")&" sono formati da debiti a breve","") -> Al 31/12/2024 l'azienda utilizzava il debito a breve in maniera non prevalente rispetto alle altre fonti di finanziamento . Per ogni 100 euro di fonti finanziarie 37 sono formati da debiti a breve
B35: =+IFERROR(IF(i="No","","Al "&TEXT(J$4,"gg/mm/aaaa")&IF(J26>0.4," l'azienda è eccessivamente sbilanciata sui debiti a breve "," l'azienda utilizzava il debito a breve in maniera non prevalente rispetto alle altre fonti di finanziamento ")&". Per ogni 100 euro di fonti finanziarie "&TEXT(J26*100,"#.###")&" sono formati da debiti a breve"),"") -> Al 31/08/2025 l'azienda è eccessivamente sbilanciata sui debiti a breve . Per ogni 100 euro di fonti finanziarie 49 sono formati da debiti a breve
B36: GRADO DI AMMORTAMENTO | D36: =+IF(Il=0,"",-Fdo/Il) | F36: =+IF(Il=0,"",-Fdo/Il) | G36: =+IF(F36>D36,"p","q") -> q | H36: =+IF(Il=0,"",-Fdo/Il) -> 0.082054976 | I36: =+IF(H36>F36,"p","q") -> q | J36: =+IF(Il=0,"",Fdo/Il) -> -0.17190651 | K36: =+IF(i="Sì",IF(J36>H36,"p","q"),"") -> q
B38: Indica il grado di obsolescenza dell'attivo fisso. Valori a 1 potrebbero connotare un'azienda con necessità di nuovi investimenti per il rinnovo di macchinari. | I38: GRAFICO
B42: =+"Al "&TEXT(D$4,"gg/mm/aaaa")&" le immobilizzazioni erano in media ammortizzate per il "&TEXT(D36,"0,0%") -> Al 31/12/2022 le immobilizzazioni erano in media ammortizzate per il
B43: =+"Al "&TEXT(F$4,"gg/mm/aaaa")&" le immobilizzazioni erano in media ammortizzate per il "&TEXT(F36,"0,0%") -> Al 31/12/2023 le immobilizzazioni erano in media ammortizzate per il
B44: =+"Al "&TEXT(H$4,"gg/mm/aaaa")&" le immobilizzazioni erano in media ammortizzate per il "&TEXT(H36,"0,0%") -> Al 31/12/2024 le immobilizzazioni erano in media ammortizzate per il 8,2%
B45: =+IF(i="No","","Al "&TEXT(J$4,"gg/mm/aaaa")&TEXT(H$4,"gg/mm/aaaa")&" le immobilizzazioni erano in media ammortizzate per il "&TEXT(H36,"0,0%")) -> Al 31/08/202531/12/2024 le immobilizzazioni erano in media ammortizzate per il 8,2%
B46: INCIDENZA DI AMMORTAMENTO | D46: =+IF(Il=0,"",Am/Il) | F46: =+IF(Il=0,"",Am/Il) | G46: =+IF(F46>D46,"p","q") -> q | H46: =+IF(Il=0,"",Am/Il) -> 0.082054976 | I46: =+IF(H46>F46,"p","q") -> q | J46: =+IF(Il=0,"",Am/Il) -> 0.090248069 | K46: =+IF(J46>H46,"p","q") -> p
B48: La differenza tra i valori dell'indice in due periodi, consente di capire la propensione ai nuovi investimenti. La diminuzione dell'indice, contemporaneo ad una diminuzione del grado di ammortamento, potrebbe invece derivare da un cambiamento nella politica d'ammortamento che, se non giustificata e in presenza di risultati economici nn particolarmente positivi, potrebbe gettare dubbi sulla veridicità e la correttezza delle scelte di bilancio. | I48: GRAFICO
B52: =+"Al "&TEXT(D$4,"gg/mm/aaaa")&" gli ammortamenti dell'esercizio erano pari al "&TEXT(D46,"0,0%")&" del valore delle immobilizzazioni lorde" -> Al 31/12/2022 gli ammortamenti dell'esercizio erano pari al del valore delle immobilizzazioni lorde
B53: =+"Al "&TEXT(F$4,"gg/mm/aaaa")&" gli ammortamenti dell'esercizio erano pari al "&TEXT(F46,"0,0%")&" del valore delle immobilizzazioni lorde" -> Al 31/12/2023 gli ammortamenti dell'esercizio erano pari al del valore delle immobilizzazioni lorde
B54: =+"Al "&TEXT(H$4,"gg/mm/aaaa")&" gli ammortamenti dell'esercizio erano pari al "&TEXT(H46,"0,0%")&" del valore delle immobilizzazioni lorde" -> Al 31/12/2024 gli ammortamenti dell'esercizio erano pari al 8,2% del valore delle immobilizzazioni lorde
B55: =+IF(i="No","","Al "&TEXT(J$4,"gg/mm/aaaa")&" gli ammortamenti dell'esercizio erano pari al "&TEXT(H46,"0,0%")&" del valore delle immobilizzazioni lorde") -> Al 31/08/2025 gli ammortamenti dell'esercizio erano pari al 8,2% del valore delle immobilizzazioni lorde
B56: MARGINE DI STRUTTURA | D56: =+IF(Im=0,"",Pn-Im) | F56: =+IF(Im=0,"",Pn-Im) | G56: =+IF(F56>D56,"p","q") -> q | H56: =+IF(Im=0,"",Pn-Im) -> 45888.5 | I56: =+IF(H56>F56,"p","q") -> q | J56: =+IF(Im=0,"",Pn-Im) -> 76368.88 | K56: =+IF(J56>H56,"p","q") -> p
B58: COPERTURA DELLE IMM. CON CAPITALE PROPRIO | D58: =+IF(Im=0,"",Pn/Im) | F58: =+IF(Im=0,"",Pn/Im) | G58: =+IF(F58>D58,"p","q") -> q | H58: =+IF(Im=0,"",Pn/Im) -> 1.5170327 | I58: =+IF(H58>F58,"p","q") -> q | J58: =+IF(Im=0,"",Pn/Im) -> 1.9492138 | K58: =+IF(J58>H58,"p","q") -> p
B59: Valore soglia: 90% - 100%
B60: MARGINE DI SICUREZZA | D60: =+IF(Im=0,"",Pn+Pl-Im) | F60: =+IF(Im=0,"",Pn+Pl-Im) | G60: =+IF(F60>D60,"p","q") -> q | H60: =+IF(Im=0,"",Pn+Pl-Im) -> 81443.46 | I60: =+IF(H60>F60,"p","q") -> q | J60: =+IF(Im=0,"",Pn+Pl-Im) -> 86826.44 | K60: =+IF(J60>H60,"p","q") -> p
B62: COPERTURA DELLE IMM. CON CAPITALE A LUNGO | D62: =+IF(Im=0,"",(Pn+Pl)/Im) | F62: =+IF(Im=0,"",(Pn+Pl)/Im) | G62: =+IF(F62>D62,"p","q") -> q | H62: =+IF(Im=0,"",(Pn+Pl)/Im) -> 1.9176358 | I62: =+IF(H62>F62,"p","q") -> q | J62: =+IF(Im=0,"",(Pn+Pl)/Im) -> 2.0791942 | K62: =+IF(J62>H62,"p","q") -> p
B63: Valore soglia: 1-1.25
B64: I margini di struttura e di sicurezza derivano dalla differenza tra l'importo delle fonti a lunga permanenza e il totale delle Immobilizzazioni nette. Hanno come scopo la verifica dell'attitudine dell'impresa a mantenere nel medio/lungo termine un costante equilibrio tra i fussi monetari in entrata e in uscita. I quozienti di copertura sono formati dal rapporto tra i mezzi a lunga permanenza e il totale delle attività immobilizzate. Esprimono una valutazione della solidità patrimoniale attraverso il grado di dipendenza dell'azienda da fonti di finanziamento esterne nella copertura degli investimenti in immobilizzazioni. | I64: GRAFICO
B68: =+IFERROR("Al "&TEXT(D$4,"gg/mm/aaaa")&" le immobilizzazioni erano "&IF(D60<0,"superiori al patrimonio netto e alle passività a medio lungo, denotando una situazione di sottocapitalizzazione per "&TEXT(ABS(D60),"#.###"),IF(D56<0,"superiori al patrimonio netto per"&TEXT(ABS(D56),"#.###")&"ma sufficientemente coperte dalle passività a medio lungo per "&TEXT(ABS(D60),"#.###"),"inferori al patrimonio netto per"&TEXT(ABS(D56),"#.###")))&". In particolare il Patrimonio Netto era pari al "&TEXT(D58,"0,00%")&" delle immobilizzazioni"&", mentre le fonti a lunga permanenza (Patrimonio Netto e Passività a lungo) erano pari al "&TEXT(D62,"0,00%"),"")
B69: =+IFERROR("Al "&TEXT(F$4,"gg/mm/aaaa")&" le immobilizzazioni erano "&IF(F60<0,"superiori al patrimonio netto e alle passività a medio lungo denotando una situazione di sottocapitalizzazione per "&TEXT(ABS(F60),"#.###"),IF(F56<0,"superiori al patrimonio netto per"&TEXT(ABS(F56),"#.###")&"ma sufficientemente coperte dalle passività a medio lungo per "&TEXT(ABS(F60),"#.###"),"inferori al patrimonio netto per"&TEXT(ABS(F56),"#.###")))&". In particolare il Patrimonio Netto era pari al "&TEXT(F58,"0,00%")&" delle immobilizzazioni"&", mentre le fonti a lunga permanenza (Patrimonio Netto e Passività a lungo) erano pari al "&TEXT(F62,"0,00%"),"")
B70: =+IFERROR("Al "&TEXT(H$4,"gg/mm/aaaa")&" le immobilizzazioni erano "&IF(H60<0,"superiori al patrimonio netto e alle passività a medio lungo denotando una situazione di sottocapitalizzazione per "&TEXT(ABS(H60),"#.###"),IF(H56<0,"superiori al patrimonio netto per"&TEXT(ABS(H56),"#.###")&"ma sufficientemente coperte dalle passività a medio lungo per "&TEXT(ABS(H60),"#.###"),"inferori al patrimonio netto per"&TEXT(ABS(H56),"#.###")))&". In particolare il Patrimonio Netto era pari al "&TEXT(H58,"0,00%")&" delle immobilizzazioni"&", mentre le fonti a lunga permanenza (Patrimonio Netto e Passività a lungo) erano pari al "&TEXT(H62,"0,00%"),"") -> Al 31/12/2024 le immobilizzazioni erano inferori al patrimonio netto per45.888. In particolare il Patrimonio Netto era pari al 151,70% delle immobilizzazioni, mentre le fonti a lunga permanenza (Patrimonio Netto e Passività a lungo) erano pari al 191,76%
A71: inv | B71: GRADO DI INDEBITAMENTO O LEVERAGE | D71: =+IF(Pn=0,"",D/Pn) | F71: =+IF(Pn=0,"",D/Pn) | G71: =+IF(F71>D71,"p","q") -> q | H71: =+IF(Pn=0,"",D/Pn) -> 1.0192301 | I71: =+IF(H71>F71,"p","q") -> q | J71: =+IF(Pn=0,"",D/Pn) -> 1.104363 | K71: =+IF(J71>H71,"p","q") -> p
B72: Valore soglia:< 3 -5
B73: Mette a confronto i mezzi finanziari a disposizione dell'azienda con vincolo di debito e quelli a titolo di capitale proprio; il tasso di indebitamento misura il grado di equilibrio tra le differenti fonti di finanziamento. Più elevato è il grado di indebitamento maggiore è il rischio finanziario. | I73: GRAFICO
B77: =+"Al "&TEXT(D$4,"gg/mm/aaaa")&IF(D71<0," Il patrimonio netto è negativo, pertanto l'indice perde di significatività. L'azienda deve essere immediatamente ricapitalizzata o messa in liquidazione", " i debiti erano pari a "&TEXT(D71,"#.###")&" volte i mezzi dei soci, denotando una situazione di "& IF(D71>5,"squilibrio finanziario da coprire mediante autofinanziamento e/o versamento da parte dei soci",IF(D71>3, "tensione finanziaria da mantenere monitorata per evitare squilibri futuri"," pieno equilibrio tra fonti proprie e di terzi"))) -> Al 31/12/2022 i debiti erano pari a volte i mezzi dei soci, denotando una situazione di squilibrio finanziario da coprire mediante autofinanziamento e/o versamento da parte dei soci
B78: =+"Al "&TEXT(F$4,"gg/mm/aaaa")&IF(F71<0," Il patrimonio netto è negativo, pertanto l'indice perde di significatività. L'azienda deve essere immediatamente ricapitalizzata o messa in liquidazione"," i debiti erano pari a "&TEXT(F71,"#.###")&" volte i mezzi dei soci, denotando una situazione di "& IF(F71>5,"squilibrio finanziario da coprire mediante autofinanziamento e/o versamento da parte dei soci",IF(F71>3, "tensione finanziaria da mantenere monitorata per evitare squilibri futuri"," pieno equilibrio tra fonti proprie e di terzi"))) -> Al 31/12/2023 i debiti erano pari a volte i mezzi dei soci, denotando una situazione di squilibrio finanziario da coprire mediante autofinanziamento e/o versamento da parte dei soci
B79: =+"Al "&TEXT(H$4,"gg/mm/aaaa")&IF(H71<0," Il patrimonio netto è negativo, pertanto l'indice perde di significatività. L'azienda deve essere immediatamente ricapitalizzata o messa in liquidazione"," i debiti erano pari a "&TEXT(H71,"#.###")&" volte i mezzi dei soci, denotando una situazione di "& IF(H71>5,"squilibrio finanziario da coprire mediante autofinanziamento e/o versamento da parte dei soci",IF(H71>3, "tensione finanziaria da mantenere monitorata per evitare squilibri futuri"," pieno equilibrio tra fonti proprie e di terzi"))) -> Al 31/12/2024 i debiti erano pari a 1 volte i mezzi dei soci, denotando una situazione di pieno equilibrio tra fonti proprie e di terzi
B80: =+IF(i="No","","Al "&TEXT(J$4,"gg/mm/aaaa")&IF(J71<0," Il patrimonio netto è negativo, pertanto l'indice perde di significatività. L'azienda deve essere immediatamente ricapitalizzata o messa in liquidazione"," i debiti erano pari a "&TEXT(J71,"#.###")&" volte i mezzi dei soci, denotando una situazione di "&IF(J71>5,"squilibrio finanziario da coprire mediante autofinanziamento e/o versamento da parte dei soci",IF(J71>3,"tensione finanziaria da mantenere monitorata per evitare squilibri futuri"," pieno equilibrio tra fonti proprie e di terzi")))) -> Al 31/08/2025 i debiti erano pari a 1 volte i mezzi dei soci, denotando una situazione di pieno equilibrio tra fonti proprie e di terzi
B81: MARGINE DI TESORERIA | D81: =+IF(Im=0,"",Cr+L-Pb) | F81: =+IF(Im=0,"",Cr+L-Pb) | G81: =+IF(F81>D81,"p","q") -> q | H81: =+IF(Im=0,"",Cr+L-Pb) -> 79523.33 | I81: =+IF(H81>F81,"p","q") -> q | J81: =+IF(Im=0,"",Cr+L-Pb) -> 84906.31 | K81: =+IF(J81>H81,"p","q") -> p
B82: Valore soglia
B83: QUOZIENTE DI LIQUIDITA' (QUICK RATIO) | D83: =+IF(Pb=0,"",(Cr+L)/Pb) | F83: =+IF(Pb=0,"",(Cr+L)/Pb) | G83: =+IF(F83>D83,"p","q") -> q | H83: =+IF(Pb=0,"",(Cr+L)/Pb) -> 1.7821226 | I83: =+IF(H83>F83,"p","q") -> q | J83: =+IF(Pb=0,"",(Cr+L)/Pb) -> 1.5217529 | K83: =+IF(J83>H83,"p","q") -> q
B84: Valore soglia: 1
B85: Sono indicatori finanziari della liquidità dell'Impresa indicano la capacità dell'azienda di "soddisfare" i debiti a breve e medio termine, mediante la liquidità disponibile e con i crediti a breve e medio termine. Nel caso in cui le attività liquide siano inferiori alle passività correnti, si hanno valori negativi per il primo indice e inferiori a uno per il secondo .
B89: =+IFERROR("Al "&TEXT(D$4,"gg/mm/aaaa")&" le attività di immediato e breve realizzo (liquidità e crediti) erano "&IF(D83<1," insufficienti, riuscendo a coprire solo il "&TEXT(D83,"0,00%")&" dei debiti a breve contratti. Qualora fosse stato necessario pagare tutti i debiti a breve sarebbero mancati € "&TEXT(ABS(D81),"#.###")," sufficienti, essendo superiori del "&TEXT(D83-1,"0,00%")&" rispetto ai debiti a breve contratti. Qualora fosse stato necessario pagare tutti i debiti a breve sarebbero avanzati "&TEXT(ABS(D81),"#.###")),"")
B90: =+IFERROR("Al "&TEXT(F$4,"gg/mm/aaaa")&" le attività di immediato e breve realizzo (liquidità e crediti) erano "&IF(F83<1," insufficienti, riuscendo a coprire solo il "&TEXT(F83,"0,00%")&" dei debiti a breve contratti. Qualora fosse stato necessario pagare tutti i debiti a breve sarebbero mancati € "&TEXT(ABS(F81),"#.###")," sufficienti, essendo superiori del "&TEXT(F83-1,"0,00%")&" rispetto ai debiti a breve contratti. Qualora fosse stato necessario pagare tutti i debiti a breve sarebbero avanzati "&TEXT(ABS(F81),"#.###")),"")
B91: =+IFERROR("Al "&TEXT(H$4,"gg/mm/aaaa")&" le attività di immediato e breve realizzo (liquidità e crediti) erano "&IF(H83<1," insufficienti, riuscendo a coprire solo il "&TEXT(H83,"0,00%")&" dei debiti a breve contratti. Qualora fosse stato necessario pagare tutti i debiti a breve sarebbero mancati € "&TEXT(ABS(H81),"#.###")," sufficienti, essendo superiori del "&TEXT(H83-1,"0,00%")&" rispetto ai debiti a breve contratti. Qualora fosse stato necessario pagare tutti i debiti a breve sarebbero avanzati "&TEXT(ABS(H81),"#.###")),"") -> Al 31/12/2024 le attività di immediato e breve realizzo (liquidità e crediti) erano sufficienti, essendo superiori del 78,21% rispetto ai debiti a breve contratti. Qualora fosse stato necessario pagare tutti i debiti a breve sarebbero avanzati 79.523
B92: =+IFERROR(IF(i="No","","Al "&TEXT(J$4,"gg/mm/aaaa")&" le attività di immediato e breve realizzo (liquidità e crediti) erano "&IF(J83<1," insufficienti, riuscendo a coprire solo il "&TEXT(J83,"0,00%")&" dei debiti a breve contratti. Qualora fosse stato necessario pagare tutti i debiti a breve sarebbero mancati € "&TEXT(ABS(J81),"#.###")," sufficienti, essendo superiori del "&TEXT(J83-1,"0,00%")&" rispetto ai debiti a breve contratti. Qualora fosse stato necessario pagare tutti i debiti a breve sarebbero avanzati "&TEXT(ABS(J81),"#.###"))),"") -> Al 31/08/2025 le attività di immediato e breve realizzo (liquidità e crediti) erano sufficienti, essendo superiori del 52,18% rispetto ai debiti a breve contratti. Qualora fosse stato necessario pagare tutti i debiti a breve sarebbero avanzati 84.906
B93: CAPITALE CIRCOLANTE NETTO | D93: =+IF(Pb=0,"",(Ac)-Pb) | F93: =+IF(Pb=0,"",(Ac)-Pb) | G93: =+IF(F93>D93,"p","q") -> q | H93: =+IF(Pb=0,"",(Ac)-Pb) -> 81443.46 | I93: =+IF(H93>F93,"p","q") -> q | J93: =+IF(Pb=0,"",(Ac)-Pb) -> 86826.44 | K93: =+IF(J93>H93,"p","q") -> p
B94: Valore soglia
B95: QUOZIENTE DI DISPONIBILITA' | D95: =+IF(Pb=0,"",(Ac/Pb)) | F95: =+IF(Pb=0,"",(Ac/Pb)) | G95: =+IF(F95>D95,"p","q") -> q | H95: =+IF(Pb=0,"",(Ac/Pb)) -> 1.8010073 | I95: =+IF(H95>F95,"p","q") -> q | J95: =+IF(Pb=0,"",(Ac/Pb)) -> 1.5335522 | K95: =+IF(J95>H95,"p","q") -> q
B96: Valore soglia
B97: Gli indici mettono a confronto gli impieghi destinati a essere realizzati in forma liquida entro un anno, con le passività, il cui rimborso è richiesto nel corso dell'anno, mostrando la capacità dell'Impresa a coprire i debiti a breve e medio termine con la liquidità disponibile (cassa e banche) i crediti a breve e medio termine e le rimanenze. Forniscono un'indicazione della capacità dell'impresa a far fronte agli impegni finanziari a breve termine, evidenziando il grado di solvibilità dell'azienda nel breve periodo. | I97: GRAFICO
B101: =+IFERROR("Al "&TEXT(D$4,"gg/mm/aaaa")&" l'intero attivo circolante (liquidità, crediti e rimanenze) era "&IF(D95<1," inferiore al passivo circolante,del "&TEXT(1-D95,"0,00%")&" Qualora fosse stato necessario pagare tutti i debiti a breve liquidando l'attivo circolante (incassando i crediti e realizzando il magazzino) sarebbero mancati € "&TEXT(ABS(D93),"#.###")," superiore del "&TEXT(D95-1,"0,00%")&" rispetto ai debiti a breve contratti. Qualora fosse stato necessario pagare tutti i debiti a breve sarebbero avanzati "&TEXT(ABS(D93),"#.###")),"")
B102: =+IFERROR("Al "&TEXT(F$4,"gg/mm/aaaa")&" l'intero attivo circolante (liquidità, crediti e rimanenze) era "&IF(F95<1," inferiore al passivo circolante,del "&TEXT(1-F95,"0,00%")&" Qualora fosse stato necessario pagare tutti i debiti a breve liquidando l'attivo circolante (incassando i crediti e realizzando il magazzino) sarebbero mancati € "&TEXT(ABS(F93),"#.###")," superiore del "&TEXT(F95-1,"0,00%")&" rispetto ai debiti a breve contratti. Qualora fosse stato necessario pagare tutti i debiti a breve sarebbero avanzati "&TEXT(ABS(F93),"#.###")),"")
B103: =+IFERROR("Al "&TEXT(H$4,"gg/mm/aaaa")&" l'intero attivo circolante (liquidità, crediti e rimanenze) era "&IF(H95<1," inferiore al passivo circolante,del "&TEXT(1-H95,"0,00%")&" Qualora fosse stato necessario pagare tutti i debiti a breve liquidando l'attivo circolante (incassando i crediti e realizzando il magazzino) sarebbero mancati € "&TEXT(ABS(H93),"#.###")," superiore del "&TEXT(H95-1,"0,00%")&" rispetto ai debiti a breve contratti. Qualora fosse stato necessario pagare tutti i debiti a breve sarebbero avanzati "&TEXT(ABS(H93),"#.###")),"") -> Al 31/12/2024 l'intero attivo circolante (liquidità, crediti e rimanenze) era superiore del 80,10% rispetto ai debiti a breve contratti. Qualora fosse stato necessario pagare tutti i debiti a breve sarebbero avanzati 81.443
B104: =+IFERROR(IF(i="No","","Al "&TEXT(J$4,"gg/mm/aaaa")&" l'intero attivo circolante (liquidità, crediti e rimanenze) era "&IF(J95<1," inferiore al passivo circolante,del "&TEXT(1-J95,"0,00%")&" Qualora fosse stato necessario pagare tutti i debiti a breve liquidando l'attivo circolante (incassando i crediti e realizzando il magazzino) sarebbero mancati € "&TEXT(ABS(J93),"#.###")," superiore del "&TEXT(J95-1,"0,00%")&" rispetto ai debiti a breve contratti. Qualora fosse stato necessario pagare tutti i debiti a breve sarebbero avanzati "&TEXT(ABS(J93),"#.###"))),"") -> Al 31/08/2025 l'intero attivo circolante (liquidità, crediti e rimanenze) era superiore del 53,36% rispetto ai debiti a breve contratti. Qualora fosse stato necessario pagare tutti i debiti a breve sarebbero avanzati 86.826
B105: RONA (Return On Net Asset) | F105: =+IF(CIn=0,"",(Ebit/g*365)/Cini) | G105: =+IF(F105>D105,"p","q") -> q | H105: =+IF(CIn=0,"",(Ebit/g*365)/Cini) -> #DIV/0! | I105: =+IF(H105>F105,"p","q") -> #DIV/0! | J105: =+IF(CIn=0,"",(Ebit/g*365)/Cini) -> 1.0659435 | K105: =+IF(J105>H105,"p","q") -> #DIV/0!
B106: Valore soglia
B107: ROI (Return on Investment) | D107: =+IF(Ci=0,"",Ro/Ci) | F107: =+IF(Ci=0,"",Ro/Ci) | G107: =+IF(F107>D107,"p","q") -> q | H107: =+IF(Ci=0,"",Ro/Ci) -> 0.68027792 | I107: =+IF(H107>F107,"p","q") -> q | J107: =+IF(Ci=0,"",Ro/Ci) -> 0.10994305 | K107: =+IF(J107>H107,"p","q") -> q
B108: Valore soglia: Wacc
B109: ROE (Return on Equity) | D109: =+IF(Pn=0,"",Rn/Pn) | F109: =+IF(Pn=0,"",Rn/Pn) | G109: =+IF(F109>D109,"p","q") -> q | H109: =+IF(Pn=0,"",Rn/Pn) -> 0.92572901 | I109: =+IF(H109>F109,"p","q") -> q | J109: =+IF(Pn=0,"",Rn/Pn) -> 0.21245608 | K109: =+IF(J109>H109,"p","q") -> q
B110: Valore soglia: Rendimento atteso dai soci
B111: Il RONA è il rapporto tra fatturato al netto dei costi gestionali e il Capitale Investito Netto. Variazioni negative indicano l'incapacità di generare redditi sufficienti a coprire investimenti e capitale circolante. Il ROI E' utile a valutare la redditività ed efficienza della gestione tipica dell'azienda, al fine di verificare la capacità dell'impresa di remunerare sia il Capitale Proprio che quello di Terzi. E' ottenuto calcolando il rapporto tra il Risultato Operativo e il Capitale Investito e non è influenzato dagli oneri/proventi finanziari in quanto non compresi nel Risultato Operativo. Il ROE misura invece la redditività del capitale investito dai soci. Determina in che percentuale il denaro investito dai soci viene remunerato; il tasso di Remunerazione dell'Investimento si ottiene calcolando il rapporto tra Utile Netto e Patrimonio Netto. In caso di patrimonio netto negativo e risultato netto negativo il ROE perde di significatività. | I111: GRAFICO
B115: =+"Al "&TEXT(D$4,"gg/mm/aaaa")&" Il capitale investito aveva un rendimento pari al "&TEXT(D107,"0,00%")& " mentre il denaro investito dai soci rendeva per il "&TEXT(D109,"0,00%") -> Al 31/12/2022 Il capitale investito aveva un rendimento pari al mentre il denaro investito dai soci rendeva per il
B116: =+"Al "&TEXT(F$4,"gg/mm/aaaa")&" Il capitale investito aveva un rendimento pari al "&TEXT(F107,"0,00%")& " mentre il denaro investito dai soci rendeva per il "&TEXT(F109,"0,00%") -> Al 31/12/2023 Il capitale investito aveva un rendimento pari al mentre il denaro investito dai soci rendeva per il
B117: =+"Al "&TEXT(H$4,"gg/mm/aaaa")&" Il capitale investito aveva un rendimento pari al "&TEXT(H107,"0,00%")& " mentre il denaro investito dai soci rendeva per il "&TEXT(H109,"0,00%") -> Al 31/12/2024 Il capitale investito aveva un rendimento pari al 68,03% mentre il denaro investito dai soci rendeva per il 92,57%
B118: =+IF(i="No","","Al "&TEXT(J$4,"gg/mm/aaaa")&" Il capitale investito aveva un rendimento pari al "&TEXT(J107,"0,00%")& " mentre il denaro investito dai soci rendeva per il "&TEXT(J109,"0,00%")) -> Al 31/08/2025 Il capitale investito aveva un rendimento pari al 10,99% mentre il denaro investito dai soci rendeva per il 21,25%
B119: GIORNI DI MAGAZZINO | D119: =+IF(V=0,"",(Ri/V)*g) | F119: =+IF(V=0,"",(Ri/V)*g) | G119: =+IF(F119>D119,"p","q") -> q | H119: =+IF(V=0,"",(Ri/V)*g) -> 0.74861234 | I119: =+IF(H119>F119,"p","q") -> q | J119: =+IF(V=0,"",(Ri/V)*g) -> 0.91318407 | K119: =+IF(J119>H119,"p","q") -> p
B121: GIORNI DURATA CREDITI | D121: =+IF((V)=0,"",(Cr/(V))*g) | F121: =+IF((V)=0,"",(Cr/(V))*g) | G121: =+IF(F121>D121,"p","q") -> q | H121: =+IF((V)=0,"",(Cr/(V))*g) -> 24.869047 | I121: =+IF(H121>F121,"p","q") -> q | J121: =+IF((V)=0,"",(Cr/(V))*g) -> 86.145721 | K121: =+IF(J121>H121,"p","q") -> p
B123: GIORNI DURATA DEBITI | D123: =+IF((Acq)=0,"",(For/(Acq))*g) | F123: =+IF((Acq)=0,"",(For/(Acq))*g) | G123: =+IF(F123>D123,"p","q") -> q | H123: =+IF((Acq)=0,"",(For/(Acq))*g) -> 34.642547 | I123: =+IF(H123>F123,"p","q") -> q | J123: =+IF((Acq)=0,"",(For/(Acq))*g) -> 75.67664 | K123: =+IF(J123>H123,"p","q") -> p
B125: CICLO MONETARIO NETTO | D125: =+IFERROR(D119+D121-D123,"") | F125: =+IFERROR(F119+F121-F123,"") | G125: =+IF(F125>D125,"p","q") -> q | H125: =+IFERROR(H119+H121-H123,"") -> -9.0248877 | I125: =+IF(H125>F125,"p","q") -> q | J125: =IFERROR(J119+J121-J123,"") -> 11.382265 | K125: =+IF(J125>H125,"p","q") -> p
B127: Gli indici di durata indicano quanti giorni i componenti del Conto Economico, dopo essersi trasformati in elementi dello stato patrimoniale, vi permangono prima di diventare liquidità. Qualora si intenda misurare gli indici di durata in periodi inferiori all’esercizio, occorrerà moltiplicare il rapporto tra elementi del conto economico e dello stato patrimoniale per il numero dei giorni del periodo considerato. | I127: GRAFICO
B131: =+IFERROR("Al "&TEXT(D$4,"gg/mm/aaaa")&" i tempi medi di permanenza delle rimanenze di magazzino erano pari a "&TEXT(D119,"#.###")&" giorni, i crediti venivano incassati mediamente a "&TEXT(D121,"#.###")&" giorni, mentre i debiti venivano pagati mediamente a "&TEXT(D123,"#.###")&" giorni, pertanto il ciclo monetario netto portava l'azienda ad essere "&IF(D125>0,"esposta","coperta")&" finanziariamente per "&TEXT(ABS(D125),"#.###")&" giorni","")
B132: =+IFERROR("Al "&TEXT(F$4,"gg/mm/aaaa")&" i tempi medi di permanenza delle rimanenze di magazzino erano pari a "&TEXT(F119,"#.###")&" giorni, i crediti venivano incassati mediamente a "&TEXT(F121,"#.###")&" giorni, mentre i debiti venivano pagati mediamente a "&TEXT(F123,"#.###")&" giorni, pertanto il ciclo monetario netto portava l'azienda ad essere "&IF(F125>0,"esposta","coperta")&" finanziariamente per "&TEXT(ABS(F125),"#.###")&" giorni","")
B133: =+IFERROR("Al "&TEXT(H$4,"gg/mm/aaaa")&" i tempi medi di permanenza delle rimanenze di magazzino erano pari a "&TEXT(H119,"#.###")&" giorni, i crediti venivano incassati mediamente a "&TEXT(H121,"#.###")&" giorni, mentre i debiti venivano pagati mediamente a "&TEXT(H123,"#.###")&" giorni, pertanto il ciclo monetario netto portava l'azienda ad essere "&IF(H125>0,"esposta","coperta")&" finanziariamente per "&TEXT(ABS(H125),"#.###")&" giorni","") -> Al 31/12/2024 i tempi medi di permanenza delle rimanenze di magazzino erano pari a 1 giorni, i crediti venivano incassati mediamente a 25 giorni, mentre i debiti venivano pagati mediamente a 35 giorni, pertanto il ciclo monetario netto portava l'azienda ad essere coperta finanziariamente per 9 giorni
B134: =+IFERROR(IF(i="No","","Al "&TEXT(H$4,"gg/mm/aaaa")&" i tempi medi di permanenza delle rimanenze di magazzino erano pari a "&TEXT(H119,"#.###")&" giorni, i crediti venivano incassati mediamente a "&TEXT(H121,"#.###")&" giorni, mentre i debiti venivano pagati mediamente a "&TEXT(H123,"#.###")&" giorni, pertanto il ciclo monetario netto portava l'azienda ad essere "&IF(H125>0,"esposta","coperta")&" finanziariamente per "&TEXT(ABS(H125),"#.###")&" giorni"),"") -> Al 31/12/2024 i tempi medi di permanenza delle rimanenze di magazzino erano pari a 1 giorni, i crediti venivano incassati mediamente a 25 giorni, mentre i debiti venivano pagati mediamente a 35 giorni, pertanto il ciclo monetario netto portava l'azienda ad essere coperta finanziariamente per 9 giorni
C136: =+D4 -> 44926 | E136: =+F4 -> 45291 | G136: =+H4 -> 45657 | I136: =+J4 -> 45900
C137: mag inc | D137: pag | E137: =+C137 -> mag inc | F137: =+D137 -> pag | G137: =+E137 -> mag inc | H137: =+F137 -> pag | I137: =+G137 -> mag inc | J137: =+H137 -> pag
B138: Durata Crediti | C138: =+D119 | E138: =+F119 | G138: =+H119 -> 0.74861234 | I138: =+J119 -> 0.91318407
B139: Durata Magazzino | C139: =+D121 | E139: =+F121 | G139: =+H121 -> 24.869047 | I139: =+J121 -> 86.145721
B140: Durata Debiti | D140: =+D123 | F140: =+F123 | H140: =+H123 -> 34.642547 | J140: =+J123 -> 75.67664
B141: Ciclo Monetario Netto | D141: =+IFERROR(C138+C139-D140,"") | F141: =+IFERROR(E138+E139-F140,"") | H141: =+IFERROR(G138+G139-H140,"") -> -9.0248877 | J141: =+IFERROR(I138+I139-J140,"") -> 11.382265

Sheet DatiI
B1: =+Menu!B2 -> 0
B2: Dr Alessandro Mattavelli ©
B3: Dati di base per gli indici di bilancio | D3: =+s -> ALFA SPA
D4: =+EOMONTH(F4,-12) -> 44926 | F4: =+EOMONTH(H4,-12) -> 45291 | H4: =+EOMONTH(DATE(Menu!E10,Menu!K10,1),0) -> 45657 | J4: =+Menu!G12 -> 45900 | K4: x
A6: Il | B6: Immobilizzazioni Lorde | D6: =+BR!D6+BR!D8+BR!D10 -> 0 | F6: =+BR!F6+BR!F8+BR!F10 -> 0 | H6: =+BR!H6+BR!H8+BR!H10 -> 96687.25 | J6: =+BR!J6+BR!J8+BR!J10 -> 97156.76
A7: Im | B7: I: Immobilizzazioni Nette o Attivo Fisso | D7: =+BR!D86 -> 0 | F7: =+BR!F86 -> 0 | H7: =+BR!H86 -> 88753.58 | J7: =+BR!J86 -> 80454.88
A8: Fdo | B8: Fdo: Fondi di ammortamento | D8: =+BR!D7+BR!D9 -> 0 | F8: =+BR!F7+BR!F9 -> 0 | H8: =+BR!H7+BR!H9 -> -7933.67 | J8: =+BR!J7+BR!J9 -> -16701.88
A9: Ri | B9: R: Rimanenze | D9: =+BR!D87 -> 0 | F9: =+BR!F87 -> 0 | H9: =+BR!H87 -> 1920.13 | J9: =+BR!J87 -> 1920.13
A10: Cr | B10: C: Crediti | D10: =+BR!D17 -> 0 | F10: =+BR!F17 -> 0 | H10: =+BR!H17 -> 63787.09 | J10: =+BR!J17 -> 181136.52
A11: Cli | B11: Cli: Crediti Commerciali | D11: =+BR!D13 -> 0 | F11: =+BR!F13 -> 0 | H11: =+BR!H13 -> 0 | J11: =+BR!J13 -> 137151.13
A12: L | B12: L: Liquidità | D12: =+BR!D19 -> 0 | F12: =+BR!F19 -> 0 | H12: =+BR!H19 -> 117412.54 | J12: =+BR!J19 -> 66502.59
A13: Am | B13: Ammortamenti | D13: =-BR!D67 -> 0 | F13: =-BR!F67 -> 0 | H13: =-BR!H67 -> 7933.67 | J13: =-BR!J67 -> 8768.21
A14: Ac | B14: R + C + L = AC: Attivo Circolante o Corrente | D14: =+BR!D20 -> 0 | F14: =+BR!F20 -> 0 | H14: =+BR!H20 -> 183119.76 | J14: =+BR!J20 -> 249559.24
A15: Ci | B15: Capitale Investito | D15: =+BR!D21 -> 0 | F15: =+BR!F21 -> 0 | H15: =+BR!H21 -> 271873.34 | J15: =+BR!J21 -> 330014.12
A16: Cin | B16: Capitale Investito Netto | D16: =+BR!D94 -> 0 | F16: =+BR!F94 -> 0 | H16: =+BR!H94 -> 51127.28 | J16: =+BR!J94 -> 117361.68
A17: Cini | B17: Capitale Investito Netto Iniziale | F17: =+D16 -> 0 | H17: =+F16 -> 0 | J17: =+H16 -> 51127.28
A18: Pn | B18: PN: Patrimonio Netto o Mezzi Propri | D18: =+BR!D99 -> 0 | F18: =+BR!F99 -> 0 | H18: =+BR!H99 -> 134642.08 | J18: =+BR!J99 -> 156823.76
A19: Pl | B19: PL: Passività Medio Lungo | D19: =+BR!D38 -> 0 | F19: =+BR!F38 -> 0 | H19: =+BR!H38 -> 35554.96 | J19: =+BR!J38 -> 10457.56
A20: Pb | B20: PB: Passività Correnti | D20: =+BR!D46 -> 0 | F20: =+BR!F46 -> 0 | H20: =+BR!H46 -> 101676.3 | J20: =+BR!J46 -> 162732.8
A21: D | B21: PB + PL = D: Debiti o Mezzi di Terzi | D21: =+BR!D47 -> 0 | F21: =+BR!F47 -> 0 | H21: =+BR!H47 -> 137231.26 | J21: =+BR!J47 -> 173190.36
A22: Pfn | B22: PFN = Posizione Finanziaria Netta | D22: =+BR!D105 -> 0 | F22: =+BR!F105 -> 0 | H22: =+BR!H105 -> -83514.8 | J22: =+BR!J105 -> -39462.08
A23: Fa | B23: F= Fatturato | D23: =+BR!D52 -> 0 | F23: =+BR!F52 -> 0 | H23: =+BR!H52 -> 938760.35 | J23: =+BR!J52*J40 -> 767476.65
A24: Co | B24: Co = Consumi | D24: =-(BR!D111+BR!D112+BR!D114) -> 0 | F24: =-(BR!F111+BR!F112+BR!F114) -> 0 | H24: =-(BR!H111+BR!H112+BR!H114) -> 0 | J24: =-(BR!J111+BR!J112+BR!J114)*J40 -> 0
A25: M | B25: M = F-C = Margine di prodotto | D25: =+BR!D59 -> 0 | F25: =+BR!F59 -> 0 | H25: =+BR!H59 -> 854512.35 | J25: =+BR!J59 -> 435817.31
A26: Rn | B26: Reddito Netto | D26: =+BR!D78 -> 0 | F26: =+BR!F78 -> 0 | H26: =+BR!H78 -> 124642.08 | J26: =+BR!J78*J40 -> 33318.161
A27: Ro | B27: Reddito Operativo | D27: =+BR!D69 -> 0 | F27: =+BR!F69 -> 0 | H27: =+BR!H69 -> 184949.43 | J27: =+BR!J69*J40 -> 36282.757
A28: Mp | B28: M% = (F-C)/F Margine % di prodotto | D28: =+(BR!D110+BR!D111+BR!D112+BR!D113+BR!D114)/BR!D110 -> #DIV/0! | F28: =+(BR!F110+BR!F111+BR!F112+BR!F113+BR!F114)/BR!F110 -> #DIV/0! | H28: =+(BR!H110+BR!H111+BR!H112+BR!H113+BR!H114)/BR!H110 -> #DIV/0! | J28: =+(BR!J110+BR!J111+BR!J112+BR!J113+BR!J114)/BR!J110 -> #DIV/0!
A29: Cv | B29: CV = Costi Variabili | D29: =-#REF! -> #REF! | F29: =-#REF! -> #REF! | H29: =-#REF! -> #REF! | J29: =-#REF! -> #REF!
A30: Cf | B30: CF = Costi Fissi | D30: =-(+#REF!+#REF!) -> #REF! | F30: =-(+#REF!+#REF!) -> #REF! | H30: =-(+#REF!+#REF!) -> #REF! | J30: =-(+#REF!+#REF!) -> #REF!
A31: E | B31: EBIT | D31: =+BR!D69 -> 0 | F31: =+BR!F69 -> 0 | H31: =+BR!H69 -> 184949.43 | J31: =+BR!J69*J40 -> 36282.757
A32: V | B32: Vendite | D32: =+BR!D52 -> 0 | F32: =+BR!F52 -> 0 | H32: =+BR!H52 -> 938760.35 | J32: =+BR!J52 -> 510950.21
A33: I | B33: Iva
A34: Acq | B34: Acquisti | D34: =-BR!D57-BR!D60-BR!D61 -> 0 | F34: =-BR!F57-BR!F60-BR!F61 -> 0 | H34: =-BR!H57-BR!H60-BR!H61 -> 636505.92 | J34: =-BR!J57-BR!J60-BR!J61 -> 428336.73
A35: For | B35: Fornitori | D35: =+BR!D40 -> 0 | F35: =+BR!F40 -> 0 | H35: =+BR!H40 -> 60246.41 | J35: =+BR!J40 -> 133395.41
A36: MOL | B36: MOL | D36: =+BR!D66-BR!D55 -> 0 | F36: =+BR!F66-BR!F55 -> 0 | H36: =+BR!H66-BR!H55 -> 191577.13 | J36: =+BR!J66-BR!J55 -> 32910.99
A37: Of | B37: Oneri finanziari lordi | D37: =+BR!D71 -> 0 | F37: =+BR!F71 -> 0 | H37: =+BR!H71 -> -4299.35 | J37: =+BR!J71 -> -1898.67
D38: =+g -> 365 | F38: =+g -> 365 | H38: =+g -> 366 | J38: =+g -> 243
B39: Inizio | D39: =+DATE(YEAR(D4),12,31)-DATE(YEAR(D4),1,1)+1 -> 365 | F39: =+DATE(YEAR(F4),12,31)-DATE(YEAR(F4),1,1)+1 -> 365 | H39: =+DATE(YEAR(H4),12,31)-DATE(YEAR(H4),1,1)+1 -> 366 | J39: =+DATE(YEAR(J4),12,31)-DATE(YEAR(J4),1,1)+1 -> 365
B40: Moltiplicatore reddito | D40: =+D39/D38 -> 1 | F40: =+F39/F38 -> 1 | H40: =+H39/H38 -> 1 | J40: =+J39/J38 -> 1.5020576

Sheet ss
A1: =+Menu!B2 -> 0
A4: Colonna1 | B4: Colonna2 | C4: Colonna3 | D4: Colonna4 | E4: Colonna5 | F4: Colonna6 | G4: Colonna7 | H4: Colonna8 | I4: Colonna9 | J4: Colonna10 | K4: Colonna11 | L4: Colonna12 | M4: Colonna13 | O4: Colonna1 | P4: Colonna2 | Q4: Colonna3 | R4: Colonna4 | S4: Colonna5 | T4: Colonna6 | U4: Colonna7 | V4: Colonna8 | W4: Colonna9
N5: =+IFERROR(MATCH("X",OFFSET(STR,N4,0),0)+N4,"")
N6: =+IFERROR(MATCH("X",OFFSET(STR,N5,0),0)+N5,"")
N7: =+IFERROR(MATCH("X",OFFSET(STR,N6,0),0)+N6,"")
N8: =+IFERROR(MATCH("X",OFFSET(STR,N7,0),0)+N7,"")
N9: =+IFERROR(MATCH("X",OFFSET(STR,N8,0),0)+N8,"")
N10: =+IFERROR(MATCH("X",OFFSET(STR,N9,0),0)+N9,"")
N11: =+IFERROR(MATCH("X",OFFSET(STR,N10,0),0)+N10,"")
N12: =+IFERROR(MATCH("X",OFFSET(STR,N11,0),0)+N11,"")
N13: =+IFERROR(MATCH("X",OFFSET(STR,N12,0),0)+N12,"")
N14: =+IFERROR(MATCH("X",OFFSET(STR,N13,0),0)+N13,"")
N15: =+IFERROR(MATCH("X",OFFSET(STR,N14,0),0)+N14,"")
N16: =+IFERROR(MATCH("X",OFFSET(STR,N15,0),0)+N15,"")
... N2999: =+IFERROR(MATCH("X",OFFSET(STR,N2998,0),0)+N2998,"")
M7309: x

Sheet Budget
B1: =+Menu!B2 -> 0 | N1: =+R134-R129 -> -56008
B3: =+s -> ALFA SPA
B4: BUDGET | F4: Ultimo Bilancio | L4: Variazioni | R4: Budget | X4: D | Z4: Note - appunti e progetti
B6: Ricavi di Vendita | D6: =+BR!H4 -> 45657 | F6: =SUM(J10:J20) -> 0 | L6: =+SUM(P10:P18) -> 0 | R6: =SUM(V10:V18) -> 0 | X6: =+R6/F6-1 -> #DIV/0!
B8: Linee di prodotto (Max 5) | D8: 1 | F8: Qta | H8: Prezzo Medio | J8: Fatturato | L8: Qta | N8: Prezzo Medio | P8: Fatturato | R8: Qta | T8: Prezzo Medio | V8: Fatturato
B10: =+IF($D$8>0,"Linea 1","") -> Linea 1 | H10: 1 | J10: =+F10*H10 -> 0 | P10: =+L10*(H10+N10)+N10*F10 -> 0 | R10: =+F10+L10 -> 0 | S10: =+O10*Q10 -> 0 | T10: =+H10+N10 -> 1 | U10: =+Q10*S10 -> 0 | V10: =+R10*T10 -> 0
R11: =+N11*P11 -> 0 | S11: =+O11*Q11 -> 0 | T11: =+P11*R11 -> 0 | U11: =+Q11*S11 -> 0 | V11: =+R11*T11 -> 0
B12: =+IF($D$8>1,"Linea 2","") | J12: =+F12*H12 -> 0 | P12: =+L12*(H12+N12)+N12*F12 -> 0 | R12: =+F12+L12 -> 0 | S12: =+O12*Q12 -> 0 | T12: =+H12+N12 -> 0 | U12: =+Q12*S12 -> 0 | V12: =+R12*T12 -> 0
R13: =+N13*P13 -> 0 | S13: =+O13*Q13 -> 0 | T13: =+P13*R13 -> 0 | U13: =+Q13*S13 -> 0 | V13: =+R13*T13 -> 0
B14: =+IF($D$8>=3,"Linea 3","") | J14: =+F14*H14 -> 0 | P14: =+L14*(H14+N14)+N14*F14 -> 0 | R14: =+F14+L14 -> 0 | S14: =+O14*Q14 -> 0 | T14: =+H14+N14 -> 0 | U14: =+Q14*S14 -> 0 | V14: =+R14*T14 -> 0
R15: =+N15*P15 -> 0 | S15: =+O15*Q15 -> 0 | T15: =+P15*R15 -> 0 | U15: =+Q15*S15 -> 0 | V15: =+R15*T15 -> 0
B16: =+IF($D$8>3,"Linea 4","") | J16: =+F16*H16 -> 0 | P16: =+L16*(H16+N16)+N16*F16 -> 0 | R16: =+F16+L16 -> 0 | S16: =+O16*Q16 -> 0 | T16: =+H16+N16 -> 0 | U16: =+Q16*S16 -> 0 | V16: =+R16*T16 -> 0
R17: =+N17*P17 -> 0 | S17: =+O17*Q17 -> 0 | T17: =+P17*R17 -> 0 | U17: =+Q17*S17 -> 0 | V17: =+R17*T17 -> 0
B18: =+IF($D$8>4,"Linea 5","") | J18: =+F18*H18 -> 0 | P18: =+L18*(H18+N18)+N18*F18 -> 0 | R18: =+F18+L18 -> 0 | S18: =+O18*Q18 -> 0 | T18: =+H18+N18 -> 0 | U18: =+Q18*S18 -> 0 | V18: =+R18*T18 -> 0
R19: =+N19*P19 -> 0 | S19: =+O19*Q19 -> 0 | T19: =+P19*R19 -> 0 | U19: =+Q19*S19 -> 0
B20: Altri Ricavi/ spese | F20: =+D24+J30+J32+J34+J36+J38 -> 0 | J20: =+F20 -> 0 | T20: =+H20+N20 -> 0 | V20: =+R20*T20 -> 0
B22: Fatturato da bilancio | D22: =+BR!H110 -> 0 | F22: =+IF(ABS(D22-F6)>1,"Se il dettaglio delle vendite è diverso dal bilancio non sarà possibile quadrare il rendiconto finanziario!","")
B24: Consumi | D24: =+BR!H111+BR!H112+BR!H114+BR!H113 -> 0 | F24: =SUM(J30:J38) -> 0 | L24: =SUM(P30:P38) -> 0 | R24: =SUM(V30:V38) -> 0 | X24: =+R24/F24-1 -> #DIV/0!
B26: Acquisti per la produzione | F26: =-BR!H114 -> 0 | L26: =+T88-F88+L24 -> 0 | R26: =+L26+F26 -> 0 | X26: =+R26/F26-1 -> #DIV/0!
R27: =+N27*P27 -> 0 | S27: =+O27*Q27 -> 0 | T27: =+P27*R27 -> 0 | U27: =+Q27*S27 -> 0 | V27: =+R27*T27 -> 0
B28: Margine % | F28: Incidenza Consumi | H28: Marg | J28: Consumi | L28: Variazione Incidenza | N28: D Marg. | P28: Var Consumi | R28: Incidenza Consumi | T28: Marg | V28: Consumi
U29: =+Q29*S29 -> 0
B30: =+IF($D$8>0,"Linea 1","") -> Linea 1 | D30: =+D10 -> 0 | H30: =+IF(F30>0,1-F30,"") | J30: =+J10*F30 -> 0 | P30: =+J10*L30+P10*(F30+L30) -> 0 | R30: =+F30+L30 -> 0 | S30: =+O30*Q30 -> 0 | T30: =+IF(R30>0,1-R30,"") | U30: =+Q30*S30 -> 0 | V30: =+R30*V10 -> 0
R31: =+N31*P31 -> 0 | S31: =+O31*Q31 -> 0 | T31: =+P31*R31 -> 0 | U31: =+Q31*S31 -> 0 | V31: =+R31*T31 -> 0
B32: =+IF($D$8>1,"Linea 2","") | D32: =+D12 -> 0 | H32: =+IF(F32>0,1-F32,"") | J32: =+J12*F32 -> 0 | N32: =-L32 -> 0 | P32: =+J12*L32+P12*(F32+L32) -> 0 | R32: =+F32+L32 -> 0 | S32: =+O32*Q32 -> 0 | T32: =+IF(R32>0,1-R32,"") | U32: =+Q32*S32 -> 0 | V32: =+R32*V12 -> 0
R33: =+N33*P33 -> 0 | S33: =+O33*Q33 -> 0 | T33: =+P33*R33 -> 0 | U33: =+Q33*S33 -> 0 | V33: =+R33*T33 -> 0
B34: =+IF($D$8>3,"Linea 3","") | D34: =+D14 -> 0 | H34: =+IF(F34>0,1-F34,"") | J34: =+J14*F34 -> 0 | N34: =-L34 -> 0 | P34: =+J14*L34+P14*(F34+L34) -> 0 | R34: =+F34+L34 -> 0 | S34: =+O34*Q34 -> 0 | T34: =+IF(R34>0,1-R34,"") | U34: =+Q34*S34 -> 0 | V34: =+R34*V14 -> 0
R35: =+N35*P35 -> 0 | S35: =+O35*Q35 -> 0 | T35: =+P35*R35 -> 0 | U35: =+Q35*S35 -> 0 | V35: =+R35*T35 -> 0
B36: =+IF($D$8>3,"Linea 4","") | D36: =+D16 -> 0 | H36: =+IF(F36>0,1-F36,"") | J36: =+J16*F36 -> 0 | N36: =-L36 -> 0 | P36: =+J16*L36+P16*(F36+L36) -> 0 | R36: =+F36+L36 -> 0 | S36: =+O36*Q36 -> 0 | T36: =+IF(R36>0,1-R36,"") | U36: =+Q36*S36 -> 0 | V36: =+R36*V16 -> 0
R37: =+N37*P37 -> 0 | S37: =+O37*Q37 -> 0 | T37: =+P37*R37 -> 0 | U37: =+Q37*S37 -> 0 | V37: =+R37*T37 -> 0
B38: =+IF($D$8>4,"Linea 5","") | D38: =+D18 -> 0 | H38: =+IF(F38>0,1-F38,"") | J38: =+J18*F38 -> 0 | N38: =-L38 -> 0 | P38: =+J18*L38+P18*(F38+L38) -> 0 | R38: =+F38+L38 -> 0 | S38: =+O38*Q38 -> 0 | T38: =+IF(R38>0,1-R38,"") | U38: =+Q38*S38 -> 0 | V38: =+R38*V18 -> 0
R39: =+N39*P39 -> 0 | S39: =+O39*Q39 -> 0 | T39: =+P39*R39 -> 0 | U39: =+Q39*S39 -> 0 | V39: =+R39*T39 -> 0
B40: Margine di Prodotto | F40: =+F6-F24 -> 0 | L40: =+R40-F40 -> 0 | R40: =+R6-R24 -> 0 | X40: =+R40/F40-1 -> #DIV/0!
R41: =+N41*P41 -> 0 | S41: =+O41*Q41 -> 0 | T41: =+P41*R41 -> 0 | U41: =+Q41*S41 -> 0 | V41: =+R41*T41 -> 0
B42: Costi variabili | D42: su un fatturato di | F42: =-BR!H115-BR!H122 -> 0 | L42: =SUM(R44:V52) -> 0 | R42: =+L42+F42 -> 0 | X42: =+R42/F42-1 -> #DIV/0!
R43: =+N43*P43 -> 0 | S43: =+O43*Q43 -> 0 | T43: =+P43*R43 -> 0 | U43: =+Q43*S43 -> 0 | V43: =+R43*T43 -> 0
B44: Provvigioni | F44: Incidenza sull'variazione di fatturato | N44: variazione costi | R44: =+L44*D44 -> 0
B46: Trasporti | F46: Incidenza sull'variazione di fatturato | N46: variazione costi | R46: =+L46*D46 -> 0
B48: Energia | F48: Incidenza sull'variazione di fatturato | N48: variazione costi | R48: =+L48*D48 -> 0
B50: Altri costi diretti industriali variabili | F50: Incidenza sull'variazione di fatturato | N50: variazione costi | R50: =+L50*D50 -> 0
B52: Altri costi diretti commerciali variabili | F52: Incidenza sull'variazione di fatturato | N52: variazione costi | R52: =+L52*D52 -> 0
R53: =+N53*P53 -> 0 | S53: =+O53*Q53 -> 0 | T53: =+P53*R53 -> 0 | U53: =+Q53*S53 -> 0 | V53: =+R53*T53 -> 0
B54: Costi Fissi | F54: =-BR!H116-BR!H118-BR!H119-BR!H123-BR!H124 -> 0 | L54: =+F58*H58+F60*H60+F64*H64+P66+SUM(R58:T64)+SUM(V58:X64)+F62*H62 -> 0 | R54: =+L54+F54 -> 0 | X54: =+R54/F54-1 -> #DIV/0!
R55: =+N55*P55 -> 0 | S55: =+O55*Q55 -> 0 | T55: =+P55*R55 -> 0 | U55: =+Q55*S55 -> 0 | V55: =+R55*T55 -> 0
D56: Costi | F56: D Dipendenti | H56: Costo Unitario Lordo | L56: Invest/Disinv. | N56: Al. Amm | P56: Var. Amm. | R56: Variazione Affitti e leasing | V56: Altre Variazioni costi
S57: =+O57*Q57 -> 0 | T57: =+P57*R57 -> 0 | U57: =+Q57*S57 -> 0 | W57: =+S57*U57 -> 0 | X57: =+T57*V57 -> 0
B58: Commerciali | D58: =-BR!H123 -> 0 | P58: =+L58*N58 -> 0
O59: =+K59*M59 -> 0
B60: Industriali | D60: =-BR!H116-BR!H118-BR!H120 -> 0 | P60: =+L60*N60 -> 0
O61: =+K61*M61 -> 0
B62: Manod'opera industriale | D62: =-BR!H119 -> 0
O63: =+K63*M63 -> 0
B64: Amministrativi e generali e vari | D64: =-BR!H124 -> 0 | P64: =+L64*N64 -> 0
S65: =+O65*Q65 -> 0 | T65: =+P65*R65 -> 0 | U65: =+Q65*S65 -> 0 | V65: =+R65*T65 -> 0
D66: =SUM(D58:D64) -> 0 | F66: =+F58*H58+F60*H60+F62*H62+F64*H64 -> 0 | L66: =SUM(L58:L64) -> 0 | P66: =SUM(P58:P64) -> 0 | R66: =+R58+R60+R64 -> 0 | V66: =+V58+V60+V64 -> 0
R67: =+N67*P67 -> 0 | S67: =+O67*Q67 -> 0 | T67: =+P67*R67 -> 0 | U67: =+Q67*S67 -> 0 | V67: =+R67*T67 -> 0
F68: % TFR | H68: Var Costo Pers. | L68: % TFR/COSTO PERS | N68: Fdo Iniziale | R68: Utilizzi | V68: FONDO FINALE
R69: =+N69*P69 -> 0 | S69: =+O69*Q69 -> 0 | T69: =+P69*R69 -> 0 | U69: =+Q69*S69 -> 0 | V69: =+R69*T69 -> 0
B70: Costo del Personale | D70: =-BR!H64 -> 103424.82 | F70: =+D72/D70 -> 0.022440648 | H70: =+F58*H58+F60*H60+F62*H62+F64*H64 -> 0 | N70: =+BR!H34 -> 1530.97 | V70: =+N70+L72-R70 -> 1530.97
S71: =+O71*Q71 -> 0 | T71: =+P71*R71 -> 0 | U71: =+Q71*S71 -> 0 | V71: =+R71*T71 -> 0
B72: Accantonamento TFR | D72: =-BR!H65 -> 2320.92 | L72: =-(+H70/(1+L70)-H70) -> 0 | P72: =+L72*N72 -> 0 | R72: Utilizzi
S73: =+O73*Q73 -> 0 | T73: =+P73*R73 -> 0 | U73: =+Q73*S73 -> 0 | V73: =+R73*T73 -> 0
B74: Altri Accantonamenti | D74: =-BR!H125 -> 0 | F74: Fondo In | H74: =-BR!H93-N70 -> 0 | L74: Accantonam. | V74: =+H74+N74-R74 -> 0
S75: =+O75*Q75 -> 0 | T75: =+P75*R75 -> 0 | U75: =+Q75*S75 -> 0 | V75: =+R75*T75 -> 0
B76: Altri Accantonamenti | F76: =-BR!H125 -> 0 | L76: =+R76-F76 -> 0 | R76: =+N74 -> 0 | X76: =+R76/F76-1 -> #DIV/0!
B78: GESTIONE FINANZIARIA | F78: =BR!H127 -> 0 | L78: =-(N110)-N112 -> 0 | R78: =+F78+L78 -> 0 | X78: =+R78/F78-1 -> #DIV/0!
R79: =+N79*P79 -> 0 | S79: =+O79*Q79 -> 0 | T79: =+P79*R79 -> 0 | U79: =+Q79*S79 -> 0 | V79: =+R79*T79 -> 0
B80: GESTIONE NON OPERATIVA E STRAORD | F80: =BR!H129 -> 0 | R80: =+F80+L80 -> 0 | X80: =+R80/F80-1 -> #DIV/0!
D84: Giorni di Rotazione | F84: Valori | H84: Var. Giorni | J84: Giorni | L84: Base di calcolo (Ricavi e Costi ) | T84: Valori Budget | X84: D
B86: Giorni medi di incasso / Crediti clienti | D86: =+IF(D22=0,0,BR!H88/D22*365) -> 0 | F86: =+D22/365*D86 -> 0 | J86: =+D86+H86 -> 0 | L86: Ricavi | P86: =+R6 -> 0 | T86: =+P86/365*J86 -> 0 | X86: =+T86-F86 -> 0
B88: Giorni medi di rotazione / Magazzino | D88: =+IF(BR!H110=0,0,BR!H87/BR!H110*365) -> 0 | F88: =+F6/365*D88 -> 0 | J88: =+D88+H88 -> 0 | L88: Ricavi | P88: =+P86 -> 0 | T88: =+P88/365*J88 -> 0 | X88: =+T88-F88 -> 0
B90: Giorni medi di pagamento / Debiti fornitori | D90: =-IF(BR!H57=0,0,BR!H40/(BR!H57+BR!H60+BR!H61)*365) -> 34.547895 | F90: =+BR!H40 -> 60246.41 | J90: =+D90+H90 -> 34.547895 | L90: Costi | P90: =+L54+L42+L26-BR!H57-BR!H60-BR!H61-F66 -> 636505.92 | T90: =+P90/365*J90 -> 60246.41 | X90: =+T90-F90 -> 0
S91: =+O91*Q91 -> 0 | T91: =+P91*R91 -> 0 | U91: =+Q91*S91 -> 0
B92: VARIAZIONI FINANZIARIE
B94: POSIZIONE FIN. INIZIALE | D94: =-BR!H102 -> 117412.54 | X94: =-BR!H102 -> 117412.54
B96: UTILE ANTE OF AMM. E ACC. | D96: =+BR!H131-BR!H127-BR!H67-BR!H125+L40-L42-L54+P66+L80+L72 -> 7933.67 | X96: =+BR!H78-(BR!H70-BR!H71)-BR!H67 -> 128276.4
B98: D Capitale di giro | D98: =-X86-X88+X90-R70 -> 0 | X98: =-(BR!H92-BR!F92) -> 36095.33
S99: =+O99*Q99 -> 0 | T99: =+P99*R99 -> 0 | U99: =+Q99*S99 -> 0
B100: Variazione Fondi | D100: =-R74 -> 0
S101: =+O101*Q101 -> 0 | T101: =+P101*R101 -> 0 | U101: =+Q101*S101 -> 0
B102: Altri Pagamenti/Incassi
S103: =+O103*Q103 -> 0 | T103: =+P103*R103 -> 0 | U103: =+Q103*S103 -> 0
B104: INVESTIMENTI | D104: =-L66 -> 0 | X104: =+BR!F11-BR!H11+BR!H67 -> -96687.25
S105: =+O105*Q105 -> 0 | T105: =+P105*R105 -> 0 | U105: =+Q105*S105 -> 0
B106: VARIAZIONE DI CASSA OPERATIVA | D106: =SUM(D96:D104) -> 7933.67 | X106: =SUM(X96:X104) -> 67684.48
S107: =+O107*Q107 -> 0 | T107: =+P107*R107 -> 0 | U107: =+Q107*S107 -> 0
B108: Variazioni Mezzi Propri | L108: Maggior Oneri finanziari | X108: =+BR!H99-BR!F99-BR!H98 -> 10000
S109: =+O109*Q109 -> 0 | T109: =+P109*R109 -> 0 | U109: =+Q109*S109 -> 0
B110: Accensioni (Pagamento) debiti finanziari | F110: Tasso Medio sul lungo periodo | N110: =+D110*L110*(1+L110) -> 0 | X110: =+BR!F103+BR!F104-BR!H103-BR!H104 -> -33897.74
B112: VARIAZIONE PFN (ante o.fin.) | D112: =SUM(D106:E110) -> 7933.67 | F112: Tasso Medio sul breve periodo | N112: =-D112*L112-D112*L112^2-D112*L112^3-D112*L112^4 -> 0 | X112: =+X106+X108 -> 77684.48
S113: =+O113*Q113 -> 0 | T113: =+P113*R113 -> 0 | U113: =+Q113*S113 -> 0
B114: Oneri Finanziari | D114: =R78 -> 0 | X114: =+BR!J127 -> 0
S115: =+O115*Q115 -> 0 | T115: =+P115*R115 -> 0 | U115: =+Q115*S115 -> 0
B116: POSIZIONE FIN. FINALE | D116: =+D112+D114+D94 -> 125346.21 | X116: =+X94+X106+X108+X110+X114 -> 161199.28
S117: =+O117*Q117 -> 0 | T117: =+P117*R117 -> 0 | U117: =+Q117*S117 -> 0
B118: Imposte | F118: =BR!H77 -> -56008 | L118: =-(+X120+X122) -> 0 | R118: =+F118+L118 -> -56008 | X118: =+IF(F118=0,"",R118/F118-1) -> 0
B120: ALIQUOTA IRES | D120: 0.24 | F120: Var . Imponibile Ires | J120: =+L40-L42-L54-L76+L78+L80 -> 0 | L120: Riprese in aumento/dim | T120: VAR. IRES | X120: =+(J120+P120)*D120 -> 0
B122: ALIQUOTA IRAP | D122: 0.039 | F122: Var . Imponibile Ires | J122: =+J120+F66+L76-L78 -> 0 | L122: Riprese in aumento/dim | T122: VAR. IRAP | X122: =+(J122+P122)*D122 -> 0
B124: Conto economico previsionale | C124: =C88 -> 0 | D124: =+D6 -> 45657 | E124: =E88 -> 0 | F124: Budget | L124: Stato Patrimoniale | P124: =+D124 -> 45657 | R124: Budget | V124: Var | Z124: =+P124 -> 45657
B125: CONTO ECONOMICO GESTIONALE | L125: ATTIVO
...

Sheet TAB
B1: COD CEE
B2: =BR!A6 -> 10
B3: =BR!A7 -> 12
B4: =BR!A8 -> 20
B5: =BR!A9 -> 22
B6: =BR!A10 -> 30
B7: =BR!A11 -> 35
B8: =BR!A12 -> 40
B9: =BR!A13 -> 50
B10: =BR!A14 -> 52
B11: =BR!A15 -> 54
B12: =BR!A16 -> 60
B13: =BR!A18 -> 70
B14: =BR!A19 -> 80
B15: =BR!A20 -> 85
B16: =BR!A21 -> 89
B17: =BR!A24 -> 90
B18: =BR!A25 -> 100
B19: =BR!A26 -> 110
B20: =BR!A27 -> 120
B21: =BR!A28 -> 130
B22: =BR!A29 -> 140
B23: =BR!A31 -> 145
B24: =BR!A32 -> 150
B25: =BR!A33 -> 160
B26: =BR!A34 -> 170
B27: =BR!A35 -> 180
B28: =BR!A36 -> 190
B29: =BR!A37 -> 192
B30: =BR!A38 -> 195
B31: =BR!A39 -> 200
B32: =BR!A40 -> 210
B33: =BR!A41 -> 220
B34: =BR!A42 -> 230
B35: =+BR!A43 -> 232
B36: =+BR!A44 -> 234
B37: =BR!A45 -> 0
B38: =BR!A46 -> 245
B39: =BR!A48 -> 249
B40: =BR!A52 -> 300
B41: =BR!A53 -> 310
B42: =BR!A54 -> 315
B43: =BR!A55 -> 320
B44: =BR!A56 -> 325
B45: =BR!A57 -> 330
B46: =BR!A58 -> 340
B47: =BR!A59 -> 355
B48: =BR!A60 -> 360
B49: =BR!A61 -> 370
B50: =BR!A62 -> 380
B51: =BR!A63 -> 385
... B55: =BR!A67 -> 410
B56: =BR!A69 -> 415
B57: =BR!A70 -> 420
B58: =BR!A71 -> 430
B59: =BR!A72 -> 432
B60: =BR!A73 -> 435
B61: =BR!A74 -> 440
B62: =BR!A75 -> 450
B63: =BR!A76 -> 455
B64: =BR!A77 -> 460
