Workbook
Name AC: REPT(CHAR(10),2)
Name Data: Relazione!$L$4
Name p: +CHAR(149)& " "
Name pu: ". "
Name s: " "
Name v: ", "

Sheet Check list
B8: 1 | C8: Il requisito dell’organizzazione dell’impresa | I8: Note | J8: Se presente, da compilare | L8: Frase SI | M8: Frase No | N8: Frase scelta | O8: Suggerimento
C10: 1.1 | E10: L’impresa dispone delle risorse chiave (umane e tecniche) per la conduzione dell’attività? | G10: NO | I10: =+IF(G10="NO","L’impresa come pensa di procurarsi tali risorse?","") -> L’impresa come pensa di procurarsi tali risorse? | L10: L’impresa dispone delle risorse chiave (umane e tecniche) per la conduzione dell’attività. | M10: L’impresa non dispone delle risorse chiave (umane e tecniche) per la conduzione dell’attività. Per questo motivo intende sviluppare le seguenti azioni: | N10: =+IF(G10="NO",M10,N10) -> L’impresa non dispone delle risorse chiave (umane e tecniche) per la conduzione dell’attività. Per questo motivo intende sviluppare le seguenti azioni: | O10: =+IF(G10="NO","Compilare spiegando: ",N10) -> Compilare spiegando:
C12: 1.2 | E12: L’impresa dispone delle competenze tecniche occorrenti per le iniziative industriali che l’imprenditore intende adottare? | G12: NO | I12: =+IF(G12="NO","Indicare le iniziative industriali per le quali l'impresa sia realisticamente in grado di disporre, eventualmente acquisendole sul mercato, delle competenzetecniche occorrenti:","") -> Indicare le iniziative industriali per le quali l'impresa sia realisticamente in grado di disporre, eventualmente acquisendole sul mercato, delle competenzetecniche occorrenti: | L12: Per quanto concerne le competenze tecniche la dotazione può considerarsi adeguata rispetto alle iniziative che l'impresa intende adottare. | M12: Considerate le iniziative che l'impresa intende adottare le competenze tecniche risultano inadeguate. Pertanto, verranno adottate le iniziative di seguito descritte. | N12: =+IF(G12="NO",M12,N12) -> Considerate le iniziative che l'impresa intende adottare le competenze tecniche risultano inadeguate. Pertanto, verranno adottate le iniziative di seguito descritte.
C14: 1.3 | E14: L’impresa ha predisposto un monitoraggio continuativo dell’andamento aziendale? | G14: NO | I14: =+IF(G14="NO","L’impresa ha quanto meno attivato il confronto con i dati di andamento del precedente esercizio, in termini di ricavi, portafogli ordini, costi e posizione finanziaria netta?","") -> L’impresa ha quanto meno attivato il confronto con i dati di andamento del precedente esercizio, in termini di ricavi, portafogli ordini, costi e posizione finanziaria netta? | K14: NO | L14: L’impresa ha predisposto un monitoraggio continuativo dell’andamento aziendale.
L15: Ha tuttavia attivato il confronto con i dati di andamento del precedente esercizio, in termini di ricavi, portafogli ordini, costi e posizione finanziaria netta
C16: 1.4 | E16: L’impresa è in grado di stimare l’andamento gestionale anche ricorrendo ad indicatori chiave gestionali (KPI) che consentano valutazioni rapide in continuo? | G16: NO | I16: =+IF(G16="NO","L’impresa è in grado di individuare gli indicatori di produttività coerenti con il proprio modello di business ed il proprio settore di attività, e di raccogliele ulteriori informazioni per la valutazione dell’andamento tendenziale?","") -> L’impresa è in grado di individuare gli indicatori di produttività coerenti con il proprio modello di business ed il proprio settore di attività, e di raccogliele ulteriori informazioni per la valutazione dell’andamento tendenziale? | K16: NO
C18: 1.5 | E18: L’impresa dispone di un piano di tesoreria a 6 mesi? | G18: NO | I18: =+IF(G18="NO","L’impresa è in grado di predisporre un prospetto delle stime delle entrate e delle uscite finanziare almeno a 13 settimane, il cui scostamento con l’andamento corrente dovrà essere valutato a consuntivo?","") -> L’impresa è in grado di predisporre un prospetto delle stime delle entrate e delle uscite finanziare almeno a 13 settimane, il cui scostamento con l’andamento corrente dovrà essere valutato a consuntivo? | K18: NO
B20: 2 | C20: Rilevazione della situazione contabile e dell’andamento corrente
C22: 2.1 | E22: L’impresa dispone di una situazione contabile recante le rettifiche di competenza e gli assestamenti di chiusura, nel rispetto del principio contabile OIC 30, quanto più possibile aggiornata e comunque non anteriore di oltre 120 giorni? | G22: NO | I22: =+IF(G22="NO","L’imprenditore è in grado di redigerla quale presupposto necessario per la predisposizione del piano?"&" La situazione contabile dovrà essere aggiornata all’occorrenza nel corso delle trattative anche per accertare le cause di eventuali scostamenti rispetto alle attese","") -> L’imprenditore è in grado di redigerla quale presupposto necessario per la predisposizione del piano? La situazione contabile dovrà essere aggiornata all’occorrenza nel corso delle trattative anche per accertare le cause di eventuali scostamenti rispetto alle attese
C24: 2.2 | E24: La situazione debitoria è completa ed affidabile? Il valore contabile dei cespiti non è superiore al maggiore trail valore recuperabile e quelli di mercato? | G24: NO | I24: =+IF(G24="NO","L'impresa intende quanto meno appostare con prudenza adeguati fondi rischi e fondi per l’adeguamento delle attività e delle passività?","") -> L'impresa intende quanto meno appostare con prudenza adeguati fondi rischi e fondi per l’adeguamento delle attività e delle passività?
C26: 2.3 | E26: È disponibile un prospetto recante l’anzianità dei crediti commerciali e le cause del ritardo di incasso tale daconsentire una valutazione oggettiva dei rischi di perdite sui crediti e una stima prudente dei tempi di incasso? | G26: NO | I26: =+IF(G26="NO","I crediti commerciali siano suddivisi in relazione alla loro anzianità?"&" Per gli scaduti che superano la fisiologia (tempi ordinari di pagamento, pur oltre la scadenza contrattuale, che caratterizzano il settore), la stima del momento dell’incasso è particolarmente prudente?","") -> I crediti commerciali siano suddivisi in relazione alla loro anzianità? Per gli scaduti che superano la fisiologia (tempi ordinari di pagamento, pur oltre la scadenza contrattuale, che caratterizzano il settore), la stima del momento dell’incasso è particolarmente prudente?
C28: 2.4 | E28: È disponibile un prospetto recante le rimanenze di magazzino con i tempi di movimentazione che consenta di individuare le giacenze oggetto di lenta rotazione? | G28: NO | I28: =+IF(G28="NO","L’imprenditore isola le giacenze di magazzino a lenta rotazione per consentire una stima corretta degli approvvigionamenti necessari?","") -> L’imprenditore isola le giacenze di magazzino a lenta rotazione per consentire una stima corretta degli approvvigionamenti necessari?
C30: 2.5 | E30: I debiti risultanti dalla contabilità sono riconciliati con quanto risultante dal certificato unico dei debiti tributari,dalla situazione debitoria complessiva dell’Agente della Riscossione, dal certificato dei debiti contributivi e perpremi assicurativi e dall’estratto della Centrale Rischi? | G30: NO | I30: =+IF(G30="NO","L'imprenditore intende individuare le cause delle differenze significative?","") -> L'imprenditore intende individuare le cause delle differenze significative?
C32: 2.6 | E32: Si è tenuto adeguatamente conto dei rischi di passività potenziali, anche derivanti dalle garanzie concesse? | G32: NO | I32: =+IF(G32="NO","L'imprenditore, anche con l’aiuto dei professionisti che assistono l’impresa, ha intenzione di stimare entità e momento del pagamento di eventuali passività potenziali?","") -> L'imprenditore, anche con l’aiuto dei professionisti che assistono l’impresa, ha intenzione di stimare entità e momento del pagamento di eventuali passività potenziali?
C34: 2.7 | E34: L’organo di controllo ed il revisore legale, quando in carica, dispongono di informazioni in base alle quali la situazione contabile di cui al punto 2.1. risulti inaffidabile o inadeguata per la redazione di un piano affidabile? | G34: NO | I34: =+IF(G34="SI","L’imprenditore ha intenzione di rimuovere le criticità quanto meno con l’appostazione di passività ulteriori o rettificando i flussi economico-finanziari attesi?","")
C36: 2.8 | E36: Sono disponibili informazioni sull’andamento corrente in termini di ricavi, portafoglio ordini, costi e flussi finanziari? È disponibile un confronto con lo stesso periodo del precedente esercizio? | G36: NO
B38: 3 | C38: Individuazione delle strategie di intervento atte a rimuovere le cause della crisi
C39: 3.1.1 | E39: Perché l’imprenditore ha percepito uno stato di crisi o uno squilibrio patrimoniale o economico-finanziario che la rende probabile? | F39: Scrivere risposta nella cella accanto
C40: 3.1.2 | E40: Quali sono le manifestazioni esteriori di tale stato | F40: Scrivere risposta nella cella accanto
C41: 3.2.1 | E41: Tenuto conto delle manifestazioni sub 3.1, quali ne sono le cause? | F41: Scrivere risposta nella cella accanto
C43: 3.2.2 | E43: Sono state individuate cause coerenti con le manifestazioni esteriori dello stato di crisi o dello squilibrio patrimoniale o economico-finanziario che la rende probabile? | G43: NO | I43: =+IF(G43="NO","L'imprenditore ha intensione di predisporre la comparazione storica degli stati patrimoniali e dei conti economici di un numero adeguato di anni?"&" la comparazione dei dati economici dovrebbe essere svolta anche sulla base dei rendiconti gestionali, sedisponibili."&" Da tale comparazione l’esperto, anche attraverso l’intervista delle principali funzioni aziendali (commerciale, operativa, risorse umane, contabile), si forma il convincimento sulle cause del declino dell’andamento aziendale","") -> L'imprenditore ha intensione di predisporre la comparazione storica degli stati patrimoniali e dei conti economici di un numero adeguato di anni? la comparazione dei dati economici dovrebbe essere svolta anche sulla base dei rendiconti gestionali, sedisponibili. Da tale comparazione l’esperto, anche attraverso l’intervista delle principali funzioni aziendali (commerciale, operativa, risorse umane, contabile), si forma il convincimento sulle cause del declino dell’andamento aziendale
C46: 3.3 | E46: L’organo di controllo ed il revisore, quando in carica, ritengono che il quadro fornito dall’imprenditore sia completo e adeguato? | G46: SI
C48: 3.4.1 | E48: Quali sono le strategie di intervento e quali le iniziative industriali che l’imprenditore intende adottare? | F48: Scrivere risposta nella cella accanto
C49: 3.4.2 | E49: Nel caso in cui l’imprenditore non sia in grado di individuarle, quali sono le strategie adottate dalle imprese concorrenti che hanno maggiore successo? | F49: Scrivere risposta nella cella accanto
C51: 3.4.3 | E51: Nel caso in cui l’imprenditore non sia in grado di individuarle, le strategie adottate dalle imprese concorrenti che hanno maggiore successo sono replicabili dall’imprenditore? | G51: SI
C53: 3.5 | E53: L’impresa dispone delle capacità e delle competenze manageriali per realizzare le iniziative industriali? | G53: SI
C55: 3.6.1 | E55: Quali sono i tempi e i relativi effetti in termini di ricavi, di costi e di investimenti delle iniziative da adottare? | F55: Scrivere risposta nella cella accanto
C56: 3.6.2 | E56: Quali sono le relative funzioni aziendali responsabili? | F56: Scrivere risposta nella cella accanto
C58: 3.7 | E58: Sono prospettabili iniziative alternative nel caso in cuI le iniziative dovessero dimostrarsi inefficaci e si manifestassero scostamenti tra gli obiettivi pianificati e quelli raggiunti? | G58: SI
C60: 3.8.1 | E60: In precedenza sono stati predisposti ulteriori piani? | G60: SI
C62: 3.8.2 | E62: Il piano è coerente con i piani redatti in precedenza? | G62: SI
C64: 3.8.3 | E64: Quali sono le differenze? | F64: Scrivere risposta nella cella accanto
C65: 3.8.4 | E65: Nel caso ve ne siano, a cosa sono dovute? | F65: Scrivere risposta nella cella accanto
C67: 3.9.1 | E67: Il piano appare credibile? Il piano è fondato su intenzioni strategiche chiare e razionali, condivisibili da parte diun lettore informato quale è l’esperto, coerenti con la situazione di fatto dell’impresa e del contesto in cuiopera? | G67: SI
C69: 3.9.2 | E69: Le strategie di intervento e le iniziative industriali individuate dall’imprenditore appaiono appropriateper il superamento delle cause della crisi? E in caso contrario quali sarebbero quelle da adottare? | G69: NO | I69: =+IF(G69="NO","Quali sarebbero quelle da adottare?","") -> Quali sarebbero quelle da adottare?
I70: =+IF(I69="","","Scrivere risposta nella cella accanto") -> Scrivere risposta nella cella accanto
B72: 4 | C72: Le proiezioni dei flussi finanziari
C73: 4.1 | E73: La stima delle proiezioni dei flussi finanziari del piano è, salvo deroghe giustificate dalla tipologia dell’impresa o dall’attività svolta, l’esito di un percorso che si dipana in ordinate fasi successive così articolate:
D74: 4.1.1 | E74: stima dei ricavi (punto. 4.3 della presente Sezione) | F74: Inserire importo nella cella accanto
D75: 4.1.2 | E75: stima dei costi variabili correlati ai ricavi (punto. 4.4 della presente Sezione) | F75: Inserire importo nella cella accanto
D76: 4.1.3 | E76: stima dei costi fissi (punto 4.4 della presente Sezione) | F76: Inserire importo nella cella accanto
D77: 4.1.4 | E77: stima degli investimenti (punto 4.6 della presente Sezione) | F77: Inserire importo nella cella accanto
D78: 4.1.5 | E78: stima degli effetti delle iniziative industriali che si intendono intraprendere in discontinuità rispetto al passato (punto 4.7 della presente Sezione) | F78: Inserire importo nella cella accanto
D80: 4.1.6 | E80: I dati economici prognostici sono coerenti (punto 4.8 della presente Sezione)? | G80: NO | I80: =+IF(G80="NO","Perché è giustificata la mancata coerenza?","") -> Perché è giustificata la mancata coerenza?
I81: =+IF(I80="","","Scrivere risposta nella cella accanto") -> Scrivere risposta nella cella accanto
D82: 4.1.7 | E82: stima dell’effetto delle operazioni straordinarie, se previste (punto 4.9 della presente Sezione) | F82: Inserire importo nella cella accanto
D83: 4.1.8 | E83: stima del pagamento delle imposte sul reddito (punto 4.10 della presente Sezione) | F83: Inserire importo nella cella accanto
D84: 4.1.9 | E84: declinazione finanziaria delle grandezze economiche e determinazione dei flussi al servizio del debito (punto 4.11 della presente Sezione) | F84: Inserire importo nella cella accanto
D85: 4.1.10 | E85: declinazione patrimoniale muovendo dalla situazione contabile di partenza (punto 4.12 della presente Sezione) | F85: Inserire importo nella cella accanto
C87: 4.2 | E87: Le proiezioni fondate su previsioni coprono un periodo massimo di 5 anni a meno che un arco temporalesuperiore sia giustificato? | G87: NO | I87: =+IF(G87="NO","Perché è giustificato un maggior arco temporale?","") -> Perché è giustificato un maggior arco temporale?
I88: =+IF(I87="","","Scrivere risposta nella cella accanto") -> Scrivere risposta nella cella accanto
C89: 4.3 | E89: Le proiezioni dei ricavi sono coerenti con i dati storici e quelli correnti? | G89: NO
D91: 4.3.1 | E91: Le variazioni dei ricavi prospettici rispetto al dato corrente dell’esercizio in corso devono essere giustificate | F91: Inserire importo nella cella accanto
D93: 4.3.2 | E93: Le variazioni dei ricavi del piano sono state confrontate con le prospettive del settore? | G93: SI
C95: 4.4.1 | E95: La stima dei costi variabili e dei costi di struttura è coerente con la situazione in atto e con i dati storici? | G95: SI
C97: 4.4.2 | E97: Quali sono i risparmi dei costi variabili e fissi e come l’imprenditore intende conseguirli? | F97: Inserire importo nella cella accanto
C98: 4.4.3 | E98: Quali sono i possibili rischi che derivano dai risparmi di costo e come intende mitigarli l’imprenditore? | F98: Inserire importo nella cella accanto
C100: 4.5 | E100: La società svolge più attività? | G100: SI | I100: =+IF(G100="SI","La stima dei costi e dei ricavi è stata effettuata separatamente per ciascuna di esse?","") -> La stima dei costi e dei ricavi è stata effettuata separatamente per ciascuna di esse? | K100: SI
C102: 4.6 | E102: Il piano tiene conto in misura adeguata degli investimenti di mantenimento occorrenti? | G102: SI | I102: L’ammontare degli investimenti di mantenimento previsti nel piano è coerente con quello del passato? | K102: SI
C104: 4.7 | E104: La stima degli effetti dellE iniziative industrialI che l’imprenditore intende intraprendere (in termini di investimenti, ricavi e costi) è coerente con le informazioni disponibili ed è ritenuta giustificata dalle diversefunzioni aziendali? | G104: SI
C106: 4.8 | E106: È stata svolta una verifica di ragionevolezza della redditività prospettica quale risulta dai paragrafi precedenti? | G106: SI
D108: 4.8.1 | E108: La redditività ed i principali indicatori chiave gestionali (KPI) prospettici, prima dell’effetto delle iniziative di cui al punto 4.7 della presente Sezione, sono coerenti con l’andamento storico? | G108: SI
D110: 4.8.2 | E110: E' giustificata ogni differenza tra l’incidenza del margine operativo lordo sui ricavi, anche a seguito delle iniziative di cui al punto 4.7 della presente Sezione, ed i benchmark di mercatodisponibili? | G110: SI
C112: 4.9 | E112: Se è stata prevista la dismissione di cespiti d'investimento, si è tenuto conto delle effettive prospettive di realizzo in termini di ammontare (al netto dei costi di dismissione) e tempi? | G112: SI | I112: =+IF(G112="SI","Le relative stime sono adeguatamente suffragate?","") -> Le relative stime sono adeguatamente suffragate? | K112: SI
C114: 4.10 | E114: Nella stima del pagamento delle imposte si è tenuto conto dell’effetto delle perdite fiscali a nuovo e delperiodo di imputazione fiscale dei costi e dei ricavi? | G114: SI
C116: 4.11 | E116: La determinazione dei flussi finanziari al servizio del debito deve essere effettuata muovendo dai dati economici. Essa può avere luogo:
D117: 4.11.1 | E117: Attraverso il ciclo di conversione in flussi di cassa che tiene conto dei tempi di incasso dei ricavi, di pagamento dei costi e di rigiro del magazzino. I tempi sono coerenti con la serie storica dell’impresa? | G117: SI
D119: 4.11.2 | E119: Sono stati dedotti dai flussi così determinati gli investimenti previsti (sia quelli di mantenimento che quellirelativi alle iniziative industriali) e il pagamento delle imposte? | G119: SI
D121: 4.11.3 | E121: Sono state portate in conto l’effetto delle dismissioni di cespiti d’investimento e di altre operazioni straordinarie previste?
D123: 4.11.4 | E123: L'impresa è considerata tra le micro e piccole imprese? | G123: SI | I123: =+IF(G123="SI","Sono state comunque poste in essere le seguenti operazioni: (i) verifica che l’ammontare degli investimenti di mantenimento sia adeguatamente espresso dagli"&" ammortamenti (portando una rettifica in caso contrario); (ii) portato in conto l’effetto delle iniziative industriali previste; (iii) tenuto conto della dismissione di cespiti e delle operazioni straordinarie programmate?","") -> Sono state comunque poste in essere le seguenti operazioni: (i) verifica che l’ammontare degli investimenti di mantenimento sia adeguatamente espresso dagli ammortamenti (portando una rettifica in caso contrario); (ii) portato in conto l’effetto delle iniziative industriali previste; (iii) tenuto conto della dismissione di cespiti e delle operazioni straordinarie programmate? | K123: SI
C125: 4.12 | E125: È opportuno che, muovendo dalle stime economiche e finanziarie, vengano determinate anche le grandezze patrimoniali. Su di esse si innesteranno le proposte alle parti interessate di cui al successivo punto 5.5 dellapresente Sezione e viene calcolata la stima dell’andamento del patrimonio netto l termine dei singoli anni delpiano | G125: SI
B127: 5 | C127: Il risanamento del debito
C128: 5.1 | E128: L’impresa, alla luce del par. 4 della presente Sezione, è in grado in futuro di generare risorse al servizio deldebito ed il risultato delle proiezioni finanziarie di cui al punto 4.10 della presente Sezione tende ad esserepositivo? | G128: SI
C129: 5.2 | E129: Il piano tiene conto, anche attraverso prove di resistenza (stress test), dei fattori di rischio e di incertezza aiquali è maggiormente esposta l’impresa? È opportuno che tali prove siano coerenti con i rischi emersi ad esitodell’intervista delle diverse funzioni aziendali e comunque avendo riguardo alle prospettive di mercato | G129: SI
C130: 5.3 | E130: La generazione di flussi positivi al servizio del debito dipende solo dalle iniziative industriali? In casoaffermativo, è opportuno che l’esito atteso delle iniziative industriali sia sottoposto a prove di resistenza (stresstest) specifiche | G130: SI
C131: 5.4 | E131: A quanto ammonta il debito che deve essere servito nei singoli anni del piano? Il debito da servire corrisponde a:- debito scaduto;- debito già riscadenziato o differito;- debito interessato da moratorie ex lege;- linee di credito bancarie utilizzate delle quali non ci si attende il rinnovo;- rate di mutuo e finanziamenti in scadenza. | G131: SI
C132: 5.5 | E132: Come l’imprenditore intende fronteggiare il debito che deve essere coperto nei diversi anni attraverso i flussi al servizio dello stesso? | G132: SI | I132: Impatto nelle singole annualità del piano di risanamento delle proposte alle parti interessate quali (una possibile tipologia è riportata nell’Allegato 1): - nuovi riscadenziamenti o dilazione di una parte del debito pendente; - stralcio di parte del debito; - la sua conversione in equity o in strumenti finanziari partecipativi; - nuove linee di credito; - nuovi aumenti di capitale sociale a pagamento e nuovi finanziamenti anche postergati.
C133: 5.6 | E133: Le proposte consentono, in via prognostica, il rispetto del minimo legale del capitale sociale al momento dellaconclusione dell’accordo, fatte salve le disposizioni speciali? | G133: SI
B135: 6 | C135: In caso di gruppi di imprese.
C136: 6.1 | E136: Il piano è redatto per le singole imprese? | G136: SI
C137: 6.2 | E137: Il piano dà evidenza dei rapporti economici, finanziari e patrimoniali infragruppo? | G137: SI
C138: 6.3 | E138: Vi sono altre imprese del gruppo che presentano difficoltà economico-finanziarie o patrimoniali? Come siintende agire per affrontarle? | G138: SI
C139: 6.4 | E139: Quali sono le altre imprese del gruppo la cui continuità aziendale dipende da quella dell’impresa? | G139: SI
C140: 6.5 | E140: Le operazioni infragruppo previste nel piano possono arrecare un pregiudizio per i creditori di un’altra impresadel gruppo? | G140: SI

Sheet SEZIONI 1-2
C2: Istruzioni: Spuntare i riquadri appositi di ogni sezione e compilare le colonne azzurre se ritenuto necessario.
A3: Nome Impresa | C3: Alpha SPA
A5: Data Verifica | D5: Firmata da
A8: 1 | D8: Il requisito dell’organizzazione dell’impresa | H8: Frase VERO | I8: Frase FALSO | J8: Frase suggerimento per commenti in caso di risposta positiva | K8: Frase suggerimento per commenti in caso di risposta negativa | L8: Frase Completa | M8: Suggerimento
C9: 1.1 | E9: L’impresa dispone delle risorse chiave (umane e tecniche) per la conduzione dell’attività? | F9: TRUE | H9: L’impresa dispone delle risorse chiave (umane e tecniche) per la conduzione dell’attività. | I9: L’impresa non dispone delle risorse chiave (umane e tecniche) per la conduzione dell’attività. | J9: Aggiungere eventuali commenti | K9: L’impresa come pensa di procurarsi tali risorse? | L9: =+OFFSET(F9,0,IF(F9,2,3)) -> L’impresa dispone delle risorse chiave (umane e tecniche) per la conduzione dell’attività. | M9: =+OFFSET(F9,0,IF(F9,4,5)) -> Aggiungere eventuali commenti
C10: 1.2 | E10: L’impresa dispone delle competenze tecniche occorrenti per le iniziative industriali che l’imprenditore intende adottare? | F10: TRUE | H10: Da un punto di vista tecnico/economico, l’impresa dispone delle competenze necessarie per le iniziative industriali che l’imprenditore intende adottare. | I10: Da un punto di vista tecnico/economico, l’impresa non dispone delle competenze necessarie per le iniziative industriali che l’imprenditore intende adottare. | J10: Aggiungere eventuali commenti | K10: Indicare le iniziative industriali per le quali l'impresa sia realisticamente in grado di disporre, eventualmente acquisendole sul mercato, delle competenze tecniche occorrenti: | L10: =+OFFSET(F10,0,IF(F10,2,3)) -> Da un punto di vista tecnico/economico, l’impresa dispone delle competenze necessarie per le iniziative industriali che l’imprenditore intende adottare. | M10: =+OFFSET(F10,0,IF(F10,4,5)) -> Aggiungere eventuali commenti
C11: 1.3 | E11: L’impresa ha predisposto un monitoraggio continuativo dell’andamento aziendale? | F11: TRUE | H11: Il sistema informativo aziendale prevede un adeguato sistema di monitoraggio continuo dell'andamento aziendale. | I11: Il monitoraggio dell'andamento aziendale appare inadeguato. | J11: Aggiungere eventuali commenti | K11: Indicare cosa intende fare per controllare la gestione | L11: =+OFFSET(F11,0,IF(F11,2,3)) -> Il sistema informativo aziendale prevede un adeguato sistema di monitoraggio continuo dell'andamento aziendale. | M11: =+OFFSET(F11,0,IF(F11,4,5)) -> Aggiungere eventuali commenti
E12: L’impresa ha attivato il confronto con i dati di andamento del precedente esercizio, in termini di ricavi? | F12: TRUE | H12: I ricavi sono costantemente monitorati. | I12: I ricavi non sono controllati in maniera adeguata. | J12: Aggiungere eventuali commenti | K12: Indicare quale controllo viene fatto e come si intende intervenire per migliorare il sistema di controllo. | L12: =+OFFSET(F12,0,IF(F12,2,3)) -> I ricavi sono costantemente monitorati. | M12: =+OFFSET(F12,0,IF(F12,4,5)) -> Aggiungere eventuali commenti
E13: L’impresa ha quanto meno attivato il confronto con i dati di andamento del precedente esercizio, in termini di portafogli ordini ? | F13: TRUE | H13: Gli ordini sono costantemente monitorati. | I13: Gli ordini non sono controllati in maniera adeguata. | J13: Aggiungere eventuali commenti | K13: Indicare quale controllo viene fatto e come si intende intervenire per migliorare il sistema di controllo. | L13: =+OFFSET(F13,0,IF(F13,2,3)) -> Gli ordini sono costantemente monitorati. | M13: =+OFFSET(F13,0,IF(F13,4,5)) -> Aggiungere eventuali commenti
E14: L’impresa ha quanto meno attivato il confronto con i dati di andamento del precedente esercizio, in termini di Posizione Finanziaria Netta? | F14: FALSE | H14: La posizione finanziaria netta è costantemente monitorata. | I14: La posizione finanziaria netta non è costantemente monitorata. | J14: Aggiungere eventuali commenti | K14: Indicare quale controllo viene fatto e come si intende intervenire per migliorare il sistema di controllo. | L14: =+OFFSET(F14,0,IF(F14,2,3)) -> La posizione finanziaria netta non è costantemente monitorata. | M14: =+OFFSET(F14,0,IF(F14,4,5)) -> Indicare quale controllo viene fatto e come si intende intervenire per migliorare il sistema di controllo.
C15: 1.4 | E15: L’impresa è in grado di stimare l’andamento gestionale anche ricorrendo ad indicatori chiave gestionali (KPI) che consentano valutazioni rapide in continuo? | F15: FALSE | H15: L'impresa ha altresì introdotto un sistema di KPI che consentono valutazioni rapide e continue, | I15: L'impresa non fa ancora ricorso a KPI che consentono valutazioni rapide e continue, | L15: =+OFFSET(F15,0,IF(F15,2,3)) -> L'impresa non fa ancora ricorso a KPI che consentono valutazioni rapide e continue, | M15: =+OFFSET(F15,0,IF(F15,4,5)) -> 0
E16: L’impresa è in grado di individuare gli indicatori di produttività coerenti con il proprio modello di business ed il proprio settore di attività, e di raccogliere ulteriori informazioni per la valutazione dell’andamento tendenziale? | F16: TRUE | H16: è in grado di individuare gli indicatori di produttività coerenti con il proprio modello di business ed il proprio settore di attività, e di raccogliere ulteriori informazioni per la valutazione dell’andamento tendenziale. | I16: non è in grado di individuare gli indicatori di produttività coerenti con il proprio modello di business ed il proprio settore di attività, e di raccogliere ulteriori informazioni per la valutazione dell’andamento tendenziale. | J16: Descrivere facendo riferimento ai metodi utilizzati (BSC, BMC, KPI, ecc) | K16: Indicare se e quando intende adottare i KPI, quale metodologia intende adottare (BSC, BMC, KPI, ecc) e quali controlli avvengono per misurare la produttività aziendale. | L16: =+OFFSET(F16,0,IF(F16,2,3)) -> è in grado di individuare gli indicatori di produttività coerenti con il proprio modello di business ed il proprio settore di attività, e di raccogliere ulteriori informazioni per la valutazione dell’andamento tendenziale. | M16: =+OFFSET(F16,0,IF(F16,4,5)) -> Descrivere facendo riferimento ai metodi utilizzati (BSC, BMC, KPI, ecc)
C17: 1.5 | E17: L’impresa dispone di un piano di tesoreria a 12 mesi? | F17: FALSE | H17: L'impresa dispone di un piano di tesoreria a 12 mesi, | I17: L'impresa non dispone di un piano di tesoreria a 12 mesi. | J17: Aggiungere eventuali commenti | K17: Spiegare le motivazioni per le quali non è stato redatto un piano di tesoreria e come si intende rimuovere gli ostacoli. | L17: =+OFFSET(F17,0,IF(F17,2,3)) -> L'impresa non dispone di un piano di tesoreria a 12 mesi. | M17: =+OFFSET(F17,0,IF(F17,4,5)) -> Spiegare le motivazioni per le quali non è stato redatto un piano di tesoreria e come si intende rimuovere gli ostacoli.
E18: L’impresa è in grado di predisporre un prospetto delle stime delle entrate e delle uscite finanziare almeno a 13 settimane, il cui scostamento con l’andamento corrente dovrà essere valutato a consuntivo? | F18: FALSE | H18: È in grado di predisporre un prospetto delle stime delle entrate e delle uscite finanziare almeno a 13 settimane, il cui scostamento con l’andamento corrente dovrà essere valutato a consuntivo. | I18: Non è in grado di predisporre un prospetto delle stime delle entrate e delle uscite finanziare almeno a 13 settimane, il cui scostamento con l’andamento corrente dovrà essere valutato a consuntivo. | J18: Aggiungere eventuali commenti | K18: Spiegare le motivazioni per le quali non è stato redatto il prospetto e come si intende rimuovere gli ostacoli. | L18: =+OFFSET(F18,0,IF(F18,2,3)) -> Non è in grado di predisporre un prospetto delle stime delle entrate e delle uscite finanziare almeno a 13 settimane, il cui scostamento con l’andamento corrente dovrà essere valutato a consuntivo. | M18: =+OFFSET(F18,0,IF(F18,4,5)) -> Spiegare le motivazioni per le quali non è stato redatto il prospetto e come si intende rimuovere gli ostacoli.
L19: =+OFFSET(F19,0,IF(F19,2,3)) -> 0 | M19: =+OFFSET(F19,0,IF(F19,4,5)) -> 0
A20: 2 | D20: Rilevazione della situazione contabile e dell’andamento corrente | H20: Frase VERO | I20: Frase FALSO | J20: Frase suggerimento per commenti in caso di risposta positiva | K20: Frase suggerimento per commenti in caso di risposta negativa | L20: =+OFFSET(F20,0,IF(F20,2,3)) -> Frase FALSO | M20: =+OFFSET(F20,0,IF(F20,4,5)) -> Frase suggerimento per commenti in caso di risposta negativa
C21: 2.1 | E21: L’impresa dispone di una situazione contabile recante le rettifiche di competenza e gli assestamenti di chiusura, nel rispetto del principio contabile OIC 30, quanto più possibile aggiornata e comunque non anteriore di oltre 120 giorni? | F21: TRUE | H21: È stata disposta una situazione contabile recante le rettifiche di competenza e gli assestamenti di chiusura, nel rispetto del principio contabile OIC 30. | I21: L'ultima situazione redatta risale a oltre 120 giorni. | J21: Aggiungere eventuali commenti | K21: Indicare i tempi previsti per una situazione aggiornata | L21: =+OFFSET(F21,0,IF(F21,2,3)) -> È stata disposta una situazione contabile recante le rettifiche di competenza e gli assestamenti di chiusura, nel rispetto del principio contabile OIC 30. | M21: =+OFFSET(F21,0,IF(F21,4,5)) -> Aggiungere eventuali commenti
C22: 2.2 | E22: La situazione debitoria è completa ed affidabile? | F22: TRUE | H22: La situazione è da considerarsi affidabile per quanto concerne la corretta rappresentazione della situazione debitoria dell'impresa. | I22: La situazione non è da considerarsi affidabile per quanto concerne la corretta rappresentazione della situazione debitoria dell'impresa. | J22: Aggiungere eventuali commenti | K22: Indicare le cause che impediscono un'affidabilità della situazione debitoria. | L22: =+OFFSET(F22,0,IF(F22,2,3)) -> La situazione è da considerarsi affidabile per quanto concerne la corretta rappresentazione della situazione debitoria dell'impresa. | M22: =+OFFSET(F22,0,IF(F22,4,5)) -> Aggiungere eventuali commenti
E23: Il valore contabile dei cespiti è adeguato e non è inferiore al maggiore tra il valore recuperabile e quelli di mercato? | F23: FALSE | H23: Non sono presenti minusvalenze latenti o potenziali insite nella valutazione dei cespiti. | I23: Il maggior contabile dei cespiti è superiore al valore di realizzo e a quello di mercato. | J23: Aggiungere eventuali commenti | K23: L'impresa intende quanto meno appostare con prudenza adeguati fondi rischi e fondi per l’adeguamento delle attività e delle passività? | L23: =+OFFSET(F23,0,IF(F23,2,3)) -> Il maggior contabile dei cespiti è superiore al valore di realizzo e a quello di mercato. | M23: =+OFFSET(F23,0,IF(F23,4,5)) -> L'impresa intende quanto meno appostare con prudenza adeguati fondi rischi e fondi per l’adeguamento delle attività e delle passività?
C24: 2.3 | E24: È disponibile un prospetto recante l’anzianità dei crediti commerciali? | F24: TRUE | H24: La funzione amministrativa dispone di un prospetto recante l’anzianità dei crediti commerciali e | I24: Non esiste in azienda un prospetto recante l’anzianità dei crediti commerciali | L24: =+OFFSET(F24,0,IF(F24,2,3)) -> La funzione amministrativa dispone di un prospetto recante l’anzianità dei crediti commerciali e | M24: =+OFFSET(F24,0,IF(F24,4,5)) -> 0
E25: Il prospetto comprende le cause del ritardo di incasso tale da consentire una valutazione oggettiva dei rischi di perdite sui crediti e una stima prudente dei tempi di incasso? | F25: FALSE | H25: le cause del ritardo di incasso tale da consentire una valutazione oggettiva dei rischi di perdite sui crediti e una stima prudente dei tempi di incasso. | I25: , non sono state analizzate le cause del ritardo di incasso tale da consentire una valutazione oggettiva dei rischi di perdite sui crediti e una stima prudente dei tempi di incasso. | J25: Aggiungere eventuali commenti | K25: Indicare eventuali interventi in termini di credit management | L25: =+OFFSET(F25,0,IF(F25,2,3)) -> , non sono state analizzate le cause del ritardo di incasso tale da consentire una valutazione oggettiva dei rischi di perdite sui crediti e una stima prudente dei tempi di incasso. | M25: =+OFFSET(F25,0,IF(F25,4,5)) -> Indicare eventuali interventi in termini di credit management
E26: I crediti commerciali sono suddivisibili in relazione alla loro anzianità? | F26: TRUE | H26: I crediti sono suddivisibili in base alla loro anzianità. | I26: Non vi sono informazioni sufficienti per suddividere i crediti in base all'anzianità. | J26: Aggiungere eventuali commenti | K26: Indicare eventuali interventi in termini di credit management | L26: =+OFFSET(F26,0,IF(F26,2,3)) -> I crediti sono suddivisibili in base alla loro anzianità. | M26: =+OFFSET(F26,0,IF(F26,4,5)) -> Aggiungere eventuali commenti
E27: Per gli scaduti che superano la fisiologia (tempi ordinari di pagamento, pur oltre la scadenza contrattuale, che caratterizzano il settore), la stima del momento dell’incasso è particolarmente prudente? | F27: FALSE | H27: Per gli scaduti che superano la fisiologia (tempi ordinari di pagamento, pur oltre la scadenza contrattuale, che caratterizzano il settore), la stima del momento dell’incasso è particolarmente prudente. | I27: Per gli scaduti che superano la fisiologia (tempi ordinari di pagamento, pur oltre la scadenza contrattuale, che caratterizzano il settore), la stima del momento dell’incasso non è da considerarsi sufficientemente prudente. | J27: Aggiungere eventuali commenti | K27: Quali elementi non sono valutati con la dovuta prudenza? | L27: =+OFFSET(F27,0,IF(F27,2,3)) -> Per gli scaduti che superano la fisiologia (tempi ordinari di pagamento, pur oltre la scadenza contrattuale, che caratterizzano il settore), la stima del momento dell’incasso non è da considerarsi sufficientemente prudente. | M27: =+OFFSET(F27,0,IF(F27,4,5)) -> Quali elementi non sono valutati con la dovuta prudenza?
C28: 2.4 | E28: È disponibile un prospetto recante le rimanenze di magazzino con i tempi di movimentazione che consenta di individuare le giacenze oggetto di lenta rotazione? | F28: TRUE | H28: È disponibile un prospetto recante le rimanenze di magazzino con i tempi di movimentazione che consenta di individuare le giacenze oggetto di lenta rotazione. | I28: Non è stato redatto alcun prospetto recante le rimanenze di magazzino con i tempi di movimentazione che consenta di individuare le giacenze oggetto di lenta rotazione. | J28: Quali sono le giacenze di magazzino a lenta rotazione? | K28: Indicare le cause e gli interventi in merito | L28: =+OFFSET(F28,0,IF(F28,2,3)) -> È disponibile un prospetto recante le rimanenze di magazzino con i tempi di movimentazione che consenta di individuare le giacenze oggetto di lenta rotazione. | M28: =+OFFSET(F28,0,IF(F28,4,5)) -> Quali sono le giacenze di magazzino a lenta rotazione?
C29: 2.5 | E29: È disponibile un prospetto di riconciliazione tra la contabilità e quanto risultante dal certificato unico dei debiti tributari,dalla situazione debitoria complessiva dell’Agente della Riscossione? | F29: FALSE | H29: L'impresa dispone di un prospetto di riconciliazione tra la contabilità e quanto risultante dal certificato unico dei debiti tributari, dalla situazione debitoria complessiva dell’Agente della Riscossione. | I29: L'impresa non ha redatto un prospetto di riconciliazione tra la contabilità e quanto risultante dal certificato unico dei debiti tributari, dalla situazione debitoria complessiva dell’Agente della Riscossione. | J29: Indicare le differenze significative | K29: Indicare le cause e gli interventi in merito | L29: =+OFFSET(F29,0,IF(F29,2,3)) -> L'impresa non ha redatto un prospetto di riconciliazione tra la contabilità e quanto risultante dal certificato unico dei debiti tributari, dalla situazione debitoria complessiva dell’Agente della Riscossione. | M29: =+OFFSET(F29,0,IF(F29,4,5)) -> Indicare le cause e gli interventi in merito
E30: È disponibile un prospetto di riconciliazione tra la contabilità e quanto risultante dal certificato per debiti contributivi e assicurativi? | F30: FALSE | H30: Non ha compilato un prospetto di riconciliazione tra la contabilità e quanto risultante dal certificato unico dei debiti contributivi e assicurativi | I30: Ha redatto un prospetto di riconciliazione tra la contabilità e quanto risultante dal certificato unico dei debiti contributivi e assicurativi | J30: Indicare le differenze significative. | K30: Indicare le cause e gli interventi in merito | L30: =+OFFSET(F30,0,IF(F30,2,3)) -> Ha redatto un prospetto di riconciliazione tra la contabilità e quanto risultante dal certificato unico dei debiti contributivi e assicurativi | M30: =+OFFSET(F30,0,IF(F30,4,5)) -> Indicare le cause e gli interventi in merito
E31: Viene esaminata periodicamente la Centrale Rischi di Banca d'Italia? | F31: TRUE | H31: La Centrale rischi di Banca D'Italia viene esaminata periodicamente e | I31: La Centrale rischi di Banca D'Italia non viene esaminata periodicamente e | L31: =+OFFSET(F31,0,IF(F31,2,3)) -> La Centrale rischi di Banca D'Italia viene esaminata periodicamente e | M31: =+OFFSET(F31,0,IF(F31,4,5)) -> 0
E32: È disponibile un prospetto di riconciliazione tra la contabilità e quanto risultante dalla Centrale Rischi? | F32: FALSE | H32: riconciliata con la contabilità. | I32: non riconciliata con la contabilità. | J32: Aggiungere eventuali commenti | K32: Indicare le cause e gli interventi in merito | L32: =+OFFSET(F32,0,IF(F32,2,3)) -> non riconciliata con la contabilità. | M32: =+OFFSET(F32,0,IF(F32,4,5)) -> Indicare le cause e gli interventi in merito
C33: 2.6 | E33: Si è tenuto adeguatamente conto dei rischi di passività potenziali? | F33: TRUE | H33: Il sistema di controllo dei rischi tiene conto anche delle passività potenziali. | I33: L’azienda non ha tenuto conto delle passività potenziali. | J33: Di che entità sono eventuali passività potenziali? | K33: Di che entità sono eventuali passività potenziali? | L33: =+OFFSET(F33,0,IF(F33,2,3)) -> Il sistema di controllo dei rischi tiene conto anche delle passività potenziali. | M33: =+OFFSET(F33,0,IF(F33,4,5)) -> Di che entità sono eventuali passività potenziali?
E34: Non esistono rischi derivanti dalle garanzie concesse? | F34: FALSE | H34: Per quanto concerne le garanzie concesse a terzi non si evidenziano rischi meritevoli di menzione. | I34: Esistono rilevanti rischi per garanzie concesse a terzi. | J34: Aggiungere eventuali commenti | K34: Descrivere e precisare se ne è stato tenuto conto a livello di fondi rischi. | L34: =+OFFSET(F34,0,IF(F34,2,3)) -> Esistono rilevanti rischi per garanzie concesse a terzi. | M34: =+OFFSET(F34,0,IF(F34,4,5)) -> Descrivere e precisare se ne è stato tenuto conto a livello di fondi rischi.
C35: 2.7 | E35: Esiste l'organo di controllo o il revisore legale? | F35: TRUE | H35: L'organo di controllo o il revisore legale è composto da | I35: Non è stato nominato l'organo di controllo o il revisore legale. | J35: Indicare i nominativi e eventuali | K35: Chiarire le ragioni. | L35: =+OFFSET(F35,0,IF(F35,2,3)) -> L'organo di controllo o il revisore legale è composto da | M35: =+OFFSET(F35,0,IF(F35,4,5)) -> Indicare i nominativi e eventuali
C36: 2.8 | E36: Sono disponibili informazioni sull'andamento corrente in termini di ricavi, portafoglio ordini, costi e flussi finanziari? | F36: TRUE | H36: Sono disponibili informazioni sull'andamento corrente in termini di ricavi, portafoglio ordini, costi e flussi finanziari. | I36: Non sono disponibili informazioni sull'andamento corrente in termini di ricavi, portafoglio ordini, costi e flussi finanziari. | J36: Quali informazioni? | K36: Aggiungere eventuali commenti | L36: =+OFFSET(F36,0,IF(F36,2,3)) -> Sono disponibili informazioni sull'andamento corrente in termini di ricavi, portafoglio ordini, costi e flussi finanziari. | M36: =+OFFSET(F36,0,IF(F36,4,5)) -> Quali informazioni?
E37: È disponibile un confronto con lo stesso periodo del precedente esercizio? | F37: TRUE | H37: È disponibile un confronto con lo stesso periodo del precedente esercizio. | I37: È disponibile un confronto con lo stesso periodo del precedente esercizio. | J37: Che tipo di confronto? | K37: Aggiungere eventuali commenti | L37: =+OFFSET(F37,0,IF(F37,2,3)) -> È disponibile un confronto con lo stesso periodo del precedente esercizio. | M37: =+OFFSET(F37,0,IF(F37,4,5)) -> Che tipo di confronto?

Sheet SEZIONI 3-4
A3: 3 | D3: Individuazione delle strategie di intervento atte a prevenire e rimuovere le cause della crisi
B4: 3.1.1 | E4: L’imprenditore non percepisce uno stato di crisi o uno squilibrio patrimoniale o economico-finanziario che la rende probabile? | F4: TRUE | H4: L’assetto contabile, amministrativo e contabile non ha rilevato elementi tali da far percepire uno stato di crisi o di squilibrio patrimoniale e/o economico finanziario. | I4: Esistono alcune evidenze tali da far presagire uno stato di crisi e o uno squilibrio economico patrimoniale. | J4: Aggiungere eventuali commenti | K4: Specificare | L4: =+OFFSET(F4,0,IF(F4,2,3)) -> L’assetto contabile, amministrativo e contabile non ha rilevato elementi tali da far percepire uno stato di crisi o di squilibrio patrimoniale e/o economico finanziario. | M4: =+OFFSET(F4,0,IF(F4,4,5)) -> Aggiungere eventuali commenti
B5: 3.1.2 | E5: Quali sono le manifestazioni esteriori di tale stato
E6: lo squilibrio percepito è di carattere: | F6: =+COUNTIF(F7:F9,TRUE)>0 -> TRUE | I6: {=IF(F6, +CONCATENATE("Per quanto concerne lo stato di crisi, ",E6, IF(F7,E7&N7,""), IF(F8,E8&N8,""), IF(F9,E9&N9,""),".")& IF(F11,CONCATENATE(AC,E11, IF(F12,E12&N12,""), IF(F13,E13&N13,""), IF(F14,E14&N14,""), IF(F15,E15&N15,""), IF(F16,E16&N16,""), IF(F17,E17&N17,""), IF(F18,E18&N18,""), IF(F19,E19&N19,""), IF(F20,E20&N20,""), IF(F21,E21&N21,""))&pu&AC&E10,""),"")} -> Per quanto concerne lo stato di crisi, lo squilibrio percepito è di carattere: economico, patrimoniale e finanziario. Sono peggiorati rispetto all'anno precedente i seguenti indicatori: fatturato, margine di contribuzione, margine di contribuzione %, EBITDA, incidenza delle passività a breve, capitale circolante netto e posizione finanziaria netta. altro (specificare)
E7: economico | F7: TRUE | N7: =+IF( COUNTIF(F8:$F$9,TRUE)=1," e ", IF( COUNTIF(F8:$F$9,TRUE)>1,", ","")) -> ,
E8: patrimoniale | F8: TRUE | N8: =+IF( COUNTIF(F9:$F$9,TRUE)=1," e ", IF( COUNTIF(F9:$F$9,TRUE)>1,", ","")) -> e
E9: finanziario | F9: TRUE
C10: Ulteriori Commenti | E10: altro (specificare) | F10: =+IF(E10>"",TRUE,FALSE) -> TRUE
E11: Sono peggiorati rispetto all'anno precedente i seguenti indicatori: | F11: =+COUNTIF(F12:F21,TRUE)>0 -> TRUE
E12: fatturato | F12: TRUE | N12: =+IF( COUNTIF(F13:$F$21,TRUE)=1," e ", IF( COUNTIF(F13:$F$21,TRUE)>1,", ","")) -> ,
E13: margine di contribuzione | F13: TRUE | N13: =+IF( COUNTIF(F14:$F$21,TRUE)=1," e ", IF( COUNTIF(F14:$F$21,TRUE)>1,", ","")) -> ,
E14: margine di contribuzione % | F14: TRUE | N14: =+IF( COUNTIF(F15:$F$21,TRUE)=1," e ", IF( COUNTIF(F15:$F$21,TRUE)>1,", ","")) -> ,
E15: EBITDA | F15: TRUE | N15: =+IF( COUNTIF(F16:$F$21,TRUE)=1," e ", IF( COUNTIF(F16:$F$21,TRUE)>1,", ","")) -> ,
E16: risultato ante imposte | F16: FALSE | N16: =+IF( COUNTIF(F17:$F$21,TRUE)=1," e ", IF( COUNTIF(F17:$F$21,TRUE)>1,", ","")) -> ,
E17: grado di indipendenza finanziaria (PN/Totale Attivo) | F17: FALSE | N17: =+IF( COUNTIF(F18:$F$21,TRUE)=1," e ", IF( COUNTIF(F18:$F$21,TRUE)>1,", ","")) -> ,
E18: copertura delle immobilizzazioni | F18: FALSE | N18: =+IF( COUNTIF(F19:$F$21,TRUE)=1," e ", IF( COUNTIF(F19:$F$21,TRUE)>1,", ","")) -> ,
E19: incidenza delle passività a breve | F19: TRUE | N19: =+IF( COUNTIF(F20:$F$21,TRUE)=1," e ", IF( COUNTIF(F20:$F$21,TRUE)>1,", ","")) -> ,
E20: capitale circolante netto | F20: TRUE | N20: =+IF( COUNTIF(F21:$F$21,TRUE)=1," e ", IF( COUNTIF(F21:$F$21,TRUE)>1,", ","")) -> e
E21: posizione finanziaria netta | F21: TRUE
E22: Si sono verificati i seguenti eventi. | I22: {=IF(OR(F23,F29,F38),+"Lo stato di crisi ha causato anomalie:"&CHAR(10)& IF(COUNTIF(F24:F28,TRUE)>0,CHAR(10)&p&"da un punto di vista commerciale"&IF(OR(F29,F38),";",pu),"")& IF(COUNTIF(F30:F36,TRUE)>0,CHAR(10)&p&"nei rapporti con le banche"&IF(F38,";",pu),"")& IF(COUNTIF(F39:F42,TRUE)>0,CHAR(10)&p&"da un punto di vista gestionale"&pu,""),"")} -> Lo stato di crisi ha causato anomalie: • da un punto di vista commerciale; • nei rapporti con le banche; • da un punto di vista gestionale.
E23: Da un punto di vista commerciale | F23: =+COUNTIF(F24:F28,TRUE)>0 -> TRUE
E24: mancati rilevanti pagamenti a fornitori | F24: TRUE | I24: {=+IF(F23,E23&" si sono verificati "& IF(F24,E24&N24,"")& IF(F25,E25&N25,"")& IF(F26,E26&N26,"")& IF(F27,E27&N27,"")& IF(F28,E28&N28,"")& pu&AC,"")} -> Da un punto di vista commerciale si sono verificati mancati rilevanti pagamenti a fornitori, significativa rinegoziazione delle condizioni di pagamento e altro (specificare). | N24: =+IF( COUNTIF(F25:$F$28,TRUE)=1," e ", IF( COUNTIF(F25:$F$28,TRUE)>1,", ","")) -> ,
E25: significativa rinegoziazione delle condizioni di pagamento | F25: TRUE | N25: =+IF( COUNTIF(F26:$F$28,TRUE)=1," e ", IF( COUNTIF(F26:$F$28,TRUE)>1,", ","")) -> e
E26: pagamento di penali rilevanti per mancate consegne | F26: FALSE | N26: =+IF( COUNTIF(F27:$F$28,TRUE)=1," e ", IF( COUNTIF(F27:$F$28,TRUE)>1,", ","")) -> e
E27: svendite rilevanti di materiale | F27: FALSE | N27: =+IF( COUNTIF(F28:$F$28,TRUE)=1," e ", IF( COUNTIF(F28:$F$28,TRUE)>1,", ","")) -> e
C28: Indicare eventuali altri eventi | E28: altro (specificare) | F28: =+IF(E28>"",TRUE,FALSE) -> TRUE
E29: Nei rapporti con le banche | F29: =+COUNTIF(F30:F37,TRUE)>0 -> TRUE | I29: {=+IF(F29,E29&" sono state rilevate "& IF(F30,E30&N30,"")& IF(F31,E31&N31,"")& IF(F32,E32&N32,"")& IF(F33,E33&N33,"")& IF(F34,E34&N34,"")& IF(F35,E35&N35,"")& IF(F36,E36&N36,"")& IF(F37,E37&N37,"")& pu&AC,"")} -> Nei rapporti con le banche sono state rilevate aumento anomalo dei crediti impagati e altro (specificare).
E30: segnalazioni inframensili negative | F30: FALSE | N30: =+IF( COUNTIF(F31:$F$37,TRUE)=1," e ", IF( COUNTIF(F31:$F$37,TRUE)>1,", ","")) -> ,
E31: sofferenze | F31: FALSE | N31: =+IF( COUNTIF(F32:$F$37,TRUE)=1," e ", IF( COUNTIF(F32:$F$37,TRUE)>1,", ","")) -> ,
E32: sconfini rilevanti entro i 90 giorni | F32: FALSE | N32: =+IF( COUNTIF(F33:$F$37,TRUE)=1," e ", IF( COUNTIF(F33:$F$37,TRUE)>1,", ","")) -> ,
E33: sconfini oltre i 90 giorni | F33: FALSE | N33: =+IF( COUNTIF(F34:$F$37,TRUE)=1," e ", IF( COUNTIF(F34:$F$37,TRUE)>1,", ","")) -> ,
E34: escussione di garanzie di terzi | F34: FALSE | N34: =+IF( COUNTIF(F35:$F$37,TRUE)=1," e ", IF( COUNTIF(F35:$F$37,TRUE)>1,", ","")) -> ,
E35: escussione di nostre garanzie a terzi | F35: FALSE | N35: =+IF( COUNTIF(F36:$F$37,TRUE)=1," e ", IF( COUNTIF(F36:$F$37,TRUE)>1,", ","")) -> ,
E36: aumento anomalo dei crediti impagati | F36: TRUE | N36: =+IF( COUNTIF(F37:$F$37,TRUE)=1," e ", IF( COUNTIF(F37:$F$37,TRUE)>1,", ","")) -> e
C37: Indicare eventuali altri eventi | E37: altro (specificare) | F37: =+IF(E37>"",TRUE,FALSE) -> TRUE
E38: Da un punto di vista gestionale si segnala | F38: =+COUNTIF(F39:F43,TRUE)>0 -> TRUE | I38: {=+IF(F38,E38& IF(F39,E39&N39,"")& IF(F40,E40&N40,"")& IF(F41,E41&N41,"")& IF(F42,E42&N42,"")& IF(F43,E43&N43,"")& pu&AC,"")} -> Da un punto di vista gestionale si segnala la perdita di clienti o commesse importanti, comparsa di concorrenti ostili e/o nuovi entranti che rischiano di ridurre ulteriormente le quote di mercato e altro (specificare).
E39: la perdita di membri della direzione con responsabilità strategiche senza una loro sostituzione | F39: FALSE | N39: =+IF( COUNTIF(F40:$F$43,TRUE)=1," e ", IF( COUNTIF(F40:$F$43,TRUE)>1,", ","")) -> ,
E40: la perdita di clienti o commesse importanti | F40: TRUE | N40: =+IF( COUNTIF(F41:$F$43,TRUE)=1," e ", IF( COUNTIF(F41:$F$43,TRUE)>1,", ","")) -> ,
E41: controversie rilevanti con il personale | F41: FALSE | N41: =+IF( COUNTIF(F43:$F$43,TRUE)=1," e ", IF( COUNTIF(F43:$F$43,TRUE)>1,", ","")) -> e
E42: comparsa di concorrenti ostili e/o nuovi entranti che rischiano di ridurre ulteriormente le quote di mercato | F42: TRUE | N42: =+IF( COUNTIF(F$43:$F43,TRUE)=1," e ", IF( COUNTIF(F$43:$F43,TRUE)>1,", ","")) -> e
C43: Indicare eventuali altri fatti gestionali meritevoli di attenzione | E43: altro (specificare) | F43: =+IF(E43>"",TRUE,FALSE) -> TRUE
E44: La situazione di difficoltà descritta ha causato un debito da ristrutturare (per mancati pagamenti e/o richieste di rientro) per | F44: =+COUNTIF(F45:F53,TRUE)>0 -> TRUE | I44: {=+IF(F44,E44& IF(F45,E45&N45,"")& IF(F46,E46&N46,"")& IF(F47,E47&N47,"")& IF(F48,E48&N48,"")& IF(F49,E49&N49,"")& IF(F50,E50&N50,"")& IF(F51,E51&N51,"")& IF(F52,E52&N52,"")& IF(F53,E53&N53,"")& pu&AC,"")} -> La situazione di difficoltà descritta ha causato un debito da ristrutturare (per mancati pagamenti e/o richieste di rientro) per fornitori di beni e servizi indispensabili e altro (specificare).
E45: fornitori di beni e servizi non indispensabili | F45: FALSE | N45: =+IF( COUNTIF(F46:$F$53,TRUE)=1," e ", IF( COUNTIF(F46:$F$53,TRUE)>1,", ","")) -> ,
E46: fornitori di beni e servizi indispensabili | F46: TRUE | N46: =+IF( COUNTIF(F47:$F$53,TRUE)=1," e ", IF( COUNTIF(F47:$F$53,TRUE)>1,", ","")) -> e
E47: imposte dirette ires - irap (saldi e acconti) | F47: FALSE | N47: =+IF( COUNTIF(F48:$F$53,TRUE)=1," e ", IF( COUNTIF(F48:$F$53,TRUE)>1,", ","")) -> e
E48: erario per ritenute fiscali | F48: FALSE | N48: =+IF( COUNTIF(F49:$F$53,TRUE)=1," e ", IF( COUNTIF(F49:$F$53,TRUE)>1,", ","")) -> e
E49: ritenute previdenziali | F49: FALSE | N49: =+IF( COUNTIF(F50:$F$53,TRUE)=1," e ", IF( COUNTIF(F50:$F$53,TRUE)>1,", ","")) -> e
E50: iva | F50: FALSE | N50: =+IF( COUNTIF(F51:$F$53,TRUE)=1," e ", IF( COUNTIF(F51:$F$53,TRUE)>1,", ","")) -> e
E51: altre imposte | F51: FALSE | N51: =+IF( COUNTIF(F52:$F$53,TRUE)=1," e ", IF( COUNTIF(F52:$F$53,TRUE)>1,", ","")) -> e
E52: dipendenti | F52: FALSE | N52: =+IF( COUNTIF(F53:$F$53,TRUE)=1," e ", IF( COUNTIF(F53:$F$53,TRUE)>1,", ","")) -> e
C53: Indicare altri eventi derivanti dalla crisi | E53: altro (specificare) | F53: =+IF(E53>"",TRUE,FALSE) -> TRUE
E54: Sul lato delle iniziative dei creditori si segnalano | F54: =+COUNTIF(F55:F61,TRUE)>0 -> TRUE | I54: {=+IF(F54,E54& IF(F55,E55&N55,"")& IF(F56,E56&N56,"")& IF(F57,E57&N57,"")& IF(F58,E58&N58,"")& IF(F59,E59&N59,"")& IF(F60,E60&N60,"")& IF(F61,E61&N61,"")& pu&AC,"")} -> Sul lato delle iniziative dei creditori si segnalano decreti ingiuntivi ricevuti ed atti di ricognitivi di avvio di azioni per il recupero dei crediti e altro (specificare).
E55: iscrizioni di ipoteche giudiziarie, pegni e forme tecniche di prelazione su beni aziendali | F55: FALSE | N55: =+IF( COUNTIF(F56:$F$61,TRUE)=1," e ", IF( COUNTIF(F56:$F$61,TRUE)>1,", ","")) -> ,
E56: decreti ingiuntivi ricevuti ed atti di ricognitivi di avvio di azioni per il recupero dei crediti | F56: TRUE | N56: =+IF( COUNTIF(F57:$F$61,TRUE)=1," e ", IF( COUNTIF(F57:$F$61,TRUE)>1,", ","")) -> e
E57: protesto di assegni e cambiali | F57: FALSE | N57: =+IF( COUNTIF(F58:$F$61,TRUE)=1," e ", IF( COUNTIF(F58:$F$61,TRUE)>1,", ","")) -> e
E58: istanze di fallimento avanzate da creditori aziendali | F58: FALSE | N58: =+IF( COUNTIF(F59:$F$61,TRUE)=1," e ", IF( COUNTIF(F59:$F$61,TRUE)>1,", ","")) -> e
E59: default/fallimento dei garanti e default/fallimento dei garantiti (rischio infragruppo) | F59: FALSE | N59: =+IF( COUNTIF(F60:$F$61,TRUE)=1," e ", IF( COUNTIF(F60:$F$61,TRUE)>1,", ","")) -> e
E60: intenzione della direzione di liquidare l’impresa o di cessare le attività | F60: FALSE | N60: =+IF( COUNTIF(F61:$F$61,TRUE)=1," e ", IF( COUNTIF(F61:$F$61,TRUE)>1,", ","")) -> e
C61: Indicare altre eventi iniziative | E61: altro (specificare) | F61: =+IF(E61>"",TRUE,FALSE) -> TRUE
B62: 3.2.1 | E62: Tenuto conto delle manifestazioni sub 3.1, quali ne sono le cause? | F62: =+COUNTIF(F63:F68,TRUE)>0 -> TRUE | I62: {=+IF(F62,"Tenuto conto delle manifestazioni, le cause sono:"&s& IF(F63,E63&N63,"")& IF(F64,E64&N64,"")& IF(F65,E65&N65,"")& IF(F66,E66&N66,"")& IF(F67,E67&N67,"")& IF(F69,CONCATENATE(AC,E69&N69,IF(F70,E70&N70,"")),""),"")} -> Tenuto conto delle manifestazioni, le cause sono: riduzione della redditività, riduzione della competività sul mercato e aumento dei costi operativi non trasferibile sui prezzi di vendita.
E63: riduzione della redditività | F63: TRUE | N63: =+IF( COUNTIF(F64:$F$68,TRUE)=1," e ", IF( COUNTIF(F64:$F$68,TRUE)>1,", ",".")) -> ,
E64: riduzione dei flussi di cassa | F64: FALSE | N64: =+IF( COUNTIF(F65:$F$68,TRUE)=1," e ", IF( COUNTIF(F65:$F$68,TRUE)>1,", ",".")) -> ,
E65: riduzione degli investimenti e aggiornamento tecnologico | F65: FALSE | N65: =+IF( COUNTIF(F66:$F$68,TRUE)=1," e ", IF( COUNTIF(F66:$F$68,TRUE)>1,", ",".")) -> ,
E66: riduzione della competività sul mercato | F66: TRUE | N66: =+IF( COUNTIF(F67:$F$68,TRUE)=1," e ", IF( COUNTIF(F67:$F$68,TRUE)>1,", ",".")) -> e
C67: Ulteriori cause | E67: aumento dei costi operativi non trasferibile sui prezzi di vendita | F67: =+IF(E67>"",TRUE,FALSE) -> TRUE | N67: =+IF( COUNTIF(F68:$F$68,TRUE)=1," e ", IF( COUNTIF(F68:$F$68,TRUE)>1,", ",".")) -> .
B69: 3.2.2 | E69: Le cause individuate sono coerenti con la crisi manifestatasi. | F69: FALSE | N69: =+IF( COUNTIF(F70:F$70,TRUE)=1," e ", IF( COUNTIF(F70:F$70,TRUE)>1,", ","")) -> e
C70: Ulteriori commenti | E70: altro (specificare) | F70: =+IF(E70>"",TRUE,FALSE) -> TRUE
H71: Frase VERO | I71: Frase FALSO | J71: Frase suggerimento per commenti in caso di risposta positiva | K71: Frase suggerimento per commenti in caso di risposta negativa | L71: Frase Completa | M71: Suggerimento
B72: 3.3 | E72: L’organo di controllo ed il revisore, quando in carica, ritengono che il quadro fornito dall’imprenditore sia completo e adeguato? | F72: FALSE | H72: L’organo di controllo ed il revisore, quando in carica, ritengono che il quadro fornito dall’imprenditore sia completo e adeguato. | I72: L’organo di controllo ed il revisore, quando in carica, non ritengono che il quadro fornito dall’imprenditore sia completo e adeguato. | J72: Aggiungere eventuali commenti | K72: Indicare le ragioni | L72: =+OFFSET(F72,0,IF(F72,2,3)) -> L’organo di controllo ed il revisore, quando in carica, non ritengono che il quadro fornito dall’imprenditore sia completo e adeguato. | M72: =+OFFSET(F72,0,IF(F72,4,5)) -> Indicare le ragioni
B73: 3.4.1 | E73: L'impresa ha individuato le strategie di intervento e le iniziative industriali che intende adottare? | F73: TRUE | H73: L'impresa ha individuato le strategie di intervento e le iniziative industriali che intende adottare. | I73: L'impresa non ha ancora individuato le strategie di intervento e le iniziative industriali che intende adottare. | J73: Quali strategie e quali iniziative? | K73: Indicare le difficoltà che non le consentono la formulazione di una strategia e i tempi previsti. | L73: =+OFFSET(F73,0,IF(F73,2,3)) -> L'impresa ha individuato le strategie di intervento e le iniziative industriali che intende adottare. | M73: =+OFFSET(F73,0,IF(F73,4,5)) -> Quali strategie e quali iniziative?
B74: 3.4.2 | E74: Esistono strategie di successo adottate dalla concorrenza? | F74: TRUE | H74: Esistono strategie di successo adottate dalla concorrenza. | I74: Non esistono strategie di successo adottate dalla concorrenza. | J74: Quali strategie? | K74: Indicare le ragioni di tale affermazione | L74: =+OFFSET(F74,0,IF(F74,2,3)) -> Esistono strategie di successo adottate dalla concorrenza. | M74: =+OFFSET(F74,0,IF(F74,4,5)) -> Quali strategie?
B75: 3.4.3 | E75: Le strategie di successo adottate dalla concorrenza sono adottabili dall'impresa? | F75: TRUE | H75: Tali strategie sono adottabili dall'impresa. | I75: Tali strategie non sono adottabili dall'impresa. | J75: Indicare se l'azienda intende avvalersene o meno | K75: Indicare le motivazioni | L75: =+OFFSET(F75,0,IF(F75,2,3)) -> Tali strategie sono adottabili dall'impresa. | M75: =+OFFSET(F75,0,IF(F75,4,5)) -> Indicare se l'azienda intende avvalersene o meno
B76: 3.5 | E76: L’impresa dispone delle capacità e delle competenze manageriali per realizzare le iniziative industriali? | F76: FALSE | H76: L’impresa dispone delle capacità e delle competenze manageriali per realizzare le iniziative industriali. | I76: L’impresa non dispone delle capacità e delle competenze manageriali per realizzare le iniziative industriali. | J76: Quali capacità e competenze? | K76: Indicare quali lacune organizzative esistono e come l'impresa intende colmarle | L76: =+OFFSET(F76,0,IF(F76,2,3)) -> L’impresa non dispone delle capacità e delle competenze manageriali per realizzare le iniziative industriali. | M76: =+OFFSET(F76,0,IF(F76,4,5)) -> Indicare quali lacune organizzative esistono e come l'impresa intende colmarle
B77: 3.6.1 | E77: Quali sono i tempi e i relativi effetti in termini di ricavi, di costi e di investimenti delle iniziative da adottare? | F77: =+IF(E78>"",TRUE,FALSE) -> TRUE | I77: =+IF(F77,"Per quanto concerne i tempi e gli effetti in termini di ricavi, di costi e di investimenti delle iniziative da adottare"&s&E78&pu,"") -> Per quanto concerne i tempi e gli effetti in termini di ricavi, di costi e di investimenti delle iniziative da adottare I tempi previsti per le iniziative industriali sono di 12 mesi, con effetti attesi su ricavi in lieve crescita e costi iniziali moderati.
C78: Se i tempi e gli effetti sono noti compilare il riquadro | E78: I tempi previsti per le iniziative industriali sono di 12 mesi, con effetti attesi su ricavi in lieve crescita e costi iniziali moderati | F78: =+IF(E78>"",TRUE,FALSE) -> TRUE
B79: 3.6.2 | E79: Quali sono le relative funzioni aziendali responsabili? | F79: =+IF(E80>"",TRUE,FALSE) -> TRUE | I79: =+IF(F79,"Le relative funzioni aziendali responsabili sono"&s&E80&pu,"") -> Le relative funzioni aziendali responsabili sono Le funzioni responsabili sono l’area manageriale e il reparto operativo per l’implementazione..
C80: Se sono note le funzioni aziendali responsabili compilare il riquadro | E80: Le funzioni responsabili sono l’area manageriale e il reparto operativo per l’implementazione. | F80: =+IF(E80>"",TRUE,FALSE) -> TRUE
B81: 3.7 | E81: Sono prospettabili iniziative alternative nel caso in cui le iniziative dovessero dimostrarsi inefficaci e si manifestassero scostamenti tra gli obiettivi pianificati e quelli raggiunti? | F81: TRUE | H81: Sono prospettabili iniziative alternative nel caso in cui le iniziative dovessero dimostrarsi inefficaci e si manifestassero scostamenti tra gli obiettivi pianificati e quelli raggiunti. | I81: Non sono prospettabili iniziative alternative nel caso in cui le iniziative dovessero dimostrarsi inefficaci e si manifestassero scostamenti tra gli obiettivi pianificati e quelli raggiunti. | J81: Quali iniziative alternative? | K81: Indicare le ragioni | L81: =+OFFSET(F81,0,IF(F81,2,3)) -> Sono prospettabili iniziative alternative nel caso in cui le iniziative dovessero dimostrarsi inefficaci e si manifestassero scostamenti tra gli obiettivi pianificati e quelli raggiunti. | M81: =+OFFSET(F81,0,IF(F81,4,5)) -> Quali iniziative alternative?
B82: 3.8.1 | E82: In precedenza sono stati predisposti ulteriori piani? | F82: TRUE | H82: In precedenza sono stati predisposti ulteriori piani. | I82: Non sono mai stati predisposti piani aziendali. | J82: Indicare l'occasione in cui si è reso necessaria la redazione del piano, chi lo ha redatto e il grado di raggiungimento rispetto agli obiettivi indicati. | K82: Indicare le motivazioni e le eventuali difficoltà e limiti di prima redazione | L82: =+OFFSET(F82,0,IF(F82,2,3)) -> In precedenza sono stati predisposti ulteriori piani. | M82: =+OFFSET(F82,0,IF(F82,4,5)) -> Indicare l'occasione in cui si è reso necessaria la redazione del piano, chi lo ha redatto e il grado di raggiungimento rispetto agli obiettivi indicati.
B83: 3.8.2 | E83: Il piano è coerente con i piani redatti in precedenza? | F83: TRUE | H83: Il piano è coerente con i piani redatti in precedenza | I83: Il piano non è coerente con i piani redatti in precedenza | L83: =+OFFSET(F83,0,IF(F83,2,3)) -> Il piano è coerente con i piani redatti in precedenza | M83: =+OFFSET(F83,0,IF(F83,4,5)) -> 0
B84: 3.8.3 | E84: Vi sono differenze significative con i piani precedenti? | F84: FALSE | H84: e vi sono differenze significative. | I84: e non vi sono differenze significative. | J84: Tali differenze a cosa sono dovute? | K84: Aggiungere eventuali commenti | L84: =+OFFSET(F84,0,IF(F84,2,3)) -> e non vi sono differenze significative. | M84: =+OFFSET(F84,0,IF(F84,4,5)) -> Aggiungere eventuali commenti
B85: 3.9.1 | E85: Il piano appare credibile? | F85: TRUE | H85: Il piano appare credibile. | I85: Il piano non appare credibile. | J85: Indicare le ragioni | K85: Indicare le ragioni | L85: =+OFFSET(F85,0,IF(F85,2,3)) -> Il piano appare credibile. | M85: =+OFFSET(F85,0,IF(F85,4,5)) -> Indicare le ragioni
B86: 3.9.2 | E86: Il piano è fondato su intenzioni strategiche chiare e razionali, condivisibili da parte di un lettore informato quale è l’esperto, coerenti con la situazione di fatto dell’impresa e del contesto in cui opera? | F86: TRUE | H86: È fondato su intenzioni strategiche chiare e razionali, condivisibili da parte di un lettore informato quale è l’esperto, coerenti con la situazione di fatto dell’impresa e del contesto in cui opera. | I86: Non è fondato su intenzioni strategiche chiare e razionali, condivisibili da parte di un lettore informato quale è l’esperto, coerenti con la situazione di fatto dell’impresa e del contesto in cui opera. | J86: Aggiungere eventuali commenti | K86: Indicare le motivazioni | L86: =+OFFSET(F86,0,IF(F86,2,3)) -> È fondato su intenzioni strategiche chiare e razionali, condivisibili da parte di un lettore informato quale è l’esperto, coerenti con la situazione di fatto dell’impresa e del contesto in cui opera. | M86: =+OFFSET(F86,0,IF(F86,4,5)) -> Aggiungere eventuali commenti
B87: 3.9.3 | E87: Le strategie di intervento e le iniziative industriali individuate dall’imprenditore appaiono appropriate per il superamento delle cause della crisi? | F87: TRUE | H87: Le strategie di intervento e le iniziative industriali individuate dall’imprenditore appaiono appropriate per il superamento delle cause della crisi. | I87: Le strategie di intervento e le iniziative industriali individuate dall’imprenditore non appaiono appropriate per il superamento delle cause della crisi. | J87: Indicare le ragioni | K87: Indicare le motivazioni | L87: =+OFFSET(F87,0,IF(F87,2,3)) -> Le strategie di intervento e le iniziative industriali individuate dall’imprenditore appaiono appropriate per il superamento delle cause della crisi. | M87: =+OFFSET(F87,0,IF(F87,4,5)) -> Indicare le ragioni
A89: 4 | D89: Le proiezioni dei flussi finanziari
B90: 4.1 | E90: La stima delle proiezioni dei flussi finanziari del piano è, salvo deroghe giustificate dalla tipologia dell’impresa o dall’attività svolta, l’esito di un percorso che si dipana in ordinate fasi successive così articolate: | F90: =+COUNTIF(F91:F101,TRUE)>0 -> TRUE
B91: 4.1.1 | E91: stima dei ricavi | F91: TRUE | I91: =+IF(F90,"La stima delle proiezioni dei flussi finanziari del piano è l'esito di un percorso che si dipana nelle seguenti fasi successive:"& IF(F91,s&E91&N91,"")& IF(F92,s&E92&N92,"")& IF(F93,s&E93&N93,"")& IF(F94,s&E94&N94,"")& IF(F95,s&E95&N95,"")& IF(F96,s&E96&N96,"")& IF(F97,s&E97&N97,"")& IF(F98,s&E98&N98,"")& IF(F99,s&E99&N99,"")& IF(F100,s&E100&N100,"")& IF(F101,s&E101&N101,"")&pu,"") -> La stima delle proiezioni dei flussi finanziari del piano è l'esito di un percorso che si dipana nelle seguenti fasi successive: stima dei ricavi, stima dei costi variabili correlati ai ricavi, stima dei costi fissi, stima degli investimenti, stima degli effetti delle iniziative industriali che si intendono intraprendere in discontinuità rispetto al passato, verifica di coerenza dei dati economici prognostici, stima del pagamento delle imposte sul reddito, declinazione finanziaria delle grandezze economiche e determinazione dei flussi al servizio del debito, declinazione patrimoniale muovendo dalla situazione contabile di partenza e altro (specificare). | N91: =+IF( COUNTIF(F92:$F$102,TRUE)=1," e ", IF( COUNTIF(F92:$F$102,TRUE)>1,", ","")) -> ,
B92: 4.1.2 | E92: stima dei costi variabili correlati ai ricavi | F92: TRUE | N92: =+IF( COUNTIF(F93:$F$102,TRUE)=1," e ", IF( COUNTIF(F93:$F$102,TRUE)>1,", ","")) -> ,
B93: 4.1.3 | E93: stima dei costi fissi | F93: TRUE | N93: =+IF( COUNTIF(F94:$F$102,TRUE)=1," e ", IF( COUNTIF(F94:$F$102,TRUE)>1,", ","")) -> ,
B94: 4.1.4 | E94: stima degli investimenti | F94: TRUE | N94: =+IF( COUNTIF(F95:$F$102,TRUE)=1," e ", IF( COUNTIF(F95:$F$102,TRUE)>1,", ","")) -> ,
B95: 4.1.5 | E95: stima degli effetti delle iniziative industriali che si intendono intraprendere in discontinuità rispetto al passato | F95: TRUE | N95: =+IF( COUNTIF(F96:$F$102,TRUE)=1," e ", IF( COUNTIF(F96:$F$102,TRUE)>1,", ","")) -> ,
B96: 4.1.6 | E96: verifica di coerenza dei dati economici prognostici | F96: TRUE | N96: =+IF( COUNTIF(F97:$F$102,TRUE)=1," e ", IF( COUNTIF(F97:$F$102,TRUE)>1,", ","")) -> ,
B97: 4.1.7 | E97: stima dell’effetto delle operazioni straordinarie, se previste 14 | F97: FALSE | N97: =+IF( COUNTIF(F98:$F$102,TRUE)=1," e ", IF( COUNTIF(F98:$F$102,TRUE)>1,", ","")) -> ,
B98: 4.1.8 | E98: stima del pagamento delle imposte sul reddito | F98: TRUE | N98: =+IF( COUNTIF(F99:$F$102,TRUE)=1," e ", IF( COUNTIF(F99:$F$102,TRUE)>1,", ","")) -> ,
B99: 4.1.9 | E99: declinazione finanziaria delle grandezze economiche e determinazione dei flussi al servizio del debito | F99: TRUE | N99: =+IF( COUNTIF(F100:$F$102,TRUE)=1," e ", IF( COUNTIF(F100:$F$102,TRUE)>1,", ","")) -> ,
B100: 4.1.10 | E100: declinazione patrimoniale muovendo dalla situazione contabile di partenza | F100: TRUE | N100: =+IF( COUNTIF(F101:$F$102,TRUE)=1," e ", IF( COUNTIF(F102:$F$102,TRUE)>1,", ","")) -> e
C101: Ulteriori commenti | E101: altro (specificare) | F101: =+IF(E101>"",TRUE,FALSE) -> TRUE | N101: =+IF( COUNTIF(F102:$F$102,TRUE)=1," e ", IF( COUNTIF(F102:$F$102,TRUE)>1,", ",""))
H102: Frase VERO | I102: Frase FALSO | J102: Frase suggerimento per commenti in caso di risposta positiva | K102: Frase suggerimento per commenti in caso di risposta negativa | L102: Frase Completa | M102: Suggerimento
B103: 4.2 | E103: Le proiezioni fondate su previsioni coprono un periodo massimo di 5 anni a meno che un arco temporale superiore sia giustificato? | F103: TRUE | H103: Le proiezioni fondate su previsioni coprono un periodo massimo di 5 anni. | I103: Le proiezioni fondate su previsioni non coprono un periodo massimo di 5 anni. | J103: Aggiungere eventuali commenti | K103: Indicare le ragioni dell'arco temporale superiore | L103: =+OFFSET(F103,0,IF(F103,2,3)) -> Le proiezioni fondate su previsioni coprono un periodo massimo di 5 anni. | M103: =+OFFSET(F103,0,IF(F103,4,5)) -> Aggiungere eventuali commenti
B105: 4.1.1 | E105: I ricavi sono stati stimati nel seguente modo | F105: =+IF(E106>"",TRUE,FALSE) -> TRUE | I105: =+IF(F105,"I ricavi sono stati stimati nel seguente modo:"&s&E106&pu,"") -> I ricavi sono stati stimati nel seguente modo: Indicare la stima dei ricavi.
...

Sheet SEZIONI 5-6
A5: 5 | C5: Il risanamento del debito | H5: Frase VERO | I5: Frase FALSO | J5: Frase suggerimento per commenti in caso di risposta positiva | K5: Frase suggerimento per commenti in caso di risposta negativa | L5: Frase Completa | M5: Suggerimento
B6: 5.1 | E6: L’impresa, alla luce del par. 4 della presente Sezione, è in grado in futuro di generare risorse al servizio del debito? | F6: TRUE | H6: L’impresa è in grado in futuro di generare risorse al servizio del debito. | I6: L’impresa non è in grado in futuro di generare risorse al servizio del debito. | J6: Indicare da dove provengono dette risorse. | K6: Indicare cosa si intende fare per sostenere il piano in altro modo | L6: =+OFFSET(F6,0,IF(F6,2,3)) -> L’impresa è in grado in futuro di generare risorse al servizio del debito. | M6: =+OFFSET(F6,0,IF(F6,4,5)) -> Indicare da dove provengono dette risorse.
E7: Il risultato delle proiezioni finanziarie di cui al punto 4.10 della presente Sezione tende ad essere positivo? | F7: FALSE | H7: Il risultato delle proiezioni finanziarie tende ad essere positivo. | I7: Il risultato delle proiezioni finanziarie tende ad essere negativo. | J7: Aggiungere eventuali commenti | K7: Aggiungere eventuali commenti | L7: =+OFFSET(F7,0,IF(F7,2,3)) -> Il risultato delle proiezioni finanziarie tende ad essere negativo. | M7: =+OFFSET(F7,0,IF(F7,4,5)) -> Aggiungere eventuali commenti
B8: 5.2 | E8: Il piano tiene conto, anche attraverso prove di resistenza (stress test), dei fattori di rischio e di incertezza ai quali è maggiormente esposta l’impresa? | F8: FALSE | H8: Il piano tiene conto, anche attraverso prove di resistenza (stress test), dei fattori di rischio e di incertezza ai quali è maggiormente esposta l’impresa. | I8: Il piano non tiene conto, anche attraverso prove di resistenza (stress test), dei fattori di rischio e di incertezza ai quali è maggiormente esposta l’impresa. | J8: Indicare i risultati dello stress test | K8: Indicare le ragioni che hanno condotto i relatori a non sottoporre il piano allo stress test | L8: =+OFFSET(F8,0,IF(F8,2,3)) -> Il piano non tiene conto, anche attraverso prove di resistenza (stress test), dei fattori di rischio e di incertezza ai quali è maggiormente esposta l’impresa. | M8: =+OFFSET(F8,0,IF(F8,4,5)) -> Indicare le ragioni che hanno condotto i relatori a non sottoporre il piano allo stress test
E9: Tali prove sono coerenti con i rischi emersi ad esito dell’intervista delle diverse funzioni aziendali avendo comunque riguardo alle prospettive di mercato? | H9: I test effettuati sono coerenti con i rischi emersi ad esito dell’intervista delle diverse funzioni aziendali avendo comunque riguardo alle prospettive di mercato. | I9: I test effettuati sono coerenti con i rischi emersi ad esito dell’intervista delle diverse funzioni aziendali avendo comunque riguardo alle prospettive di mercato. | J9: Aggiungere eventuali commenti | K9: Aggiungere eventuali commenti | L9: =+OFFSET(F9,0,IF(F9,2,3)) -> I test effettuati sono coerenti con i rischi emersi ad esito dell’intervista delle diverse funzioni aziendali avendo comunque riguardo alle prospettive di mercato. | M9: =+OFFSET(F9,0,IF(F9,4,5)) -> Aggiungere eventuali commenti
B10: 5.3 | E10: La generazione di flussi positivi al servizio del debito dipende solo dalle iniziative industriali? | F10: FALSE | H10: La generazione di flussi positivi al servizio del debito dipende solo dalle iniziative industriali. | I10: La generazione di flussi positivi al servizio del debito non dipende solo dalle iniziative industriali. | J10: Aggiungere eventuali commenti | K10: Aggiungere eventuali commenti | L10: =+OFFSET(F10,0,IF(F10,2,3)) -> La generazione di flussi positivi al servizio del debito non dipende solo dalle iniziative industriali. | M10: =+OFFSET(F10,0,IF(F10,4,5)) -> Aggiungere eventuali commenti
B11: 5.4 | E11: A quanto ammonta il debito che deve essere servito nei singoli anni del piano? | F11: FALSE | I11: =+IF(F11,"Il debito che deve essere servito nei singoli anni del piano ammonta a"&s&E12&pu,"")
C12: Ulteriori commenti | E12: Il debito complessivo da servire è di 500.000 €, suddiviso in rate annuali di 100.000 € per cinque anni | F12: FALSE
B13: 5.5 | E13: Come l’imprenditore intende fronteggiare il debito che deve essere coperto nei diversi anni attraverso i flussi al servizio dello stesso? | F13: FALSE | I13: =+IF(F13,"L’imprenditore intende fronteggiare il debito che deve essere coperto nei diversi anni attraverso i flussi al servizio dello stesso"&s&E14&pu,"")
C14: Ulteriori commenti | E14: L’imprenditore prevede di utilizzare i flussi di cassa generati dal miglioramento operativo e da un incremento dei ricavi, insieme alla rinegoziazione di alcuni termini di pagamento con i fornitori. | F14: FALSE
H15: Frase VERO | I15: Frase FALSO | J15: Frase suggerimento per commenti in caso di risposta positiva | K15: Frase suggerimento per commenti in caso di risposta negativa | L15: Frase Completa | M15: Suggerimento
B16: 5.6 | E16: Le proposte consentono, in via prognostica, il rispetto del minimo legale del capitale sociale al momento della conclusione dell’accordo, fatte salve le disposizioni speciali? | F16: FALSE | H16: Le proposte consentono, in via prognostica, il rispetto del minimo legale del capitale sociale al momento della conclusione dell’accordo, fatte salve le disposizioni speciali. | I16: Le proposte non consentono, in via prognostica, il rispetto del minimo legale del capitale sociale al momento della conclusione dell’accordo, fatte salve le disposizioni speciali. | J16: Aggiungere eventuali commenti | K16: Aggiungere eventuali commenti | L16: =+OFFSET(F16,0,IF(F16,2,3)) -> Le proposte non consentono, in via prognostica, il rispetto del minimo legale del capitale sociale al momento della conclusione dell’accordo, fatte salve le disposizioni speciali. | M16: =+OFFSET(F16,0,IF(F16,4,5)) -> Aggiungere eventuali commenti
A18: 6 | C18: In caso di gruppi di imprese
B19: 6.1 | E19: Il piano è redatto per le singole imprese? | F19: FALSE | H19: Il piano è redatto per le singole imprese. | I19: Il piano è redatto per le singole imprese. | J19: Aggiungere eventuali commenti | K19: Aggiungere eventuali commenti | L19: =+OFFSET(F19,0,IF(F19,2,3)) -> Il piano è redatto per le singole imprese. | M19: =+OFFSET(F19,0,IF(F19,4,5)) -> Aggiungere eventuali commenti
B20: 6.2 | E20: Il piano dà evidenza dei rapporti economici, finanziari e patrimoniali infragruppo? | F20: FALSE | H20: Il piano dà evidenza dei rapporti economici, finanziari e patrimoniali infragruppo. | I20: Il piano non dà evidenza dei rapporti economici, finanziari e patrimoniali infragruppo. | J20: Aggiungere eventuali commenti | K20: Aggiungere eventuali commenti | L20: =+OFFSET(F20,0,IF(F20,2,3)) -> Il piano non dà evidenza dei rapporti economici, finanziari e patrimoniali infragruppo. | M20: =+OFFSET(F20,0,IF(F20,4,5)) -> Aggiungere eventuali commenti
B21: 6.3 | E21: Vi sono altre imprese del gruppo che presentano difficoltà economico-finanziarie o patrimoniali? Come siintende agire per affrontarle? | F21: FALSE | H21: Vi sono altre imprese del gruppo che presentano difficoltà economico-finanziarie o patrimoniali? | I21: Non vi sono altre imprese del gruppo che presentano difficoltà economico-finanziarie o patrimoniali? | J21: Aggiungere eventuali commenti | K21: Aggiungere eventuali commenti | L21: =+OFFSET(F21,0,IF(F21,2,3)) -> Non vi sono altre imprese del gruppo che presentano difficoltà economico-finanziarie o patrimoniali? | M21: =+OFFSET(F21,0,IF(F21,4,5)) -> Aggiungere eventuali commenti
F22: FALSE | I22: =+IF(F22,"L’imprenditore intende affrontarle"&s&E23&pu,"")
C23: Come si intende agire per affrontarle? | E23: indicare come l'imprenditore intende affrontarle | F23: FALSE
B24: 6.4 | E24: Esistono altre imprese del gruppo la cui continuità aziendale dipende da quella dell’impresa? | F24: FALSE | I24: =+IF(F24,"Le altre imprese del gruppo la cui continuità aziendale dipende da quella dell’impresa sono"&s&E25&pu,"")
C25: Quali sono le imprese e perché? | E25: indicare quali sono le altre imprese del gruppo la cui continuità aziendale dipende da quella dell'impresa | F25: FALSE
B26: 6.5 | E26: Le operazioni infragruppo previste nel piano possono arrecare un pregiudizio per i creditori di un’altra impresa del gruppo? | F26: FALSE | H26: Le operazioni infragruppo previste nel piano possono arrecare un pregiudizio per i creditori di un’altra impresa del gruppo. | I26: Le operazioni infragruppo previste nel piano non possono arrecare un pregiudizio per i creditori di un’altra impresa del gruppo. | J26: Aggiungere eventuali commenti | K26: Aggiungere eventuali commenti | L26: =+OFFSET(F26,0,IF(F26,2,3)) -> Le operazioni infragruppo previste nel piano non possono arrecare un pregiudizio per i creditori di un’altra impresa del gruppo. | M26: =+OFFSET(F26,0,IF(F26,4,5)) -> Aggiungere eventuali commenti
C27: Specificare | E27: indicare quali sono le altre imprese del gruppo la cui continuità aziendale dipende da quella dell'impresa

Sheet Relazione
L2: RELAZIONE FINALE
L3: =+'SEZIONI 1-2'!$C$3 -> Alpha SPA
A4: SEZIONE 1-2 | L4: =+'SEZIONI 1-2'!C5 -> 0
B5: =+'SEZIONI 1-2'!$D$8 -> Il requisito dell’organizzazione dell’impresa | I5: =+B5 -> Il requisito dell’organizzazione dell’impresa | L5: =+I5 -> Il requisito dell’organizzazione dell’impresa
D6: =+'SEZIONI 1-2'!L9 -> L’impresa dispone delle risorse chiave (umane e tecniche) per la conduzione dell’attività. | J6: =+CONCATENATE(D6, IF(D7>"",(s&D7),"")) -> L’impresa dispone delle risorse chiave (umane e tecniche) per la conduzione dell’attività. Dispone infatti di tecnologie adeguate e l'organico risulta adeguato alle attività operative richieste per il raggiungimento degli obiettivi. | L6: {=+CONCATENATE(J6,AC,J7,AC,J8,s,J9,s,J10,s,J11,AC,J12,AC,J13)} -> L’impresa dispone delle risorse chiave (umane e tecniche) per la conduzione dell’attività. Dispone infatti di tecnologie adeguate e l'organico risulta adeguato alle attività operative richieste per il raggiungimento degli obiettivi. Da un punto di vista tecnico/economico, l’impresa dispone delle competenze necessarie per le iniziative industriali che l’imprenditore intende adottare. Ad oggi la capacità produttiva risulta adeguata e il management è in grado di affrontare le sfide previste dai piani aziendali e dal Budget. Il sistema informativo aziendale prevede un adeguato sistema di monitoraggio continuo dell'andamento aziendale. L'azienda dispone di un ERP in cloud che consente accessi autorizzati e protetti. I ricavi sono costantemente monitorati. L'azienda ha predisposto un sistema di Business Intelligence collegato al gestionale aziendale che consente un monitoraggio in tempo reale Gli ordini sono costantemente monitorati. La posizione finanziaria netta non è costantemente monitorata. L'azienda predispone solo un conto economico periodico e non predisponendo lo stato patrimoniale non è in grado di analizzare periodicamente le variazioni della PFN. Tuttavia è in corso un miglioramento del sistema di scritture di assestamento inframensili che consentirà di completare le analisi mensili. L'impresa non fa ancora ricorso a KPI che consentono valutazioni rapide e continue, è in grado di individuare gli indicatori di produttività coerenti con il proprio modello di business ed il proprio settore di attività, e di raccogliere ulteriori informazioni per la valutazione dell’andamento tendenziale. Per il momento l'azienda si limita ad utilizzare gli indicatori previsti dal sistema di qualità in quanto ritenuti adeguatamente informativi. L'impresa non dispone di un piano di tesoreria a 12 mesi. Non è in grado di predisporre un prospetto delle stime delle entrate e delle uscite finanziare almeno a 13 settimane, il cui scostamento con l’andamento corrente dovrà essere valutato a consuntivo.
C7: =+'SEZIONI 1-2'!M9 -> Aggiungere eventuali commenti | D7: Dispone infatti di tecnologie adeguate e l'organico risulta adeguato alle attività operative richieste per il raggiungimento degli obiettivi. | J7: =CONCATENATE(D8, IF(D9>"",(s&D9),"")) -> Da un punto di vista tecnico/economico, l’impresa dispone delle competenze necessarie per le iniziative industriali che l’imprenditore intende adottare. Ad oggi la capacità produttiva risulta adeguata e il management è in grado di affrontare le sfide previste dai piani aziendali e dal Budget.
D8: =+'SEZIONI 1-2'!L10 -> Da un punto di vista tecnico/economico, l’impresa dispone delle competenze necessarie per le iniziative industriali che l’imprenditore intende adottare. | J8: =+CONCATENATE(D10, IF(D11>"",(s&D11),"")) -> Il sistema informativo aziendale prevede un adeguato sistema di monitoraggio continuo dell'andamento aziendale. L'azienda dispone di un ERP in cloud che consente accessi autorizzati e protetti.
C9: =+'SEZIONI 1-2'!M10 -> Aggiungere eventuali commenti | D9: Ad oggi la capacità produttiva risulta adeguata e il management è in grado di affrontare le sfide previste dai piani aziendali e dal Budget. | J9: =+CONCATENATE(D12, IF(D13>"",(s&D13),"")) -> I ricavi sono costantemente monitorati. L'azienda ha predisposto un sistema di Business Intelligence collegato al gestionale aziendale che consente un monitoraggio in tempo reale
D10: =+'SEZIONI 1-2'!L11 -> Il sistema informativo aziendale prevede un adeguato sistema di monitoraggio continuo dell'andamento aziendale. | J10: =CONCATENATE(D14, IF(D15>"",(s&D15),"")) -> Gli ordini sono costantemente monitorati.
C11: =+'SEZIONI 1-2'!M11 -> Aggiungere eventuali commenti | D11: L'azienda dispone di un ERP in cloud che consente accessi autorizzati e protetti. | J11: =CONCATENATE(D16, IF(D17>"",(s&D17),"")) -> La posizione finanziaria netta non è costantemente monitorata. L'azienda predispone solo un conto economico periodico e non predisponendo lo stato patrimoniale non è in grado di analizzare periodicamente le variazioni della PFN. Tuttavia è in corso un miglioramento del sistema di scritture di assestamento inframensili che consentirà di completare le analisi mensili.
D12: =+'SEZIONI 1-2'!L12 -> I ricavi sono costantemente monitorati. | J12: =CONCATENATE(D18, IF(D19>"",(s&D19),""),s,D20,IF(D21>"",(s&D21),"")) -> L'impresa non fa ancora ricorso a KPI che consentono valutazioni rapide e continue, è in grado di individuare gli indicatori di produttività coerenti con il proprio modello di business ed il proprio settore di attività, e di raccogliere ulteriori informazioni per la valutazione dell’andamento tendenziale. Per il momento l'azienda si limita ad utilizzare gli indicatori previsti dal sistema di qualità in quanto ritenuti adeguatamente informativi.
C13: =+'SEZIONI 1-2'!M12 -> Aggiungere eventuali commenti | D13: L'azienda ha predisposto un sistema di Business Intelligence collegato al gestionale aziendale che consente un monitoraggio in tempo reale | J13: =CONCATENATE(D22, IF(D23>"",(s&D23),""),s,D24,IF(D25>"",(s&D25),"")) -> L'impresa non dispone di un piano di tesoreria a 12 mesi. Non è in grado di predisporre un prospetto delle stime delle entrate e delle uscite finanziare almeno a 13 settimane, il cui scostamento con l’andamento corrente dovrà essere valutato a consuntivo.
D14: =+'SEZIONI 1-2'!L13 -> Gli ordini sono costantemente monitorati.
C15: =+'SEZIONI 1-2'!M13 -> Aggiungere eventuali commenti | I15: =+B26 -> Rilevazione della situazione contabile e dell’andamento corrente | L15: =+I15 -> Rilevazione della situazione contabile e dell’andamento corrente
D16: =+'SEZIONI 1-2'!L14 -> La posizione finanziaria netta non è costantemente monitorata. | J16: =CONCATENATE(D27, IF(D28>"",(s&D28),"")) -> È stata disposta una situazione contabile recante le rettifiche di competenza e gli assestamenti di chiusura, nel rispetto del principio contabile OIC 30. | L16: {=+CONCATENATE(J16,s,J17,s,J18,s,J19,s,J20,s,J21,s,J22,AC,J23,AC,J24,AC,J25,AC,J26,AC,J27)} -> È stata disposta una situazione contabile recante le rettifiche di competenza e gli assestamenti di chiusura, nel rispetto del principio contabile OIC 30. La situazione è da considerarsi affidabile per quanto concerne la corretta rappresentazione della situazione debitoria dell'impresa. Il maggior contabile dei cespiti è superiore al valore di realizzo e a quello di mercato. La funzione amministrativa dispone di un prospetto recante l’anzianità dei crediti commerciali e , non sono state analizzate le cause del ritardo di incasso tale da consentire una valutazione oggettiva dei rischi di perdite sui crediti e una stima prudente dei tempi di incasso. I crediti sono suddivisibili in base alla loro anzianità. Per gli scaduti che superano la fisiologia (tempi ordinari di pagamento, pur oltre la scadenza contrattuale, che caratterizzano il settore), la stima del momento dell’incasso non è da considerarsi sufficientemente prudente. È disponibile un prospetto recante le rimanenze di magazzino con i tempi di movimentazione che consenta di individuare le giacenze oggetto di lenta rotazione. L'impresa non ha redatto un prospetto di riconciliazione tra la contabilità e quanto risultante dal certificato unico dei debiti tributari, dalla situazione debitoria complessiva dell’Agente della Riscossione. Ha redatto un prospetto di riconciliazione tra la contabilità e quanto risultante dal certificato unico dei debiti contributivi e assicurativi La Centrale rischi di Banca D'Italia viene esaminata periodicamente e non riconciliata con la contabilità. Il sistema di controllo dei rischi tiene conto anche delle passività potenziali. Esistono rilevanti rischi per garanzie concesse a terzi. L'organo di controllo o il revisore legale è composto da
C17: =+'SEZIONI 1-2'!M14 -> Indicare quale controllo viene fatto e come si intende intervenire per migliorare il sistema di controllo. | D17: L'azienda predispone solo un conto economico periodico e non predisponendo lo stato patrimoniale non è in grado di analizzare periodicamente le variazioni della PFN. Tuttavia è in corso un miglioramento del sistema di scritture di assestamento inframensili che consentirà di completare le analisi mensili. | J17: =CONCATENATE(D29, IF(D30>"",(s&D30),"")) -> La situazione è da considerarsi affidabile per quanto concerne la corretta rappresentazione della situazione debitoria dell'impresa.
D18: =+'SEZIONI 1-2'!L15 -> L'impresa non fa ancora ricorso a KPI che consentono valutazioni rapide e continue, | J18: =CONCATENATE(D31, IF(D32>"",(s&D32),"")) -> Il maggior contabile dei cespiti è superiore al valore di realizzo e a quello di mercato.
C19: =+'SEZIONI 1-2'!M15 -> 0 | J19: =CONCATENATE(D33, IF(D34>"",(s&D34),""),s,D35,IF(D36>"",(s&D36),"")) -> La funzione amministrativa dispone di un prospetto recante l’anzianità dei crediti commerciali e , non sono state analizzate le cause del ritardo di incasso tale da consentire una valutazione oggettiva dei rischi di perdite sui crediti e una stima prudente dei tempi di incasso.
D20: =+'SEZIONI 1-2'!L16 -> è in grado di individuare gli indicatori di produttività coerenti con il proprio modello di business ed il proprio settore di attività, e di raccogliere ulteriori informazioni per la valutazione dell’andamento tendenziale. | J20: =CONCATENATE(D37,IF(D38>"",(s&D38),"")) -> I crediti sono suddivisibili in base alla loro anzianità.
C21: =+'SEZIONI 1-2'!M16 -> Descrivere facendo riferimento ai metodi utilizzati (BSC, BMC, KPI, ecc) | D21: Per il momento l'azienda si limita ad utilizzare gli indicatori previsti dal sistema di qualità in quanto ritenuti adeguatamente informativi. | J21: =CONCATENATE(D39,IF(D40>"",(s&D40),"")) -> Per gli scaduti che superano la fisiologia (tempi ordinari di pagamento, pur oltre la scadenza contrattuale, che caratterizzano il settore), la stima del momento dell’incasso non è da considerarsi sufficientemente prudente.
D22: =+'SEZIONI 1-2'!L17 -> L'impresa non dispone di un piano di tesoreria a 12 mesi. | J22: =CONCATENATE(D41,IF(D42>"",(s&D42),"")) -> È disponibile un prospetto recante le rimanenze di magazzino con i tempi di movimentazione che consenta di individuare le giacenze oggetto di lenta rotazione.
C23: =+'SEZIONI 1-2'!M17 -> Spiegare le motivazioni per le quali non è stato redatto un piano di tesoreria e come si intende rimuovere gli ostacoli. | J23: =CONCATENATE(D43, IF(D44>"",(s&D44),""),s,D45,IF(D46>"",(s&D46),"")) -> L'impresa non ha redatto un prospetto di riconciliazione tra la contabilità e quanto risultante dal certificato unico dei debiti tributari, dalla situazione debitoria complessiva dell’Agente della Riscossione. Ha redatto un prospetto di riconciliazione tra la contabilità e quanto risultante dal certificato unico dei debiti contributivi e assicurativi
D24: =+'SEZIONI 1-2'!L18 -> Non è in grado di predisporre un prospetto delle stime delle entrate e delle uscite finanziare almeno a 13 settimane, il cui scostamento con l’andamento corrente dovrà essere valutato a consuntivo. | J24: =CONCATENATE(D47, IF(D48>"",(s&D48),""),s,D49,IF(D50>"",(s&D50),"")) -> La Centrale rischi di Banca D'Italia viene esaminata periodicamente e non riconciliata con la contabilità.
C25: =+'SEZIONI 1-2'!M18 -> Spiegare le motivazioni per le quali non è stato redatto il prospetto e come si intende rimuovere gli ostacoli. | J25: =CONCATENATE(D51,IF(D52>"",(s&D52),"")) -> Il sistema di controllo dei rischi tiene conto anche delle passività potenziali.
B26: =+'SEZIONI 1-2'!$D$20 -> Rilevazione della situazione contabile e dell’andamento corrente | J26: =CONCATENATE(D53,IF(D54>"",(s&D54),"")) -> Esistono rilevanti rischi per garanzie concesse a terzi.
D27: =+'SEZIONI 1-2'!L21 -> È stata disposta una situazione contabile recante le rettifiche di competenza e gli assestamenti di chiusura, nel rispetto del principio contabile OIC 30. | J27: =CONCATENATE(D55,IF(D56>"",(s&D56),"")) -> L'organo di controllo o il revisore legale è composto da
C28: =+'SEZIONI 1-2'!M21 -> Aggiungere eventuali commenti
D29: =+'SEZIONI 1-2'!L22 -> La situazione è da considerarsi affidabile per quanto concerne la corretta rappresentazione della situazione debitoria dell'impresa. | L29: =+I32 -> Individuazione delle strategie di intervento atte a prevenire e rimuovere le cause della crisi
C30: =+'SEZIONI 1-2'!M22 -> Aggiungere eventuali commenti | L30: {=+CONCATENATE(J33,s,J34,s,J35,AC,J36,s,J37,s,J38,s,J39,s,J40,s,J41,s,J42,AC,J43,AC,J44,s,J45,s,J46,s,J47,s,J48,s,J49,AC,J50,s,J51,s,J52,s,J53,s,J54,AC,J55)} -> L’assetto contabile, amministrativo e contabile non ha rilevato elementi tali da far percepire uno stato di crisi o di squilibrio patrimoniale e/o economico finanziario. Per quanto concerne lo stato di crisi, lo squilibrio percepito è di carattere: economico, patrimoniale e finanziario. Sono peggiorati rispetto all'anno precedente i seguenti indicatori: fatturato, margine di contribuzione, margine di contribuzione %, EBITDA, incidenza delle passività a breve, capitale circolante netto e posizione finanziaria netta. altro (specificare) Lo stato di crisi ha causato anomalie: • da un punto di vista commerciale; • nei rapporti con le banche; • da un punto di vista gestionale. Da un punto di vista commerciale si sono verificati mancati rilevanti pagamenti a fornitori, significativa rinegoziazione delle condizioni di pagamento e altro (specificare). Nei rapporti con le banche sono state rilevate aumento anomalo dei crediti impagati e altro (specificare). Da un punto di vista gestionale si segnala la perdita di clienti o commesse importanti, comparsa di concorrenti ostili e/o nuovi entranti che rischiano di ridurre ulteriormente le quote di mercato e altro (specificare). La situazione di difficoltà descritta ha causato un debito da ristrutturare (per mancati pagamenti e/o richieste di rientro) per fornitori di beni e servizi indispensabili e altro (specificare). Sul lato delle iniziative dei creditori si segnalano decreti ingiuntivi ricevuti ed atti di ricognitivi di avvio di azioni per il recupero dei crediti e altro (specificare). Tenuto conto delle manifestazioni, le cause sono: riduzione della redditività, riduzione della competività sul mercato e aumento dei costi operativi non trasferibile sui prezzi di vendita. L’organo di controllo ed il revisore, quando in carica, non ritengono che il quadro fornito dall’imprenditore sia completo e adeguato. L'impresa ha individuato le strategie di intervento e le iniziative industriali che intende adottare. Esistono strategie di successo adottate dalla concorrenza. Tali strategie sono adottabili dall'impresa. L’impresa non dispone delle capacità e delle competenze manageriali per realizzare le iniziative industriali. Per quanto concerne i tempi e gli effetti in termini di ricavi, di costi e di investimenti delle iniziative da adottare I tempi previsti per le iniziative industriali sono di 12 mesi, con effetti attesi su ricavi in lieve crescita e costi iniziali moderati. Le relative funzioni aziendali responsabili sono Le funzioni responsabili sono l’area manageriale e il reparto operativo per l’implementazione.. Sono prospettabili iniziative alternative nel caso in cui le iniziative dovessero dimostrarsi inefficaci e si manifestassero scostamenti tra gli obiettivi pianificati e quelli raggiunti. In precedenza sono stati predisposti ulteriori piani. Il piano è coerente con i piani redatti in precedenza e non vi sono differenze significative. Il piano appare credibile. È fondato su intenzioni strategiche chiare e razionali, condivisibili da parte di un lettore informato quale è l’esperto, coerenti con la situazione di fatto dell’impresa e del contesto in cui opera. Le strategie di intervento e le iniziative industriali individuate dall’imprenditore appaiono appropriate per il superamento delle cause della crisi.
D31: =+'SEZIONI 1-2'!L23 -> Il maggior contabile dei cespiti è superiore al valore di realizzo e a quello di mercato.
C32: =+'SEZIONI 1-2'!M23 -> L'impresa intende quanto meno appostare con prudenza adeguati fondi rischi e fondi per l’adeguamento delle attività e delle passività? | I32: =+B63 -> Individuazione delle strategie di intervento atte a prevenire e rimuovere le cause della crisi
D33: =+'SEZIONI 1-2'!L24 -> La funzione amministrativa dispone di un prospetto recante l’anzianità dei crediti commerciali e | J33: =CONCATENATE(D64,IF(D65>"",(s&D65),"")) -> L’assetto contabile, amministrativo e contabile non ha rilevato elementi tali da far percepire uno stato di crisi o di squilibrio patrimoniale e/o economico finanziario.
C34: =+'SEZIONI 1-2'!M24 -> 0 | J34: =CONCATENATE(D66,IF(D67>"",(s&D67),"")) -> Per quanto concerne lo stato di crisi, lo squilibrio percepito è di carattere: economico, patrimoniale e finanziario. Sono peggiorati rispetto all'anno precedente i seguenti indicatori: fatturato, margine di contribuzione, margine di contribuzione %, EBITDA, incidenza delle passività a breve, capitale circolante netto e posizione finanziaria netta. altro (specificare)
D35: =+'SEZIONI 1-2'!L25 -> , non sono state analizzate le cause del ritardo di incasso tale da consentire una valutazione oggettiva dei rischi di perdite sui crediti e una stima prudente dei tempi di incasso. | J35: =CONCATENATE(D68,IF(D69>"",(s&D69),"")) -> Lo stato di crisi ha causato anomalie: • da un punto di vista commerciale; • nei rapporti con le banche; • da un punto di vista gestionale.
C36: =+'SEZIONI 1-2'!M25 -> Indicare eventuali interventi in termini di credit management | J36: =CONCATENATE(D70,IF(D71>"",(s&D71),"")) -> Da un punto di vista commerciale si sono verificati mancati rilevanti pagamenti a fornitori, significativa rinegoziazione delle condizioni di pagamento e altro (specificare).
D37: =+'SEZIONI 1-2'!L26 -> I crediti sono suddivisibili in base alla loro anzianità. | J37: =CONCATENATE(D72,IF(D73>"",(s&D73),"")) -> Nei rapporti con le banche sono state rilevate aumento anomalo dei crediti impagati e altro (specificare).
C38: =+'SEZIONI 1-2'!M26 -> Aggiungere eventuali commenti | J38: =CONCATENATE(D74,IF(D75>"",(s&D75),"")) -> Da un punto di vista gestionale si segnala la perdita di clienti o commesse importanti, comparsa di concorrenti ostili e/o nuovi entranti che rischiano di ridurre ulteriormente le quote di mercato e altro (specificare).
D39: =+'SEZIONI 1-2'!L27 -> Per gli scaduti che superano la fisiologia (tempi ordinari di pagamento, pur oltre la scadenza contrattuale, che caratterizzano il settore), la stima del momento dell’incasso non è da considerarsi sufficientemente prudente. | J39: =CONCATENATE(D76,IF(D77>"",(s&D77),"")) -> La situazione di difficoltà descritta ha causato un debito da ristrutturare (per mancati pagamenti e/o richieste di rientro) per fornitori di beni e servizi indispensabili e altro (specificare).
C40: =+'SEZIONI 1-2'!M27 -> Quali elementi non sono valutati con la dovuta prudenza? | J40: =CONCATENATE(D78,IF(D79>"",(s&D79),"")) -> Sul lato delle iniziative dei creditori si segnalano decreti ingiuntivi ricevuti ed atti di ricognitivi di avvio di azioni per il recupero dei crediti e altro (specificare).
D41: =+'SEZIONI 1-2'!L28 -> È disponibile un prospetto recante le rimanenze di magazzino con i tempi di movimentazione che consenta di individuare le giacenze oggetto di lenta rotazione. | J41: =CONCATENATE(D80,IF(D81>"",(s&D81),"")) -> Tenuto conto delle manifestazioni, le cause sono: riduzione della redditività, riduzione della competività sul mercato e aumento dei costi operativi non trasferibile sui prezzi di vendita.
C42: =+'SEZIONI 1-2'!M28 -> Quali sono le giacenze di magazzino a lenta rotazione? | J42: =CONCATENATE(D82,IF(D83>"",(s&D83),"")) -> L’organo di controllo ed il revisore, quando in carica, non ritengono che il quadro fornito dall’imprenditore sia completo e adeguato.
D43: =+'SEZIONI 1-2'!L29 -> L'impresa non ha redatto un prospetto di riconciliazione tra la contabilità e quanto risultante dal certificato unico dei debiti tributari, dalla situazione debitoria complessiva dell’Agente della Riscossione. | J43: =CONCATENATE(D84,IF(D85>"",(s&D85),"")) -> L'impresa ha individuato le strategie di intervento e le iniziative industriali che intende adottare.
C44: =+'SEZIONI 1-2'!M29 -> Indicare le cause e gli interventi in merito | J44: =CONCATENATE(D86,IF(D87>"",(s&D87),"")) -> Esistono strategie di successo adottate dalla concorrenza.
D45: =+'SEZIONI 1-2'!L30 -> Ha redatto un prospetto di riconciliazione tra la contabilità e quanto risultante dal certificato unico dei debiti contributivi e assicurativi | J45: =CONCATENATE(D88,IF(D89>"",(s&D89),"")) -> Tali strategie sono adottabili dall'impresa.
C46: =+'SEZIONI 1-2'!M30 -> Indicare le cause e gli interventi in merito | J46: =CONCATENATE(D90,IF(D91>"",(s&D91),"")) -> L’impresa non dispone delle capacità e delle competenze manageriali per realizzare le iniziative industriali.
D47: =+'SEZIONI 1-2'!L31 -> La Centrale rischi di Banca D'Italia viene esaminata periodicamente e | J47: =CONCATENATE(D92,IF(D93>"",(s&D93),"")) -> Per quanto concerne i tempi e gli effetti in termini di ricavi, di costi e di investimenti delle iniziative da adottare I tempi previsti per le iniziative industriali sono di 12 mesi, con effetti attesi su ricavi in lieve crescita e costi iniziali moderati.
C48: =+'SEZIONI 1-2'!M31 -> 0 | J48: =CONCATENATE(D94,IF(D95>"",(s&D95),"")) -> Le relative funzioni aziendali responsabili sono Le funzioni responsabili sono l’area manageriale e il reparto operativo per l’implementazione..
D49: =+'SEZIONI 1-2'!L32 -> non riconciliata con la contabilità. | J49: =CONCATENATE(D96,IF(D97>"",(s&D97),"")) -> Sono prospettabili iniziative alternative nel caso in cui le iniziative dovessero dimostrarsi inefficaci e si manifestassero scostamenti tra gli obiettivi pianificati e quelli raggiunti.
C50: =+'SEZIONI 1-2'!M32 -> Indicare le cause e gli interventi in merito | J50: =CONCATENATE(D98,IF(D99>"",(s&D99),"")) -> In precedenza sono stati predisposti ulteriori piani.
D51: =+'SEZIONI 1-2'!L33 -> Il sistema di controllo dei rischi tiene conto anche delle passività potenziali. | J51: =CONCATENATE(D100,IF(D101>"",(s&D101),"")) -> Il piano è coerente con i piani redatti in precedenza
C52: =+'SEZIONI 1-2'!M33 -> Di che entità sono eventuali passività potenziali? | J52: =CONCATENATE(D102,IF(D103>"",(s&D103),"")) -> e non vi sono differenze significative.
D53: =+'SEZIONI 1-2'!L34 -> Esistono rilevanti rischi per garanzie concesse a terzi. | J53: =CONCATENATE(D104,IF(D105>"",(s&D105),"")) -> Il piano appare credibile.
C54: =+'SEZIONI 1-2'!M34 -> Descrivere e precisare se ne è stato tenuto conto a livello di fondi rischi. | J54: =CONCATENATE(D106,IF(D107>"",(s&D107),"")) -> È fondato su intenzioni strategiche chiare e razionali, condivisibili da parte di un lettore informato quale è l’esperto, coerenti con la situazione di fatto dell’impresa e del contesto in cui opera. | L54: =+I57 -> Le proiezioni dei flussi finanziari
D55: =+'SEZIONI 1-2'!L35 -> L'organo di controllo o il revisore legale è composto da | J55: =CONCATENATE(D108,IF(D109>"",(s&D109),"")) -> Le strategie di intervento e le iniziative industriali individuate dall’imprenditore appaiono appropriate per il superamento delle cause della crisi. | L55: {=+CONCATENATE(J58,AC,J59,AC,J60,s,J61,s,J62,s,J63,AC,J64,s,J65,s,J66,AC,J67,AC,J68,AC,J69,AC,J70,s,J71,AC,J72,AC,J73,s,J74,s,J75,s,J76,AC,J77,AC,J78,AC,J79,AC,J80,AC,J81,AC,J82,AC,J83)} -> La stima delle proiezioni dei flussi finanziari del piano è l'esito di un percorso che si dipana nelle seguenti fasi successive: stima dei ricavi, stima dei costi variabili correlati ai ricavi, stima dei costi fissi, stima degli investimenti, stima degli effetti delle iniziative industriali che si intendono intraprendere in discontinuità rispetto al passato, verifica di coerenza dei dati economici prognostici, stima del pagamento delle imposte sul reddito, declinazione finanziaria delle grandezze economiche e determinazione dei flussi al servizio del debito, declinazione patrimoniale muovendo dalla situazione contabile di partenza e altro (specificare). Le proiezioni fondate su previsioni coprono un periodo massimo di 5 anni. I ricavi sono stati stimati nel seguente modo: Indicare la stima dei ricavi. Le proiezioni dei ricavi sono coerenti con i dati storici e quelli correnti. Le variazioni dei ricavi prospettici rispetto al dato corrente dell’esercizio in corso sono state giustificate in maniera adeguata. Le variazioni dei ricavi del piano sono state confrontate con le prospettive del settore. La metodologia di stima dei costi variabili correlati ai ricavi e dei costi fissi è la seguente: Indicare la metodologia di stima dei costi variabili e dei costi fissi. La stima dei costi variabili e dei costi di struttura è coerente con la situazione in atto e con i dati storici. I risparmi dei costi variabili e fissi sono: i risparmi previsti derivano dall’efficientamento dei processi produttivi, stimati in una riduzione del 7% dei costi variabili.. I possibili rischi che derivano dai risparmi di costo: i risparmi previsti derivano dall’efficientamento dei processi produttivi, stimati in una riduzione del 7% dei costi variabili.. La metodologia di stima degli investimenti è la seguente: Indicare la metodologia di stima degli investimenti. La società non svolge più attività. Il piano tiene conto in misura adeguata degli investimenti di mantenimento occorrenti. La metodologia di stima degli effetti delle iniziative industriali che si intendono intraprendere in discontinuità rispetto al passato è la seguente: Indicare la metodologia di stima degli effetti delle iniziative industriali che si intendono intraprendere in discontinuità rispetto al passato. La stima degli effetti di tali iniziative (in termini di investimenti, ricavi e costi) è coerente con le informazioni disponibili ed è ritenuta giustificata dalle diverse funzioni aziendali. I dati economici prognostici sono coerenti. È stata svolta una verifica di ragionevolezza della redditività prospettica quale risulta dai paragrafi precedenti. La redditività ed i principali indicatori chiave gestionali (KPI) prospettici sono coerenti con l’andamento storico. Non è giustificata ogni differenza tra l’incidenza del margine operativo lordo sui ricavi ed i benchmark di mercato disponibili. Non sono previste operazioni straordinarie. Non è stata prevista la dismissione di cespiti d'investimento. Non è stato stimato il pagamento delle imposte sul reddito. Nella stima del pagamento delle imposte si è tenuto conto dell’effetto delle perdite fiscali a nuovo e del periodo di imputazione fiscale dei costi e dei ricavi. Non è presente declinazione finanziaria delle grandezze economiche e determinazione dei flussi al servizio del debito. La determinazione dei flussi finanziari al servizio del debito è stata effettuata muovendo dai dati economici. Essa ha avuto luogo: • Attraverso il ciclo di conversione in flussi di cassa che tiene conto dei tempi di incasso dei ricavi, di pagamento dei costi e di rigiro del magazzino. • Deducendo dai flussi così determinati gli investimenti previsti (sia quelli di mantenimento che quelli relativi alle iniziative industriali) e il pagamento delle imposte. Aggiungere eventuali commenti. • Per semplicità le micro e le piccole imprese possono ricorrere alle sole grandezze economiche senza convertirle in flussi di cassa. L'impresa è considerata tra le micro e piccole imprese. L'impresa ha verificato che l’ammontare degli investimenti di mantenimento sia adeguatamente espresso dagli ammortamenti (portando una rettifica in caso contrario). L'impresa ha considerato l’effetto delle iniziative industriali previste. L'impresa ha determinato le grandezze patrimoniali. Su di esse si innestano le poposte alle parti interessate e viene calcolata la stima dell’andamento del patrimonio netto al termine dei singoli anni del piano.
C56: =+'SEZIONI 1-2'!M35 -> Indicare i nominativi e eventuali
I57: =+B111 -> Le proiezioni dei flussi finanziari
J58: =CONCATENATE(D112,IF(D113>"",(s&D113),"")) -> La stima delle proiezioni dei flussi finanziari del piano è l'esito di un percorso che si dipana nelle seguenti fasi successive: stima dei ricavi, stima dei costi variabili correlati ai ricavi, stima dei costi fissi, stima degli investimenti, stima degli effetti delle iniziative industriali che si intendono intraprendere in discontinuità rispetto al passato, verifica di coerenza dei dati economici prognostici, stima del pagamento delle imposte sul reddito, declinazione finanziaria delle grandezze economiche e determinazione dei flussi al servizio del debito, declinazione patrimoniale muovendo dalla situazione contabile di partenza e altro (specificare).
J59: =CONCATENATE(D114,IF(D115>"",(s&D115),"")) -> Le proiezioni fondate su previsioni coprono un periodo massimo di 5 anni.
J60: =CONCATENATE(D116,IF(D117>"",(s&D117),"")) -> I ricavi sono stati stimati nel seguente modo: Indicare la stima dei ricavi.
J61: =IF(J60="","",CONCATENATE(D118,IF(D119>"",(s&D119),""))) -> Le proiezioni dei ricavi sono coerenti con i dati storici e quelli correnti.
A62: SEZIONE 3-4 | J62: =IF(J60="","",CONCATENATE(D120,IF(D121>"",(s&D121),""))) -> Le variazioni dei ricavi prospettici rispetto al dato corrente dell’esercizio in corso sono state giustificate in maniera adeguata.
B63: =+'SEZIONI 3-4'!D3 -> Individuazione delle strategie di intervento atte a prevenire e rimuovere le cause della crisi | J63: =IF(J60="","",CONCATENATE(D122,IF(D123>"",(s&D123),""))) -> Le variazioni dei ricavi del piano sono state confrontate con le prospettive del settore.
D64: =+'SEZIONI 3-4'!L4 -> L’assetto contabile, amministrativo e contabile non ha rilevato elementi tali da far percepire uno stato di crisi o di squilibrio patrimoniale e/o economico finanziario. | J64: =CONCATENATE(D124,IF(D125>"",(s&D125),"")) -> La metodologia di stima dei costi variabili correlati ai ricavi e dei costi fissi è la seguente: Indicare la metodologia di stima dei costi variabili e dei costi fissi.
C65: =+'SEZIONI 3-4'!M4 -> Aggiungere eventuali commenti | J65: =IF(J64="","",CONCATENATE(D126,IF(D127>"",(s&D127),""))) -> La stima dei costi variabili e dei costi di struttura è coerente con la situazione in atto e con i dati storici.
D66: =+'SEZIONI 3-4'!I6 -> Per quanto concerne lo stato di crisi, lo squilibrio percepito è di carattere: economico, patrimoniale e finanziario. Sono peggiorati rispetto all'anno precedente i seguenti indicatori: fatturato, margine di contribuzione, margine di contribuzione %, EBITDA, incidenza delle passività a breve, capitale circolante netto e posizione finanziaria netta. altro (specificare) | J66: =IF(J64="","",CONCATENATE(D128,IF(D129>"",(s&D129),""))) -> I risparmi dei costi variabili e fissi sono: i risparmi previsti derivano dall’efficientamento dei processi produttivi, stimati in una riduzione del 7% dei costi variabili.. I possibili rischi che derivano dai risparmi di costo: i risparmi previsti derivano dall’efficientamento dei processi produttivi, stimati in una riduzione del 7% dei costi variabili..
J67: =CONCATENATE(D130,IF(D131>"",(s&D131),"")) -> La metodologia di stima degli investimenti è la seguente: Indicare la metodologia di stima degli investimenti.
D68: =+'SEZIONI 3-4'!I22 -> Lo stato di crisi ha causato anomalie: • da un punto di vista commerciale; • nei rapporti con le banche; • da un punto di vista gestionale. | J68: =CONCATENATE(D132,IF(D133>"",(s&D133),"")) -> La società non svolge più attività.
J69: =IF(J67="","",CONCATENATE(D134,IF(D135>"",(s&D135),""))) -> Il piano tiene conto in misura adeguata degli investimenti di mantenimento occorrenti.
D70: =+'SEZIONI 3-4'!I24 -> Da un punto di vista commerciale si sono verificati mancati rilevanti pagamenti a fornitori, significativa rinegoziazione delle condizioni di pagamento e altro (specificare). | J70: =CONCATENATE(D136,IF(D137>"",(s&D137),"")) -> La metodologia di stima degli effetti delle iniziative industriali che si intendono intraprendere in discontinuità rispetto al passato è la seguente: Indicare la metodologia di stima degli effetti delle iniziative industriali che si intendono intraprendere in discontinuità rispetto al passato.
J71: =+IF(J70="","",CONCATENATE(D138,IF(D139>"",(s&D139),""))) -> La stima degli effetti di tali iniziative (in termini di investimenti, ricavi e costi) è coerente con le informazioni disponibili ed è ritenuta giustificata dalle diverse funzioni aziendali.
D72: =+'SEZIONI 3-4'!I29 -> Nei rapporti con le banche sono state rilevate aumento anomalo dei crediti impagati e altro (specificare). | J72: =CONCATENATE(D140,IF(D141>"",(s&D141),"")) -> I dati economici prognostici sono coerenti.
J73: =CONCATENATE(D142,IF(D143>"",(s&D143),"")) -> È stata svolta una verifica di ragionevolezza della redditività prospettica quale risulta dai paragrafi precedenti.
D74: =+'SEZIONI 3-4'!I38 -> Da un punto di vista gestionale si segnala la perdita di clienti o commesse importanti, comparsa di concorrenti ostili e/o nuovi entranti che rischiano di ridurre ulteriormente le quote di mercato e altro (specificare). | J74: =CONCATENATE(D144,IF(D145>"",(s&D145),"")) -> La redditività ed i principali indicatori chiave gestionali (KPI) prospettici sono coerenti con l’andamento storico.
J75: =CONCATENATE(D146,IF(D147>"",(s&D147),"")) -> Non è giustificata ogni differenza tra l’incidenza del margine operativo lordo sui ricavi ed i benchmark di mercato disponibili.
D76: =+'SEZIONI 3-4'!I44 -> La situazione di difficoltà descritta ha causato un debito da ristrutturare (per mancati pagamenti e/o richieste di rientro) per fornitori di beni e servizi indispensabili e altro (specificare). | J76: =CONCATENATE(D148,IF(D149>"",(s&D149),"")) -> Non sono previste operazioni straordinarie.
J77: =CONCATENATE(D150,IF(D151>"",(s&D151),"")) -> Non è stata prevista la dismissione di cespiti d'investimento.
D78: =+'SEZIONI 3-4'!I54 -> Sul lato delle iniziative dei creditori si segnalano decreti ingiuntivi ricevuti ed atti di ricognitivi di avvio di azioni per il recupero dei crediti e altro (specificare). | J78: =CONCATENATE(D152,IF(D153>"",(s&D153),"")) -> Non è stato stimato il pagamento delle imposte sul reddito.
J79: =IF(J78="","",CONCATENATE(D154,IF(D155>"",(s&D155),""))) -> Nella stima del pagamento delle imposte si è tenuto conto dell’effetto delle perdite fiscali a nuovo e del periodo di imputazione fiscale dei costi e dei ricavi.
D80: =+'SEZIONI 3-4'!I62 -> Tenuto conto delle manifestazioni, le cause sono: riduzione della redditività, riduzione della competività sul mercato e aumento dei costi operativi non trasferibile sui prezzi di vendita. | J80: =CONCATENATE(D156,IF(D157>"",(s&D157),"")) -> Non è presente declinazione finanziaria delle grandezze economiche e determinazione dei flussi al servizio del debito.
J81: =IF(J80="","",CONCATENATE(D158,IF(D159>"",(s&D159),""))) -> La determinazione dei flussi finanziari al servizio del debito è stata effettuata muovendo dai dati economici. Essa ha avuto luogo: • Attraverso il ciclo di conversione in flussi di cassa che tiene conto dei tempi di incasso dei ricavi, di pagamento dei costi e di rigiro del magazzino. • Deducendo dai flussi così determinati gli investimenti previsti (sia quelli di mantenimento che quelli relativi alle iniziative industriali) e il pagamento delle imposte. Aggiungere eventuali commenti. • Per semplicità le micro e le piccole imprese possono ricorrere alle sole grandezze economiche senza convertirle in flussi di cassa. L'impresa è considerata tra le micro e piccole imprese. L'impresa ha verificato che l’ammontare degli investimenti di mantenimento sia adeguatamente espresso dagli ammortamenti (portando una rettifica in caso contrario). L'impresa ha considerato l’effetto delle iniziative industriali previste. | L81: =+I84 -> Il risanamento del debito
D82: =+'SEZIONI 3-4'!L72 -> L’organo di controllo ed il revisore, quando in carica, non ritengono che il quadro fornito dall’imprenditore sia completo e adeguato. | J82: =CONCATENATE(D160,IF(D161>"",(s&D161),"")) -> L'impresa ha determinato le grandezze patrimoniali. | L82: {=+CONCATENATE(J85,s,J86,AC,J87,s,J88,AC,J89,AC,J90,AC,J91,AC,J92)} -> L’impresa è in grado in futuro di generare risorse al servizio del debito. Il risultato delle proiezioni finanziarie tende ad essere negativo. Il piano non tiene conto, anche attraverso prove di resistenza (stress test), dei fattori di rischio e di incertezza ai quali è maggiormente esposta l’impresa. I test effettuati sono coerenti con i rischi emersi ad esito dell’intervista delle diverse funzioni aziendali avendo comunque riguardo alle prospettive di mercato. La generazione di flussi positivi al servizio del debito non dipende solo dalle iniziative industriali. Le proposte non consentono, in via prognostica, il rispetto del minimo legale del capitale sociale al momento della conclusione dell’accordo, fatte salve le disposizioni speciali.
C83: =+'SEZIONI 3-4'!M72 -> Indicare le ragioni | J83: =CONCATENATE(D162, IF(D163>"",(s&D163),""),s,D164,IF(D165>"",(s&D165),"")) -> Su di esse si innestano le poposte alle parti interessate e viene calcolata la stima dell’andamento del patrimonio netto al termine dei singoli anni del piano.
D84: =+'SEZIONI 3-4'!L73 -> L'impresa ha individuato le strategie di intervento e le iniziative industriali che intende adottare. | I84: =+'SEZIONI 5-6'!C5 -> Il risanamento del debito
C85: =+'SEZIONI 3-4'!M73 -> Quali strategie e quali iniziative? | J85: =CONCATENATE(D169,IF(D170>"",(s&D170),"")) -> L’impresa è in grado in futuro di generare risorse al servizio del debito.
D86: =+'SEZIONI 3-4'!L74 -> Esistono strategie di successo adottate dalla concorrenza. | J86: =CONCATENATE(D171,IF(D172>"",(s&D172),"")) -> Il risultato delle proiezioni finanziarie tende ad essere negativo.
C87: =+'SEZIONI 3-4'!M74 -> Quali strategie? | J87: =CONCATENATE(D173,IF(D174>"",(s&D174),"")) -> Il piano non tiene conto, anche attraverso prove di resistenza (stress test), dei fattori di rischio e di incertezza ai quali è maggiormente esposta l’impresa.
D88: =+'SEZIONI 3-4'!L75 -> Tali strategie sono adottabili dall'impresa. | J88: =CONCATENATE(D175,IF(D176>"",(s&D176),"")) -> I test effettuati sono coerenti con i rischi emersi ad esito dell’intervista delle diverse funzioni aziendali avendo comunque riguardo alle prospettive di mercato.
C89: =+'SEZIONI 3-4'!M75 -> Indicare se l'azienda intende avvalersene o meno | J89: =CONCATENATE(D177,IF(D178>"",(s&D178),"")) -> La generazione di flussi positivi al servizio del debito non dipende solo dalle iniziative industriali.
D90: =+'SEZIONI 3-4'!L76 -> L’impresa non dispone delle capacità e delle competenze manageriali per realizzare le iniziative industriali. | J90: =CONCATENATE(D179,IF(D180>"",(s&D180),""))
C91: =+'SEZIONI 3-4'!M76 -> Indicare quali lacune organizzative esistono e come l'impresa intende colmarle | J91: =CONCATENATE(D181,IF(D182>"",(s&D182),"")) | L91: =+I94 -> In caso di gruppi di imprese
D92: =+'SEZIONI 3-4'!I77 -> Per quanto concerne i tempi e gli effetti in termini di ricavi, di costi e di investimenti delle iniziative da adottare I tempi previsti per le iniziative industriali sono di 12 mesi, con effetti attesi su ricavi in lieve crescita e costi iniziali moderati. | J92: =CONCATENATE(D183,IF(D184>"",(s&D184),"")) -> Le proposte non consentono, in via prognostica, il rispetto del minimo legale del capitale sociale al momento della conclusione dell’accordo, fatte salve le disposizioni speciali. | L92: {=+CONCATENATE(J95,AC,J96,AC,J97,s,J98,AC,J99,AC,J100)} -> Il piano è redatto per le singole imprese. Il piano non dà evidenza dei rapporti economici, finanziari e patrimoniali infragruppo. Non vi sono altre imprese del gruppo che presentano difficoltà economico-finanziarie o patrimoniali? Le operazioni infragruppo previste nel piano non possono arrecare un pregiudizio per i creditori di un’altra impresa del gruppo.
C93: =+'SEZIONI 3-4'!M77 -> 0
D94: =+'SEZIONI 3-4'!I79 -> Le relative funzioni aziendali responsabili sono Le funzioni responsabili sono l’area manageriale e il reparto operativo per l’implementazione.. | I94: =+'SEZIONI 5-6'!C18 -> In caso di gruppi di imprese
C95: =+'SEZIONI 3-4'!M79 -> 0 | J95: =CONCATENATE(D187,IF(D188>"",(s&D188),"")) -> Il piano è redatto per le singole imprese.
D96: =+'SEZIONI 3-4'!L81 -> Sono prospettabili iniziative alternative nel caso in cui le iniziative dovessero dimostrarsi inefficaci e si manifestassero scostamenti tra gli obiettivi pianificati e quelli raggiunti. | J96: =CONCATENATE(D189,IF(D190>"",(s&D190),"")) -> Il piano non dà evidenza dei rapporti economici, finanziari e patrimoniali infragruppo.
C97: =+'SEZIONI 3-4'!M81 -> Quali iniziative alternative? | J97: =CONCATENATE(D191,IF(D192>"",(s&D192),"")) -> Non vi sono altre imprese del gruppo che presentano difficoltà economico-finanziarie o patrimoniali?
D98: =+'SEZIONI 3-4'!L82 -> In precedenza sono stati predisposti ulteriori piani. | J98: =CONCATENATE(D193,IF(D194>"",(s&D194),"")) | L98: ='SEZIONI 1-2'!E5 -> 0
C99: =+'SEZIONI 3-4'!M82 -> Indicare l'occasione in cui si è reso necessaria la redazione del piano, chi lo ha redatto e il grado di raggiungimento rispetto agli obiettivi indicati. | J99: =CONCATENATE(D195,IF(D196>"",(s&D196),"")) | L99: _________________________________
D100: =+'SEZIONI 3-4'!L83 -> Il piano è coerente con i piani redatti in precedenza | J100: =CONCATENATE(D197,IF(D198>"",(s&D198),"")) -> Le operazioni infragruppo previste nel piano non possono arrecare un pregiudizio per i creditori di un’altra impresa del gruppo.
C101: =+'SEZIONI 3-4'!M83 -> 0
...

Sheet Relazione Compatta (solo 365)
A4: Relazione in formato compatto (Disponibile solo con Excel 365)
A5: {=+_xlfn._xlws.FILTER(Relazione!L3:L99,(Relazione!L3:L99)>0)} -> Alpha SPA
A6: Il requisito dell’organizzazione dell’impresa
A7: L’impresa dispone delle risorse chiave (umane e tecniche) per la conduzione dell’attività. Dispone infatti di tecnologie adeguate e l'organico risulta adeguato alle attività operative richieste per il raggiungimento degli obiettivi. Da un punto di vista tecnico/economico, l’impresa dispone delle competenze necessarie per le iniziative industriali che l’imprenditore intende adottare. Ad oggi la capacità produttiva risulta adeguata e il management è in grado di affrontare le sfide previste dai piani aziendali e dal Budget. Il sistema informativo aziendale prevede un adeguato sistema di monitoraggio continuo dell'andamento aziendale. L'azienda dispone di un ERP in cloud che consente accessi autorizzati e protetti. I ricavi sono costantemente monitorati. L'azienda ha predisposto un sistema di Business Intelligence collegato al gestionale aziendale che consente un monitoraggio in tempo reale Gli ordini sono costantemente monitorati. La posizione finanziaria netta non è costantemente monitorata. L'azienda predispone solo un conto economico periodico e non predisponendo lo stato patrimoniale non è in grado di analizzare periodicamente le variazioni della PFN. Tuttavia è in corso un miglioramento del sistema di scritture di assestamento inframensili che consentirà di completare le analisi mensili. L'impresa non fa ancora ricorso a KPI che consentono valutazioni rapide e continue, è in grado di individuare gli indicatori di produttività coerenti con il proprio modello di business ed il proprio settore di attività, e di raccogliere ulteriori informazioni per la valutazione dell’andamento tendenziale. Per il momento l'azienda si limita ad utilizzare gli indicatori previsti dal sistema di qualità in quanto ritenuti adeguatamente informativi. L'impresa non dispone di un piano di tesoreria a 12 mesi. Non è in grado di predisporre un prospetto delle stime delle entrate e delle uscite finanziare almeno a 13 settimane, il cui scostamento con l’andamento corrente dovrà essere valutato a consuntivo.
A8: Rilevazione della situazione contabile e dell’andamento corrente
A9: È stata disposta una situazione contabile recante le rettifiche di competenza e gli assestamenti di chiusura, nel rispetto del principio contabile OIC 30. La situazione è da considerarsi affidabile per quanto concerne la corretta rappresentazione della situazione debitoria dell'impresa. Il maggior contabile dei cespiti è superiore al valore di realizzo e a quello di mercato. La funzione amministrativa dispone di un prospetto recante l’anzianità dei crediti commerciali e , non sono state analizzate le cause del ritardo di incasso tale da consentire una valutazione oggettiva dei rischi di perdite sui crediti e una stima prudente dei tempi di incasso. I crediti sono suddivisibili in base alla loro anzianità. Per gli scaduti che superano la fisiologia (tempi ordinari di pagamento, pur oltre la scadenza contrattuale, che caratterizzano il settore), la stima del momento dell’incasso non è da considerarsi sufficientemente prudente. È disponibile un prospetto recante le rimanenze di magazzino con i tempi di movimentazione che consenta di individuare le giacenze oggetto di lenta rotazione. L'impresa non ha redatto un prospetto di riconciliazione tra la contabilità e quanto risultante dal certificato unico dei debiti tributari, dalla situazione debitoria complessiva dell’Agente della Riscossione. Ha redatto un prospetto di riconciliazione tra la contabilità e quanto risultante dal certificato unico dei debiti contributivi e assicurativi La Centrale rischi di Banca D'Italia viene esaminata periodicamente e non riconciliata con la contabilità. Il sistema di controllo dei rischi tiene conto anche delle passività potenziali. Esistono rilevanti rischi per garanzie concesse a terzi. L'organo di controllo o il revisore legale è composto da
A10: Individuazione delle strategie di intervento atte a prevenire e rimuovere le cause della crisi
A11: L’assetto contabile, amministrativo e contabile non ha rilevato elementi tali da far percepire uno stato di crisi o di squilibrio patrimoniale e/o economico finanziario. Per quanto concerne lo stato di crisi, lo squilibrio percepito è di carattere: economico, patrimoniale e finanziario. Sono peggiorati rispetto all'anno precedente i seguenti indicatori: fatturato, margine di contribuzione, margine di contribuzione %, EBITDA, incidenza delle passività a breve, capitale circolante netto e posizione finanziaria netta. altro (specificare) Lo stato di crisi ha causato anomalie: • da un punto di vista commerciale; • nei rapporti con le banche; • da un punto di vista gestionale. Da un punto di vista commerciale si sono verificati mancati rilevanti pagamenti a fornitori, significativa rinegoziazione delle condizioni di pagamento e altro (specificare). Nei rapporti con le banche sono state rilevate aumento anomalo dei crediti impagati e altro (specificare). Da un punto di vista gestionale si segnala la perdita di clienti o commesse importanti, comparsa di concorrenti ostili e/o nuovi entranti che rischiano di ridurre ulteriormente le quote di mercato e altro (specificare). La situazione di difficoltà descritta ha causato un debito da ristrutturare (per mancati pagamenti e/o richieste di rientro) per fornitori di beni e servizi indispensabili e altro (specificare). Sul lato delle iniziative dei creditori si segnalano decreti ingiuntivi ricevuti ed atti di ricognitivi di avvio di azioni per il recupero dei crediti e altro (specificare). Tenuto conto delle manifestazioni, le cause sono: riduzione della redditività, riduzione della competività sul mercato e aumento dei costi operativi non trasferibile sui prezzi di vendita. L’organo di controllo ed il revisore, quando in carica, non ritengono che il quadro fornito dall’imprenditore sia completo e adeguato. L'impresa ha individuato le strategie di intervento e le iniziative industriali che intende adottare. Esistono strategie di successo adottate dalla concorrenza. Tali strategie sono adottabili dall'impresa. L’impresa non dispone delle capacità e delle competenze manageriali per realizzare le iniziative industriali. Per quanto concerne i tempi e gli effetti in termini di ricavi, di costi e di investimenti delle iniziative da adottare I tempi previsti per le iniziative industriali sono di 12 mesi, con effetti attesi su ricavi in lieve crescita e costi iniziali moderati. Le relative funzioni aziendali responsabili sono Le funzioni responsabili sono l’area manageriale e il reparto operativo per l’implementazione.. Sono prospettabili iniziative alternative nel caso in cui le iniziative dovessero dimostrarsi inefficaci e si manifestassero scostamenti tra gli obiettivi pianificati e quelli raggiunti. In precedenza sono stati predisposti ulteriori piani. Il piano è coerente con i piani redatti in precedenza e non vi sono differenze significative. Il piano appare credibile. È fondato su intenzioni strategiche chiare e razionali, condivisibili da parte di un lettore informato quale è l’esperto, coerenti con la situazione di fatto dell’impresa e del contesto in cui opera. Le strategie di intervento e le iniziative industriali individuate dall’imprenditore appaiono appropriate per il superamento delle cause della crisi.
A12: Le proiezioni dei flussi finanziari
A13: La stima delle proiezioni dei flussi finanziari del piano è l'esito di un percorso che si dipana nelle seguenti fasi successive: stima dei ricavi, stima dei costi variabili correlati ai ricavi, stima dei costi fissi, stima degli investimenti, stima degli effetti delle iniziative industriali che si intendono intraprendere in discontinuità rispetto al passato, verifica di coerenza dei dati economici prognostici, stima del pagamento delle imposte sul reddito, declinazione finanziaria delle grandezze economiche e determinazione dei flussi al servizio del debito, declinazione patrimoniale muovendo dalla situazione contabile di partenza e altro (specificare). Le proiezioni fondate su previsioni coprono un periodo massimo di 5 anni. I ricavi sono stati stimati nel seguente modo: Indicare la stima dei ricavi. Le proiezioni dei ricavi sono coerenti con i dati storici e quelli correnti. Le variazioni dei ricavi prospettici rispetto al dato corrente dell’esercizio in corso sono state giustificate in maniera adeguata. Le variazioni dei ricavi del piano sono state confrontate con le prospettive del settore. La metodologia di stima dei costi variabili correlati ai ricavi e dei costi fissi è la seguente: Indicare la metodologia di stima dei costi variabili e dei costi fissi. La stima dei costi variabili e dei costi di struttura è coerente con la situazione in atto e con i dati storici. I risparmi dei costi variabili e fissi sono: i risparmi previsti derivano dall’efficientamento dei processi produttivi, stimati in una riduzione del 7% dei costi variabili.. I possibili rischi che derivano dai risparmi di costo: i risparmi previsti derivano dall’efficientamento dei processi produttivi, stimati in una riduzione del 7% dei costi variabili.. La metodologia di stima degli investimenti è la seguente: Indicare la metodologia di stima degli investimenti. La società non svolge più attività. Il piano tiene conto in misura adeguata degli investimenti di mantenimento occorrenti. La metodologia di stima degli effetti delle iniziative industriali che si intendono intraprendere in discontinuità rispetto al passato è la seguente: Indicare la metodologia di stima degli effetti delle iniziative industriali che si intendono intraprendere in discontinuità rispetto al passato. La stima degli effetti di tali iniziative (in termini di investimenti, ricavi e costi) è coerente con le informazioni disponibili ed è ritenuta giustificata dalle diverse funzioni aziendali. I dati economici prognostici sono coerenti. È stata svolta una verifica di ragionevolezza della redditività prospettica quale risulta dai paragrafi precedenti. La redditività ed i principali indicatori chiave gestionali (KPI) prospettici sono coerenti con l’andamento storico. Non è giustificata ogni differenza tra l’incidenza del margine operativo lordo sui ricavi ed i benchmark di mercato disponibili. Non sono previste operazioni straordinarie. Non è stata prevista la dismissione di cespiti d'investimento. Non è stato stimato il pagamento delle imposte sul reddito. Nella stima del pagamento delle imposte si è tenuto conto dell’effetto delle perdite fiscali a nuovo e del periodo di imputazione fiscale dei costi e dei ricavi. Non è presente declinazione finanziaria delle grandezze economiche e determinazione dei flussi al servizio del debito. La determinazione dei flussi finanziari al servizio del debito è stata effettuata muovendo dai dati economici. Essa ha avuto luogo: • Attraverso il ciclo di conversione in flussi di cassa che tiene conto dei tempi di incasso dei ricavi, di pagamento dei costi e di rigiro del magazzino. • Deducendo dai flussi così determinati gli investimenti previsti (sia quelli di mantenimento che quelli relativi alle iniziative industriali) e il pagamento delle imposte. Aggiungere eventuali commenti. • Per semplicità le micro e le piccole imprese possono ricorrere alle sole grandezze economiche senza convertirle in flussi di cassa. L'impresa è considerata tra le micro e piccole imprese. L'impresa ha verificato che l’ammontare degli investimenti di mantenimento sia adeguatamente espresso dagli ammortamenti (portando una rettifica in caso contrario). L'impresa ha considerato l’effetto delle iniziative industriali previste. L'impresa ha determinato le grandezze patrimoniali. Su di esse si innestano le poposte alle parti interessate e viene calcolata la stima dell’andamento del patrimonio netto al termine dei singoli anni del piano.
A14: Il risanamento del debito
A15: L’impresa è in grado in futuro di generare risorse al servizio del debito. Il risultato delle proiezioni finanziarie tende ad essere negativo. Il piano non tiene conto, anche attraverso prove di resistenza (stress test), dei fattori di rischio e di incertezza ai quali è maggiormente esposta l’impresa. I test effettuati sono coerenti con i rischi emersi ad esito dell’intervista delle diverse funzioni aziendali avendo comunque riguardo alle prospettive di mercato. La generazione di flussi positivi al servizio del debito non dipende solo dalle iniziative industriali. Le proposte non consentono, in via prognostica, il rispetto del minimo legale del capitale sociale al momento della conclusione dell’accordo, fatte salve le disposizioni speciali.
A16: In caso di gruppi di imprese
A17: Il piano è redatto per le singole imprese. Il piano non dà evidenza dei rapporti economici, finanziari e patrimoniali infragruppo. Non vi sono altre imprese del gruppo che presentano difficoltà economico-finanziarie o patrimoniali? Le operazioni infragruppo previste nel piano non possono arrecare un pregiudizio per i creditori di un’altra impresa del gruppo.
A18: _________________________________
