Workbook
Name Beni: B[Bene]
Name Cat: Gruppi[Cat]
Name ic: DATI!$A$24
Name IR: RIGHT(DATI!$D$24,4)="IRES"
Name p: DATI!$A$1
Name Prat: Tabella3[Nome Pratica]
Name Ris: CalcoloRapido!A$12
Name ristr: Tabelle!$AF$8
Name t: DATI!$E$24
Name Tipi: TipoSoc[TIPO]
Name Tipim: TipoImm[Tipologia]
Name Valfisc: CalcoloRapido!A$8
Name Valnorm: CalcoloRapido!A$6
Name Valnormù: CalcoloRapido!A$6
Name VC: CalcoloRapido!A$7
Name VF: DATI!$E$33
Name VN: DATI!$E$32
Name VOE: CalcoloRapido!A$6
Name VP_1: CalcoloRapido!A$9

Sheet Foglio1
B2: ID | C2: CODTRIB | D2: DESCR
B3: 1 | C3: 1836 | D3: Imposta sostitutiva per l’assegnazione, cessione dei beni ai soci o società trasformate
B4: 2 | C4: 1837 | D4: Imposta sostitutiva sulle riserve in sospensione d’imposta annullate per effetto dell’assegnazione dei beni ai soci o società trasformate
B5: 3 | C5: 1127 | D5: Imposta sostitutiva per l’estromissione dei beni immobili strumentali dall’impresa individuale
B7: =DATI!$D$89 -> F24 DA VERSARE ENTRO IL 30/11/2025 | E7: INT | F7: DEC
B8: Codice tributo (assegnazione, cessione e società trasformate) | D8: =IF(DATI!I34>0,Foglio1!C3,"") -> 1836
B9: Importo 60% cod 1836 | D9: =(IF(DATI!$I$34>0,ROUND(DATI!$I$34*60%,2),"")) -> 5191.2 | E9: =+IFERROR(+IF(D9>0,(+TRUNC(D9)),""),"") -> 5191 | F9: =+IF(D9>0,+RIGHT(D9,2),"") -> ,2
B10: Importo 60% cod 1837 | D10: =IF(DATI!$I$36>0,ROUND(DATI!$I$36*60%,2),0) -> 0 | E10: =+IFERROR(+IF(D10>0,(+TRUNC(D10)),""),"") | F10: =+IF(D10>0,+RIGHT(D10,2),"")
B11: Tot importi | D11: =IFERROR(IF(D8>0,D9+D10,""),0) -> 5191.2 | E11: =+IFERROR(+IF(D11>0,(+TRUNC(D11)),""),"") -> 5191 | F11: =+IF(D11>0,+RIGHT(D11,2),"") -> ,2
B13: =DATI!$D$103 -> F24 DA VERSARE ENTRO IL 30/09/2025
B14: Codice tributo sospensione d'imposte | D14: =IF(DATI!I36>0,Foglio1!C4,"")
B15: Importo 40% cod 1836 | D15: =IF(DATI!$I$34>0,ROUND(DATI!$I$34*40%,2),"") -> 3460.8 | E15: =+IFERROR(+IF(D15>0,(+TRUNC(D15)),""),"") -> 3460 | F15: =+IF(D15>0,+RIGHT(D15,2),"") -> ,8
B16: Importo 40% cod 1837 | D16: =IF(DATI!$I$36>0,ROUND(DATI!$I$36*40%,2),0) -> 0 | E16: =+IFERROR(+IF(D16>0,(+TRUNC(D16)),""),"") | F16: =+IF(D16>0,+RIGHT(D16,2),"")
B17: Tot Importi | D17: =IFERROR(IF(D14>0,D15+D16,""),0) -> 3460.8 | E17: =+IFERROR(+IF(D17>0,(+TRUNC(D17)),""),"") -> 3460 | F17: =+IF(D17>0,+RIGHT(D17,2),"") -> ,8
B19: Anno di riferimento | D19: 2024
B20: Anno di riferimento | D20: =+IF(DATI!I36>0,2017,"")
B21: Anno di riferimento | D21: 2024
B22: Anno di riferimento | D22: =+IF(DATI!I36>0,2018,"")
B25: 0 0 | D25: =+IF(DATI!$I$34>0,Foglio1!B25,"") -> 0 0
B26: 0 0 | D26: =+IF(DATI!$I$36>0,Foglio1!B26,"")
B27: 0 0 | D27: =IF(DATI!I34>0,B27,"") -> 0 0

Sheet DATI
A1: 1
C7: Studio | H7: Cliente
C9: Ind. Studio | H9: Indirizzo
C11: Cap-Città | H11: Cap-Città
C13: P. IVA - C.F. | H13: P. IVA - C.F.
B18: =+"Simulazione operazione di "&B19&" agevolata relativa a beni immobili e mobili registrati di "&I7&" redatta da "&D7 -> Simulazione operazione di Assegnazione agevolata relativa a beni immobili e mobili registrati di redatta da
B19: =+OFFSET(Tabelle!AT1,A1,0) -> Assegnazione
D22: Nome | E22: Alpha SPA | K22: Quadro di controllo
A23: TRUE | D23: Tipo società | E23: Società a responsabilità limitata | G23: IRAP | H23: 0.039 | K23: I soci sono tutti agevolabili | N23: =+IFERROR(SUM(A_1[Agevolabile])/COUNTA(A_1[Nome]),"") -> 1
A24: FALSE | D24: =+"Imposta applicabile alle cessioni: "&VLOOKUP(E23,TipoSoc[],2,0) -> Imposta applicabile alle cessioni: IRES | E24: 0.24 | K24: Gli immobili sono tutti agevolabili | N24: =+IFERROR(SUM(B[Agevolabile])/COUNTA(B[Bene]),"") -> 1
A25: TRUE | D25: Comodo | H25: =+IF(RIGHT(D24,4)="IRES","Dividendi imponibili per il socio","NESSUNA TASSAZIONE DEI DIVIDENDI SUL SOCIO. RILEVA L'EVENTUALE SOTTOZERO") -> Dividendi imponibili per il socio | K25: La ripartizione delle quote somma 100% | N25: =+SUMPRODUCT(A_1[Quota partecipazione al momento dell''operazione],Soci!$A$7:$A$106) -> 100
A26: TRUE | K26: Tutti i beni in tabella sono stati assegnati | N26: =+(Assegnazione!$H$3=Beni!$H$3)*1 -> 1
D27: Aliquota applicabile | E27: =(A25*1+A26*1+A28*1>1)*2.5%+8% -> 0.105 | K27: Il patrimonio netto si è ridotto correttamente | N27: =+OR('Tassazione Soci'!$G$8=VF,p<>1)*1 -> 1
A28: FALSE
B30: Riepilogo Operazione
D32: Totale valore normale o di cessione Beni (A) | E32: =+Assegnazione!M3 -> 302400 | H32: Imposte sostitutive con agevolazione | K32: Imposte indirette | N32: Altre imposte
D33: - Totale valore fiscale (B) | E33: =+Assegnazione!H3 -> 220000 | H33: =+B19 -> Assegnazione
D34: = Base imponibile (A-B) (*) | E34: =+I34/E27 -> 82400 | H34: ="Imposta sostitutiva: "&TEXT(E27,"0,00%") -> Imposta sostitutiva: 10,50% | I34: =+Assegnazione!V3 -> 8652 | K34: IVA | L34: =+Assegnazione!R3 -> 0 | N34: Dirette sui soci | O34: =+'Tassazione Soci'!O12 -> 57200
D35: Effetti contabili | K35: Rettifica della detrazione | L35: =+'Rettifica della detrazione'!F3 -> 50000
D36: Ricavi - Variazioni delle rimanenze | E36: =+(SUMIF(B[Iscritto a Bilancio come],"Rimanenze",B[Valore contabile attribuito])-SUMIF(B[Iscritto a Bilancio come],"Rimanenze",B[Valore netto contabile fiscalmente riconosciuto]))*(p<3) -> 0 | H36: Affrancamento Riserve: 13% | I36: =+'Tassazione Soci'!J9 -> 0 | K36: Registro e IC | L36: =+Assegnazione!Y3+Assegnazione!Z3 -> 600 | N36: IRAP | O36: =+Assegnazione!Q3-SUMPRODUCT(Assegnazione[Agevolabile],Assegnazione[IRAP]) -> 0
D37: =+IF(E37>0,"Plusvalenza","Minusvalenza") -> Minusvalenza | E37: =+(SUMIF(B[Iscritto a Bilancio come],"<>"&"Rimanenze",B[Valore contabile attribuito])-SUMIF(B[Iscritto a Bilancio come],"<>"&"Rimanenze",B[Valore netto contabile fiscalmente riconosciuto]))*(p<3) -> 0 | H37: I rata (30/09/26) | I37: =+(I34+I36)*0.6 -> 5191.2
D38: Effetti sull'imponibile IRES | E38: =+E37*AND(p=2,E37<0) -> 0 | H38: II rata (30/11/26) | I38: =+I37/0.6*0.4 -> 3460.8 | K38: Indirette non agevolate | L38: =+SUMIF(Assegnazione[Agevolabile],0,Assegnazione[Ipotecaria e catastale senza agevolazione])+SUMIF(Assegnazione[Agevolabile],0,Assegnazione[Imposta di registro senza agevolazione]) -> 0 | N38: Dirette non ag. | O38: =+SUMIF(Assegnazione[Agevolabile],0,Assegnazione[Tassazione diretta senza agevolazione])+SUMIF(Assegnazione[Agevolabile],0,Assegnazione[IRAP]) -> 0
D39: Effetti sull'imponibile IRAP | E39: =+(E36<0)*E36+E37*(E37<0) -> 0
D40: Effetto sul ROL | E40: =+E36+E37 -> 0 | K40: Tassazione su finanziamenti | L40: =+'Tassazione Soci'!J11 -> 0
D41: Futura tassazione della distribuzione delle riserve generate | J41: COSTO OPERAZIONE CON AGEVOLAZIONE | L41: =+I34+I36+L34+L35+L36+L38+O34+O36+O38+L40 -> 116452
D42: Riserve generate | E42: =+(E36+E37)*(SUM(E36:E37)>0) -> 0 | J42: COSTO CESSIONE SENZA AGEVOLAZIONE | L42: =+Assegnazione!U3 -> 34520
D43: Riserve che NON daranno luogo a tassazione | E43: =+MIN(E42,E34) -> 0 | J43: RISPARMIO | L43: =+L42-L41 -> -81932
D44: Riserve che daranno luogo a tassazione | E44: =+E42-E43 -> 0 | J44: Valore normale assegnato | L44: =+Beni!G3 -> 300000
S45: =+IF(L44=0,"","Costo operazione: "&TEXT(L41/L44,"0,0%")&" su valore normale assegnato pari a "&TEXT(L44,"€ 0.000"))&IF(L43>0," Conseguendo un risparmio di €"&TEXT(L43,"#.##0"),"") -> Costo operazione: 38,8% su valore normale assegnato pari a € 300.000
D46: (*) I componenti positivi sono assoggettati a imposta sostitutiva al netto dei componenti negativi realizzati solo su beni merce
H64: =+Assegnazione!V3/DATI!E27-DATI!I64 -> 82400 | I64: =+SUMIF(Assegnazione[Tipologia],"Altri Beni",Assegnazione[Imposta sostitutiva])/E27 -> 0 | K64: =+IF(E27>8%,"X","") -> X | N64: =+I34 -> 8652 | O64: =+N64*0.6 -> 5191.2
H65: =+'Tassazione Soci'!J7 -> 0 | N65: =+H65*13% -> 0 | O65: =+N65*0.6 -> 0
H68: costo normale beni immobili | I68: c. fiscalmente riconosciuto beni immobili | J68: differenza | L68: imponibile RQ84
H69: =+SUMIF(B[Tipologia],"<>Altri Beni",B[Valore normale]) -> 300000 | I69: =+SUMIF(B[Tipologia],"<>Altri Beni",B[Valore netto contabile fiscalmente riconosciuto]) -> 220000 | J69: =+H69-I69 -> 80000 | L69: =+H69-H73 -> 300000
H72: costo normale beni mobili | I72: c. fiscalmente riconosciuto beni mobili | J72: differenza | L72: imp sost L 208/15 | N72: imp sost L 232/16
H73: =+SUMIF(B[Tipologia],"Altri Beni",B[Valore normale]) -> 0 | I73: =+SUMIF(B[Tipologia],"Altri Beni",B[Valore netto contabile fiscalmente riconosciuto]) -> 0 | J73: =+H73-I73 -> 0 | N73: =I34 -> 8652
H75: riserve in sospensione annullate | L75: imp sost L 208/15 ris in sosp | N75: imp sost L 232/16 ris in sosp
H76: =+'Tassazione Soci'!D8 -> 0 | N76: ='Tassazione Soci'!J9 -> 0
D77: MODELLO REDDITI 2025
D89: F24 DA VERSARE ENTRO IL 30/11/2025
D103: F24 DA VERSARE ENTRO IL 30/09/2025

Sheet Società
A5: Dati di bilancio | B5: Ante operazioni | D5: Valori annullati | F5: Valori residui
A6: Capitale sociale | B6: 800000 | D6: =+'Tassazione Soci'!E9 -> 0 | F6: =+B6-D6 -> 800000
A7: Riserve di utili | B7: 600000 | D7: =+'Tassazione Soci'!B9 -> 220000 | F7: =+B7-D7 -> 380000
A8: Riserve di capitale | B8: 500000 | D8: =+'Tassazione Soci'!C9 -> 0 | F8: =+B8-D8 -> 500000
A9: Ris. in sosp. di imposta | B9: 100000 | D9: =+'Tassazione Soci'!D9 -> 0 | F9: =+B9-D9 -> 100000
A10: PATRIMONIO NETTO | B10: =SUM(B6:B9) -> 2000000 | D10: =SUM(D6:D9) -> 220000 | F10: =SUM(F6:F9) -> 1780000

Sheet Soci
B3: In questa e nelle prossime tabelle compilare le sole colonne con l'intestazione scritta in nero.
B4: Soci (o nudi proprietari) al | C4: 45930 | E4: =+SUM(A_1[Quota partecipazione al momento dell''operazione]) -> 1 | F4: =+SUM(A_1[Costo della Partecipaz.]) -> 200000 | G4: =+IF(p=3,IF(COUNTIF(A_1[Agevolabile],0)=0,"","Risultano nuovi soci rispetto alla compagine al 30/09/2015: trasformazione non possibile"),"")
B5: Nome | C5: Data iscrizione libro soci | D5: Tipo (PF) | E5: Quota partecipazione al momento dell'operazione | F5: Costo della Partecipaz. | G5: Aliquota Marginale socio/Tassazione sostitutiva | H5: QUOTA TAX DIVIDENDI (100%-58,14%-5%-40%) | I5: Agevolabile
A6: 100 | B6: Socio X | C6: 45292 | D6: PF | E6: 0.5 | F6: 100000 | G6: 0.26 | H6: 1 | I6: =+IF(A_1[[#This Row],[Nome]]="","",(A_1[[#This Row],[Data iscrizione libro soci]]<=$C$4)*1) -> 1
A7: 100 | B7: Socio Y | C7: 45930 | D7: PF | E7: 0.5 | F7: 100000 | G7: 0.26 | H7: 1 | I7: =+IF(A_1[[#This Row],[Nome]]="","",(A_1[[#This Row],[Data iscrizione libro soci]]<=$C$4)*1) -> 1
A8: 100 | I8: =+IF(A_1[[#This Row],[Nome]]="","",(A_1[[#This Row],[Data iscrizione libro soci]]<=$C$4)*1)
A9: 100 | I9: =+IF(A_1[[#This Row],[Nome]]="","",(A_1[[#This Row],[Data iscrizione libro soci]]<=$C$4)*1)
A10: 100 | I10: =+IF(A_1[[#This Row],[Nome]]="","",(A_1[[#This Row],[Data iscrizione libro soci]]<=$C$4)*1)
A11: 100 | I11: =+IF(A_1[[#This Row],[Nome]]="","",(A_1[[#This Row],[Data iscrizione libro soci]]<=$C$4)*1)
A12: 100 | I12: =+IF(A_1[[#This Row],[Nome]]="","",(A_1[[#This Row],[Data iscrizione libro soci]]<=$C$4)*1)
A13: 100 | I13: =+IF(A_1[[#This Row],[Nome]]="","",(A_1[[#This Row],[Data iscrizione libro soci]]<=$C$4)*1)
A14: 100 | I14: =+IF(A_1[[#This Row],[Nome]]="","",(A_1[[#This Row],[Data iscrizione libro soci]]<=$C$4)*1)
A15: 100 | I15: =+IF(A_1[[#This Row],[Nome]]="","",(A_1[[#This Row],[Data iscrizione libro soci]]<=$C$4)*1)
A16: 100 | I16: =+IF(A_1[[#This Row],[Nome]]="","",(A_1[[#This Row],[Data iscrizione libro soci]]<=$C$4)*1)
A17: 100 | I17: =+IF(A_1[[#This Row],[Nome]]="","",(A_1[[#This Row],[Data iscrizione libro soci]]<=$C$4)*1)
A18: 100 | I18: =+IF(A_1[[#This Row],[Nome]]="","",(A_1[[#This Row],[Data iscrizione libro soci]]<=$C$4)*1)
A19: 100 | I19: =+IF(A_1[[#This Row],[Nome]]="","",(A_1[[#This Row],[Data iscrizione libro soci]]<=$C$4)*1)
... A105: 100 | I105: =+IF(A_1[[#This Row],[Nome]]="","",(A_1[[#This Row],[Data iscrizione libro soci]]<=$C$4)*1)
A106: 100

Sheet Beni
A3: Beni assegnati | G3: =SUM(B[Valore normale]) -> 300000 | H3: =SUM(B[Valore netto contabile fiscalmente riconosciuto]) -> 220000 | I3: =SUM(B[Valore contabile attribuito]) -> 220000 | N3: =SUM(B[Valore catastale]) -> 302400 | Q3: =SUM(B[Valore ai fini dell''imposta di registro]) -> 302400 | R3: =+(SUM(B[Imponibile Imposta sostitutiva])>0)*1*SUM(B[Imponibile Imposta sostitutiva]) -> 82400 | S3: =SUM(B[Iva se dovuta]) -> 0 | T3: =SUM(B[Imposta di registro (fissa + prop) senza agevolazione]) -> 200 | U3: =SUM(B[Ipotecaria e catastale senza agevolazione]) -> 12000 | V3: =SUM(B[Imposta di registro in misura fissa agevolata]) -> 200 | W3: =SUM(B[Imposta di registro prop. Agevolata]) -> 0 | X3: =SUM(B[Totale imposta di registro])*(p<3)+200*(p=3) -> 200 | Y3: =SUM(B[Ipotecaria catastale agevolata]) -> 400
A4: Bene | B4: Anno Acquisizione o ultimazione | C4: Tipologia | D4: Strumentale per destinazione | E4: Categoria Catastale | F4: Rendita catastale | G4: Valore normale | H4: Valore netto contabile fiscalmente riconosciuto | I4: Valore contabile attribuito | J4: Valore inserito manualmente | K4: Iscritto a Bilancio come | L4: Imponibile Iva | M4: Opzione per prezzo-valore (s/n) | N4: Valore catastale | O4: Agevolabile | P4: Valore ai fini dell'atto | Q4: Valore ai fini dell'imposta di registro | R4: Imponibile Imposta sostitutiva | S4: Iva se dovuta | T4: Imposta di registro (fissa + prop) senza agevolazione | U4: Ipotecaria e catastale senza agevolazione | V4: Imposta di registro in misura fissa agevolata | W4: Imposta di registro prop. Agevolata | X4: Totale imposta di registro | Y4: Ipotecaria catastale agevolata | Z4: Fattura
A5: Capannone | B5: 2024 | C5: Immobili Strumentali >5 anni o no Iva per opzione | D5: No | E5: D | F5: 4800 | G5: 300000 | H5: 220000 | I5: 220000 | K5: Immobilizzazioni | M5: s | N5: =+IF(B[[#This Row],[Categoria Catastale]]="",0,VLOOKUP(B[[#This Row],[Categoria Catastale]],Gruppi[],6,0)*B[[#This Row],[Rendita catastale]]) -> 302400 | O5: =+IF(A5="","",IF(D5="Sì",0,1)) -> 1 | P5: =+IF(B[[#This Row],[Valore inserito manualmente]]>0,B[[#This Row],[Valore inserito manualmente]],B[[#This Row],[Valore catastale]]) -> 302400 | Q5: =+IF(OR(B[[#This Row],[Opzione per prezzo-valore (s/n)]]="s",B[[#This Row],[Valore inserito manualmente]]=0),B[[#This Row],[Valore catastale]],B[[#This Row],[Valore inserito manualmente]]) -> 302400 | R5: =IF(OR(B[[#This Row],[Valore ai fini dell''atto]]>B[[#This Row],[Valore netto contabile fiscalmente riconosciuto]],B[[#This Row],[Iscritto a Bilancio come]]="Rimanenze"),B[[#This Row],[Valore ai fini dell''atto]]-B[[#This Row],[Valore netto contabile fiscalmente riconosciuto]],0) -> 82400 | S5: =+IF(B[[#This Row],[Bene]]="","",VLOOKUP(B[[#This Row],[Tipologia]],TipoImm[],3,0)*B[[#This Row],[Imponibile Iva]]) -> 0 | T5: =+IF(B[[#This Row],[Bene]]="","",VLOOKUP(B[[#This Row],[Tipologia]],TipoImm[],6,0)*B[[#This Row],[Valore catastale]]+VLOOKUP(B[[#This Row],[Tipologia]],TipoImm[],4,0)) -> 200 | U5: =+IF(B[[#This Row],[Bene]]="","",VLOOKUP(B[[#This Row],[Tipologia]],TipoImm[],8,0)*B[[#This Row],[Valore normale]]+VLOOKUP(B[[#This Row],[Tipologia]],TipoImm[],9,0)) -> 12000 | V5: =+IF(OR(B[[#This Row],[Bene]]="",B[[#This Row],[Agevolabile]]=0),0,VLOOKUP(B[[#This Row],[Tipologia]],TipoImm[],5,0)) -> 200 | W5: =+IF(B[[#This Row],[Bene]]="",0,IFERROR(MAX(1000,IF(OR(B[[#This Row],[Bene]]="",B[[#This Row],[Agevolabile]]=0,B[[#This Row],[Bene]]=0),0,VLOOKUP(B[[#This Row],[Tipologia]],TipoImm[],7,0))*B[[#This Row],[Valore catastale]]),""))*(IFERROR(VLOOKUP(B[[#This Row],[Tipologia]],TipoImm[],7,0),0)>0) -> 0 | X5: =SUM(B[[#This Row],[Imposta di registro in misura fissa agevolata]:[Imposta di registro prop. Agevolata]]) -> 200 | Y5: =+IF(B[[#This Row],[Bene]]="",0,VLOOKUP(B[[#This Row],[Tipologia]],TipoImm[],10,0)) -> 400 | Z5: =+IF(p=3,"",IF(B[[#This Row],[Tipologia]]="","",VLOOKUP(B[[#This Row],[Tipologia]],TipoImm[],MATCH($Z$4,Tabelle!$AF$1:$AR$1,0),0))) -> Esente art. 10 c.1 n 8 ter
N6: =+IF(B[[#This Row],[Categoria Catastale]]="",0,VLOOKUP(B[[#This Row],[Categoria Catastale]],Gruppi[],6,0)*B[[#This Row],[Rendita catastale]]) -> 0 | O6: =+IF(A6="","",IF(D6="Sì",0,1)) | P6: =+IF(B[[#This Row],[Valore inserito manualmente]]>0,B[[#This Row],[Valore inserito manualmente]],B[[#This Row],[Valore catastale]]) -> 0 | Q6: =+IF(OR(B[[#This Row],[Opzione per prezzo-valore (s/n)]]="s",B[[#This Row],[Valore inserito manualmente]]=0),B[[#This Row],[Valore catastale]],B[[#This Row],[Valore inserito manualmente]]) -> 0 | R6: =IF(OR(B[[#This Row],[Valore ai fini dell''atto]]>B[[#This Row],[Valore netto contabile fiscalmente riconosciuto]],B[[#This Row],[Iscritto a Bilancio come]]="Rimanenze"),B[[#This Row],[Valore ai fini dell''atto]]-B[[#This Row],[Valore netto contabile fiscalmente riconosciuto]],0) -> 0 | S6: =+IF(B[[#This Row],[Bene]]="","",VLOOKUP(B[[#This Row],[Tipologia]],TipoImm[],3,0)*B[[#This Row],[Imponibile Iva]]) | T6: =+IF(B[[#This Row],[Bene]]="","",VLOOKUP(B[[#This Row],[Tipologia]],TipoImm[],6,0)*B[[#This Row],[Valore catastale]]+VLOOKUP(B[[#This Row],[Tipologia]],TipoImm[],4,0)) | U6: =+IF(B[[#This Row],[Bene]]="","",VLOOKUP(B[[#This Row],[Tipologia]],TipoImm[],8,0)*B[[#This Row],[Valore normale]]+VLOOKUP(B[[#This Row],[Tipologia]],TipoImm[],9,0)) | V6: =+IF(OR(B[[#This Row],[Bene]]="",B[[#This Row],[Agevolabile]]=0),0,VLOOKUP(B[[#This Row],[Tipologia]],TipoImm[],5,0)) -> 0 | W6: =+IF(B[[#This Row],[Bene]]="",0,IFERROR(MAX(1000,IF(OR(B[[#This Row],[Bene]]="",B[[#This Row],[Agevolabile]]=0,B[[#This Row],[Bene]]=0),0,VLOOKUP(B[[#This Row],[Tipologia]],TipoImm[],7,0))*B[[#This Row],[Valore catastale]]),""))*(IFERROR(VLOOKUP(B[[#This Row],[Tipologia]],TipoImm[],7,0),0)>0) -> 0 | X6: =SUM(B[[#This Row],[Imposta di registro in misura fissa agevolata]:[Imposta di registro prop. Agevolata]]) -> 0 | Y6: =+IF(B[[#This Row],[Bene]]="",0,VLOOKUP(B[[#This Row],[Tipologia]],TipoImm[],10,0)) -> 0 | Z6: =+IF(p=3,"",IF(B[[#This Row],[Tipologia]]="","",VLOOKUP(B[[#This Row],[Tipologia]],TipoImm[],MATCH($Z$4,Tabelle!$AF$1:$AR$1,0),0)))
N7: =+IF(B[[#This Row],[Categoria Catastale]]="",0,VLOOKUP(B[[#This Row],[Categoria Catastale]],Gruppi[],6,0)*B[[#This Row],[Rendita catastale]]) -> 0 | O7: =+IF(A7="","",IF(D7="Sì",0,1)) | P7: =+IF(B[[#This Row],[Valore inserito manualmente]]>0,B[[#This Row],[Valore inserito manualmente]],B[[#This Row],[Valore catastale]]) -> 0 | Q7: =+IF(OR(B[[#This Row],[Opzione per prezzo-valore (s/n)]]="s",B[[#This Row],[Valore inserito manualmente]]=0),B[[#This Row],[Valore catastale]],B[[#This Row],[Valore inserito manualmente]]) -> 0 | R7: =IF(OR(B[[#This Row],[Valore ai fini dell''atto]]>B[[#This Row],[Valore netto contabile fiscalmente riconosciuto]],B[[#This Row],[Iscritto a Bilancio come]]="Rimanenze"),B[[#This Row],[Valore ai fini dell''atto]]-B[[#This Row],[Valore netto contabile fiscalmente riconosciuto]],0) -> 0 | S7: =+IF(B[[#This Row],[Bene]]="","",VLOOKUP(B[[#This Row],[Tipologia]],TipoImm[],3,0)*B[[#This Row],[Imponibile Iva]]) | T7: =+IF(B[[#This Row],[Bene]]="","",VLOOKUP(B[[#This Row],[Tipologia]],TipoImm[],6,0)*B[[#This Row],[Valore catastale]]+VLOOKUP(B[[#This Row],[Tipologia]],TipoImm[],4,0)) | U7: =+IF(B[[#This Row],[Bene]]="","",VLOOKUP(B[[#This Row],[Tipologia]],TipoImm[],8,0)*B[[#This Row],[Valore normale]]+VLOOKUP(B[[#This Row],[Tipologia]],TipoImm[],9,0)) | V7: =+IF(OR(B[[#This Row],[Bene]]="",B[[#This Row],[Agevolabile]]=0),0,VLOOKUP(B[[#This Row],[Tipologia]],TipoImm[],5,0)) -> 0 | W7: =+IF(B[[#This Row],[Bene]]="",0,IFERROR(MAX(1000,IF(OR(B[[#This Row],[Bene]]="",B[[#This Row],[Agevolabile]]=0,B[[#This Row],[Bene]]=0),0,VLOOKUP(B[[#This Row],[Tipologia]],TipoImm[],7,0))*B[[#This Row],[Valore catastale]]),""))*(IFERROR(VLOOKUP(B[[#This Row],[Tipologia]],TipoImm[],7,0),0)>0) -> 0 | X7: =SUM(B[[#This Row],[Imposta di registro in misura fissa agevolata]:[Imposta di registro prop. Agevolata]]) -> 0 | Y7: =+IF(B[[#This Row],[Bene]]="",0,VLOOKUP(B[[#This Row],[Tipologia]],TipoImm[],10,0)) -> 0 | Z7: =+IF(p=3,"",IF(B[[#This Row],[Tipologia]]="","",VLOOKUP(B[[#This Row],[Tipologia]],TipoImm[],MATCH($Z$4,Tabelle!$AF$1:$AR$1,0),0)))
N8: =+IF(B[[#This Row],[Categoria Catastale]]="",0,VLOOKUP(B[[#This Row],[Categoria Catastale]],Gruppi[],6,0)*B[[#This Row],[Rendita catastale]]) -> 0 | O8: =+IF(A8="","",IF(D8="Sì",0,1)) | P8: =+IF(B[[#This Row],[Valore inserito manualmente]]>0,B[[#This Row],[Valore inserito manualmente]],B[[#This Row],[Valore catastale]]) -> 0 | Q8: =+IF(OR(B[[#This Row],[Opzione per prezzo-valore (s/n)]]="s",B[[#This Row],[Valore inserito manualmente]]=0),B[[#This Row],[Valore catastale]],B[[#This Row],[Valore inserito manualmente]]) -> 0 | R8: =IF(OR(B[[#This Row],[Valore ai fini dell''atto]]>B[[#This Row],[Valore netto contabile fiscalmente riconosciuto]],B[[#This Row],[Iscritto a Bilancio come]]="Rimanenze"),B[[#This Row],[Valore ai fini dell''atto]]-B[[#This Row],[Valore netto contabile fiscalmente riconosciuto]],0) -> 0 | S8: =+IF(B[[#This Row],[Bene]]="","",VLOOKUP(B[[#This Row],[Tipologia]],TipoImm[],3,0)*B[[#This Row],[Imponibile Iva]]) | T8: =+IF(B[[#This Row],[Bene]]="","",VLOOKUP(B[[#This Row],[Tipologia]],TipoImm[],6,0)*B[[#This Row],[Valore catastale]]+VLOOKUP(B[[#This Row],[Tipologia]],TipoImm[],4,0)) | U8: =+IF(B[[#This Row],[Bene]]="","",VLOOKUP(B[[#This Row],[Tipologia]],TipoImm[],8,0)*B[[#This Row],[Valore normale]]+VLOOKUP(B[[#This Row],[Tipologia]],TipoImm[],9,0)) | V8: =+IF(OR(B[[#This Row],[Bene]]="",B[[#This Row],[Agevolabile]]=0),0,VLOOKUP(B[[#This Row],[Tipologia]],TipoImm[],5,0)) -> 0 | W8: =+IF(B[[#This Row],[Bene]]="",0,IFERROR(MAX(1000,IF(OR(B[[#This Row],[Bene]]="",B[[#This Row],[Agevolabile]]=0,B[[#This Row],[Bene]]=0),0,VLOOKUP(B[[#This Row],[Tipologia]],TipoImm[],7,0))*B[[#This Row],[Valore catastale]]),""))*(IFERROR(VLOOKUP(B[[#This Row],[Tipologia]],TipoImm[],7,0),0)>0) -> 0 | X8: =SUM(B[[#This Row],[Imposta di registro in misura fissa agevolata]:[Imposta di registro prop. Agevolata]]) -> 0 | Y8: =+IF(B[[#This Row],[Bene]]="",0,VLOOKUP(B[[#This Row],[Tipologia]],TipoImm[],10,0)) -> 0 | Z8: =+IF(p=3,"",IF(B[[#This Row],[Tipologia]]="","",VLOOKUP(B[[#This Row],[Tipologia]],TipoImm[],MATCH($Z$4,Tabelle!$AF$1:$AR$1,0),0)))
N9: =+IF(B[[#This Row],[Categoria Catastale]]="",0,VLOOKUP(B[[#This Row],[Categoria Catastale]],Gruppi[],6,0)*B[[#This Row],[Rendita catastale]]) -> 0 | O9: =+IF(A9="","",IF(D9="Sì",0,1)) | P9: =+IF(B[[#This Row],[Valore inserito manualmente]]>0,B[[#This Row],[Valore inserito manualmente]],B[[#This Row],[Valore catastale]]) -> 0 | Q9: =+IF(OR(B[[#This Row],[Opzione per prezzo-valore (s/n)]]="s",B[[#This Row],[Valore inserito manualmente]]=0),B[[#This Row],[Valore catastale]],B[[#This Row],[Valore inserito manualmente]]) -> 0 | R9: =IF(OR(B[[#This Row],[Valore ai fini dell''atto]]>B[[#This Row],[Valore netto contabile fiscalmente riconosciuto]],B[[#This Row],[Iscritto a Bilancio come]]="Rimanenze"),B[[#This Row],[Valore ai fini dell''atto]]-B[[#This Row],[Valore netto contabile fiscalmente riconosciuto]],0) -> 0 | S9: =+IF(B[[#This Row],[Bene]]="","",VLOOKUP(B[[#This Row],[Tipologia]],TipoImm[],3,0)*B[[#This Row],[Imponibile Iva]]) | T9: =+IF(B[[#This Row],[Bene]]="","",VLOOKUP(B[[#This Row],[Tipologia]],TipoImm[],6,0)*B[[#This Row],[Valore catastale]]+VLOOKUP(B[[#This Row],[Tipologia]],TipoImm[],4,0)) | U9: =+IF(B[[#This Row],[Bene]]="","",VLOOKUP(B[[#This Row],[Tipologia]],TipoImm[],8,0)*B[[#This Row],[Valore normale]]+VLOOKUP(B[[#This Row],[Tipologia]],TipoImm[],9,0)) | V9: =+IF(OR(B[[#This Row],[Bene]]="",B[[#This Row],[Agevolabile]]=0),0,VLOOKUP(B[[#This Row],[Tipologia]],TipoImm[],5,0)) -> 0 | W9: =+IF(B[[#This Row],[Bene]]="",0,IFERROR(MAX(1000,IF(OR(B[[#This Row],[Bene]]="",B[[#This Row],[Agevolabile]]=0,B[[#This Row],[Bene]]=0),0,VLOOKUP(B[[#This Row],[Tipologia]],TipoImm[],7,0))*B[[#This Row],[Valore catastale]]),""))*(IFERROR(VLOOKUP(B[[#This Row],[Tipologia]],TipoImm[],7,0),0)>0) -> 0 | X9: =SUM(B[[#This Row],[Imposta di registro in misura fissa agevolata]:[Imposta di registro prop. Agevolata]]) -> 0 | Y9: =+IF(B[[#This Row],[Bene]]="",0,VLOOKUP(B[[#This Row],[Tipologia]],TipoImm[],10,0)) -> 0 | Z9: =+IF(p=3,"",IF(B[[#This Row],[Tipologia]]="","",VLOOKUP(B[[#This Row],[Tipologia]],TipoImm[],MATCH($Z$4,Tabelle!$AF$1:$AR$1,0),0)))
N10: =+IF(B[[#This Row],[Categoria Catastale]]="",0,VLOOKUP(B[[#This Row],[Categoria Catastale]],Gruppi[],6,0)*B[[#This Row],[Rendita catastale]]) -> 0 | O10: =+IF(A10="","",IF(D10="Sì",0,1)) | P10: =+IF(B[[#This Row],[Valore inserito manualmente]]>0,B[[#This Row],[Valore inserito manualmente]],B[[#This Row],[Valore catastale]]) -> 0 | Q10: =+IF(OR(B[[#This Row],[Opzione per prezzo-valore (s/n)]]="s",B[[#This Row],[Valore inserito manualmente]]=0),B[[#This Row],[Valore catastale]],B[[#This Row],[Valore inserito manualmente]]) -> 0 | R10: =IF(OR(B[[#This Row],[Valore ai fini dell''atto]]>B[[#This Row],[Valore netto contabile fiscalmente riconosciuto]],B[[#This Row],[Iscritto a Bilancio come]]="Rimanenze"),B[[#This Row],[Valore ai fini dell''atto]]-B[[#This Row],[Valore netto contabile fiscalmente riconosciuto]],0) -> 0 | S10: =+IF(B[[#This Row],[Bene]]="","",VLOOKUP(B[[#This Row],[Tipologia]],TipoImm[],3,0)*B[[#This Row],[Imponibile Iva]]) | T10: =+IF(B[[#This Row],[Bene]]="","",VLOOKUP(B[[#This Row],[Tipologia]],TipoImm[],6,0)*B[[#This Row],[Valore catastale]]+VLOOKUP(B[[#This Row],[Tipologia]],TipoImm[],4,0)) | U10: =+IF(B[[#This Row],[Bene]]="","",VLOOKUP(B[[#This Row],[Tipologia]],TipoImm[],8,0)*B[[#This Row],[Valore normale]]+VLOOKUP(B[[#This Row],[Tipologia]],TipoImm[],9,0)) | V10: =+IF(OR(B[[#This Row],[Bene]]="",B[[#This Row],[Agevolabile]]=0),0,VLOOKUP(B[[#This Row],[Tipologia]],TipoImm[],5,0)) -> 0 | W10: =+IF(B[[#This Row],[Bene]]="",0,IFERROR(MAX(1000,IF(OR(B[[#This Row],[Bene]]="",B[[#This Row],[Agevolabile]]=0,B[[#This Row],[Bene]]=0),0,VLOOKUP(B[[#This Row],[Tipologia]],TipoImm[],7,0))*B[[#This Row],[Valore catastale]]),""))*(IFERROR(VLOOKUP(B[[#This Row],[Tipologia]],TipoImm[],7,0),0)>0) -> 0 | X10: =SUM(B[[#This Row],[Imposta di registro in misura fissa agevolata]:[Imposta di registro prop. Agevolata]]) -> 0 | Y10: =+IF(B[[#This Row],[Bene]]="",0,VLOOKUP(B[[#This Row],[Tipologia]],TipoImm[],10,0)) -> 0 | Z10: =+IF(p=3,"",IF(B[[#This Row],[Tipologia]]="","",VLOOKUP(B[[#This Row],[Tipologia]],TipoImm[],MATCH($Z$4,Tabelle!$AF$1:$AR$1,0),0)))
N11: =+IF(B[[#This Row],[Categoria Catastale]]="",0,VLOOKUP(B[[#This Row],[Categoria Catastale]],Gruppi[],6,0)*B[[#This Row],[Rendita catastale]]) -> 0 | O11: =+IF(A11="","",IF(D11="Sì",0,1)) | P11: =+IF(B[[#This Row],[Valore inserito manualmente]]>0,B[[#This Row],[Valore inserito manualmente]],B[[#This Row],[Valore catastale]]) -> 0 | Q11: =+IF(OR(B[[#This Row],[Opzione per prezzo-valore (s/n)]]="s",B[[#This Row],[Valore inserito manualmente]]=0),B[[#This Row],[Valore catastale]],B[[#This Row],[Valore inserito manualmente]]) -> 0 | R11: =IF(OR(B[[#This Row],[Valore ai fini dell''atto]]>B[[#This Row],[Valore netto contabile fiscalmente riconosciuto]],B[[#This Row],[Iscritto a Bilancio come]]="Rimanenze"),B[[#This Row],[Valore ai fini dell''atto]]-B[[#This Row],[Valore netto contabile fiscalmente riconosciuto]],0) -> 0 | S11: =+IF(B[[#This Row],[Bene]]="","",VLOOKUP(B[[#This Row],[Tipologia]],TipoImm[],3,0)*B[[#This Row],[Imponibile Iva]]) | T11: =+IF(B[[#This Row],[Bene]]="","",VLOOKUP(B[[#This Row],[Tipologia]],TipoImm[],6,0)*B[[#This Row],[Valore catastale]]+VLOOKUP(B[[#This Row],[Tipologia]],TipoImm[],4,0)) | U11: =+IF(B[[#This Row],[Bene]]="","",VLOOKUP(B[[#This Row],[Tipologia]],TipoImm[],8,0)*B[[#This Row],[Valore normale]]+VLOOKUP(B[[#This Row],[Tipologia]],TipoImm[],9,0)) | V11: =+IF(OR(B[[#This Row],[Bene]]="",B[[#This Row],[Agevolabile]]=0),0,VLOOKUP(B[[#This Row],[Tipologia]],TipoImm[],5,0)) -> 0 | W11: =+IF(B[[#This Row],[Bene]]="",0,IFERROR(MAX(1000,IF(OR(B[[#This Row],[Bene]]="",B[[#This Row],[Agevolabile]]=0,B[[#This Row],[Bene]]=0),0,VLOOKUP(B[[#This Row],[Tipologia]],TipoImm[],7,0))*B[[#This Row],[Valore catastale]]),""))*(IFERROR(VLOOKUP(B[[#This Row],[Tipologia]],TipoImm[],7,0),0)>0) -> 0 | X11: =SUM(B[[#This Row],[Imposta di registro in misura fissa agevolata]:[Imposta di registro prop. Agevolata]]) -> 0 | Y11: =+IF(B[[#This Row],[Bene]]="",0,VLOOKUP(B[[#This Row],[Tipologia]],TipoImm[],10,0)) -> 0 | Z11: =+IF(p=3,"",IF(B[[#This Row],[Tipologia]]="","",VLOOKUP(B[[#This Row],[Tipologia]],TipoImm[],MATCH($Z$4,Tabelle!$AF$1:$AR$1,0),0)))
N12: =+IF(B[[#This Row],[Categoria Catastale]]="",0,VLOOKUP(B[[#This Row],[Categoria Catastale]],Gruppi[],6,0)*B[[#This Row],[Rendita catastale]]) -> 0 | O12: =+IF(A12="","",IF(D12="Sì",0,1)) | P12: =+IF(B[[#This Row],[Valore inserito manualmente]]>0,B[[#This Row],[Valore inserito manualmente]],B[[#This Row],[Valore catastale]]) -> 0 | Q12: =+IF(OR(B[[#This Row],[Opzione per prezzo-valore (s/n)]]="s",B[[#This Row],[Valore inserito manualmente]]=0),B[[#This Row],[Valore catastale]],B[[#This Row],[Valore inserito manualmente]]) -> 0 | R12: =IF(OR(B[[#This Row],[Valore ai fini dell''atto]]>B[[#This Row],[Valore netto contabile fiscalmente riconosciuto]],B[[#This Row],[Iscritto a Bilancio come]]="Rimanenze"),B[[#This Row],[Valore ai fini dell''atto]]-B[[#This Row],[Valore netto contabile fiscalmente riconosciuto]],0) -> 0 | S12: =+IF(B[[#This Row],[Bene]]="","",VLOOKUP(B[[#This Row],[Tipologia]],TipoImm[],3,0)*B[[#This Row],[Imponibile Iva]]) | T12: =+IF(B[[#This Row],[Bene]]="","",VLOOKUP(B[[#This Row],[Tipologia]],TipoImm[],6,0)*B[[#This Row],[Valore catastale]]+VLOOKUP(B[[#This Row],[Tipologia]],TipoImm[],4,0)) | U12: =+IF(B[[#This Row],[Bene]]="","",VLOOKUP(B[[#This Row],[Tipologia]],TipoImm[],8,0)*B[[#This Row],[Valore normale]]+VLOOKUP(B[[#This Row],[Tipologia]],TipoImm[],9,0)) | V12: =+IF(OR(B[[#This Row],[Bene]]="",B[[#This Row],[Agevolabile]]=0),0,VLOOKUP(B[[#This Row],[Tipologia]],TipoImm[],5,0)) -> 0 | W12: =+IF(B[[#This Row],[Bene]]="",0,IFERROR(MAX(1000,IF(OR(B[[#This Row],[Bene]]="",B[[#This Row],[Agevolabile]]=0,B[[#This Row],[Bene]]=0),0,VLOOKUP(B[[#This Row],[Tipologia]],TipoImm[],7,0))*B[[#This Row],[Valore catastale]]),""))*(IFERROR(VLOOKUP(B[[#This Row],[Tipologia]],TipoImm[],7,0),0)>0) -> 0 | X12: =SUM(B[[#This Row],[Imposta di registro in misura fissa agevolata]:[Imposta di registro prop. Agevolata]]) -> 0 | Y12: =+IF(B[[#This Row],[Bene]]="",0,VLOOKUP(B[[#This Row],[Tipologia]],TipoImm[],10,0)) -> 0 | Z12: =+IF(p=3,"",IF(B[[#This Row],[Tipologia]]="","",VLOOKUP(B[[#This Row],[Tipologia]],TipoImm[],MATCH($Z$4,Tabelle!$AF$1:$AR$1,0),0)))
N13: =+IF(B[[#This Row],[Categoria Catastale]]="",0,VLOOKUP(B[[#This Row],[Categoria Catastale]],Gruppi[],6,0)*B[[#This Row],[Rendita catastale]]) -> 0 | O13: =+IF(A13="","",IF(D13="Sì",0,1)) | P13: =+IF(B[[#This Row],[Valore inserito manualmente]]>0,B[[#This Row],[Valore inserito manualmente]],B[[#This Row],[Valore catastale]]) -> 0 | Q13: =+IF(OR(B[[#This Row],[Opzione per prezzo-valore (s/n)]]="s",B[[#This Row],[Valore inserito manualmente]]=0),B[[#This Row],[Valore catastale]],B[[#This Row],[Valore inserito manualmente]]) -> 0 | R13: =IF(OR(B[[#This Row],[Valore ai fini dell''atto]]>B[[#This Row],[Valore netto contabile fiscalmente riconosciuto]],B[[#This Row],[Iscritto a Bilancio come]]="Rimanenze"),B[[#This Row],[Valore ai fini dell''atto]]-B[[#This Row],[Valore netto contabile fiscalmente riconosciuto]],0) -> 0 | S13: =+IF(B[[#This Row],[Bene]]="","",VLOOKUP(B[[#This Row],[Tipologia]],TipoImm[],3,0)*B[[#This Row],[Imponibile Iva]]) | T13: =+IF(B[[#This Row],[Bene]]="","",VLOOKUP(B[[#This Row],[Tipologia]],TipoImm[],6,0)*B[[#This Row],[Valore catastale]]+VLOOKUP(B[[#This Row],[Tipologia]],TipoImm[],4,0)) | U13: =+IF(B[[#This Row],[Bene]]="","",VLOOKUP(B[[#This Row],[Tipologia]],TipoImm[],8,0)*B[[#This Row],[Valore normale]]+VLOOKUP(B[[#This Row],[Tipologia]],TipoImm[],9,0)) | V13: =+IF(OR(B[[#This Row],[Bene]]="",B[[#This Row],[Agevolabile]]=0),0,VLOOKUP(B[[#This Row],[Tipologia]],TipoImm[],5,0)) -> 0 | W13: =+IF(B[[#This Row],[Bene]]="",0,IFERROR(MAX(1000,IF(OR(B[[#This Row],[Bene]]="",B[[#This Row],[Agevolabile]]=0,B[[#This Row],[Bene]]=0),0,VLOOKUP(B[[#This Row],[Tipologia]],TipoImm[],7,0))*B[[#This Row],[Valore catastale]]),""))*(IFERROR(VLOOKUP(B[[#This Row],[Tipologia]],TipoImm[],7,0),0)>0) -> 0 | X13: =SUM(B[[#This Row],[Imposta di registro in misura fissa agevolata]:[Imposta di registro prop. Agevolata]]) -> 0 | Y13: =+IF(B[[#This Row],[Bene]]="",0,VLOOKUP(B[[#This Row],[Tipologia]],TipoImm[],10,0)) -> 0 | Z13: =+IF(p=3,"",IF(B[[#This Row],[Tipologia]]="","",VLOOKUP(B[[#This Row],[Tipologia]],TipoImm[],MATCH($Z$4,Tabelle!$AF$1:$AR$1,0),0)))
N14: =+IF(B[[#This Row],[Categoria Catastale]]="",0,VLOOKUP(B[[#This Row],[Categoria Catastale]],Gruppi[],6,0)*B[[#This Row],[Rendita catastale]]) -> 0 | O14: =+IF(A14="","",IF(D14="Sì",0,1)) | P14: =+IF(B[[#This Row],[Valore inserito manualmente]]>0,B[[#This Row],[Valore inserito manualmente]],B[[#This Row],[Valore catastale]]) -> 0 | Q14: =+IF(OR(B[[#This Row],[Opzione per prezzo-valore (s/n)]]="s",B[[#This Row],[Valore inserito manualmente]]=0),B[[#This Row],[Valore catastale]],B[[#This Row],[Valore inserito manualmente]]) -> 0 | R14: =IF(OR(B[[#This Row],[Valore ai fini dell''atto]]>B[[#This Row],[Valore netto contabile fiscalmente riconosciuto]],B[[#This Row],[Iscritto a Bilancio come]]="Rimanenze"),B[[#This Row],[Valore ai fini dell''atto]]-B[[#This Row],[Valore netto contabile fiscalmente riconosciuto]],0) -> 0 | S14: =+IF(B[[#This Row],[Bene]]="","",VLOOKUP(B[[#This Row],[Tipologia]],TipoImm[],3,0)*B[[#This Row],[Imponibile Iva]]) | T14: =+IF(B[[#This Row],[Bene]]="","",VLOOKUP(B[[#This Row],[Tipologia]],TipoImm[],6,0)*B[[#This Row],[Valore catastale]]+VLOOKUP(B[[#This Row],[Tipologia]],TipoImm[],4,0)) | U14: =+IF(B[[#This Row],[Bene]]="","",VLOOKUP(B[[#This Row],[Tipologia]],TipoImm[],8,0)*B[[#This Row],[Valore normale]]+VLOOKUP(B[[#This Row],[Tipologia]],TipoImm[],9,0)) | V14: =+IF(OR(B[[#This Row],[Bene]]="",B[[#This Row],[Agevolabile]]=0),0,VLOOKUP(B[[#This Row],[Tipologia]],TipoImm[],5,0)) -> 0 | W14: =+IF(B[[#This Row],[Bene]]="",0,IFERROR(MAX(1000,IF(OR(B[[#This Row],[Bene]]="",B[[#This Row],[Agevolabile]]=0,B[[#This Row],[Bene]]=0),0,VLOOKUP(B[[#This Row],[Tipologia]],TipoImm[],7,0))*B[[#This Row],[Valore catastale]]),""))*(IFERROR(VLOOKUP(B[[#This Row],[Tipologia]],TipoImm[],7,0),0)>0) -> 0 | X14: =SUM(B[[#This Row],[Imposta di registro in misura fissa agevolata]:[Imposta di registro prop. Agevolata]]) -> 0 | Y14: =+IF(B[[#This Row],[Bene]]="",0,VLOOKUP(B[[#This Row],[Tipologia]],TipoImm[],10,0)) -> 0 | Z14: =+IF(p=3,"",IF(B[[#This Row],[Tipologia]]="","",VLOOKUP(B[[#This Row],[Tipologia]],TipoImm[],MATCH($Z$4,Tabelle!$AF$1:$AR$1,0),0)))
N15: =+IF(B[[#This Row],[Categoria Catastale]]="",0,VLOOKUP(B[[#This Row],[Categoria Catastale]],Gruppi[],6,0)*B[[#This Row],[Rendita catastale]]) -> 0 | O15: =+IF(A15="","",IF(D15="Sì",0,1)) | P15: =+IF(B[[#This Row],[Valore inserito manualmente]]>0,B[[#This Row],[Valore inserito manualmente]],B[[#This Row],[Valore catastale]]) -> 0 | Q15: =+IF(OR(B[[#This Row],[Opzione per prezzo-valore (s/n)]]="s",B[[#This Row],[Valore inserito manualmente]]=0),B[[#This Row],[Valore catastale]],B[[#This Row],[Valore inserito manualmente]]) -> 0 | R15: =IF(OR(B[[#This Row],[Valore ai fini dell''atto]]>B[[#This Row],[Valore netto contabile fiscalmente riconosciuto]],B[[#This Row],[Iscritto a Bilancio come]]="Rimanenze"),B[[#This Row],[Valore ai fini dell''atto]]-B[[#This Row],[Valore netto contabile fiscalmente riconosciuto]],0) -> 0 | S15: =+IF(B[[#This Row],[Bene]]="","",VLOOKUP(B[[#This Row],[Tipologia]],TipoImm[],3,0)*B[[#This Row],[Imponibile Iva]]) | T15: =+IF(B[[#This Row],[Bene]]="","",VLOOKUP(B[[#This Row],[Tipologia]],TipoImm[],6,0)*B[[#This Row],[Valore catastale]]+VLOOKUP(B[[#This Row],[Tipologia]],TipoImm[],4,0)) | U15: =+IF(B[[#This Row],[Bene]]="","",VLOOKUP(B[[#This Row],[Tipologia]],TipoImm[],8,0)*B[[#This Row],[Valore normale]]+VLOOKUP(B[[#This Row],[Tipologia]],TipoImm[],9,0)) | V15: =+IF(OR(B[[#This Row],[Bene]]="",B[[#This Row],[Agevolabile]]=0),0,VLOOKUP(B[[#This Row],[Tipologia]],TipoImm[],5,0)) -> 0 | W15: =+IF(B[[#This Row],[Bene]]="",0,IFERROR(MAX(1000,IF(OR(B[[#This Row],[Bene]]="",B[[#This Row],[Agevolabile]]=0,B[[#This Row],[Bene]]=0),0,VLOOKUP(B[[#This Row],[Tipologia]],TipoImm[],7,0))*B[[#This Row],[Valore catastale]]),""))*(IFERROR(VLOOKUP(B[[#This Row],[Tipologia]],TipoImm[],7,0),0)>0) -> 0 | X15: =SUM(B[[#This Row],[Imposta di registro in misura fissa agevolata]:[Imposta di registro prop. Agevolata]]) -> 0 | Y15: =+IF(B[[#This Row],[Bene]]="",0,VLOOKUP(B[[#This Row],[Tipologia]],TipoImm[],10,0)) -> 0 | Z15: =+IF(p=3,"",IF(B[[#This Row],[Tipologia]]="","",VLOOKUP(B[[#This Row],[Tipologia]],TipoImm[],MATCH($Z$4,Tabelle!$AF$1:$AR$1,0),0)))
N16: =+IF(B[[#This Row],[Categoria Catastale]]="",0,VLOOKUP(B[[#This Row],[Categoria Catastale]],Gruppi[],6,0)*B[[#This Row],[Rendita catastale]]) -> 0 | O16: =+IF(A16="","",IF(D16="Sì",0,1)) | P16: =+IF(B[[#This Row],[Valore inserito manualmente]]>0,B[[#This Row],[Valore inserito manualmente]],B[[#This Row],[Valore catastale]]) -> 0 | Q16: =+IF(OR(B[[#This Row],[Opzione per prezzo-valore (s/n)]]="s",B[[#This Row],[Valore inserito manualmente]]=0),B[[#This Row],[Valore catastale]],B[[#This Row],[Valore inserito manualmente]]) -> 0 | R16: =IF(OR(B[[#This Row],[Valore ai fini dell''atto]]>B[[#This Row],[Valore netto contabile fiscalmente riconosciuto]],B[[#This Row],[Iscritto a Bilancio come]]="Rimanenze"),B[[#This Row],[Valore ai fini dell''atto]]-B[[#This Row],[Valore netto contabile fiscalmente riconosciuto]],0) -> 0 | S16: =+IF(B[[#This Row],[Bene]]="","",VLOOKUP(B[[#This Row],[Tipologia]],TipoImm[],3,0)*B[[#This Row],[Imponibile Iva]]) | T16: =+IF(B[[#This Row],[Bene]]="","",VLOOKUP(B[[#This Row],[Tipologia]],TipoImm[],6,0)*B[[#This Row],[Valore catastale]]+VLOOKUP(B[[#This Row],[Tipologia]],TipoImm[],4,0)) | U16: =+IF(B[[#This Row],[Bene]]="","",VLOOKUP(B[[#This Row],[Tipologia]],TipoImm[],8,0)*B[[#This Row],[Valore normale]]+VLOOKUP(B[[#This Row],[Tipologia]],TipoImm[],9,0)) | V16: =+IF(OR(B[[#This Row],[Bene]]="",B[[#This Row],[Agevolabile]]=0),0,VLOOKUP(B[[#This Row],[Tipologia]],TipoImm[],5,0)) -> 0 | W16: =+IF(B[[#This Row],[Bene]]="",0,IFERROR(MAX(1000,IF(OR(B[[#This Row],[Bene]]="",B[[#This Row],[Agevolabile]]=0,B[[#This Row],[Bene]]=0),0,VLOOKUP(B[[#This Row],[Tipologia]],TipoImm[],7,0))*B[[#This Row],[Valore catastale]]),""))*(IFERROR(VLOOKUP(B[[#This Row],[Tipologia]],TipoImm[],7,0),0)>0) -> 0 | X16: =SUM(B[[#This Row],[Imposta di registro in misura fissa agevolata]:[Imposta di registro prop. Agevolata]]) -> 0 | Y16: =+IF(B[[#This Row],[Bene]]="",0,VLOOKUP(B[[#This Row],[Tipologia]],TipoImm[],10,0)) -> 0 | Z16: =+IF(p=3,"",IF(B[[#This Row],[Tipologia]]="","",VLOOKUP(B[[#This Row],[Tipologia]],TipoImm[],MATCH($Z$4,Tabelle!$AF$1:$AR$1,0),0)))
N17: =+IF(B[[#This Row],[Categoria Catastale]]="",0,VLOOKUP(B[[#This Row],[Categoria Catastale]],Gruppi[],6,0)*B[[#This Row],[Rendita catastale]]) -> 0 | O17: =+IF(A17="","",IF(D17="Sì",0,1)) | P17: =+IF(B[[#This Row],[Valore inserito manualmente]]>0,B[[#This Row],[Valore inserito manualmente]],B[[#This Row],[Valore catastale]]) -> 0 | Q17: =+IF(OR(B[[#This Row],[Opzione per prezzo-valore (s/n)]]="s",B[[#This Row],[Valore inserito manualmente]]=0),B[[#This Row],[Valore catastale]],B[[#This Row],[Valore inserito manualmente]]) -> 0 | R17: =IF(OR(B[[#This Row],[Valore ai fini dell''atto]]>B[[#This Row],[Valore netto contabile fiscalmente riconosciuto]],B[[#This Row],[Iscritto a Bilancio come]]="Rimanenze"),B[[#This Row],[Valore ai fini dell''atto]]-B[[#This Row],[Valore netto contabile fiscalmente riconosciuto]],0) -> 0 | S17: =+IF(B[[#This Row],[Bene]]="","",VLOOKUP(B[[#This Row],[Tipologia]],TipoImm[],3,0)*B[[#This Row],[Imponibile Iva]]) | T17: =+IF(B[[#This Row],[Bene]]="","",VLOOKUP(B[[#This Row],[Tipologia]],TipoImm[],6,0)*B[[#This Row],[Valore catastale]]+VLOOKUP(B[[#This Row],[Tipologia]],TipoImm[],4,0)) | U17: =+IF(B[[#This Row],[Bene]]="","",VLOOKUP(B[[#This Row],[Tipologia]],TipoImm[],8,0)*B[[#This Row],[Valore normale]]+VLOOKUP(B[[#This Row],[Tipologia]],TipoImm[],9,0)) | V17: =+IF(OR(B[[#This Row],[Bene]]="",B[[#This Row],[Agevolabile]]=0),0,VLOOKUP(B[[#This Row],[Tipologia]],TipoImm[],5,0)) -> 0 | W17: =+IF(B[[#This Row],[Bene]]="",0,IFERROR(MAX(1000,IF(OR(B[[#This Row],[Bene]]="",B[[#This Row],[Agevolabile]]=0,B[[#This Row],[Bene]]=0),0,VLOOKUP(B[[#This Row],[Tipologia]],TipoImm[],7,0))*B[[#This Row],[Valore catastale]]),""))*(IFERROR(VLOOKUP(B[[#This Row],[Tipologia]],TipoImm[],7,0),0)>0) -> 0 | X17: =SUM(B[[#This Row],[Imposta di registro in misura fissa agevolata]:[Imposta di registro prop. Agevolata]]) -> 0 | Y17: =+IF(B[[#This Row],[Bene]]="",0,VLOOKUP(B[[#This Row],[Tipologia]],TipoImm[],10,0)) -> 0 | Z17: =+IF(p=3,"",IF(B[[#This Row],[Tipologia]]="","",VLOOKUP(B[[#This Row],[Tipologia]],TipoImm[],MATCH($Z$4,Tabelle!$AF$1:$AR$1,0),0)))
... N104: =+IF(B[[#This Row],[Categoria Catastale]]="",0,VLOOKUP(B[[#This Row],[Categoria Catastale]],Gruppi[],6,0)*B[[#This Row],[Rendita catastale]]) -> 0 | O104: =+IF(A104="","",IF(D104="Sì",0,1)) | P104: =+IF(B[[#This Row],[Valore inserito manualmente]]>0,B[[#This Row],[Valore inserito manualmente]],B[[#This Row],[Valore catastale]]) -> 0 | Q104: =+IF(OR(B[[#This Row],[Opzione per prezzo-valore (s/n)]]="s",B[[#This Row],[Valore inserito manualmente]]=0),B[[#This Row],[Valore catastale]],B[[#This Row],[Valore inserito manualmente]]) -> 0 | R104: =IF(OR(B[[#This Row],[Valore ai fini dell''atto]]>B[[#This Row],[Valore netto contabile fiscalmente riconosciuto]],B[[#This Row],[Iscritto a Bilancio come]]="Rimanenze"),B[[#This Row],[Valore ai fini dell''atto]]-B[[#This Row],[Valore netto contabile fiscalmente riconosciuto]],0) -> 0 | S104: =+IF(B[[#This Row],[Bene]]="","",VLOOKUP(B[[#This Row],[Tipologia]],TipoImm[],3,0)*B[[#This Row],[Imponibile Iva]]) | T104: =+IF(B[[#This Row],[Bene]]="","",VLOOKUP(B[[#This Row],[Tipologia]],TipoImm[],6,0)*B[[#This Row],[Valore catastale]]+VLOOKUP(B[[#This Row],[Tipologia]],TipoImm[],4,0)) | U104: =+IF(B[[#This Row],[Bene]]="","",VLOOKUP(B[[#This Row],[Tipologia]],TipoImm[],8,0)*B[[#This Row],[Valore normale]]+VLOOKUP(B[[#This Row],[Tipologia]],TipoImm[],9,0)) | V104: =+IF(OR(B[[#This Row],[Bene]]="",B[[#This Row],[Agevolabile]]=0),0,VLOOKUP(B[[#This Row],[Tipologia]],TipoImm[],5,0)) -> 0 | W104: =+IF(B[[#This Row],[Bene]]="",0,IFERROR(MAX(1000,IF(OR(B[[#This Row],[Bene]]="",B[[#This Row],[Agevolabile]]=0,B[[#This Row],[Bene]]=0),0,VLOOKUP(B[[#This Row],[Tipologia]],TipoImm[],7,0))*B[[#This Row],[Valore catastale]]),""))*(IFERROR(VLOOKUP(B[[#This Row],[Tipologia]],TipoImm[],7,0),0)>0) -> 0 | X104: =SUM(B[[#This Row],[Imposta di registro in misura fissa agevolata]:[Imposta di registro prop. Agevolata]]) -> 0 | Y104: =+IF(B[[#This Row],[Bene]]="",0,VLOOKUP(B[[#This Row],[Tipologia]],TipoImm[],10,0)) -> 0 | Z104: =+IF(p=3,"",IF(B[[#This Row],[Tipologia]]="","",VLOOKUP(B[[#This Row],[Tipologia]],TipoImm[],MATCH($Z$4,Tabelle!$AF$1:$AR$1,0),0)))

Sheet Tabelle
A1: TIPO | B1: Tassazione | D1: Cat | E1: Base | F1: Molt. | G1: Magg. | H1: Ult. Riv. | I1: Val. Cat. | J1: Agevolabile | L1: Cat | M1: Descr | N1: Moltiplicatore | O1: Prima Casa | R1: TIPO | S1: TAX | V1: TIPO BENE | W1: TIPO SOCIETA' | X1: IMPONIBILE | Y1: Tipologia | Z1: IVA | AA1: Registro | AB1: Ipotecaria Catastale | AC1: agevolabile | AD1: AnniRett | AF1: Tipologia | AG1: Immobili | AH1: IVA | AI1: RegistroFisso | AJ1: RegistroAG | AK1: RegProp | AL1: RegPropAG | AM1: IpocatProp | AN1: IpoCat | AO1: IpoCatAG | AP1: Agevolabile | AQ1: Fattura | AS1: IdPratica | AT1: Nome Pratica
A2: Società per azioni | B2: IRES | D2: Terreni | E2: Reddito Dominicale | F2: 75 | G2: 1.25 | H2: 0.2 | I2: =+Gruppi[[#This Row],[Molt.]]*Gruppi[[#This Row],[Magg.]]*(1+Gruppi[[#This Row],[Ult. Riv.]]) -> 112.5 | L2: A/1 | M2: Abitazioni di tipo signorile | N2: 120 | O2: 120 | R2: PF | S2: 0.4972 | V2: Immobili abitativi | W2: Impresa di costruzione o ristrutturazione che ha ultimato l'intervento da non oltre 5 anni | X2: imponibile per obbligo | Y2: Prima Casa | Z2: 0.04 | AA2: 200 | AB2: 400 | AC2: 1 | AD2: 10 | AF2: Immobili abitativi da costruttrici <5 anni (Iva per obbligo) o Iva per opzione | AG2: Sì | AH2: 0.1 | AI2: 200 | AJ2: 200 | AN2: 400 | AO2: 400 | AP2: 1 | AQ2: Imponibile 10% | AS2: 1 | AT2: Assegnazione
A3: Società in accomandita per azioni | B3: IRES | D3: A (escluso A/10) | E3: Rendita Catastale | F3: 100 | G3: 1.05 | H3: 0.2 | I3: =+Gruppi[[#This Row],[Molt.]]*Gruppi[[#This Row],[Magg.]]*(1+Gruppi[[#This Row],[Ult. Riv.]]) -> 126 | L3: A/2 | M3: Abitazioni di tipo civile | N3: 120 | O3: 110 | R3: PG | S3: 1 | V3: Immobili abitativi | W3: Impresa di costruzione o ristrutturazione che ha ultimato l'intervento da non oltre 5 anni | X3: imponibile per obbligo | Y3: Case non A/1, A/8 o A/9 | Z3: 0.1 | AA3: 200 | AB3: 400 | AC3: 1 | AD3: 10 | AF3: Immobili abitativi - Prima casa da impresa costr. (< 5 anni o Iva per opzione) | AG3: Sì | AH3: 0.04 | AI3: 200 | AJ3: 200 | AN3: 400 | AO3: 400 | AP3: 1 | AQ3: Imponibile 4% | AS3: 2 | AT3: Cessione
A4: Società a responsabilità limitata | B4: IRES | D4: A prima casa | E4: Rendita Catastale | F4: 100 | G4: 1.05 | H4: 0.1 | I4: =+Gruppi[[#This Row],[Molt.]]*Gruppi[[#This Row],[Magg.]]*(1+Gruppi[[#This Row],[Ult. Riv.]]) -> 115.5 | L4: A/3 | M4: Abitazioni di tipo economico | N4: 120 | O4: 110 | R4: PEX | S4: 0.05 | V4: Immobili abitativi | W4: Impresa di costruzione o ristrutturazione che ha ultimato l'intervento da non oltre 5 anni | X4: imponibile per obbligo | Y4: Lusso | Z4: 0.22 | AA4: 200 | AB4: 400 | AC4: 1 | AD4: 10 | AF4: Immobili lusso da impresa costr. (< 5 anni o Iva per opzione) | AG4: Sì | AH4: 0.22 | AI4: 200 | AJ4: 200 | AN4: 400 | AO4: 400 | AP4: 1 | AQ4: Imponibile 22% | AS4: 3 | AT4: =+IF(DATI!$A$23,"Trasformazione","") -> Trasformazione
A5: Società in nome collettivo | B5: IRPEF | D5: A/10 | E5: Rendita Catastale | F5: 50 | G5: 1.04 | H5: 0.2 | I5: 63 | L5: A/4 | M5: Abitazioni di tipo popolare | N5: 120 | O5: 110 | V5: Immobili abitativi | W5: Impresa di costruzione o ristrutturazione che ha ultimato l'intervento da oltre 5 anni | X5: imponibile per opzione | Z5: 0 | AA5: 200 | AB5: 400 | AC5: 1 | AD5: 10 | AF5: Immobili abitativi (>5 anni o Opzione no IVA) | AG5: Sì | AK5: 0.09 | AL5: 0.045 | AN5: 100 | AO5: 100 | AP5: 1 | AQ5: Esente art. 10 c.1 n 8 bis
A6: Società in accomandita semplice | B6: IRPEF | D6: B | E6: Rendita Catastale | F6: 100 | G6: 1.05 | H6: 0.68 | I6: =+Gruppi[[#This Row],[Molt.]]*Gruppi[[#This Row],[Magg.]]*(1+Gruppi[[#This Row],[Ult. Riv.]]) -> 176.4 | L6: A/5 | M6: Abitazioni di tipo ultrapopolare | N6: 120 | O6: 110 | V6: Immobili abitativi | W6: Impresa di costruzione o ristrutturazione che ha ultimato l'intervento da oltre 5 anni | X6: imponibile per obbligo | Y6: Non Prima casa | Z6: 0.22 | AA6: 0.045 | AB6: 100 | AC6: 1 | AD6: 10 | AF6: Immobili abitativi - Prima casa (>5 anni o Opzione no IVA) | AG6: Sì | AK6: 0.02 | AL6: 0.01 | AN6: 100 | AO6: 100 | AP6: 1 | AQ6: Esente art. 10 c.1 n 8 bis
A7: Società trasparente | B7: IRPEF | D7: C (escluso C/1) | E7: Rendita Catastale | F7: 100 | G7: 1.05 | H7: 0.2 | I7: =+Gruppi[[#This Row],[Molt.]]*Gruppi[[#This Row],[Magg.]]*(1+Gruppi[[#This Row],[Ult. Riv.]]) -> 126 | L7: A/6 | M7: Abitazioni di tipo rurale | N7: 120 | O7: 110 | V7: Immobili abitativi | W7: Impresa di costruzione o ristrutturazione che ha ultimato l'intervento da oltre 5 anni | X7: imponibile per obbligo | Y7: Prima Casa | Z7: 0.22 | AA7: 0.01 | AB7: 100 | AC7: 1 | AD7: 10 | AF7: Immobili abitativi acquistati senza addebito IVA | AG7: Sì | AK7: 0.09 | AL7: 0.045 | AN7: 100 | AO7: 100 | AQ7: Fuori campo IVA
D8: C/1 | E8: Rendita Catastale | F8: 34 | G8: 1.05 | H8: 0.2 | I8: =+Gruppi[[#This Row],[Molt.]]*Gruppi[[#This Row],[Magg.]]*(1+Gruppi[[#This Row],[Ult. Riv.]]) -> 42.84 | L8: A/7 | M8: Abitazioni in villini | N8: 120 | O8: 120 | V8: Immobili abitativi | W8: Altri soggetti IVA diversi dall'impresa di costruzione o ristrutturazione | X8: Esente | Y8: Non Prima casa | Z8: 0 | AA8: 0.045 | AB8: 100 | AC8: 1 | AD8: 10 | AF8: Immobili abitativi - Prima casa acquistati senza addebito IVA | AG8: Sì | AK8: 0.02 | AL8: 0.01 | AN8: 100 | AO8: 100 | AQ8: Fuori campo IVA
D9: D | E9: Rendita Catastale | F9: 50 | G9: 1.05 | H9: 0.2 | I9: =+Gruppi[[#This Row],[Molt.]]*Gruppi[[#This Row],[Magg.]]*(1+Gruppi[[#This Row],[Ult. Riv.]]) -> 63 | L9: A/8 | M9: Abitazioni in ville | N9: 120 | O9: 120 | V9: Immobili abitativi | W9: Altri soggetti IVA diversi dall'impresa di costruzione o ristrutturazione | X9: Esente | Y9: Prima Casa | Z9: 0 | AA9: 0.01 | AB9: 100 | AC9: 1 | AD9: 10 | AF9: Immobili Strumentali <5 anni (Iva per obbligo) o Iva per opzione | AG9: Sì | AH9: 0.22 | AI9: 200 | AJ9: 200 | AM9: 0.04 | AO9: 400 | AP9: 1 | AQ9: Imponibile 22%
D10: E | E10: Rendita Catastale | F10: 34 | G10: 1.05 | H10: 0.2 | I10: =+Gruppi[[#This Row],[Molt.]]*Gruppi[[#This Row],[Magg.]]*(1+Gruppi[[#This Row],[Ult. Riv.]]) -> 42.84 | L10: A/9 | M10: Castelli, palazzi di eminenti pregi artistici o storici | N10: 120 | O10: 110 | V10: Immobili abitativi | W10: Chiunque ha acquistato il fabbricato senza addebito dell'IVA (solo assegnazioni) | X10: Fuori Campo | Y10: Non Prima casa | Z10: 0 | AA10: 0.045 | AB10: 100 | AC10: 1 | AD10: 10 | AF10: Immobili Strumentali >5 anni o no Iva per opzione | AG10: Sì | AI10: 200 | AJ10: 200 | AM10: 0.04 | AO10: 400 | AP10: 1 | AQ10: Esente art. 10 c.1 n 8 ter
L11: A/10 | M11: Uffici e studi privati | N11: 60 | V11: Immobili abitativi | W11: Chiunque ha acquistato il fabbricato senza addebito dell'IVA (solo assegnazioni) | X11: Fuori Campo | Y11: Prima Casa | Z11: 0 | AA11: 0.01 | AB11: 100 | AC11: 1 | AD11: 10 | AF11: Immobili strumentali acquistati senza addebito IVA dest. Commerciale | AG11: Sì | AK11: 0.04 | AL11: 0.02 | AM11: 0.03 | AO11: 400 | AP11: 1 | AQ11: Fuori campo IVA
L12: A/11 | M12: Abitazioni ed alloggi tipici dei luoghi | N12: 120 | V12: Immobili strumentali | W12: Impresa di costruzione o ristrutturazione che ha ultimato l'intervento da non oltre 5 anni | X12: imponibile per obbligo | Z12: 0.22 | AA12: 200 | AB12: 400 | AC12: 1 | AD12: 10 | AF12: Immobili strumentali acquistato senza addebito IVA altre destinazioni | AG12: Sì | AK12: 0.09 | AL12: 0.045 | AO12: 100 | AP12: 1 | AQ12: Fuori campo IVA
L13: B/1 | M13: Collegi e convitti, educandati; ricoveri; orfanotrofi; ospizi; conventi; | N13: 168 | V13: Immobili strumentali | W13: Impresa di costruzione o ristrutturazione che ha ultimato l'intervento da oltre 5 anni | X13: Esente in assenza di opzione | Z13: 0.22 | AA13: 200 | AB13: 400 | AC13: 1 | AD13: 10 | AF13: Terreno Edificabile | AG13: No | AH13: 0.22 | AI13: 200 | AJ13: 200 | AN13: 400 | AO13: 400 | AP13: 1 | AQ13: Imponibile 22%
L14: B/2 | M14: Case di cura ed ospedali (senza fine di lucro) | N14: 168 | V14: Immobili strumentali | W14: Altri soggetti IVA diversi dall'impresa di costruzione o ristrutturazione | X14: imponibile per opzione | Z14: 0 | AA14: 200 | AB14: 400 | AC14: 1 | AD14: 10 | AF14: Terreno Edificabile acquistato FUORI CAMPO IVA | AG14: No | AH14: 0.22 | AK14: 0.09 | AL14: 0.045 | AN14: 100 | AO14: 100 | AP14: 1 | AQ14: Imponibile 22%
L15: B/3 | M15: Prigioni e riformatori | N15: 168 | V15: Immobili strumentali | W15: Chiunque ha acquistato il fabbricato senza addebito dell'IVA (solo assegnazioni) | X15: Fuori Campo | Z15: 0 | AA15: 0.045 | AB15: 400 | AC15: 1 | AD15: 10 | AF15: Terreno Agricolo | AG15: No | AH15: 0 | AK15: 0.15 | AL15: 0.075 | AN15: 100 | AO15: 100 | AP15: 1 | AQ15: Fuori campo IVA
L16: B/4 | M16: Uffici pubblici | N16: 168 | V16: Immobili strumentali | W16: Chiunque ha acquistato il fabbricato senza addebito dell'IVA (solo assegnazioni) | X16: Fuori Campo | Z16: 0 | AA16: 0.02 | AB16: 100 | AC16: 1 | AD16: 10 | AF16: Terreno Agricolo (cessionario Colt. Diretto o IAP) | AG16: No | AH16: 0 | AI16: 200 | AJ16: 200 | AM16: 0.01 | AN16: 200 | AO16: 400 | AP16: 1 | AQ16: Fuori campo IVA
L17: B/5 | M17: Scuole e laboratori scientifici | N17: 168 | V17: Terreno Edificabile | W17: Chiunque | X17: Imponibile | Z17: 0.22 | AA17: 200 | AB17: 400 | AC17: 1 | AD17: 10 | AF17: Terreno non Edificabile né Agricolo | AG17: No | AH17: 0 | AK17: 0.09 | AL17: 0.045 | AN17: 100 | AO17: 100 | AP17: 1 | AQ17: Esente
A18: Ver. 11.5 | L18: B/6 | M18: Biblioteche, pinacoteche, musei, gallerie, accademie che non hanno sede in edifici della categoria A/9 | N18: 168 | V18: Terreno Agricolo | W18: Chiunque | X18: Fuori Campo (cessionario IAP) | Z18: 0 | AA18: 200 | AB18: 400 | AD18: 10 | AF18: Altri Beni | AG18: Sì | AH18: 0.22 | AP18: 1 | AQ18: Imponibile 22%
L19: B/7 | M19: Cappelle ed oratori non destinati all’esercizio pubblico del culto | N19: 168 | V19: Terreno Agricolo | W19: Chiunque | X19: Fuori Campo (altri casi) | Z19: 0 | AA19: 0.075 | AB19: 100 | AC19: 1 | AD19: 10
L20: B/8 | M20: Magazzini sotterranei per depositi di derrate | N20: 168 | V20: Terreno non Edificabile né Agricolo | W20: Chiunque | X20: Fuori Campo | Z20: 0 | AA20: 0.045 | AB20: 100 | AC20: 1 | AD20: 10
L21: C/1 | M21: Negozi e botteghe | N21: 40.8 | V21: Atri Beni | W21: Chiunque | Z21: 0.22 | AA21: 0 | AB21: 0 | AC21: 1 | AD21: 5
L22: C/2 | M22: Magazzini e locali di deposito | N22: 120
L23: C/3 | M23: Laboratori per arti e mestieri | N23: 120
L24: C/4 | M24: Fabbricati e locali per esercizi sportivi (senza fine di lucro) | N24: 120
L25: C/5 | M25: Stabilimenti balneari e di acque curative (senza fine di lucro) | N25: 120
L26: C/6 | M26: Stalle, scuderie, rimesse, autorimesse (senza fine di lucro) | N26: 120
L27: C/7 | M27: Tettoie chiuse od aperte | N27: 120
L28: D/1 | M28: Opifici | N28: 60
L29: D/2 | M29: Alberghi e pensioni (con fine di lucro) | N29: 60
L30: D/3 | M30: Teatri, cinematografi, sale per concerti e spettacoli e simili (con fine di lucro) | N30: 60
L31: D/4 | M31: Case di cura ed ospedali (con fine di lucro) | N31: 60
L32: D/5 | M32: Istituto di credito, cambio e assicurazione (con fine di lucro) | N32: 60
L33: D/6 | M33: Fabbricati e locali per esercizi sportivi (con fine di lucro) | N33: 60
... L37: D/10 | M37: Fabbricati per funzioni produttive connesse alle attività agricole. | N37: 60

Sheet Assegnazione
AA2: Totale Tassazione agevolata | AB2: Risparmio
A3: =+DATI!B19 -> Assegnazione | H3: =+SUM(Assegnazione[Valore Fiscalmente riconosciuto]) -> 220000 | I3: =+SUM(Assegnazione[Valore Normale]) -> 300000 | L3: =+SUM(Assegnazione[Valore Catastale]) -> 302400 | M3: =+SUM(Assegnazione[Valore ai fini dell''atto]) -> 302400 | N3: =+SUM(Assegnazione[Valore fiscale ai fini della Tassazione soci]) -> 220000 | P3: =+SUM(Assegnazione[Tassazione diretta senza agevolazione]) -> 19200 | Q3: =+SUM(Assegnazione[IRAP]) -> 3120 | R3: =+SUM(Assegnazione[Iva se dovuta]) -> 0 | S3: =+SUM(Assegnazione[Imposta di registro senza agevolazione]) -> 200 | T3: =+SUM(Assegnazione[Ipotecaria e catastale senza agevolazione]) -> 12000 | U3: =+SUM(Assegnazione[Tassazione totale senza agevolazione]) -> 34520 | V3: =+Beni!R3*DATI!$E$27 -> 8652 | W3: =+SUM(Assegnazione[Imposta di registro in misura fissa]) -> 200 | Y3: =+SUM(Assegnazione[Imposta di registro agevolata])*(p<3)+(p=3)*200 -> 200 | Z3: =+SUM(Assegnazione[Ipotecaria catastale agevolata]) -> 400 | AA3: =+Y3+Z3+V3 -> 9252 | AB3: =+U3-AA3 -> 25268
A4: Bene | B4: Quota di assegnazione | C4: Socio | D4: Imponibile IVA | E4: Valore dichiarato in atto (se diverso da catastale) | F4: Tipologia | G4: Agevolabile | H4: Valore Fiscalmente riconosciuto | I4: Valore Normale | J4: % Assegnata | K4: % Capitale | L4: Valore Catastale | M4: Valore ai fini dell'atto | N4: Valore fiscale ai fini della Tassazione soci | O4: Opzione per prezzo-valore (s/n) | P4: Tassazione diretta senza agevolazione | Q4: IRAP | R4: Iva se dovuta | S4: Imposta di registro senza agevolazione | T4: Ipotecaria e catastale senza agevolazione | U4: Tassazione totale senza agevolazione | V4: Imposta sostitutiva | W4: Imposta di registro in misura fissa | X4: Imposta di registro prop. | Y4: Imposta di registro agevolata | Z4: Ipotecaria catastale agevolata
A5: Capannone | B5: 0.5 | C5: Socio X | D5: =+SUMIF(B[Bene],Assegnazione[[#This Row],[Bene]],B[Imponibile Iva])*Assegnazione[[#This Row],[Quota di assegnazione]] -> 0 | E5: =+SUMIF(B[Bene],Assegnazione[[#This Row],[Bene]],B[Valore inserito manualmente])*Assegnazione[[#This Row],[Quota di assegnazione]] -> 0 | F5: =+IF(A5="","",VLOOKUP(Assegnazione[[#This Row],[Bene]],B[],3,0)) -> Immobili Strumentali >5 anni o no Iva per opzione | G5: =+IFERROR(VLOOKUP(Assegnazione[[#This Row],[Bene]],B[],MATCH("Agevolabile",Beni!$A$4:$AC$4,0),0)*VLOOKUP(Assegnazione[[#This Row],[Socio]],A_1[],8,0),"") -> 1 | H5: =+SUMIF(B[Bene],Assegnazione[[#This Row],[Bene]],B[Valore netto contabile fiscalmente riconosciuto])*Assegnazione[[#This Row],[Quota di assegnazione]] -> 110000 | I5: =+SUMIF(B[Bene],Assegnazione[[#This Row],[Bene]],B[Valore normale])*Assegnazione[[#This Row],[Quota di assegnazione]] -> 150000 | J5: =+IF(Assegnazione[[#This Row],[Bene]]="",0,SUMIF(Assegnazione[Socio],Assegnazione[[#This Row],[Socio]],Assegnazione[Valore Normale])/$I$3) -> 0.5 | K5: =IF(Assegnazione[[#This Row],[Bene]]="","",SUMIF(A_1[Nome],Assegnazione[[#This Row],[Socio]],A_1[Quota partecipazione al momento dell''operazione])) -> 0.5 | L5: =+SUMIF(B[Bene],Assegnazione[[#This Row],[Bene]],B[Valore catastale])*Assegnazione[[#This Row],[Quota di assegnazione]] -> 151200 | M5: =+IF(OR(Assegnazione[[#This Row],[Valore dichiarato in atto (se diverso da catastale)]]>0,Assegnazione[[#This Row],[Agevolabile]]=0),Assegnazione[[#This Row],[Valore dichiarato in atto (se diverso da catastale)]],Assegnazione[[#This Row],[Valore Catastale]]) -> 151200 | N5: =+MIN(Assegnazione[[#This Row],[Valore ai fini dell''atto]],Assegnazione[[#This Row],[Valore Fiscalmente riconosciuto]]) -> 110000 | O5: =+IFERROR(VLOOKUP(Assegnazione[[#This Row],[Bene]],B[],MATCH($O$4,Beni!$A$4:$Z$4,0),0),"") -> s | P5: =+IF(Assegnazione[[#This Row],[Valore Fiscalmente riconosciuto]]>Assegnazione[[#This Row],[Valore Normale]],0,(Assegnazione[[#This Row],[Valore Normale]]-Assegnazione[[#This Row],[Valore Fiscalmente riconosciuto]])*t) -> 9600 | Q5: =+IF(Assegnazione[[#This Row],[Valore Fiscalmente riconosciuto]]>Assegnazione[[#This Row],[Valore Normale]],0,(Assegnazione[[#This Row],[Valore Normale]]-Assegnazione[[#This Row],[Valore Fiscalmente riconosciuto]])*DATI!$H$23) -> 1560 | R5: =+SUMIF(B[Bene],Assegnazione[[#This Row],[Bene]],B[Iva se dovuta])*Assegnazione[[#This Row],[Quota di assegnazione]] -> 0 | S5: =+SUMIF(B[Bene],Assegnazione[[#This Row],[Bene]],B[Imposta di registro (fissa + prop) senza agevolazione])*Assegnazione[[#This Row],[Quota di assegnazione]] -> 100 | T5: =+SUMIF(B[Bene],Assegnazione[[#This Row],[Bene]],B[Ipotecaria e catastale senza agevolazione])*Assegnazione[[#This Row],[Quota di assegnazione]] -> 6000 | U5: =+SUM(Assegnazione[[#This Row],[Tassazione diretta senza agevolazione]:[Ipotecaria e catastale senza agevolazione]]) -> 17260 | V5: =+SUMIF(B[Bene],Assegnazione[[#This Row],[Bene]],B[Imponibile Imposta sostitutiva])*Assegnazione[[#This Row],[Quota di assegnazione]]*DATI!$E$27 -> 4326 | W5: =+SUMIF(B[Bene],Assegnazione[[#This Row],[Bene]],B[Imposta di registro in misura fissa agevolata])*Assegnazione[[#This Row],[Quota di assegnazione]] -> 100 | X5: =+SUMIF(B[Bene],Assegnazione[[#This Row],[Bene]],B[Imposta di registro prop. Agevolata])*Assegnazione[[#This Row],[Quota di assegnazione]] -> 0 | Y5: =+IFERROR(Assegnazione[[#This Row],[Imposta di registro in misura fissa]]+Assegnazione[[#This Row],[Imposta di registro prop.]],"") -> 100 | Z5: =+SUMIF(B[Bene],Assegnazione[[#This Row],[Bene]],B[Ipotecaria catastale agevolata])*Assegnazione[[#This Row],[Quota di assegnazione]] -> 200
A6: Capannone | B6: 0.5 | C6: Socio Y | D6: =+SUMIF(B[Bene],Assegnazione[[#This Row],[Bene]],B[Imponibile Iva])*Assegnazione[[#This Row],[Quota di assegnazione]] -> 0 | E6: =+SUMIF(B[Bene],Assegnazione[[#This Row],[Bene]],B[Valore inserito manualmente])*Assegnazione[[#This Row],[Quota di assegnazione]] -> 0 | F6: =+IF(A6="","",VLOOKUP(Assegnazione[[#This Row],[Bene]],B[],3,0)) -> Immobili Strumentali >5 anni o no Iva per opzione | G6: =+IFERROR(VLOOKUP(Assegnazione[[#This Row],[Bene]],B[],MATCH("Agevolabile",Beni!$A$4:$AC$4,0),0)*VLOOKUP(Assegnazione[[#This Row],[Socio]],A_1[],8,0),"") -> 1 | H6: =+SUMIF(B[Bene],Assegnazione[[#This Row],[Bene]],B[Valore netto contabile fiscalmente riconosciuto])*Assegnazione[[#This Row],[Quota di assegnazione]] -> 110000 | I6: =+SUMIF(B[Bene],Assegnazione[[#This Row],[Bene]],B[Valore normale])*Assegnazione[[#This Row],[Quota di assegnazione]] -> 150000 | J6: =+IF(Assegnazione[[#This Row],[Bene]]="",0,SUMIF(Assegnazione[Socio],Assegnazione[[#This Row],[Socio]],Assegnazione[Valore Normale])/$I$3) -> 0.5 | K6: =IF(Assegnazione[[#This Row],[Bene]]="","",SUMIF(A_1[Nome],Assegnazione[[#This Row],[Socio]],A_1[Quota partecipazione al momento dell''operazione])) -> 0.5 | L6: =+SUMIF(B[Bene],Assegnazione[[#This Row],[Bene]],B[Valore catastale])*Assegnazione[[#This Row],[Quota di assegnazione]] -> 151200 | M6: =+IF(OR(Assegnazione[[#This Row],[Valore dichiarato in atto (se diverso da catastale)]]>0,Assegnazione[[#This Row],[Agevolabile]]=0),Assegnazione[[#This Row],[Valore dichiarato in atto (se diverso da catastale)]],Assegnazione[[#This Row],[Valore Catastale]]) -> 151200 | N6: =+MIN(Assegnazione[[#This Row],[Valore ai fini dell''atto]],Assegnazione[[#This Row],[Valore Fiscalmente riconosciuto]]) -> 110000 | O6: =+IFERROR(VLOOKUP(Assegnazione[[#This Row],[Bene]],B[],MATCH($O$4,Beni!$A$4:$Z$4,0),0),"") -> s | P6: =+IF(Assegnazione[[#This Row],[Valore Fiscalmente riconosciuto]]>Assegnazione[[#This Row],[Valore Normale]],0,(Assegnazione[[#This Row],[Valore Normale]]-Assegnazione[[#This Row],[Valore Fiscalmente riconosciuto]])*t) -> 9600 | Q6: =+IF(Assegnazione[[#This Row],[Valore Fiscalmente riconosciuto]]>Assegnazione[[#This Row],[Valore Normale]],0,(Assegnazione[[#This Row],[Valore Normale]]-Assegnazione[[#This Row],[Valore Fiscalmente riconosciuto]])*DATI!$H$23) -> 1560 | R6: =+SUMIF(B[Bene],Assegnazione[[#This Row],[Bene]],B[Iva se dovuta])*Assegnazione[[#This Row],[Quota di assegnazione]] -> 0 | S6: =+SUMIF(B[Bene],Assegnazione[[#This Row],[Bene]],B[Imposta di registro (fissa + prop) senza agevolazione])*Assegnazione[[#This Row],[Quota di assegnazione]] -> 100 | T6: =+SUMIF(B[Bene],Assegnazione[[#This Row],[Bene]],B[Ipotecaria e catastale senza agevolazione])*Assegnazione[[#This Row],[Quota di assegnazione]] -> 6000 | U6: =+SUM(Assegnazione[[#This Row],[Tassazione diretta senza agevolazione]:[Ipotecaria e catastale senza agevolazione]]) -> 17260 | V6: =+SUMIF(B[Bene],Assegnazione[[#This Row],[Bene]],B[Imponibile Imposta sostitutiva])*Assegnazione[[#This Row],[Quota di assegnazione]]*DATI!$E$27 -> 4326 | W6: =+SUMIF(B[Bene],Assegnazione[[#This Row],[Bene]],B[Imposta di registro in misura fissa agevolata])*Assegnazione[[#This Row],[Quota di assegnazione]] -> 100 | X6: =+SUMIF(B[Bene],Assegnazione[[#This Row],[Bene]],B[Imposta di registro prop. Agevolata])*Assegnazione[[#This Row],[Quota di assegnazione]] -> 0 | Y6: =+IFERROR(Assegnazione[[#This Row],[Imposta di registro in misura fissa]]+Assegnazione[[#This Row],[Imposta di registro prop.]],"") -> 100 | Z6: =+SUMIF(B[Bene],Assegnazione[[#This Row],[Bene]],B[Ipotecaria catastale agevolata])*Assegnazione[[#This Row],[Quota di assegnazione]] -> 200
D7: =+SUMIF(B[Bene],Assegnazione[[#This Row],[Bene]],B[Imponibile Iva])*Assegnazione[[#This Row],[Quota di assegnazione]] -> 0 | E7: =+SUMIF(B[Bene],Assegnazione[[#This Row],[Bene]],B[Valore inserito manualmente])*Assegnazione[[#This Row],[Quota di assegnazione]] -> 0 | F7: =+IF(A7="","",VLOOKUP(Assegnazione[[#This Row],[Bene]],B[],3,0)) | G7: =+IFERROR(VLOOKUP(Assegnazione[[#This Row],[Bene]],B[],MATCH("Agevolabile",Beni!$A$4:$AC$4,0),0)*VLOOKUP(Assegnazione[[#This Row],[Socio]],A_1[],8,0),"") | H7: =+SUMIF(B[Bene],Assegnazione[[#This Row],[Bene]],B[Valore netto contabile fiscalmente riconosciuto])*Assegnazione[[#This Row],[Quota di assegnazione]] -> 0 | I7: =+SUMIF(B[Bene],Assegnazione[[#This Row],[Bene]],B[Valore normale])*Assegnazione[[#This Row],[Quota di assegnazione]] -> 0 | J7: =+IF(Assegnazione[[#This Row],[Bene]]="",0,SUMIF(Assegnazione[Socio],Assegnazione[[#This Row],[Socio]],Assegnazione[Valore Normale])/$I$3) -> 0 | K7: =IF(Assegnazione[[#This Row],[Bene]]="","",SUMIF(A_1[Nome],Assegnazione[[#This Row],[Socio]],A_1[Quota partecipazione al momento dell''operazione])) | L7: =+SUMIF(B[Bene],Assegnazione[[#This Row],[Bene]],B[Valore catastale])*Assegnazione[[#This Row],[Quota di assegnazione]] -> 0 | M7: =+IF(OR(Assegnazione[[#This Row],[Valore dichiarato in atto (se diverso da catastale)]]>0,Assegnazione[[#This Row],[Agevolabile]]=0),Assegnazione[[#This Row],[Valore dichiarato in atto (se diverso da catastale)]],Assegnazione[[#This Row],[Valore Catastale]]) -> 0 | N7: =+MIN(Assegnazione[[#This Row],[Valore ai fini dell''atto]],Assegnazione[[#This Row],[Valore Fiscalmente riconosciuto]]) -> 0 | O7: =+IFERROR(VLOOKUP(Assegnazione[[#This Row],[Bene]],B[],MATCH($O$4,Beni!$A$4:$Z$4,0),0),"") | P7: =+IF(Assegnazione[[#This Row],[Valore Fiscalmente riconosciuto]]>Assegnazione[[#This Row],[Valore Normale]],0,(Assegnazione[[#This Row],[Valore Normale]]-Assegnazione[[#This Row],[Valore Fiscalmente riconosciuto]])*t) -> 0 | Q7: =+IF(Assegnazione[[#This Row],[Valore Fiscalmente riconosciuto]]>Assegnazione[[#This Row],[Valore Normale]],0,(Assegnazione[[#This Row],[Valore Normale]]-Assegnazione[[#This Row],[Valore Fiscalmente riconosciuto]])*DATI!$H$23) -> 0 | R7: =+SUMIF(B[Bene],Assegnazione[[#This Row],[Bene]],B[Iva se dovuta])*Assegnazione[[#This Row],[Quota di assegnazione]] -> 0 | S7: =+SUMIF(B[Bene],Assegnazione[[#This Row],[Bene]],B[Imposta di registro (fissa + prop) senza agevolazione])*Assegnazione[[#This Row],[Quota di assegnazione]] -> 0 | T7: =+SUMIF(B[Bene],Assegnazione[[#This Row],[Bene]],B[Ipotecaria e catastale senza agevolazione])*Assegnazione[[#This Row],[Quota di assegnazione]] -> 0 | U7: =+SUM(Assegnazione[[#This Row],[Tassazione diretta senza agevolazione]:[Ipotecaria e catastale senza agevolazione]]) -> 0 | V7: =+SUMIF(B[Bene],Assegnazione[[#This Row],[Bene]],B[Imponibile Imposta sostitutiva])*Assegnazione[[#This Row],[Quota di assegnazione]]*DATI!$E$27 -> 0 | W7: =+SUMIF(B[Bene],Assegnazione[[#This Row],[Bene]],B[Imposta di registro in misura fissa agevolata])*Assegnazione[[#This Row],[Quota di assegnazione]] -> 0 | X7: =+SUMIF(B[Bene],Assegnazione[[#This Row],[Bene]],B[Imposta di registro prop. Agevolata])*Assegnazione[[#This Row],[Quota di assegnazione]] -> 0 | Y7: =+IFERROR(Assegnazione[[#This Row],[Imposta di registro in misura fissa]]+Assegnazione[[#This Row],[Imposta di registro prop.]],"") -> 0 | Z7: =+SUMIF(B[Bene],Assegnazione[[#This Row],[Bene]],B[Ipotecaria catastale agevolata])*Assegnazione[[#This Row],[Quota di assegnazione]] -> 0
D8: =+SUMIF(B[Bene],Assegnazione[[#This Row],[Bene]],B[Imponibile Iva])*Assegnazione[[#This Row],[Quota di assegnazione]] -> 0 | E8: =+SUMIF(B[Bene],Assegnazione[[#This Row],[Bene]],B[Valore inserito manualmente])*Assegnazione[[#This Row],[Quota di assegnazione]] -> 0 | F8: =+IF(A8="","",VLOOKUP(Assegnazione[[#This Row],[Bene]],B[],3,0)) | G8: =+IFERROR(VLOOKUP(Assegnazione[[#This Row],[Bene]],B[],MATCH("Agevolabile",Beni!$A$4:$AC$4,0),0)*VLOOKUP(Assegnazione[[#This Row],[Socio]],A_1[],8,0),"") | H8: =+SUMIF(B[Bene],Assegnazione[[#This Row],[Bene]],B[Valore netto contabile fiscalmente riconosciuto])*Assegnazione[[#This Row],[Quota di assegnazione]] -> 0 | I8: =+SUMIF(B[Bene],Assegnazione[[#This Row],[Bene]],B[Valore normale])*Assegnazione[[#This Row],[Quota di assegnazione]] -> 0 | J8: =+IF(Assegnazione[[#This Row],[Bene]]="",0,SUMIF(Assegnazione[Socio],Assegnazione[[#This Row],[Socio]],Assegnazione[Valore Normale])/$I$3) -> 0 | K8: =IF(Assegnazione[[#This Row],[Bene]]="","",SUMIF(A_1[Nome],Assegnazione[[#This Row],[Socio]],A_1[Quota partecipazione al momento dell''operazione])) | L8: =+SUMIF(B[Bene],Assegnazione[[#This Row],[Bene]],B[Valore catastale])*Assegnazione[[#This Row],[Quota di assegnazione]] -> 0 | M8: =+IF(OR(Assegnazione[[#This Row],[Valore dichiarato in atto (se diverso da catastale)]]>0,Assegnazione[[#This Row],[Agevolabile]]=0),Assegnazione[[#This Row],[Valore dichiarato in atto (se diverso da catastale)]],Assegnazione[[#This Row],[Valore Catastale]]) -> 0 | N8: =+MIN(Assegnazione[[#This Row],[Valore ai fini dell''atto]],Assegnazione[[#This Row],[Valore Fiscalmente riconosciuto]]) -> 0 | O8: =+IFERROR(VLOOKUP(Assegnazione[[#This Row],[Bene]],B[],MATCH($O$4,Beni!$A$4:$Z$4,0),0),"") | P8: =+IF(Assegnazione[[#This Row],[Valore Fiscalmente riconosciuto]]>Assegnazione[[#This Row],[Valore Normale]],0,(Assegnazione[[#This Row],[Valore Normale]]-Assegnazione[[#This Row],[Valore Fiscalmente riconosciuto]])*t) -> 0 | Q8: =+IF(Assegnazione[[#This Row],[Valore Fiscalmente riconosciuto]]>Assegnazione[[#This Row],[Valore Normale]],0,(Assegnazione[[#This Row],[Valore Normale]]-Assegnazione[[#This Row],[Valore Fiscalmente riconosciuto]])*DATI!$H$23) -> 0 | R8: =+SUMIF(B[Bene],Assegnazione[[#This Row],[Bene]],B[Iva se dovuta])*Assegnazione[[#This Row],[Quota di assegnazione]] -> 0 | S8: =+SUMIF(B[Bene],Assegnazione[[#This Row],[Bene]],B[Imposta di registro (fissa + prop) senza agevolazione])*Assegnazione[[#This Row],[Quota di assegnazione]] -> 0 | T8: =+SUMIF(B[Bene],Assegnazione[[#This Row],[Bene]],B[Ipotecaria e catastale senza agevolazione])*Assegnazione[[#This Row],[Quota di assegnazione]] -> 0 | U8: =+SUM(Assegnazione[[#This Row],[Tassazione diretta senza agevolazione]:[Ipotecaria e catastale senza agevolazione]]) -> 0 | V8: =+SUMIF(B[Bene],Assegnazione[[#This Row],[Bene]],B[Imponibile Imposta sostitutiva])*Assegnazione[[#This Row],[Quota di assegnazione]]*DATI!$E$27 -> 0 | W8: =+SUMIF(B[Bene],Assegnazione[[#This Row],[Bene]],B[Imposta di registro in misura fissa agevolata])*Assegnazione[[#This Row],[Quota di assegnazione]] -> 0 | X8: =+SUMIF(B[Bene],Assegnazione[[#This Row],[Bene]],B[Imposta di registro prop. Agevolata])*Assegnazione[[#This Row],[Quota di assegnazione]] -> 0 | Y8: =+IFERROR(Assegnazione[[#This Row],[Imposta di registro in misura fissa]]+Assegnazione[[#This Row],[Imposta di registro prop.]],"") -> 0 | Z8: =+SUMIF(B[Bene],Assegnazione[[#This Row],[Bene]],B[Ipotecaria catastale agevolata])*Assegnazione[[#This Row],[Quota di assegnazione]] -> 0
D9: =+SUMIF(B[Bene],Assegnazione[[#This Row],[Bene]],B[Imponibile Iva])*Assegnazione[[#This Row],[Quota di assegnazione]] -> 0 | E9: =+SUMIF(B[Bene],Assegnazione[[#This Row],[Bene]],B[Valore inserito manualmente])*Assegnazione[[#This Row],[Quota di assegnazione]] -> 0 | F9: =+IF(A9="","",VLOOKUP(Assegnazione[[#This Row],[Bene]],B[],3,0)) | G9: =+IFERROR(VLOOKUP(Assegnazione[[#This Row],[Bene]],B[],MATCH("Agevolabile",Beni!$A$4:$AC$4,0),0)*VLOOKUP(Assegnazione[[#This Row],[Socio]],A_1[],8,0),"") | H9: =+SUMIF(B[Bene],Assegnazione[[#This Row],[Bene]],B[Valore netto contabile fiscalmente riconosciuto])*Assegnazione[[#This Row],[Quota di assegnazione]] -> 0 | I9: =+SUMIF(B[Bene],Assegnazione[[#This Row],[Bene]],B[Valore normale])*Assegnazione[[#This Row],[Quota di assegnazione]] -> 0 | J9: =+IF(Assegnazione[[#This Row],[Bene]]="",0,SUMIF(Assegnazione[Socio],Assegnazione[[#This Row],[Socio]],Assegnazione[Valore Normale])/$I$3) -> 0 | K9: =IF(Assegnazione[[#This Row],[Bene]]="","",SUMIF(A_1[Nome],Assegnazione[[#This Row],[Socio]],A_1[Quota partecipazione al momento dell''operazione])) | L9: =+SUMIF(B[Bene],Assegnazione[[#This Row],[Bene]],B[Valore catastale])*Assegnazione[[#This Row],[Quota di assegnazione]] -> 0 | M9: =+IF(OR(Assegnazione[[#This Row],[Valore dichiarato in atto (se diverso da catastale)]]>0,Assegnazione[[#This Row],[Agevolabile]]=0),Assegnazione[[#This Row],[Valore dichiarato in atto (se diverso da catastale)]],Assegnazione[[#This Row],[Valore Catastale]]) -> 0 | N9: =+MIN(Assegnazione[[#This Row],[Valore ai fini dell''atto]],Assegnazione[[#This Row],[Valore Fiscalmente riconosciuto]]) -> 0 | O9: =+IFERROR(VLOOKUP(Assegnazione[[#This Row],[Bene]],B[],MATCH($O$4,Beni!$A$4:$Z$4,0),0),"") | P9: =+IF(Assegnazione[[#This Row],[Valore Fiscalmente riconosciuto]]>Assegnazione[[#This Row],[Valore Normale]],0,(Assegnazione[[#This Row],[Valore Normale]]-Assegnazione[[#This Row],[Valore Fiscalmente riconosciuto]])*t) -> 0 | Q9: =+IF(Assegnazione[[#This Row],[Valore Fiscalmente riconosciuto]]>Assegnazione[[#This Row],[Valore Normale]],0,(Assegnazione[[#This Row],[Valore Normale]]-Assegnazione[[#This Row],[Valore Fiscalmente riconosciuto]])*DATI!$H$23) -> 0 | R9: =+SUMIF(B[Bene],Assegnazione[[#This Row],[Bene]],B[Iva se dovuta])*Assegnazione[[#This Row],[Quota di assegnazione]] -> 0 | S9: =+SUMIF(B[Bene],Assegnazione[[#This Row],[Bene]],B[Imposta di registro (fissa + prop) senza agevolazione])*Assegnazione[[#This Row],[Quota di assegnazione]] -> 0 | T9: =+SUMIF(B[Bene],Assegnazione[[#This Row],[Bene]],B[Ipotecaria e catastale senza agevolazione])*Assegnazione[[#This Row],[Quota di assegnazione]] -> 0 | U9: =+SUM(Assegnazione[[#This Row],[Tassazione diretta senza agevolazione]:[Ipotecaria e catastale senza agevolazione]]) -> 0 | V9: =+SUMIF(B[Bene],Assegnazione[[#This Row],[Bene]],B[Imponibile Imposta sostitutiva])*Assegnazione[[#This Row],[Quota di assegnazione]]*DATI!$E$27 -> 0 | W9: =+SUMIF(B[Bene],Assegnazione[[#This Row],[Bene]],B[Imposta di registro in misura fissa agevolata])*Assegnazione[[#This Row],[Quota di assegnazione]] -> 0 | X9: =+SUMIF(B[Bene],Assegnazione[[#This Row],[Bene]],B[Imposta di registro prop. Agevolata])*Assegnazione[[#This Row],[Quota di assegnazione]] -> 0 | Y9: =+IFERROR(Assegnazione[[#This Row],[Imposta di registro in misura fissa]]+Assegnazione[[#This Row],[Imposta di registro prop.]],"") -> 0 | Z9: =+SUMIF(B[Bene],Assegnazione[[#This Row],[Bene]],B[Ipotecaria catastale agevolata])*Assegnazione[[#This Row],[Quota di assegnazione]] -> 0
D10: =+SUMIF(B[Bene],Assegnazione[[#This Row],[Bene]],B[Imponibile Iva])*Assegnazione[[#This Row],[Quota di assegnazione]] -> 0 | E10: =+SUMIF(B[Bene],Assegnazione[[#This Row],[Bene]],B[Valore inserito manualmente])*Assegnazione[[#This Row],[Quota di assegnazione]] -> 0 | F10: =+IF(A10="","",VLOOKUP(Assegnazione[[#This Row],[Bene]],B[],3,0)) | G10: =+IFERROR(VLOOKUP(Assegnazione[[#This Row],[Bene]],B[],MATCH("Agevolabile",Beni!$A$4:$AC$4,0),0)*VLOOKUP(Assegnazione[[#This Row],[Socio]],A_1[],8,0),"") | H10: =+SUMIF(B[Bene],Assegnazione[[#This Row],[Bene]],B[Valore netto contabile fiscalmente riconosciuto])*Assegnazione[[#This Row],[Quota di assegnazione]] -> 0 | I10: =+SUMIF(B[Bene],Assegnazione[[#This Row],[Bene]],B[Valore normale])*Assegnazione[[#This Row],[Quota di assegnazione]] -> 0 | J10: =+IF(Assegnazione[[#This Row],[Bene]]="",0,SUMIF(Assegnazione[Socio],Assegnazione[[#This Row],[Socio]],Assegnazione[Valore Normale])/$I$3) -> 0 | K10: =IF(Assegnazione[[#This Row],[Bene]]="","",SUMIF(A_1[Nome],Assegnazione[[#This Row],[Socio]],A_1[Quota partecipazione al momento dell''operazione])) | L10: =+SUMIF(B[Bene],Assegnazione[[#This Row],[Bene]],B[Valore catastale])*Assegnazione[[#This Row],[Quota di assegnazione]] -> 0 | M10: =+IF(OR(Assegnazione[[#This Row],[Valore dichiarato in atto (se diverso da catastale)]]>0,Assegnazione[[#This Row],[Agevolabile]]=0),Assegnazione[[#This Row],[Valore dichiarato in atto (se diverso da catastale)]],Assegnazione[[#This Row],[Valore Catastale]]) -> 0 | N10: =+MIN(Assegnazione[[#This Row],[Valore ai fini dell''atto]],Assegnazione[[#This Row],[Valore Fiscalmente riconosciuto]]) -> 0 | O10: =+IFERROR(VLOOKUP(Assegnazione[[#This Row],[Bene]],B[],MATCH($O$4,Beni!$A$4:$Z$4,0),0),"") | P10: =+IF(Assegnazione[[#This Row],[Valore Fiscalmente riconosciuto]]>Assegnazione[[#This Row],[Valore Normale]],0,(Assegnazione[[#This Row],[Valore Normale]]-Assegnazione[[#This Row],[Valore Fiscalmente riconosciuto]])*t) -> 0 | Q10: =+IF(Assegnazione[[#This Row],[Valore Fiscalmente riconosciuto]]>Assegnazione[[#This Row],[Valore Normale]],0,(Assegnazione[[#This Row],[Valore Normale]]-Assegnazione[[#This Row],[Valore Fiscalmente riconosciuto]])*DATI!$H$23) -> 0 | R10: =+SUMIF(B[Bene],Assegnazione[[#This Row],[Bene]],B[Iva se dovuta])*Assegnazione[[#This Row],[Quota di assegnazione]] -> 0 | S10: =+SUMIF(B[Bene],Assegnazione[[#This Row],[Bene]],B[Imposta di registro (fissa + prop) senza agevolazione])*Assegnazione[[#This Row],[Quota di assegnazione]] -> 0 | T10: =+SUMIF(B[Bene],Assegnazione[[#This Row],[Bene]],B[Ipotecaria e catastale senza agevolazione])*Assegnazione[[#This Row],[Quota di assegnazione]] -> 0 | U10: =+SUM(Assegnazione[[#This Row],[Tassazione diretta senza agevolazione]:[Ipotecaria e catastale senza agevolazione]]) -> 0 | V10: =+SUMIF(B[Bene],Assegnazione[[#This Row],[Bene]],B[Imponibile Imposta sostitutiva])*Assegnazione[[#This Row],[Quota di assegnazione]]*DATI!$E$27 -> 0 | W10: =+SUMIF(B[Bene],Assegnazione[[#This Row],[Bene]],B[Imposta di registro in misura fissa agevolata])*Assegnazione[[#This Row],[Quota di assegnazione]] -> 0 | X10: =+SUMIF(B[Bene],Assegnazione[[#This Row],[Bene]],B[Imposta di registro prop. Agevolata])*Assegnazione[[#This Row],[Quota di assegnazione]] -> 0 | Y10: =+IFERROR(Assegnazione[[#This Row],[Imposta di registro in misura fissa]]+Assegnazione[[#This Row],[Imposta di registro prop.]],"") -> 0 | Z10: =+SUMIF(B[Bene],Assegnazione[[#This Row],[Bene]],B[Ipotecaria catastale agevolata])*Assegnazione[[#This Row],[Quota di assegnazione]] -> 0
D11: =+SUMIF(B[Bene],Assegnazione[[#This Row],[Bene]],B[Imponibile Iva])*Assegnazione[[#This Row],[Quota di assegnazione]] -> 0 | E11: =+SUMIF(B[Bene],Assegnazione[[#This Row],[Bene]],B[Valore inserito manualmente])*Assegnazione[[#This Row],[Quota di assegnazione]] -> 0 | F11: =+IF(A11="","",VLOOKUP(Assegnazione[[#This Row],[Bene]],B[],3,0)) | G11: =+IFERROR(VLOOKUP(Assegnazione[[#This Row],[Bene]],B[],MATCH("Agevolabile",Beni!$A$4:$AC$4,0),0)*VLOOKUP(Assegnazione[[#This Row],[Socio]],A_1[],8,0),"") | H11: =+SUMIF(B[Bene],Assegnazione[[#This Row],[Bene]],B[Valore netto contabile fiscalmente riconosciuto])*Assegnazione[[#This Row],[Quota di assegnazione]] -> 0 | I11: =+SUMIF(B[Bene],Assegnazione[[#This Row],[Bene]],B[Valore normale])*Assegnazione[[#This Row],[Quota di assegnazione]] -> 0 | J11: =+IF(Assegnazione[[#This Row],[Bene]]="",0,SUMIF(Assegnazione[Socio],Assegnazione[[#This Row],[Socio]],Assegnazione[Valore Normale])/$I$3) -> 0 | K11: =IF(Assegnazione[[#This Row],[Bene]]="","",SUMIF(A_1[Nome],Assegnazione[[#This Row],[Socio]],A_1[Quota partecipazione al momento dell''operazione])) | L11: =+SUMIF(B[Bene],Assegnazione[[#This Row],[Bene]],B[Valore catastale])*Assegnazione[[#This Row],[Quota di assegnazione]] -> 0 | M11: =+IF(OR(Assegnazione[[#This Row],[Valore dichiarato in atto (se diverso da catastale)]]>0,Assegnazione[[#This Row],[Agevolabile]]=0),Assegnazione[[#This Row],[Valore dichiarato in atto (se diverso da catastale)]],Assegnazione[[#This Row],[Valore Catastale]]) -> 0 | N11: =+MIN(Assegnazione[[#This Row],[Valore ai fini dell''atto]],Assegnazione[[#This Row],[Valore Fiscalmente riconosciuto]]) -> 0 | O11: =+IFERROR(VLOOKUP(Assegnazione[[#This Row],[Bene]],B[],MATCH($O$4,Beni!$A$4:$Z$4,0),0),"") | P11: =+IF(Assegnazione[[#This Row],[Valore Fiscalmente riconosciuto]]>Assegnazione[[#This Row],[Valore Normale]],0,(Assegnazione[[#This Row],[Valore Normale]]-Assegnazione[[#This Row],[Valore Fiscalmente riconosciuto]])*t) -> 0 | Q11: =+IF(Assegnazione[[#This Row],[Valore Fiscalmente riconosciuto]]>Assegnazione[[#This Row],[Valore Normale]],0,(Assegnazione[[#This Row],[Valore Normale]]-Assegnazione[[#This Row],[Valore Fiscalmente riconosciuto]])*DATI!$H$23) -> 0 | R11: =+SUMIF(B[Bene],Assegnazione[[#This Row],[Bene]],B[Iva se dovuta])*Assegnazione[[#This Row],[Quota di assegnazione]] -> 0 | S11: =+SUMIF(B[Bene],Assegnazione[[#This Row],[Bene]],B[Imposta di registro (fissa + prop) senza agevolazione])*Assegnazione[[#This Row],[Quota di assegnazione]] -> 0 | T11: =+SUMIF(B[Bene],Assegnazione[[#This Row],[Bene]],B[Ipotecaria e catastale senza agevolazione])*Assegnazione[[#This Row],[Quota di assegnazione]] -> 0 | U11: =+SUM(Assegnazione[[#This Row],[Tassazione diretta senza agevolazione]:[Ipotecaria e catastale senza agevolazione]]) -> 0 | V11: =+SUMIF(B[Bene],Assegnazione[[#This Row],[Bene]],B[Imponibile Imposta sostitutiva])*Assegnazione[[#This Row],[Quota di assegnazione]]*DATI!$E$27 -> 0 | W11: =+SUMIF(B[Bene],Assegnazione[[#This Row],[Bene]],B[Imposta di registro in misura fissa agevolata])*Assegnazione[[#This Row],[Quota di assegnazione]] -> 0 | X11: =+SUMIF(B[Bene],Assegnazione[[#This Row],[Bene]],B[Imposta di registro prop. Agevolata])*Assegnazione[[#This Row],[Quota di assegnazione]] -> 0 | Y11: =+IFERROR(Assegnazione[[#This Row],[Imposta di registro in misura fissa]]+Assegnazione[[#This Row],[Imposta di registro prop.]],"") -> 0 | Z11: =+SUMIF(B[Bene],Assegnazione[[#This Row],[Bene]],B[Ipotecaria catastale agevolata])*Assegnazione[[#This Row],[Quota di assegnazione]] -> 0
D12: =+SUMIF(B[Bene],Assegnazione[[#This Row],[Bene]],B[Imponibile Iva])*Assegnazione[[#This Row],[Quota di assegnazione]] -> 0 | E12: =+SUMIF(B[Bene],Assegnazione[[#This Row],[Bene]],B[Valore inserito manualmente])*Assegnazione[[#This Row],[Quota di assegnazione]] -> 0 | F12: =+IF(A12="","",VLOOKUP(Assegnazione[[#This Row],[Bene]],B[],3,0)) | G12: =+IFERROR(VLOOKUP(Assegnazione[[#This Row],[Bene]],B[],MATCH("Agevolabile",Beni!$A$4:$AC$4,0),0)*VLOOKUP(Assegnazione[[#This Row],[Socio]],A_1[],8,0),"") | H12: =+SUMIF(B[Bene],Assegnazione[[#This Row],[Bene]],B[Valore netto contabile fiscalmente riconosciuto])*Assegnazione[[#This Row],[Quota di assegnazione]] -> 0 | I12: =+SUMIF(B[Bene],Assegnazione[[#This Row],[Bene]],B[Valore normale])*Assegnazione[[#This Row],[Quota di assegnazione]] -> 0 | J12: =+IF(Assegnazione[[#This Row],[Bene]]="",0,SUMIF(Assegnazione[Socio],Assegnazione[[#This Row],[Socio]],Assegnazione[Valore Normale])/$I$3) -> 0 | K12: =IF(Assegnazione[[#This Row],[Bene]]="","",SUMIF(A_1[Nome],Assegnazione[[#This Row],[Socio]],A_1[Quota partecipazione al momento dell''operazione])) | L12: =+SUMIF(B[Bene],Assegnazione[[#This Row],[Bene]],B[Valore catastale])*Assegnazione[[#This Row],[Quota di assegnazione]] -> 0 | M12: =+IF(OR(Assegnazione[[#This Row],[Valore dichiarato in atto (se diverso da catastale)]]>0,Assegnazione[[#This Row],[Agevolabile]]=0),Assegnazione[[#This Row],[Valore dichiarato in atto (se diverso da catastale)]],Assegnazione[[#This Row],[Valore Catastale]]) -> 0 | N12: =+MIN(Assegnazione[[#This Row],[Valore ai fini dell''atto]],Assegnazione[[#This Row],[Valore Fiscalmente riconosciuto]]) -> 0 | O12: =+IFERROR(VLOOKUP(Assegnazione[[#This Row],[Bene]],B[],MATCH($O$4,Beni!$A$4:$Z$4,0),0),"") | P12: =+IF(Assegnazione[[#This Row],[Valore Fiscalmente riconosciuto]]>Assegnazione[[#This Row],[Valore Normale]],0,(Assegnazione[[#This Row],[Valore Normale]]-Assegnazione[[#This Row],[Valore Fiscalmente riconosciuto]])*t) -> 0 | Q12: =+IF(Assegnazione[[#This Row],[Valore Fiscalmente riconosciuto]]>Assegnazione[[#This Row],[Valore Normale]],0,(Assegnazione[[#This Row],[Valore Normale]]-Assegnazione[[#This Row],[Valore Fiscalmente riconosciuto]])*DATI!$H$23) -> 0 | R12: =+SUMIF(B[Bene],Assegnazione[[#This Row],[Bene]],B[Iva se dovuta])*Assegnazione[[#This Row],[Quota di assegnazione]] -> 0 | S12: =+SUMIF(B[Bene],Assegnazione[[#This Row],[Bene]],B[Imposta di registro (fissa + prop) senza agevolazione])*Assegnazione[[#This Row],[Quota di assegnazione]] -> 0 | T12: =+SUMIF(B[Bene],Assegnazione[[#This Row],[Bene]],B[Ipotecaria e catastale senza agevolazione])*Assegnazione[[#This Row],[Quota di assegnazione]] -> 0 | U12: =+SUM(Assegnazione[[#This Row],[Tassazione diretta senza agevolazione]:[Ipotecaria e catastale senza agevolazione]]) -> 0 | V12: =+SUMIF(B[Bene],Assegnazione[[#This Row],[Bene]],B[Imponibile Imposta sostitutiva])*Assegnazione[[#This Row],[Quota di assegnazione]]*DATI!$E$27 -> 0 | W12: =+SUMIF(B[Bene],Assegnazione[[#This Row],[Bene]],B[Imposta di registro in misura fissa agevolata])*Assegnazione[[#This Row],[Quota di assegnazione]] -> 0 | X12: =+SUMIF(B[Bene],Assegnazione[[#This Row],[Bene]],B[Imposta di registro prop. Agevolata])*Assegnazione[[#This Row],[Quota di assegnazione]] -> 0 | Y12: =+IFERROR(Assegnazione[[#This Row],[Imposta di registro in misura fissa]]+Assegnazione[[#This Row],[Imposta di registro prop.]],"") -> 0 | Z12: =+SUMIF(B[Bene],Assegnazione[[#This Row],[Bene]],B[Ipotecaria catastale agevolata])*Assegnazione[[#This Row],[Quota di assegnazione]] -> 0
D13: =+SUMIF(B[Bene],Assegnazione[[#This Row],[Bene]],B[Imponibile Iva])*Assegnazione[[#This Row],[Quota di assegnazione]] -> 0 | E13: =+SUMIF(B[Bene],Assegnazione[[#This Row],[Bene]],B[Valore inserito manualmente])*Assegnazione[[#This Row],[Quota di assegnazione]] -> 0 | F13: =+IF(A13="","",VLOOKUP(Assegnazione[[#This Row],[Bene]],B[],3,0)) | G13: =+IFERROR(VLOOKUP(Assegnazione[[#This Row],[Bene]],B[],MATCH("Agevolabile",Beni!$A$4:$AC$4,0),0)*VLOOKUP(Assegnazione[[#This Row],[Socio]],A_1[],8,0),"") | H13: =+SUMIF(B[Bene],Assegnazione[[#This Row],[Bene]],B[Valore netto contabile fiscalmente riconosciuto])*Assegnazione[[#This Row],[Quota di assegnazione]] -> 0 | I13: =+SUMIF(B[Bene],Assegnazione[[#This Row],[Bene]],B[Valore normale])*Assegnazione[[#This Row],[Quota di assegnazione]] -> 0 | J13: =+IF(Assegnazione[[#This Row],[Bene]]="",0,SUMIF(Assegnazione[Socio],Assegnazione[[#This Row],[Socio]],Assegnazione[Valore Normale])/$I$3) -> 0 | K13: =IF(Assegnazione[[#This Row],[Bene]]="","",SUMIF(A_1[Nome],Assegnazione[[#This Row],[Socio]],A_1[Quota partecipazione al momento dell''operazione])) | L13: =+SUMIF(B[Bene],Assegnazione[[#This Row],[Bene]],B[Valore catastale])*Assegnazione[[#This Row],[Quota di assegnazione]] -> 0 | M13: =+IF(OR(Assegnazione[[#This Row],[Valore dichiarato in atto (se diverso da catastale)]]>0,Assegnazione[[#This Row],[Agevolabile]]=0),Assegnazione[[#This Row],[Valore dichiarato in atto (se diverso da catastale)]],Assegnazione[[#This Row],[Valore Catastale]]) -> 0 | N13: =+MIN(Assegnazione[[#This Row],[Valore ai fini dell''atto]],Assegnazione[[#This Row],[Valore Fiscalmente riconosciuto]]) -> 0 | O13: =+IFERROR(VLOOKUP(Assegnazione[[#This Row],[Bene]],B[],MATCH($O$4,Beni!$A$4:$Z$4,0),0),"") | P13: =+IF(Assegnazione[[#This Row],[Valore Fiscalmente riconosciuto]]>Assegnazione[[#This Row],[Valore Normale]],0,(Assegnazione[[#This Row],[Valore Normale]]-Assegnazione[[#This Row],[Valore Fiscalmente riconosciuto]])*t) -> 0 | Q13: =+IF(Assegnazione[[#This Row],[Valore Fiscalmente riconosciuto]]>Assegnazione[[#This Row],[Valore Normale]],0,(Assegnazione[[#This Row],[Valore Normale]]-Assegnazione[[#This Row],[Valore Fiscalmente riconosciuto]])*DATI!$H$23) -> 0 | R13: =+SUMIF(B[Bene],Assegnazione[[#This Row],[Bene]],B[Iva se dovuta])*Assegnazione[[#This Row],[Quota di assegnazione]] -> 0 | S13: =+SUMIF(B[Bene],Assegnazione[[#This Row],[Bene]],B[Imposta di registro (fissa + prop) senza agevolazione])*Assegnazione[[#This Row],[Quota di assegnazione]] -> 0 | T13: =+SUMIF(B[Bene],Assegnazione[[#This Row],[Bene]],B[Ipotecaria e catastale senza agevolazione])*Assegnazione[[#This Row],[Quota di assegnazione]] -> 0 | U13: =+SUM(Assegnazione[[#This Row],[Tassazione diretta senza agevolazione]:[Ipotecaria e catastale senza agevolazione]]) -> 0 | V13: =+SUMIF(B[Bene],Assegnazione[[#This Row],[Bene]],B[Imponibile Imposta sostitutiva])*Assegnazione[[#This Row],[Quota di assegnazione]]*DATI!$E$27 -> 0 | W13: =+SUMIF(B[Bene],Assegnazione[[#This Row],[Bene]],B[Imposta di registro in misura fissa agevolata])*Assegnazione[[#This Row],[Quota di assegnazione]] -> 0 | X13: =+SUMIF(B[Bene],Assegnazione[[#This Row],[Bene]],B[Imposta di registro prop. Agevolata])*Assegnazione[[#This Row],[Quota di assegnazione]] -> 0 | Y13: =+IFERROR(Assegnazione[[#This Row],[Imposta di registro in misura fissa]]+Assegnazione[[#This Row],[Imposta di registro prop.]],"") -> 0 | Z13: =+SUMIF(B[Bene],Assegnazione[[#This Row],[Bene]],B[Ipotecaria catastale agevolata])*Assegnazione[[#This Row],[Quota di assegnazione]] -> 0
D14: =+SUMIF(B[Bene],Assegnazione[[#This Row],[Bene]],B[Imponibile Iva])*Assegnazione[[#This Row],[Quota di assegnazione]] -> 0 | E14: =+SUMIF(B[Bene],Assegnazione[[#This Row],[Bene]],B[Valore inserito manualmente])*Assegnazione[[#This Row],[Quota di assegnazione]] -> 0 | F14: =+IF(A14="","",VLOOKUP(Assegnazione[[#This Row],[Bene]],B[],3,0)) | G14: =+IFERROR(VLOOKUP(Assegnazione[[#This Row],[Bene]],B[],MATCH("Agevolabile",Beni!$A$4:$AC$4,0),0)*VLOOKUP(Assegnazione[[#This Row],[Socio]],A_1[],8,0),"") | H14: =+SUMIF(B[Bene],Assegnazione[[#This Row],[Bene]],B[Valore netto contabile fiscalmente riconosciuto])*Assegnazione[[#This Row],[Quota di assegnazione]] -> 0 | I14: =+SUMIF(B[Bene],Assegnazione[[#This Row],[Bene]],B[Valore normale])*Assegnazione[[#This Row],[Quota di assegnazione]] -> 0 | J14: =+IF(Assegnazione[[#This Row],[Bene]]="",0,SUMIF(Assegnazione[Socio],Assegnazione[[#This Row],[Socio]],Assegnazione[Valore Normale])/$I$3) -> 0 | K14: =IF(Assegnazione[[#This Row],[Bene]]="","",SUMIF(A_1[Nome],Assegnazione[[#This Row],[Socio]],A_1[Quota partecipazione al momento dell''operazione])) | L14: =+SUMIF(B[Bene],Assegnazione[[#This Row],[Bene]],B[Valore catastale])*Assegnazione[[#This Row],[Quota di assegnazione]] -> 0 | M14: =+IF(OR(Assegnazione[[#This Row],[Valore dichiarato in atto (se diverso da catastale)]]>0,Assegnazione[[#This Row],[Agevolabile]]=0),Assegnazione[[#This Row],[Valore dichiarato in atto (se diverso da catastale)]],Assegnazione[[#This Row],[Valore Catastale]]) -> 0 | N14: =+MIN(Assegnazione[[#This Row],[Valore ai fini dell''atto]],Assegnazione[[#This Row],[Valore Fiscalmente riconosciuto]]) -> 0 | O14: =+IFERROR(VLOOKUP(Assegnazione[[#This Row],[Bene]],B[],MATCH($O$4,Beni!$A$4:$Z$4,0),0),"") | P14: =+IF(Assegnazione[[#This Row],[Valore Fiscalmente riconosciuto]]>Assegnazione[[#This Row],[Valore Normale]],0,(Assegnazione[[#This Row],[Valore Normale]]-Assegnazione[[#This Row],[Valore Fiscalmente riconosciuto]])*t) -> 0 | Q14: =+IF(Assegnazione[[#This Row],[Valore Fiscalmente riconosciuto]]>Assegnazione[[#This Row],[Valore Normale]],0,(Assegnazione[[#This Row],[Valore Normale]]-Assegnazione[[#This Row],[Valore Fiscalmente riconosciuto]])*DATI!$H$23) -> 0 | R14: =+SUMIF(B[Bene],Assegnazione[[#This Row],[Bene]],B[Iva se dovuta])*Assegnazione[[#This Row],[Quota di assegnazione]] -> 0 | S14: =+SUMIF(B[Bene],Assegnazione[[#This Row],[Bene]],B[Imposta di registro (fissa + prop) senza agevolazione])*Assegnazione[[#This Row],[Quota di assegnazione]] -> 0 | T14: =+SUMIF(B[Bene],Assegnazione[[#This Row],[Bene]],B[Ipotecaria e catastale senza agevolazione])*Assegnazione[[#This Row],[Quota di assegnazione]] -> 0 | U14: =+SUM(Assegnazione[[#This Row],[Tassazione diretta senza agevolazione]:[Ipotecaria e catastale senza agevolazione]]) -> 0 | V14: =+SUMIF(B[Bene],Assegnazione[[#This Row],[Bene]],B[Imponibile Imposta sostitutiva])*Assegnazione[[#This Row],[Quota di assegnazione]]*DATI!$E$27 -> 0 | W14: =+SUMIF(B[Bene],Assegnazione[[#This Row],[Bene]],B[Imposta di registro in misura fissa agevolata])*Assegnazione[[#This Row],[Quota di assegnazione]] -> 0 | X14: =+SUMIF(B[Bene],Assegnazione[[#This Row],[Bene]],B[Imposta di registro prop. Agevolata])*Assegnazione[[#This Row],[Quota di assegnazione]] -> 0 | Y14: =+IFERROR(Assegnazione[[#This Row],[Imposta di registro in misura fissa]]+Assegnazione[[#This Row],[Imposta di registro prop.]],"") -> 0 | Z14: =+SUMIF(B[Bene],Assegnazione[[#This Row],[Bene]],B[Ipotecaria catastale agevolata])*Assegnazione[[#This Row],[Quota di assegnazione]] -> 0
D15: =+SUMIF(B[Bene],Assegnazione[[#This Row],[Bene]],B[Imponibile Iva])*Assegnazione[[#This Row],[Quota di assegnazione]] -> 0 | E15: =+SUMIF(B[Bene],Assegnazione[[#This Row],[Bene]],B[Valore inserito manualmente])*Assegnazione[[#This Row],[Quota di assegnazione]] -> 0 | F15: =+IF(A15="","",VLOOKUP(Assegnazione[[#This Row],[Bene]],B[],3,0)) | G15: =+IFERROR(VLOOKUP(Assegnazione[[#This Row],[Bene]],B[],MATCH("Agevolabile",Beni!$A$4:$AC$4,0),0)*VLOOKUP(Assegnazione[[#This Row],[Socio]],A_1[],8,0),"") | H15: =+SUMIF(B[Bene],Assegnazione[[#This Row],[Bene]],B[Valore netto contabile fiscalmente riconosciuto])*Assegnazione[[#This Row],[Quota di assegnazione]] -> 0 | I15: =+SUMIF(B[Bene],Assegnazione[[#This Row],[Bene]],B[Valore normale])*Assegnazione[[#This Row],[Quota di assegnazione]] -> 0 | J15: =+IF(Assegnazione[[#This Row],[Bene]]="",0,SUMIF(Assegnazione[Socio],Assegnazione[[#This Row],[Socio]],Assegnazione[Valore Normale])/$I$3) -> 0 | K15: =IF(Assegnazione[[#This Row],[Bene]]="","",SUMIF(A_1[Nome],Assegnazione[[#This Row],[Socio]],A_1[Quota partecipazione al momento dell''operazione])) | L15: =+SUMIF(B[Bene],Assegnazione[[#This Row],[Bene]],B[Valore catastale])*Assegnazione[[#This Row],[Quota di assegnazione]] -> 0 | M15: =+IF(OR(Assegnazione[[#This Row],[Valore dichiarato in atto (se diverso da catastale)]]>0,Assegnazione[[#This Row],[Agevolabile]]=0),Assegnazione[[#This Row],[Valore dichiarato in atto (se diverso da catastale)]],Assegnazione[[#This Row],[Valore Catastale]]) -> 0 | N15: =+MIN(Assegnazione[[#This Row],[Valore ai fini dell''atto]],Assegnazione[[#This Row],[Valore Fiscalmente riconosciuto]]) -> 0 | O15: =+IFERROR(VLOOKUP(Assegnazione[[#This Row],[Bene]],B[],MATCH($O$4,Beni!$A$4:$Z$4,0),0),"") | P15: =+IF(Assegnazione[[#This Row],[Valore Fiscalmente riconosciuto]]>Assegnazione[[#This Row],[Valore Normale]],0,(Assegnazione[[#This Row],[Valore Normale]]-Assegnazione[[#This Row],[Valore Fiscalmente riconosciuto]])*t) -> 0 | Q15: =+IF(Assegnazione[[#This Row],[Valore Fiscalmente riconosciuto]]>Assegnazione[[#This Row],[Valore Normale]],0,(Assegnazione[[#This Row],[Valore Normale]]-Assegnazione[[#This Row],[Valore Fiscalmente riconosciuto]])*DATI!$H$23) -> 0 | R15: =+SUMIF(B[Bene],Assegnazione[[#This Row],[Bene]],B[Iva se dovuta])*Assegnazione[[#This Row],[Quota di assegnazione]] -> 0 | S15: =+SUMIF(B[Bene],Assegnazione[[#This Row],[Bene]],B[Imposta di registro (fissa + prop) senza agevolazione])*Assegnazione[[#This Row],[Quota di assegnazione]] -> 0 | T15: =+SUMIF(B[Bene],Assegnazione[[#This Row],[Bene]],B[Ipotecaria e catastale senza agevolazione])*Assegnazione[[#This Row],[Quota di assegnazione]] -> 0 | U15: =+SUM(Assegnazione[[#This Row],[Tassazione diretta senza agevolazione]:[Ipotecaria e catastale senza agevolazione]]) -> 0 | V15: =+SUMIF(B[Bene],Assegnazione[[#This Row],[Bene]],B[Imponibile Imposta sostitutiva])*Assegnazione[[#This Row],[Quota di assegnazione]]*DATI!$E$27 -> 0 | W15: =+SUMIF(B[Bene],Assegnazione[[#This Row],[Bene]],B[Imposta di registro in misura fissa agevolata])*Assegnazione[[#This Row],[Quota di assegnazione]] -> 0 | X15: =+SUMIF(B[Bene],Assegnazione[[#This Row],[Bene]],B[Imposta di registro prop. Agevolata])*Assegnazione[[#This Row],[Quota di assegnazione]] -> 0 | Y15: =+IFERROR(Assegnazione[[#This Row],[Imposta di registro in misura fissa]]+Assegnazione[[#This Row],[Imposta di registro prop.]],"") -> 0 | Z15: =+SUMIF(B[Bene],Assegnazione[[#This Row],[Bene]],B[Ipotecaria catastale agevolata])*Assegnazione[[#This Row],[Quota di assegnazione]] -> 0
D16: =+SUMIF(B[Bene],Assegnazione[[#This Row],[Bene]],B[Imponibile Iva])*Assegnazione[[#This Row],[Quota di assegnazione]] -> 0 | E16: =+SUMIF(B[Bene],Assegnazione[[#This Row],[Bene]],B[Valore inserito manualmente])*Assegnazione[[#This Row],[Quota di assegnazione]] -> 0 | F16: =+IF(A16="","",VLOOKUP(Assegnazione[[#This Row],[Bene]],B[],3,0)) | G16: =+IFERROR(VLOOKUP(Assegnazione[[#This Row],[Bene]],B[],MATCH("Agevolabile",Beni!$A$4:$AC$4,0),0)*VLOOKUP(Assegnazione[[#This Row],[Socio]],A_1[],8,0),"") | H16: =+SUMIF(B[Bene],Assegnazione[[#This Row],[Bene]],B[Valore netto contabile fiscalmente riconosciuto])*Assegnazione[[#This Row],[Quota di assegnazione]] -> 0 | I16: =+SUMIF(B[Bene],Assegnazione[[#This Row],[Bene]],B[Valore normale])*Assegnazione[[#This Row],[Quota di assegnazione]] -> 0 | J16: =+IF(Assegnazione[[#This Row],[Bene]]="",0,SUMIF(Assegnazione[Socio],Assegnazione[[#This Row],[Socio]],Assegnazione[Valore Normale])/$I$3) -> 0 | K16: =IF(Assegnazione[[#This Row],[Bene]]="","",SUMIF(A_1[Nome],Assegnazione[[#This Row],[Socio]],A_1[Quota partecipazione al momento dell''operazione])) | L16: =+SUMIF(B[Bene],Assegnazione[[#This Row],[Bene]],B[Valore catastale])*Assegnazione[[#This Row],[Quota di assegnazione]] -> 0 | M16: =+IF(OR(Assegnazione[[#This Row],[Valore dichiarato in atto (se diverso da catastale)]]>0,Assegnazione[[#This Row],[Agevolabile]]=0),Assegnazione[[#This Row],[Valore dichiarato in atto (se diverso da catastale)]],Assegnazione[[#This Row],[Valore Catastale]]) -> 0 | N16: =+MIN(Assegnazione[[#This Row],[Valore ai fini dell''atto]],Assegnazione[[#This Row],[Valore Fiscalmente riconosciuto]]) -> 0 | O16: =+IFERROR(VLOOKUP(Assegnazione[[#This Row],[Bene]],B[],MATCH($O$4,Beni!$A$4:$Z$4,0),0),"") | P16: =+IF(Assegnazione[[#This Row],[Valore Fiscalmente riconosciuto]]>Assegnazione[[#This Row],[Valore Normale]],0,(Assegnazione[[#This Row],[Valore Normale]]-Assegnazione[[#This Row],[Valore Fiscalmente riconosciuto]])*t) -> 0 | Q16: =+IF(Assegnazione[[#This Row],[Valore Fiscalmente riconosciuto]]>Assegnazione[[#This Row],[Valore Normale]],0,(Assegnazione[[#This Row],[Valore Normale]]-Assegnazione[[#This Row],[Valore Fiscalmente riconosciuto]])*DATI!$H$23) -> 0 | R16: =+SUMIF(B[Bene],Assegnazione[[#This Row],[Bene]],B[Iva se dovuta])*Assegnazione[[#This Row],[Quota di assegnazione]] -> 0 | S16: =+SUMIF(B[Bene],Assegnazione[[#This Row],[Bene]],B[Imposta di registro (fissa + prop) senza agevolazione])*Assegnazione[[#This Row],[Quota di assegnazione]] -> 0 | T16: =+SUMIF(B[Bene],Assegnazione[[#This Row],[Bene]],B[Ipotecaria e catastale senza agevolazione])*Assegnazione[[#This Row],[Quota di assegnazione]] -> 0 | U16: =+SUM(Assegnazione[[#This Row],[Tassazione diretta senza agevolazione]:[Ipotecaria e catastale senza agevolazione]]) -> 0 | V16: =+SUMIF(B[Bene],Assegnazione[[#This Row],[Bene]],B[Imponibile Imposta sostitutiva])*Assegnazione[[#This Row],[Quota di assegnazione]]*DATI!$E$27 -> 0 | W16: =+SUMIF(B[Bene],Assegnazione[[#This Row],[Bene]],B[Imposta di registro in misura fissa agevolata])*Assegnazione[[#This Row],[Quota di assegnazione]] -> 0 | X16: =+SUMIF(B[Bene],Assegnazione[[#This Row],[Bene]],B[Imposta di registro prop. Agevolata])*Assegnazione[[#This Row],[Quota di assegnazione]] -> 0 | Y16: =+IFERROR(Assegnazione[[#This Row],[Imposta di registro in misura fissa]]+Assegnazione[[#This Row],[Imposta di registro prop.]],"") -> 0 | Z16: =+SUMIF(B[Bene],Assegnazione[[#This Row],[Bene]],B[Ipotecaria catastale agevolata])*Assegnazione[[#This Row],[Quota di assegnazione]] -> 0
D17: =+SUMIF(B[Bene],Assegnazione[[#This Row],[Bene]],B[Imponibile Iva])*Assegnazione[[#This Row],[Quota di assegnazione]] -> 0 | E17: =+SUMIF(B[Bene],Assegnazione[[#This Row],[Bene]],B[Valore inserito manualmente])*Assegnazione[[#This Row],[Quota di assegnazione]] -> 0 | F17: =+IF(A17="","",VLOOKUP(Assegnazione[[#This Row],[Bene]],B[],3,0)) | G17: =+IFERROR(VLOOKUP(Assegnazione[[#This Row],[Bene]],B[],MATCH("Agevolabile",Beni!$A$4:$AC$4,0),0)*VLOOKUP(Assegnazione[[#This Row],[Socio]],A_1[],8,0),"") | H17: =+SUMIF(B[Bene],Assegnazione[[#This Row],[Bene]],B[Valore netto contabile fiscalmente riconosciuto])*Assegnazione[[#This Row],[Quota di assegnazione]] -> 0 | I17: =+SUMIF(B[Bene],Assegnazione[[#This Row],[Bene]],B[Valore normale])*Assegnazione[[#This Row],[Quota di assegnazione]] -> 0 | J17: =+IF(Assegnazione[[#This Row],[Bene]]="",0,SUMIF(Assegnazione[Socio],Assegnazione[[#This Row],[Socio]],Assegnazione[Valore Normale])/$I$3) -> 0 | K17: =IF(Assegnazione[[#This Row],[Bene]]="","",SUMIF(A_1[Nome],Assegnazione[[#This Row],[Socio]],A_1[Quota partecipazione al momento dell''operazione])) | L17: =+SUMIF(B[Bene],Assegnazione[[#This Row],[Bene]],B[Valore catastale])*Assegnazione[[#This Row],[Quota di assegnazione]] -> 0 | M17: =+IF(OR(Assegnazione[[#This Row],[Valore dichiarato in atto (se diverso da catastale)]]>0,Assegnazione[[#This Row],[Agevolabile]]=0),Assegnazione[[#This Row],[Valore dichiarato in atto (se diverso da catastale)]],Assegnazione[[#This Row],[Valore Catastale]]) -> 0 | N17: =+MIN(Assegnazione[[#This Row],[Valore ai fini dell''atto]],Assegnazione[[#This Row],[Valore Fiscalmente riconosciuto]]) -> 0 | O17: =+IFERROR(VLOOKUP(Assegnazione[[#This Row],[Bene]],B[],MATCH($O$4,Beni!$A$4:$Z$4,0),0),"") | P17: =+IF(Assegnazione[[#This Row],[Valore Fiscalmente riconosciuto]]>Assegnazione[[#This Row],[Valore Normale]],0,(Assegnazione[[#This Row],[Valore Normale]]-Assegnazione[[#This Row],[Valore Fiscalmente riconosciuto]])*t) -> 0 | Q17: =+IF(Assegnazione[[#This Row],[Valore Fiscalmente riconosciuto]]>Assegnazione[[#This Row],[Valore Normale]],0,(Assegnazione[[#This Row],[Valore Normale]]-Assegnazione[[#This Row],[Valore Fiscalmente riconosciuto]])*DATI!$H$23) -> 0 | R17: =+SUMIF(B[Bene],Assegnazione[[#This Row],[Bene]],B[Iva se dovuta])*Assegnazione[[#This Row],[Quota di assegnazione]] -> 0 | S17: =+SUMIF(B[Bene],Assegnazione[[#This Row],[Bene]],B[Imposta di registro (fissa + prop) senza agevolazione])*Assegnazione[[#This Row],[Quota di assegnazione]] -> 0 | T17: =+SUMIF(B[Bene],Assegnazione[[#This Row],[Bene]],B[Ipotecaria e catastale senza agevolazione])*Assegnazione[[#This Row],[Quota di assegnazione]] -> 0 | U17: =+SUM(Assegnazione[[#This Row],[Tassazione diretta senza agevolazione]:[Ipotecaria e catastale senza agevolazione]]) -> 0 | V17: =+SUMIF(B[Bene],Assegnazione[[#This Row],[Bene]],B[Imponibile Imposta sostitutiva])*Assegnazione[[#This Row],[Quota di assegnazione]]*DATI!$E$27 -> 0 | W17: =+SUMIF(B[Bene],Assegnazione[[#This Row],[Bene]],B[Imposta di registro in misura fissa agevolata])*Assegnazione[[#This Row],[Quota di assegnazione]] -> 0 | X17: =+SUMIF(B[Bene],Assegnazione[[#This Row],[Bene]],B[Imposta di registro prop. Agevolata])*Assegnazione[[#This Row],[Quota di assegnazione]] -> 0 | Y17: =+IFERROR(Assegnazione[[#This Row],[Imposta di registro in misura fissa]]+Assegnazione[[#This Row],[Imposta di registro prop.]],"") -> 0 | Z17: =+SUMIF(B[Bene],Assegnazione[[#This Row],[Bene]],B[Ipotecaria catastale agevolata])*Assegnazione[[#This Row],[Quota di assegnazione]] -> 0
D18: =+SUMIF(B[Bene],Assegnazione[[#This Row],[Bene]],B[Imponibile Iva])*Assegnazione[[#This Row],[Quota di assegnazione]] -> 0 | E18: =+SUMIF(B[Bene],Assegnazione[[#This Row],[Bene]],B[Valore inserito manualmente])*Assegnazione[[#This Row],[Quota di assegnazione]] -> 0 | F18: =+IF(A18="","",VLOOKUP(Assegnazione[[#This Row],[Bene]],B[],3,0)) | G18: =+IFERROR(VLOOKUP(Assegnazione[[#This Row],[Bene]],B[],MATCH("Agevolabile",Beni!$A$4:$AC$4,0),0)*VLOOKUP(Assegnazione[[#This Row],[Socio]],A_1[],8,0),"") | H18: =+SUMIF(B[Bene],Assegnazione[[#This Row],[Bene]],B[Valore netto contabile fiscalmente riconosciuto])*Assegnazione[[#This Row],[Quota di assegnazione]] -> 0 | I18: =+SUMIF(B[Bene],Assegnazione[[#This Row],[Bene]],B[Valore normale])*Assegnazione[[#This Row],[Quota di assegnazione]] -> 0 | J18: =+IF(Assegnazione[[#This Row],[Bene]]="",0,SUMIF(Assegnazione[Socio],Assegnazione[[#This Row],[Socio]],Assegnazione[Valore Normale])/$I$3) -> 0 | K18: =IF(Assegnazione[[#This Row],[Bene]]="","",SUMIF(A_1[Nome],Assegnazione[[#This Row],[Socio]],A_1[Quota partecipazione al momento dell''operazione])) | L18: =+SUMIF(B[Bene],Assegnazione[[#This Row],[Bene]],B[Valore catastale])*Assegnazione[[#This Row],[Quota di assegnazione]] -> 0 | M18: =+IF(OR(Assegnazione[[#This Row],[Valore dichiarato in atto (se diverso da catastale)]]>0,Assegnazione[[#This Row],[Agevolabile]]=0),Assegnazione[[#This Row],[Valore dichiarato in atto (se diverso da catastale)]],Assegnazione[[#This Row],[Valore Catastale]]) -> 0 | N18: =+MIN(Assegnazione[[#This Row],[Valore ai fini dell''atto]],Assegnazione[[#This Row],[Valore Fiscalmente riconosciuto]]) -> 0 | O18: =+IFERROR(VLOOKUP(Assegnazione[[#This Row],[Bene]],B[],MATCH($O$4,Beni!$A$4:$Z$4,0),0),"") | P18: =+IF(Assegnazione[[#This Row],[Valore Fiscalmente riconosciuto]]>Assegnazione[[#This Row],[Valore Normale]],0,(Assegnazione[[#This Row],[Valore Normale]]-Assegnazione[[#This Row],[Valore Fiscalmente riconosciuto]])*t) -> 0 | Q18: =+IF(Assegnazione[[#This Row],[Valore Fiscalmente riconosciuto]]>Assegnazione[[#This Row],[Valore Normale]],0,(Assegnazione[[#This Row],[Valore Normale]]-Assegnazione[[#This Row],[Valore Fiscalmente riconosciuto]])*DATI!$H$23) -> 0 | R18: =+SUMIF(B[Bene],Assegnazione[[#This Row],[Bene]],B[Iva se dovuta])*Assegnazione[[#This Row],[Quota di assegnazione]] -> 0 | S18: =+SUMIF(B[Bene],Assegnazione[[#This Row],[Bene]],B[Imposta di registro (fissa + prop) senza agevolazione])*Assegnazione[[#This Row],[Quota di assegnazione]] -> 0 | T18: =+SUMIF(B[Bene],Assegnazione[[#This Row],[Bene]],B[Ipotecaria e catastale senza agevolazione])*Assegnazione[[#This Row],[Quota di assegnazione]] -> 0 | U18: =+SUM(Assegnazione[[#This Row],[Tassazione diretta senza agevolazione]:[Ipotecaria e catastale senza agevolazione]]) -> 0 | V18: =+SUMIF(B[Bene],Assegnazione[[#This Row],[Bene]],B[Imponibile Imposta sostitutiva])*Assegnazione[[#This Row],[Quota di assegnazione]]*DATI!$E$27 -> 0 | W18: =+SUMIF(B[Bene],Assegnazione[[#This Row],[Bene]],B[Imposta di registro in misura fissa agevolata])*Assegnazione[[#This Row],[Quota di assegnazione]] -> 0 | X18: =+SUMIF(B[Bene],Assegnazione[[#This Row],[Bene]],B[Imposta di registro prop. Agevolata])*Assegnazione[[#This Row],[Quota di assegnazione]] -> 0 | Y18: =+IFERROR(Assegnazione[[#This Row],[Imposta di registro in misura fissa]]+Assegnazione[[#This Row],[Imposta di registro prop.]],"") -> 0 | Z18: =+SUMIF(B[Bene],Assegnazione[[#This Row],[Bene]],B[Ipotecaria catastale agevolata])*Assegnazione[[#This Row],[Quota di assegnazione]] -> 0
... D203: =+SUMIF(B[Bene],Assegnazione[[#This Row],[Bene]],B[Imponibile Iva])*Assegnazione[[#This Row],[Quota di assegnazione]] -> 0 | E203: =+SUMIF(B[Bene],Assegnazione[[#This Row],[Bene]],B[Valore inserito manualmente])*Assegnazione[[#This Row],[Quota di assegnazione]] -> 0 | F203: =+IF(A203="","",VLOOKUP(Assegnazione[[#This Row],[Bene]],B[],3,0)) | G203: =+IFERROR(VLOOKUP(Assegnazione[[#This Row],[Bene]],B[],MATCH("Agevolabile",Beni!$A$4:$AC$4,0),0)*VLOOKUP(Assegnazione[[#This Row],[Socio]],A_1[],8,0),"") | H203: =+SUMIF(B[Bene],Assegnazione[[#This Row],[Bene]],B[Valore netto contabile fiscalmente riconosciuto])*Assegnazione[[#This Row],[Quota di assegnazione]] -> 0 | I203: =+SUMIF(B[Bene],Assegnazione[[#This Row],[Bene]],B[Valore normale])*Assegnazione[[#This Row],[Quota di assegnazione]] -> 0 | J203: =+IF(Assegnazione[[#This Row],[Bene]]="",0,SUMIF(Assegnazione[Socio],Assegnazione[[#This Row],[Socio]],Assegnazione[Valore Normale])/$I$3) -> 0 | K203: =IF(Assegnazione[[#This Row],[Bene]]="","",SUMIF(A_1[Nome],Assegnazione[[#This Row],[Socio]],A_1[Quota partecipazione al momento dell''operazione])) | L203: =+SUMIF(B[Bene],Assegnazione[[#This Row],[Bene]],B[Valore catastale])*Assegnazione[[#This Row],[Quota di assegnazione]] -> 0 | M203: =+IF(OR(Assegnazione[[#This Row],[Valore dichiarato in atto (se diverso da catastale)]]>0,Assegnazione[[#This Row],[Agevolabile]]=0),Assegnazione[[#This Row],[Valore dichiarato in atto (se diverso da catastale)]],Assegnazione[[#This Row],[Valore Catastale]]) -> 0 | N203: =+MIN(Assegnazione[[#This Row],[Valore ai fini dell''atto]],Assegnazione[[#This Row],[Valore Fiscalmente riconosciuto]]) -> 0 | O203: =+IFERROR(VLOOKUP(Assegnazione[[#This Row],[Bene]],B[],MATCH($O$4,Beni!$A$4:$Z$4,0),0),"") | P203: =+IF(Assegnazione[[#This Row],[Valore Fiscalmente riconosciuto]]>Assegnazione[[#This Row],[Valore Normale]],0,(Assegnazione[[#This Row],[Valore Normale]]-Assegnazione[[#This Row],[Valore Fiscalmente riconosciuto]])*t) -> 0 | Q203: =+IF(Assegnazione[[#This Row],[Valore Fiscalmente riconosciuto]]>Assegnazione[[#This Row],[Valore Normale]],0,(Assegnazione[[#This Row],[Valore Normale]]-Assegnazione[[#This Row],[Valore Fiscalmente riconosciuto]])*DATI!$H$23) -> 0 | R203: =+SUMIF(B[Bene],Assegnazione[[#This Row],[Bene]],B[Iva se dovuta])*Assegnazione[[#This Row],[Quota di assegnazione]] -> 0 | S203: =+SUMIF(B[Bene],Assegnazione[[#This Row],[Bene]],B[Imposta di registro (fissa + prop) senza agevolazione])*Assegnazione[[#This Row],[Quota di assegnazione]] -> 0 | T203: =+SUMIF(B[Bene],Assegnazione[[#This Row],[Bene]],B[Ipotecaria e catastale senza agevolazione])*Assegnazione[[#This Row],[Quota di assegnazione]] -> 0 | U203: =+SUM(Assegnazione[[#This Row],[Tassazione diretta senza agevolazione]:[Ipotecaria e catastale senza agevolazione]]) -> 0 | V203: =+SUMIF(B[Bene],Assegnazione[[#This Row],[Bene]],B[Imponibile Imposta sostitutiva])*Assegnazione[[#This Row],[Quota di assegnazione]]*DATI!$E$27 -> 0 | W203: =+SUMIF(B[Bene],Assegnazione[[#This Row],[Bene]],B[Imposta di registro in misura fissa agevolata])*Assegnazione[[#This Row],[Quota di assegnazione]] -> 0 | X203: =+SUMIF(B[Bene],Assegnazione[[#This Row],[Bene]],B[Imposta di registro prop. Agevolata])*Assegnazione[[#This Row],[Quota di assegnazione]] -> 0 | Y203: =+IFERROR(Assegnazione[[#This Row],[Imposta di registro in misura fissa]]+Assegnazione[[#This Row],[Imposta di registro prop.]],"") -> 0 | Z203: =+SUMIF(B[Bene],Assegnazione[[#This Row],[Bene]],B[Ipotecaria catastale agevolata])*Assegnazione[[#This Row],[Quota di assegnazione]] -> 0
D204: =+SUMIF(B[Bene],Assegnazione[[#This Row],[Bene]],B[Imponibile Iva])*Assegnazione[[#This Row],[Quota di assegnazione]] -> 0 | E204: =+SUMIF(B[Bene],Assegnazione[[#This Row],[Bene]],B[Valore inserito manualmente])*Assegnazione[[#This Row],[Quota di assegnazione]] -> 0 | G204: =+IFERROR(VLOOKUP(Assegnazione[[#This Row],[Bene]],B[],MATCH("Agevolabile",Beni!$A$4:$AC$4,0),0)*VLOOKUP(Assegnazione[[#This Row],[Socio]],A_1[],8,0),"") | H204: =+SUMIF(B[Bene],Assegnazione[[#This Row],[Bene]],B[Valore netto contabile fiscalmente riconosciuto])*Assegnazione[[#This Row],[Quota di assegnazione]] -> 0 | I204: =+SUMIF(B[Bene],Assegnazione[[#This Row],[Bene]],B[Valore normale])*Assegnazione[[#This Row],[Quota di assegnazione]] -> 0 | J204: =+IF(Assegnazione[[#This Row],[Bene]]="",0,SUMIF(Assegnazione[Socio],Assegnazione[[#This Row],[Socio]],Assegnazione[Valore Normale])/$I$3) -> 0 | K204: =IF(Assegnazione[[#This Row],[Bene]]="","",SUMIF(A_1[Nome],Assegnazione[[#This Row],[Socio]],A_1[Quota partecipazione al momento dell''operazione])) | L204: =+SUMIF(B[Bene],Assegnazione[[#This Row],[Bene]],B[Valore catastale])*Assegnazione[[#This Row],[Quota di assegnazione]] -> 0 | M204: =+IF(OR(Assegnazione[[#This Row],[Valore dichiarato in atto (se diverso da catastale)]]>0,Assegnazione[[#This Row],[Agevolabile]]=0),Assegnazione[[#This Row],[Valore dichiarato in atto (se diverso da catastale)]],Assegnazione[[#This Row],[Valore Catastale]]) -> 0 | N204: =+MIN(Assegnazione[[#This Row],[Valore ai fini dell''atto]],Assegnazione[[#This Row],[Valore Fiscalmente riconosciuto]]) -> 0 | O204: =+IFERROR(VLOOKUP(Assegnazione[[#This Row],[Bene]],B[],MATCH($O$4,Beni!$A$4:$Z$4,0),0),"") | P204: =+IF(Assegnazione[[#This Row],[Valore Fiscalmente riconosciuto]]>Assegnazione[[#This Row],[Valore Normale]],0,(Assegnazione[[#This Row],[Valore Normale]]-Assegnazione[[#This Row],[Valore Fiscalmente riconosciuto]])*t) -> 0 | Q204: =+IF(Assegnazione[[#This Row],[Valore Fiscalmente riconosciuto]]>Assegnazione[[#This Row],[Valore Normale]],0,(Assegnazione[[#This Row],[Valore Normale]]-Assegnazione[[#This Row],[Valore Fiscalmente riconosciuto]])*DATI!$H$23) -> 0 | R204: =+SUMIF(B[Bene],Assegnazione[[#This Row],[Bene]],B[Iva se dovuta])*Assegnazione[[#This Row],[Quota di assegnazione]] -> 0 | S204: =+SUMIF(B[Bene],Assegnazione[[#This Row],[Bene]],B[Imposta di registro (fissa + prop) senza agevolazione])*Assegnazione[[#This Row],[Quota di assegnazione]] -> 0 | T204: =+SUMIF(B[Bene],Assegnazione[[#This Row],[Bene]],B[Ipotecaria e catastale senza agevolazione])*Assegnazione[[#This Row],[Quota di assegnazione]] -> 0 | U204: =+SUM(Assegnazione[[#This Row],[Tassazione diretta senza agevolazione]:[Ipotecaria e catastale senza agevolazione]]) -> 0 | V204: =+SUMIF(B[Bene],Assegnazione[[#This Row],[Bene]],B[Imponibile Imposta sostitutiva])*Assegnazione[[#This Row],[Quota di assegnazione]]*DATI!$E$27 -> 0 | W204: =+SUMIF(B[Bene],Assegnazione[[#This Row],[Bene]],B[Imposta di registro in misura fissa agevolata])*Assegnazione[[#This Row],[Quota di assegnazione]] -> 0 | X204: =+SUMIF(B[Bene],Assegnazione[[#This Row],[Bene]],B[Imposta di registro prop. Agevolata])*Assegnazione[[#This Row],[Quota di assegnazione]] -> 0 | Y204: =+IFERROR(Assegnazione[[#This Row],[Imposta di registro in misura fissa]]+Assegnazione[[#This Row],[Imposta di registro prop.]],"") -> 0 | Z204: =+SUMIF(B[Bene],Assegnazione[[#This Row],[Bene]],B[Ipotecaria catastale agevolata])*Assegnazione[[#This Row],[Quota di assegnazione]] -> 0

Sheet Tassazione Soci
A3: =+IF(p=1,IF(IR,"L’assegnazione dei beni ai soci comporta la necessità di annullare riserve contabili (di utili e/o di capitale) in misura pari al valore contabile attribuito al bene in sede di assegnazione",DATI!H25),IF(p=2,"Non occorre considerare alcuna variazione delle riserve; la contropartita dell'immobile sarà un debito per il cessionario","Non occorre compilare: in caso di trasformazione tutte le riserve si intendono distribuite")) -> L’assegnazione dei beni ai soci comporta la necessità di annullare riserve contabili (di utili e/o di capitale) in misura pari al valore contabile attribuito al bene in sede di assegnazione | L3: =+DATI!S45 -> Costo operazione: 38,8% su valore normale assegnato pari a € 300.000
A4: Valore contabile bene assegnato | C4: =+Beni!I3*(p=1) -> 220000 | D4: =+IF(AND(p=1,IR),IF($G$8=C4,"",IF(G8>C4,"Riduzione riserve in eccesso per ","Riduzione riserve in difetto per ")&TEXT(ABS(C4-G8),"€ #.###,00")),"")
A5: =+IF(AND(p=1,C4>SUM(B8:D8)+E12),"Attenzione le riserve non sono sufficienti a coprire interamente il valore contabile assegnato pertanto, fatto salvo il caso di messa in liquidazione, l'assegnazione potrebbe non essere possibile. "," ")&IF(AND(p=1,SUM(B10:C10)>0,D8>0),CHAR(13)&"Il contribuente può utilizzare le riserve in sospensione d’imposta solo dopo aver utilizzato le altre (riserve di utili e di capitale) già disponibili. ","") | N5: Importo | O5: %
B6: =+IF(IR,"Utili","") -> Utili | C6: =+IF(IR,"Riserve","Valore normale") -> Riserve | D6: =+IF(IR,"Riserve in sospensione","") -> Riserve in sospensione | E6: =+IF(IR,"Capitale sociale","") -> Capitale sociale | F6: Accollo debiti | G6: Totale | I6: Affrancamento riserve 13% | M6: Utili | N6: =+B8 -> 220000 | O6: =+IFERROR(N6/SUM(B8:C8,E8),0) -> 1
A7: Disponibile | B7: =+Società!B7 -> 600000 | C7: =+Società!B8 -> 500000 | D7: =+Società!B9 -> 100000 | E7: =+Società!B6 -> 800000 | G7: =SUM(B7:E7) -> 2000000 | I7: Imponibile | J7: =+IF(p=3,D7,D8) -> 0 | M7: Riserve | N7: =+C8 -> 0 | O7: =+IFERROR(N7/SUM(B8:C8,E8),0) -> 0
A8: Riduzione utili e riserve | B8: 220000 | F8: =+E12 -> 0 | G8: =SUM(B8:F8) -> 220000 | H8: =+OR($G$8=C4,p>1)*1 -> 1 | M8: Capitale sociale | N8: =+E8 -> 0 | O8: =+IFERROR(N8/SUM(B9:C9,E9),0) -> 0
B9: =+B8*(p=1)+B7*(p=3) -> 220000 | C9: =+C8*(p=1)+C7*(p=3) -> 0 | D9: =+D8*(p=1)+D7*(p=3) -> 0 | E9: =+E8 -> 0 | G9: =SUM(C9:D9) -> 0 | I9: Imposta | J9: =+J7*13% -> 0 | M9: Il pagamento della imposta sostitutiva del 13 per cento libera le riserve utilizzate in sede di assegnazione ed è definitivo e liberatorio anche per i soci assegnatari di qualsiasi ulteriore tassazione.
A10: Residuo | B10: =+B7-B8 -> 380000 | C10: =+C7-C8 -> 500000 | D10: =+D7-D8 -> 100000 | E10: =+E7-E8 -> 800000 | G10: =+G7-G9 -> 2000000
A11: FALSE | I11: Tassazione finanziamenti (3%) | J11: =(A11=TRUE)*SUM(Tabella7[Accollo debiti])*3% -> 0
A12: =+IF(p=1,"","Questa tabella non è significativa in caso di cessione o trasformazione") | C12: =SUM(Tabella7[Netto assegnato (Costo fiscale del bene in capo al socio)]) -> 302400 | E12: =SUM(Tabella7[Accollo debiti]) -> 0 | F12: =SUM(Tabella7[Base netta]) -> 220000 | G12: =SUM(Tabella7[Utili]) -> 220000 | H12: =SUM(Tabella7[Riserve]) -> 0 | I12: =SUM(Tabella7[Capitale sociale]) -> 0 | J12: =SUM(Tabella7[Totale attribuito]) -> 0 | L12: =SUM(Tabella7[Valore Part.]) -> 200000 | M12: =SUM(Tabella7[Dividendi da "Sottozero"]) -> 0 | N12: =SUM(Tabella7[Totale Redditi]) -> 220000 | O12: =SUM(Tabella7[Maggior IRPEF/Sostitutiva]) -> 57200 | P12: =SUM(Tabella7[Valore Normale attribuito]) -> 300000
A13: Socio | B13: % Cap | C13: Netto assegnato (Costo fiscale del bene in capo al socio) | D13: % Beni | E13: Accollo debiti | F13: Base netta | G13: Utili | H13: Riserve | I13: Capitale sociale | J13: Totale attribuito | K13: % Imp. Div. | L13: Valore Part. | M13: Dividendi da "Sottozero" | N13: Totale Redditi | O13: Maggior IRPEF/Sostitutiva | P13: Valore Normale attribuito | Q13: Dividendo teorico distribuito | R13: Eventuale conguaglio spettante
A14: =+IF(Soci!B6="","",Soci!B6) -> Socio X | B14: =+IF(Tabella7[[#This Row],[Socio]]="","",Soci!E6) -> 0.5 | C14: =+SUMIFS(Assegnazione[Valore ai fini dell''atto],Assegnazione[Agevolabile],1,Assegnazione[Socio],Tabella7[[#This Row],[Socio]])+SUMIFS(Assegnazione[Valore Normale],Assegnazione[Agevolabile],0,Assegnazione[Socio],Tabella7[[#This Row],[Socio]]) -> 151200 | D14: =+IF(Tabella7[[#This Row],[Socio]]="","",Tabella7[[#This Row],[Netto assegnato (Costo fiscale del bene in capo al socio)]]/'Tassazione Soci'!$C$12) -> 0.5 | F14: =+IFERROR(IF(Tabella7[[#This Row],[Socio]]="","",(Assegnazione!$H$3*Tabella7[[#This Row],[% Beni]]-Tabella7[[#This Row],[Accollo debiti]]-$D$8*Tabella7[[#This Row],[% Beni]])*((Assegnazione!$H$3*Tabella7[[#This Row],[% Beni]]-Tabella7[[#This Row],[Accollo debiti]])>0))*(p=1)+$B$7*(p=3)*Tabella7[[#This Row],[% Beni]],0) -> 110000 | G14: =+IFERROR(MAX(0,((SUMIF(Assegnazione[Socio],Tabella7[[#This Row],[Socio]],Assegnazione[Valore fiscale ai fini della Tassazione soci])-Tabella7[[#This Row],[Accollo debiti]])-$D$8*Tabella7[[#This Row],[% Beni]])*(p=1)*$O$6)+Tabella7[[#This Row],[Base netta]]*(p=3),0) -> 110000 | H14: =+IFERROR(MAX(0,((SUMIF(Assegnazione[Socio],Tabella7[[#This Row],[Socio]],Assegnazione[Valore fiscale ai fini della Tassazione soci])-Tabella7[[#This Row],[Accollo debiti]])-$D$8*Tabella7[[#This Row],[% Beni]])*(p=1)*$O$7)+Tabella7[[#This Row],[Base netta]]*(p=3),0) -> 0 | I14: =+IF(Tabella7[[#This Row],[Socio]]="",0,'Tassazione Soci'!E$9*$B14) -> 0 | J14: =+(Tabella7[[#This Row],[Riserve]]+Tabella7[[#This Row],[Capitale sociale]])*(p=1) -> 0 | K14: =+Soci!H6 -> 1 | L14: =+IF(Tabella7[[#This Row],[Socio]]="","",MAX(0,Soci!F6-Tabella7[[#This Row],[Riserve]])+(p=3)*(Tabella7[[#This Row],[% Beni]]*DATI!$E$34)) -> 100000 | M14: =+(Tabella7[[#This Row],[Totale attribuito]]-Soci!F6)*((Tabella7[[#This Row],[Totale attribuito]]-Soci!F6)>0) -> 0 | N14: =+IFERROR((Tabella7[[#This Row],[Dividendi da "Sottozero"]]+Tabella7[[#This Row],[Utili]]*IR)*Tabella7[[#This Row],[% Imp. Div.]],0)*(p=1) -> 110000 | O14: =+Tabella7[[#This Row],[Totale Redditi]]*Soci!G6 -> 28600 | P14: =+SUMIF(Assegnazione[Socio],Tabella7[[#This Row],[Socio]],Assegnazione[Valore Normale]) -> 150000 | Q14: =+IFERROR(Tabella7[[#This Row],[Valore Normale attribuito]]/Tabella7[[#This Row],[% Cap]],0)*(p=1) -> 300000 | R14: =+IFERROR(MAX(Tabella7[Dividendo teorico distribuito])*Tabella7[[#This Row],[% Cap]]-Tabella7[[#This Row],[Valore Normale attribuito]],0)*(p=1) -> 0
A15: =+IF(Soci!B7="","",Soci!B7) -> Socio Y | B15: =+IF(Tabella7[[#This Row],[Socio]]="","",Soci!E7) -> 0.5 | C15: =+SUMIFS(Assegnazione[Valore ai fini dell''atto],Assegnazione[Agevolabile],1,Assegnazione[Socio],Tabella7[[#This Row],[Socio]])+SUMIFS(Assegnazione[Valore Normale],Assegnazione[Agevolabile],0,Assegnazione[Socio],Tabella7[[#This Row],[Socio]]) -> 151200 | D15: =+IF(Tabella7[[#This Row],[Socio]]="","",Tabella7[[#This Row],[Netto assegnato (Costo fiscale del bene in capo al socio)]]/'Tassazione Soci'!$C$12) -> 0.5 | F15: =+IFERROR(IF(Tabella7[[#This Row],[Socio]]="","",(Assegnazione!$H$3*Tabella7[[#This Row],[% Beni]]-Tabella7[[#This Row],[Accollo debiti]]-$D$8*Tabella7[[#This Row],[% Beni]])*((Assegnazione!$H$3*Tabella7[[#This Row],[% Beni]]-Tabella7[[#This Row],[Accollo debiti]])>0))*(p=1)+$B$7*(p=3)*Tabella7[[#This Row],[% Beni]],0) -> 110000 | G15: =+IFERROR(MAX(0,((SUMIF(Assegnazione[Socio],Tabella7[[#This Row],[Socio]],Assegnazione[Valore fiscale ai fini della Tassazione soci])-Tabella7[[#This Row],[Accollo debiti]])-$D$8*Tabella7[[#This Row],[% Beni]])*(p=1)*$O$6)+Tabella7[[#This Row],[Base netta]]*(p=3),0) -> 110000 | H15: =+IFERROR(MAX(0,((SUMIF(Assegnazione[Socio],Tabella7[[#This Row],[Socio]],Assegnazione[Valore fiscale ai fini della Tassazione soci])-Tabella7[[#This Row],[Accollo debiti]])-$D$8*Tabella7[[#This Row],[% Beni]])*(p=1)*$O$7)+Tabella7[[#This Row],[Base netta]]*(p=3),0) -> 0 | I15: =+IF(Tabella7[[#This Row],[Socio]]="",0,'Tassazione Soci'!E$9*$B15) -> 0 | J15: =+(Tabella7[[#This Row],[Riserve]]+Tabella7[[#This Row],[Capitale sociale]])*(p=1) -> 0 | K15: =+Soci!H7 -> 1 | L15: =+IF(Tabella7[[#This Row],[Socio]]="","",MAX(0,Soci!F7-Tabella7[[#This Row],[Riserve]])+(p=3)*(Tabella7[[#This Row],[% Beni]]*DATI!$E$34)) -> 100000 | M15: =+(Tabella7[[#This Row],[Totale attribuito]]-Soci!F7)*((Tabella7[[#This Row],[Totale attribuito]]-Soci!F7)>0) -> 0 | N15: =+IFERROR((Tabella7[[#This Row],[Dividendi da "Sottozero"]]+Tabella7[[#This Row],[Utili]]*IR)*Tabella7[[#This Row],[% Imp. Div.]],0)*(p=1) -> 110000 | O15: =+Tabella7[[#This Row],[Totale Redditi]]*Soci!G7 -> 28600 | P15: =+SUMIF(Assegnazione[Socio],Tabella7[[#This Row],[Socio]],Assegnazione[Valore Normale]) -> 150000 | Q15: =+IFERROR(Tabella7[[#This Row],[Valore Normale attribuito]]/Tabella7[[#This Row],[% Cap]],0)*(p=1) -> 300000 | R15: =+IFERROR(MAX(Tabella7[Dividendo teorico distribuito])*Tabella7[[#This Row],[% Cap]]-Tabella7[[#This Row],[Valore Normale attribuito]],0)*(p=1) -> 0
A16: =+IF(Soci!B8="","",Soci!B8) | B16: =+IF(Tabella7[[#This Row],[Socio]]="","",Soci!E8) | C16: =+SUMIFS(Assegnazione[Valore ai fini dell''atto],Assegnazione[Agevolabile],1,Assegnazione[Socio],Tabella7[[#This Row],[Socio]])+SUMIFS(Assegnazione[Valore Normale],Assegnazione[Agevolabile],0,Assegnazione[Socio],Tabella7[[#This Row],[Socio]]) -> 0 | D16: =+IF(Tabella7[[#This Row],[Socio]]="","",Tabella7[[#This Row],[Netto assegnato (Costo fiscale del bene in capo al socio)]]/'Tassazione Soci'!$C$12) | F16: =+IFERROR(IF(Tabella7[[#This Row],[Socio]]="","",(Assegnazione!$H$3*Tabella7[[#This Row],[% Beni]]-Tabella7[[#This Row],[Accollo debiti]]-$D$8*Tabella7[[#This Row],[% Beni]])*((Assegnazione!$H$3*Tabella7[[#This Row],[% Beni]]-Tabella7[[#This Row],[Accollo debiti]])>0))*(p=1)+$B$7*(p=3)*Tabella7[[#This Row],[% Beni]],0) -> 0 | G16: =+IFERROR(MAX(0,((SUMIF(Assegnazione[Socio],Tabella7[[#This Row],[Socio]],Assegnazione[Valore fiscale ai fini della Tassazione soci])-Tabella7[[#This Row],[Accollo debiti]])-$D$8*Tabella7[[#This Row],[% Beni]])*(p=1)*$O$6)+Tabella7[[#This Row],[Base netta]]*(p=3),0) -> 0 | H16: =+IFERROR(MAX(0,((SUMIF(Assegnazione[Socio],Tabella7[[#This Row],[Socio]],Assegnazione[Valore fiscale ai fini della Tassazione soci])-Tabella7[[#This Row],[Accollo debiti]])-$D$8*Tabella7[[#This Row],[% Beni]])*(p=1)*$O$7)+Tabella7[[#This Row],[Base netta]]*(p=3),0) -> 0 | I16: =+IF(Tabella7[[#This Row],[Socio]]="",0,'Tassazione Soci'!E$9*$B16) -> 0 | J16: =+(Tabella7[[#This Row],[Riserve]]+Tabella7[[#This Row],[Capitale sociale]])*(p=1) -> 0 | K16: =+Soci!H8 -> 0 | L16: =+IF(Tabella7[[#This Row],[Socio]]="","",MAX(0,Soci!F8-Tabella7[[#This Row],[Riserve]])+(p=3)*(Tabella7[[#This Row],[% Beni]]*DATI!$E$34)) | M16: =+(Tabella7[[#This Row],[Totale attribuito]]-Soci!F8)*((Tabella7[[#This Row],[Totale attribuito]]-Soci!F8)>0) -> 0 | N16: =+IFERROR((Tabella7[[#This Row],[Dividendi da "Sottozero"]]+Tabella7[[#This Row],[Utili]]*IR)*Tabella7[[#This Row],[% Imp. Div.]],0)*(p=1) -> 0 | O16: =+Tabella7[[#This Row],[Totale Redditi]]*Soci!G8 -> 0 | P16: =+SUMIF(Assegnazione[Socio],Tabella7[[#This Row],[Socio]],Assegnazione[Valore Normale]) -> 0 | Q16: =+IFERROR(Tabella7[[#This Row],[Valore Normale attribuito]]/Tabella7[[#This Row],[% Cap]],0)*(p=1) -> 0 | R16: =+IFERROR(MAX(Tabella7[Dividendo teorico distribuito])*Tabella7[[#This Row],[% Cap]]-Tabella7[[#This Row],[Valore Normale attribuito]],0)*(p=1) -> 0
A17: =+IF(Soci!B9="","",Soci!B9) | B17: =+IF(Tabella7[[#This Row],[Socio]]="","",Soci!E9) | C17: =+SUMIFS(Assegnazione[Valore ai fini dell''atto],Assegnazione[Agevolabile],1,Assegnazione[Socio],Tabella7[[#This Row],[Socio]])+SUMIFS(Assegnazione[Valore Normale],Assegnazione[Agevolabile],0,Assegnazione[Socio],Tabella7[[#This Row],[Socio]]) -> 0 | D17: =+IF(Tabella7[[#This Row],[Socio]]="","",Tabella7[[#This Row],[Netto assegnato (Costo fiscale del bene in capo al socio)]]/'Tassazione Soci'!$C$12) | F17: =+IFERROR(IF(Tabella7[[#This Row],[Socio]]="","",(Assegnazione!$H$3*Tabella7[[#This Row],[% Beni]]-Tabella7[[#This Row],[Accollo debiti]]-$D$8*Tabella7[[#This Row],[% Beni]])*((Assegnazione!$H$3*Tabella7[[#This Row],[% Beni]]-Tabella7[[#This Row],[Accollo debiti]])>0))*(p=1)+$B$7*(p=3)*Tabella7[[#This Row],[% Beni]],0) -> 0 | G17: =+IFERROR(MAX(0,((SUMIF(Assegnazione[Socio],Tabella7[[#This Row],[Socio]],Assegnazione[Valore fiscale ai fini della Tassazione soci])-Tabella7[[#This Row],[Accollo debiti]])-$D$8*Tabella7[[#This Row],[% Beni]])*(p=1)*$O$6)+Tabella7[[#This Row],[Base netta]]*(p=3),0) -> 0 | H17: =+IFERROR(MAX(0,((SUMIF(Assegnazione[Socio],Tabella7[[#This Row],[Socio]],Assegnazione[Valore fiscale ai fini della Tassazione soci])-Tabella7[[#This Row],[Accollo debiti]])-$D$8*Tabella7[[#This Row],[% Beni]])*(p=1)*$O$7)+Tabella7[[#This Row],[Base netta]]*(p=3),0) -> 0 | I17: =+IF(Tabella7[[#This Row],[Socio]]="",0,'Tassazione Soci'!E$9*$B17) -> 0 | J17: =+(Tabella7[[#This Row],[Riserve]]+Tabella7[[#This Row],[Capitale sociale]])*(p=1) -> 0 | K17: =+Soci!H9 -> 0 | L17: =+IF(Tabella7[[#This Row],[Socio]]="","",MAX(0,Soci!F9-Tabella7[[#This Row],[Riserve]])+(p=3)*(Tabella7[[#This Row],[% Beni]]*DATI!$E$34)) | M17: =+(Tabella7[[#This Row],[Totale attribuito]]-Soci!F9)*((Tabella7[[#This Row],[Totale attribuito]]-Soci!F9)>0) -> 0 | N17: =+IFERROR((Tabella7[[#This Row],[Dividendi da "Sottozero"]]+Tabella7[[#This Row],[Utili]]*IR)*Tabella7[[#This Row],[% Imp. Div.]],0)*(p=1) -> 0 | O17: =+Tabella7[[#This Row],[Totale Redditi]]*Soci!G9 -> 0 | P17: =+SUMIF(Assegnazione[Socio],Tabella7[[#This Row],[Socio]],Assegnazione[Valore Normale]) -> 0 | Q17: =+IFERROR(Tabella7[[#This Row],[Valore Normale attribuito]]/Tabella7[[#This Row],[% Cap]],0)*(p=1) -> 0 | R17: =+IFERROR(MAX(Tabella7[Dividendo teorico distribuito])*Tabella7[[#This Row],[% Cap]]-Tabella7[[#This Row],[Valore Normale attribuito]],0)*(p=1) -> 0
A18: =+IF(Soci!B10="","",Soci!B10) | B18: =+IF(Tabella7[[#This Row],[Socio]]="","",Soci!E10) | C18: =+SUMIFS(Assegnazione[Valore ai fini dell''atto],Assegnazione[Agevolabile],1,Assegnazione[Socio],Tabella7[[#This Row],[Socio]])+SUMIFS(Assegnazione[Valore Normale],Assegnazione[Agevolabile],0,Assegnazione[Socio],Tabella7[[#This Row],[Socio]]) -> 0 | D18: =+IF(Tabella7[[#This Row],[Socio]]="","",Tabella7[[#This Row],[Netto assegnato (Costo fiscale del bene in capo al socio)]]/'Tassazione Soci'!$C$12) | F18: =+IFERROR(IF(Tabella7[[#This Row],[Socio]]="","",(Assegnazione!$H$3*Tabella7[[#This Row],[% Beni]]-Tabella7[[#This Row],[Accollo debiti]]-$D$8*Tabella7[[#This Row],[% Beni]])*((Assegnazione!$H$3*Tabella7[[#This Row],[% Beni]]-Tabella7[[#This Row],[Accollo debiti]])>0))*(p=1)+$B$7*(p=3)*Tabella7[[#This Row],[% Beni]],0) -> 0 | G18: =+IFERROR(MAX(0,((SUMIF(Assegnazione[Socio],Tabella7[[#This Row],[Socio]],Assegnazione[Valore fiscale ai fini della Tassazione soci])-Tabella7[[#This Row],[Accollo debiti]])-$D$8*Tabella7[[#This Row],[% Beni]])*(p=1)*$O$6)+Tabella7[[#This Row],[Base netta]]*(p=3),0) -> 0 | H18: =+IFERROR(MAX(0,((SUMIF(Assegnazione[Socio],Tabella7[[#This Row],[Socio]],Assegnazione[Valore fiscale ai fini della Tassazione soci])-Tabella7[[#This Row],[Accollo debiti]])-$D$8*Tabella7[[#This Row],[% Beni]])*(p=1)*$O$7)+Tabella7[[#This Row],[Base netta]]*(p=3),0) -> 0 | I18: =+IF(Tabella7[[#This Row],[Socio]]="",0,'Tassazione Soci'!E$9*$B18) -> 0 | J18: =+(Tabella7[[#This Row],[Riserve]]+Tabella7[[#This Row],[Capitale sociale]])*(p=1) -> 0 | K18: =+Soci!H10 -> 0 | L18: =+IF(Tabella7[[#This Row],[Socio]]="","",MAX(0,Soci!F10-Tabella7[[#This Row],[Riserve]])+(p=3)*(Tabella7[[#This Row],[% Beni]]*DATI!$E$34)) | M18: =+(Tabella7[[#This Row],[Totale attribuito]]-Soci!F10)*((Tabella7[[#This Row],[Totale attribuito]]-Soci!F10)>0) -> 0 | N18: =+IFERROR((Tabella7[[#This Row],[Dividendi da "Sottozero"]]+Tabella7[[#This Row],[Utili]]*IR)*Tabella7[[#This Row],[% Imp. Div.]],0)*(p=1) -> 0 | O18: =+Tabella7[[#This Row],[Totale Redditi]]*Soci!G10 -> 0 | P18: =+SUMIF(Assegnazione[Socio],Tabella7[[#This Row],[Socio]],Assegnazione[Valore Normale]) -> 0 | Q18: =+IFERROR(Tabella7[[#This Row],[Valore Normale attribuito]]/Tabella7[[#This Row],[% Cap]],0)*(p=1) -> 0 | R18: =+IFERROR(MAX(Tabella7[Dividendo teorico distribuito])*Tabella7[[#This Row],[% Cap]]-Tabella7[[#This Row],[Valore Normale attribuito]],0)*(p=1) -> 0
A19: =+IF(Soci!B11="","",Soci!B11) | B19: =+IF(Tabella7[[#This Row],[Socio]]="","",Soci!E11) | C19: =+SUMIFS(Assegnazione[Valore ai fini dell''atto],Assegnazione[Agevolabile],1,Assegnazione[Socio],Tabella7[[#This Row],[Socio]])+SUMIFS(Assegnazione[Valore Normale],Assegnazione[Agevolabile],0,Assegnazione[Socio],Tabella7[[#This Row],[Socio]]) -> 0 | D19: =+IF(Tabella7[[#This Row],[Socio]]="","",Tabella7[[#This Row],[Netto assegnato (Costo fiscale del bene in capo al socio)]]/'Tassazione Soci'!$C$12) | F19: =+IFERROR(IF(Tabella7[[#This Row],[Socio]]="","",(Assegnazione!$H$3*Tabella7[[#This Row],[% Beni]]-Tabella7[[#This Row],[Accollo debiti]]-$D$8*Tabella7[[#This Row],[% Beni]])*((Assegnazione!$H$3*Tabella7[[#This Row],[% Beni]]-Tabella7[[#This Row],[Accollo debiti]])>0))*(p=1)+$B$7*(p=3)*Tabella7[[#This Row],[% Beni]],0) -> 0 | G19: =+IFERROR(MAX(0,((SUMIF(Assegnazione[Socio],Tabella7[[#This Row],[Socio]],Assegnazione[Valore fiscale ai fini della Tassazione soci])-Tabella7[[#This Row],[Accollo debiti]])-$D$8*Tabella7[[#This Row],[% Beni]])*(p=1)*$O$6)+Tabella7[[#This Row],[Base netta]]*(p=3),0) -> 0 | H19: =+IFERROR(MAX(0,((SUMIF(Assegnazione[Socio],Tabella7[[#This Row],[Socio]],Assegnazione[Valore fiscale ai fini della Tassazione soci])-Tabella7[[#This Row],[Accollo debiti]])-$D$8*Tabella7[[#This Row],[% Beni]])*(p=1)*$O$7)+Tabella7[[#This Row],[Base netta]]*(p=3),0) -> 0 | I19: =+IF(Tabella7[[#This Row],[Socio]]="",0,'Tassazione Soci'!E$9*$B19) -> 0 | J19: =+(Tabella7[[#This Row],[Riserve]]+Tabella7[[#This Row],[Capitale sociale]])*(p=1) -> 0 | K19: =+Soci!H11 -> 0 | L19: =+IF(Tabella7[[#This Row],[Socio]]="","",MAX(0,Soci!F11-Tabella7[[#This Row],[Riserve]])+(p=3)*(Tabella7[[#This Row],[% Beni]]*DATI!$E$34)) | M19: =+(Tabella7[[#This Row],[Totale attribuito]]-Soci!F11)*((Tabella7[[#This Row],[Totale attribuito]]-Soci!F11)>0) -> 0 | N19: =+IFERROR((Tabella7[[#This Row],[Dividendi da "Sottozero"]]+Tabella7[[#This Row],[Utili]]*IR)*Tabella7[[#This Row],[% Imp. Div.]],0)*(p=1) -> 0 | O19: =+Tabella7[[#This Row],[Totale Redditi]]*Soci!G11 -> 0 | P19: =+SUMIF(Assegnazione[Socio],Tabella7[[#This Row],[Socio]],Assegnazione[Valore Normale]) -> 0 | Q19: =+IFERROR(Tabella7[[#This Row],[Valore Normale attribuito]]/Tabella7[[#This Row],[% Cap]],0)*(p=1) -> 0 | R19: =+IFERROR(MAX(Tabella7[Dividendo teorico distribuito])*Tabella7[[#This Row],[% Cap]]-Tabella7[[#This Row],[Valore Normale attribuito]],0)*(p=1) -> 0
A20: =+IF(Soci!B12="","",Soci!B12) | B20: =+IF(Tabella7[[#This Row],[Socio]]="","",Soci!E12) | C20: =+SUMIFS(Assegnazione[Valore ai fini dell''atto],Assegnazione[Agevolabile],1,Assegnazione[Socio],Tabella7[[#This Row],[Socio]])+SUMIFS(Assegnazione[Valore Normale],Assegnazione[Agevolabile],0,Assegnazione[Socio],Tabella7[[#This Row],[Socio]]) -> 0 | D20: =+IF(Tabella7[[#This Row],[Socio]]="","",Tabella7[[#This Row],[Netto assegnato (Costo fiscale del bene in capo al socio)]]/'Tassazione Soci'!$C$12) | F20: =+IFERROR(IF(Tabella7[[#This Row],[Socio]]="","",(Assegnazione!$H$3*Tabella7[[#This Row],[% Beni]]-Tabella7[[#This Row],[Accollo debiti]]-$D$8*Tabella7[[#This Row],[% Beni]])*((Assegnazione!$H$3*Tabella7[[#This Row],[% Beni]]-Tabella7[[#This Row],[Accollo debiti]])>0))*(p=1)+$B$7*(p=3)*Tabella7[[#This Row],[% Beni]],0) -> 0 | G20: =+IFERROR(MAX(0,((SUMIF(Assegnazione[Socio],Tabella7[[#This Row],[Socio]],Assegnazione[Valore fiscale ai fini della Tassazione soci])-Tabella7[[#This Row],[Accollo debiti]])-$D$8*Tabella7[[#This Row],[% Beni]])*(p=1)*$O$6)+Tabella7[[#This Row],[Base netta]]*(p=3),0) -> 0 | H20: =+IFERROR(MAX(0,((SUMIF(Assegnazione[Socio],Tabella7[[#This Row],[Socio]],Assegnazione[Valore fiscale ai fini della Tassazione soci])-Tabella7[[#This Row],[Accollo debiti]])-$D$8*Tabella7[[#This Row],[% Beni]])*(p=1)*$O$7)+Tabella7[[#This Row],[Base netta]]*(p=3),0) -> 0 | I20: =+IF(Tabella7[[#This Row],[Socio]]="",0,'Tassazione Soci'!E$9*$B20) -> 0 | J20: =+(Tabella7[[#This Row],[Riserve]]+Tabella7[[#This Row],[Capitale sociale]])*(p=1) -> 0 | K20: =+Soci!H12 -> 0 | L20: =+IF(Tabella7[[#This Row],[Socio]]="","",MAX(0,Soci!F12-Tabella7[[#This Row],[Riserve]])+(p=3)*(Tabella7[[#This Row],[% Beni]]*DATI!$E$34)) | M20: =+(Tabella7[[#This Row],[Totale attribuito]]-Soci!F12)*((Tabella7[[#This Row],[Totale attribuito]]-Soci!F12)>0) -> 0 | N20: =+IFERROR((Tabella7[[#This Row],[Dividendi da "Sottozero"]]+Tabella7[[#This Row],[Utili]]*IR)*Tabella7[[#This Row],[% Imp. Div.]],0)*(p=1) -> 0 | O20: =+Tabella7[[#This Row],[Totale Redditi]]*Soci!G12 -> 0 | P20: =+SUMIF(Assegnazione[Socio],Tabella7[[#This Row],[Socio]],Assegnazione[Valore Normale]) -> 0 | Q20: =+IFERROR(Tabella7[[#This Row],[Valore Normale attribuito]]/Tabella7[[#This Row],[% Cap]],0)*(p=1) -> 0 | R20: =+IFERROR(MAX(Tabella7[Dividendo teorico distribuito])*Tabella7[[#This Row],[% Cap]]-Tabella7[[#This Row],[Valore Normale attribuito]],0)*(p=1) -> 0
A21: =+IF(Soci!B13="","",Soci!B13) | B21: =+IF(Tabella7[[#This Row],[Socio]]="","",Soci!E13) | C21: =+SUMIFS(Assegnazione[Valore ai fini dell''atto],Assegnazione[Agevolabile],1,Assegnazione[Socio],Tabella7[[#This Row],[Socio]])+SUMIFS(Assegnazione[Valore Normale],Assegnazione[Agevolabile],0,Assegnazione[Socio],Tabella7[[#This Row],[Socio]]) -> 0 | D21: =+IF(Tabella7[[#This Row],[Socio]]="","",Tabella7[[#This Row],[Netto assegnato (Costo fiscale del bene in capo al socio)]]/'Tassazione Soci'!$C$12) | F21: =+IFERROR(IF(Tabella7[[#This Row],[Socio]]="","",(Assegnazione!$H$3*Tabella7[[#This Row],[% Beni]]-Tabella7[[#This Row],[Accollo debiti]]-$D$8*Tabella7[[#This Row],[% Beni]])*((Assegnazione!$H$3*Tabella7[[#This Row],[% Beni]]-Tabella7[[#This Row],[Accollo debiti]])>0))*(p=1)+$B$7*(p=3)*Tabella7[[#This Row],[% Beni]],0) -> 0 | G21: =+IFERROR(MAX(0,((SUMIF(Assegnazione[Socio],Tabella7[[#This Row],[Socio]],Assegnazione[Valore fiscale ai fini della Tassazione soci])-Tabella7[[#This Row],[Accollo debiti]])-$D$8*Tabella7[[#This Row],[% Beni]])*(p=1)*$O$6)+Tabella7[[#This Row],[Base netta]]*(p=3),0) -> 0 | H21: =+IFERROR(MAX(0,((SUMIF(Assegnazione[Socio],Tabella7[[#This Row],[Socio]],Assegnazione[Valore fiscale ai fini della Tassazione soci])-Tabella7[[#This Row],[Accollo debiti]])-$D$8*Tabella7[[#This Row],[% Beni]])*(p=1)*$O$7)+Tabella7[[#This Row],[Base netta]]*(p=3),0) -> 0 | I21: =+IF(Tabella7[[#This Row],[Socio]]="",0,'Tassazione Soci'!E$9*$B21) -> 0 | J21: =+(Tabella7[[#This Row],[Riserve]]+Tabella7[[#This Row],[Capitale sociale]])*(p=1) -> 0 | K21: =+Soci!H13 -> 0 | L21: =+IF(Tabella7[[#This Row],[Socio]]="","",MAX(0,Soci!F13-Tabella7[[#This Row],[Riserve]])+(p=3)*(Tabella7[[#This Row],[% Beni]]*DATI!$E$34)) | M21: =+(Tabella7[[#This Row],[Totale attribuito]]-Soci!F13)*((Tabella7[[#This Row],[Totale attribuito]]-Soci!F13)>0) -> 0 | N21: =+IFERROR((Tabella7[[#This Row],[Dividendi da "Sottozero"]]+Tabella7[[#This Row],[Utili]]*IR)*Tabella7[[#This Row],[% Imp. Div.]],0)*(p=1) -> 0 | O21: =+Tabella7[[#This Row],[Totale Redditi]]*Soci!G13 -> 0 | P21: =+SUMIF(Assegnazione[Socio],Tabella7[[#This Row],[Socio]],Assegnazione[Valore Normale]) -> 0 | Q21: =+IFERROR(Tabella7[[#This Row],[Valore Normale attribuito]]/Tabella7[[#This Row],[% Cap]],0)*(p=1) -> 0 | R21: =+IFERROR(MAX(Tabella7[Dividendo teorico distribuito])*Tabella7[[#This Row],[% Cap]]-Tabella7[[#This Row],[Valore Normale attribuito]],0)*(p=1) -> 0
A22: =+IF(Soci!B14="","",Soci!B14) | B22: =+IF(Tabella7[[#This Row],[Socio]]="","",Soci!E14) | C22: =+SUMIFS(Assegnazione[Valore ai fini dell''atto],Assegnazione[Agevolabile],1,Assegnazione[Socio],Tabella7[[#This Row],[Socio]])+SUMIFS(Assegnazione[Valore Normale],Assegnazione[Agevolabile],0,Assegnazione[Socio],Tabella7[[#This Row],[Socio]]) -> 0 | D22: =+IF(Tabella7[[#This Row],[Socio]]="","",Tabella7[[#This Row],[Netto assegnato (Costo fiscale del bene in capo al socio)]]/'Tassazione Soci'!$C$12) | F22: =+IFERROR(IF(Tabella7[[#This Row],[Socio]]="","",(Assegnazione!$H$3*Tabella7[[#This Row],[% Beni]]-Tabella7[[#This Row],[Accollo debiti]]-$D$8*Tabella7[[#This Row],[% Beni]])*((Assegnazione!$H$3*Tabella7[[#This Row],[% Beni]]-Tabella7[[#This Row],[Accollo debiti]])>0))*(p=1)+$B$7*(p=3)*Tabella7[[#This Row],[% Beni]],0) -> 0 | G22: =+IFERROR(MAX(0,((SUMIF(Assegnazione[Socio],Tabella7[[#This Row],[Socio]],Assegnazione[Valore fiscale ai fini della Tassazione soci])-Tabella7[[#This Row],[Accollo debiti]])-$D$8*Tabella7[[#This Row],[% Beni]])*(p=1)*$O$6)+Tabella7[[#This Row],[Base netta]]*(p=3),0) -> 0 | H22: =+IFERROR(MAX(0,((SUMIF(Assegnazione[Socio],Tabella7[[#This Row],[Socio]],Assegnazione[Valore fiscale ai fini della Tassazione soci])-Tabella7[[#This Row],[Accollo debiti]])-$D$8*Tabella7[[#This Row],[% Beni]])*(p=1)*$O$7)+Tabella7[[#This Row],[Base netta]]*(p=3),0) -> 0 | I22: =+IF(Tabella7[[#This Row],[Socio]]="",0,'Tassazione Soci'!E$9*$B22) -> 0 | J22: =+(Tabella7[[#This Row],[Riserve]]+Tabella7[[#This Row],[Capitale sociale]])*(p=1) -> 0 | K22: =+Soci!H14 -> 0 | L22: =+IF(Tabella7[[#This Row],[Socio]]="","",MAX(0,Soci!F14-Tabella7[[#This Row],[Riserve]])+(p=3)*(Tabella7[[#This Row],[% Beni]]*DATI!$E$34)) | M22: =+(Tabella7[[#This Row],[Totale attribuito]]-Soci!F14)*((Tabella7[[#This Row],[Totale attribuito]]-Soci!F14)>0) -> 0 | N22: =+IFERROR((Tabella7[[#This Row],[Dividendi da "Sottozero"]]+Tabella7[[#This Row],[Utili]]*IR)*Tabella7[[#This Row],[% Imp. Div.]],0)*(p=1) -> 0 | O22: =+Tabella7[[#This Row],[Totale Redditi]]*Soci!G14 -> 0 | P22: =+SUMIF(Assegnazione[Socio],Tabella7[[#This Row],[Socio]],Assegnazione[Valore Normale]) -> 0 | Q22: =+IFERROR(Tabella7[[#This Row],[Valore Normale attribuito]]/Tabella7[[#This Row],[% Cap]],0)*(p=1) -> 0 | R22: =+IFERROR(MAX(Tabella7[Dividendo teorico distribuito])*Tabella7[[#This Row],[% Cap]]-Tabella7[[#This Row],[Valore Normale attribuito]],0)*(p=1) -> 0
A23: =+IF(Soci!B15="","",Soci!B15) | B23: =+IF(Tabella7[[#This Row],[Socio]]="","",Soci!E15) | C23: =+SUMIFS(Assegnazione[Valore ai fini dell''atto],Assegnazione[Agevolabile],1,Assegnazione[Socio],Tabella7[[#This Row],[Socio]])+SUMIFS(Assegnazione[Valore Normale],Assegnazione[Agevolabile],0,Assegnazione[Socio],Tabella7[[#This Row],[Socio]]) -> 0 | D23: =+IF(Tabella7[[#This Row],[Socio]]="","",Tabella7[[#This Row],[Netto assegnato (Costo fiscale del bene in capo al socio)]]/'Tassazione Soci'!$C$12) | F23: =+IFERROR(IF(Tabella7[[#This Row],[Socio]]="","",(Assegnazione!$H$3*Tabella7[[#This Row],[% Beni]]-Tabella7[[#This Row],[Accollo debiti]]-$D$8*Tabella7[[#This Row],[% Beni]])*((Assegnazione!$H$3*Tabella7[[#This Row],[% Beni]]-Tabella7[[#This Row],[Accollo debiti]])>0))*(p=1)+$B$7*(p=3)*Tabella7[[#This Row],[% Beni]],0) -> 0 | G23: =+IFERROR(MAX(0,((SUMIF(Assegnazione[Socio],Tabella7[[#This Row],[Socio]],Assegnazione[Valore fiscale ai fini della Tassazione soci])-Tabella7[[#This Row],[Accollo debiti]])-$D$8*Tabella7[[#This Row],[% Beni]])*(p=1)*$O$6)+Tabella7[[#This Row],[Base netta]]*(p=3),0) -> 0 | H23: =+IFERROR(MAX(0,((SUMIF(Assegnazione[Socio],Tabella7[[#This Row],[Socio]],Assegnazione[Valore fiscale ai fini della Tassazione soci])-Tabella7[[#This Row],[Accollo debiti]])-$D$8*Tabella7[[#This Row],[% Beni]])*(p=1)*$O$7)+Tabella7[[#This Row],[Base netta]]*(p=3),0) -> 0 | I23: =+IF(Tabella7[[#This Row],[Socio]]="",0,'Tassazione Soci'!E$9*$B23) -> 0 | J23: =+(Tabella7[[#This Row],[Riserve]]+Tabella7[[#This Row],[Capitale sociale]])*(p=1) -> 0 | K23: =+Soci!H15 -> 0 | L23: =+IF(Tabella7[[#This Row],[Socio]]="","",MAX(0,Soci!F15-Tabella7[[#This Row],[Riserve]])+(p=3)*(Tabella7[[#This Row],[% Beni]]*DATI!$E$34)) | M23: =+(Tabella7[[#This Row],[Totale attribuito]]-Soci!F15)*((Tabella7[[#This Row],[Totale attribuito]]-Soci!F15)>0) -> 0 | N23: =+IFERROR((Tabella7[[#This Row],[Dividendi da "Sottozero"]]+Tabella7[[#This Row],[Utili]]*IR)*Tabella7[[#This Row],[% Imp. Div.]],0)*(p=1) -> 0 | O23: =+Tabella7[[#This Row],[Totale Redditi]]*Soci!G15 -> 0 | P23: =+SUMIF(Assegnazione[Socio],Tabella7[[#This Row],[Socio]],Assegnazione[Valore Normale]) -> 0 | Q23: =+IFERROR(Tabella7[[#This Row],[Valore Normale attribuito]]/Tabella7[[#This Row],[% Cap]],0)*(p=1) -> 0 | R23: =+IFERROR(MAX(Tabella7[Dividendo teorico distribuito])*Tabella7[[#This Row],[% Cap]]-Tabella7[[#This Row],[Valore Normale attribuito]],0)*(p=1) -> 0
A24: =+IF(Soci!B16="","",Soci!B16) | B24: =+IF(Tabella7[[#This Row],[Socio]]="","",Soci!E16) | C24: =+SUMIFS(Assegnazione[Valore ai fini dell''atto],Assegnazione[Agevolabile],1,Assegnazione[Socio],Tabella7[[#This Row],[Socio]])+SUMIFS(Assegnazione[Valore Normale],Assegnazione[Agevolabile],0,Assegnazione[Socio],Tabella7[[#This Row],[Socio]]) -> 0 | D24: =+IF(Tabella7[[#This Row],[Socio]]="","",Tabella7[[#This Row],[Netto assegnato (Costo fiscale del bene in capo al socio)]]/'Tassazione Soci'!$C$12) | F24: =+IFERROR(IF(Tabella7[[#This Row],[Socio]]="","",(Assegnazione!$H$3*Tabella7[[#This Row],[% Beni]]-Tabella7[[#This Row],[Accollo debiti]]-$D$8*Tabella7[[#This Row],[% Beni]])*((Assegnazione!$H$3*Tabella7[[#This Row],[% Beni]]-Tabella7[[#This Row],[Accollo debiti]])>0))*(p=1)+$B$7*(p=3)*Tabella7[[#This Row],[% Beni]],0) -> 0 | G24: =+IFERROR(MAX(0,((SUMIF(Assegnazione[Socio],Tabella7[[#This Row],[Socio]],Assegnazione[Valore fiscale ai fini della Tassazione soci])-Tabella7[[#This Row],[Accollo debiti]])-$D$8*Tabella7[[#This Row],[% Beni]])*(p=1)*$O$6)+Tabella7[[#This Row],[Base netta]]*(p=3),0) -> 0 | H24: =+IFERROR(MAX(0,((SUMIF(Assegnazione[Socio],Tabella7[[#This Row],[Socio]],Assegnazione[Valore fiscale ai fini della Tassazione soci])-Tabella7[[#This Row],[Accollo debiti]])-$D$8*Tabella7[[#This Row],[% Beni]])*(p=1)*$O$7)+Tabella7[[#This Row],[Base netta]]*(p=3),0) -> 0 | I24: =+IF(Tabella7[[#This Row],[Socio]]="",0,'Tassazione Soci'!E$9*$B24) -> 0 | J24: =+(Tabella7[[#This Row],[Riserve]]+Tabella7[[#This Row],[Capitale sociale]])*(p=1) -> 0 | K24: =+Soci!H16 -> 0 | L24: =+IF(Tabella7[[#This Row],[Socio]]="","",MAX(0,Soci!F16-Tabella7[[#This Row],[Riserve]])+(p=3)*(Tabella7[[#This Row],[% Beni]]*DATI!$E$34)) | M24: =+(Tabella7[[#This Row],[Totale attribuito]]-Soci!F16)*((Tabella7[[#This Row],[Totale attribuito]]-Soci!F16)>0) -> 0 | N24: =+IFERROR((Tabella7[[#This Row],[Dividendi da "Sottozero"]]+Tabella7[[#This Row],[Utili]]*IR)*Tabella7[[#This Row],[% Imp. Div.]],0)*(p=1) -> 0 | O24: =+Tabella7[[#This Row],[Totale Redditi]]*Soci!G16 -> 0 | P24: =+SUMIF(Assegnazione[Socio],Tabella7[[#This Row],[Socio]],Assegnazione[Valore Normale]) -> 0 | Q24: =+IFERROR(Tabella7[[#This Row],[Valore Normale attribuito]]/Tabella7[[#This Row],[% Cap]],0)*(p=1) -> 0 | R24: =+IFERROR(MAX(Tabella7[Dividendo teorico distribuito])*Tabella7[[#This Row],[% Cap]]-Tabella7[[#This Row],[Valore Normale attribuito]],0)*(p=1) -> 0
A25: =+IF(Soci!B17="","",Soci!B17) | B25: =+IF(Tabella7[[#This Row],[Socio]]="","",Soci!E17) | C25: =+SUMIFS(Assegnazione[Valore ai fini dell''atto],Assegnazione[Agevolabile],1,Assegnazione[Socio],Tabella7[[#This Row],[Socio]])+SUMIFS(Assegnazione[Valore Normale],Assegnazione[Agevolabile],0,Assegnazione[Socio],Tabella7[[#This Row],[Socio]]) -> 0 | D25: =+IF(Tabella7[[#This Row],[Socio]]="","",Tabella7[[#This Row],[Netto assegnato (Costo fiscale del bene in capo al socio)]]/'Tassazione Soci'!$C$12) | F25: =+IFERROR(IF(Tabella7[[#This Row],[Socio]]="","",(Assegnazione!$H$3*Tabella7[[#This Row],[% Beni]]-Tabella7[[#This Row],[Accollo debiti]]-$D$8*Tabella7[[#This Row],[% Beni]])*((Assegnazione!$H$3*Tabella7[[#This Row],[% Beni]]-Tabella7[[#This Row],[Accollo debiti]])>0))*(p=1)+$B$7*(p=3)*Tabella7[[#This Row],[% Beni]],0) -> 0 | G25: =+IFERROR(MAX(0,((SUMIF(Assegnazione[Socio],Tabella7[[#This Row],[Socio]],Assegnazione[Valore fiscale ai fini della Tassazione soci])-Tabella7[[#This Row],[Accollo debiti]])-$D$8*Tabella7[[#This Row],[% Beni]])*(p=1)*$O$6)+Tabella7[[#This Row],[Base netta]]*(p=3),0) -> 0 | H25: =+IFERROR(MAX(0,((SUMIF(Assegnazione[Socio],Tabella7[[#This Row],[Socio]],Assegnazione[Valore fiscale ai fini della Tassazione soci])-Tabella7[[#This Row],[Accollo debiti]])-$D$8*Tabella7[[#This Row],[% Beni]])*(p=1)*$O$7)+Tabella7[[#This Row],[Base netta]]*(p=3),0) -> 0 | I25: =+IF(Tabella7[[#This Row],[Socio]]="",0,'Tassazione Soci'!E$9*$B25) -> 0 | J25: =+(Tabella7[[#This Row],[Riserve]]+Tabella7[[#This Row],[Capitale sociale]])*(p=1) -> 0 | K25: =+Soci!H17 -> 0 | L25: =+IF(Tabella7[[#This Row],[Socio]]="","",MAX(0,Soci!F17-Tabella7[[#This Row],[Riserve]])+(p=3)*(Tabella7[[#This Row],[% Beni]]*DATI!$E$34)) | M25: =+(Tabella7[[#This Row],[Totale attribuito]]-Soci!F17)*((Tabella7[[#This Row],[Totale attribuito]]-Soci!F17)>0) -> 0 | N25: =+IFERROR((Tabella7[[#This Row],[Dividendi da "Sottozero"]]+Tabella7[[#This Row],[Utili]]*IR)*Tabella7[[#This Row],[% Imp. Div.]],0)*(p=1) -> 0 | O25: =+Tabella7[[#This Row],[Totale Redditi]]*Soci!G17 -> 0 | P25: =+SUMIF(Assegnazione[Socio],Tabella7[[#This Row],[Socio]],Assegnazione[Valore Normale]) -> 0 | Q25: =+IFERROR(Tabella7[[#This Row],[Valore Normale attribuito]]/Tabella7[[#This Row],[% Cap]],0)*(p=1) -> 0 | R25: =+IFERROR(MAX(Tabella7[Dividendo teorico distribuito])*Tabella7[[#This Row],[% Cap]]-Tabella7[[#This Row],[Valore Normale attribuito]],0)*(p=1) -> 0
... A113: =+IF(Soci!B105="","",Soci!B105) | B113: =+IF(Tabella7[[#This Row],[Socio]]="","",Soci!E105) | C113: =+SUMIFS(Assegnazione[Valore ai fini dell''atto],Assegnazione[Agevolabile],1,Assegnazione[Socio],Tabella7[[#This Row],[Socio]])+SUMIFS(Assegnazione[Valore Normale],Assegnazione[Agevolabile],0,Assegnazione[Socio],Tabella7[[#This Row],[Socio]]) -> 0 | D113: =+IF(Tabella7[[#This Row],[Socio]]="","",Tabella7[[#This Row],[Netto assegnato (Costo fiscale del bene in capo al socio)]]/'Tassazione Soci'!$C$12) | F113: =+IFERROR(IF(Tabella7[[#This Row],[Socio]]="","",(Assegnazione!$H$3*Tabella7[[#This Row],[% Beni]]-Tabella7[[#This Row],[Accollo debiti]]-$D$8*Tabella7[[#This Row],[% Beni]])*((Assegnazione!$H$3*Tabella7[[#This Row],[% Beni]]-Tabella7[[#This Row],[Accollo debiti]])>0))*(p=1)+$B$7*(p=3)*Tabella7[[#This Row],[% Beni]],0) -> 0 | G113: =+IFERROR(MAX(0,((SUMIF(Assegnazione[Socio],Tabella7[[#This Row],[Socio]],Assegnazione[Valore fiscale ai fini della Tassazione soci])-Tabella7[[#This Row],[Accollo debiti]])-$D$8*Tabella7[[#This Row],[% Beni]])*(p=1)*$O$6)+Tabella7[[#This Row],[Base netta]]*(p=3),0) -> 0 | H113: =+IFERROR(MAX(0,((SUMIF(Assegnazione[Socio],Tabella7[[#This Row],[Socio]],Assegnazione[Valore fiscale ai fini della Tassazione soci])-Tabella7[[#This Row],[Accollo debiti]])-$D$8*Tabella7[[#This Row],[% Beni]])*(p=1)*$O$7)+Tabella7[[#This Row],[Base netta]]*(p=3),0) -> 0 | I113: =+IF(Tabella7[[#This Row],[Socio]]="",0,'Tassazione Soci'!E$9*$B113) -> 0 | J113: =+(Tabella7[[#This Row],[Riserve]]+Tabella7[[#This Row],[Capitale sociale]])*(p=1) -> 0 | K113: =+Soci!H105 -> 0 | L113: =+IF(Tabella7[[#This Row],[Socio]]="","",MAX(0,Soci!F105-Tabella7[[#This Row],[Riserve]])+(p=3)*(Tabella7[[#This Row],[% Beni]]*DATI!$E$34)) | M113: =+(Tabella7[[#This Row],[Totale attribuito]]-Soci!F105)*((Tabella7[[#This Row],[Totale attribuito]]-Soci!F105)>0) -> 0 | N113: =+IFERROR((Tabella7[[#This Row],[Dividendi da "Sottozero"]]+Tabella7[[#This Row],[Utili]]*IR)*Tabella7[[#This Row],[% Imp. Div.]],0)*(p=1) -> 0 | O113: =+Tabella7[[#This Row],[Totale Redditi]]*Soci!G105 -> 0 | P113: =+SUMIF(Assegnazione[Socio],Tabella7[[#This Row],[Socio]],Assegnazione[Valore Normale]) -> 0 | Q113: =+IFERROR(Tabella7[[#This Row],[Valore Normale attribuito]]/Tabella7[[#This Row],[% Cap]],0)*(p=1) -> 0 | R113: =+IFERROR(MAX(Tabella7[Dividendo teorico distribuito])*Tabella7[[#This Row],[% Cap]]-Tabella7[[#This Row],[Valore Normale attribuito]],0)*(p=1) -> 0

Sheet Rettifica della detrazione
A3: Eventuale rettifica della detrazione a norma dell’art. 19-bis2 | F3: =SUM(Tabella10[Rettifica della detrazione]) -> 50000
A4: Anno | B4: Bene | C4: Iva portata in detrazione | D4: Anni da considerare ai fini della rett. | E4: Anni residui | F4: Rettifica della detrazione
A5: 2020 | B5: Capannone | C5: 100000 | D5: =+IF(Tabella10[[#This Row],[Anno]]="","",IFERROR(IF(VLOOKUP(Tabella10[[#This Row],[Bene]],B[[Bene]:[Tipologia]],3,0)="Altri Beni",5,10),10)) -> 10 | E5: =+IFERROR(IF(Tabella10[[#This Row],[Anno]]+Tabella10[[#This Row],[Anni da considerare ai fini della rett.]]-1<=2024,0,(Tabella10[[#This Row],[Anno]]+Tabella10[[#This Row],[Anni da considerare ai fini della rett.]]-2024-1)/Tabella10[[#This Row],[Anni da considerare ai fini della rett.]]),"") -> 0.5 | F5: =+IFERROR(Tabella10[[#This Row],[Iva portata in detrazione]]*Tabella10[[#This Row],[Anni residui]],0) -> 50000
D6: =+IF(Tabella10[[#This Row],[Anno]]="","",IFERROR(IF(VLOOKUP(Tabella10[[#This Row],[Bene]],B[[Bene]:[Tipologia]],3,0)="Altri Beni",5,10),10)) | E6: =+IFERROR(IF(Tabella10[[#This Row],[Anno]]+Tabella10[[#This Row],[Anni da considerare ai fini della rett.]]-1<=2024,0,(Tabella10[[#This Row],[Anno]]+Tabella10[[#This Row],[Anni da considerare ai fini della rett.]]-2024-1)/Tabella10[[#This Row],[Anni da considerare ai fini della rett.]]),"") | F6: =+IFERROR(Tabella10[[#This Row],[Iva portata in detrazione]]*Tabella10[[#This Row],[Anni residui]],0) -> 0
D7: =+IF(Tabella10[[#This Row],[Anno]]="","",IFERROR(IF(VLOOKUP(Tabella10[[#This Row],[Bene]],B[[Bene]:[Tipologia]],3,0)="Altri Beni",5,10),10)) | E7: =+IFERROR(IF(Tabella10[[#This Row],[Anno]]+Tabella10[[#This Row],[Anni da considerare ai fini della rett.]]-1<=2024,0,(Tabella10[[#This Row],[Anno]]+Tabella10[[#This Row],[Anni da considerare ai fini della rett.]]-2024-1)/Tabella10[[#This Row],[Anni da considerare ai fini della rett.]]),"") | F7: =+IFERROR(Tabella10[[#This Row],[Iva portata in detrazione]]*Tabella10[[#This Row],[Anni residui]],0) -> 0
D8: =+IF(Tabella10[[#This Row],[Anno]]="","",IFERROR(IF(VLOOKUP(Tabella10[[#This Row],[Bene]],B[[Bene]:[Tipologia]],3,0)="Altri Beni",5,10),10)) | E8: =+IFERROR(IF(Tabella10[[#This Row],[Anno]]+Tabella10[[#This Row],[Anni da considerare ai fini della rett.]]-1<=2024,0,(Tabella10[[#This Row],[Anno]]+Tabella10[[#This Row],[Anni da considerare ai fini della rett.]]-2024-1)/Tabella10[[#This Row],[Anni da considerare ai fini della rett.]]),"") | F8: =+IFERROR(Tabella10[[#This Row],[Iva portata in detrazione]]*Tabella10[[#This Row],[Anni residui]],0) -> 0
D9: =+IF(Tabella10[[#This Row],[Anno]]="","",IFERROR(IF(VLOOKUP(Tabella10[[#This Row],[Bene]],B[[Bene]:[Tipologia]],3,0)="Altri Beni",5,10),10)) | E9: =+IFERROR(IF(Tabella10[[#This Row],[Anno]]+Tabella10[[#This Row],[Anni da considerare ai fini della rett.]]-1<=2024,0,(Tabella10[[#This Row],[Anno]]+Tabella10[[#This Row],[Anni da considerare ai fini della rett.]]-2024-1)/Tabella10[[#This Row],[Anni da considerare ai fini della rett.]]),"") | F9: =+IFERROR(Tabella10[[#This Row],[Iva portata in detrazione]]*Tabella10[[#This Row],[Anni residui]],0) -> 0
D10: =+IF(Tabella10[[#This Row],[Anno]]="","",IFERROR(IF(VLOOKUP(Tabella10[[#This Row],[Bene]],B[[Bene]:[Tipologia]],3,0)="Altri Beni",5,10),10)) | E10: =+IFERROR(IF(Tabella10[[#This Row],[Anno]]+Tabella10[[#This Row],[Anni da considerare ai fini della rett.]]-1<=2024,0,(Tabella10[[#This Row],[Anno]]+Tabella10[[#This Row],[Anni da considerare ai fini della rett.]]-2024-1)/Tabella10[[#This Row],[Anni da considerare ai fini della rett.]]),"") | F10: =+IFERROR(Tabella10[[#This Row],[Iva portata in detrazione]]*Tabella10[[#This Row],[Anni residui]],0) -> 0
D11: =+IF(Tabella10[[#This Row],[Anno]]="","",IFERROR(IF(VLOOKUP(Tabella10[[#This Row],[Bene]],B[[Bene]:[Tipologia]],3,0)="Altri Beni",5,10),10)) | E11: =+IFERROR(IF(Tabella10[[#This Row],[Anno]]+Tabella10[[#This Row],[Anni da considerare ai fini della rett.]]-1<=2024,0,(Tabella10[[#This Row],[Anno]]+Tabella10[[#This Row],[Anni da considerare ai fini della rett.]]-2024-1)/Tabella10[[#This Row],[Anni da considerare ai fini della rett.]]),"") | F11: =+IFERROR(Tabella10[[#This Row],[Iva portata in detrazione]]*Tabella10[[#This Row],[Anni residui]],0) -> 0
D12: =+IF(Tabella10[[#This Row],[Anno]]="","",IFERROR(IF(VLOOKUP(Tabella10[[#This Row],[Bene]],B[[Bene]:[Tipologia]],3,0)="Altri Beni",5,10),10)) | E12: =+IFERROR(IF(Tabella10[[#This Row],[Anno]]+Tabella10[[#This Row],[Anni da considerare ai fini della rett.]]-1<=2024,0,(Tabella10[[#This Row],[Anno]]+Tabella10[[#This Row],[Anni da considerare ai fini della rett.]]-2024-1)/Tabella10[[#This Row],[Anni da considerare ai fini della rett.]]),"") | F12: =+IFERROR(Tabella10[[#This Row],[Iva portata in detrazione]]*Tabella10[[#This Row],[Anni residui]],0) -> 0
D13: =+IF(Tabella10[[#This Row],[Anno]]="","",IFERROR(IF(VLOOKUP(Tabella10[[#This Row],[Bene]],B[[Bene]:[Tipologia]],3,0)="Altri Beni",5,10),10)) | E13: =+IFERROR(IF(Tabella10[[#This Row],[Anno]]+Tabella10[[#This Row],[Anni da considerare ai fini della rett.]]-1<=2024,0,(Tabella10[[#This Row],[Anno]]+Tabella10[[#This Row],[Anni da considerare ai fini della rett.]]-2024-1)/Tabella10[[#This Row],[Anni da considerare ai fini della rett.]]),"") | F13: =+IFERROR(Tabella10[[#This Row],[Iva portata in detrazione]]*Tabella10[[#This Row],[Anni residui]],0) -> 0
D14: =+IF(Tabella10[[#This Row],[Anno]]="","",IFERROR(IF(VLOOKUP(Tabella10[[#This Row],[Bene]],B[[Bene]:[Tipologia]],3,0)="Altri Beni",5,10),10)) | E14: =+IFERROR(IF(Tabella10[[#This Row],[Anno]]+Tabella10[[#This Row],[Anni da considerare ai fini della rett.]]-1<=2024,0,(Tabella10[[#This Row],[Anno]]+Tabella10[[#This Row],[Anni da considerare ai fini della rett.]]-2024-1)/Tabella10[[#This Row],[Anni da considerare ai fini della rett.]]),"") | F14: =+IFERROR(Tabella10[[#This Row],[Iva portata in detrazione]]*Tabella10[[#This Row],[Anni residui]],0) -> 0
D15: =+IF(Tabella10[[#This Row],[Anno]]="","",IFERROR(IF(VLOOKUP(Tabella10[[#This Row],[Bene]],B[[Bene]:[Tipologia]],3,0)="Altri Beni",5,10),10)) | E15: =+IFERROR(IF(Tabella10[[#This Row],[Anno]]+Tabella10[[#This Row],[Anni da considerare ai fini della rett.]]-1<=2024,0,(Tabella10[[#This Row],[Anno]]+Tabella10[[#This Row],[Anni da considerare ai fini della rett.]]-2024-1)/Tabella10[[#This Row],[Anni da considerare ai fini della rett.]]),"") | F15: =+IFERROR(Tabella10[[#This Row],[Iva portata in detrazione]]*Tabella10[[#This Row],[Anni residui]],0) -> 0
D16: =+IF(Tabella10[[#This Row],[Anno]]="","",IFERROR(IF(VLOOKUP(Tabella10[[#This Row],[Bene]],B[[Bene]:[Tipologia]],3,0)="Altri Beni",5,10),10)) | E16: =+IFERROR(IF(Tabella10[[#This Row],[Anno]]+Tabella10[[#This Row],[Anni da considerare ai fini della rett.]]-1<=2024,0,(Tabella10[[#This Row],[Anno]]+Tabella10[[#This Row],[Anni da considerare ai fini della rett.]]-2024-1)/Tabella10[[#This Row],[Anni da considerare ai fini della rett.]]),"") | F16: =+IFERROR(Tabella10[[#This Row],[Iva portata in detrazione]]*Tabella10[[#This Row],[Anni residui]],0) -> 0
D17: =+IF(Tabella10[[#This Row],[Anno]]="","",IFERROR(IF(VLOOKUP(Tabella10[[#This Row],[Bene]],B[[Bene]:[Tipologia]],3,0)="Altri Beni",5,10),10)) | E17: =+IFERROR(IF(Tabella10[[#This Row],[Anno]]+Tabella10[[#This Row],[Anni da considerare ai fini della rett.]]-1<=2024,0,(Tabella10[[#This Row],[Anno]]+Tabella10[[#This Row],[Anni da considerare ai fini della rett.]]-2024-1)/Tabella10[[#This Row],[Anni da considerare ai fini della rett.]]),"") | F17: =+IFERROR(Tabella10[[#This Row],[Iva portata in detrazione]]*Tabella10[[#This Row],[Anni residui]],0) -> 0
... D24: =+IF(Tabella10[[#This Row],[Anno]]="","",IFERROR(IF(VLOOKUP(Tabella10[[#This Row],[Bene]],B[[Bene]:[Tipologia]],3,0)="Altri Beni",5,10),10)) | E24: =+IFERROR(IF(Tabella10[[#This Row],[Anno]]+Tabella10[[#This Row],[Anni da considerare ai fini della rett.]]-1<=2024,0,(Tabella10[[#This Row],[Anno]]+Tabella10[[#This Row],[Anni da considerare ai fini della rett.]]-2024-1)/Tabella10[[#This Row],[Anni da considerare ai fini della rett.]]),"") | F24: =+IFERROR(Tabella10[[#This Row],[Iva portata in detrazione]]*Tabella10[[#This Row],[Anni residui]],0) -> 0

Sheet Tariffa
A3: Calcolo tariffa professionale in base al DM 140/2012
B6: Valore normale | C6: =+Beni!G3 -> 300000
B7: Valore atto | C7: =+Assegnazione!M3 -> 302400
B9: Valore della pratica
B11: valore pratica: | C11: =+C9 -> 0
B12: Riquadro 8.1 art. 26 c.1 | C12: Min | D12: Max
B13: fino a euro 2.000.000 dallo 0,75% al 2% | C13: =+MIN(2000000,$C$11)*0.75% -> 0 | D13: =+MIN(2000000,$C$11)*2% -> 0
B14: oltre euro 2.000.000 dallo 0,50% allo 0,75% | C14: =+MAX(C11-2000000,0)*0.5% -> 0 | D14: =+MAX(C11-2000000,0)*0.75% -> 0
B16: Totale | C16: =+SUM(C13:C14) -> 0 | D16: =+SUM(D13:D14) -> 0

Sheet CalcoloRapido
B4: ="Calcolo rapido "&DATI!B19 -> Calcolo rapido Assegnazione
B5: Sigla | D5: Definizione | E5: Formule | F5: Caso1 | G5: Caso2 | H5: Caso3 | I5: Caso4 | J5: Caso5 | K5: Caso6 | L5: Caso7
B6: VN | C6: : | D6: Valore Normale | F6: 300000 | G6: 230000 | H6: 140000 | I6: 120000 | J6: 1170000 | K6: 260000 | L6: 260000
B7: VC | C7: : | D7: Valore Catastale | F7: 277200 | G7: 201600 | H7: 129780 | I7: 113400 | J7: 756000 | K7: 260000 | L7: 260000
B8: VF | C8: : | D8: Valore Fiscale | H8: 120600 | I8: 90000 | J8: 127500 | K8: 166500 | L8: 166500
B9: VP_1 | C9: : | D9: Valore partecipazione ante operazione | K9: 200000 | L9: 100000
B10: Tipo | C10: : | D10: Società di capitali | I10: TRUE | J10: TRUE | K10: TRUE | L10: TRUE
B11: Com | C11: : | D11: Società di comodo
B12: Ris | C12: : | D12: % Riserve sul totale distribuito | J12: 1 | K12: 1 | L12: 1
B13: IIS | C13: : | D13: Importo Imposta Sostitutiva | F13: =MAX(VC-Valfisc,0) -> 277200 | G13: =MAX(VC-Valfisc,0) -> 201600 | H13: =MAX(VC-Valfisc,0) -> 9180 | I13: =MAX(VC-Valfisc,0) -> 23400 | J13: =MAX(VC-Valfisc,0) -> 628500 | K13: =MAX(VC-Valfisc,0) -> 93500 | L13: =MAX(VC-Valfisc,0) -> 93500
B14: IS | C14: : | D14: Imposta sostitutiva (no comodo) | F14: =+F13*(0.08+0.02*F11) -> 22176 | G14: =+G13*(0.08+0.02*G11) -> 16128 | H14: =+H13*(0.08+0.02*H11) -> 734.4 | I14: =+I13*(0.08+0.02*I11) -> 1872 | J14: =+J13*(0.08+0.02*J11) -> 50280 | K14: =+K13*(0.08+0.02*K11) -> 7480 | L14: =+L13*(0.08+0.02*L11) -> 7480
B15: VB | C15: : | D15: Valore Beni in capo ai soci | F15: =VC -> 277200 | G15: =VC -> 201600 | H15: =VC -> 129780 | I15: =VC -> 113400 | J15: =VC -> 756000 | K15: =VC -> 260000 | L15: =VC -> 260000
B16: VP_2 | C16: : | D16: Valore partecipazione post operazione | F16: =MAX(VP_1-MIN(VC,Valfisc)*Ris,0)*(p<>2)+F9*(p=2) -> 0 | G16: =MAX(VP_1-MIN(VC,Valfisc)*Ris,0)*(p<>2)+G9*(p=2) -> 0 | H16: =MAX(VP_1-MIN(VC,Valfisc)*Ris,0)*(p<>2)+H9*(p=2) -> 0 | I16: =MAX(VP_1-MIN(VC,Valfisc)*Ris,0)*(p<>2)+I9*(p=2) -> 0 | J16: =MAX(VP_1-MIN(VC,Valfisc)*Ris,0)*(p<>2)+J9*(p=2) -> 0 | K16: =MAX(VP_1-MIN(VC,Valfisc)*Ris,0)*(p<>2)+K9*(p=2) -> 33500 | L16: =MAX(VP_1-MIN(VC,Valfisc)*Ris,0)*(p<>2)+L9*(p=2) -> 0
B17: RS | C17: : | D17: Reddito sottozero | F17: =MAX(0,MIN(VC,Valfisc)*Ris-VP_1,0)*(p=1)*F10 -> 0 | G17: =MAX(0,MIN(VC,Valfisc)*Ris-VP_1,0)*(p=1)*G10 -> 0 | H17: =MAX(0,MIN(VC,Valfisc)*Ris-VP_1,0)*(p=1)*H10 -> 0 | I17: =MAX(0,MIN(VC,Valfisc)*Ris-VP_1,0)*(p=1)*I10 -> 0 | J17: =MAX(0,MIN(VC,Valfisc)*Ris-VP_1,0)*(p=1)*J10 -> 127500 | K17: =MAX(0,MIN(VC,Valfisc)*Ris-VP_1,0)*(p=1)*K10 -> 0 | L17: =MAX(0,MIN(VC,Valfisc)*Ris-VP_1,0)*(p=1)*L10 -> 66500
B18: DS | C18: : | D18: Dividendi socio | F18: =(1-Ris)*MIN(VC,Valfisc)*(p=1)*F10 -> 0 | G18: =(1-Ris)*MIN(VC,Valfisc)*(p=1)*G10 -> 0 | H18: =(1-Ris)*MIN(VC,Valfisc)*(p=1)*H10 -> 0 | I18: =(1-Ris)*MIN(VC,Valfisc)*(p=1)*I10 -> 90000 | J18: =(1-Ris)*MIN(VC,Valfisc)*(p=1)*J10 -> 0 | K18: =(1-Ris)*MIN(VC,Valfisc)*(p=1)*K10 -> 0 | L18: =(1-Ris)*MIN(VC,Valfisc)*(p=1)*L10 -> 0
